Workbook
Name \A: #REF!
Name _epmOfflineCondition_: 1
Name _epmOfflineCondition_: 1
Name DATA1: #REF!
Name DATA1: #REF!
Name DATA1: #REF!
Name DATA1: #REF!
Name DATA1: #REF!
Name DATA2: #REF!
Name DATA2: #REF!
Name DATA2: #REF!
Name DATA2: #REF!
Name DATA2: #REF!
Name DATA3: #REF!
Name DATA3: #REF!
Name DATA3: #REF!
Name DATA3: #REF!
Name DATA3: #REF!
Name DATA4: #REF!
Name DATA4: #REF!
Name DATA4: #REF!
Name DATA4: #REF!
Name DATA4: #REF!
Name qykjzdcwbbxjllbxxGridlb_10: #REF!
Name qykjzdcwbbxjllbxxGridlb_19: #REF!
Name qykjzdcwbbxjllbxxGridlb_28: #REF!
Name qykjzdcwbbxjllbxxGridlb_31: #REF!
Name qykjzdcwbbxjllbxxGridlb_52: #REF!
Name qykjzdcwbbxjllbxxGridlb_53: #REF!
Name qykjzdcwbbxjllbxxGridlb_56: #REF!
Name TEST0: #REF!
Name TEST0: #REF!
Name TEST0: #REF!
Name TEST0: #REF!
Name TEST0: #REF!
Name TESTHKEY: #REF!
Name TESTHKEY: #REF!
Name TESTHKEY: #REF!
Name TESTHKEY: #REF!
Name TESTHKEY: #REF!
Name TESTKEYS: #REF!
Name TESTKEYS: #REF!
Name TESTKEYS: #REF!
Name TESTKEYS: #REF!
Name TESTKEYS: #REF!
Name TESTVKEY: #REF!
Name TESTVKEY: #REF!
Name TESTVKEY: #REF!
Name TESTVKEY: #REF!
Name TESTVKEY: #REF!
Name 设备发票明细: #REF!
Name 设备发票明细: #REF!
Name 设备发票明细: #REF!
Name 设备发票明细: #REF!
Name 设备发票明细: #REF!

Sheet 累计税金汇总表
A1: 时间：所属期 单位：元 | C1: 税金缴纳标准 | D1: 202412 | E1: 202501 | F1: 202502 | G1: 202503 | H1: 202504 | I1: 202505 | J1: 202506 | K1: 202507 | L1: 202508 | M1: 202509 | N1: 202510 | O1: 202511 | P1: 202512
A2: 基数 | B2: 账面收入 | D2: 1.5126491e+09 | E2: 4.3116584e+08 | F2: 3.5558408e+08 | G2: 48816138 | H2: 97382183 | I2: 50884270 | J2: 1.2171605e+08 | K2: 1.1081929e+08 | L2: 1.7958369e+08 | M2: 1.7442616e+08 | N2: 1.1709462e+08 | O2: 1.7393182e+09 | P2: 3.9147228e+09
B3: 其他收益
B4: 项目开票 | D4: 1.1262598e+09 | E4: 7.805366e+08 | F4: 5.2620168e+08 | G4: 4.7608694e+08 | H4: 78604519 | I4: 37974761 | J4: 2.3684048e+08 | K4: 1.0914781e+08 | L4: 1.4016733e+08 | M4: 2.3979933e+08 | N4: 3.1389905e+08 | O4: 1.0132121e+09 | P4: 1.094647e+09
B5: 利息开票
B6: 销项税额 | C6: A | D6: 1.5335725e+08 | E6: 54874884 | F6: 45434329 | G6: 4651212.5 | H6: 9372591.2 | I6: 4606639.5 | J6: 10897955 | K6: 9901838.1 | L6: 12579095 | M6: 16661164 | N6: 12198025 | O6: 2.2262931e+08 | P6: 4.7460854e+08
B7: 本期进项税额 | C7: B | D7: 67835873 | E7: 72025452 | F7: 60425055 | G7: 7987426.8 | H7: 7347644.3 | I7: 7003174.4 | J7: 4385018.7 | K7: 6626261.8 | L7: 22887594 | M7: 18893309 | N7: 18347860 | O7: 1.8479839e+08 | P7: 4.0848101e+08
B8: 上期留抵税额 | C8: C | O8: 2228173.5 | P8: 1210358
B9: 进项税额转出 | C9: D | E9: 14956.1 | F9: 3542.11 | G9: 595805.07 | H9: 22641.51 | J9: 272019.39 | K9: 43475.46 | L9: 267177.47 | M9: 82568.81 | P9: 603847.64
B10: 异地预缴税增值税 | C10: E | D10: 11847361 | G10: 29781.96 | H10: 2217866.5 | I10: 655226.71 | J10: 382841.63 | L10: 116982.96 | M10: 2762668.3 | P10: 7694589.5
B11: 应纳增值税额 | C11: A-B-C+D-E | D11: 73674014 | P11: 57826431
A12: 税金 | B12: 增值税 | D12: 73674014 | E12: =E11 -> 0 | F12: =F11 -> 0 | G12: =G11 -> 0 | H12: 0 | I12: =I11 -> 0 | J12: =J11 -> 0 | K12: =K11 -> 0 | L12: =L11 -> 0 | M12: =M11 -> 0 | N12: =N11 -> 0 | O12: =O11 -> 0 | P12: =P11 -> 57826431
B13: 印花税 | D13: 1051983.4 | J13: 330365.58
B14: 城建税 | C14: 增值税额的7% | D14: 5157181 | E14: =E12*0.07 -> 0 | F14: =F12*0.07 -> 0 | G14: =G12*0.07 -> 0 | H14: =H12*0.07 -> 0 | I14: =I12*0.07 -> 0 | J14: =J12*0.07 -> 0 | K14: =K12*0.07 -> 0 | L14: =L12*0.07 -> 0 | ... P14: =P12*0.07 -> 4047850.2
B15: 教育费附加 | C15: 增值税额的3% | D15: 2210220.4 | E15: =E12*0.03 -> 0 | F15: =F12*0.03 -> 0 | G15: =G12*0.03 -> 0 | H15: =H12*0.03 -> 0 | I15: =I12*0.03 -> 0 | J15: =J12*0.03 -> 0 | K15: =K12*0.03 -> 0 | L15: =L12*0.03 -> 0 | ... P15: =P12*0.03 -> 1734792.9
B16: 地方教育费附加 | C16: 增值税额的2% | D16: 1473480.3 | E16: =E12*0.02 -> 0 | F16: =F12*0.02 -> 0 | G16: =G12*0.02 -> 0 | H16: =H12*0.02 -> 0 | I16: =I12*0.02 -> 0 | J16: =J12*0.02 -> 0 | K16: =K12*0.02 -> 0 | L16: =L12*0.02 -> 0 | ... P16: =P12*0.02 -> 1156528.6
B17: 房产税
B18: 城镇土地使用
B19: 企业所得税 | D19: 3.8001788e+08 | J19: 29332502 | M19: 25579909 | P19: 77589714
B20: 个税
B21: 残疾人保障金 | K21: 181635.35
B22: 合计 | D22: =SUM(D12:D21) -> 4.6358476e+08 | E22: =SUM(E12:E21) -> 0 | F22: =SUM(F12:F21) -> 0 | G22: =SUM(G12:G21) -> 0 | H22: =SUM(H12:H21) -> 0 | I22: =SUM(I12:I21) -> 0 | J22: =SUM(J12:J21) -> 29662867 | K22: =SUM(K12:K21) -> 181635.35 | ... P22: =SUM(P12:P21) -> 1.4235532e+08
F26: 异地预缴 | H26: 异地预缴 | I26: 企业所得税
F27: 郎溪景宇风力发电有限公司 | H27: 郎溪
F28: 馆陶县汇恒风电有限公司 | H28: 察哈尔景源
F29: 伊金霍洛旗悦盛新能源有限公司 | H29: 定远纳驰 | I29: 450039.33
H30: 定远纳风 | I30: 734696.74
H31: 哈密博景
F33: 中国石油天然气股份有限公司 吐哈油田分公司 | H33: 吐哈油田 | I33: 136.15
F34: 定远智贮能源科技有限公司 | H34: 远景定远智慧储能共享电站项目 EPC | I34: 61976.18
E37: 45748 | F37: 定边远边汇新能源有限公司 | H37: 定边县红柳沟镇白兴庄 | I37: 443045.39
E39: 45778 | F39: 乌海市远鸿富景新能源科技有限公司 | H39: 乌海市金湖独立储能电站项目EPC总承 | I39: 96963.75
F40: 招银金融租赁有限公司 | H40: 利豪鸡泽县50MW保障类风电场 | I40: 172641.17
E42: 45809 | F42: 滨州远凌新能源有限责任公司 | H42: 滨州北海储能电站项目 | I42: 59826.73
F43: 清水河县云景风力发电有限公 司 | H43: 清水河县城关分散式风电场项目EPC总承包 | I43: 62095.04
E44: 2025.7 | H44: 射阳汇智风电场项目 EPC 总承包采购合同 | I44: 98649.14
E45: 2025.8 | G45: 陕西省榆林市靖边县东南部天赐湾乡 | H45: 靖边县状泽城河100兆瓦风电场项目EPC工程总承包合同 | I45: 364233.03
E46: 2025.9 | G46: 内蒙古自治区乌兰察布市察哈尔右翼后旗 | I46: 288997.39

Sheet 累计项目税收明细表202512
J1: ='累计项目税收明细表2017-202302'!G355 -> 1.1960885e+10 | K1: ='累计项目税收明细表2017-202302'!H355 -> 1.1569549e+10 | L1: =SUBTOTAL(9,L8:L143) -> 4.42397e+08 | M1: =SUBTOTAL(9,M9:M143) -> 5.4813931e+08 | N1: =SUBTOTAL(9,N8:N143) -> 5.2125169e+08 | O1: =SUBTOTAL(9,O8:O143) -> 5.1244236e+08 | P1: =SUBTOTAL(9,P8:P143) -> 6.3590871e+08 | Q1: =SUBTOTAL(9,Q8:Q143) -> 5.4741284e+08 | R1: =SUBTOTAL(9,R8:R150) -> 3.0901827e+08 | S1: =SUBTOTAL(9,S8:S150) -> 3.4998131e+08 | T1: =SUBTOTAL(9,T8:T157) -> 5.5568377e+08 | U1: =SUBTOTAL(9,U8:U150) -> 5.1789361e+08 | V1: =SUBTOTAL(9,V8:V150) -> 6.7448332e+08 | W1: =SUBTOTAL(9,W8:W150) -> 5.424389e+08 | X1: =SUBTOTAL(9,X8:X150) -> 3.3679561e+08 | Y1: =SUBTOTAL(9,Y8:Y150) -> 4.5653185e+08
B2: 项目类型 | C2: 公司代码 或项目号 | D2: 项目名称 | E2: 类别 | F2: 税率 | G2: 累计收入 | H2: 累计开票 | I2: 未开票收入 | J2: 202403之前月度 收入额小计 | K2: 202403之前月度 开票额小计 | L2: 202403账面收入 | M2: 202403开票 | N2: 202404账面收入 | O2: 202404开票 | P2: 202405账面收入 | Q2: 202405开票 | R2: 202406账面收入 | S2: 202406开票 | T2: 202407账面收入 | U2: 202407开票 | V2: 202408账面收入 | W2: 202408开票 | X2: 202409账面收入 | Y2: 202409开票 | Z2: 202410账面收入 | AA2: 202410开票 | AB2: 202411账面收入 | AC2: 202411开票 | AD2: 202412账面收入 | AE2: 202412开票 | AF2: 202501账面收入 | AG2: 202501开票 | AH2: 202502账面收入 | AI2: 202502开票 | AJ2: 202503账面收入 | AK2: 202503开票 | AL2: 202504账面收入 | AM2: 202504开票 | AN2: 202505账面收入 | AO2: 202505开票 | AP2: 202506账面收入 | AQ2: 202506开票 | AR2: 202507账面收入 | AS2: 202507开票 | AT2: 202508预开票金额 | AU2: 202508账面收入 | AV2: 202508开票 | AW2: 202509账面收入 | AX2: 202509开票 | AY2: 202510账面收入 | AZ2: 202510开票 | BA2: 202510预开票 | BB2: 202510预开票冲回 | BC2: 202511账面收入 | BD2: 202511开票 | BE2: 202511预开票 | BF2: 202511预开票冲回 | BG2: 202512账面收入 | BH2: 202512开票 | BI2: 202512预开票 | BJ2: 202512预开票冲回
D3: 202403之前 各月度数据结转 | E3: 商品销售 | F3: 0.16 | G3: =SUM(J3,L3,N3,P3,R3,T3,V3,X3,Z3) -> 467927.48 | H3: =SUM(K3,M3,O3,Q3) -> 88819830 | I3: =G3-H3 -> -88351903 | J3: 467927.48 | K3: 88819830
E4: 工程施工 | F4: 0.1 | G4: =SUM(J4,L4,N4,P4,R4,T4,V4,X4,Z4) -> -1.2564439e+08 | H4: =SUM(K4,M4,O4,Q4) -> -47524533 | I4: =G4-H4 -> -78119852 | J4: -1.2564439e+08 | K4: -47524533
E5: 商品销售 | F5: 0.13 | G5: =SUM(J5,L5,N5,P5,R5,T5,V5,X5,Z5) -> 6.6085485e+09 | H5: =SUM(K5,M5,O5,Q5) -> 6.2670488e+09 | I5: =G5-H5 -> 3.414997e+08 | J5: 6.6085485e+09 | K5: 6.2670488e+09
E6: 工程施工 | F6: 0.09 | G6: =SUM(J6,L6,N6,P6,R6,T6,V6,X6,Z6) -> 5.0145477e+09 | H6: =SUM(K6,M6,O6,Q6) -> 4.892353e+09 | I6: =G6-H6 -> 1.221947e+08 | J6: 5.0145477e+09 | K6: 4.892353e+09
E7: 设计咨询 | F7: 0.06 | G7: =SUM(J7,L7,N7,P7,R7,T7,V7,X7,Z7) -> 4.6296552e+08 | H7: =SUM(K7,M7,O7,Q7) -> 3.6885177e+08 | I7: =G7-H7 -> 94113747 | J7: 4.6296552e+08 | K7: 3.6885177e+08 | Y7: 0
B8: EPC自建 | C8: 2346 | D8: 安徽宣城郎溪 | E8: 商品销售 | F8: 0.13 | G8: =SUM(J8,L8,N8,P8,R8,T8,V8,X8,Z8,AB8,AD8,AF8,AH8,AJ8,AL8,AN8,AP8,AR8,AU8,AW8,AY8,BC8,BG8) -> 32635696 | H8: =SUM(K8,M8,O8,Q8,S8,U8,W8,Y8,AA8,AC8,AE8,AG8,AI8,AK8,AM8,AO8,AQ8,AS8,AV8,AX8,AZ8,BD8,BH8) -> 37275653 | I8: =G8-H8 -> -4639956.4 | N8: 7575879.3 | O8: 11624470 | P8: 17461283 | Q8: 7575879.3 | R8: 2028030.5 | S8: 10476770 | T8: 184101.94 | V8: 5386401.3 | W8: 0 | X8: 0 | Y8: 0 | AJ8: 0 | AK8: 7598533.8
C9: 2346 | E9: 工程施工 | F9: 0.09 | G9: =SUM(J9,L9,N9,P9,R9,T9,V9,X9,Z9,AB9,AD9,AF9,AH9,AJ9,AL9,AN9,AP9,AR9,AU9,AW9,AY9,BC9,BG9) -> 9498435.8 | H9: =SUM(K9,M9,O9,Q9,S9,U9,W9,Y9,AA9,AC9,AE9,AG9,AI9,AK9,AM9,AO9,AQ9,AS9,AV9,AX9,AZ9,BD9,BH9) -> 19399126 | I9: =G9-H9 -> -9900690.2 | L9: 1044857.3 | N9: 2871503.7 | P9: 1423208.3 | Q9: 15363805 | R9: 2364082.2 | S9: 4035321.1 | T9: 1100229.4 | V9: 470183.49 | W9: 0 | X9: 224371.56 | Y9: 0
C10: 2346 | E10: 设计咨询 | F10: 0.06 | G10: =SUM(J10,L10,N10,P10,R10,T10,V10,X10,Z10,AB10,AD10,AF10,AH10,AJ10,AL10,AN10,AP10,AR10,AU10,AW10,AY10,BC10,BG10) -> 1587499.4 | H10: =SUM(K10,M10,O10,Q10,S10,U10,W10,Y10,AA10,AC10,AE10,AG10,AI10,AK10,AM10,AO10,AQ10,AS10,AV10,AX10,AZ10,BD10,BH10) -> 1604523.2 | I10: =G10-H10 -> -17023.79 | L10: 116896.06 | N10: 170311.43 | P10: 316972.4 | Q10: 1050616 | R10: 634803.18 | S10: 362041.83 | T10: 201873.22 | U10: 45222.28 | V10: 68316.87 | W10: 68316.87 | X10: 44486.8 | Y10: 44486.8 | Z10: 33839.49 | AA10: 33839.49
C11: 安新县阔达有色金属熔炼有限公司 | D11: 安徽宣城郎溪 | E11: 商品销售 | F11: 0.13 | G11: =SUM(J11,L11,N11,P11,R11,T11,V11,X11,Z11,AB11,AD11,AF11,AH11,AJ11,AL11,AN11,AP11,AR11,AU11,AW11,AY11,BC11,BG11) -> 0 | H11: =SUM(K11,M11,O11,Q11,S11,U11,W11,Y11,AA11,AC11,AE11,AG11,AI11,AK11,AM11,AO11,AQ11,AS11,AV11,AX11,AZ11,BD11,BH11) -> 81415.93 | BH11: 81415.93
E12: 工程施工 | F12: 0.09 | G12: =SUM(J12,L12,N12,P12,R12,T12,V12,X12,Z12,AB12,AD12,AF12,AH12,AJ12,AL12,AN12,AP12,AR12,AU12,AW12,AY12,BC12,BG12) -> 0 | H12: =SUM(K12,M12,O12,Q12,S12,U12,W12,Y12,AA12,AC12,AE12,AG12,AI12,AK12,AM12,AO12,AQ12,AS12,AV12,AX12,AZ12,BD12,BH12) -> 0
E13: 设计咨询 | F13: 0.06 | G13: =SUM(J13,L13,N13,P13,R13,T13,V13,X13,Z13,AB13,AD13,AF13,AH13,AJ13,AL13,AN13,AP13,AR13,AU13,AW13,AY13,BC13,BG13) -> 0 | H13: =SUM(K13,M13,O13,Q13,S13,U13,W13,Y13,AA13,AC13,AE13,AG13,AI13,AK13,AM13,AO13,AQ13,AS13,AV13,AX13,AZ13,BD13,BH13) -> 0
B14: EPC自建 | C14: 3660 | D14: 巴彦淖尔 | E14: 商品销售 | F14: 0.13 | G14: =SUM(J14,L14,N14,P14,R14,T14,V14,X14,Z14,AB14,AD14,AF14,AH14,AJ14,AL14,AN14,AP14,AR14,AU14,AW14,AY14,BC14,BG14) -> 8211701.3 | H14: =SUM(K14,M14,O14,Q14,S14,U14,W14,Y14,AA14,AC14,AE14,AG14,AI14,AK14,AM14,AO14,AQ14,AS14,AV14,AX14,AZ14,BD14,BH14) -> 11336364 | I14: =G14-H14 -> -3124662.7 | L14: 8130064.1 | M14: 3124662.6 | N14: 81637.17 | V14: 0 | W14: 0 | X14: 0 | Y14: 8211701.4
C15: 3660 | E15: 工程施工 | F15: 0.09 | G15: =SUM(J15,L15,N15,P15,R15,T15,V15,X15,Z15,AB15,AD15,AF15,AH15,AJ15,AL15,AN15,AP15,AR15,AU15,AW15,AY15,BC15,BG15) -> 4.6214846e+08 | H15: =SUM(K15,M15,O15,Q15,S15,U15,W15,Y15,AA15,AC15,AE15,AG15,AI15,AK15,AM15,AO15,AQ15,AS15,AV15,AX15,AZ15,BD15,BH15) -> 4.6214846e+08 | I15: =G15-H15 -> -0.029999912 | L15: 1.8904657e+08 | M15: 1.8348624e+08 | N15: 2.2018349e+08 | O15: 2.2018349e+08 | P15: 1.9266055e+08 | Q15: 1.9266055e+08 | U15: 3981328.1 | V15: 1239039.6 | W15: 0 | X15: 0 | Y15: 2818045.8 | AD15: -1.4098119e+08 | AE15: 0 | AI15: -1.4098119e+08
C16: 3660 | E16: 设计咨询 | F16: 0.06 | G16: =SUM(J16,L16,N16,P16,R16,T16,V16,X16,Z16,AB16,AD16,AF16,AH16,AJ16,AL16,AN16,AP16,AR16,AU16,AW16,AY16,BC16,BG16) -> 5519384.1 | H16: =SUM(K16,M16,O16,Q16,S16,U16,W16,Y16,AA16,AC16,AE16,AG16,AI16,AK16,AM16,AO16,AQ16,AS16,AV16,AX16,AZ16,BD16,BH16) -> 6976051.5 | I16: =G16-H16 -> -1456667.3 | L16: 5238515.3 | M16: 1456667.3 | N16: -81637.17 | T16: 212735.85 | U16: 4216037.7 | V16: 52152 | W16: 0 | X16: 0 | Y16: 1205728.3 | AD16: 97618.11 | AE16: 97618.11
B17: EPC自建 | C17: 4030 | D17: 定边白兴庄 | E17: 商品销售 | F17: 0.13 | G17: =SUM(J17,L17,N17,P17,R17,T17,V17,X17,Z17,AB17,AD17,AF17,AH17,AJ17,AL17,AN17,AP17,AR17,AU17,AW17,AY17,BC17,BG17) -> 2.0329258e+08 | H17: =SUM(K17,M17,O17,Q17,S17,U17,W17,Y17,AA17,AC17,AE17,AG17,AI17,AK17,AM17,AO17,AQ17,AS17,AV17,AX17,AZ17,BD17,BH17) -> 1.1134199e+08 | I17: =G17-H17 -> 91950591 | N17: 3664601.8 | P17: 222234.5 | R17: 18651916 | S17: 0 | T17: 53556348 | V17: 14543776 | W17: 0 | X17: -9581572.7 | Y17: 8347326.5 | Z17: 32102530 | AA17: 11020813 | AB17: 90132743 | AC17: 91973846
C18: 4030 | E18: 工程施工 | F18: 0.09 | G18: =SUM(J18,L18,N18,P18,R18,T18,V18,X18,Z18,AB18,AD18,AF18,AH18,AJ18,AL18,AN18,AP18,AR18,AU18,AW18,AY18,BC18,BG18) -> 2.1309161e+08 | H18: =SUM(K18,M18,O18,Q18,S18,U18,W18,Y18,AA18,AC18,AE18,AG18,AI18,AK18,AM18,AO18,AQ18,AS18,AV18,AX18,AZ18,BD18,BH18) -> 1.8890447e+08 | I18: =G18-H18 -> 24187141 | L18: 489233.5 | N18: 9211423.6 | O18: 45871560 | P18: 10406006 | R18: 14196013 | S18: 0 | T18: 12344910 | V18: 9578080.4 | W18: 0 | X18: 15013767 | Y18: 18679332 | Z18: 37165437 | AA18: 9429091.5 | AB18: 53132537 | AC18: 63370283 | AD18: 51554199 | AE18: 51554199
C19: 4030 | E19: 设计咨询 | F19: 0.06 | G19: =SUM(J19,L19,N19,P19,R19,T19,V19,X19,Z19,AB19,AD19,AF19,AH19,AJ19,AL19,AN19,AP19,AR19,AU19,AW19,AY19,BC19,BG19) -> 8329405.3 | H19: =SUM(K19,M19,O19,Q19,S19,U19,W19,Y19,AA19,AC19,AE19,AG19,AI19,AK19,AM19,AO19,AQ19,AS19,AV19,AX19,AZ19,BD19,BH19) -> 7940431.8 | I19: =G19-H19 -> 388973.51 | L19: 43891.61 | N19: 685280.75 | P19: 64486.14 | R19: 156301.33 | S19: 60092.57 | T19: 3078319.5 | U19: 60296.37 | V19: =563843.01+91089.15 -> 654932.16 | W19: 91089.15 | X19: 165683.66 | Y19: 4427586 | Z19: 3031830.8 | AA19: 474936.19 | AB19: 448679.26 | AC19: 2826431.5
B20: EPC自建 | C20: 4020 | D20: 定边王家梁 | E20: 商品销售 | F20: 0.13 | G20: =SUM(J20,L20,N20,P20,R20,T20,V20,X20,Z20,AB20,AD20,AF20,AH20,AJ20,AL20,AN20,AP20,AR20,AU20,AW20,AY20,BC20,BG20) -> 1.0538136e+08 | H20: =SUM(K20,M20,O20,Q20,S20,U20,W20,Y20,AA20,AC20,AE20,AG20,AI20,AK20,AM20,AO20,AQ20,AS20,AV20,AX20,AZ20,BD20,BH20) -> 1.0767405e+08 | I20: =G20-H20 -> -2292690.1 | M20: 2292690 | N20: 10422345 | R20: 660150.8 | S20: 0 | T20: 27073953 | V20: 3545901.1 | W20: 13168633 | X20: 11705115 | Y20: 3422302.7 | Z20: 51973899 | AA20: 36816530 | AI20: 51973899
C21: 4020 | E21: 工程施工 | F21: 0.09 | G21: =SUM(J21,L21,N21,P21,R21,T21,V21,X21,Z21,AB21,AD21,AF21,AH21,AJ21,AL21,AN21,AP21,AR21,AU21,AW21,AY21,BC21,BG21) -> 2.9721338e+08 | H21: =SUM(K21,M21,O21,Q21,S21,U21,W21,Y21,AA21,AC21,AE21,AG21,AI21,AK21,AM21,AO21,AQ21,AS21,AV21,AX21,AZ21,BD21,BH21) -> 3.2681651e+08 | I21: =G21-H21 -> -29603135 | L21: 5244190.5 | M21: 29823783 | N21: 13660419 | O21: 1.6430483e+08 | P21: 27909442 | R21: 19309601 | S21: 0 | T21: 12545273 | V21: 7283802.8 | W21: 73424735 | X21: 8064138.7 | Y21: 2271099.1 | Z21: 2.0319651e+08 | AA21: 47672842 | AE21: 9319218.1
C22: 4020 | E22: 设计咨询 | F22: 0.06 | G22: =SUM(J22,L22,N22,P22,R22,T22,V22,X22,Z22,AB22,AD22,AF22,AH22,AJ22,AL22,AN22,AP22,AR22,AU22,AW22,AY22,BC22,BG22) -> 15200557 | H22: =SUM(K22,M22,O22,Q22,S22,U22,W22,Y22,AA22,AC22,AE22,AG22,AI22,AK22,AM22,AO22,AQ22,AS22,AV22,AX22,AZ22,BD22,BH22) -> 29092126 | I22: =G22-H22 -> -13891569 | L22: 387382.3 | M22: 6720925.1 | N22: 1991865.6 | O22: 614275.5 | P22: 1033444.8 | R22: 605451.16 | S22: 60092.57 | T22: 3642158.9 | U22: 60296.37 | V22: =451080.26+91089.15 -> 542169.41 | W22: 14187371 | X22: 453844.04 | Y22: 510396 | Z22: 5695184.2 | AA22: 394528.3 | AD22: 849056.6 | AE22: 5695184.2 | AG22: 849056.6
B23: EPC自建 | C23: 2319 | D23: 定远乘风 | E23: 商品销售 | F23: 0.13 | G23: =SUM(J23,L23,N23,P23,R23,T23,V23,X23,Z23,AB23,AD23,AF23,AH23,AJ23,AL23,AN23,AP23,AR23,AU23,AW23,AY23,BC23,BG23) -> 1.2192612e+08 | H23: =SUM(K23,M23,O23,Q23,S23,U23,W23,Y23,AA23,AC23,AE23,AG23,AI23,AK23,AM23,AO23,AQ23,AS23,AV23,AX23,AZ23,BD23,BH23) -> 1.4448884e+08 | I23: =G23-H23 -> -22562720 | L23: 3184412.9 | P23: 3053970.6 | R23: 1591338.1 | S23: 0 | T23: 28616.54 | U23: 30132373 | V23: 22396948 | W23: 0 | X23: 23544881 | Y23: 0 | Z23: 68125955 | AA23: 54847.11 | AC23: 1.1404155e+08 | AD23: 0 | AE23: 260067.96
C24: 2319 | E24: 工程施工 | F24: 0.09 | G24: =SUM(J24,L24,N24,P24,R24,T24,V24,X24,Z24,AB24,AD24,AF24,AH24,AJ24,AL24,AN24,AP24,AR24,AU24,AW24,AY24,BC24,BG24) -> 4.0298493e+08 | H24: =SUM(K24,M24,O24,Q24,S24,U24,W24,Y24,AA24,AC24,AE24,AG24,AI24,AK24,AM24,AO24,AQ24,AS24,AV24,AX24,AZ24,BD24,BH24) -> 4.7599102e+08 | I24: =G24-H24 -> -73006093 | L24: -493692.65 | N24: 11024685 | P24: 9616720.9 | R24: 15488844 | S24: 0 | T24: 5873943.7 | U24: 1.0864265e+08 | V24: 8786601.5 | W24: 0 | X24: 15887463 | Y24: 0 | Z24: 43577732 | AB24: 2.9396666e+08 | AC24: 74125740 | AD24: -744034.87 | AE24: 2.9322263e+08
C25: 2319 | E25: 设计咨询 | F25: 0.06 | G25: =SUM(J25,L25,N25,P25,R25,T25,V25,X25,Z25,AB25,AD25,AF25,AH25,AJ25,AL25,AN25,AP25,AR25,AU25,AW25,AY25,BC25,BG25) -> 12445292 | H25: =SUM(K25,M25,O25,Q25,S25,U25,W25,Y25,AA25,AC25,AE25,AG25,AI25,AK25,AM25,AO25,AQ25,AS25,AV25,AX25,AZ25,BD25,BH25) -> 25072324 | I25: =G25-H25 -> -12627032 | P25: 572632.47 | R25: 1198794.8 | S25: 60092.57 | T25: 1933105.9 | U25: 15442087 | V25: =2056169.38+91089.15 -> 2147258.5 | W25: -1053820.4 | X25: 1316111 | Y25: 59315.74 | Z25: 5207673.3 | AC25: 10494933 | AF25: 69716.4 | AG25: 69716.4
B26: EPC自建 | C26: 2318 | D26: 定远欣月 | E26: 商品销售 | F26: 0.13 | G26: =SUM(J26,L26,N26,P26,R26,T26,V26,X26,Z26,AB26,AD26,AF26,AH26,AJ26,AL26,AN26,AP26,AR26,AU26,AW26,AY26,BC26,BG26) -> 91048578 | H26: =SUM(K26,M26,O26,Q26,S26,U26,W26,Y26,AA26,AC26,AE26,AG26,AI26,AK26,AM26,AO26,AQ26,AS26,AV26,AX26,AZ26,BD26,BH26) -> 94539002 | I26: =G26-H26 -> -3490424.3 | P26: 18248654 | R26: 14223009 | S26: 0 | T26: 24448246 | U26: 35962087 | V26: 6740165.1 | W26: 0 | X26: -3136198 | Y26: 0 | Z26: 30470275 | AB26: 54427.05 | AC26: 58576915
C27: 2318 | E27: 工程施工 | F27: 0.09 | G27: =SUM(J27,L27,N27,P27,R27,T27,V27,X27,Z27,AB27,AD27,AF27,AH27,AJ27,AL27,AN27,AP27,AR27,AU27,AW27,AY27,BC27,BG27) -> 2.385241e+08 | H27: =SUM(K27,M27,O27,Q27,S27,U27,W27,Y27,AA27,AC27,AE27,AG27,AI27,AK27,AM27,AO27,AQ27,AS27,AV27,AX27,AZ27,BD27,BH27) -> 2.7753196e+08 | I27: =G27-H27 -> -39007863 | L27: -634747.7 | N27: 4893183.6 | P27: 1363532.1 | R27: 7882465.7 | S27: 0 | T27: 3424803.4 | U27: 52512297 | V27: 3477768.1 | W27: 0 | X27: -545268.65 | Y27: 0 | Z27: 17266715 | AB27: 1.5728736e+08 | AC27: 1.8091138e+08 | AD27: 44108287 | AE27: 44108287
C28: 2318 | E28: 设计咨询 | F28: 0.06 | G28: =SUM(J28,L28,N28,P28,R28,T28,V28,X28,Z28,AB28,AD28,AF28,AH28,AJ28,AL28,AN28,AP28,AR28,AU28,AW28,AY28,BC28,BG28) -> 9887422.4 | H28: =SUM(K28,M28,O28,Q28,S28,U28,W28,Y28,AA28,AC28,AE28,AG28,AI28,AK28,AM28,AO28,AQ28,AS28,AV28,AX28,AZ28,BD28,BH28) -> 22107136 | I28: =G28-H28 -> -12219713 | L28: 625546.26 | N28: 721744.48 | P28: 1109241.8 | R28: 848738.92 | S28: 45069.41 | T28: 1125155.6 | U28: 16630790 | V28: =1480911.13+68316.91 -> 1549228 | W28: -935850.35 | X28: 281836.92 | Y28: 44486.75 | Z28: 3625930.4 | AC28: 6322639.7
B29: EPC自建 | C29: 2A50 | D29: 定远独立储能 | E29: 商品销售 | F29: 0.13 | G29: =SUM(J29,L29,N29,P29,R29,T29,V29,X29,Z29,AB29,AD29,AF29,AH29,AJ29,AL29,AN29,AP29,AR29,AU29,AW29,AY29,BC29,BG29) -> 0 | H29: =SUM(K29,M29,O29,Q29,S29,U29,W29,Y29,AA29,AC29,AE29,AG29,AI29,AK29,AM29,AO29,AQ29,AS29,AV29,AX29,AZ29,BD29,BH29) -> 9836350.8 | I29: =G29-H29 -> -9836350.8 | V29: 0 | W29: 0 | X29: 0 | Y29: 0 | Z29: 117923.07 | AH29: -117923.07 | AJ29: 0 | AK29: 9836350.8
C30: 2A50 | E30: 工程施工 | F30: 0.09 | G30: =SUM(J30,L30,N30,P30,R30,T30,V30,X30,Z30,AB30,AD30,AF30,AH30,AJ30,AL30,AN30,AP30,AR30,AU30,AW30,AY30,BC30,BG30) -> 2073641.8 | H30: =SUM(K30,M30,O30,Q30,S30,U30,W30,Y30,AA30,AC30,AE30,AG30,AI30,AK30,AM30,AO30,AQ30,AS30,AV30,AX30,AZ30,BD30,BH30) -> 30988092 | I30: =G30-H30 -> -28914451 | V30: 0 | W30: 0 | X30: 0 | Y30: 0 | Z30: 2073641.8 | AI30: 30988092
C31: 2A50 | E31: 设计咨询 | F31: 0.06 | G31: =SUM(J31,L31,N31,P31,R31,T31,V31,X31,Z31,AB31,AD31,AF31,AH31,AJ31,AL31,AN31,AP31,AR31,AU31,AW31,AY31,BC31,BG31) -> 1726122.2 | H31: =SUM(K31,M31,O31,Q31,S31,U31,W31,Y31,AA31,AC31,AE31,AG31,AI31,AK31,AM31,AO31,AQ31,AS31,AV31,AX31,AZ31,BD31,BH31) -> 8077291.4 | I31: =G31-H31 -> -6351169.2 | L31: 1262584.2 | N31: 112007.19 | Q31: 7725760.7 | U31: 0 | V31: 0 | W31: 0 | X31: 0 | Y31: 0 | Z31: 351530.75 | AJ31: 0 | AK31: 351530.74
B32: EPC自建 | C32: 1080 | D32: 丰宁 | E32: 商品销售 | F32: 0.13 | G32: =SUM(J32,L32,N32,P32,R32,T32,V32,X32,Z32,AB32,AD32,AF32,AH32,AJ32,AL32,AN32,AP32,AR32,AU32,AW32,AY32,BC32,BG32) -> 0 | H32: =SUM(K32,M32,O32,Q32,S32,U32,W32,Y32,AA32,AC32,AE32,AG32,AI32,AK32,AM32,AO32,AQ32,AS32,AV32,AX32,AZ32,BD32,BH32) -> 0 | I32: =G32-H32 -> 0
C33: 1080 | E33: 工程施工 | F33: 0.09 | G33: =SUM(J33,L33,N33,P33,R33,T33,V33,X33,Z33,AB33,AD33,AF33,AH33,AJ33,AL33,AN33,AP33,AR33,AU33,AW33,AY33,BC33,BG33) -> 0 | H33: =SUM(K33,M33,O33,Q33,S33,U33,W33,Y33,AA33,AC33,AE33,AG33,AI33,AK33,AM33,AO33,AQ33,AS33,AV33,AX33,AZ33,BD33,BH33) -> 379237.83 | I33: =G33-H33 -> -379237.83 | AI33: 379237.83
C34: 1080 | E34: 设计咨询 | F34: 0.06 | G34: =SUM(J34,L34,N34,P34,R34,T34,V34,X34,Z34,AB34,AD34,AF34,AH34,AJ34,AL34,AN34,AP34,AR34,AU34,AW34,AY34,BC34,BG34) -> 0 | H34: =SUM(K34,M34,O34,Q34,S34,U34,W34,Y34,AA34,AC34,AE34,AG34,AI34,AK34,AM34,AO34,AQ34,AS34,AV34,AX34,AZ34,BD34,BH34) -> 475794.07 | I34: =G34-H34 -> -475794.07 | AI34: 475794.07
B35: EPC自建 | C35: 1080 | D35: 丰宁二期 | E35: 商品销售 | F35: 0.13 | G35: =SUM(J35,L35,N35,P35,R35,T35,V35,X35,Z35,AB35,AD35,AF35,AH35,AJ35,AL35,AN35,AP35,AR35,AU35,AW35,AY35,BC35,BG35) -> 2.1818304e+08 | H35: =SUM(K35,M35,O35,Q35,S35,U35,W35,Y35,AA35,AC35,AE35,AG35,AI35,AK35,AM35,AO35,AQ35,AS35,AV35,AX35,AZ35,BD35,BH35) -> 2.0772881e+08 | I35: =G35-H35 -> 10454224 | N35: 22944611 | P35: 9632042.6 | Q35: 21162439 | R35: 35911880 | S35: 11414215 | T35: 10896695 | V35: 1.0628981e+08 | W35: 36354351 | X35: 4407911.8 | Y35: 83150389 | Z35: 28100089 | AA35: 27533528 | AE35: 4012784.8 | AI35: 24101106
C36: 1080 | E36: 工程施工 | F36: 0.09 | G36: =SUM(J36,L36,N36,P36,R36,T36,V36,X36,Z36,AB36,AD36,AF36,AH36,AJ36,AL36,AN36,AP36,AR36,AU36,AW36,AY36,BC36,BG36) -> 1.1833155e+09 | H36: =SUM(K36,M36,O36,Q36,S36,U36,W36,Y36,AA36,AC36,AE36,AG36,AI36,AK36,AM36,AO36,AQ36,AS36,AV36,AX36,AZ36,BD36,BH36) -> 1.0976805e+09 | I36: =G36-H36 -> 85635052 | L36: 2011104.1 | N36: 16149385 | P36: 24831319 | R36: 29735687 | S36: 49099875 | T36: 1.5868586e+08 | U36: 1.3761468e+08 | V36: 1.7189511e+08 | W36: 2.0677017e+08 | X36: 1.1730584e+08 | Y36: 1.2733723e+08 | Z36: 75373568 | AA36: 28836197 | AD36: 5.8732768e+08 | AE36: 1.4418091e+08 | AG36: 2.7522936e+08 | AI36: 1.2861208e+08 | AN36: -91743119 | AP36: 91743119
C37: 1080 | E37: 设计咨询 | F37: 0.06 | G37: =SUM(J37,L37,N37,P37,R37,T37,V37,X37,Z37,AB37,AD37,AF37,AH37,AJ37,AL37,AN37,AP37,AR37,AU37,AW37,AY37,BC37,BG37) -> 20771259 | H37: =SUM(K37,M37,O37,Q37,S37,U37,W37,Y37,AA37,AC37,AE37,AG37,AI37,AK37,AM37,AO37,AQ37,AS37,AV37,AX37,AZ37,BD37,BH37) -> 22230481 | I37: =G37-H37 -> -1459221.8 | L37: 439078.6 | N37: 1226790.2 | P37: -113038.25 | Q37: 2831283.8 | R37: 60092.57 | S37: 60092.57 | T37: 472894.22 | U37: 60296.37 | V37: =7294630.9+91089.15 -> 7385720 | W37: 684455.55 | X37: 2150705.6 | Y37: 7353946.6 | Z37: 9149015.7 | AA37: 2091389.9 | AE37: 9149015.7
B38: EPC自建 | C38: 1080 | D38: 丰宁三期 | E38: 商品销售 | F38: 0.13 | G38: =SUM(J38,L38,N38,P38,R38,T38,V38,X38,Z38,AB38,AD38,AF38,AH38,AJ38,AL38,AN38,AP38,AR38,AU38,AW38,AY38,BC38,BG38) -> 1.3184584e+08 | H38: =SUM(K38,M38,O38,Q38,S38,U38,W38,Y38,AA38,AC38,AE38,AG38,AI38,AK38,AM38,AO38,AQ38,AS38,AV38,AX38,AZ38,BD38,BH38) -> 1.4230007e+08 | I38: =G38-H38 -> -10454224 | N38: 11498521 | P38: 7347191.1 | Q38: 11498521 | R38: 6781679.1 | S38: 7347191.1 | T38: 0.02 | V38: 80139398 | W38: 17235903 | X38: 4038990.7 | Y38: 0 | Z38: 22040064 | AA38: 84178389 | AE38: 15258591 | AI38: 6781472.8
C39: 1080 | E39: 工程施工 | F39: 0.09 | G39: =SUM(J39,L39,N39,P39,R39,T39,V39,X39,Z39,AB39,AD39,AF39,AH39,AJ39,AL39,AN39,AP39,AR39,AU39,AW39,AY39,BC39,BG39) -> 4.5751058e+08 | H39: =SUM(K39,M39,O39,Q39,S39,U39,W39,Y39,AA39,AC39,AE39,AG39,AI39,AK39,AM39,AO39,AQ39,AS39,AV39,AX39,AZ39,BD39,BH39) -> 4.5996331e+08 | I39: =G39-H39 -> -2452735.4 | L39: 498586.12 | N39: 5439135.9 | P39: 15436790 | R39: 23070803 | S39: 23827247 | T39: 27932492 | V39: 33910823 | W39: 51003294 | X39: 24149722 | Y39: 21902159 | Z39: 25856795 | AA39: 36158386 | AD39: 3.0121543e+08 | AE39: 3.2707223e+08
C40: 1080 | E40: 设计咨询 | F40: 0.06 | G40: =SUM(J40,L40,N40,P40,R40,T40,V40,X40,Z40,AB40,AD40,AF40,AH40,AJ40,AL40,AN40,AP40,AR40,AU40,AW40,AY40,BC40,BG40) -> 16797953 | H40: =SUM(K40,M40,O40,Q40,S40,U40,W40,Y40,AA40,AC40,AE40,AG40,AI40,AK40,AM40,AO40,AQ40,AS40,AV40,AX40,AZ40,BD40,BH40) -> 19963111 | I40: =G40-H40 -> -3165158.3 | L40: 404945.11 | N40: 887361.61 | P40: -78904.76 | Q40: 4197791.7 | R40: 60092.57 | S40: 60092.57 | T40: 652067.3 | U40: 60296.37 | V40: =5996293.68+91089.15 -> 6087382.8 | W40: 863628.63 | X40: 1635477.4 | Y40: 59315.74 | Z40: 7149530.6 | AA40: 7572455.4 | AE40: 7149530.6
B41: EPC自建 | C41: 2316 | D41: 广西融水 | E41: 商品销售 | F41: 0.13 | G41: =SUM(J41,L41,N41,P41,R41,T41,V41,X41,Z41,AB41,AD41,AF41,AH41,AJ41,AL41,AN41,AP41,AR41,AU41,AW41,AY41,BC41,BG41) -> 3526106.2 | H41: =SUM(K41,M41,O41,Q41,S41,U41,W41,Y41,AA41,AC41,AE41,AG41,AI41,AK41,AM41,AO41,AQ41,AS41,AV41,AX41,AZ41,BD41,BH41) -> 3526106.2 | I41: =G41-H41 -> 0 | V41: 0 | W41: 0 | X41: 0 | Y41: 0 | AD41: 3526106.2 | AK41: 3526106.2
C42: 2316 | E42: 工程施工 | F42: 0.09 | G42: =SUM(J42,L42,N42,P42,R42,T42,V42,X42,Z42,AB42,AD42,AF42,AH42,AJ42,AL42,AN42,AP42,AR42,AU42,AW42,AY42,BC42,BG42) -> 0 | H42: =SUM(K42,M42,O42,Q42,S42,U42,W42,Y42,AA42,AC42,AE42,AG42,AI42,AK42,AM42,AO42,AQ42,AS42,AV42,AX42,AZ42,BD42,BH42) -> 0 | I42: =G42-H42 -> 0 | V42: 0 | W42: 0 | X42: 0 | Y42: 0
C43: 2316 | E43: 设计咨询 | F43: 0.06 | G43: =SUM(J43,L43,N43,P43,R43,T43,V43,X43,Z43,AB43,AD43,AF43,AH43,AJ43,AL43,AN43,AP43,AR43,AU43,AW43,AY43,BC43,BG43) -> 3187758.4 | H43: =SUM(K43,M43,O43,Q43,S43,U43,W43,Y43,AA43,AC43,AE43,AG43,AI43,AK43,AM43,AO43,AQ43,AS43,AV43,AX43,AZ43,BD43,BH43) -> 10589330 | I43: =G43-H43 -> -7401571.8 | L43: =-6425985.71+6471185.29 -> 45199.58 | M43: 6439798.6 | N43: 54164.39 | P43: 832458.31 | Q43: 1061137.2 | R43: 313557.91 | S43: 60092.57 | T43: 60296.37 | U43: 110522.47 | V43: =119624.91+91089.15 -> 210714.06 | W43: 91089.15 | X43: 753655.36 | Y43: 59315.74 | Z43: 45119.28 | AA43: 45119.28 | AB43: 95097.08 | AC43: 95097.08 | AD43: 71287.13 | AG43: 1849662.1 | AK43: 71287.13 | AP43: 284905.66 | AQ43: 284905.66 | AR43: 201165.05 | AS43: 201165.05 | AW43: 220138.24 | AZ43: 220138.24
B44: EPC自建 | C44: 2026 | D44: 河南濮阳台前 | E44: 商品销售 | F44: 0.13 | G44: =SUM(J44,L44,N44,P44,R44,T44,V44,X44,Z44,AB44,AD44,AF44,AH44,AJ44,AL44,AN44,AP44,AR44,AU44,AW44,AY44,BC44,BG44) -> 0 | H44: =SUM(K44,M44,O44,Q44,S44,U44,W44,Y44,AA44,AC44,AE44,AG44,AI44,AK44,AM44,AO44,AQ44,AS44,AV44,AX44,AZ44,BD44,BH44) -> 31750113 | I44: =G44-H44 -> -31750113 | M44: 31750113 | V44: 0 | W44: 0 | X44: 0 | Y44: 0
C45: 2026 | E45: 工程施工 | F45: 0.09 | G45: =SUM(J45,L45,N45,P45,R45,T45,V45,X45,Z45,AB45,AD45,AF45,AH45,AJ45,AL45,AN45,AP45,AR45,AU45,AW45,AY45,BC45,BG45) -> 0 | H45: =SUM(K45,M45,O45,Q45,S45,U45,W45,Y45,AA45,AC45,AE45,AG45,AI45,AK45,AM45,AO45,AQ45,AS45,AV45,AX45,AZ45,BD45,BH45) -> 33171636 | I45: =G45-H45 -> -33171636 | M45: 33171636 | V45: 0 | W45: 0 | X45: 0 | Y45: 0
C46: 2026 | E46: 设计咨询 | F46: 0.06 | G46: =SUM(J46,L46,N46,P46,R46,T46,V46,X46,Z46,AB46,AD46,AF46,AH46,AJ46,AL46,AN46,AP46,AR46,AU46,AW46,AY46,BC46,BG46) -> 235849.06 | H46: =SUM(K46,M46,O46,Q46,S46,U46,W46,Y46,AA46,AC46,AE46,AG46,AI46,AK46,AM46,AO46,AQ46,AS46,AV46,AX46,AZ46,BD46,BH46) -> 4299687 | I46: =G46-H46 -> -4063837.9 | L46: 235849.06 | M46: 4299687 | V46: 0 | W46: 0 | X46: 0 | Y46: 0
B47: EPC自建 | C47: 3314 | D47: 江西高安 | E47: 商品销售 | F47: 0.13 | G47: =SUM(J47,L47,N47,P47,R47,T47,V47,X47,Z47,AB47,AD47,AF47,AH47,AJ47,AL47,AN47,AP47,AR47,AU47,AW47,AY47,BC47,BG47) -> 70891363 | H47: =SUM(K47,M47,O47,Q47,S47,U47,W47,Y47,AA47,AC47,AE47,AG47,AI47,AK47,AM47,AO47,AQ47,AS47,AV47,AX47,AZ47,BD47,BH47) -> 91744119 | I47: =G47-H47 -> -20852756 | L47: 12608407 | N47: 13606195 | P47: 13606195 | Q47: 47067357 | R47: 13661517 | S47: 13606195 | T47: 6803097.3 | V47: 3473441.9 | W47: 20464615 | X47: 1224583.2 | Y47: 0 | Z47: 5907926.6 | AA47: 4337007.4 | AJ47: 0 | AK47: 6268944.3
C48: 3314 | E48: 工程施工 | F48: 0.09 | G48: =SUM(J48,L48,N48,P48,R48,T48,V48,X48,Z48,AB48,AD48,AF48,AH48,AJ48,AL48,AN48,AP48,AR48,AU48,AW48,AY48,BC48,BG48) -> 1.0104876e+08 | H48: =SUM(K48,M48,O48,Q48,S48,U48,W48,Y48,AA48,AC48,AE48,AG48,AI48,AK48,AM48,AO48,AQ48,AS48,AV48,AX48,AZ48,BD48,BH48) -> 1.5990496e+08 | I48: =G48-H48 -> -58856195 | L48: 2430176.7 | N48: 4192187.1 | P48: 2922190.4 | R48: 7321918.8 | S48: 68400749 | T48: 4366907.6 | V48: 3350080.6 | W48: 11688826 | X48: 3602505 | Y48: 2521858.6 | Z48: 12889061 | AA48: 4430727.1 | AJ48: 0 | AK48: 12889061 | AL48: 59973737 | AM48: 59973737 | AR48: -0.01
C49: 3314 | E49: 设计咨询 | F49: 0.06 | G49: =SUM(J49,L49,N49,P49,R49,T49,V49,X49,Z49,AB49,AD49,AF49,AH49,AJ49,AL49,AN49,AP49,AR49,AU49,AW49,AY49,BC49,BG49) -> 14007096 | H49: =SUM(K49,M49,O49,Q49,S49,U49,W49,Y49,AA49,AC49,AE49,AG49,AI49,AK49,AM49,AO49,AQ49,AS49,AV49,AX49,AZ49,BD49,BH49) -> 16122173 | I49: =G49-H49 -> -2115077.3 | L49: 358897.98 | N49: 560269.57 | P49: 271800.08 | Q49: 2979681.3 | R49: 175308.31 | S49: 279199.94 | T49: 738198.42 | U49: 137455.33 | V49: =2418745.68+68316.87 -> 2487062.5 | W49: =823215.02+68316.87 -> 891531.89 | X49: 141236.73 | Y49: 0 | Z49: 9274322.3 | AA49: 2559982.4 | AJ49: 0 | AK49: 9274322.3
B50: EPC自建 | C50: 2016 | D50: 内蒙察右后旗项目二 | E50: 商品销售 | F50: 0.13 | G50: =SUM(J50,L50,N50,P50,R50,T50,V50,X50,Z50,AB50,AD50,AF50,AH50,AJ50,AL50,AN50,AP50,AR50,AU50,AW50,AY50,BC50,BG50) -> 19584963 | H50: =SUM(K50,M50,O50,Q50,S50,U50,W50,Y50,AA50,AC50,AE50,AG50,AI50,AK50,AM50,AO50,AQ50,AS50,AV50,AX50,AZ50,BD50,BH50) -> 19584963 | I50: =G50-H50 -> 0 | P50: 19584963 | R50: 0 | S50: 19584963 | V50: 0 | W50: 0 | X50: 0 | Y50: 0
C51: 2016 | E51: 工程施工 | F51: 0.09 | G51: =SUM(J51,L51,N51,P51,R51,T51,V51,X51,Z51,AB51,AD51,AF51,AH51,AJ51,AL51,AN51,AP51,AR51,AU51,AW51,AY51,BC51,BG51) -> 3991345.2 | H51: =SUM(K51,M51,O51,Q51,S51,U51,W51,Y51,AA51,AC51,AE51,AG51,AI51,AK51,AM51,AO51,AQ51,AS51,AV51,AX51,AZ51,BD51,BH51) -> 5446187.1 | I51: =G51-H51 -> -1454841.9 | R51: 0 | S51: 1454841.9 | V51: 0 | W51: 0 | X51: 0 | Y51: 0 | Z51: 3991345.2 | AC51: 3991345.2 | AR51: 0.01
C52: 2016 | E52: 设计咨询 | F52: 0.06 | G52: =SUM(J52,L52,N52,P52,R52,T52,V52,X52,Z52,AB52,AD52,AF52,AH52,AJ52,AL52,AN52,AP52,AR52,AU52,AW52,AY52,BC52,BG52) -> 4027205.7 | H52: =SUM(K52,M52,O52,Q52,S52,U52,W52,Y52,AA52,AC52,AE52,AG52,AI52,AK52,AM52,AO52,AQ52,AS52,AV52,AX52,AZ52,BD52,BH52) -> 3314881.9 | I52: =G52-H52 -> 712323.84 | L52: 20225.69 | N52: 89988.01 | P52: 18834.8 | Q52: 1207772.6 | R52: 22534.72 | S52: 22534.72 | T52: 22611.14 | U52: 41445.94 | V52: =1880746.37+34158.42 -> 1914904.8 | W52: 34158.42 | X52: 22243.4 | Y52: 155622.33 | Z52: 1853347.8 | AD52: 62515.32 | AI52: 1853347.8
B53: EPC自建 | C53: 2016 | D53: 内蒙察右后旗项目一 | E53: 商品销售 | F53: 0.13 | G53: =SUM(J53,L53,N53,P53,R53,T53,V53,X53,Z53,AB53,AD53,AF53,AH53,AJ53,AL53,AN53,AP53,AR53,AU53,AW53,AY53,BC53,BG53) -> 36181724 | H53: =SUM(K53,M53,O53,Q53,S53,U53,W53,Y53,AA53,AC53,AE53,AG53,AI53,AK53,AM53,AO53,AQ53,AS53,AV53,AX53,AZ53,BD53,BH53) -> 36181724 | I53: =G53-H53 -> 0 | P53: 27152204 | R53: 176101.34 | S53: 27152204 | V53: 3723884 | W53: 0 | X53: 0 | Y53: 3899985.3 | Z53: 5129535.4 | AI53: 5129535.4
C54: 2016 | E54: 工程施工 | F54: 0.09 | G54: =SUM(J54,L54,N54,P54,R54,T54,V54,X54,Z54,AB54,AD54,AF54,AH54,AJ54,AL54,AN54,AP54,AR54,AU54,AW54,AY54,BC54,BG54) -> 2.0832883e+08 | H54: =SUM(K54,M54,O54,Q54,S54,U54,W54,Y54,AA54,AC54,AE54,AG54,AI54,AK54,AM54,AO54,AQ54,AS54,AV54,AX54,AZ54,BD54,BH54) -> 2.1315087e+08 | I54: =G54-H54 -> -4822035.7 | L54: 507798.16 | N54: 1269495.4 | P54: 1360228.2 | R54: 0 | S54: 7959557.4 | T54: 1973247.2 | V54: 305907.77 | W54: 0 | X54: 7646759.4 | Y54: 2279155 | Z54: 50766702 | AC54: 11936901 | AI54: 46476560 | AR54: 73394495 | AS54: 73394495 | AU54: 71104199 | AX54: 71104199
C55: 2016 | E55: 设计咨询 | F55: 0.06 | G55: =SUM(J55,L55,N55,P55,R55,T55,V55,X55,Z55,AB55,AD55,AF55,AH55,AJ55,AL55,AN55,AP55,AR55,AU55,AW55,AY55,BC55,BG55) -> 15348125 | H55: =SUM(K55,M55,O55,Q55,S55,U55,W55,Y55,AA55,AC55,AE55,AG55,AI55,AK55,AM55,AO55,AQ55,AS55,AV55,AX55,AZ55,BD55,BH55) -> 17209687 | I55: =G55-H55 -> -1861562.5 | L55: 20225.69 | N55: 908379.56 | P55: 650679.63 | Q55: 980285.04 | R55: 2821931.8 | S55: 654379.55 | T55: 731886.98 | U55: 41445.94 | V55: =1959365.19+34158.42 -> 1993523.6 | W55: 34158.42 | X55: 1011104.7 | Y55: 7237649 | Z55: 6674545.2 | AB55: 900636.97 | AI55: 8626558.7 | AL55: 221438.68 | AR55: 0.01 | AS55: 221438.68 | AU55: -586228 | AX55: -586228
B56: EPC自建 | C56: 4470 | D56: 内蒙伊旗风光储 | E56: 商品销售 | F56: 0.13 | G56: =SUM(J56,L56,N56,P56,R56,T56,V56,X56,Z56,AB56,AD56,AF56,AH56,AJ56,AL56,AN56,AP56,AR56,AU56,AW56,AY56,BC56,BG56) -> 1.5632661e+08 | H56: =SUM(K56,M56,O56,Q56,S56,U56,W56,Y56,AA56,AC56,AE56,AG56,AI56,AK56,AM56,AO56,AQ56,AS56,AV56,AX56,AZ56,BD56,BH56) -> 62114591 | I56: =G56-H56 -> 94212016 | L56: 12953097 | N56: 7559164.6 | P56: 3793850.7 | T56: 55278600 | V56: 52916259 | W56: 9840417.2 | X56: 10795169 | Y56: 0 | AA56: -54847.11 | AB56: 114480.68 | AC56: -79871.12 | AD56: 16916191 | AE56: 50514064 | AF56: 12535.93 | AL56: 1882292.1 | AN56: 13869886 | AP56: 3314574.2 | AQ56: 1894828.1 | AW56: -103706.42 | BC56: -20924241 | BG56: -2051547.6
C57: 4470 | E57: 工程施工 | F57: 0.09 | G57: =SUM(J57,L57,N57,P57,R57,T57,V57,X57,Z57,AB57,AD57,AF57,AH57,AJ57,AL57,AN57,AP57,AR57,AU57,AW57,AY57,BC57,BG57) -> 1.269103e+08 | H57: =SUM(K57,M57,O57,Q57,S57,U57,W57,Y57,AA57,AC57,AE57,AG57,AI57,AK57,AM57,AO57,AQ57,AS57,AV57,AX57,AZ57,BD57,BH57) -> 1.2446601e+08 | I57: =G57-H57 -> 2444285 | N57: 12131406 | P57: 32038296 | Q57: 49098165 | T57: 23227907 | V57: 28676174 | W57: 32191615 | X57: 16473081 | Y57: 16473081 | Z57: 12571169 | AA57: 12571169 | AD57: 7925458.3 | AE57: 7925458.3 | AF57: =2781089.72+401414.45 -> 3182504.2 | AL57: 62534.4 | AN57: 288592.24 | AP57: 3479357.8 | AQ57: 6206522.4 | AW57: -220368.17 | BC57: -18201528 | BG57: 5275711.8
C58: 4470 | E58: 设计咨询 | F58: 0.06 | G58: =SUM(J58,L58,N58,P58,R58,T58,V58,X58,Z58,AB58,AD58,AF58,AH58,AJ58,AL58,AN58,AP58,AR58,AU58,AW58,AY58,BC58,BG58) -> 31903821 | H58: =SUM(K58,M58,O58,Q58,S58,U58,W58,Y58,AA58,AC58,AE58,AG58,AI58,AK58,AM58,AO58,AQ58,AS58,AV58,AX58,AZ58,BD58,BH58) -> 52059489 | I58: =G58-H58 -> -20155668 | L58: =53935.17+6741.9 -> 60677.07 | N58: =126783.7+6770.55 -> 133554.25 | P58: =605292.35+6278.27 -> 611570.62 | U58: 41285582 | V58: 91089.15 | W58: 91089.15 | X58: 602950.62 | Y58: 757667.6 | Z58: 251408.63 | AA58: 251408.63 | AC58: 11887.15 | AD58: 1892980.1 | AE58: 8434196.8 | AF58: 227323.24 | AL58: 3587500 | AN58: 594201.85 | AQ58: 1227657.2 | AW58: 1366564.2 | BC58: -351429.1 | BG58: 22835430
C59: 甘肃宏宇天成电力工程有限公司 | D59: 内蒙伊旗风光储 | E59: 商品销售 | F59: 0.13 | G59: =SUM(J59,L59,N59,P59,R59,T59,V59,X59,Z59,AB59,AD59,AF59,AH59,AJ59,AL59,AN59,AP59,AR59,AU59,AW59,AY59,BC59,BG59) -> 0 | H59: =SUM(K59,M59,O59,Q59,S59,U59,W59,Y59,AA59,AC59,AE59,AG59,AI59,AK59,AM59,AO59,AQ59,AS59,AV59,AX59,AZ59,BD59,BH59) -> 2451327.5 | BH59: 2451327.5
E60: 工程施工 | F60: 0.09 | G60: =SUM(J60,L60,N60,P60,R60,T60,V60,X60,Z60,AB60,AD60,AF60,AH60,AJ60,AL60,AN60,AP60,AR60,AU60,AW60,AY60,BC60,BG60) -> 0 | H60: =SUM(K60,M60,O60,Q60,S60,U60,W60,Y60,AA60,AC60,AE60,AG60,AI60,AK60,AM60,AO60,AQ60,AS60,AV60,AX60,AZ60,BD60,BH60) -> 0
E61: 设计咨询 | F61: 0.06 | G61: =SUM(J61,L61,N61,P61,R61,T61,V61,X61,Z61,AB61,AD61,AF61,AH61,AJ61,AL61,AN61,AP61,AR61,AU61,AW61,AY61,BC61,BG61) -> 0 | H61: =SUM(K61,M61,O61,Q61,S61,U61,W61,Y61,AA61,AC61,AE61,AG61,AI61,AK61,AM61,AO61,AQ61,AS61,AV61,AX61,AZ61,BD61,BH61) -> 0
C62: 河间市绿洁再生资源回收有限公司 | D62: 内蒙伊旗风光储 | E62: 商品销售 | F62: 0.13 | G62: =SUM(J62,L62,N62,P62,R62,T62,V62,X62,Z62,AB62,AD62,AF62,AH62,AJ62,AL62,AN62,AP62,AR62,AU62,AW62,AY62,BC62,BG62) -> 0 | H62: =SUM(K62,M62,O62,Q62,S62,U62,W62,Y62,AA62,AC62,AE62,AG62,AI62,AK62,AM62,AO62,AQ62,AS62,AV62,AX62,AZ62,BD62,BH62) -> 361770.42 | BH62: 361770.42
E63: 工程施工 | F63: 0.09 | G63: =SUM(J63,L63,N63,P63,R63,T63,V63,X63,Z63,AB63,AD63,AF63,AH63,AJ63,AL63,AN63,AP63,AR63,AU63,AW63,AY63,BC63,BG63) -> 0 | H63: =SUM(K63,M63,O63,Q63,S63,U63,W63,Y63,AA63,AC63,AE63,AG63,AI63,AK63,AM63,AO63,AQ63,AS63,AV63,AX63,AZ63,BD63,BH63) -> 0
E64: 设计咨询 | F64: 0.06 | G64: =SUM(J64,L64,N64,P64,R64,T64,V64,X64,Z64,AB64,AD64,AF64,AH64,AJ64,AL64,AN64,AP64,AR64,AU64,AW64,AY64,BC64,BG64) -> 0 | H64: =SUM(K64,M64,O64,Q64,S64,U64,W64,Y64,AA64,AC64,AE64,AG64,AI64,AK64,AM64,AO64,AQ64,AS64,AV64,AX64,AZ64,BD64,BH64) -> 0
B65: EPC自建 | C65: 3A18 | D65: 钦州灵山独立储能 | E65: 商品销售 | F65: 0.13 | G65: =SUM(J65,L65,N65,P65,R65,T65,V65,X65,Z65,AB65,AD65,AF65,AH65,AJ65,AL65,AN65,AP65,AR65,AU65,AW65,AY65,BC65,BG65) -> 0 | H65: =SUM(K65,M65,O65,Q65,S65,U65,W65,Y65,AA65,AC65,AE65,AG65,AI65,AK65,AM65,AO65,AQ65,AS65,AV65,AX65,AZ65,BD65,BH65) -> 0 | I65: =G65-H65 -> 0 | V65: 0 | W65: 0 | X65: 0 | Y65: 0
C66: 3A18 | E66: 工程施工 | F66: 0.09 | G66: =SUM(J66,L66,N66,P66,R66,T66,V66,X66,Z66,AB66,AD66,AF66,AH66,AJ66,AL66,AN66,AP66,AR66,AU66,AW66,AY66,BC66,BG66) -> 0 | H66: =SUM(K66,M66,O66,Q66,S66,U66,W66,Y66,AA66,AC66,AE66,AG66,AI66,AK66,AM66,AO66,AQ66,AS66,AV66,AX66,AZ66,BD66,BH66) -> 0 | I66: =G66-H66 -> 0 | V66: 0 | W66: 0 | X66: 0 | Y66: 0
C67: 3A18 | E67: 设计咨询 | F67: 0.06 | G67: =SUM(J67,L67,N67,P67,R67,T67,V67,X67,Z67,AB67,AD67,AF67,AH67,AJ67,AL67,AN67,AP67,AR67,AU67,AW67,AY67,BC67,BG67) -> 60072 | H67: =SUM(K67,M67,O67,Q67,S67,U67,W67,Y67,AA67,AC67,AE67,AG67,AI67,AK67,AM67,AO67,AQ67,AS67,AV67,AX67,AZ67,BD67,BH67) -> 813027.61 | I67: =G67-H67 -> -752955.61 | L67: 7219.88 | N67: 7220.06 | P67: 7307.29 | R67: 7319.78 | S67: 7319.78 | T67: 11645.92 | U67: 805707.83 | V67: 0 | W67: 0 | X67: 0 | Y67: 0 | AR67: 19359.07
B68: EPC自建 | C68: 3318 | D68: 新疆巴里坤 | E68: 商品销售 | F68: 0.13 | G68: =SUM(J68,L68,N68,P68,R68,T68,V68,X68,Z68,AB68,AD68,AF68,AH68,AJ68,AL68,AN68,AP68,AR68,AU68,AW68,AY68,BC68,BG68) -> 0 | H68: =SUM(K68,M68,O68,Q68,S68,U68,W68,Y68,AA68,AC68,AE68,AG68,AI68,AK68,AM68,AO68,AQ68,AS68,AV68,AX68,AZ68,BD68,BH68) -> 0 | I68: =G68-H68 -> 0 | V68: 0 | W68: 0 | X68: 0 | Y68: 0
C69: 3318 | E69: 工程施工 | F69: 0.09 | G69: =SUM(J69,L69,N69,P69,R69,T69,V69,X69,Z69,AB69,AD69,AF69,AH69,AJ69,AL69,AN69,AP69,AR69,AU69,AW69,AY69,BC69,BG69) -> 0 | H69: =SUM(K69,M69,O69,Q69,S69,U69,W69,Y69,AA69,AC69,AE69,AG69,AI69,AK69,AM69,AO69,AQ69,AS69,AV69,AX69,AZ69,BD69,BH69) -> 0 | I69: =G69-H69 -> 0 | V69: 0 | W69: 0 | X69: 0 | Y69: 0
C70: 3318 | E70: 设计咨询 | F70: 0.06 | G70: =SUM(J70,L70,N70,P70,R70,T70,V70,X70,Z70,AB70,AD70,AF70,AH70,AJ70,AL70,AN70,AP70,AR70,AU70,AW70,AY70,BC70,BG70) -> 1132075.5 | H70: =SUM(K70,M70,O70,Q70,S70,U70,W70,Y70,AA70,AC70,AE70,AG70,AI70,AK70,AM70,AO70,AQ70,AS70,AV70,AX70,AZ70,BD70,BH70) -> 1132075.5 | I70: =G70-H70 -> 0 | L70: 1132075.5 | M70: 1132075.5 | V70: 0 | W70: 0 | X70: 0 | Y70: 0
B71: EPC自建 | C71: 3350 | D71: 射阳汇智风电场110kv升压站站内设备检测工程 | E71: 商品销售 | F71: 0.13 | G71: =SUM(J71,L71,N71,P71,R71,T71,V71,X71,Z71,AB71,AD71,AF71,AH71,AJ71,AL71,AN71,AP71,AR71,AU71,AW71,AY71,BC71,BG71) -> 0 | H71: =SUM(K71,M71,O71,Q71,S71,U71,W71,Y71,AA71,AC71,AE71,AG71,AI71,AK71,AM71,AO71,AQ71,AS71,AV71,AX71,AZ71,BD71,BH71) -> 0 | I71: =G71-H71 -> 0 | V71: 0 | W71: 0 | X71: 0 | Y71: 0
C72: 3350 | E72: 工程施工 | F72: 0.09 | G72: =SUM(J72,L72,N72,P72,R72,T72,V72,X72,Z72,AB72,AD72,AF72,AH72,AJ72,AL72,AN72,AP72,AR72,AU72,AW72,AY72,BC72,BG72) -> 0 | H72: =SUM(K72,M72,O72,Q72,S72,U72,W72,Y72,AA72,AC72,AE72,AG72,AI72,AK72,AM72,AO72,AQ72,AS72,AV72,AX72,AZ72,BD72,BH72) -> 479041.85 | I72: =G72-H72 -> -479041.85 | Q72: 258731.46 | V72: 0 | W72: 0 | X72: 0 | Y72: 0 | AE72: -258731.46 | AM72: 479041.85
C73: 3350 | E73: 设计咨询 | F73: 0.06 | G73: =SUM(J73,L73,N73,P73,R73,T73,V73,X73,Z73,AB73,AD73,AF73,AH73,AJ73,AL73,AN73,AP73,AR73,AU73,AW73,AY73,BC73,BG73) -> 0 | H73: =SUM(K73,M73,O73,Q73,S73,U73,W73,Y73,AA73,AC73,AE73,AG73,AI73,AK73,AM73,AO73,AQ73,AS73,AV73,AX73,AZ73,BD73,BH73) -> 0 | I73: =G73-H73 -> 0 | R73: 191067.96 | S73: 0 | V73: 0 | W73: 0 | X73: 0 | Y73: 0 | BC73: -191067.96
B74: EPC自建 | C74: 4470 | D74: 内蒙鄂尔多斯风电场运检维护项目 | E74: 商品销售 | F74: 0.13 | G74: =SUM(J74,L74,N74,P74,R74,T74,V74,X74,Z74,AB74,AD74,AF74,AH74,AJ74,AL74,AN74,AP74,AR74,AU74,AW74,AY74,BC74,BG74) -> 38525142 | H74: =SUM(K74,M74,O74,Q74,S74,U74,W74,Y74,AA74,AC74,AE74,AG74,AI74,AK74,AM74,AO74,AQ74,AS74,AV74,AX74,AZ74,BD74,BH74) -> 16726499 | I74: =G74-H74 -> 21798643 | R74: 535025.56 | S74: 0 | U74: 16726499 | V74: =4376588 -> 4376588 | W74: 0 | X74: 0 | Y74: 0 | Z74: 32984880 | AB74: 610464.6 | AN74: 18184.68
C75: 4470 | E75: 工程施工 | F75: 0.09 | G75: =SUM(J75,L75,N75,P75,R75,T75,V75,X75,Z75,AB75,AD75,AF75,AH75,AJ75,AL75,AN75,AP75,AR75,AU75,AW75,AY75,BC75,BG75) -> 2594225.3 | H75: =SUM(K75,M75,O75,Q75,S75,U75,W75,Y75,AA75,AC75,AE75,AG75,AI75,AK75,AM75,AO75,AQ75,AS75,AV75,AX75,AZ75,BD75,BH75) -> 31473110 | I75: =G75-H75 -> -28878885 | Q75: 486312.49 | R75: 831989.3 | S75: 0 | U75: 30542864 | V75: =831989.3+930246.74 -> 1762236 | W75: 930246.74 | X75: 0 | Y75: 0 | AE75: -486312.49
C76: 4470 | E76: 设计咨询 | F76: 0.06 | G76: =SUM(J76,L76,N76,P76,R76,T76,V76,X76,Z76,AB76,AD76,AF76,AH76,AJ76,AL76,AN76,AP76,AR76,AU76,AW76,AY76,BC76,BG76) -> 47143610 | H76: =SUM(K76,M76,O76,Q76,S76,U76,W76,Y76,AA76,AC76,AE76,AG76,AI76,AK76,AM76,AO76,AQ76,AS76,AV76,AX76,AZ76,BD76,BH76) -> 7511.57 | I76: =G76-H76 -> 47136098 | R76: 7511.57 | S76: 7511.57 | T76: 41339457 | V76: 0 | W76: 0 | X76: 0 | Y76: 0 | AB76: 5796641.1 | BC76: 0
B77: EPC自建 | C77: 4470 | D77: 内蒙伊旗风光储-光伏 | E77: 商品销售 | F77: 0.13 | G77: =SUM(J77,L77,N77,P77,R77,T77,V77,X77,Z77,AB77,AD77,AF77,AH77,AJ77,AL77,AN77,AP77,AR77,AU77,AW77,AY77,BC77,BG77) -> 27234067 | H77: =SUM(K77,M77,O77,Q77,S77,U77,W77,Y77,AA77,AC77,AE77,AG77,AI77,AK77,AM77,AO77,AQ77,AS77,AV77,AX77,AZ77,BD77,BH77) -> 63552791 | I77: =G77-H77 -> -36318724 | R77: 19775234 | S77: 50697108 | T77: 535025.56 | V77: 0 | W77: 0 | X77: 2690452.9 | Y77: 2690452.9 | Z77: 1610020.5 | AA77: 1610020.5 | AD77: 323827.43 | AE77: 6057103.7 | AF77: 1710381 | AH77: 412382.29 | AQ77: 1186468.6 | AR77: 518750.43 | AV77: 1311637.2 | AY77: -342007.13
C78: 4470 | E78: 工程施工 | F78: 0.09 | G78: =SUM(J78,L78,N78,P78,R78,T78,V78,X78,Z78,AB78,AD78,AF78,AH78,AJ78,AL78,AN78,AP78,AR78,AU78,AW78,AY78,BC78,BG78) -> 20631616 | H78: =SUM(K78,M78,O78,Q78,S78,U78,W78,Y78,AA78,AC78,AE78,AG78,AI78,AK78,AM78,AO78,AQ78,AS78,AV78,AX78,AZ78,BD78,BH78) -> 8131237.4 | I78: =G78-H78 -> 12500378 | R78: 11119160 | S78: 917431.19 | V78: 207306.14 | W78: 207306.14 | X78: 0 | Y78: 0 | AB78: 270555.32 | AD78: 757261.12 | AE78: =2421239.72+270555.32 -> 2691795 | AF78: 5127803.9 | AQ78: 3671822.6 | AR78: 188073.4 | AV78: 642882.47 | AY78: 402538 | BG78: 2558917.5
C79: 4470 | E79: 设计咨询 | F79: 0.06 | G79: =SUM(J79,L79,N79,P79,R79,T79,V79,X79,Z79,AB79,AD79,AF79,AH79,AJ79,AL79,AN79,AP79,AR79,AU79,AW79,AY79,BC79,BG79) -> 945443.01 | H79: =SUM(K79,M79,O79,Q79,S79,U79,W79,Y79,AA79,AC79,AE79,AG79,AI79,AK79,AM79,AO79,AQ79,AS79,AV79,AX79,AZ79,BD79,BH79) -> 1160920.3 | I79: =G79-H79 -> -215477.27 | R79: 60092.57 | S79: 687778.13 | V79: =186949.69+11386.14 -> 198335.83 | W79: =186949.69+11386.14 -> 198335.83 | X79: 7414.46 | Y79: 7414.46 | Z79: 5639.92 | AA79: 5639.92 | AB79: 11887.15 | AD79: 197931.19 | AE79: 197931.19 | AR79: 63820.75 | AU79: 15471.7 | AV79: 63820.75 | AY79: 287000 | BG79: 97849.44
B80: EPC自建 | C80: 4570 | D80: 河北沧县 | E80: 商品销售 | F80: 0.13 | G80: =SUM(J80,L80,N80,P80,R80,T80,V80,X80,Z80,AB80,AD80,AF80,AH80,AJ80,AL80,AN80,AP80,AR80,AU80,AW80,AY80,BC80,BG80) -> 40316.81 | H80: =SUM(K80,M80,O80,Q80,S80,U80,W80,Y80,AA80,AC80,AE80,AG80,AI80,AK80,AM80,AO80,AQ80,AS80,AV80,AX80,AZ80,BD80,BH80) -> 40316.81 | I80: =G80-H80 -> 0 | V80: 40316.81 | W80: 0 | X80: 0 | Y80: 0 | AG80: 40316.81
C81: 4570 | E81: 工程施工 | F81: 0.09 | G81: =SUM(J81,L81,N81,P81,R81,T81,V81,X81,Z81,AB81,AD81,AF81,AH81,AJ81,AL81,AN81,AP81,AR81,AU81,AW81,AY81,BC81,BG81) -> 291262.14 | H81: =SUM(K81,M81,O81,Q81,S81,U81,W81,Y81,AA81,AC81,AE81,AG81,AI81,AK81,AM81,AO81,AQ81,AS81,AV81,AX81,AZ81,BD81,BH81) -> 291262.14 | I81: =G81-H81 -> 0 | L81: 291262.14 | M81: 291262.14 | V81: 0 | W81: 0 | X81: 0 | Y81: 0
C82: 4570 | E82: 设计咨询 | F82: 0.06 | G82: =SUM(J82,L82,N82,P82,R82,T82,V82,X82,Z82,AB82,AD82,AF82,AH82,AJ82,AL82,AN82,AP82,AR82,AU82,AW82,AY82,BC82,BG82) -> 10105098 | H82: =SUM(K82,M82,O82,Q82,S82,U82,W82,Y82,AA82,AC82,AE82,AG82,AI82,AK82,AM82,AO82,AQ82,AS82,AV82,AX82,AZ82,BD82,BH82) -> 10455261 | I82: =G82-H82 -> -350163.07 | L82: =4391330.09+329654.87 -> 4720985 | M82: 4203905.6 | N82: 488607.91 | P82: 323799.97 | Q82: 1355850.4 | R82: 864773.96 | S82: 67604.15 | T82: 67833.42 | U82: 124337.79 | V82: =1327755.84+102475.29 -> 1430231.1 | W82: 102475.29 | X82: 962956.63 | Y82: 66730.21 | Z82: 50759.24 | AA82: 50759.24 | AB82: 467059.25 | AC82: 467059.25 | AD82: 300060.87 | AG82: 3588508.5 | AN82: 157232.7 | AQ82: 157232.7 | AR82: 181699.17 | AS82: 181699.17 | AU82: 89098.55 | AZ82: 89098.55
B83: EPC自建 | C83: 2351 | D83: 河南濮阳昆吾 | E83: 商品销售 | F83: 0.13 | G83: =SUM(J83,L83,N83,P83,R83,T83,V83,X83,Z83,AB83,AD83,AF83,AH83,AJ83,AL83,AN83,AP83,AR83,AU83,AW83,AY83,BC83,BG83) -> 0 | H83: =SUM(K83,M83,O83,Q83,S83,U83,W83,Y83,AA83,AC83,AE83,AG83,AI83,AK83,AM83,AO83,AQ83,AS83,AV83,AX83,AZ83,BD83,BH83) -> 0 | I83: =G83-H83 -> 0 | V83: 0 | W83: 0 | X83: 0 | Y83: 0
C84: 2351 | E84: 工程施工 | F84: 0.09 | G84: =SUM(J84,L84,N84,P84,R84,T84,V84,X84,Z84,AB84,AD84,AF84,AH84,AJ84,AL84,AN84,AP84,AR84,AU84,AW84,AY84,BC84,BG84) -> 769393.45 | H84: =SUM(K84,M84,O84,Q84,S84,U84,W84,Y84,AA84,AC84,AE84,AG84,AI84,AK84,AM84,AO84,AQ84,AS84,AV84,AX84,AZ84,BD84,BH84) -> 769393.45 | I84: =G84-H84 -> 0 | L84: 769393.45 | M84: 769393.45 | V84: 0 | W84: 0 | X84: 0 | Y84: 0
C85: 2351 | E85: 设计咨询 | F85: 0.06 | G85: =SUM(J85,L85,N85,P85,R85,T85,V85,X85,Z85,AB85,AD85,AF85,AH85,AJ85,AL85,AN85,AP85,AR85,AU85,AW85,AY85,BC85,BG85) -> 8138787.5 | H85: =SUM(K85,M85,O85,Q85,S85,U85,W85,Y85,AA85,AC85,AE85,AG85,AI85,AK85,AM85,AO85,AQ85,AS85,AV85,AX85,AZ85,BD85,BH85) -> 8461721.4 | I85: =G85-H85 -> -322933.89 | L85: =354587.32+4501401.45 -> 4855988.8 | M85: 3388193.9 | N85: 420738.6 | P85: 226506.05 | Q85: 2123417 | R85: 761004.23 | S85: 45069.43 | T85: 93440.31 | U85: 82891.85 | V85: 203692.85 | W85: 68316.87 | X85: 44486.8 | Y85: 44486.8 | Z85: 306376.18 | AA85: 33839.49 | AB85: 143021.01 | AC85: 71322.9 | AD85: 167722.12 | AG85: 1520650.4 | AJ85: 89108.91 | AK85: 256831.03 | AN85: 260405.04 | AP85: 78613.21 | AQ85: 339018.25 | AR85: 27096.43 | AS85: 27096.43 | AU85: 460587 | BH85: 460587
B86: EPC自建 | C86: 3307 | D86: 灵山玖伯一期 | E86: 商品销售 | F86: 0.13 | G86: =SUM(J86,L86,N86,P86,R86,T86,V86,X86,Z86,AB86,AD86,AF86,AH86,AJ86,AL86,AN86,AP86,AR86,AU86,AW86,AY86,BC86,BG86) -> 0 | H86: =SUM(K86,M86,O86,Q86,S86,U86,W86,Y86,AA86,AC86,AE86,AG86,AI86,AK86,AM86,AO86,AQ86,AS86,AV86,AX86,AZ86,BD86,BH86) -> 0 | I86: =G86-H86 -> 0 | V86: 0 | W86: 0 | X86: 0 | Y86: 0
C87: 3307 | E87: 工程施工 | F87: 0.09 | G87: =SUM(J87,L87,N87,P87,R87,T87,V87,X87,Z87,AB87,AD87,AF87,AH87,AJ87,AL87,AN87,AP87,AR87,AU87,AW87,AY87,BC87,BG87) -> 194174.76 | H87: =SUM(K87,M87,O87,Q87,S87,U87,W87,Y87,AA87,AC87,AE87,AG87,AI87,AK87,AM87,AO87,AQ87,AS87,AV87,AX87,AZ87,BD87,BH87) -> 194174.76 | I87: =G87-H87 -> 0 | L87: 194174.76 | M87: 194174.76 | V87: 0 | W87: 0 | X87: 0 | Y87: 0
C88: 3307 | E88: 设计咨询 | F88: 0.06 | G88: =SUM(J88,L88,N88,P88,R88,T88,V88,X88,Z88,AB88,AD88,AF88,AH88,AJ88,AL88,AN88,AP88,AR88,AU88,AW88,AY88,BC88,BG88) -> 5322473.7 | H88: =SUM(K88,M88,O88,Q88,S88,U88,W88,Y88,AA88,AC88,AE88,AG88,AI88,AK88,AM88,AO88,AQ88,AS88,AV88,AX88,AZ88,BD88,BH88) -> 5584965 | I88: =G88-H88 -> -262491.27 | L88: =1978162.8+131078.12 -> 2109240.9 | M88: 1918579.9 | N88: 54164.39 | P88: 555432.9 | Q88: 500605.24 | R88: 60092.57 | S88: 60092.57 | U88: 110522.47 | V88: =525589.21+91089.15 -> 616678.36 | W88: 91089.15 | X88: 141957.25 | Y88: 59315.74 | Z88: 45119.32 | AA88: 45119.32 | AB88: 175474.56 | AC88: 95097.2 | AD88: 87852.62 | AE88: 87852.62 | AG88: 1193814.9 | AH88: 1099136.7 | AI88: 1099136.7 | BC88: 323739.19 | BG88: 53584.91 | BH88: 323739.19
B89: EPC自建 | C89: 3307 | D89: 灵山玖伯二期 | E89: 商品销售 | F89: 0.13 | G89: =SUM(J89,L89,N89,P89,R89,T89,V89,X89,Z89,AB89,AD89,AF89,AH89,AJ89,AL89,AN89,AP89,AR89,AU89,AW89,AY89,BC89,BG89) -> 0 | H89: =SUM(K89,M89,O89,Q89,S89,U89,W89,Y89,AA89,AC89,AE89,AG89,AI89,AK89,AM89,AO89,AQ89,AS89,AV89,AX89,AZ89,BD89,BH89) -> 0 | I89: =G89-H89 -> 0 | V89: 0 | W89: 0 | X89: 0 | Y89: 0
C90: 3307 | E90: 工程施工 | F90: 0.09 | G90: =SUM(J90,L90,N90,P90,R90,T90,V90,X90,Z90,AB90,AD90,AF90,AH90,AJ90,AL90,AN90,AP90,AR90,AU90,AW90,AY90,BC90,BG90) -> 0 | H90: =SUM(K90,M90,O90,Q90,S90,U90,W90,Y90,AA90,AC90,AE90,AG90,AI90,AK90,AM90,AO90,AQ90,AS90,AV90,AX90,AZ90,BD90,BH90) -> 0 | I90: =G90-H90 -> 0 | V90: 0 | W90: 0 | X90: 0 | Y90: 0
C91: 3307 | E91: 设计咨询 | F91: 0.06 | G91: =SUM(J91,L91,N91,P91,R91,T91,V91,X91,Z91,AB91,AD91,AF91,AH91,AJ91,AL91,AN91,AP91,AR91,AU91,AW91,AY91,BC91,BG91) -> 3482281.2 | H91: =SUM(K91,M91,O91,Q91,S91,U91,W91,Y91,AA91,AC91,AE91,AG91,AI91,AK91,AM91,AO91,AQ91,AS91,AV91,AX91,AZ91,BD91,BH91) -> 3677764.7 | I91: =G91-H91 -> -195483.44 | L91: =1299437.53+115623.92 -> 1415061.4 | M91: 1245812.9 | N91: 54164.39 | P91: 352625.48 | Q91: 479192.75 | R91: 60092.57 | S91: 60092.57 | T91: 120592.74 | U91: 110522.47 | V91: =408373.06+91089.15 -> 499462.21 | W91: 91089.15 | X91: 59315.74 | Y91: 59315.74 | Z91: 45119.32 | AA91: 45119.32 | AB91: 95097.2 | AC91: 95097.2 | AD91: 87852.62 | AE91: 87852.62 | AG91: 710772.44 | AH91: 473848.28 | AI91: 473848.28 | BC91: 219049.25 | BH91: 219049.25
B92: EPC自建 | C92: 2058 | D92: 钦南久沙 | E92: 商品销售 | F92: 0.13 | G92: =SUM(J92,L92,N92,P92,R92,T92,V92,X92,Z92,AB92,AD92,AF92,AH92,AJ92,AL92,AN92,AP92,AR92,AU92,AW92,AY92,BC92,BG92) -> 165026.55 | H92: =SUM(K92,M92,O92,Q92,S92,U92,W92,Y92,AA92,AC92,AE92,AG92,AI92,AK92,AM92,AO92,AQ92,AS92,AV92,AX92,AZ92,BD92,BH92) -> 165026.55 | I92: =G92-H92 -> 0 | V92: 0 | W92: 0 | X92: 0 | Y92: 0 | AW92: 165026.55 | AX92: 165026.55
C93: 2058 | E93: 工程施工 | F93: 0.09 | G93: =SUM(J93,L93,N93,P93,R93,T93,V93,X93,Z93,AB93,AD93,AF93,AH93,AJ93,AL93,AN93,AP93,AR93,AU93,AW93,AY93,BC93,BG93) -> 0 | H93: =SUM(K93,M93,O93,Q93,S93,U93,W93,Y93,AA93,AC93,AE93,AG93,AI93,AK93,AM93,AO93,AQ93,AS93,AV93,AX93,AZ93,BD93,BH93) -> 0 | I93: =G93-H93 -> 0 | V93: 0 | W93: 0 | X93: 0 | Y93: 0
C94: 2058 | E94: 设计咨询 | F94: 0.06 | G94: =SUM(J94,L94,N94,P94,R94,T94,V94,X94,Z94,AB94,AD94,AF94,AH94,AJ94,AL94,AN94,AP94,AR94,AU94,AW94,AY94,BC94,BG94) -> 3616053.3 | H94: =SUM(K94,M94,O94,Q94,S94,U94,W94,Y94,AA94,AC94,AE94,AG94,AI94,AK94,AM94,AO94,AQ94,AS94,AV94,AX94,AZ94,BD94,BH94) -> 3786782.5 | I94: =G94-H94 -> -170729.16 | L94: =1077061.32+144175.76 -> 1221237.1 | M94: 995856.92 | N94: 221154.96 | P94: 74754.4 | Q94: 705314.59 | R94: =60092.57+81205.45 -> 141298.02 | S94: 60092.57 | T94: 366187.35 | U94: 110522.47 | V94: =484600.63+91089.15 -> 575689.78 | W94: 91089.15 | X94: 59315.74 | Y94: 59315.74 | Z94: 45119.32 | AA94: 45119.32 | AB94: 387259.95 | AD94: 111327.04 | AG94: 1195435 | AJ94: 200000 | AK94: 311327.04 | AL94: 185642.56 | AN94: 27067.09 | AQ94: 212709.65
B95: EPC自建 | C95: 3308 | D95: 灵山文利 | E95: 商品销售 | F95: 0.13 | G95: =SUM(J95,L95,N95,P95,R95,T95,V95,X95,Z95,AB95,AD95,AF95,AH95,AJ95,AL95,AN95,AP95,AR95,AU95,AW95,AY95,BC95,BG95) -> 0 | H95: =SUM(K95,M95,O95,Q95,S95,U95,W95,Y95,AA95,AC95,AE95,AG95,AI95,AK95,AM95,AO95,AQ95,AS95,AV95,AX95,AZ95,BD95,BH95) -> 0 | I95: =G95-H95 -> 0 | V95: 0 | W95: 0 | X95: 0 | Y95: 0
C96: 3308 | E96: 工程施工 | F96: 0.09 | G96: =SUM(J96,L96,N96,P96,R96,T96,V96,X96,Z96,AB96,AD96,AF96,AH96,AJ96,AL96,AN96,AP96,AR96,AU96,AW96,AY96,BC96,BG96) -> 214563.11 | H96: =SUM(K96,M96,O96,Q96,S96,U96,W96,Y96,AA96,AC96,AE96,AG96,AI96,AK96,AM96,AO96,AQ96,AS96,AV96,AX96,AZ96,BD96,BH96) -> 214563.11 | I96: =G96-H96 -> 0 | L96: 214563.11 | M96: 214563.11 | V96: 0 | W96: 0 | X96: 0 | Y96: 0
C97: 3308 | E97: 设计咨询 | F97: 0.06 | G97: =SUM(J97,L97,N97,P97,R97,T97,V97,X97,Z97,AB97,AD97,AF97,AH97,AJ97,AL97,AN97,AP97,AR97,AU97,AW97,AY97,BC97,BG97) -> 10809477 | H97: =SUM(K97,M97,O97,Q97,S97,U97,W97,Y97,AA97,AC97,AE97,AG97,AI97,AK97,AM97,AO97,AQ97,AS97,AV97,AX97,AZ97,BD97,BH97) -> 11105978 | I97: =G97-H97 -> -296501.27 | L97: =3640904.27+199508.76 -> 3840413 | M97: 3640904.3 | N97: 60934.95 | P97: 406510.66 | Q97: 556944.98 | R97: 67604.15 | S97: 67604.15 | T97: 2107833.4 | U97: 124337.79 | V97: =102475.29+1542313.07 -> 1644788.4 | W97: 102475.29 | X97: 66730.21 | Y97: 66730.21 | Z97: 50759.24 | AA97: 50759.24 | AB97: 106984.35 | AC97: 106984.35 | AD97: 179211.56 | AE97: 98834.2 | AG97: 3932319.4 | AH97: 1659585.2 | AI97: 1659585.2 | AK97: 80377.36 | BC97: 618121.66 | BH97: 618121.66
B98: EPC自建 | C98: 2057 | D98: 钦州三期 （枫木山） | E98: 商品销售 | F98: 0.13 | G98: =SUM(J98,L98,N98,P98,R98,T98,V98,X98,Z98,AB98,AD98,AF98,AH98,AJ98,AL98,AN98,AP98,AR98,AU98,AW98,AY98,BC98,BG98) -> 0 | H98: =SUM(K98,M98,O98,Q98,S98,U98,W98,Y98,AA98,AC98,AE98,AG98,AI98,AK98,AM98,AO98,AQ98,AS98,AV98,AX98,AZ98,BD98,BH98) -> 0 | I98: =G98-H98 -> 0 | V98: 0 | W98: 0 | X98: 0 | Y98: 0
C99: 2057 | E99: 工程施工 | F99: 0.09 | G99: =SUM(J99,L99,N99,P99,R99,T99,V99,X99,Z99,AB99,AD99,AF99,AH99,AJ99,AL99,AN99,AP99,AR99,AU99,AW99,AY99,BC99,BG99) -> 0 | H99: =SUM(K99,M99,O99,Q99,S99,U99,W99,Y99,AA99,AC99,AE99,AG99,AI99,AK99,AM99,AO99,AQ99,AS99,AV99,AX99,AZ99,BD99,BH99) -> 0 | I99: =G99-H99 -> 0 | V99: 0 | W99: 0 | X99: 0 | Y99: 0
C100: 2057 | E100: 设计咨询 | F100: 0.06 | G100: =SUM(J100,L100,N100,P100,R100,T100,V100,X100,Z100,AB100,AD100,AF100,AH100,AJ100,AL100,AN100,AP100,AR100,AU100,AW100,AY100,BC100,BG100) -> 1706596.8 | H100: =SUM(K100,M100,O100,Q100,S100,U100,W100,Y100,AA100,AC100,AE100,AG100,AI100,AK100,AM100,AO100,AQ100,AS100,AV100,AX100,AZ100,BD100,BH100) -> 1903931 | I100: =G100-H100 -> -197334.22 | L100: =497018.11+195454.72 -> 692472.83 | M100: 195454.72 | N100: 40623.3 | P100: 37669.57 | Q100: 734975.63 | R100: 45069.43 | S100: 45069.43 | T100: 45222.28 | U100: 82891.85 | V100: =200000+68316.87 -> 268316.87 | W100: 68316.87 | X100: 44486.8 | Y100: 44486.8 | Z100: 33839.49 | AA100: 33839.49 | AB100: 166298.74 | AF100: 277164.57 | AG100: 366298.74 | AK100: 277164.57 | BC100: 55432.92 | BH100: 55432.92
...

Sheet 累计项目税收明细表2017-202302
C1: 注意 | D1: 牟平、绿港历史项目须一、二期合并计算 | G1: =SUBTOTAL(9,G3:G349) -> 1.1897425e+10 | H1: =SUBTOTAL(9,H3:H349) -> 1.1509362e+10 | I1: =SUBTOTAL(9,I3:I349) -> 1.3200528e+09 | J1: =SUBTOTAL(9,J3:J349) -> 1.1896884e+10 | K1: =SUBTOTAL(9,K3:K349) -> 3.7949045e+08 | L1: =SUBTOTAL(9,L3:L349) -> -23479405 | M1: =SUBTOTAL(9,M3:M349) -> 1.5664612e+09 | N1: =SUBTOTAL(9,N3:N349) -> 8.5686222e+08 | ... EU1: =SUBTOTAL(9,EU3:EU349) -> 22112371 | EV1: =SUBTOTAL(9,EV3:EV349,EV351:EV354) -> 8.4086634e+08 | EW1: =SUBTOTAL(9,EW3:EW349,EW351:EW354) -> 5.2084957e+08 | EX1: =SUBTOTAL(9,EX3:EX349,EX351:EX354) -> 90002075 | EY1: =SUBTOTAL(9,EY3:EY349,EY351:EY354) -> 8.4086634e+08 | EZ1: =SUBTOTAL(9,EZ3:EZ349,EZ351:EZ354) -> 1.43 | FA1: =SUBTOTAL(9,FA3:FA349,FA351:FA354) -> 5.9911248e+08 | FB1: =SUBTOTAL(9,FB3:FB349,FB351:FB354) -> 5.2499889e+08 | FC1: =SUBTOTAL(9,FC3:FC349,FC351:FC354) -> 72791645 | ... GX1: =SUBTOTAL(9,GX3:GX349,GX351:GX354) -> -0.63000001
C2: 项目分类 | D2: 项目名称 | E2: 类别 | F2: 税率 | G2: 累计收入 | H2: 累计开票 | I2: 累计销项 | J2: 累计申报收入 | K2: 未开票收入 | L2: 预开票统计 | M2: 17-20年累计收入 | N2: 17-20年累计开票 | O2: 17-20年累计销项 | P2: 202013收入 | Q2: 202101收入 | R2: 202101开票 | S2: 202101销项 | T2: 202101申报收入 | U2: 帐税收入差异 | V2: 202102收入 | W2: 202102开票 | X2: 202102销项 | Y2: 202102申报收入 | Z2: 帐税收入差异 | AA2: 202103收入 | AB2: 202103开票 | AC2: 202103销项 | AD2: 202103申报收入 | AE2: 帐税收入差异 | AF2: 202104收入 | AG2: 202104开票 | AH2: 202104销项 | AI2: 202104申报收入 | AJ2: 帐税收入差异 | AK2: 202105收入 | AL2: 202105开票 | AM2: 202105销项 | AN2: 202105申报收入 | AO2: 帐税收入差异 | AP2: 202106收入 | AQ2: 202106开票 | AR2: 202106销项 | AS2: 202106申报收入 | AT2: 帐税收入差异 | AU2: 202107收入 | AV2: 202107开票 | AW2: 202107销项 | AX2: 202107申报收入 | AY2: 帐税收入差异 | AZ2: 202108收入 | BA2: 202108开票 | BB2: 202108销项 | BC2: 202108申报收入 | BD2: 帐税收入差异 | BE2: 202109收入 | BF2: 202109开票 | BG2: 202109销项 | BH2: 202109申报收入 | BI2: 帐税收入差异 | BJ2: 202110收入 | BK2: 202110开票 | BL2: 202110销项 | BM2: 202110申报收入 | BN2: 帐税收入差异 | BO2: 202111收入 | BP2: 202111开票 | BQ2: 202111销项 | BR2: 202111申报收入 | BS2: 帐税收入差异 | BT2: 202112收入 | BU2: 202112开票 | BV2: 202112销项 | BW2: 202112申报收入 | BX2: 帐税收入差异 | BY2: 202201收入 | BZ2: 202201开票 | CA2: 202201销项 | CB2: 202201申报收入 | CC2: 帐税收入差异 | CD2: 202202收入 | CE2: 202202开票 | CF2: 202202销项 | CG2: 202202申报收入 | CH2: 帐税收入差异 | CI2: 202203收入 | CJ2: 202203开票 | CK2: 202203销项 | CL2: 202203申报收入 | CM2: 帐税收入差异 | CN2: 202204收入 | CO2: 202204开票 | CP2: 202204销项 | CQ2: 202204申报收入 | CR2: 帐税收入差异 | CS2: 202205收入 | CT2: 202205开票 | CU2: 202205销项 | CV2: 202205申报收入 | CW2: 帐税收入差异 | CX2: 202206收入 | CY2: 202206开票 | CZ2: 202206销项 | DA2: 202206申报收入 | DB2: 帐税收入差异 | DC2: 202207收入 | DD2: 202207开票 | DE2: 202207销项 | DF2: 202207申报收入 | DG2: 帐税收入差异 | DH2: 202208收入 | DI2: 202208开票 | DJ2: 202208销项 | DK2: 202208申报收入 | DL2: 帐税收入差异 | DM2: 202209收入 | DN2: 202209开票 | DO2: 202209销项 | DP2: 202209申报收入 | DQ2: 帐税收入差异 | DR2: 202210收入 | DS2: 202210开票 | DT2: 202210销项 | DU2: 202210申报收入 | DV2: 帐税收入差异 | DW2: 202211收入 | DX2: 202211开票 | DY2: 202211销项 | DZ2: 202211申报收入 | EA2: 帐税收入差异 | EB2: 202212收入 | EC2: 202212开票 | ED2: 202212销项 | EE2: 202212申报收入 | EF2: 帐税收入差异 | EG2: 202301收入 | EH2: 202301开票 | EI2: 202301销项 | EJ2: 202301申报收入 | EK2: 帐税收入差异 | EL2: 202302收入 | EM2: 202302开票 | EN2: 202302销项 | EO2: 202302申报收入 | EP2: 帐税收入差异 | EQ2: 202303收入 | ER2: 202303开票 | ES2: 202303销项 | ET2: 202303申报收入 | EU2: 帐税收入差异 | EV2: 202304收入 | EW2: 202304开票 | EX2: 202304销项 | EY2: 202304申报收入 | EZ2: 帐税收入差异 | FA2: 202305收入 | FB2: 202305开票 | FC2: 202305销项 | FD2: 202305申报收入 | FE2: 帐税收入差异 | FF2: 202306收入 | FG2: 202306开票 | FH2: 202306销项 | FI2: 202306申报收入 | FJ2: 帐税收入差异 | FK2: 202307收入 | FL2: 202307开票 | FM2: 202307销项 | FN2: 202307申报收入 | FO2: 帐税收入差异 | FP2: 202308收入 | FQ2: 202308开票 | FR2: 202308销项 | FS2: 202308申报收入 | FT2: 帐税收入差异 | FU2: 202309收入 | FV2: 202309开票 | FW2: 202309销项 | FX2: 202309申报收入 | FY2: 帐税收入差异 | FZ2: 202310收入 | GA2: 202310开票 | GB2: 202310销项 | GC2: 202310申报收入 | GD2: 帐税收入差异 | GE2: 202311收入 | GF2: 202311开票 | GG2: 202311销项 | GH2: 202311申报收入 | GI2: 帐税收入差异 | GJ2: 202312收入 | GK2: 202312开票 | GL2: 202312销项 | GM2: 202312申报收入 | GN2: 帐税收入差异 | GO2: 202401收入 | GP2: 202401开票 | GQ2: 202401销项 | GR2: 202401申报收入 | GS2: 帐税收入差异 | GT2: 202402收入 | GU2: 202402开票 | GV2: 202402销项 | GW2: 202402申报收入 | GX2: 帐税收入差异
B3: 1050 | C3: 内部EPC项目 | D3: 1050（智慧能源） | E3: 商品销售 | F3: 0.16 | G3: =SUM(M3,P3:Q3,V3,AA3,AF3,AK3,AP3,AU3,AZ3,BE3,BJ3,BO3,BT3,BY3,CD3,CI3,CN3,CS3,CX3,DC3,DH3,DM3,DR3,DW3,EB3,EG3,EL3,EQ3,EV3,FA3,FF3,FK3,FP3,FU3,FZ3,GE3,GJ3,GO3,GT3) -> 0 | H3: =SUM(N3,R3,W3,AB3,AG3,AL3,AQ3,AV3,BA3,BF3,BK3,BP3,BU3,BZ3,CE3,CJ3,CO3,CT3,CY3,DD3,DI3,DN3,DS3,DX3,EC3,EH3,EM3,ER3,EW3,FB3,FG3,FL3,FQ3,FV3,GA3,GF3,GK3,GP3,GU3) -> 0 | I3: =SUM(O3,S3,X3,AC3,AH3,AM3,AR3,AW3,BB3,BG3,BL3,BQ3,BV3,CA3,CF3,CK3,CP3,CU3,CZ3,DE3,DJ3,DO3,DT3,DY3,ED3,EI3,EN3,ES3,EX3,FC3,FH3,FM3,FR3,FW3,GB3,GG3,GL3,GQ3,GV3) -> 0 | J3: =I3/F3 -> 0 | K3: =I3/F3-H3 -> 0 | L3: =H3-J3 -> 0 | M3: =SUM(S3,V3:W3,AB3,AG3,AL3,AQ3,AV3,BA3,BF3,BK3,BP3,BU3,BZ3,CE3,CJ3,CO3,CT3,CY3,DD3,DI3,DN3,DS3,DX3,EC3,EH3,EM3,ER3,EW3,FB3) -> 0 | N3: =SUM(T3,X3,AC3,AH3,AM3,AR3,AW3,BB3,BG3,BL3,BQ3,BV3,CA3,CF3,CK3,CP3,CU3,CZ3,DE3,DJ3,DO3,DT3,DY3,ED3,EI3,EN3,ES3,EX3,FC3) -> 0 | O3: =SUM(U3,Y3,AD3,AI3,AN3,AS3,AX3,BC3,BH3,BM3,BR3,BW3,CB3,CG3,CL3,CQ3,CV3,DA3,DF3,DK3,DP3,DU3,DZ3,EE3,EJ3,EO3,ET3,EY3,FD3) -> 0 | P3: =SUM(V3,Y3:Z3,AE3,AJ3,AO3,AT3,AY3,BD3,BI3,BN3,BS3,BX3,CC3,CH3,CM3,CR3,CW3,DB3,DG3,DL3,DQ3,DV3,EA3,EF3,EK3,EP3,EU3,EZ3,FE3) -> 0 | Q3: =SUM(W3,AA3,AF3,AK3,AP3,AU3,AZ3,BE3,BJ3,BO3,BT3,BY3,CD3,CI3,CN3,CS3,CX3,DC3,DH3,DM3,DR3,DW3,EB3,EG3,EL3,EQ3,EV3,FA3,FF3) -> 0 | R3: =SUM(X3,AB3,AG3,AL3,AQ3,AV3,BA3,BF3,BK3,BP3,BU3,BZ3,CE3,CJ3,CO3,CT3,CY3,DD3,DI3,DN3,DS3,DX3,EC3,EH3,EM3,ER3,EW3,FB3,FG3) -> 0 | S3: =SUM(Y3,AB3:AC3,AH3,AM3,AR3,AW3,BB3,BG3,BL3,BQ3,BV3,CA3,CF3,CK3,CP3,CU3,CZ3,DE3,DJ3,DO3,DT3,DY3,ED3,EI3,EN3,ES3,EX3,FC3,FH3) -> 0 | T3: =SUM(Z3,AD3,AI3,AN3,AS3,AX3,BC3,BH3,BM3,BR3,BW3,CB3,CG3,CL3,CQ3,CV3,DA3,DF3,DK3,DP3,DU3,DZ3,EE3,EJ3,EO3,ET3,EY3,FD3,FI3) -> 0 | U3: =SUM(AA3,AE3,AJ3,AO3,AT3,AY3,BD3,BI3,BN3,BS3,BX3,CC3,CH3,CM3,CR3,CW3,DB3,DG3,DL3,DQ3,DV3,EA3,EF3,EK3,EP3,EU3,EZ3,FE3,FJ3) -> 0 | V3: =SUM(AB3,AE3:AF3,AK3,AP3,AU3,AZ3,BE3,BJ3,BO3,BT3,BY3,CD3,CI3,CN3,CS3,CX3,DC3,DH3,DM3,DR3,DW3,EB3,EG3,EL3,EQ3,EV3,FA3,FF3,FK3) -> 0 | W3: =SUM(AC3,AG3,AL3,AQ3,AV3,BA3,BF3,BK3,BP3,BU3,BZ3,CE3,CJ3,CO3,CT3,CY3,DD3,DI3,DN3,DS3,DX3,EC3,EH3,EM3,ER3,EW3,FB3,FG3,FL3) -> 0 | X3: =SUM(AD3,AH3,AM3,AR3,AW3,BB3,BG3,BL3,BQ3,BV3,CA3,CF3,CK3,CP3,CU3,CZ3,DE3,DJ3,DO3,DT3,DY3,ED3,EI3,EN3,ES3,EX3,FC3,FH3,FM3) -> 0 | Y3: =SUM(AE3,AH3:AI3,AN3,AS3,AX3,BC3,BH3,BM3,BR3,BW3,CB3,CG3,CL3,CQ3,CV3,DA3,DF3,DK3,DP3,DU3,DZ3,EE3,EJ3,EO3,ET3,EY3,FD3,FI3,FN3) -> 0 | Z3: =SUM(AF3,AJ3,AO3,AT3,AY3,BD3,BI3,BN3,BS3,BX3,CC3,CH3,CM3,CR3,CW3,DB3,DG3,DL3,DQ3,DV3,EA3,EF3,EK3,EP3,EU3,EZ3,FE3,FJ3,FO3) -> 0 | AA3: =SUM(AG3,AK3,AP3,AU3,AZ3,BE3,BJ3,BO3,BT3,BY3,CD3,CI3,CN3,CS3,CX3,DC3,DH3,DM3,DR3,DW3,EB3,EG3,EL3,EQ3,EV3,FA3,FF3,FK3,FP3) -> 0 | AB3: =SUM(AH3,AK3:AL3,AQ3,AV3,BA3,BF3,BK3,BP3,BU3,BZ3,CE3,CJ3,CO3,CT3,CY3,DD3,DI3,DN3,DS3,DX3,EC3,EH3,EM3,ER3,EW3,FB3,FG3,FL3,FQ3) -> 0 | AC3: =SUM(AI3,AM3,AR3,AW3,BB3,BG3,BL3,BQ3,BV3,CA3,CF3,CK3,CP3,CU3,CZ3,DE3,DJ3,DO3,DT3,DY3,ED3,EI3,EN3,ES3,EX3,FC3,FH3,FM3,FR3) -> 0 | AD3: =SUM(AJ3,AN3,AS3,AX3,BC3,BH3,BM3,BR3,BW3,CB3,CG3,CL3,CQ3,CV3,DA3,DF3,DK3,DP3,DU3,DZ3,EE3,EJ3,EO3,ET3,EY3,FD3,FI3,FN3,FS3) -> 0 | AE3: =SUM(AK3,AN3:AO3,AT3,AY3,BD3,BI3,BN3,BS3,BX3,CC3,CH3,CM3,CR3,CW3,DB3,DG3,DL3,DQ3,DV3,EA3,EF3,EK3,EP3,EU3,EZ3,FE3,FJ3,FO3,FT3) -> 0 | AF3: =SUM(AL3,AP3,AU3,AZ3,BE3,BJ3,BO3,BT3,BY3,CD3,CI3,CN3,CS3,CX3,DC3,DH3,DM3,DR3,DW3,EB3,EG3,EL3,EQ3,EV3,FA3,FF3,FK3,FP3,FU3) -> 0 | AG3: =SUM(AM3,AQ3,AV3,BA3,BF3,BK3,BP3,BU3,BZ3,CE3,CJ3,CO3,CT3,CY3,DD3,DI3,DN3,DS3,DX3,EC3,EH3,EM3,ER3,EW3,FB3,FG3,FL3,FQ3,FV3) -> 0 | AH3: =SUM(AN3,AQ3:AR3,AW3,BB3,BG3,BL3,BQ3,BV3,CA3,CF3,CK3,CP3,CU3,CZ3,DE3,DJ3,DO3,DT3,DY3,ED3,EI3,EN3,ES3,EX3,FC3,FH3,FM3,FR3,FW3) -> 0 | AI3: =SUM(AO3,AS3,AX3,BC3,BH3,BM3,BR3,BW3,CB3,CG3,CL3,CQ3,CV3,DA3,DF3,DK3,DP3,DU3,DZ3,EE3,EJ3,EO3,ET3,EY3,FD3,FI3,FN3,FS3,FX3) -> 0 | AJ3: =SUM(AP3,AT3,AY3,BD3,BI3,BN3,BS3,BX3,CC3,CH3,CM3,CR3,CW3,DB3,DG3,DL3,DQ3,DV3,EA3,EF3,EK3,EP3,EU3,EZ3,FE3,FJ3,FO3,FT3,FY3) -> 0 | AK3: =SUM(AQ3,AT3:AU3,AZ3,BE3,BJ3,BO3,BT3,BY3,CD3,CI3,CN3,CS3,CX3,DC3,DH3,DM3,DR3,DW3,EB3,EG3,EL3,EQ3,EV3,FA3,FF3,FK3,FP3,FU3,FZ3) -> 0 | AL3: =SUM(AR3,AV3,BA3,BF3,BK3,BP3,BU3,BZ3,CE3,CJ3,CO3,CT3,CY3,DD3,DI3,DN3,DS3,DX3,EC3,EH3,EM3,ER3,EW3,FB3,FG3,FL3,FQ3,FV3,GA3) -> 0 | AM3: =SUM(AS3,AW3,BB3,BG3,BL3,BQ3,BV3,CA3,CF3,CK3,CP3,CU3,CZ3,DE3,DJ3,DO3,DT3,DY3,ED3,EI3,EN3,ES3,EX3,FC3,FH3,FM3,FR3,FW3,GB3) -> 0 | AN3: =SUM(AT3,AW3:AX3,BC3,BH3,BM3,BR3,BW3,CB3,CG3,CL3,CQ3,CV3,DA3,DF3,DK3,DP3,DU3,DZ3,EE3,EJ3,EO3,ET3,EY3,FD3,FI3,FN3,FS3,FX3,GC3) -> 0 | AO3: =SUM(AU3,AY3,BD3,BI3,BN3,BS3,BX3,CC3,CH3,CM3,CR3,CW3,DB3,DG3,DL3,DQ3,DV3,EA3,EF3,EK3,EP3,EU3,EZ3,FE3,FJ3,FO3,FT3,FY3,GD3) -> 0 | AP3: =SUM(AV3,AZ3,BE3,BJ3,BO3,BT3,BY3,CD3,CI3,CN3,CS3,CX3,DC3,DH3,DM3,DR3,DW3,EB3,EG3,EL3,EQ3,EV3,FA3,FF3,FK3,FP3,FU3,FZ3,GE3) -> 0 | AQ3: =SUM(AW3,AZ3:BA3,BF3,BK3,BP3,BU3,BZ3,CE3,CJ3,CO3,CT3,CY3,DD3,DI3,DN3,DS3,DX3,EC3,EH3,EM3,ER3,EW3,FB3,FG3,FL3,FQ3,FV3,GA3,GF3) -> 0 | AR3: =SUM(AX3,BB3,BG3,BL3,BQ3,BV3,CA3,CF3,CK3,CP3,CU3,CZ3,DE3,DJ3,DO3,DT3,DY3,ED3,EI3,EN3,ES3,EX3,FC3,FH3,FM3,FR3,FW3,GB3,GG3) -> 0 | AS3: =SUM(AY3,BC3,BH3,BM3,BR3,BW3,CB3,CG3,CL3,CQ3,CV3,DA3,DF3,DK3,DP3,DU3,DZ3,EE3,EJ3,EO3,ET3,EY3,FD3,FI3,FN3,FS3,FX3,GC3,GH3) -> 0 | AT3: =SUM(AZ3,BC3:BD3,BI3,BN3,BS3,BX3,CC3,CH3,CM3,CR3,CW3,DB3,DG3,DL3,DQ3,DV3,EA3,EF3,EK3,EP3,EU3,EZ3,FE3,FJ3,FO3,FT3,FY3,GD3,GI3) -> 0 | AU3: =SUM(BA3,BE3,BJ3,BO3,BT3,BY3,CD3,CI3,CN3,CS3,CX3,DC3,DH3,DM3,DR3,DW3,EB3,EG3,EL3,EQ3,EV3,FA3,FF3,FK3,FP3,FU3,FZ3,GE3,GJ3) -> 0 | AV3: =SUM(BB3,BF3,BK3,BP3,BU3,BZ3,CE3,CJ3,CO3,CT3,CY3,DD3,DI3,DN3,DS3,DX3,EC3,EH3,EM3,ER3,EW3,FB3,FG3,FL3,FQ3,FV3,GA3,GF3,GK3) -> 0 | AW3: =SUM(BC3,BF3:BG3,BL3,BQ3,BV3,CA3,CF3,CK3,CP3,CU3,CZ3,DE3,DJ3,DO3,DT3,DY3,ED3,EI3,EN3,ES3,EX3,FC3,FH3,FM3,FR3,FW3,GB3,GG3,GL3) -> 0 | AX3: =SUM(BD3,BH3,BM3,BR3,BW3,CB3,CG3,CL3,CQ3,CV3,DA3,DF3,DK3,DP3,DU3,DZ3,EE3,EJ3,EO3,ET3,EY3,FD3,FI3,FN3,FS3,FX3,GC3,GH3,GM3) -> 0 | AY3: =SUM(BE3,BI3,BN3,BS3,BX3,CC3,CH3,CM3,CR3,CW3,DB3,DG3,DL3,DQ3,DV3,EA3,EF3,EK3,EP3,EU3,EZ3,FE3,FJ3,FO3,FT3,FY3,GD3,GI3,GN3) -> 0 | AZ3: =SUM(BF3,BI3:BJ3,BO3,BT3,BY3,CD3,CI3,CN3,CS3,CX3,DC3,DH3,DM3,DR3,DW3,EB3,EG3,EL3,EQ3,EV3,FA3,FF3,FK3,FP3,FU3,FZ3,GE3,GJ3,GO3) -> 0 | BA3: =SUM(BG3,BK3,BP3,BU3,BZ3,CE3,CJ3,CO3,CT3,CY3,DD3,DI3,DN3,DS3,DX3,EC3,EH3,EM3,ER3,EW3,FB3,FG3,FL3,FQ3,FV3,GA3,GF3,GK3,GP3) -> 0 | BB3: =SUM(BH3,BL3,BQ3,BV3,CA3,CF3,CK3,CP3,CU3,CZ3,DE3,DJ3,DO3,DT3,DY3,ED3,EI3,EN3,ES3,EX3,FC3,FH3,FM3,FR3,FW3,GB3,GG3,GL3,GQ3) -> 0 | BC3: =SUM(BI3,BL3:BM3,BR3,BW3,CB3,CG3,CL3,CQ3,CV3,DA3,DF3,DK3,DP3,DU3,DZ3,EE3,EJ3,EO3,ET3,EY3,FD3,FI3,FN3,FS3,FX3,GC3,GH3,GM3,GR3) -> 0 | BD3: =SUM(BJ3,BN3,BS3,BX3,CC3,CH3,CM3,CR3,CW3,DB3,DG3,DL3,DQ3,DV3,EA3,EF3,EK3,EP3,EU3,EZ3,FE3,FJ3,FO3,FT3,FY3,GD3,GI3,GN3,GS3) -> 0 | BE3: =SUM(BK3,BO3,BT3,BY3,CD3,CI3,CN3,CS3,CX3,DC3,DH3,DM3,DR3,DW3,EB3,EG3,EL3,EQ3,EV3,FA3,FF3,FK3,FP3,FU3,FZ3,GE3,GJ3,GO3,GT3) -> 0 | BF3: =SUM(BL3,BO3:BP3,BU3,BZ3,CE3,CJ3,CO3,CT3,CY3,DD3,DI3,DN3,DS3,DX3,EC3,EH3,EM3,ER3,EW3,FB3,FG3,FL3,FQ3,FV3,GA3,GF3,GK3,GP3,GU3) -> 0 | BG3: =SUM(BM3,BQ3,BV3,CA3,CF3,CK3,CP3,CU3,CZ3,DE3,DJ3,DO3,DT3,DY3,ED3,EI3,EN3,ES3,EX3,FC3,FH3,FM3,FR3,FW3,GB3,GG3,GL3,GQ3,GV3) -> 0 | BH3: =SUM(BN3,BR3,BW3,CB3,CG3,CL3,CQ3,CV3,DA3,DF3,DK3,DP3,DU3,DZ3,EE3,EJ3,EO3,ET3,EY3,FD3,FI3,FN3,FS3,FX3,GC3,GH3,GM3,GR3,GW3) -> 0 | BI3: =SUM(BO3,BR3:BS3,BX3,CC3,CH3,CM3,CR3,CW3,DB3,DG3,DL3,DQ3,DV3,EA3,EF3,EK3,EP3,EU3,EZ3,FE3,FJ3,FO3,FT3,FY3,GD3,GI3,GN3,GS3,GX3) -> 0 | BJ3: =SUM(BP3,BT3,BY3,CD3,CI3,CN3,CS3,CX3,DC3,DH3,DM3,DR3,DW3,EB3,EG3,EL3,EQ3,EV3,FA3,FF3,FK3,FP3,FU3,FZ3,GE3,GJ3,GO3,GT3,GY3) -> 0 | BK3: =SUM(BQ3,BU3,BZ3,CE3,CJ3,CO3,CT3,CY3,DD3,DI3,DN3,DS3,DX3,EC3,EH3,EM3,ER3,EW3,FB3,FG3,FL3,FQ3,FV3,GA3,GF3,GK3,GP3,GU3,GZ3) -> 0 | BL3: =SUM(BR3,BU3:BV3,CA3,CF3,CK3,CP3,CU3,CZ3,DE3,DJ3,DO3,DT3,DY3,ED3,EI3,EN3,ES3,EX3,FC3,FH3,FM3,FR3,FW3,GB3,GG3,GL3,GQ3,GV3,HA3) -> 0 | BM3: =SUM(BS3,BW3,CB3,CG3,CL3,CQ3,CV3,DA3,DF3,DK3,DP3,DU3,DZ3,EE3,EJ3,EO3,ET3,EY3,FD3,FI3,FN3,FS3,FX3,GC3,GH3,GM3,GR3,GW3,HB3) -> 0 | BN3: =SUM(BT3,BX3,CC3,CH3,CM3,CR3,CW3,DB3,DG3,DL3,DQ3,DV3,EA3,EF3,EK3,EP3,EU3,EZ3,FE3,FJ3,FO3,FT3,FY3,GD3,GI3,GN3,GS3,GX3,HC3) -> 0 | BO3: =SUM(BU3,BX3:BY3,CD3,CI3,CN3,CS3,CX3,DC3,DH3,DM3,DR3,DW3,EB3,EG3,EL3,EQ3,EV3,FA3,FF3,FK3,FP3,FU3,FZ3,GE3,GJ3,GO3,GT3,GY3,HD3) -> 0 | BP3: =SUM(BV3,BZ3,CE3,CJ3,CO3,CT3,CY3,DD3,DI3,DN3,DS3,DX3,EC3,EH3,EM3,ER3,EW3,FB3,FG3,FL3,FQ3,FV3,GA3,GF3,GK3,GP3,GU3,GZ3,HE3) -> 0 | BQ3: =SUM(BW3,CA3,CF3,CK3,CP3,CU3,CZ3,DE3,DJ3,DO3,DT3,DY3,ED3,EI3,EN3,ES3,EX3,FC3,FH3,FM3,FR3,FW3,GB3,GG3,GL3,GQ3,GV3,HA3,HF3) -> 0 | BR3: =SUM(BX3,CA3:CB3,CG3,CL3,CQ3,CV3,DA3,DF3,DK3,DP3,DU3,DZ3,EE3,EJ3,EO3,ET3,EY3,FD3,FI3,FN3,FS3,FX3,GC3,GH3,GM3,GR3,GW3,HB3,HG3) -> 0 | BS3: =SUM(BY3,CC3,CH3,CM3,CR3,CW3,DB3,DG3,DL3,DQ3,DV3,EA3,EF3,EK3,EP3,EU3,EZ3,FE3,FJ3,FO3,FT3,FY3,GD3,GI3,GN3,GS3,GX3,HC3,HH3) -> 0 | BT3: =SUM(BZ3,CD3,CI3,CN3,CS3,CX3,DC3,DH3,DM3,DR3,DW3,EB3,EG3,EL3,EQ3,EV3,FA3,FF3,FK3,FP3,FU3,FZ3,GE3,GJ3,GO3,GT3,GY3,HD3,HI3) -> 0 | BU3: =SUM(CA3,CD3:CE3,CJ3,CO3,CT3,CY3,DD3,DI3,DN3,DS3,DX3,EC3,EH3,EM3,ER3,EW3,FB3,FG3,FL3,FQ3,FV3,GA3,GF3,GK3,GP3,GU3,GZ3,HE3,HJ3) -> 0 | BV3: =SUM(CB3,CF3,CK3,CP3,CU3,CZ3,DE3,DJ3,DO3,DT3,DY3,ED3,EI3,EN3,ES3,EX3,FC3,FH3,FM3,FR3,FW3,GB3,GG3,GL3,GQ3,GV3,HA3,HF3,HK3) -> 0 | BW3: =SUM(CC3,CG3,CL3,CQ3,CV3,DA3,DF3,DK3,DP3,DU3,DZ3,EE3,EJ3,EO3,ET3,EY3,FD3,FI3,FN3,FS3,FX3,GC3,GH3,GM3,GR3,GW3,HB3,HG3,HL3) -> 0 | BX3: =SUM(CD3,CG3:CH3,CM3,CR3,CW3,DB3,DG3,DL3,DQ3,DV3,EA3,EF3,EK3,EP3,EU3,EZ3,FE3,FJ3,FO3,FT3,FY3,GD3,GI3,GN3,GS3,GX3,HC3,HH3,HM3) -> 0 | BY3: =SUM(CE3,CI3,CN3,CS3,CX3,DC3,DH3,DM3,DR3,DW3,EB3,EG3,EL3,EQ3,EV3,FA3,FF3,FK3,FP3,FU3,FZ3,GE3,GJ3,GO3,GT3,GY3,HD3,HI3,HN3) -> 0 | BZ3: =SUM(CF3,CJ3,CO3,CT3,CY3,DD3,DI3,DN3,DS3,DX3,EC3,EH3,EM3,ER3,EW3,FB3,FG3,FL3,FQ3,FV3,GA3,GF3,GK3,GP3,GU3,GZ3,HE3,HJ3,HO3) -> 0 | CA3: =SUM(CG3,CJ3:CK3,CP3,CU3,CZ3,DE3,DJ3,DO3,DT3,DY3,ED3,EI3,EN3,ES3,EX3,FC3,FH3,FM3,FR3,FW3,GB3,GG3,GL3,GQ3,GV3,HA3,HF3,HK3,HP3) -> 0 | CB3: =SUM(CH3,CL3,CQ3,CV3,DA3,DF3,DK3,DP3,DU3,DZ3,EE3,EJ3,EO3,ET3,EY3,FD3,FI3,FN3,FS3,FX3,GC3,GH3,GM3,GR3,GW3,HB3,HG3,HL3,HQ3) -> 0 | CC3: =SUM(CI3,CM3,CR3,CW3,DB3,DG3,DL3,DQ3,DV3,EA3,EF3,EK3,EP3,EU3,EZ3,FE3,FJ3,FO3,FT3,FY3,GD3,GI3,GN3,GS3,GX3,HC3,HH3,HM3,HR3) -> 0 | CD3: =SUM(CJ3,CM3:CN3,CS3,CX3,DC3,DH3,DM3,DR3,DW3,EB3,EG3,EL3,EQ3,EV3,FA3,FF3,FK3,FP3,FU3,FZ3,GE3,GJ3,GO3,GT3,GY3,HD3,HI3,HN3,HS3) -> 0 | CE3: =SUM(CK3,CO3,CT3,CY3,DD3,DI3,DN3,DS3,DX3,EC3,EH3,EM3,ER3,EW3,FB3,FG3,FL3,FQ3,FV3,GA3,GF3,GK3,GP3,GU3,GZ3,HE3,HJ3,HO3,HT3) -> 0 | CF3: =SUM(CL3,CP3,CU3,CZ3,DE3,DJ3,DO3,DT3,DY3,ED3,EI3,EN3,ES3,EX3,FC3,FH3,FM3,FR3,FW3,GB3,GG3,GL3,GQ3,GV3,HA3,HF3,HK3,HP3,HU3) -> 0 | CG3: =SUM(CM3,CP3:CQ3,CV3,DA3,DF3,DK3,DP3,DU3,DZ3,EE3,EJ3,EO3,ET3,EY3,FD3,FI3,FN3,FS3,FX3,GC3,GH3,GM3,GR3,GW3,HB3,HG3,HL3,HQ3,HV3) -> 0 | CH3: =SUM(CN3,CR3,CW3,DB3,DG3,DL3,DQ3,DV3,EA3,EF3,EK3,EP3,EU3,EZ3,FE3,FJ3,FO3,FT3,FY3,GD3,GI3,GN3,GS3,GX3,HC3,HH3,HM3,HR3,HW3) -> 0 | CI3: =SUM(CO3,CS3,CX3,DC3,DH3,DM3,DR3,DW3,EB3,EG3,EL3,EQ3,EV3,FA3,FF3,FK3,FP3,FU3,FZ3,GE3,GJ3,GO3,GT3,GY3,HD3,HI3,HN3,HS3,HX3) -> 0 | CJ3: =SUM(CP3,CS3:CT3,CY3,DD3,DI3,DN3,DS3,DX3,EC3,EH3,EM3,ER3,EW3,FB3,FG3,FL3,FQ3,FV3,GA3,GF3,GK3,GP3,GU3,GZ3,HE3,HJ3,HO3,HT3,HY3) -> 0 | CK3: =SUM(CQ3,CU3,CZ3,DE3,DJ3,DO3,DT3,DY3,ED3,EI3,EN3,ES3,EX3,FC3,FH3,FM3,FR3,FW3,GB3,GG3,GL3,GQ3,GV3,HA3,HF3,HK3,HP3,HU3,HZ3) -> 0 | CL3: =SUM(CR3,CV3,DA3,DF3,DK3,DP3,DU3,DZ3,EE3,EJ3,EO3,ET3,EY3,FD3,FI3,FN3,FS3,FX3,GC3,GH3,GM3,GR3,GW3,HB3,HG3,HL3,HQ3,HV3,IA3) -> 0 | CM3: =SUM(CS3,CV3:CW3,DB3,DG3,DL3,DQ3,DV3,EA3,EF3,EK3,EP3,EU3,EZ3,FE3,FJ3,FO3,FT3,FY3,GD3,GI3,GN3,GS3,GX3,HC3,HH3,HM3,HR3,HW3,IB3) -> 0 | CN3: =SUM(CT3,CX3,DC3,DH3,DM3,DR3,DW3,EB3,EG3,EL3,EQ3,EV3,FA3,FF3,FK3,FP3,FU3,FZ3,GE3,GJ3,GO3,GT3,GY3,HD3,HI3,HN3,HS3,HX3,IC3) -> 0 | CO3: =SUM(CU3,CY3,DD3,DI3,DN3,DS3,DX3,EC3,EH3,EM3,ER3,EW3,FB3,FG3,FL3,FQ3,FV3,GA3,GF3,GK3,GP3,GU3,GZ3,HE3,HJ3,HO3,HT3,HY3,ID3) -> 0 | CP3: =SUM(CV3,CY3:CZ3,DE3,DJ3,DO3,DT3,DY3,ED3,EI3,EN3,ES3,EX3,FC3,FH3,FM3,FR3,FW3,GB3,GG3,GL3,GQ3,GV3,HA3,HF3,HK3,HP3,HU3,HZ3,IE3) -> 0 | CQ3: =SUM(CW3,DA3,DF3,DK3,DP3,DU3,DZ3,EE3,EJ3,EO3,ET3,EY3,FD3,FI3,FN3,FS3,FX3,GC3,GH3,GM3,GR3,GW3,HB3,HG3,HL3,HQ3,HV3,IA3,IF3) -> 0 | CR3: =SUM(CX3,DB3,DG3,DL3,DQ3,DV3,EA3,EF3,EK3,EP3,EU3,EZ3,FE3,FJ3,FO3,FT3,FY3,GD3,GI3,GN3,GS3,GX3,HC3,HH3,HM3,HR3,HW3,IB3,IG3) -> 0 | CS3: =SUM(CY3,DB3:DC3,DH3,DM3,DR3,DW3,EB3,EG3,EL3,EQ3,EV3,FA3,FF3,FK3,FP3,FU3,FZ3,GE3,GJ3,GO3,GT3,GY3,HD3,HI3,HN3,HS3,HX3,IC3,IH3) -> 0 | CT3: =SUM(CZ3,DD3,DI3,DN3,DS3,DX3,EC3,EH3,EM3,ER3,EW3,FB3,FG3,FL3,FQ3,FV3,GA3,GF3,GK3,GP3,GU3,GZ3,HE3,HJ3,HO3,HT3,HY3,ID3,II3) -> 0 | CU3: =SUM(DA3,DE3,DJ3,DO3,DT3,DY3,ED3,EI3,EN3,ES3,EX3,FC3,FH3,FM3,FR3,FW3,GB3,GG3,GL3,GQ3,GV3,HA3,HF3,HK3,HP3,HU3,HZ3,IE3,IJ3) -> 0 | CV3: =SUM(DB3,DE3:DF3,DK3,DP3,DU3,DZ3,EE3,EJ3,EO3,ET3,EY3,FD3,FI3,FN3,FS3,FX3,GC3,GH3,GM3,GR3,GW3,HB3,HG3,HL3,HQ3,HV3,IA3,IF3,IK3) -> 0 | CW3: =SUM(DC3,DG3,DL3,DQ3,DV3,EA3,EF3,EK3,EP3,EU3,EZ3,FE3,FJ3,FO3,FT3,FY3,GD3,GI3,GN3,GS3,GX3,HC3,HH3,HM3,HR3,HW3,IB3,IG3,IL3) -> 0 | CX3: =SUM(DD3,DH3,DM3,DR3,DW3,EB3,EG3,EL3,EQ3,EV3,FA3,FF3,FK3,FP3,FU3,FZ3,GE3,GJ3,GO3,GT3,GY3,HD3,HI3,HN3,HS3,HX3,IC3,IH3,IM3) -> 0 | CY3: =SUM(DE3,DH3:DI3,DN3,DS3,DX3,EC3,EH3,EM3,ER3,EW3,FB3,FG3,FL3,FQ3,FV3,GA3,GF3,GK3,GP3,GU3,GZ3,HE3,HJ3,HO3,HT3,HY3,ID3,II3,IN3) -> 0 | CZ3: =SUM(DF3,DJ3,DO3,DT3,DY3,ED3,EI3,EN3,ES3,EX3,FC3,FH3,FM3,FR3,FW3,GB3,GG3,GL3,GQ3,GV3,HA3,HF3,HK3,HP3,HU3,HZ3,IE3,IJ3,IO3) -> 0 | DA3: =SUM(DG3,DK3,DP3,DU3,DZ3,EE3,EJ3,EO3,ET3,EY3,FD3,FI3,FN3,FS3,FX3,GC3,GH3,GM3,GR3,GW3,HB3,HG3,HL3,HQ3,HV3,IA3,IF3,IK3,IP3) -> 0 | DB3: =SUM(DH3,DK3:DL3,DQ3,DV3,EA3,EF3,EK3,EP3,EU3,EZ3,FE3,FJ3,FO3,FT3,FY3,GD3,GI3,GN3,GS3,GX3,HC3,HH3,HM3,HR3,HW3,IB3,IG3,IL3,IQ3) -> 0 | DC3: =SUM(DI3,DM3,DR3,DW3,EB3,EG3,EL3,EQ3,EV3,FA3,FF3,FK3,FP3,FU3,FZ3,GE3,GJ3,GO3,GT3,GY3,HD3,HI3,HN3,HS3,HX3,IC3,IH3,IM3,IR3) -> 0 | DF3: =DE3/F3 -> 0 | DG3: =DC3-DF3 -> 0 | DK3: =DJ3/F3 -> 0 | DL3: =DK3-DH3 -> 0 | DP3: =DO3/F3 -> 0 | DQ3: =DP3-DM3 -> 0 | DU3: =DT3/F3 -> 0 | DV3: =DU3-DR3 -> 0 | DZ3: =ROUND(DY3/F3,2) -> 0 | EA3: =ROUND(DZ3-DW3,2) -> 0 | EF3: =EE3-EB3 -> 0 | EJ3: =ROUND(EI3/F3,2) -> 0 | EK3: =ROUND(EJ3-EG3,2) -> 0 | EO3: =ROUND(EN3/F3,2) -> 0 | EP3: =ROUND(EO3-EL3,2) -> 0 | ET3: =ROUND(ES3/F3,2) -> 0 | EU3: =ROUND(ET3-EQ3,2) -> 0 | EY3: =ROUND(EX3/F3,2) -> 0 | EZ3: =ROUND(EY3-EV3,2) -> 0 | FD3: =ROUND(FC3/F3,2) -> 0 | FE3: =ROUND(FD3-FA3,2) -> 0 | FI3: =FH3/F3 -> 0 | FJ3: =ROUND(FI3-FF3,2) -> 0 | FN3: =ROUND(FM3/F3,2) -> 0 | FO3: =ROUND(FN3-FK3,2) -> 0 | FS3: =ROUND(FR3/F3,2) -> 0 | FT3: =FS3-FP3 -> 0 | FX3: =ROUND(FW3/F3,2) -> 0 | FY3: =FX3-FU3 -> 0 | GC3: =ROUND(GB3/F3,2) -> 0 | GD3: =GC3-FZ3 -> 0 | GH3: =GG3/F3 -> 0 | GI3: =GH3-GE3 -> 0 | GM3: =GL3/F3 -> 0 | GN3: =GM3-GJ3 -> 0 | GR3: =GQ3/F3 -> 0 | GS3: =GR3-GO3 -> 0 | GW3: =ROUND(GV3/F3,2) -> 0 | GX3: =GW3-GT3 -> 0
B4: 1050 | F4: 0.13 | G4: =SUM(M4,P4:Q4,V4,AA4,AF4,AK4,AP4,AU4,AZ4,BE4,BJ4,BO4,BT4,BY4,CD4,CI4,CN4,CS4,CX4,DC4,DH4,DM4,DR4,DW4,EB4,EG4,EL4,EQ4,EV4,FA4,FF4,FK4,FP4,FU4,FZ4,GE4,GJ4,GO4,GT4) -> 3497388.1 | H4: =SUM(N4,R4,W4,AB4,AG4,AL4,AQ4,AV4,BA4,BF4,BK4,BP4,BU4,BZ4,CE4,CJ4,CO4,CT4,CY4,DD4,DI4,DN4,DS4,DX4,EC4,EH4,EM4,ER4,EW4,FB4,FG4,FL4,FQ4,FV4,GA4,GF4,GK4,GP4,GU4) -> 0 | I4: =SUM(O4,S4,X4,AC4,AH4,AM4,AR4,AW4,BB4,BG4,BL4,BQ4,BV4,CA4,CF4,CK4,CP4,CU4,CZ4,DE4,DJ4,DO4,DT4,DY4,ED4,EI4,EN4,ES4,EX4,FC4,FH4,FM4,FR4,FW4,GB4,GG4,GL4,GQ4,GV4) -> 454660.46 | J4: =I4/F4 -> 3497388.1 | K4: =I4/F4-H4 -> 3497388.1 | L4: =H4-J4 -> -3497388.1 | M4: 3497388.1 | N4: 0 | O4: 454660.46 | T4: 0 | U4: =T4-Q4 -> 0 | Z4: =Y4-V4 -> 0 | AD4: =AC4/F4 -> 0 | AE4: =AD4-AA4 -> 0 | AI4: =AH4/F4 -> 0 | AJ4: =AI4-AF4 -> 0 | AN4: =AM4/F4 -> 0 | AO4: =AN4-AK4 -> 0 | AS4: =AR4/F4 -> 0 | AT4: =AS4-AP4 -> 0 | AX4: =AW4/F4 -> 0 | AY4: =AX4-AU4 -> 0 | BC4: =BB4/F4 -> 0 | BH4: =BG4/F4 -> 0 | BI4: =BH4-BE4 -> 0 | BM4: =BL4/F4 -> 0 | BN4: =BM4-BJ4 -> 0 | BR4: =BQ4/F4 -> 0 | BS4: =BR4-BO4 -> 0 | BX4: =BW4-BT4 -> 0 | CB4: =CA4/F4 -> 0 | CC4: =CB4-BY4 -> 0 | CG4: =CF4/F4 -> 0 | CH4: =CG4-CD4 -> 0 | CL4: =CK4/F4 -> 0 | CM4: =CL4-CI4 -> 0 | CR4: =ROUND(CQ4-CN4,2) -> 0 | CW4: =CV4-CS4 -> 0 | DA4: =ROUND(CZ4/F4,2) -> 0 | DB4: =ROUND(DA4-CX4,2) -> 0 | DF4: =DE4/F4 -> 0 | DG4: =DC4-DF4 -> 0 | DK4: =DJ4/F4 -> 0 | DL4: =DK4-DH4 -> 0 | DP4: =DO4/F4 -> 0 | DQ4: =DP4-DM4 -> 0 | DU4: =DT4/F4 -> 0 | DV4: =DU4-DR4 -> 0 | DZ4: =ROUND(DY4/F4,2) -> 0 | EA4: =ROUND(DZ4-DW4,2) -> 0 | EF4: =EE4-EB4 -> 0 | EJ4: =ROUND(EI4/F4,2) -> 0 | EK4: =ROUND(EJ4-EG4,2) -> 0 | EO4: =ROUND(EN4/F4,2) -> 0 | EP4: =ROUND(EO4-EL4,2) -> 0 | ET4: =ROUND(ES4/F4,2) -> 0 | EU4: =ROUND(ET4-EQ4,2) -> 0 | EY4: =ROUND(EX4/F4,2) -> 0 | EZ4: =ROUND(EY4-EV4,2) -> 0 | FD4: =ROUND(FC4/F4,2) -> 0 | FE4: =ROUND(FD4-FA4,2) -> 0 | FI4: =FH4/F4 -> 0 | FJ4: =ROUND(FI4-FF4,2) -> 0 | FN4: =ROUND(FM4/F4,2) -> 0 | FO4: =ROUND(FN4-FK4,2) -> 0 | FS4: =ROUND(FR4/F4,2) -> 0 | FT4: =FS4-FP4 -> 0 | FX4: =ROUND(FW4/F4,2) -> 0 | FY4: =FX4-FU4 -> 0 | GC4: =ROUND(GB4/F4,2) -> 0 | GD4: =GC4-FZ4 -> 0 | GH4: =GG4/F4 -> 0 | GI4: =GH4-GE4 -> 0 | GM4: =GL4/F4 -> 0 | GN4: =GM4-GJ4 -> 0 | GR4: =GQ4/F4 -> 0 | GS4: =GR4-GO4 -> 0 | GW4: =ROUND(GV4/F4,2) -> 0 | GX4: =GW4-GT4 -> 0
B5: 1050 | E5: 工程施工 | F5: 0.1 | G5: =SUM(M5,P5:Q5,V5,AA5,AF5,AK5,AP5,AU5,AZ5,BE5,BJ5,BO5,BT5,BY5,CD5,CI5,CN5,CS5,CX5,DC5,DH5,DM5,DR5,DW5,EB5,EG5,EL5,EQ5,EV5,FA5,FF5,FK5,FP5,FU5,FZ5,GE5,GJ5,GO5,GT5) -> 16159346 | H5: =SUM(N5,R5,W5,AB5,AG5,AL5,AQ5,AV5,BA5,BF5,BK5,BP5,BU5,BZ5,CE5,CJ5,CO5,CT5,CY5,DD5,DI5,DN5,DS5,DX5,EC5,EH5,EM5,ER5,EW5,FB5,FG5,FL5,FQ5,FV5,GA5,GF5,GK5,GP5,GU5) -> 16159346 | I5: =SUM(O5,S5,X5,AC5,AH5,AM5,AR5,AW5,BB5,BG5,BL5,BQ5,BV5,CA5,CF5,CK5,CP5,CU5,CZ5,DE5,DJ5,DO5,DT5,DY5,ED5,EI5,EN5,ES5,EX5,FC5,FH5,FM5,FR5,FW5,GB5,GG5,GL5,GQ5,GV5) -> 1615934.6 | J5: =I5/F5 -> 16159346 | K5: =I5/F5-H5 -> -0.050000001 | L5: =H5-J5 -> 0.050000001 | M5: 16159346 | N5: 16159346 | O5: 1615934.6 | T5: 0 | U5: =T5-Q5 -> 0 | Z5: =Y5-V5 -> 0 | AD5: =AC5/F5 -> 0 | AE5: =AD5-AA5 -> 0 | AI5: =AH5/F5 -> 0 | AJ5: =AI5-AF5 -> 0 | AN5: =AM5/F5 -> 0 | AO5: =AN5-AK5 -> 0 | AS5: =AR5/F5 -> 0 | AT5: =AS5-AP5 -> 0 | AX5: =AW5/F5 -> 0 | AY5: =AX5-AU5 -> 0 | BC5: =BB5/F5 -> 0 | BH5: =BG5/F5 -> 0 | BI5: =BH5-BE5 -> 0 | BM5: =BL5/F5 -> 0 | BN5: =BM5-BJ5 -> 0 | BR5: =BQ5/F5 -> 0 | BS5: =BR5-BO5 -> 0 | BX5: =BW5-BT5 -> 0 | CB5: =CA5/F5 -> 0 | CC5: =CB5-BY5 -> 0 | CG5: =CF5/F5 -> 0 | CH5: =CG5-CD5 -> 0 | CL5: =CK5/F5 -> 0 | CM5: =CL5-CI5 -> 0 | CR5: =ROUND(CQ5-CN5,2) -> 0 | CW5: =CV5-CS5 -> 0 | DA5: =ROUND(CZ5/F5,2) -> 0 | DB5: =ROUND(DA5-CX5,2) -> 0 | DF5: =DE5/F5 -> 0 | DG5: =DC5-DF5 -> 0 | DK5: =DJ5/F5 -> 0 | DL5: =DK5-DH5 -> 0 | DP5: =DO5/F5 -> 0 | DQ5: =DP5-DM5 -> 0 | DU5: =DT5/F5 -> 0 | DV5: =DU5-DR5 -> 0 | DZ5: =ROUND(DY5/F5,2) -> 0 | EA5: =ROUND(DZ5-DW5,2) -> 0 | EF5: =EE5-EB5 -> 0 | EJ5: =ROUND(EI5/F5,2) -> 0 | EK5: =ROUND(EJ5-EG5,2) -> 0 | EO5: =ROUND(EN5/F5,2) -> 0 | EP5: =ROUND(EO5-EL5,2) -> 0 | ET5: =ROUND(ES5/F5,2) -> 0 | EU5: =ROUND(ET5-EQ5,2) -> 0 | EY5: =ROUND(EX5/F5,2) -> 0 | EZ5: =ROUND(EY5-EV5,2) -> 0 | FD5: =ROUND(FC5/F5,2) -> 0 | FE5: =ROUND(FD5-FA5,2) -> 0 | FI5: =FH5/F5 -> 0 | FJ5: =ROUND(FI5-FF5,2) -> 0 | FN5: =ROUND(FM5/F5,2) -> 0 | FO5: =ROUND(FN5-FK5,2) -> 0 | FS5: =ROUND(FR5/F5,2) -> 0 | FT5: =FS5-FP5 -> 0 | FX5: =ROUND(FW5/F5,2) -> 0 | FY5: =FX5-FU5 -> 0 | GC5: =ROUND(GB5/F5,2) -> 0 | GD5: =GC5-FZ5 -> 0 | GH5: =GG5/F5 -> 0 | GI5: =GH5-GE5 -> 0 | GM5: =GL5/F5 -> 0 | GN5: =GM5-GJ5 -> 0 | GR5: =GQ5/F5 -> 0 | GS5: =GR5-GO5 -> 0 | GW5: =ROUND(GV5/F5,2) -> 0 | GX5: =GW5-GT5 -> 0
B6: 1050 | F6: 0.09 | G6: =SUM(M6,P6:Q6,V6,AA6,AF6,AK6,AP6,AU6,AZ6,BE6,BJ6,BO6,BT6,BY6,CD6,CI6,CN6,CS6,CX6,DC6,DH6,DM6,DR6,DW6,EB6,EG6,EL6,EQ6,EV6,FA6,FF6,FK6,FP6,FU6,FZ6,GE6,GJ6,GO6,GT6) -> 5805849.7 | H6: =SUM(N6,R6,W6,AB6,AG6,AL6,AQ6,AV6,BA6,BF6,BK6,BP6,BU6,BZ6,CE6,CJ6,CO6,CT6,CY6,DD6,DI6,DN6,DS6,DX6,EC6,EH6,EM6,ER6,EW6,FB6,FG6,FL6,FQ6,FV6,GA6,GF6,GK6,GP6,GU6) -> 0 | I6: =SUM(O6,S6,X6,AC6,AH6,AM6,AR6,AW6,BB6,BG6,BL6,BQ6,BV6,CA6,CF6,CK6,CP6,CU6,CZ6,DE6,DJ6,DO6,DT6,DY6,ED6,EI6,EN6,ES6,EX6,FC6,FH6,FM6,FR6,FW6,GB6,GG6,GL6,GQ6,GV6) -> 522526.47 | J6: =I6/F6 -> 5805849.7 | K6: =I6/F6-H6 -> 5805849.7 | L6: =H6-J6 -> -5805849.7 | M6: 5805849.7 | N6: 0 | O6: 522526.47 | T6: 0 | U6: =T6-Q6 -> 0 | Z6: =Y6-V6 -> 0 | AD6: =AC6/F6 -> 0 | AE6: =AD6-AA6 -> 0 | AI6: =AH6/F6 -> 0 | AJ6: =AI6-AF6 -> 0 | AN6: =AM6/F6 -> 0 | AO6: =AN6-AK6 -> 0 | AS6: =AR6/F6 -> 0 | AT6: =AS6-AP6 -> 0 | AX6: =AW6/F6 -> 0 | AY6: =AX6-AU6 -> 0 | BC6: =BB6/F6 -> 0 | BH6: =BG6/F6 -> 0 | BI6: =BH6-BE6 -> 0 | BM6: =BL6/F6 -> 0 | BN6: =BM6-BJ6 -> 0 | BR6: =BQ6/F6 -> 0 | BS6: =BR6-BO6 -> 0 | BX6: =BW6-BT6 -> 0 | CB6: =CA6/F6 -> 0 | CC6: =CB6-BY6 -> 0 | CG6: =CF6/F6 -> 0 | CH6: =CG6-CD6 -> 0 | CL6: =CK6/F6 -> 0 | CM6: =CL6-CI6 -> 0 | CR6: =ROUND(CQ6-CN6,2) -> 0 | CW6: =CV6-CS6 -> 0 | DA6: =ROUND(CZ6/F6,2) -> 0 | DB6: =ROUND(DA6-CX6,2) -> 0 | DF6: =DE6/F6 -> 0 | DG6: =DC6-DF6 -> 0 | DK6: =DJ6/F6 -> 0 | DL6: =DK6-DH6 -> 0 | DP6: =DO6/F6 -> 0 | DQ6: =DP6-DM6 -> 0 | DU6: =DT6/F6 -> 0 | DV6: =DU6-DR6 -> 0 | DZ6: =ROUND(DY6/F6,2) -> 0 | EA6: =ROUND(DZ6-DW6,2) -> 0 | EF6: =EE6-EB6 -> 0 | EJ6: =ROUND(EI6/F6,2) -> 0 | EK6: =ROUND(EJ6-EG6,2) -> 0 | EO6: =ROUND(EN6/F6,2) -> 0 | EP6: =ROUND(EO6-EL6,2) -> 0 | ET6: =ROUND(ES6/F6,2) -> 0 | EU6: =ROUND(ET6-EQ6,2) -> 0 | EY6: =ROUND(EX6/F6,2) -> 0 | EZ6: =ROUND(EY6-EV6,2) -> 0 | FD6: =ROUND(FC6/F6,2) -> 0 | FE6: =ROUND(FD6-FA6,2) -> 0 | FI6: =FH6/F6 -> 0 | FJ6: =ROUND(FI6-FF6,2) -> 0 | FN6: =ROUND(FM6/F6,2) -> 0 | FO6: =ROUND(FN6-FK6,2) -> 0 | FS6: =ROUND(FR6/F6,2) -> 0 | FT6: =FS6-FP6 -> 0 | FX6: =ROUND(FW6/F6,2) -> 0 | FY6: =FX6-FU6 -> 0 | GC6: =ROUND(GB6/F6,2) -> 0 | GD6: =GC6-FZ6 -> 0 | GH6: =GG6/F6 -> 0 | GI6: =GH6-GE6 -> 0 | GM6: =GL6/F6 -> 0 | GN6: =GM6-GJ6 -> 0 | GR6: =GQ6/F6 -> 0 | GS6: =GR6-GO6 -> 0 | GW6: =ROUND(GV6/F6,2) -> 0 | GX6: =GW6-GT6 -> 0
B7: 1050 | E7: 设计咨询 | F7: 0.06 | G7: =SUM(M7,P7:Q7,V7,AA7,AF7,AK7,AP7,AU7,AZ7,BE7,BJ7,BO7,BT7,BY7,CD7,CI7,CN7,CS7,CX7,DC7,DH7,DM7,DR7,DW7,EB7,EG7,EL7,EQ7,EV7,FA7,FF7,FK7,FP7,FU7,FZ7,GE7,GJ7,GO7,GT7) -> 275818.22 | H7: =SUM(N7,R7,W7,AB7,AG7,AL7,AQ7,AV7,BA7,BF7,BK7,BP7,BU7,BZ7,CE7,CJ7,CO7,CT7,CY7,DD7,DI7,DN7,DS7,DX7,EC7,EH7,EM7,ER7,EW7,FB7,FG7,FL7,FQ7,FV7,GA7,GF7,GK7,GP7,GU7) -> 139872.96 | I7: =SUM(O7,S7,X7,AC7,AH7,AM7,AR7,AW7,BB7,BG7,BL7,BQ7,BV7,CA7,CF7,CK7,CP7,CU7,CZ7,DE7,DJ7,DO7,DT7,DY7,ED7,EI7,EN7,ES7,EX7,FC7,FH7,FM7,FR7,FW7,GB7,GG7,GL7,GQ7,GV7) -> 16549.083 | J7: =I7/F7 -> 275818.05 | K7: =I7/F7-H7 -> 135945.09 | L7: =H7-J7 -> -135945.09 | M7: 268958.26 | N7: 0 | O7: 16137.492 | T7: 0 | U7: =T7-Q7 -> 0 | Z7: =Y7-V7 -> 0 | AD7: =AC7/F7 -> 0 | AE7: =AD7-AA7 -> 0 | AI7: =AH7/F7 -> 0 | AJ7: =AI7-AF7 -> 0 | AN7: =AM7/F7 -> 0 | AO7: =AN7-AK7 -> 0 | AS7: =AR7/F7 -> 0 | AT7: =AS7-AP7 -> 0 | AU7: 2936.68 | AW7: 176.20092 | AX7: =AW7/F7 -> 2936.682 | AY7: =AX7-AU7 -> 0.002 | AZ7: 3176.41 | BB7: 190.58 | BC7: =BB7/F7 -> 3176.3333 | BH7: =BG7/F7 -> 0 | BI7: =BH7-BE7 -> 0 | BK7: 139872.96 | BM7: =BL7/F7 -> 0 | BN7: =BM7-BJ7 -> 0 | BR7: =BQ7/F7 -> 0 | BS7: =BR7-BO7 -> 0 | BX7: =BW7-BT7 -> 0 | CB7: =CA7/F7 -> 0 | CC7: =CB7-BY7 -> 0 | CG7: =CF7/F7 -> 0 | CH7: =CG7-CD7 -> 0 | CL7: =CK7/F7 -> 0 | CM7: =CL7-CI7 -> 0 | CR7: =ROUND(CQ7-CN7,2) -> 0 | CW7: =CV7-CS7 -> 0 | DA7: =ROUND(CZ7/F7,2) -> 0 | DB7: =ROUND(DA7-CX7,2) -> 0 | DF7: =DE7/F7 -> 0 | DG7: =DC7-DF7 -> 0 | DH7: 746.87 | DJ7: 44.81 | DK7: =DJ7/F7 -> 746.83333 | DL7: =DK7-DH7 -> -0.036666667 | DP7: =DO7/F7 -> 0 | DQ7: =DP7-DM7 -> 0 | DU7: =DT7/F7 -> 0 | DV7: =DU7-DR7 -> 0 | DZ7: =ROUND(DY7/F7,2) -> 0 | EA7: =ROUND(DZ7-DW7,2) -> 0 | EF7: =EE7-EB7 -> 0 | EJ7: =ROUND(EI7/F7,2) -> 0 | EK7: =ROUND(EJ7-EG7,2) -> 0 | EO7: =ROUND(EN7/F7,2) -> 0 | EP7: =ROUND(EO7-EL7,2) -> 0 | ET7: =ROUND(ES7/F7,2) -> 0 | EU7: =ROUND(ET7-EQ7,2) -> 0 | EY7: =ROUND(EX7/F7,2) -> 0 | EZ7: =ROUND(EY7-EV7,2) -> 0 | FD7: =ROUND(FC7/F7,2) -> 0 | FE7: =ROUND(FD7-FA7,2) -> 0 | FI7: =FH7/F7 -> 0 | FJ7: =ROUND(FI7-FF7,2) -> 0 | FN7: =ROUND(FM7/F7,2) -> 0 | FO7: =ROUND(FN7-FK7,2) -> 0 | FS7: =ROUND(FR7/F7,2) -> 0 | FT7: =FS7-FP7 -> 0 | FX7: =ROUND(FW7/F7,2) -> 0 | FY7: =FX7-FU7 -> 0 | GC7: =ROUND(GB7/F7,2) -> 0 | GD7: =GC7-FZ7 -> 0 | GH7: =GG7/F7 -> 0 | GI7: =GH7-GE7 -> 0 | GM7: =GL7/F7 -> 0 | GN7: =GM7-GJ7 -> 0 | GR7: =GQ7/F7 -> 0 | GS7: =GR7-GO7 -> 0 | GW7: =ROUND(GV7/F7,2) -> 0 | GX7: =GW7-GT7 -> 0
B8: 1080 | D8: 1080（丰宁） | E8: 商品销售 | F8: 0.13 | G8: =SUM(M8,P8:Q8,V8,AA8,AF8,AK8,AP8,AU8,AZ8,BE8,BJ8,BO8,BT8,BY8,CD8,CI8,CN8,CS8,CX8,DC8,DH8,DM8,DR8,DW8,EB8,EG8,EL8,EQ8,EV8,FA8,FF8,FK8,FP8,FU8,FZ8,GE8,GJ8,GO8,GT8) -> 1.4159292e+08 | H8: =SUM(N8,R8,W8,AB8,AG8,AL8,AQ8,AV8,BA8,BF8,BK8,BP8,BU8,BZ8,CE8,CJ8,CO8,CT8,CY8,DD8,DI8,DN8,DS8,DX8,EC8,EH8,EM8,ER8,EW8,FB8,FG8,FL8,FQ8,FV8,GA8,GF8,GK8,GP8,GU8) -> 1.4159292e+08 | I8: =SUM(O8,S8,X8,AC8,AH8,AM8,AR8,AW8,BB8,BG8,BL8,BQ8,BV8,CA8,CF8,CK8,CP8,CU8,CZ8,DE8,DJ8,DO8,DT8,DY8,ED8,EI8,EN8,ES8,EX8,FC8,FH8,FM8,FR8,FW8,GB8,GG8,GL8,GQ8,GV8) -> 18407080 | J8: =I8/F8 -> 1.4159292e+08 | K8: =I8/F8-H8 -> 0.46923074 | L8: =H8-J8 -> -0.46923074 | M8: 82650966 | N8: 1.4159292e+08 | O8: 18407080 | P8: 58941955 | T8: 0 | U8: =T8-Q8 -> 0 | Z8: =Y8-V8 -> 0 | AD8: =AC8/F8 -> 0 | AE8: =AD8-AA8 -> 0 | AI8: =AH8/F8 -> 0 | AJ8: =AI8-AF8 -> 0 | AN8: =AM8/F8 -> 0 | AO8: =AN8-AK8 -> 0 | AS8: =AR8/F8 -> 0 | AT8: =AS8-AP8 -> 0 | AX8: =AW8/F8 -> 0 | AY8: =AX8-AU8 -> 0 | BC8: =BB8/F8 -> 0 | BH8: =BG8/F8 -> 0 | BI8: =BH8-BE8 -> 0 | BM8: =BL8/F8 -> 0 | BN8: =BM8-BJ8 -> 0 | BR8: =BQ8/F8 -> 0 | BS8: =BR8-BO8 -> 0 | BX8: =BW8-BT8 -> 0 | CB8: =CA8/F8 -> 0 | CC8: =CB8-BY8 -> 0 | CG8: =CF8/F8 -> 0 | CH8: =CG8-CD8 -> 0 | CL8: =CK8/F8 -> 0 | CM8: =CL8-CI8 -> 0 | CR8: =ROUND(CQ8-CN8,2) -> 0 | CW8: =CV8-CS8 -> 0 | DA8: =ROUND(CZ8/F8,2) -> 0 | DB8: =ROUND(DA8-CX8,2) -> 0 | DF8: =DE8/F8 -> 0 | DG8: =DC8-DF8 -> 0 | DK8: =DJ8/F8 -> 0 | DL8: =DK8-DH8 -> 0 | DP8: =DO8/F8 -> 0 | DQ8: =DP8-DM8 -> 0 | DU8: =DT8/F8 -> 0 | DV8: =DU8-DR8 -> 0 | DZ8: =ROUND(DY8/F8,2) -> 0 | EA8: =ROUND(DZ8-DW8,2) -> 0 | EF8: =EE8-EB8 -> 0 | EJ8: =ROUND(EI8/F8,2) -> 0 | EK8: =ROUND(EJ8-EG8,2) -> 0 | EO8: =ROUND(EN8/F8,2) -> 0 | EP8: =ROUND(EO8-EL8,2) -> 0 | ET8: =ROUND(ES8/F8,2) -> 0 | EU8: =ROUND(ET8-EQ8,2) -> 0 | EY8: =ROUND(EX8/F8,2) -> 0 | EZ8: =ROUND(EY8-EV8,2) -> 0 | FD8: =ROUND(FC8/F8,2) -> 0 | FE8: =ROUND(FD8-FA8,2) -> 0 | FI8: =FH8/F8 -> 0 | FJ8: =ROUND(FI8-FF8,2) -> 0 | FN8: =ROUND(FM8/F8,2) -> 0 | FO8: =ROUND(FN8-FK8,2) -> 0 | FS8: =ROUND(FR8/F8,2) -> 0 | FT8: =FS8-FP8 -> 0 | FX8: =ROUND(FW8/F8,2) -> 0 | FY8: =FX8-FU8 -> 0 | GC8: =ROUND(GB8/F8,2) -> 0 | GD8: =GC8-FZ8 -> 0 | GH8: =GG8/F8 -> 0 | GI8: =GH8-GE8 -> 0 | GM8: =GL8/F8 -> 0 | GN8: =GM8-GJ8 -> 0 | GR8: =GQ8/F8 -> 0 | GS8: =GR8-GO8 -> 0 | GW8: =ROUND(GV8/F8,2) -> 0 | GX8: =GW8-GT8 -> 0
B9: 1080 | E9: 工程施工 | F9: 0.09 | G9: =SUM(M9,P9:Q9,V9,AA9,AF9,AK9,AP9,AU9,AZ9,BE9,BJ9,BO9,BT9,BY9,CD9,CI9,CN9,CS9,CX9,DC9,DH9,DM9,DR9,DW9,EB9,EG9,EL9,EQ9,EV9,FA9,FF9,FK9,FP9,FU9,FZ9,GE9,GJ9,GO9,GT9) -> 52351181 | H9: =SUM(N9,R9,W9,AB9,AG9,AL9,AQ9,AV9,BA9,BF9,BK9,BP9,BU9,BZ9,CE9,CJ9,CO9,CT9,CY9,DD9,DI9,DN9,DS9,DX9,EC9,EH9,EM9,ER9,EW9,FB9,FG9,FL9,FQ9,FV9,GA9,GF9,GK9,GP9,GU9) -> 51971943 | I9: =SUM(O9,S9,X9,AC9,AH9,AM9,AR9,AW9,BB9,BG9,BL9,BQ9,BV9,CA9,CF9,CK9,CP9,CU9,CZ9,DE9,DJ9,DO9,DT9,DY9,ED9,EI9,EN9,ES9,EX9,FC9,FH9,FM9,FR9,FW9,GB9,GG9,GL9,GQ9,GV9) -> 4711606.3 | J9: =I9/F9 -> 52351181 | K9: =I9/F9-H9 -> 379237.89 | L9: =H9-J9 -> -379237.89 | M9: 1.0939348e+08 | N9: 0 | O9: 9845413.6 | P9: =-52921541.4-4500000 -> -57421541 | S9: -1360542.6 | T9: -15117140 | U9: =T9-Q9 -> -15117140 | Z9: =Y9-V9 -> 0 | AC9: -170884.6 | AD9: =AC9/F9 -> -1898717.8 | AE9: =AD9-AA9 -> -1898717.8 | AH9: -289580.32 | AI9: =AH9/F9 -> -3217559.1 | AJ9: =AI9-AF9 -> -3217559.1 | AL9: 51971943 | AM9: -2821202.9 | AN9: =AM9/F9 -> -31346699 | AO9: =AN9-AK9 -> -31346699 | AR9: -525728.34 | AS9: =AR9/F9 -> -5841426 | AT9: =AS9-AP9 -> -5841426 | AV9: =AP9*0.09 -> 0 | AX9: =AW9/F9 -> 0 | AY9: =AX9-AU9 -> 0 | BC9: =BB9/F9 -> 0 | BH9: =BG9/F9 -> 0 | BI9: =BH9-BE9 -> 0 | BM9: =BL9/F9 -> 0 | BN9: =BM9-BJ9 -> 0 | BR9: =BQ9/F9 -> 0 | BS9: =BR9-BO9 -> 0 | BX9: =BW9-BT9 -> 0 | BY9: 1261555.8 | CA9: 113540.02 | CB9: =CA9/F9 -> 1261555.8 | CC9: =CB9-BY9 -> -0.022222222 | CG9: =CF9/F9 -> 0 | CH9: =CG9-CD9 -> 0 | CL9: =CK9/F9 -> 0 | CM9: =CL9-CI9 -> 0 | CR9: =ROUND(CQ9-CN9,2) -> 0 | CW9: =CV9-CS9 -> 0 | CX9: -882317.97 | CZ9: -79408.61 | DA9: =ROUND(CZ9/F9,2) -> -882317.89 | DB9: =ROUND(DA9-CX9,2) -> 0.08 | DF9: =DE9/F9 -> 0 | DG9: =DC9-DF9 -> 0 | DK9: =DJ9/F9 -> 0 | DL9: =DK9-DH9 -> 0 | DP9: =DO9/F9 -> 0 | DQ9: =DP9-DM9 -> 0 | DU9: =DT9/F9 -> 0 | DV9: =DU9-DR9 -> 0 | DZ9: =ROUND(DY9/F9,2) -> 0 | EA9: =ROUND(DZ9-DW9,2) -> 0 | EF9: =EE9-EB9 -> 0 | EJ9: =ROUND(EI9/F9,2) -> 0 | EK9: =ROUND(EJ9-EG9,2) -> 0 | EO9: =ROUND(EN9/F9,2) -> 0 | EP9: =ROUND(EO9-EL9,2) -> 0 | ET9: =ROUND(ES9/F9,2) -> 0 | EU9: =ROUND(ET9-EQ9,2) -> 0 | EY9: =ROUND(EX9/F9,2) -> 0 | EZ9: =ROUND(EY9-EV9,2) -> 0 | FD9: =ROUND(FC9/F9,2) -> 0 | FE9: =ROUND(FD9-FA9,2) -> 0 | FI9: =FH9/F9 -> 0 | FJ9: =ROUND(FI9-FF9,2) -> 0 | FN9: =ROUND(FM9/F9,2) -> 0 | FO9: =ROUND(FN9-FK9,2) -> 0 | FS9: =ROUND(FR9/F9,2) -> 0 | FT9: =FS9-FP9 -> 0 | FX9: =ROUND(FW9/F9,2) -> 0 | FY9: =FX9-FU9 -> 0 | GC9: =ROUND(GB9/F9,2) -> 0 | GD9: =GC9-FZ9 -> 0 | GH9: =GG9/F9 -> 0 | GI9: =GH9-GE9 -> 0 | GM9: =GL9/F9 -> 0 | GN9: =GM9-GJ9 -> 0 | GR9: =GQ9/F9 -> 0 | GS9: =GR9-GO9 -> 0 | GW9: =ROUND(GV9/F9,2) -> 0 | GX9: =GW9-GT9 -> 0
B10: 1080 | E10: 设计咨询 | F10: 0.06 | G10: =SUM(M10,P10:Q10,V10,AA10,AF10,AK10,AP10,AU10,AZ10,BE10,BJ10,BO10,BT10,BY10,CD10,CI10,CN10,CS10,CX10,DC10,DH10,DM10,DR10,DW10,EB10,EG10,EL10,EQ10,EV10,FA10,FF10,FK10,FP10,FU10,FZ10,GE10,GJ10,GO10,GT10) -> 475794.07 | H10: =SUM(N10,R10,W10,AB10,AG10,AL10,AQ10,AV10,BA10,BF10,BK10,BP10,BU10,BZ10,CE10,CJ10,CO10,CT10,CY10,DD10,DI10,DN10,DS10,DX10,EC10,EH10,EM10,ER10,EW10,FB10,FG10,FL10,FQ10,FV10,GA10,GF10,GK10,GP10,GU10) -> 0 | I10: =SUM(O10,S10,X10,AC10,AH10,AM10,AR10,AW10,BB10,BG10,BL10,BQ10,BV10,CA10,CF10,CK10,CP10,CU10,CZ10,DE10,DJ10,DO10,DT10,DY10,ED10,EI10,EN10,ES10,EX10,FC10,FH10,FM10,FR10,FW10,GB10,GG10,GL10,GQ10,GV10) -> 28547.649 | J10: =I10/F10 -> 475794.16 | K10: =I10/F10-H10 -> 475794.16 | L10: =H10-J10 -> -475794.16 | M10: 0 | N10: 0 | O10: 0 | T10: 0 | U10: =T10-Q10 -> 0 | Z10: =Y10-V10 -> 0 | AD10: =AC10/F10 -> 0 | AE10: =AD10-AA10 -> 0 | AI10: =AH10/F10 -> 0 | AJ10: =AI10-AF10 -> 0 | AN10: =AM10/F10 -> 0 | AO10: =AN10-AK10 -> 0 | AS10: =AR10/F10 -> 0 | AT10: =AS10-AP10 -> 0 | AU10: 27445.64 | AW10: 1646.7387 | AX10: =AW10/F10 -> 27445.645 | AY10: =AX10-AU10 -> 0.0055 | AZ10: 29686.05 | BB10: 1781.16 | BC10: =BB10/F10 -> 29686 | BE10: 30288.91 | BG10: 1817.33 | BH10: =BG10/F10 -> 30288.833 | BI10: =BH10-BE10 -> -0.076666667 | BJ10: 39286.88 | BL10: 2357.21 | BM10: =BL10/F10 -> 39286.833 | BN10: =BM10-BJ10 -> -0.046666667 | BO10: 48891.58 | BQ10: 2933.4948 | BR10: =BQ10/F10 -> 48891.58 | BS10: =BR10-BO10 -> 0 | BT10: 30378.46 | BV10: 1822.71 | BW10: 30378.46 | BX10: =BW10-BT10 -> 0 | BY10: 97829.05 | CA10: 5869.74 | CB10: =CA10/F10 -> 97829 | CC10: =CB10-BY10 -> -0.05 | CD10: 17779.88 | CF10: 1066.79 | CG10: =CF10/F10 -> 17779.833 | CH10: =CG10-CD10 -> -0.046666667 | CI10: 10524.61 | CK10: 631.48 | CL10: =CK10/F10 -> 10524.667 | CM10: =CL10-CI10 -> 0.056666667 | CN10: 11892.42 | CP10: 713.55 | CQ10: 11892.42 | CR10: =ROUND(CQ10-CN10,2) -> 0 | CS10: 11933.09 | CU10: 715.99 | CV10: 11933.09 | CW10: =CV10-CS10 -> 0 | CX10: 3563.92 | CZ10: 213.84 | DA10: =ROUND(CZ10/F10,2) -> 3564 | DB10: =ROUND(DA10-CX10,2) -> 0.08 | DC10: 6980.01 | DE10: 418.8 | DF10: =DE10/F10 -> 6980 | DG10: =DC10-DF10 -> 0.01 | DH10: 6980.01 | DJ10: 418.8 | DK10: =DJ10/F10 -> 6980 | DL10: =DK10-DH10 -> -0.01 | DM10: 9052.56 | DO10: 543.15 | DP10: =DO10/F10 -> 9052.5 | DQ10: =DP10-DM10 -> -0.06 | DR10: 8259.02 | DT10: 495.54 | DU10: =DT10/F10 -> 8259 | DV10: =DU10-DR10 -> -0.02 | DW10: 8335.96 | DY10: 500.16 | DZ10: =ROUND(DY10/F10,2) -> 8336 | EA10: =ROUND(DZ10-DW10,2) -> 0.04 | EB10: 17528.93 | ED10: 1051.7358 | EE10: 17528.93 | EF10: =EE10-EB10 -> 0 | EG10: 44823.59 | EI10: 2689.42 | EJ10: =ROUND(EI10/F10,2) -> 44823.67 | EK10: =ROUND(EJ10-EG10,2) -> 0.08 | EL10: 4073.2 | EN10: 244.39 | EO10: =ROUND(EN10/F10,2) -> 4073.17 | EP10: =ROUND(EO10-EL10,2) -> -0.03 | EQ10: 5057.76 | ES10: 303.47 | ET10: =ROUND(ES10/F10,2) -> 5057.83 | EU10: =ROUND(ET10-EQ10,2) -> 0.07 | EV10: 5202.54 | EX10: 312.15 | EY10: =ROUND(EX10/F10,2) -> 5202.5 | EZ10: =ROUND(EY10-EV10,2) -> -0.04 | FD10: =ROUND(FC10/F10,2) -> 0 | FE10: =ROUND(FD10-FA10,2) -> 0 | FI10: =FH10/F10 -> 0 | FJ10: =ROUND(FI10-FF10,2) -> 0 | FN10: =ROUND(FM10/F10,2) -> 0 | FO10: =ROUND(FN10-FK10,2) -> 0 | FS10: =ROUND(FR10/F10,2) -> 0 | FT10: =FS10-FP10 -> 0 | FX10: =ROUND(FW10/F10,2) -> 0 | FY10: =FX10-FU10 -> 0 | GC10: =ROUND(GB10/F10,2) -> 0 | GD10: =GC10-FZ10 -> 0 | GH10: =GG10/F10 -> 0 | GI10: =GH10-GE10 -> 0 | GM10: =GL10/F10 -> 0 | GN10: =GM10-GJ10 -> 0 | GR10: =GQ10/F10 -> 0 | GS10: =GR10-GO10 -> 0 | GW10: =ROUND(GV10/F10,2) -> 0 | GX10: =GW10-GT10 -> 0
B11: 1080 | D11: 1080（丰宁二期） | E11: 商品销售 | F11: 0.13 | G11: =SUM(M11,P11:Q11,V11,AA11,AF11,AK11,AP11,AU11,AZ11,BE11,BJ11,BO11,BT11,BY11,CD11,CI11,CN11,CS11,CX11,DC11,DH11,DM11,DR11,DW11,EB11,EG11,EL11,EQ11,EV11,FA11,FF11,FK11,FP11,FU11,FZ11,GE11,GJ11,GO11,GT11) -> 0 | H11: =SUM(N11,R11,W11,AB11,AG11,AL11,AQ11,AV11,BA11,BF11,BK11,BP11,BU11,BZ11,CE11,CJ11,CO11,CT11,CY11,DD11,DI11,DN11,DS11,DX11,EC11,EH11,EM11,ER11,EW11,FB11,FG11,FL11,FQ11,FV11,GA11,GF11,GK11,GP11,GU11) -> 0 | I11: =SUM(O11,S11,X11,AC11,AH11,AM11,AR11,AW11,BB11,BG11,BL11,BQ11,BV11,CA11,CF11,CK11,CP11,CU11,CZ11,DE11,DJ11,DO11,DT11,DY11,ED11,EI11,EN11,ES11,EX11,FC11,FH11,FM11,FR11,FW11,GB11,GG11,GL11,GQ11,GV11) -> 0 | J11: =I11/F11 -> 0 | K11: =I11/F11-H11 -> 0 | L11: =H11-J11 -> 0 | CR11: =ROUND(CQ11-CN11,2) -> 0 | CW11: =CV11-CS11 -> 0 | DA11: =ROUND(CZ11/F11,2) -> 0 | DB11: =ROUND(DA11-CX11,2) -> 0 | DF11: =DE11/F11 -> 0 | DG11: =DC11-DF11 -> 0 | DK11: =DJ11/F11 -> 0 | DL11: =DK11-DH11 -> 0 | DP11: =DO11/F11 -> 0 | DQ11: =DP11-DM11 -> 0 | DU11: =DT11/F11 -> 0 | DV11: =DU11-DR11 -> 0 | DZ11: =ROUND(DY11/F11,2) -> 0 | EA11: =ROUND(DZ11-DW11,2) -> 0 | EF11: =EE11-EB11 -> 0 | EJ11: =ROUND(EI11/F11,2) -> 0 | EK11: =ROUND(EJ11-EG11,2) -> 0 | EO11: =ROUND(EN11/F11,2) -> 0 | EP11: =ROUND(EO11-EL11,2) -> 0 | ET11: =ROUND(ES11/F11,2) -> 0 | EU11: =ROUND(ET11-EQ11,2) -> 0 | EY11: =ROUND(EX11/F11,2) -> 0 | EZ11: =ROUND(EY11-EV11,2) -> 0 | FD11: =ROUND(FC11/F11,2) -> 0 | FE11: =ROUND(FD11-FA11,2) -> 0 | FI11: =FH11/F11 -> 0 | FJ11: =ROUND(FI11-FF11,2) -> 0 | FN11: =ROUND(FM11/F11,2) -> 0 | FO11: =ROUND(FN11-FK11,2) -> 0 | FS11: =ROUND(FR11/F11,2) -> 0 | FT11: =FS11-FP11 -> 0 | FX11: =ROUND(FW11/F11,2) -> 0 | FY11: =FX11-FU11 -> 0 | GC11: =ROUND(GB11/F11,2) -> 0 | GD11: =GC11-FZ11 -> 0 | GH11: =GG11/F11 -> 0 | GI11: =GH11-GE11 -> 0 | GM11: =GL11/F11 -> 0 | GN11: =GM11-GJ11 -> 0 | GR11: =GQ11/F11 -> 0 | GS11: =GR11-GO11 -> 0 | GW11: =ROUND(GV11/F11,2) -> 0 | GX11: =GW11-GT11 -> 0
B12: 1080 | E12: 工程施工 | F12: 0.09 | G12: =SUM(M12,P12:Q12,V12,AA12,AF12,AK12,AP12,AU12,AZ12,BE12,BJ12,BO12,BT12,BY12,CD12,CI12,CN12,CS12,CX12,DC12,DH12,DM12,DR12,DW12,EB12,EG12,EL12,EQ12,EV12,FA12,FF12,FK12,FP12,FU12,FZ12,GE12,GJ12,GO12,GT12) -> 6108066.9 | H12: =SUM(N12,R12,W12,AB12,AG12,AL12,AQ12,AV12,BA12,BF12,BK12,BP12,BU12,BZ12,CE12,CJ12,CO12,CT12,CY12,DD12,DI12,DN12,DS12,DX12,EC12,EH12,EM12,ER12,EW12,FB12,FG12,FL12,FQ12,FV12,GA12,GF12,GK12,GP12,GU12) -> 0 | I12: =SUM(O12,S12,X12,AC12,AH12,AM12,AR12,AW12,BB12,BG12,BL12,BQ12,BV12,CA12,CF12,CK12,CP12,CU12,CZ12,DE12,DJ12,DO12,DT12,DY12,ED12,EI12,EN12,ES12,EX12,FC12,FH12,FM12,FR12,FW12,GB12,GG12,GL12,GQ12,GV12) -> 549726.02 | J12: =I12/F12 -> 6108066.9 | K12: =I12/F12-H12 -> 6108066.9 | L12: =H12-J12 -> -6108066.9 | CR12: =ROUND(CQ12-CN12,2) -> 0 | CW12: =CV12-CS12 -> 0 | DA12: =ROUND(CZ12/F12,2) -> 0 | DB12: =ROUND(DA12-CX12,2) -> 0 | DF12: =DE12/F12 -> 0 | DG12: =DC12-DF12 -> 0 | DK12: =DJ12/F12 -> 0 | DL12: =DK12-DH12 -> 0 | DP12: =DO12/F12 -> 0 | DQ12: =DP12-DM12 -> 0 | DU12: =DT12/F12 -> 0 | DV12: =DU12-DR12 -> 0 | DZ12: =ROUND(DY12/F12,2) -> 0 | EA12: =ROUND(DZ12-DW12,2) -> 0 | EF12: =EE12-EB12 -> 0 | EJ12: =ROUND(EI12/F12,2) -> 0 | EK12: =ROUND(EJ12-EG12,2) -> 0 | EO12: =ROUND(EN12/F12,2) -> 0 | EP12: =ROUND(EO12-EL12,2) -> 0 | ET12: =ROUND(ES12/F12,2) -> 0 | EU12: =ROUND(ET12-EQ12,2) -> 0 | EY12: =ROUND(EX12/F12,2) -> 0 | EZ12: =ROUND(EY12-EV12,2) -> 0 | FD12: =ROUND(FC12/F12,2) -> 0 | FE12: =ROUND(FD12-FA12,2) -> 0 | FI12: =FH12/F12 -> 0 | FJ12: =ROUND(FI12-FF12,2) -> 0 | FN12: =ROUND(FM12/F12,2) -> 0 | FO12: =ROUND(FN12-FK12,2) -> 0 | FS12: =ROUND(FR12/F12,2) -> 0 | FT12: =FS12-FP12 -> 0 | FU12: 1410550.4 | FW12: 126949.54 | FX12: =ROUND(FW12/F12,2) -> 1410550.4 | FY12: =FX12-FU12 -> -0.01 | GC12: =ROUND(GB12/F12,2) -> 0 | GD12: =GC12-FZ12 -> 0 | GE12: 3286966 | GG12: 295826.94 | GH12: =GG12/F12 -> 3286966 | GI12: =GH12-GE12 -> -0.03 | GJ12: 1410550.4 | GL12: 126949.54 | GM12: =GL12/F12 -> 1410550.4 | GN12: =GM12-GJ12 -> -0.0055555555 | GR12: =GQ12/F12 -> 0 | GS12: =GR12-GO12 -> 0 | GW12: =ROUND(GV12/F12,2) -> 0 | GX12: =GW12-GT12 -> 0
B13: 1080 | E13: 设计咨询 | F13: 0.06 | G13: =SUM(M13,P13:Q13,V13,AA13,AF13,AK13,AP13,AU13,AZ13,BE13,BJ13,BO13,BT13,BY13,CD13,CI13,CN13,CS13,CX13,DC13,DH13,DM13,DR13,DW13,EB13,EG13,EL13,EQ13,EV13,FA13,FF13,FK13,FP13,FU13,FZ13,GE13,GJ13,GO13,GT13) -> 5717060.5 | H13: =SUM(N13,R13,W13,AB13,AG13,AL13,AQ13,AV13,BA13,BF13,BK13,BP13,BU13,BZ13,CE13,CJ13,CO13,CT13,CY13,DD13,DI13,DN13,DS13,DX13,EC13,EH13,EM13,ER13,EW13,FB13,FG13,FL13,FQ13,FV13,GA13,GF13,GK13,GP13,GU13) -> 2596564.4 | I13: =SUM(O13,S13,X13,AC13,AH13,AM13,AR13,AW13,BB13,BG13,BL13,BQ13,BV13,CA13,CF13,CK13,CP13,CU13,CZ13,DE13,DJ13,DO13,DT13,DY13,ED13,EI13,EN13,ES13,EX13,FC13,FH13,FM13,FR13,FW13,GB13,GG13,GL13,GQ13,GV13) -> 343023.6 | J13: =I13/F13 -> 5717060.1 | K13: =I13/F13-H13 -> 3120495.6 | L13: =H13-J13 -> -3120495.6 | CN13: 124878.06 | CP13: 7492.68 | CQ13: 124878.06 | CR13: =ROUND(CQ13-CN13,2) -> 0 | CS13: 21325.93 | CU13: 1279.56 | CV13: 21325.93 | CW13: =CV13-CS13 -> 0 | CX13: 23049.37 | CZ13: 1382.96 | DA13: =ROUND(CZ13/F13,2) -> 23049.33 | DB13: =ROUND(DA13-CX13,2) -> -0.04 | DC13: 27684.51 | DE13: 1661.07 | DF13: =DE13/F13 -> 27684.5 | DG13: =DC13-DF13 -> 0.01 | DH13: 25907.01 | DJ13: 1554.42 | DK13: =DJ13/F13 -> 25907 | DL13: =DK13-DH13 -> -0.01 | DM13: 30416.01 | DO13: 1824.96 | DP13: =DO13/F13 -> 30416 | DQ13: =DP13-DM13 -> -0.01 | DR13: 26955.45 | DT13: 1617.33 | DU13: =DT13/F13 -> 26955.5 | DV13: =DU13-DR13 -> 0.05 | DW13: 773349.59 | DY13: 46400.97 | DZ13: =ROUND(DY13/F13,2) -> 773349.5 | EA13: =ROUND(DZ13-DW13,2) -> -0.09 | EB13: 1405665.1 | ED13: 84339.904 | EE13: 1405665.1 | EF13: =EE13-EB13 -> 0 | EG13: 108821.37 | EI13: 6529.28 | EJ13: =ROUND(EI13/F13,2) -> 108821.33 | EK13: =ROUND(EJ13-EG13,2) -> -0.04 | EL13: 28512.07 | EN13: 1710.72 | EO13: =ROUND(EN13/F13,2) -> 28512 | EP13: =ROUND(EO13-EL13,2) -> -0.07 | EQ13: 42390.36 | ER13: 2596564.4 | ES13: 2543.42 | ET13: =ROUND(ES13/F13,2) -> 42390.33 | EU13: =ROUND(ET13-EQ13,2) -> -0.03 | EV13: 44768.35 | EX13: 2686.1 | EY13: =ROUND(EX13/F13,2) -> 44768.33 | EZ13: =ROUND(EY13-EV13,2) -> -0.02 | FA13: 51067.08 | FC13: 3064.02 | FD13: =ROUND(FC13/F13,2) -> 51067 | FE13: =ROUND(FD13-FA13,2) -> -0.08 | FF13: 785466.23 | FH13: 47127.97 | FI13: =FH13/F13 -> 785466.17 | FJ13: =ROUND(FI13-FF13,2) -> -0.06 | FK13: 49452.77 | FM13: 2967.17 | FN13: =ROUND(FM13/F13,2) -> 49452.83 | FO13: =ROUND(FN13-FK13,2) -> 0.06 | FP13: 47821.31 | FQ13: 0 | FR13: 2869.28 | FS13: =ROUND(FR13/F13,2) -> 47821.33 | FT13: =FS13-FP13 -> 0.02 | FU13: 46498.97 | FW13: 2789.94 | FX13: =ROUND(FW13/F13,2) -> 46499 | FY13: =FX13-FU13 -> 0.03 | FZ13: 39152.32 | GB13: 2349.14 | GC13: =ROUND(GB13/F13,2) -> 39152.33 | GD13: =GC13-FZ13 -> 0.01 | GE13: 487640.38 | GG13: 29258.42 | GH13: =GG13/F13 -> 487640.33 | GI13: =GH13-GE13 -> -0.046666667 | GJ13: 834841.46 | GL13: 50090.48 | GM13: =GL13/F13 -> 834841.33 | GN13: =GM13-GJ13 -> -0.12666667 | GO13: 68493.26 | GQ13: 4109.59 | GR13: =GQ13/F13 -> 68493.167 | GS13: =GR13-GO13 -> -0.093333333 | GT13: 622903.61 | GV13: 37374.22 | GW13: =ROUND(GV13/F13,2) -> 622903.67 | GX13: =GW13-GT13 -> 0.06
B14: 1080 | D14: 1080（丰宁三期） | E14: 商品销售 | F14: 0.13 | G14: =SUM(M14,P14:Q14,V14,AA14,AF14,AK14,AP14,AU14,AZ14,BE14,BJ14,BO14,BT14,BY14,CD14,CI14,CN14,CS14,CX14,DC14,DH14,DM14,DR14,DW14,EB14,EG14,EL14,EQ14,EV14,FA14,FF14,FK14,FP14,FU14,FZ14,GE14,GJ14,GO14,GT14) -> 0 | H14: =SUM(N14,R14,W14,AB14,AG14,AL14,AQ14,AV14,BA14,BF14,BK14,BP14,BU14,BZ14,CE14,CJ14,CO14,CT14,CY14,DD14,DI14,DN14,DS14,DX14,EC14,EH14,EM14,ER14,EW14,FB14,FG14,FL14,FQ14,FV14,GA14,GF14,GK14,GP14,GU14) -> 0 | I14: =SUM(O14,S14,X14,AC14,AH14,AM14,AR14,AW14,BB14,BG14,BL14,BQ14,BV14,CA14,CF14,CK14,CP14,CU14,CZ14,DE14,DJ14,DO14,DT14,DY14,ED14,EI14,EN14,ES14,EX14,FC14,FH14,FM14,FR14,FW14,GB14,GG14,GL14,GQ14,GV14) -> 0 | J14: =I14/F14 -> 0 | K14: =I14/F14-H14 -> 0 | L14: =H14-J14 -> 0 | CR14: =ROUND(CQ14-CN14,2) -> 0 | CW14: =CV14-CS14 -> 0 | DA14: =ROUND(CZ14/F14,2) -> 0 | DB14: =ROUND(DA14-CX14,2) -> 0 | DF14: =DE14/F14 -> 0 | DG14: =DC14-DF14 -> 0 | DK14: =DJ14/F14 -> 0 | DL14: =DK14-DH14 -> 0 | DP14: =DO14/F14 -> 0 | DQ14: =DP14-DM14 -> 0 | DU14: =DT14/F14 -> 0 | DV14: =DU14-DR14 -> 0 | DZ14: =ROUND(DY14/F14,2) -> 0 | EA14: =ROUND(DZ14-DW14,2) -> 0 | EF14: =EE14-EB14 -> 0 | EJ14: =ROUND(EI14/F14,2) -> 0 | EK14: =ROUND(EJ14-EG14,2) -> 0 | EO14: =ROUND(EN14/F14,2) -> 0 | EP14: =ROUND(EO14-EL14,2) -> 0 | ET14: =ROUND(ES14/F14,2) -> 0 | EU14: =ROUND(ET14-EQ14,2) -> 0 | EY14: =ROUND(EX14/F14,2) -> 0 | EZ14: =ROUND(EY14-EV14,2) -> 0 | FD14: =ROUND(FC14/F14,2) -> 0 | FE14: =ROUND(FD14-FA14,2) -> 0 | FI14: =FH14/F14 -> 0 | FJ14: =ROUND(FI14-FF14,2) -> 0 | FN14: =ROUND(FM14/F14,2) -> 0 | FO14: =ROUND(FN14-FK14,2) -> 0 | FS14: =ROUND(FR14/F14,2) -> 0 | FT14: =FS14-FP14 -> 0 | FX14: =ROUND(FW14/F14,2) -> 0 | FY14: =FX14-FU14 -> 0 | GC14: =ROUND(GB14/F14,2) -> 0 | GD14: =GC14-FZ14 -> 0 | GH14: =GG14/F14 -> 0 | GI14: =GH14-GE14 -> 0 | GM14: =GL14/F14 -> 0 | GN14: =GM14-GJ14 -> 0 | GR14: =GQ14/F14 -> 0 | GS14: =GR14-GO14 -> 0 | GW14: =ROUND(GV14/F14,2) -> 0 | GX14: =GW14-GT14 -> 0
B15: 1080 | E15: 工程施工 | F15: 0.09 | G15: =SUM(M15,P15:Q15,V15,AA15,AF15,AK15,AP15,AU15,AZ15,BE15,BJ15,BO15,BT15,BY15,CD15,CI15,CN15,CS15,CX15,DC15,DH15,DM15,DR15,DW15,EB15,EG15,EL15,EQ15,EV15,FA15,FF15,FK15,FP15,FU15,FZ15,GE15,GJ15,GO15,GT15) -> 2452735.5 | H15: =SUM(N15,R15,W15,AB15,AG15,AL15,AQ15,AV15,BA15,BF15,BK15,BP15,BU15,BZ15,CE15,CJ15,CO15,CT15,CY15,DD15,DI15,DN15,DS15,DX15,EC15,EH15,EM15,ER15,EW15,FB15,FG15,FL15,FQ15,FV15,GA15,GF15,GK15,GP15,GU15) -> 0 | I15: =SUM(O15,S15,X15,AC15,AH15,AM15,AR15,AW15,BB15,BG15,BL15,BQ15,BV15,CA15,CF15,CK15,CP15,CU15,CZ15,DE15,DJ15,DO15,DT15,DY15,ED15,EI15,EN15,ES15,EX15,FC15,FH15,FM15,FR15,FW15,GB15,GG15,GL15,GQ15,GV15) -> 220746.19 | J15: =I15/F15 -> 2452735.4 | K15: =I15/F15-H15 -> 2452735.4 | L15: =H15-J15 -> -2452735.4 | CR15: =ROUND(CQ15-CN15,2) -> 0 | CW15: =CV15-CS15 -> 0 | DA15: =ROUND(CZ15/F15,2) -> 0 | DB15: =ROUND(DA15-CX15,2) -> 0 | DF15: =DE15/F15 -> 0 | DG15: =DC15-DF15 -> 0 | DK15: =DJ15/F15 -> 0 | DL15: =DK15-DH15 -> 0 | DP15: =DO15/F15 -> 0 | DQ15: =DP15-DM15 -> 0 | DU15: =DT15/F15 -> 0 | DV15: =DU15-DR15 -> 0 | DZ15: =ROUND(DY15/F15,2) -> 0 | EA15: =ROUND(DZ15-DW15,2) -> 0 | EF15: =EE15-EB15 -> 0 | EJ15: =ROUND(EI15/F15,2) -> 0 | EK15: =ROUND(EJ15-EG15,2) -> 0 | EO15: =ROUND(EN15/F15,2) -> 0 | EP15: =ROUND(EO15-EL15,2) -> 0 | ET15: =ROUND(ES15/F15,2) -> 0 | EU15: =ROUND(ET15-EQ15,2) -> 0 | EY15: =ROUND(EX15/F15,2) -> 0 | EZ15: =ROUND(EY15-EV15,2) -> 0 | FD15: =ROUND(FC15/F15,2) -> 0 | FE15: =ROUND(FD15-FA15,2) -> 0 | FI15: =FH15/F15 -> 0 | FJ15: =ROUND(FI15-FF15,2) -> 0 | FN15: =ROUND(FM15/F15,2) -> 0 | FO15: =ROUND(FN15-FK15,2) -> 0 | FS15: =ROUND(FR15/F15,2) -> 0 | FT15: =FS15-FP15 -> 0 | FX15: =ROUND(FW15/F15,2) -> 0 | FY15: =FX15-FU15 -> 0 | GC15: =ROUND(GB15/F15,2) -> 0 | GD15: =GC15-FZ15 -> 0 | GE15: 2452735.5 | GG15: 220746.19 | GH15: =GG15/F15 -> 2452735.4 | GI15: =GH15-GE15 -> -0.0055555557 | GM15: =GL15/F15 -> 0 | GN15: =GM15-GJ15 -> 0 | GR15: =GQ15/F15 -> 0 | GS15: =GR15-GO15 -> 0 | GW15: =ROUND(GV15/F15,2) -> 0 | GX15: =GW15-GT15 -> 0
B16: 1080 | E16: 设计咨询 | F16: 0.06 | G16: =SUM(M16,P16:Q16,V16,AA16,AF16,AK16,AP16,AU16,AZ16,BE16,BJ16,BO16,BT16,BY16,CD16,CI16,CN16,CS16,CX16,DC16,DH16,DM16,DR16,DW16,EB16,EG16,EL16,EQ16,EV16,FA16,FF16,FK16,FP16,FU16,FZ16,GE16,GJ16,GO16,GT16) -> 3484602 | H16: =SUM(N16,R16,W16,AB16,AG16,AL16,AQ16,AV16,BA16,BF16,BK16,BP16,BU16,BZ16,CE16,CJ16,CO16,CT16,CY16,DD16,DI16,DN16,DS16,DX16,EC16,EH16,EM16,ER16,EW16,FB16,FG16,FL16,FQ16,FV16,GA16,GF16,GK16,GP16,GU16) -> 1980718 | I16: =SUM(O16,S16,X16,AC16,AH16,AM16,AR16,AW16,BB16,BG16,BL16,BQ16,BV16,CA16,CF16,CK16,CP16,CU16,CZ16,DE16,DJ16,DO16,DT16,DY16,ED16,EI16,EN16,ES16,EX16,FC16,FH16,FM16,FR16,FW16,GB16,GG16,GL16,GQ16,GV16) -> 209076.09 | J16: =I16/F16 -> 3484601.6 | K16: =I16/F16-H16 -> 1503883.6 | L16: =H16-J16 -> -1503883.6 | CN16: 83252.05 | CP16: 4995.13 | CQ16: 83252.05 | CR16: =ROUND(CQ16-CN16,2) -> 0 | CS16: 19193.34 | CU16: 1151.6 | CV16: 19193.34 | CW16: =CV16-CS16 -> 0 | CX16: 20744.43 | CZ16: 1244.67 | DA16: =ROUND(CZ16/F16,2) -> 20744.5 | DB16: =ROUND(DA16-CX16,2) -> 0.07 | DC16: 24916.05 | DE16: 1494.96 | DF16: =DE16/F16 -> 24916 | DG16: =DC16-DF16 -> 0.05 | DH16: 23316.31 | DJ16: 1398.98 | DK16: =DJ16/F16 -> 23316.333 | DL16: =DK16-DH16 -> 0.023333333 | DM16: 27374.4 | DO16: 1642.46 | DP16: =DO16/F16 -> 27374.333 | DQ16: =DP16-DM16 -> -0.066666667 | DR16: 24259.9 | DT16: 1455.59 | DU16: =DT16/F16 -> 24259.833 | DV16: =DU16-DR16 -> -0.066666667 | DW16: 25797.65 | DY16: 1547.86 | DZ16: =ROUND(DY16/F16,2) -> 25797.67 | EA16: =ROUND(DZ16-DW16,2) -> 0.02 | EB16: 1182791.4 | ED16: 70967.485 | EE16: 1182791.4 | EF16: =EE16-EB16 -> 0 | EG16: 523411.61 | EI16: 31404.69 | EJ16: =ROUND(EI16/F16,2) -> 523411.5 | EK16: =ROUND(EJ16-EG16,2) -> -0.11 | EL16: 25660.86 | EN16: 1539.65 | EO16: =ROUND(EN16/F16,2) -> 25660.83 | EP16: =ROUND(EO16-EL16,2) -> -0.03 | EQ16: 40397.5 | ER16: 1980718 | ES16: 2423.85 | ET16: =ROUND(ES16/F16,2) -> 40397.5 | EU16: =ROUND(ET16-EQ16,2) -> 0 | EV16: 42663.69 | EX16: 2559.82 | EY16: =ROUND(EX16/F16,2) -> 42663.67 | EZ16: =ROUND(EY16-EV16,2) -> -0.02 | FA16: 48692.23 | FC16: 2921.53 | FD16: =ROUND(FC16/F16,2) -> 48692.17 | FE16: =ROUND(FD16-FA16,2) -> -0.06 | FF16: 51854.67 | FH16: 3111.28 | FI16: =FH16/F16 -> 51854.667 | FJ16: =ROUND(FI16-FF16,2) -> 0 | FK16: 46890.55 | FM16: 2813.43 | FN16: =ROUND(FM16/F16,2) -> 46890.5 | FO16: =ROUND(FN16-FK16,2) -> -0.05 | FP16: 45288.73 | FQ16: 0 | FR16: 2717.32 | FS16: =ROUND(FR16/F16,2) -> 45288.67 | FT16: =FS16-FP16 -> -0.06 | FU16: 44036.45 | FW16: 2642.19 | FX16: =ROUND(FW16/F16,2) -> 44036.5 | FY16: =FX16-FU16 -> 0.05 | FZ16: 37077.08 | GB16: 2224.63 | GC16: =ROUND(GB16/F16,2) -> 37077.17 | GD16: =GC16-FZ16 -> 0.09 | GE16: 404119.51 | GG16: 24247.17 | GH16: =GG16/F16 -> 404119.5 | GI16: =GH16-GE16 -> -0.01 | GJ16: 95273.23 | GL16: 5716.39 | GM16: =GL16/F16 -> 95273.167 | GN16: =GM16-GJ16 -> -0.063333333 | GO16: 63366.01 | GQ16: 3801.95 | GR16: =GQ16/F16 -> 63365.833 | GS16: =GR16-GO16 -> -0.17666667 | GT16: 584224.37 | GV16: 35053.46 | GW16: =ROUND(GV16/F16,2) -> 584224.33 | GX16: =GW16-GT16 -> -0.04
B17: 1300 | D17: 1300（牟平一期） | E17: 商品销售 | F17: 0.16 | G17: =SUM(M17,P17:Q17,V17,AA17,AF17,AK17,AP17,AU17,AZ17,BE17,BJ17,BO17,BT17,BY17,CD17,CI17,CN17,CS17,CX17,DC17,DH17,DM17,DR17,DW17,EB17,EG17,EL17,EQ17,EV17,FA17,FF17,FK17,FP17,FU17,FZ17,GE17,GJ17,GO17,GT17) -> 0 | H17: =SUM(N17,R17,W17,AB17,AG17,AL17,AQ17,AV17,BA17,BF17,BK17,BP17,BU17,BZ17,CE17,CJ17,CO17,CT17,CY17,DD17,DI17,DN17,DS17,DX17,EC17,EH17,EM17,ER17,EW17,FB17,FG17,FL17,FQ17,FV17,GA17,GF17,GK17,GP17,GU17) -> 47536174 | I17: =SUM(O17,S17,X17,AC17,AH17,AM17,AR17,AW17,BB17,BG17,BL17,BQ17,BV17,CA17,CF17,CK17,CP17,CU17,CZ17,DE17,DJ17,DO17,DT17,DY17,ED17,EI17,EN17,ES17,EX17,FC17,FH17,FM17,FR17,FW17,GB17,GG17,GL17,GQ17,GV17) -> 7605788 | J17: =I17/F17 -> 47536175 | N17: 47536174 | O17: 7605788 | T17: 0 | U17: =T17-Q17 -> 0 | Z17: =Y17-V17 -> 0 | AD17: =AC17/F17 -> 0 | AE17: =AD17-AA17 -> 0 | AI17: =AH17/F17 -> 0 | AJ17: =AI17-AF17 -> 0 | AN17: =AM17/F17 -> 0 | AO17: =AN17-AK17 -> 0 | AS17: =AR17/F17 -> 0 | AT17: =AS17-AP17 -> 0 | AX17: =AW17/F17 -> 0 | AY17: =AX17-AU17 -> 0 | BC17: =BB17/F17 -> 0 | BH17: =BG17/F17 -> 0 | BI17: =BH17-BE17 -> 0 | BM17: =BL17/F17 -> 0 | BN17: =BM17-BJ17 -> 0 | BR17: =BQ17/F17 -> 0 | BS17: =BR17-BO17 -> 0 | BX17: =BW17-BT17 -> 0 | CB17: =CA17/F17 -> 0 | CC17: =CB17-BY17 -> 0 | CG17: =CF17/F17 -> 0 | CH17: =CG17-CD17 -> 0 | CL17: =CK17/F17 -> 0 | CM17: =CL17-CI17 -> 0 | CR17: =ROUND(CQ17-CN17,2) -> 0 | CW17: =CV17-CS17 -> 0 | DA17: =ROUND(CZ17/F17,2) -> 0 | DB17: =ROUND(DA17-CX17,2) -> 0 | DF17: =DE17/F17 -> 0 | DG17: =DC17-DF17 -> 0 | DK17: =DJ17/F17 -> 0 | DL17: =DK17-DH17 -> 0 | DP17: =DO17/F17 -> 0 | DQ17: =DP17-DM17 -> 0 | DU17: =DT17/F17 -> 0 | DV17: =DU17-DR17 -> 0 | DZ17: =ROUND(DY17/F17,2) -> 0 | EA17: =ROUND(DZ17-DW17,2) -> 0 | EF17: =EE17-EB17 -> 0 | EJ17: =ROUND(EI17/F17,2) -> 0 | EK17: =ROUND(EJ17-EG17,2) -> 0 | EO17: =ROUND(EN17/F17,2) -> 0 | EP17: =ROUND(EO17-EL17,2) -> 0 | ET17: =ROUND(ES17/F17,2) -> 0 | EU17: =ROUND(ET17-EQ17,2) -> 0 | EY17: =ROUND(EX17/F17,2) -> 0 | EZ17: =ROUND(EY17-EV17,2) -> 0 | FD17: =ROUND(FC17/F17,2) -> 0 | FE17: =ROUND(FD17-FA17,2) -> 0 | FI17: =FH17/F17 -> 0 | FJ17: =ROUND(FI17-FF17,2) -> 0 | FN17: =ROUND(FM17/F17,2) -> 0 | FO17: =ROUND(FN17-FK17,2) -> 0 | FS17: =ROUND(FR17/F17,2) -> 0 | FT17: =FS17-FP17 -> 0 | FX17: =ROUND(FW17/F17,2) -> 0 | FY17: =FX17-FU17 -> 0 | GC17: =ROUND(GB17/F17,2) -> 0 | GD17: =GC17-FZ17 -> 0 | GH17: =GG17/F17 -> 0 | GI17: =GH17-GE17 -> 0 | GM17: =GL17/F17 -> 0 | GN17: =GM17-GJ17 -> 0 | GR17: =GQ17/F17 -> 0 | GS17: =GR17-GO17 -> 0 | GW17: =ROUND(GV17/F17,2) -> 0 | GX17: =GW17-GT17 -> 0
B18: 1300 | F18: 0.13 | G18: =SUM(M18,P18:Q18,V18,AA18,AF18,AK18,AP18,AU18,AZ18,BE18,BJ18,BO18,BT18,BY18,CD18,CI18,CN18,CS18,CX18,DC18,DH18,DM18,DR18,DW18,EB18,EG18,EL18,EQ18,EV18,FA18,FF18,FK18,FP18,FU18,FZ18,GE18,GJ18,GO18,GT18) -> 64515557 | H18: =SUM(N18,R18,W18,AB18,AG18,AL18,AQ18,AV18,BA18,BF18,BK18,BP18,BU18,BZ18,CE18,CJ18,CO18,CT18,CY18,DD18,DI18,DN18,DS18,DX18,EC18,EH18,EM18,ER18,EW18,FB18,FG18,FL18,FQ18,FV18,GA18,GF18,GK18,GP18,GU18) -> 16171698 | I18: =SUM(O18,S18,X18,AC18,AH18,AM18,AR18,AW18,BB18,BG18,BL18,BQ18,BV18,CA18,CF18,CK18,CP18,CU18,CZ18,DE18,DJ18,DO18,DT18,DY18,ED18,EI18,EN18,ES18,EX18,FC18,FH18,FM18,FR18,FW18,GB18,GG18,GL18,GQ18,GV18) -> 2094519.5 | J18: =I18/F18 -> 16111688 | M18: 64515557 | N18: 16111688 | O18: 2094519.5 | T18: 0 | U18: =T18-Q18 -> 0 | Z18: =Y18-V18 -> 0 | AB18: 60009.32 | AD18: =AC18/F18 -> 0 | AE18: =AD18-AA18 -> 0 | AI18: =AH18/F18 -> 0 | AJ18: =AI18-AF18 -> 0 | AN18: =AM18/F18 -> 0 | AO18: =AN18-AK18 -> 0 | AS18: =AR18/F18 -> 0 | AT18: =AS18-AP18 -> 0 | AX18: =AW18/F18 -> 0 | AY18: =AX18-AU18 -> 0 | BC18: =BB18/F18 -> 0 | BH18: =BG18/F18 -> 0 | BI18: =BH18-BE18 -> 0 | BM18: =BL18/F18 -> 0 | BN18: =BM18-BJ18 -> 0 | BR18: =BQ18/F18 -> 0 | BS18: =BR18-BO18 -> 0 | BX18: =BW18-BT18 -> 0 | CB18: =CA18/F18 -> 0 | CC18: =CB18-BY18 -> 0 | CG18: =CF18/F18 -> 0 | CH18: =CG18-CD18 -> 0 | CL18: =CK18/F18 -> 0 | CM18: =CL18-CI18 -> 0 | CR18: =ROUND(CQ18-CN18,2) -> 0 | CW18: =CV18-CS18 -> 0 | DA18: =ROUND(CZ18/F18,2) -> 0 | DB18: =ROUND(DA18-CX18,2) -> 0 | DF18: =DE18/F18 -> 0 | DG18: =DC18-DF18 -> 0 | DK18: =DJ18/F18 -> 0 | DL18: =DK18-DH18 -> 0 | DP18: =DO18/F18 -> 0 | DQ18: =DP18-DM18 -> 0 | DU18: =DT18/F18 -> 0 | DV18: =DU18-DR18 -> 0 | DZ18: =ROUND(DY18/F18,2) -> 0 | EA18: =ROUND(DZ18-DW18,2) -> 0 | EF18: =EE18-EB18 -> 0 | EJ18: =ROUND(EI18/F18,2) -> 0 | EK18: =ROUND(EJ18-EG18,2) -> 0 | EO18: =ROUND(EN18/F18,2) -> 0 | EP18: =ROUND(EO18-EL18,2) -> 0 | ET18: =ROUND(ES18/F18,2) -> 0 | EU18: =ROUND(ET18-EQ18,2) -> 0 | EY18: =ROUND(EX18/F18,2) -> 0 | EZ18: =ROUND(EY18-EV18,2) -> 0 | FD18: =ROUND(FC18/F18,2) -> 0 | FE18: =ROUND(FD18-FA18,2) -> 0 | FI18: =FH18/F18 -> 0 | FJ18: =ROUND(FI18-FF18,2) -> 0 | FN18: =ROUND(FM18/F18,2) -> 0 | FO18: =ROUND(FN18-FK18,2) -> 0 | FS18: =ROUND(FR18/F18,2) -> 0 | FT18: =FS18-FP18 -> 0 | FX18: =ROUND(FW18/F18,2) -> 0 | FY18: =FX18-FU18 -> 0 | GC18: =ROUND(GB18/F18,2) -> 0 | GD18: =GC18-FZ18 -> 0 | GH18: =GG18/F18 -> 0 | GI18: =GH18-GE18 -> 0 | GM18: =GL18/F18 -> 0 | GN18: =GM18-GJ18 -> 0 | GR18: =GQ18/F18 -> 0 | GS18: =GR18-GO18 -> 0 | GW18: =ROUND(GV18/F18,2) -> 0 | GX18: =GW18-GT18 -> 0
B19: 1300 | E19: 工程施工 | F19: 0.09 | G19: =SUM(M19,P19:Q19,V19,AA19,AF19,AK19,AP19,AU19,AZ19,BE19,BJ19,BO19,BT19,BY19,CD19,CI19,CN19,CS19,CX19,DC19,DH19,DM19,DR19,DW19,EB19,EG19,EL19,EQ19,EV19,FA19,FF19,FK19,FP19,FU19,FZ19,GE19,GJ19,GO19,GT19) -> 1.3928778e+08 | H19: =SUM(N19,R19,W19,AB19,AG19,AL19,AQ19,AV19,BA19,BF19,BK19,BP19,BU19,BZ19,CE19,CJ19,CO19,CT19,CY19,DD19,DI19,DN19,DS19,DX19,EC19,EH19,EM19,ER19,EW19,FB19,FG19,FL19,FQ19,FV19,GA19,GF19,GK19,GP19,GU19) -> 1.3928778e+08 | I19: =SUM(O19,S19,X19,AC19,AH19,AM19,AR19,AW19,BB19,BG19,BL19,BQ19,BV19,CA19,CF19,CK19,CP19,CU19,CZ19,DE19,DJ19,DO19,DT19,DY19,ED19,EI19,EN19,ES19,EX19,FC19,FH19,FM19,FR19,FW19,GB19,GG19,GL19,GQ19,GV19) -> 12535900 | J19: =I19/F19 -> 1.3928778e+08 | M19: 1.3928778e+08 | N19: 1.0243734e+08 | O19: 12535900 | T19: 0 | U19: =T19-Q19 -> 0 | Z19: =Y19-V19 -> 0 | AB19: 36850436 | AD19: =AC19/F19 -> 0 | AE19: =AD19-AA19 -> 0 | AI19: =AH19/F19 -> 0 | AJ19: =AI19-AF19 -> 0 | AN19: =AM19/F19 -> 0 | AO19: =AN19-AK19 -> 0 | AS19: =AR19/F19 -> 0 | AT19: =AS19-AP19 -> 0 | AX19: =AW19/F19 -> 0 | AY19: =AX19-AU19 -> 0 | BC19: =BB19/F19 -> 0 | BH19: =BG19/F19 -> 0 | BI19: =BH19-BE19 -> 0 | BM19: =BL19/F19 -> 0 | BN19: =BM19-BJ19 -> 0 | BR19: =BQ19/F19 -> 0 | BS19: =BR19-BO19 -> 0 | BX19: =BW19-BT19 -> 0 | CB19: =CA19/F19 -> 0 | CC19: =CB19-BY19 -> 0 | CG19: =CF19/F19 -> 0 | CH19: =CG19-CD19 -> 0 | CL19: =CK19/F19 -> 0 | CM19: =CL19-CI19 -> 0 | CR19: =ROUND(CQ19-CN19,2) -> 0 | CW19: =CV19-CS19 -> 0 | DA19: =ROUND(CZ19/F19,2) -> 0 | DB19: =ROUND(DA19-CX19,2) -> 0 | DF19: =DE19/F19 -> 0 | DG19: =DC19-DF19 -> 0 | DK19: =DJ19/F19 -> 0 | DL19: =DK19-DH19 -> 0 | DP19: =DO19/F19 -> 0 | DQ19: =DP19-DM19 -> 0 | DU19: =DT19/F19 -> 0 | DV19: =DU19-DR19 -> 0 | DZ19: =ROUND(DY19/F19,2) -> 0 | EA19: =ROUND(DZ19-DW19,2) -> 0 | EF19: =EE19-EB19 -> 0 | EJ19: =ROUND(EI19/F19,2) -> 0 | EK19: =ROUND(EJ19-EG19,2) -> 0 | EO19: =ROUND(EN19/F19,2) -> 0 | EP19: =ROUND(EO19-EL19,2) -> 0 | ET19: =ROUND(ES19/F19,2) -> 0 | EU19: =ROUND(ET19-EQ19,2) -> 0 | EY19: =ROUND(EX19/F19,2) -> 0 | EZ19: =ROUND(EY19-EV19,2) -> 0 | FD19: =ROUND(FC19/F19,2) -> 0 | FE19: =ROUND(FD19-FA19,2) -> 0 | FI19: =FH19/F19 -> 0 | FJ19: =ROUND(FI19-FF19,2) -> 0 | FN19: =ROUND(FM19/F19,2) -> 0 | FO19: =ROUND(FN19-FK19,2) -> 0 | FS19: =ROUND(FR19/F19,2) -> 0 | FT19: =FS19-FP19 -> 0 | FX19: =ROUND(FW19/F19,2) -> 0 | FY19: =FX19-FU19 -> 0 | GC19: =ROUND(GB19/F19,2) -> 0 | GD19: =GC19-FZ19 -> 0 | GH19: =GG19/F19 -> 0 | GI19: =GH19-GE19 -> 0 | GM19: =GL19/F19 -> 0 | GN19: =GM19-GJ19 -> 0 | GR19: =GQ19/F19 -> 0 | GS19: =GR19-GO19 -> 0 | GW19: =ROUND(GV19/F19,2) -> 0 | GX19: =GW19-GT19 -> 0
B20: 1300 | E20: 设计咨询 | F20: 0.06 | G20: =SUM(M20,P20:Q20,V20,AA20,AF20,AK20,AP20,AU20,AZ20,BE20,BJ20,BO20,BT20,BY20,CD20,CI20,CN20,CS20,CX20,DC20,DH20,DM20,DR20,DW20,EB20,EG20,EL20,EQ20,EV20,FA20,FF20,FK20,FP20,FU20,FZ20,GE20,GJ20,GO20,GT20) -> 5274214.8 | H20: =SUM(N20,R20,W20,AB20,AG20,AL20,AQ20,AV20,BA20,BF20,BK20,BP20,BU20,BZ20,CE20,CJ20,CO20,CT20,CY20,DD20,DI20,DN20,DS20,DX20,EC20,EH20,EM20,ER20,EW20,FB20,FG20,FL20,FQ20,FV20,GA20,GF20,GK20,GP20,GU20) -> 5204278.3 | I20: =SUM(O20,S20,X20,AC20,AH20,AM20,AR20,AW20,BB20,BG20,BL20,BQ20,BV20,CA20,CF20,CK20,CP20,CU20,CZ20,DE20,DJ20,DO20,DT20,DY20,ED20,EI20,EN20,ES20,EX20,FC20,FH20,FM20,FR20,FW20,GB20,GG20,GL20,GQ20,GV20) -> 316452.89 | J20: =I20/F20 -> 5274214.8 | M20: 5204278.3 | N20: 5204278.3 | O20: 312256.7 | T20: 0 | U20: =T20-Q20 -> 0 | Z20: =Y20-V20 -> 0 | AD20: =AC20/F20 -> 0 | AE20: =AD20-AA20 -> 0 | AI20: =AH20/F20 -> 0 | AJ20: =AI20-AF20 -> 0 | AN20: =AM20/F20 -> 0 | AO20: =AN20-AK20 -> 0 | AS20: =AR20/F20 -> 0 | AT20: =AS20-AP20 -> 0 | AU20: 21956.51 | AW20: 1317.3905 | AX20: =AW20/F20 -> 21956.508 | AY20: =AX20-AU20 -> -0.002 | AZ20: 23748.84 | BB20: 1424.93 | BC20: =BB20/F20 -> 23748.833 | BE20: 24231.13 | BG20: 1453.87 | BH20: =BG20/F20 -> 24231.167 | BI20: =BH20-BE20 -> 0.036666667 | BM20: =BL20/F20 -> 0 | BN20: =BM20-BJ20 -> 0 | BQ20: 0 | BR20: =BQ20/F20 -> 0 | BS20: =BR20-BO20 -> 0 | BX20: =BW20-BT20 -> 0 | CB20: =CA20/F20 -> 0 | CC20: =CB20-BY20 -> 0 | CG20: =CF20/F20 -> 0 | CH20: =CG20-CD20 -> 0 | CL20: =CK20/F20 -> 0 | CM20: =CL20-CI20 -> 0 | CR20: =ROUND(CQ20-CN20,2) -> 0 | CW20: =CV20-CS20 -> 0 | DA20: =ROUND(CZ20/F20,2) -> 0 | DB20: =ROUND(DA20-CX20,2) -> 0 | DF20: =DE20/F20 -> 0 | DG20: =DC20-DF20 -> 0 | DK20: =DJ20/F20 -> 0 | DL20: =DK20-DH20 -> 0 | DP20: =DO20/F20 -> 0 | DQ20: =DP20-DM20 -> 0 | DU20: =DT20/F20 -> 0 | DV20: =DU20-DR20 -> 0 | DZ20: =ROUND(DY20/F20,2) -> 0 | EA20: =ROUND(DZ20-DW20,2) -> 0 | EF20: =EE20-EB20 -> 0 | EJ20: =ROUND(EI20/F20,2) -> 0 | EK20: =ROUND(EJ20-EG20,2) -> 0 | EO20: =ROUND(EN20/F20,2) -> 0 | EP20: =ROUND(EO20-EL20,2) -> 0 | ET20: =ROUND(ES20/F20,2) -> 0 | EU20: =ROUND(ET20-EQ20,2) -> 0 | EY20: =ROUND(EX20/F20,2) -> 0 | EZ20: =ROUND(EY20-EV20,2) -> 0 | FD20: =ROUND(FC20/F20,2) -> 0 | FE20: =ROUND(FD20-FA20,2) -> 0 | FI20: =FH20/F20 -> 0 | FJ20: =ROUND(FI20-FF20,2) -> 0 | FN20: =ROUND(FM20/F20,2) -> 0 | FO20: =ROUND(FN20-FK20,2) -> 0 | FS20: =ROUND(FR20/F20,2) -> 0 | FT20: =FS20-FP20 -> 0 | FX20: =ROUND(FW20/F20,2) -> 0 | FY20: =FX20-FU20 -> 0 | GC20: =ROUND(GB20/F20,2) -> 0 | GD20: =GC20-FZ20 -> 0 | GH20: =GG20/F20 -> 0 | GI20: =GH20-GE20 -> 0 | GM20: =GL20/F20 -> 0 | GN20: =GM20-GJ20 -> 0 | GR20: =GQ20/F20 -> 0 | GS20: =GR20-GO20 -> 0 | GW20: =ROUND(GV20/F20,2) -> 0 | GX20: =GW20-GT20 -> 0
B21: 1300 | D21: 1300（牟平二期） | E21: 商品销售 | F21: 0.13 | G21: =SUM(M21,P21:Q21,V21,AA21,AF21,AK21,AP21,AU21,AZ21,BE21,BJ21,BO21,BT21,BY21,CD21,CI21,CN21,CS21,CX21,DC21,DH21,DM21,DR21,DW21,EB21,EG21,EL21,EQ21,EV21,FA21,FF21,FK21,FP21,FU21,FZ21,GE21,GJ21,GO21,GT21) -> 83523104 | H21: =SUM(N21,R21,W21,AB21,AG21,AL21,AQ21,AV21,BA21,BF21,BK21,BP21,BU21,BZ21,CE21,CJ21,CO21,CT21,CY21,DD21,DI21,DN21,DS21,DX21,EC21,EH21,EM21,ER21,EW21,FB21,FG21,FL21,FQ21,FV21,GA21,GF21,GK21,GP21,GU21) -> 84330789 | I21: =SUM(O21,S21,X21,AC21,AH21,AM21,AR21,AW21,BB21,BG21,BL21,BQ21,BV21,CA21,CF21,CK21,CP21,CU21,CZ21,DE21,DJ21,DO21,DT21,DY21,ED21,EI21,EN21,ES21,EX21,FC21,FH21,FM21,FR21,FW21,GB21,GG21,GL21,GQ21,GV21) -> 10970804 | J21: =I21/F21 -> 84390798 | M21: 83523104 | N21: 84330789 | O21: 10970804 | T21: 0 | U21: =T21-Q21 -> 0 | Z21: =Y21-V21 -> 0 | AD21: =AC21/F21 -> 0 | AE21: =AD21-AA21 -> 0 | AI21: =AH21/F21 -> 0 | AJ21: =AI21-AF21 -> 0 | AN21: =AM21/F21 -> 0 | AO21: =AN21-AK21 -> 0 | AS21: =AR21/F21 -> 0 | AT21: =AS21-AP21 -> 0 | AX21: =AW21/F21 -> 0 | AY21: =AX21-AU21 -> 0 | BC21: =BB21/F21 -> 0 | BH21: =BG21/F21 -> 0 | BI21: =BH21-BE21 -> 0 | BM21: =BL21/F21 -> 0 | BN21: =BM21-BJ21 -> 0 | BR21: =BQ21/F21 -> 0 | BS21: =BR21-BO21 -> 0 | BX21: =BW21-BT21 -> 0 | CB21: =CA21/F21 -> 0 | CC21: =CB21-BY21 -> 0 | CG21: =CF21/F21 -> 0 | CH21: =CG21-CD21 -> 0 | CL21: =CK21/F21 -> 0 | CM21: =CL21-CI21 -> 0 | CR21: =ROUND(CQ21-CN21,2) -> 0 | CW21: =CV21-CS21 -> 0 | DA21: =ROUND(CZ21/F21,2) -> 0 | DB21: =ROUND(DA21-CX21,2) -> 0 | DF21: =DE21/F21 -> 0 | DG21: =DC21-DF21 -> 0 | DK21: =DJ21/F21 -> 0 | DL21: =DK21-DH21 -> 0 | DP21: =DO21/F21 -> 0 | DQ21: =DP21-DM21 -> 0 | DU21: =DT21/F21 -> 0 | DV21: =DU21-DR21 -> 0 | DZ21: =ROUND(DY21/F21,2) -> 0 | EA21: =ROUND(DZ21-DW21,2) -> 0 | EF21: =EE21-EB21 -> 0 | EJ21: =ROUND(EI21/F21,2) -> 0 | EK21: =ROUND(EJ21-EG21,2) -> 0 | EO21: =ROUND(EN21/F21,2) -> 0 | EP21: =ROUND(EO21-EL21,2) -> 0 | ET21: =ROUND(ES21/F21,2) -> 0 | EU21: =ROUND(ET21-EQ21,2) -> 0 | EY21: =ROUND(EX21/F21,2) -> 0 | EZ21: =ROUND(EY21-EV21,2) -> 0 | FD21: =ROUND(FC21/F21,2) -> 0 | FE21: =ROUND(FD21-FA21,2) -> 0 | FI21: =FH21/F21 -> 0 | FJ21: =ROUND(FI21-FF21,2) -> 0 | FN21: =ROUND(FM21/F21,2) -> 0 | FO21: =ROUND(FN21-FK21,2) -> 0 | FS21: =ROUND(FR21/F21,2) -> 0 | FT21: =FS21-FP21 -> 0 | FX21: =ROUND(FW21/F21,2) -> 0 | FY21: =FX21-FU21 -> 0 | GC21: =ROUND(GB21/F21,2) -> 0 | GD21: =GC21-FZ21 -> 0 | GH21: =GG21/F21 -> 0 | GI21: =GH21-GE21 -> 0 | GM21: =GL21/F21 -> 0 | GN21: =GM21-GJ21 -> 0 | GR21: =GQ21/F21 -> 0 | GS21: =GR21-GO21 -> 0 | GW21: =ROUND(GV21/F21,2) -> 0 | GX21: =GW21-GT21 -> 0
B22: 1300 | E22: 工程施工 | F22: 0.09 | G22: =SUM(M22,P22:Q22,V22,AA22,AF22,AK22,AP22,AU22,AZ22,BE22,BJ22,BO22,BT22,BY22,CD22,CI22,CN22,CS22,CX22,DC22,DH22,DM22,DR22,DW22,EB22,EG22,EL22,EQ22,EV22,FA22,FF22,FK22,FP22,FU22,FZ22,GE22,GJ22,GO22,GT22) -> 1.1658137e+08 | H22: =SUM(N22,R22,W22,AB22,AG22,AL22,AQ22,AV22,BA22,BF22,BK22,BP22,BU22,BZ22,CE22,CJ22,CO22,CT22,CY22,DD22,DI22,DN22,DS22,DX22,EC22,EH22,EM22,ER22,EW22,FB22,FG22,FL22,FQ22,FV22,GA22,GF22,GK22,GP22,GU22) -> 1.1658137e+08 | I22: =SUM(O22,S22,X22,AC22,AH22,AM22,AR22,AW22,BB22,BG22,BL22,BQ22,BV22,CA22,CF22,CK22,CP22,CU22,CZ22,DE22,DJ22,DO22,DT22,DY22,ED22,EI22,EN22,ES22,EX22,FC22,FH22,FM22,FR22,FW22,GB22,GG22,GL22,GQ22,GV22) -> 10492323 | J22: =I22/F22 -> 1.1658137e+08 | M22: 1.1621813e+08 | N22: 44036697 | O22: 10459632 | P22: 363240.66 | T22: 0 | U22: =T22-Q22 -> 0 | Z22: =Y22-V22 -> 0 | AB22: 72544673 | AC22: =P22*F22 -> 32691.659 | AD22: =AC22/F22 -> 363240.66 | AE22: =AD22-AA22 -> 363240.66 | AI22: =AH22/F22 -> 0 | AJ22: =AI22-AF22 -> 0 | AN22: =AM22/F22 -> 0 | AO22: =AN22-AK22 -> 0 | AS22: =AR22/F22 -> 0 | AT22: =AS22-AP22 -> 0 | AX22: =AW22/F22 -> 0 | AY22: =AX22-AU22 -> 0 | BC22: =BB22/F22 -> 0 | BH22: =BG22/F22 -> 0 | BI22: =BH22-BE22 -> 0 | BM22: =BL22/F22 -> 0 | BN22: =BM22-BJ22 -> 0 | BR22: =BQ22/F22 -> 0 | BS22: =BR22-BO22 -> 0 | BX22: =BW22-BT22 -> 0 | CB22: =CA22/F22 -> 0 | CC22: =CB22-BY22 -> 0 | CG22: =CF22/F22 -> 0 | CH22: =CG22-CD22 -> 0 | CL22: =CK22/F22 -> 0 | CM22: =CL22-CI22 -> 0 | CR22: =ROUND(CQ22-CN22,2) -> 0 | CW22: =CV22-CS22 -> 0 | DA22: =ROUND(CZ22/F22,2) -> 0 | DB22: =ROUND(DA22-CX22,2) -> 0 | DF22: =DE22/F22 -> 0 | DG22: =DC22-DF22 -> 0 | DK22: =DJ22/F22 -> 0 | DL22: =DK22-DH22 -> 0 | DP22: =DO22/F22 -> 0 | DQ22: =DP22-DM22 -> 0 | DU22: =DT22/F22 -> 0 | DV22: =DU22-DR22 -> 0 | DZ22: =ROUND(DY22/F22,2) -> 0 | EA22: =ROUND(DZ22-DW22,2) -> 0 | EF22: =EE22-EB22 -> 0 | EJ22: =ROUND(EI22/F22,2) -> 0 | EK22: =ROUND(EJ22-EG22,2) -> 0 | EO22: =ROUND(EN22/F22,2) -> 0 | EP22: =ROUND(EO22-EL22,2) -> 0 | ET22: =ROUND(ES22/F22,2) -> 0 | EU22: =ROUND(ET22-EQ22,2) -> 0 | EY22: =ROUND(EX22/F22,2) -> 0 | EZ22: =ROUND(EY22-EV22,2) -> 0 | FD22: =ROUND(FC22/F22,2) -> 0 | FE22: =ROUND(FD22-FA22,2) -> 0 | FI22: =FH22/F22 -> 0 | FJ22: =ROUND(FI22-FF22,2) -> 0 | FN22: =ROUND(FM22/F22,2) -> 0 | FO22: =ROUND(FN22-FK22,2) -> 0 | FS22: =ROUND(FR22/F22,2) -> 0 | FT22: =FS22-FP22 -> 0 | FX22: =ROUND(FW22/F22,2) -> 0 | FY22: =FX22-FU22 -> 0 | GC22: =ROUND(GB22/F22,2) -> 0 | GD22: =GC22-FZ22 -> 0 | GH22: =GG22/F22 -> 0 | GI22: =GH22-GE22 -> 0 | GM22: =GL22/F22 -> 0 | GN22: =GM22-GJ22 -> 0 | GR22: =GQ22/F22 -> 0 | GS22: =GR22-GO22 -> 0 | GW22: =ROUND(GV22/F22,2) -> 0 | GX22: =GW22-GT22 -> 0
B23: 1300 | E23: 设计咨询 | F23: 0.06 | G23: =SUM(M23,P23:Q23,V23,AA23,AF23,AK23,AP23,AU23,AZ23,BE23,BJ23,BO23,BT23,BY23,CD23,CI23,CN23,CS23,CX23,DC23,DH23,DM23,DR23,DW23,EB23,EG23,EL23,EQ23,EV23,FA23,FF23,FK23,FP23,FU23,FZ23,GE23,GJ23,GO23,GT23) -> 17136198 | H23: =SUM(N23,R23,W23,AB23,AG23,AL23,AQ23,AV23,BA23,BF23,BK23,BP23,BU23,BZ23,CE23,CJ23,CO23,CT23,CY23,DD23,DI23,DN23,DS23,DX23,EC23,EH23,EM23,ER23,EW23,FB23,FG23,FL23,FQ23,FV23,GA23,GF23,GK23,GP23,GU23) -> 17066261 | I23: =SUM(O23,S23,X23,AC23,AH23,AM23,AR23,AW23,BB23,BG23,BL23,BQ23,BV23,CA23,CF23,CK23,CP23,CU23,CZ23,DE23,DJ23,DO23,DT23,DY23,ED23,EI23,EN23,ES23,EX23,FC23,FH23,FM23,FR23,FW23,GB23,GG23,GL23,GQ23,GV23) -> 1028171.9 | J23: =I23/F23 -> 17136198 | M23: 17066261 | N23: 0 | O23: 1023975.7 | T23: 0 | U23: =T23-Q23 -> 0 | Z23: =Y23-V23 -> 0 | AB23: 17066261 | AD23: =AC23/F23 -> 0 | AE23: =AD23-AA23 -> 0 | AI23: =AH23/F23 -> 0 | AJ23: =AI23-AF23 -> 0 | AN23: =AM23/F23 -> 0 | AO23: =AN23-AK23 -> 0 | AS23: =AR23/F23 -> 0 | AT23: =AS23-AP23 -> 0 | AU23: 21956.51 | AW23: 1317.39 | AX23: =AW23/F23 -> 21956.5 | AY23: =AX23-AU23 -> -0.01 | AZ23: 23748.84 | BB23: 1424.93 | BC23: =BB23/F23 -> 23748.833 | BE23: 24231.13 | BG23: 1453.87 | BH23: =BG23/F23 -> 24231.167 | BI23: =BH23-BE23 -> 0.036666667 | BM23: =BL23/F23 -> 0 | BN23: =BM23-BJ23 -> 0 | BQ23: 0 | BR23: =BQ23/F23 -> 0 | BS23: =BR23-BO23 -> 0 | BX23: =BW23-BT23 -> 0 | CB23: =CA23/F23 -> 0 | CC23: =CB23-BY23 -> 0 | CG23: =CF23/F23 -> 0 | CH23: =CG23-CD23 -> 0 | CL23: =CK23/F23 -> 0 | CM23: =CL23-CI23 -> 0 | CR23: =ROUND(CQ23-CN23,2) -> 0 | CW23: =CV23-CS23 -> 0 | DA23: =ROUND(CZ23/F23,2) -> 0 | DB23: =ROUND(DA23-CX23,2) -> 0 | DF23: =DE23/F23 -> 0 | DG23: =DC23-DF23 -> 0 | DK23: =DJ23/F23 -> 0 | DL23: =DK23-DH23 -> 0 | DP23: =DO23/F23 -> 0 | DQ23: =DP23-DM23 -> 0 | DU23: =DT23/F23 -> 0 | DV23: =DU23-DR23 -> 0 | DZ23: =ROUND(DY23/F23,2) -> 0 | EA23: =ROUND(DZ23-DW23,2) -> 0 | EF23: =EE23-EB23 -> 0 | EJ23: =ROUND(EI23/F23,2) -> 0 | EK23: =ROUND(EJ23-EG23,2) -> 0 | EO23: =ROUND(EN23/F23,2) -> 0 | EP23: =ROUND(EO23-EL23,2) -> 0 | ET23: =ROUND(ES23/F23,2) -> 0 | EU23: =ROUND(ET23-EQ23,2) -> 0 | EY23: =ROUND(EX23/F23,2) -> 0 | EZ23: =ROUND(EY23-EV23,2) -> 0 | FD23: =ROUND(FC23/F23,2) -> 0 | FE23: =ROUND(FD23-FA23,2) -> 0 | FI23: =FH23/F23 -> 0 | FJ23: =ROUND(FI23-FF23,2) -> 0 | FN23: =ROUND(FM23/F23,2) -> 0 | FO23: =ROUND(FN23-FK23,2) -> 0 | FS23: =ROUND(FR23/F23,2) -> 0 | FT23: =FS23-FP23 -> 0 | FX23: =ROUND(FW23/F23,2) -> 0 | FY23: =FX23-FU23 -> 0 | GC23: =ROUND(GB23/F23,2) -> 0 | GD23: =GC23-FZ23 -> 0 | GH23: =GG23/F23 -> 0 | GI23: =GH23-GE23 -> 0 | GM23: =GL23/F23 -> 0 | GN23: =GM23-GJ23 -> 0 | GR23: =GQ23/F23 -> 0 | GS23: =GR23-GO23 -> 0 | GW23: =ROUND(GV23/F23,2) -> 0 | GX23: =GW23-GT23 -> 0
B24: 2310 | D24: 2310（吉县一期） | E24: 商品销售 | F24: 0.13 | G24: =SUM(M24,P24:Q24,V24,AA24,AF24,AK24,AP24,AU24,AZ24,BE24,BJ24,BO24,BT24,BY24,CD24,CI24,CN24,CS24,CX24,DC24,DH24,DM24,DR24,DW24,EB24,EG24,EL24,EQ24,EV24,FA24,FF24,FK24,FP24,FU24,FZ24,GE24,GJ24,GO24,GT24) -> 59837204 | H24: =SUM(N24,R24,W24,AB24,AG24,AL24,AQ24,AV24,BA24,BF24,BK24,BP24,BU24,BZ24,CE24,CJ24,CO24,CT24,CY24,DD24,DI24,DN24,DS24,DX24,EC24,EH24,EM24,ER24,EW24,FB24,FG24,FL24,FQ24,FV24,GA24,GF24,GK24,GP24,GU24) -> 59837204 | I24: =SUM(O24,S24,X24,AC24,AH24,AM24,AR24,AW24,BB24,BG24,BL24,BQ24,BV24,CA24,CF24,CK24,CP24,CU24,CZ24,DE24,DJ24,DO24,DT24,DY24,ED24,EI24,EN24,ES24,EX24,FC24,FH24,FM24,FR24,FW24,GB24,GG24,GL24,GQ24,GV24) -> 7778836.5 | J24: =I24/F24 -> 59837204 | K24: =I24/F24-H24 -> 0.029999994 | L24: =J24-G24 -> 0.0092264935 | M24: 59837204 | N24: 40599469 | O24: 7778836.5 | T24: 0 | U24: =T24-Q24 -> 0 | Z24: =Y24-V24 -> 0 | AB24: 19237734 | AD24: =AC24/F24 -> 0 | AE24: =AD24-AA24 -> 0 | AI24: =AH24/F24 -> 0 | AJ24: =AI24-AF24 -> 0 | AN24: =AM24/F24 -> 0 | AO24: =AN24-AK24 -> 0 | AS24: =AR24/F24 -> 0 | AT24: =AS24-AP24 -> 0 | AX24: =AW24/F24 -> 0 | AY24: =AX24-AU24 -> 0 | BC24: =BB24/F24 -> 0 | BH24: =BG24/F24 -> 0 | BI24: =BH24-BE24 -> 0 | BM24: =BL24/F24 -> 0 | BN24: =BM24-BJ24 -> 0 | BR24: =BQ24/F24 -> 0 | BS24: =BR24-BO24 -> 0 | BX24: =BW24-BT24 -> 0 | CB24: =CA24/F24 -> 0 | CC24: =CB24-BY24 -> 0 | CG24: =CF24/F24 -> 0 | CH24: =CG24-CD24 -> 0 | CL24: =CK24/F24 -> 0 | CM24: =CL24-CI24 -> 0 | CR24: =ROUND(CQ24-CN24,2) -> 0 | CW24: =CV24-CS24 -> 0 | DA24: =ROUND(CZ24/F24,2) -> 0 | DB24: =ROUND(DA24-CX24,2) -> 0 | DF24: =DE24/F24 -> 0 | DG24: =DC24-DF24 -> 0 | DK24: =DJ24/F24 -> 0 | DL24: =DK24-DH24 -> 0 | DP24: =DO24/F24 -> 0 | DQ24: =DP24-DM24 -> 0 | DU24: =DT24/F24 -> 0 | DV24: =DU24-DR24 -> 0 | DZ24: =ROUND(DY24/F24,2) -> 0 | EA24: =ROUND(DZ24-DW24,2) -> 0 | EF24: =EE24-EB24 -> 0 | EJ24: =ROUND(EI24/F24,2) -> 0 | EK24: =ROUND(EJ24-EG24,2) -> 0 | EO24: =ROUND(EN24/F24,2) -> 0 | EP24: =ROUND(EO24-EL24,2) -> 0 | ET24: =ROUND(ES24/F24,2) -> 0 | EU24: =ROUND(ET24-EQ24,2) -> 0 | EY24: =ROUND(EX24/F24,2) -> 0 | EZ24: =ROUND(EY24-EV24,2) -> 0 | FD24: =ROUND(FC24/F24,2) -> 0 | FE24: =ROUND(FD24-FA24,2) -> 0 | FI24: =FH24/F24 -> 0 | FJ24: =ROUND(FI24-FF24,2) -> 0 | FN24: =ROUND(FM24/F24,2) -> 0 | FO24: =ROUND(FN24-FK24,2) -> 0 | FS24: =ROUND(FR24/F24,2) -> 0 | FT24: =FS24-FP24 -> 0 | FX24: =ROUND(FW24/F24,2) -> 0 | FY24: =FX24-FU24 -> 0 | GC24: =ROUND(GB24/F24,2) -> 0 | GD24: =GC24-FZ24 -> 0 | GH24: =GG24/F24 -> 0 | GI24: =GH24-GE24 -> 0 | GM24: =GL24/F24 -> 0 | GN24: =GM24-GJ24 -> 0 | GR24: =GQ24/F24 -> 0 | GS24: =GR24-GO24 -> 0 | GW24: =ROUND(GV24/F24,2) -> 0 | GX24: =GW24-GT24 -> 0
B25: 2310 | E25: 工程施工 | F25: 0.09 | G25: =SUM(M25,P25:Q25,V25,AA25,AF25,AK25,AP25,AU25,AZ25,BE25,BJ25,BO25,BT25,BY25,CD25,CI25,CN25,CS25,CX25,DC25,DH25,DM25,DR25,DW25,EB25,EG25,EL25,EQ25,EV25,FA25,FF25,FK25,FP25,FU25,FZ25,GE25,GJ25,GO25,GT25) -> 58740671 | H25: =SUM(N25,R25,W25,AB25,AG25,AL25,AQ25,AV25,BA25,BF25,BK25,BP25,BU25,BZ25,CE25,CJ25,CO25,CT25,CY25,DD25,DI25,DN25,DS25,DX25,EC25,EH25,EM25,ER25,EW25,FB25,FG25,FL25,FQ25,FV25,GA25,GF25,GK25,GP25,GU25) -> 58740671 | I25: =SUM(O25,S25,X25,AC25,AH25,AM25,AR25,AW25,BB25,BG25,BL25,BQ25,BV25,CA25,CF25,CK25,CP25,CU25,CZ25,DE25,DJ25,DO25,DT25,DY25,ED25,EI25,EN25,ES25,EX25,FC25,FH25,FM25,FR25,FW25,GB25,GG25,GL25,GQ25,GV25) -> 5286660.4 | J25: =I25/F25 -> 58740671 | K25: =I25/F25-H25 -> 0.016363665 | L25: =J25-G25 -> -0.0036363378 | M25: 58329011 | N25: 0 | O25: 5249611 | P25: =2562581.99-2150921.93 -> 411660.06 | T25: 0 | U25: =T25-Q25 -> 0 | X25: 230632.38 | Y25: =X25/F25 -> 2562582 | Z25: =Y25-V25 -> 2562582 | AB25: 60891593 | AD25: =AC25/F25 -> 0 | AE25: =AD25-AA25 -> 0 | AG25: -2150921.9 | AH25: =AG25*F25 -> -193582.97 | AI25: =AH25/F25 -> -2150921.9 | AJ25: =AI25-AF25 -> -2150921.9 | AN25: =AM25/F25 -> 0 | AO25: =AN25-AK25 -> 0 | AS25: =AR25/F25 -> 0 | AT25: =AS25-AP25 -> 0 | AX25: =AW25/F25 -> 0 | AY25: =AX25-AU25 -> 0 | BC25: =BB25/F25 -> 0 | BH25: =BG25/F25 -> 0 | BI25: =BH25-BE25 -> 0 | BM25: =BL25/F25 -> 0 | BN25: =BM25-BJ25 -> 0 | BR25: =BQ25/F25 -> 0 | BS25: =BR25-BO25 -> 0 | BX25: =BW25-BT25 -> 0 | CB25: =CA25/F25 -> 0 | CC25: =CB25-BY25 -> 0 | CG25: =CF25/F25 -> 0 | CH25: =CG25-CD25 -> 0 | CL25: =CK25/F25 -> 0 | CM25: =CL25-CI25 -> 0 | CR25: =ROUND(CQ25-CN25,2) -> 0 | CW25: =CV25-CS25 -> 0 | DA25: =ROUND(CZ25/F25,2) -> 0 | DB25: =ROUND(DA25-CX25,2) -> 0 | DF25: =DE25/F25 -> 0 | DG25: =DC25-DF25 -> 0 | DK25: =DJ25/F25 -> 0 | DL25: =DK25-DH25 -> 0 | DP25: =DO25/F25 -> 0 | DQ25: =DP25-DM25 -> 0 | DU25: =DT25/F25 -> 0 | DV25: =DU25-DR25 -> 0 | DZ25: =ROUND(DY25/F25,2) -> 0 | EA25: =ROUND(DZ25-DW25,2) -> 0 | EF25: =EE25-EB25 -> 0 | EJ25: =ROUND(EI25/F25,2) -> 0 | EK25: =ROUND(EJ25-EG25,2) -> 0 | EO25: =ROUND(EN25/F25,2) -> 0 | EP25: =ROUND(EO25-EL25,2) -> 0 | ET25: =ROUND(ES25/F25,2) -> 0 | EU25: =ROUND(ET25-EQ25,2) -> 0 | EY25: =ROUND(EX25/F25,2) -> 0 | EZ25: =ROUND(EY25-EV25,2) -> 0 | FD25: =ROUND(FC25/F25,2) -> 0 | FE25: =ROUND(FD25-FA25,2) -> 0 | FI25: =FH25/F25 -> 0 | FJ25: =ROUND(FI25-FF25,2) -> 0 | FN25: =ROUND(FM25/F25,2) -> 0 | FO25: =ROUND(FN25-FK25,2) -> 0 | FS25: =ROUND(FR25/F25,2) -> 0 | FT25: =FS25-FP25 -> 0 | FX25: =ROUND(FW25/F25,2) -> 0 | FY25: =FX25-FU25 -> 0 | GC25: =ROUND(GB25/F25,2) -> 0 | GD25: =GC25-FZ25 -> 0 | GH25: =GG25/F25 -> 0 | GI25: =GH25-GE25 -> 0 | GM25: =GL25/F25 -> 0 | GN25: =GM25-GJ25 -> 0 | GR25: =GQ25/F25 -> 0 | GS25: =GR25-GO25 -> 0 | GW25: =ROUND(GV25/F25,2) -> 0 | GX25: =GW25-GT25 -> 0
B26: 2310 | E26: 设计咨询 | F26: 0.06 | G26: =SUM(M26,P26:Q26,V26,AA26,AF26,AK26,AP26,AU26,AZ26,BE26,BJ26,BO26,BT26,BY26,CD26,CI26,CN26,CS26,CX26,DC26,DH26,DM26,DR26,DW26,EB26,EG26,EL26,EQ26,EV26,FA26,FF26,FK26,FP26,FU26,FZ26,GE26,GJ26,GO26,GT26) -> 43710.29 | H26: =SUM(N26,R26,W26,AB26,AG26,AL26,AQ26,AV26,BA26,BF26,BK26,BP26,BU26,BZ26,CE26,CJ26,CO26,CT26,CY26,DD26,DI26,DN26,DS26,DX26,EC26,EH26,EM26,ER26,EW26,FB26,FG26,FL26,FQ26,FV26,GA26,GF26,GK26,GP26,GU26) -> 43710.29 | I26: =SUM(O26,S26,X26,AC26,AH26,AM26,AR26,AW26,BB26,BG26,BL26,BQ26,BV26,CA26,CF26,CK26,CP26,CU26,CZ26,DE26,DJ26,DO26,DT26,DY26,ED26,EI26,EN26,ES26,EX26,FC26,FH26,FM26,FR26,FW26,GB26,GG26,GL26,GQ26,GV26) -> 2622.619 | J26: =I26/F26 -> 43710.317 | K26: =I26/F26-H26 -> 0.0275 | L26: =J26-G26 -> 0.0275 | T26: 0 | U26: =T26-Q26 -> 0 | Y26: =X26/F26 -> 0 | Z26: =Y26-V26 -> 0 | AD26: =AC26/F26 -> 0 | AE26: =AD26-AA26 -> 0 | AI26: =AH26/F26 -> 0 | AJ26: =AI26-AF26 -> 0 | AN26: =AM26/F26 -> 0 | AO26: =AN26-AK26 -> 0 | AS26: =AR26/F26 -> 0 | AT26: =AS26-AP26 -> 0 | AU26: 13722.82 | AW26: 823.36905 | AX26: =AW26/F26 -> 13722.817 | AY26: =AX26-AU26 -> -0.0025 | AZ26: 14843.02 | BB26: 890.58 | BC26: =BB26/F26 -> 14843 | BE26: 15144.45 | BG26: 908.67 | BH26: =BG26/F26 -> 15144.5 | BI26: =BH26-BE26 -> 0.05 | BK26: 43710.29 | BM26: =BL26/F26 -> 0 | BN26: =BM26-BJ26 -> 0 | BQ26: 0 | BR26: =BQ26/F26 -> 0 | BS26: =BR26-BO26 -> 0 | BX26: =BW26-BT26 -> 0 | CB26: =CA26/F26 -> 0 | CC26: =CB26-BY26 -> 0 | CG26: =CF26/F26 -> 0 | CH26: =CG26-CD26 -> 0 | CL26: =CK26/F26 -> 0 | CM26: =CL26-CI26 -> 0 | CR26: =ROUND(CQ26-CN26,2) -> 0 | CW26: =CV26-CS26 -> 0 | DA26: =ROUND(CZ26/F26,2) -> 0 | DB26: =ROUND(DA26-CX26,2) -> 0 | DF26: =DE26/F26 -> 0 | DG26: =DC26-DF26 -> 0 | DK26: =DJ26/F26 -> 0 | DL26: =DK26-DH26 -> 0 | DP26: =DO26/F26 -> 0 | DQ26: =DP26-DM26 -> 0 | DU26: =DT26/F26 -> 0 | DV26: =DU26-DR26 -> 0 | DZ26: =ROUND(DY26/F26,2) -> 0 | EA26: =ROUND(DZ26-DW26,2) -> 0 | EF26: =EE26-EB26 -> 0 | EJ26: =ROUND(EI26/F26,2) -> 0 | EK26: =ROUND(EJ26-EG26,2) -> 0 | EO26: =ROUND(EN26/F26,2) -> 0 | EP26: =ROUND(EO26-EL26,2) -> 0 | ET26: =ROUND(ES26/F26,2) -> 0 | EU26: =ROUND(ET26-EQ26,2) -> 0 | EY26: =ROUND(EX26/F26,2) -> 0 | EZ26: =ROUND(EY26-EV26,2) -> 0 | FD26: =ROUND(FC26/F26,2) -> 0 | FE26: =ROUND(FD26-FA26,2) -> 0 | FI26: =FH26/F26 -> 0 | FJ26: =ROUND(FI26-FF26,2) -> 0 | FN26: =ROUND(FM26/F26,2) -> 0 | FO26: =ROUND(FN26-FK26,2) -> 0 | FS26: =ROUND(FR26/F26,2) -> 0 | FT26: =FS26-FP26 -> 0 | FX26: =ROUND(FW26/F26,2) -> 0 | FY26: =FX26-FU26 -> 0 | GC26: =ROUND(GB26/F26,2) -> 0 | GD26: =GC26-FZ26 -> 0 | GH26: =GG26/F26 -> 0 | GI26: =GH26-GE26 -> 0 | GM26: =GL26/F26 -> 0 | GN26: =GM26-GJ26 -> 0 | GR26: =GQ26/F26 -> 0 | GS26: =GR26-GO26 -> 0 | GW26: =ROUND(GV26/F26,2) -> 0 | GX26: =GW26-GT26 -> 0
B27: 2320 | D27: 2320（EPC） | E27: 商品销售 | F27: 0.13 | G27: =SUM(M27,P27:Q27,V27,AA27,AF27,AK27,AP27,AU27,AZ27,BE27,BJ27,BO27,BT27,BY27,CD27,CI27,CN27,CS27,CX27,DC27,DH27,DM27,DR27,DW27,EB27,EG27,EL27,EQ27,EV27,FA27,FF27,FK27,FP27,FU27,FZ27,GE27,GJ27,GO27,GT27) -> 21603594 | H27: =SUM(N27,R27,W27,AB27,AG27,AL27,AQ27,AV27,BA27,BF27,BK27,BP27,BU27,BZ27,CE27,CJ27,CO27,CT27,CY27,DD27,DI27,DN27,DS27,DX27,EC27,EH27,EM27,ER27,EW27,FB27,FG27,FL27,FQ27,FV27,GA27,GF27,GK27,GP27,GU27) -> 21603594 | I27: =SUM(O27,S27,X27,AC27,AH27,AM27,AR27,AW27,BB27,BG27,BL27,BQ27,BV27,CA27,CF27,CK27,CP27,CU27,CZ27,DE27,DJ27,DO27,DT27,DY27,ED27,EI27,EN27,ES27,EX27,FC27,FH27,FM27,FR27,FW27,GB27,GG27,GL27,GQ27,GV27) -> 2808467.2 | J27: =I27/F27 -> 21603594 | K27: =I27/F27-H27 -> 0.22076923 | L27: =J27-G27 -> 0.22076923 | M27: 21603594 | N27: 21603594 | O27: 2808467.2 | T27: 0 | U27: =T27-Q27 -> 0 | Y27: =X27/F27 -> 0 | Z27: =Y27-V27 -> 0 | AD27: =AC27/F27 -> 0 | AE27: =AD27-AA27 -> 0 | AI27: =AH27/F27 -> 0 | AJ27: =AI27-AF27 -> 0 | AN27: =AM27/F27 -> 0 | AO27: =AN27-AK27 -> 0 | AS27: =AR27/F27 -> 0 | AT27: =AS27-AP27 -> 0 | AX27: =AW27/F27 -> 0 | AY27: =AX27-AU27 -> 0 | BC27: =BB27/F27 -> 0 | BH27: =BG27/F27 -> 0 | BI27: =BH27-BE27 -> 0 | BM27: =BL27/F27 -> 0 | BN27: =BM27-BJ27 -> 0 | BR27: =BQ27/F27 -> 0 | BS27: =BR27-BO27 -> 0 | BX27: =BW27-BT27 -> 0 | CB27: =CA27/F27 -> 0 | CC27: =CB27-BY27 -> 0 | CG27: =CF27/F27 -> 0 | CH27: =CG27-CD27 -> 0 | CL27: =CK27/F27 -> 0 | CM27: =CL27-CI27 -> 0 | CR27: =ROUND(CQ27-CN27,2) -> 0 | CW27: =CV27-CS27 -> 0 | DA27: =ROUND(CZ27/F27,2) -> 0 | DB27: =ROUND(DA27-CX27,2) -> 0 | DF27: =DE27/F27 -> 0 | DG27: =DC27-DF27 -> 0 | DK27: =DJ27/F27 -> 0 | DL27: =DK27-DH27 -> 0 | DP27: =DO27/F27 -> 0 | DQ27: =DP27-DM27 -> 0 | DU27: =DT27/F27 -> 0 | DV27: =DU27-DR27 -> 0 | DZ27: =ROUND(DY27/F27,2) -> 0 | EA27: =ROUND(DZ27-DW27,2) -> 0 | EF27: =EE27-EB27 -> 0 | EJ27: =ROUND(EI27/F27,2) -> 0 | EK27: =ROUND(EJ27-EG27,2) -> 0 | EO27: =ROUND(EN27/F27,2) -> 0 | EP27: =ROUND(EO27-EL27,2) -> 0 | ET27: =ROUND(ES27/F27,2) -> 0 | EU27: =ROUND(ET27-EQ27,2) -> 0 | EY27: =ROUND(EX27/F27,2) -> 0 | EZ27: =ROUND(EY27-EV27,2) -> 0 | FD27: =ROUND(FC27/F27,2) -> 0 | FE27: =ROUND(FD27-FA27,2) -> 0 | FI27: =FH27/F27 -> 0 | FJ27: =ROUND(FI27-FF27,2) -> 0 | FN27: =ROUND(FM27/F27,2) -> 0 | FO27: =ROUND(FN27-FK27,2) -> 0 | FS27: =ROUND(FR27/F27,2) -> 0 | FT27: =FS27-FP27 -> 0 | FX27: =ROUND(FW27/F27,2) -> 0 | FY27: =FX27-FU27 -> 0 | GC27: =ROUND(GB27/F27,2) -> 0 | GD27: =GC27-FZ27 -> 0 | GH27: =GG27/F27 -> 0 | GI27: =GH27-GE27 -> 0 | GM27: =GL27/F27 -> 0 | GN27: =GM27-GJ27 -> 0 | GR27: =GQ27/F27 -> 0 | GS27: =GR27-GO27 -> 0 | GW27: =ROUND(GV27/F27,2) -> 0 | GX27: =GW27-GT27 -> 0
B28: 2320 | E28: 工程施工 | F28: 0.09 | G28: =SUM(M28,P28:Q28,V28,AA28,AF28,AK28,AP28,AU28,AZ28,BE28,BJ28,BO28,BT28,BY28,CD28,CI28,CN28,CS28,CX28,DC28,DH28,DM28,DR28,DW28,EB28,EG28,EL28,EQ28,EV28,FA28,FF28,FK28,FP28,FU28,FZ28,GE28,GJ28,GO28,GT28) -> 7011909.1 | H28: =SUM(N28,R28,W28,AB28,AG28,AL28,AQ28,AV28,BA28,BF28,BK28,BP28,BU28,BZ28,CE28,CJ28,CO28,CT28,CY28,DD28,DI28,DN28,DS28,DX28,EC28,EH28,EM28,ER28,EW28,FB28,FG28,FL28,FQ28,FV28,GA28,GF28,GK28,GP28,GU28) -> 7011909.1 | I28: =SUM(O28,S28,X28,AC28,AH28,AM28,AR28,AW28,BB28,BG28,BL28,BQ28,BV28,CA28,CF28,CK28,CP28,CU28,CZ28,DE28,DJ28,DO28,DT28,DY28,ED28,EI28,EN28,ES28,EX28,FC28,FH28,FM28,FR28,FW28,GB28,GG28,GL28,GQ28,GV28) -> 631071.83 | J28: =I28/F28 -> 7011909.2 | K28: =I28/F28-H28 -> 0.14222222 | L28: =J28-G28 -> 0.14222222 | M28: 7011909.1 | N28: 7011909.1 | O28: 631071.83 | T28: 0 | U28: =T28-Q28 -> 0 | Y28: =X28/F28 -> 0 | Z28: =Y28-V28 -> 0 | AD28: =AC28/F28 -> 0 | AE28: =AD28-AA28 -> 0 | AI28: =AH28/F28 -> 0 | AJ28: =AI28-AF28 -> 0 | AN28: =AM28/F28 -> 0 | AO28: =AN28-AK28 -> 0 | AS28: =AR28/F28 -> 0 | AT28: =AS28-AP28 -> 0 | AX28: =AW28/F28 -> 0 | AY28: =AX28-AU28 -> 0 | BC28: =BB28/F28 -> 0 | BH28: =BG28/F28 -> 0 | BI28: =BH28-BE28 -> 0 | BM28: =BL28/F28 -> 0 | BN28: =BM28-BJ28 -> 0 | BR28: =BQ28/F28 -> 0 | BS28: =BR28-BO28 -> 0 | BX28: =BW28-BT28 -> 0 | CB28: =CA28/F28 -> 0 | CC28: =CB28-BY28 -> 0 | CG28: =CF28/F28 -> 0 | CH28: =CG28-CD28 -> 0 | CL28: =CK28/F28 -> 0 | CM28: =CL28-CI28 -> 0 | CR28: =ROUND(CQ28-CN28,2) -> 0 | CW28: =CV28-CS28 -> 0 | DA28: =ROUND(CZ28/F28,2) -> 0 | DB28: =ROUND(DA28-CX28,2) -> 0 | DF28: =DE28/F28 -> 0 | DG28: =DC28-DF28 -> 0 | DK28: =DJ28/F28 -> 0 | DL28: =DK28-DH28 -> 0 | DP28: =DO28/F28 -> 0 | DQ28: =DP28-DM28 -> 0 | DU28: =DT28/F28 -> 0 | DV28: =DU28-DR28 -> 0 | DZ28: =ROUND(DY28/F28,2) -> 0 | EA28: =ROUND(DZ28-DW28,2) -> 0 | EF28: =EE28-EB28 -> 0 | EJ28: =ROUND(EI28/F28,2) -> 0 | EK28: =ROUND(EJ28-EG28,2) -> 0 | EO28: =ROUND(EN28/F28,2) -> 0 | EP28: =ROUND(EO28-EL28,2) -> 0 | ET28: =ROUND(ES28/F28,2) -> 0 | EU28: =ROUND(ET28-EQ28,2) -> 0 | EY28: =ROUND(EX28/F28,2) -> 0 | EZ28: =ROUND(EY28-EV28,2) -> 0 | FD28: =ROUND(FC28/F28,2) -> 0 | FE28: =ROUND(FD28-FA28,2) -> 0 | FI28: =FH28/F28 -> 0 | FJ28: =ROUND(FI28-FF28,2) -> 0 | FN28: =ROUND(FM28/F28,2) -> 0 | FO28: =ROUND(FN28-FK28,2) -> 0 | FS28: =ROUND(FR28/F28,2) -> 0 | FT28: =FS28-FP28 -> 0 | FX28: =ROUND(FW28/F28,2) -> 0 | FY28: =FX28-FU28 -> 0 | GC28: =ROUND(GB28/F28,2) -> 0 | GD28: =GC28-FZ28 -> 0 | GH28: =GG28/F28 -> 0 | GI28: =GH28-GE28 -> 0 | GM28: =GL28/F28 -> 0 | GN28: =GM28-GJ28 -> 0 | GR28: =GQ28/F28 -> 0 | GS28: =GR28-GO28 -> 0 | GW28: =ROUND(GV28/F28,2) -> 0 | GX28: =GW28-GT28 -> 0
B29: 2320 | E29: 设计咨询 | F29: 0.06 | G29: =SUM(M29,P29:Q29,V29,AA29,AF29,AK29,AP29,AU29,AZ29,BE29,BJ29,BO29,BT29,BY29,CD29,CI29,CN29,CS29,CX29,DC29,DH29,DM29,DR29,DW29,EB29,EG29,EL29,EQ29,EV29,FA29,FF29,FK29,FP29,FU29,FZ29,GE29,GJ29,GO29,GT29) -> 2003490.6 | H29: =SUM(N29,R29,W29,AB29,AG29,AL29,AQ29,AV29,BA29,BF29,BK29,BP29,BU29,BZ29,CE29,CJ29,CO29,CT29,CY29,DD29,DI29,DN29,DS29,DX29,EC29,EH29,EM29,ER29,EW29,FB29,FG29,FL29,FQ29,FV29,GA29,GF29,GK29,GP29,GU29) -> 2003490.6 | I29: =SUM(O29,S29,X29,AC29,AH29,AM29,AR29,AW29,BB29,BG29,BL29,BQ29,BV29,CA29,CF29,CK29,CP29,CU29,CZ29,DE29,DJ29,DO29,DT29,DY29,ED29,EI29,EN29,ES29,EX29,FC29,FH29,FM29,FR29,FW29,GB29,GG29,GL29,GQ29,GV29) -> 120209.44 | J29: =I29/F29 -> 2003490.7 | K29: =I29/F29-H29 -> 0.10666667 | L29: =J29-G29 -> 0.10666667 | M29: 2003490.6 | N29: 2003490.6 | O29: 120209.44 | T29: 0 | U29: =T29-Q29 -> 0 | Y29: =X29/F29 -> 0 | Z29: =Y29-V29 -> 0 | AD29: =AC29/F29 -> 0 | AE29: =AD29-AA29 -> 0 | AI29: =AH29/F29 -> 0 | AJ29: =AI29-AF29 -> 0 | AN29: =AM29/F29 -> 0 | AO29: =AN29-AK29 -> 0 | AS29: =AR29/F29 -> 0 | AT29: =AS29-AP29 -> 0 | AX29: =AW29/F29 -> 0 | AY29: =AX29-AU29 -> 0 | BC29: =BB29/F29 -> 0 | BH29: =BG29/F29 -> 0 | BI29: =BH29-BE29 -> 0 | BM29: =BL29/F29 -> 0 | BN29: =BM29-BJ29 -> 0 | BQ29: 0 | BR29: =BQ29/F29 -> 0 | BS29: =BR29-BO29 -> 0 | BX29: =BW29-BT29 -> 0 | CB29: =CA29/F29 -> 0 | CC29: =CB29-BY29 -> 0 | CG29: =CF29/F29 -> 0 | CH29: =CG29-CD29 -> 0 | CL29: =CK29/F29 -> 0 | CM29: =CL29-CI29 -> 0 | CR29: =ROUND(CQ29-CN29,2) -> 0 | CW29: =CV29-CS29 -> 0 | DA29: =ROUND(CZ29/F29,2) -> 0 | DB29: =ROUND(DA29-CX29,2) -> 0 | DF29: =DE29/F29 -> 0 | DG29: =DC29-DF29 -> 0 | DK29: =DJ29/F29 -> 0 | DL29: =DK29-DH29 -> 0 | DP29: =DO29/F29 -> 0 | DQ29: =DP29-DM29 -> 0 | DU29: =DT29/F29 -> 0 | DV29: =DU29-DR29 -> 0 | DZ29: =ROUND(DY29/F29,2) -> 0 | EA29: =ROUND(DZ29-DW29,2) -> 0 | EF29: =EE29-EB29 -> 0 | EJ29: =ROUND(EI29/F29,2) -> 0 | EK29: =ROUND(EJ29-EG29,2) -> 0 | EO29: =ROUND(EN29/F29,2) -> 0 | EP29: =ROUND(EO29-EL29,2) -> 0 | ET29: =ROUND(ES29/F29,2) -> 0 | EU29: =ROUND(ET29-EQ29,2) -> 0 | EY29: =ROUND(EX29/F29,2) -> 0 | EZ29: =ROUND(EY29-EV29,2) -> 0 | FD29: =ROUND(FC29/F29,2) -> 0 | FE29: =ROUND(FD29-FA29,2) -> 0 | FI29: =FH29/F29 -> 0 | FJ29: =ROUND(FI29-FF29,2) -> 0 | FN29: =ROUND(FM29/F29,2) -> 0 | FO29: =ROUND(FN29-FK29,2) -> 0 | FS29: =ROUND(FR29/F29,2) -> 0 | FT29: =FS29-FP29 -> 0 | FX29: =ROUND(FW29/F29,2) -> 0 | FY29: =FX29-FU29 -> 0 | GC29: =ROUND(GB29/F29,2) -> 0 | GD29: =GC29-FZ29 -> 0 | GH29: =GG29/F29 -> 0 | GI29: =GH29-GE29 -> 0 | GM29: =GL29/F29 -> 0 | GN29: =GM29-GJ29 -> 0 | GR29: =GQ29/F29 -> 0 | GS29: =GR29-GO29 -> 0 | GW29: =ROUND(GV29/F29,2) -> 0 | GX29: =GW29-GT29 -> 0
B30: 2330 | D30: 2330 (濉溪一期)【已出售】 | E30: 商品销售 | F30: 0.13 | G30: =SUM(M30,P30:Q30,V30,AA30,AF30,AK30,AP30,AU30,AZ30,BE30,BJ30,BO30,BT30,BY30,CD30,CI30,CN30,CS30,CX30,DC30,DH30,DM30,DR30,DW30,EB30,EG30,EL30,EQ30,EV30,FA30,FF30,FK30,FP30,FU30,FZ30,GE30,GJ30,GO30,GT30) -> 64076361 | H30: =SUM(N30,R30,W30,AB30,AG30,AL30,AQ30,AV30,BA30,BF30,BK30,BP30,BU30,BZ30,CE30,CJ30,CO30,CT30,CY30,DD30,DI30,DN30,DS30,DX30,EC30,EH30,EM30,ER30,EW30,FB30,FG30,FL30,FQ30,FV30,GA30,GF30,GK30,GP30,GU30) -> 64076361 | I30: =SUM(O30,S30,X30,AC30,AH30,AM30,AR30,AW30,BB30,BG30,BL30,BQ30,BV30,CA30,CF30,CK30,CP30,CU30,CZ30,DE30,DJ30,DO30,DT30,DY30,ED30,EI30,EN30,ES30,EX30,FC30,FH30,FM30,FR30,FW30,GB30,GG30,GL30,GQ30,GV30) -> 8329926.9 | J30: =I30/F30 -> 64076361 | K30: =I30/F30-H30 -> 0.014092684 | L30: =J30-G30 -> 0 | M30: 64076361 | N30: 64021518 | O30: 8329926.9 | T30: 0 | U30: =T30-Q30 -> 0 | Y30: =X30/F30 -> 0 | Z30: =Y30-V30 -> 0 | AB30: 54843.43 | AD30: =AC30/F30 -> 0 | AE30: =AD30-AA30 -> 0 | AI30: =AH30/F30 -> 0 | AJ30: =AI30-AF30 -> 0 | AN30: =AM30/F30 -> 0 | AO30: =AN30-AK30 -> 0 | AS30: =AR30/F30 -> 0 | AT30: =AS30-AP30 -> 0 | AX30: =AW30/F30 -> 0 | AY30: =AX30-AU30 -> 0 | BC30: =BB30/F30 -> 0 | BH30: =BG30/F30 -> 0 | BI30: =BH30-BE30 -> 0 | BM30: =BL30/F30 -> 0 | BN30: =BM30-BJ30 -> 0 | BR30: =BQ30/F30 -> 0 | BS30: =BR30-BO30 -> 0 | BX30: =BW30-BT30 -> 0 | CB30: =CA30/F30 -> 0 | CC30: =CB30-BY30 -> 0 | CG30: =CF30/F30 -> 0 | CH30: =CG30-CD30 -> 0 | CL30: =CK30/F30 -> 0 | CM30: =CL30-CI30 -> 0 | CR30: =ROUND(CQ30-CN30,2) -> 0 | CW30: =CV30-CS30 -> 0 | DA30: =ROUND(CZ30/F30,2) -> 0 | DB30: =ROUND(DA30-CX30,2) -> 0 | DF30: =DE30/F30 -> 0 | DG30: =DC30-DF30 -> 0 | DK30: =DJ30/F30 -> 0 | DL30: =DK30-DH30 -> 0 | DP30: =DO30/F30 -> 0 | DQ30: =DP30-DM30 -> 0 | DU30: =DT30/F30 -> 0 | DV30: =DU30-DR30 -> 0 | DZ30: =ROUND(DY30/F30,2) -> 0 | EA30: =ROUND(DZ30-DW30,2) -> 0 | EF30: =EE30-EB30 -> 0 | EJ30: =ROUND(EI30/F30,2) -> 0 | EK30: =ROUND(EJ30-EG30,2) -> 0 | EO30: =ROUND(EN30/F30,2) -> 0 | EP30: =ROUND(EO30-EL30,2) -> 0 | ET30: =ROUND(ES30/F30,2) -> 0 | EU30: =ROUND(ET30-EQ30,2) -> 0 | EY30: =ROUND(EX30/F30,2) -> 0 | EZ30: =ROUND(EY30-EV30,2) -> 0 | FD30: =ROUND(FC30/F30,2) -> 0 | FE30: =ROUND(FD30-FA30,2) -> 0 | FI30: =FH30/F30 -> 0 | FJ30: =ROUND(FI30-FF30,2) -> 0 | FN30: =ROUND(FM30/F30,2) -> 0 | FO30: =ROUND(FN30-FK30,2) -> 0 | FS30: =ROUND(FR30/F30,2) -> 0 | FT30: =FS30-FP30 -> 0 | FX30: =ROUND(FW30/F30,2) -> 0 | FY30: =FX30-FU30 -> 0 | GC30: =ROUND(GB30/F30,2) -> 0 | GD30: =GC30-FZ30 -> 0 | GH30: =GG30/F30 -> 0 | GI30: =GH30-GE30 -> 0 | GM30: =GL30/F30 -> 0 | GN30: =GM30-GJ30 -> 0 | GR30: =GQ30/F30 -> 0 | GS30: =GR30-GO30 -> 0 | GW30: =ROUND(GV30/F30,2) -> 0 | GX30: =GW30-GT30 -> 0
B31: 2330 | E31: 工程施工 | F31: 0.09 | G31: =SUM(M31,P31:Q31,V31,AA31,AF31,AK31,AP31,AU31,AZ31,BE31,BJ31,BO31,BT31,BY31,CD31,CI31,CN31,CS31,CX31,DC31,DH31,DM31,DR31,DW31,EB31,EG31,EL31,EQ31,EV31,FA31,FF31,FK31,FP31,FU31,FZ31,GE31,GJ31,GO31,GT31) -> 1.0988747e+08 | H31: =SUM(N31,R31,W31,AB31,AG31,AL31,AQ31,AV31,BA31,BF31,BK31,BP31,BU31,BZ31,CE31,CJ31,CO31,CT31,CY31,DD31,DI31,DN31,DS31,DX31,EC31,EH31,EM31,ER31,EW31,FB31,FG31,FL31,FQ31,FV31,GA31,GF31,GK31,GP31,GU31) -> 1.0988747e+08 | I31: =SUM(O31,S31,X31,AC31,AH31,AM31,AR31,AW31,BB31,BG31,BL31,BQ31,BV31,CA31,CF31,CK31,CP31,CU31,CZ31,DE31,DJ31,DO31,DT31,DY31,ED31,EI31,EN31,ES31,EX31,FC31,FH31,FM31,FR31,FW31,GB31,GG31,GL31,GQ31,GV31) -> 9889871.9 | J31: =I31/F31 -> 1.0988747e+08 | K31: =I31/F31-H31 -> 0.11098121 | L31: =J31-G31 -> 0.0046482235 | M31: 1.0988747e+08 | N31: 1.0959156e+08 | O31: 9889871.9 | T31: 0 | U31: =T31-Q31 -> 0 | Y31: =X31/F31 -> 0 | Z31: =Y31-V31 -> 0 | AB31: 295906.59 | AD31: =AC31/F31 -> 0 | AE31: =AD31-AA31 -> 0 | AI31: =AH31/F31 -> 0 | AJ31: =AI31-AF31 -> 0 | AN31: =AM31/F31 -> 0 | AO31: =AN31-AK31 -> 0 | AS31: =AR31/F31 -> 0 | AT31: =AS31-AP31 -> 0 | AX31: =AW31/F31 -> 0 | AY31: =AX31-AU31 -> 0 | BC31: =BB31/F31 -> 0 | BH31: =BG31/F31 -> 0 | BI31: =BH31-BE31 -> 0 | BM31: =BL31/F31 -> 0 | BN31: =BM31-BJ31 -> 0 | BR31: =BQ31/F31 -> 0 | BS31: =BR31-BO31 -> 0 | BX31: =BW31-BT31 -> 0 | CB31: =CA31/F31 -> 0 | CC31: =CB31-BY31 -> 0 | CG31: =CF31/F31 -> 0 | CH31: =CG31-CD31 -> 0 | CL31: =CK31/F31 -> 0 | CM31: =CL31-CI31 -> 0 | CR31: =ROUND(CQ31-CN31,2) -> 0 | CW31: =CV31-CS31 -> 0 | DA31: =ROUND(CZ31/F31,2) -> 0 | DB31: =ROUND(DA31-CX31,2) -> 0 | DF31: =DE31/F31 -> 0 | DG31: =DC31-DF31 -> 0 | DK31: =DJ31/F31 -> 0 | DL31: =DK31-DH31 -> 0 | DP31: =DO31/F31 -> 0 | DQ31: =DP31-DM31 -> 0 | DU31: =DT31/F31 -> 0 | DV31: =DU31-DR31 -> 0 | DZ31: =ROUND(DY31/F31,2) -> 0 | EA31: =ROUND(DZ31-DW31,2) -> 0 | EF31: =EE31-EB31 -> 0 | EJ31: =ROUND(EI31/F31,2) -> 0 | EK31: =ROUND(EJ31-EG31,2) -> 0 | EO31: =ROUND(EN31/F31,2) -> 0 | EP31: =ROUND(EO31-EL31,2) -> 0 | ET31: =ROUND(ES31/F31,2) -> 0 | EU31: =ROUND(ET31-EQ31,2) -> 0 | EY31: =ROUND(EX31/F31,2) -> 0 | EZ31: =ROUND(EY31-EV31,2) -> 0 | FD31: =ROUND(FC31/F31,2) -> 0 | FE31: =ROUND(FD31-FA31,2) -> 0 | FI31: =FH31/F31 -> 0 | FJ31: =ROUND(FI31-FF31,2) -> 0 | FN31: =ROUND(FM31/F31,2) -> 0 | FO31: =ROUND(FN31-FK31,2) -> 0 | FS31: =ROUND(FR31/F31,2) -> 0 | FT31: =FS31-FP31 -> 0 | FX31: =ROUND(FW31/F31,2) -> 0 | FY31: =FX31-FU31 -> 0 | GC31: =ROUND(GB31/F31,2) -> 0 | GD31: =GC31-FZ31 -> 0 | GH31: =GG31/F31 -> 0 | GI31: =GH31-GE31 -> 0 | GM31: =GL31/F31 -> 0 | GN31: =GM31-GJ31 -> 0 | GR31: =GQ31/F31 -> 0 | GS31: =GR31-GO31 -> 0 | GW31: =ROUND(GV31/F31,2) -> 0 | GX31: =GW31-GT31 -> 0
B32: 2330 | E32: 设计咨询 | F32: 0.06 | G32: =SUM(M32,P32:Q32,V32,AA32,AF32,AK32,AP32,AU32,AZ32,BE32,BJ32,BO32,BT32,BY32,CD32,CI32,CN32,CS32,CX32,DC32,DH32,DM32,DR32,DW32,EB32,EG32,EL32,EQ32,EV32,FA32,FF32,FK32,FP32,FU32,FZ32,GE32,GJ32,GO32,GT32) -> 3490 | H32: =SUM(N32,R32,W32,AB32,AG32,AL32,AQ32,AV32,BA32,BF32,BK32,BP32,BU32,BZ32,CE32,CJ32,CO32,CT32,CY32,DD32,DI32,DN32,DS32,DX32,EC32,EH32,EM32,ER32,EW32,FB32,FG32,FL32,FQ32,FV32,GA32,GF32,GK32,GP32,GU32) -> 0 | I32: =SUM(O32,S32,X32,AC32,AH32,AM32,AR32,AW32,BB32,BG32,BL32,BQ32,BV32,CA32,CF32,CK32,CP32,CU32,CZ32,DE32,DJ32,DO32,DT32,DY32,ED32,EI32,EN32,ES32,EX32,FC32,FH32,FM32,FR32,FW32,GB32,GG32,GL32,GQ32,GV32) -> 209.4 | J32: =I32/F32 -> 3490 | K32: =I32/F32-H32 -> 3490 | L32: =J32-G32 -> 0 | T32: 0 | U32: =T32-Q32 -> 0 | Y32: =X32/F32 -> 0 | Z32: =Y32-V32 -> 0 | AD32: =AC32/F32 -> 0 | AE32: =AD32-AA32 -> 0 | AI32: =AH32/F32 -> 0 | AJ32: =AI32-AF32 -> 0 | AN32: =AM32/F32 -> 0 | AO32: =AN32-AK32 -> 0 | AS32: =AR32/F32 -> 0 | AT32: =AS32-AP32 -> 0 | AX32: =AW32/F32 -> 0 | AY32: =AX32-AU32 -> 0 | BC32: =BB32/F32 -> 0 | BH32: =BG32/F32 -> 0 | BI32: =BH32-BE32 -> 0 | BM32: =BL32/F32 -> 0 | BN32: =BM32-BJ32 -> 0 | BQ32: 0 | BR32: =BQ32/F32 -> 0 | BS32: =BR32-BO32 -> 0 | BX32: =BW32-BT32 -> 0 | CB32: =CA32/F32 -> 0 | CC32: =CB32-BY32 -> 0 | CG32: =CF32/F32 -> 0 | CH32: =CG32-CD32 -> 0 | CL32: =CK32/F32 -> 0 | CM32: =CL32-CI32 -> 0 | CR32: =ROUND(CQ32-CN32,2) -> 0 | CW32: =CV32-CS32 -> 0 | DA32: =ROUND(CZ32/F32,2) -> 0 | DB32: =ROUND(DA32-CX32,2) -> 0 | DC32: 3490 | DE32: 209.4 | DF32: =DE32/F32 -> 3490 | DG32: =DC32-DF32 -> 0 | DK32: =DJ32/F32 -> 0 | DL32: =DK32-DH32 -> 0 | DP32: =DO32/F32 -> 0 | DQ32: =DP32-DM32 -> 0 | DU32: =DT32/F32 -> 0 | DV32: =DU32-DR32 -> 0 | DZ32: =ROUND(DY32/F32,2) -> 0 | EA32: =ROUND(DZ32-DW32,2) -> 0 | EF32: =EE32-EB32 -> 0 | EJ32: =ROUND(EI32/F32,2) -> 0 | EK32: =ROUND(EJ32-EG32,2) -> 0 | EO32: =ROUND(EN32/F32,2) -> 0 | EP32: =ROUND(EO32-EL32,2) -> 0 | ET32: =ROUND(ES32/F32,2) -> 0 | EU32: =ROUND(ET32-EQ32,2) -> 0 | EY32: =ROUND(EX32/F32,2) -> 0 | EZ32: =ROUND(EY32-EV32,2) -> 0 | FD32: =ROUND(FC32/F32,2) -> 0 | FE32: =ROUND(FD32-FA32,2) -> 0 | FI32: =FH32/F32 -> 0 | FJ32: =ROUND(FI32-FF32,2) -> 0 | FN32: =ROUND(FM32/F32,2) -> 0 | FO32: =ROUND(FN32-FK32,2) -> 0 | FS32: =ROUND(FR32/F32,2) -> 0 | FT32: =FS32-FP32 -> 0 | FX32: =ROUND(FW32/F32,2) -> 0 | FY32: =FX32-FU32 -> 0 | GC32: =ROUND(GB32/F32,2) -> 0 | GD32: =GC32-FZ32 -> 0 | GH32: =GG32/F32 -> 0 | GI32: =GH32-GE32 -> 0 | GM32: =GL32/F32 -> 0 | GN32: =GM32-GJ32 -> 0 | GR32: =GQ32/F32 -> 0 | GS32: =GR32-GO32 -> 0 | GW32: =ROUND(GV32/F32,2) -> 0 | GX32: =GW32-GT32 -> 0
B33: 2330 | D33: 2330 (濉溪二期)【已出售】 | E33: 商品销售 | F33: 0.13 | G33: =SUM(M33,P33:Q33,V33,AA33,AF33,AK33,AP33,AU33,AZ33,BE33,BJ33,BO33,BT33,BY33,CD33,CI33,CN33,CS33,CX33,DC33,DH33,DM33,DR33,DW33,EB33,EG33,EL33,EQ33,EV33,FA33,FF33,FK33,FP33,FU33,FZ33,GE33,GJ33,GO33,GT33) -> 32603041 | H33: =SUM(N33,R33,W33,AB33,AG33,AL33,AQ33,AV33,BA33,BF33,BK33,BP33,BU33,BZ33,CE33,CJ33,CO33,CT33,CY33,DD33,DI33,DN33,DS33,DX33,EC33,EH33,EM33,ER33,EW33,FB33,FG33,FL33,FQ33,FV33,GA33,GF33,GK33,GP33,GU33) -> 32603041 | I33: =SUM(O33,S33,X33,AC33,AH33,AM33,AR33,AW33,BB33,BG33,BL33,BQ33,BV33,CA33,CF33,CK33,CP33,CU33,CZ33,DE33,DJ33,DO33,DT33,DY33,ED33,EI33,EN33,ES33,EX33,FC33,FH33,FM33,FR33,FW33,GB33,GG33,GL33,GQ33,GV33) -> 4238395.4 | J33: =I33/F33 -> 32603041 | K33: =I33/F33-H33 -> 0.0095999986 | L33: =J33-G33 -> 0 | M33: 32321413 | N33: 0 | O33: 4201783.7 | Q33: 281628.32 | S33: 36611.682 | T33: 281628.32 | U33: =T33-Q33 -> 0 | Y33: =X33/F33 -> 0 | Z33: =Y33-V33 -> 0 | AB33: 32603041 | AD33: =AC33/F33 -> 0 | AE33: =AD33-AA33 -> 0 | AI33: =AH33/F33 -> 0 | AJ33: =AI33-AF33 -> 0 | AN33: =AM33/F33 -> 0 | AO33: =AN33-AK33 -> 0 | AS33: =AR33/F33 -> 0 | AT33: =AS33-AP33 -> 0 | AX33: =AW33/F33 -> 0 | AY33: =AX33-AU33 -> 0 | BC33: =BB33/F33 -> 0 | BH33: =BG33/F33 -> 0 | BI33: =BH33-BE33 -> 0 | BM33: =BL33/F33 -> 0 | BN33: =BM33-BJ33 -> 0 | BR33: =BQ33/F33 -> 0 | BS33: =BR33-BO33 -> 0 | BX33: =BW33-BT33 -> 0 | CB33: =CA33/F33 -> 0 | CC33: =CB33-BY33 -> 0 | CG33: =CF33/F33 -> 0 | CH33: =CG33-CD33 -> 0 | CL33: =CK33/F33 -> 0 | CM33: =CL33-CI33 -> 0 | CR33: =ROUND(CQ33-CN33,2) -> 0 | CW33: =CV33-CS33 -> 0 | DA33: =ROUND(CZ33/F33,2) -> 0 | DB33: =ROUND(DA33-CX33,2) -> 0 | DF33: =DE33/F33 -> 0 | DG33: =DC33-DF33 -> 0 | DK33: =DJ33/F33 -> 0 | DL33: =DK33-DH33 -> 0 | DP33: =DO33/F33 -> 0 | DQ33: =DP33-DM33 -> 0 | DU33: =DT33/F33 -> 0 | DV33: =DU33-DR33 -> 0 | DZ33: =ROUND(DY33/F33,2) -> 0 | EA33: =ROUND(DZ33-DW33,2) -> 0 | EF33: =EE33-EB33 -> 0 | EJ33: =ROUND(EI33/F33,2) -> 0 | EK33: =ROUND(EJ33-EG33,2) -> 0 | EO33: =ROUND(EN33/F33,2) -> 0 | EP33: =ROUND(EO33-EL33,2) -> 0 | ET33: =ROUND(ES33/F33,2) -> 0 | EU33: =ROUND(ET33-EQ33,2) -> 0 | EY33: =ROUND(EX33/F33,2) -> 0 | EZ33: =ROUND(EY33-EV33,2) -> 0 | FD33: =ROUND(FC33/F33,2) -> 0 | FE33: =ROUND(FD33-FA33,2) -> 0 | FI33: =FH33/F33 -> 0 | FJ33: =ROUND(FI33-FF33,2) -> 0 | FN33: =ROUND(FM33/F33,2) -> 0 | FO33: =ROUND(FN33-FK33,2) -> 0 | FS33: =ROUND(FR33/F33,2) -> 0 | FT33: =FS33-FP33 -> 0 | FX33: =ROUND(FW33/F33,2) -> 0 | FY33: =FX33-FU33 -> 0 | GC33: =ROUND(GB33/F33,2) -> 0 | GD33: =GC33-FZ33 -> 0 | GH33: =GG33/F33 -> 0 | GI33: =GH33-GE33 -> 0 | GM33: =GL33/F33 -> 0 | GN33: =GM33-GJ33 -> 0 | GR33: =GQ33/F33 -> 0 | GS33: =GR33-GO33 -> 0 | GW33: =ROUND(GV33/F33,2) -> 0 | GX33: =GW33-GT33 -> 0
B34: 2330 | E34: 工程施工 | F34: 0.09 | G34: =SUM(M34,P34:Q34,V34,AA34,AF34,AK34,AP34,AU34,AZ34,BE34,BJ34,BO34,BT34,BY34,CD34,CI34,CN34,CS34,CX34,DC34,DH34,DM34,DR34,DW34,EB34,EG34,EL34,EQ34,EV34,FA34,FF34,FK34,FP34,FU34,FZ34,GE34,GJ34,GO34,GT34) -> 27044037 | H34: =SUM(N34,R34,W34,AB34,AG34,AL34,AQ34,AV34,BA34,BF34,BK34,BP34,BU34,BZ34,CE34,CJ34,CO34,CT34,CY34,DD34,DI34,DN34,DS34,DX34,EC34,EH34,EM34,ER34,EW34,FB34,FG34,FL34,FQ34,FV34,GA34,GF34,GK34,GP34,GU34) -> 27044037 | I34: =SUM(O34,S34,X34,AC34,AH34,AM34,AR34,AW34,BB34,BG34,BL34,BQ34,BV34,CA34,CF34,CK34,CP34,CU34,CZ34,DE34,DJ34,DO34,DT34,DY34,ED34,EI34,EN34,ES34,EX34,FC34,FH34,FM34,FR34,FW34,GB34,GG34,GL34,GQ34,GV34) -> 2433963.3 | J34: =I34/F34 -> 27044037 | K34: =I34/F34-H34 -> 0.0092477053 | L34: =J34-G34 -> 0 | M34: 23130233 | N34: 3840000 | O34: 2081721 | P34: 935779.82 | Q34: 2978023.9 | S34: 268022.15 | T34: 2978023.9 | U34: =T34-Q34 -> 0 | Y34: =X34/F34 -> 0 | Z34: =Y34-V34 -> 0 | AB34: 23204037 | AC34: =P34*F34 -> 84220.184 | AD34: =AC34/F34 -> 935779.82 | AE34: =AD34-AA34 -> 935779.82 | AI34: =AH34/F34 -> 0 | AJ34: =AI34-AF34 -> 0 | AN34: =AM34/F34 -> 0 | AO34: =AN34-AK34 -> 0 | AS34: =AR34/F34 -> 0 | AT34: =AS34-AP34 -> 0 | AX34: =AW34/F34 -> 0 | AY34: =AX34-AU34 -> 0 | BC34: =BB34/F34 -> 0 | BH34: =BG34/F34 -> 0 | BI34: =BH34-BE34 -> 0 | BM34: =BL34/F34 -> 0 | BN34: =BM34-BJ34 -> 0 | BR34: =BQ34/F34 -> 0 | BS34: =BR34-BO34 -> 0 | BX34: =BW34-BT34 -> 0 | CB34: =CA34/F34 -> 0 | CC34: =CB34-BY34 -> 0 | CG34: =CF34/F34 -> 0 | CH34: =CG34-CD34 -> 0 | CL34: =CK34/F34 -> 0 | CM34: =CL34-CI34 -> 0 | CR34: =ROUND(CQ34-CN34,2) -> 0 | CW34: =CV34-CS34 -> 0 | DA34: =ROUND(CZ34/F34,2) -> 0 | DB34: =ROUND(DA34-CX34,2) -> 0 | DF34: =DE34/F34 -> 0 | DG34: =DC34-DF34 -> 0 | DK34: =DJ34/F34 -> 0 | DL34: =DK34-DH34 -> 0 | DP34: =DO34/F34 -> 0 | DQ34: =DP34-DM34 -> 0 | DU34: =DT34/F34 -> 0 | DV34: =DU34-DR34 -> 0 | DZ34: =ROUND(DY34/F34,2) -> 0 | EA34: =ROUND(DZ34-DW34,2) -> 0 | EF34: =EE34-EB34 -> 0 | EJ34: =ROUND(EI34/F34,2) -> 0 | EK34: =ROUND(EJ34-EG34,2) -> 0 | EO34: =ROUND(EN34/F34,2) -> 0 | EP34: =ROUND(EO34-EL34,2) -> 0 | ET34: =ROUND(ES34/F34,2) -> 0 | EU34: =ROUND(ET34-EQ34,2) -> 0 | EY34: =ROUND(EX34/F34,2) -> 0 | EZ34: =ROUND(EY34-EV34,2) -> 0 | FD34: =ROUND(FC34/F34,2) -> 0 | FE34: =ROUND(FD34-FA34,2) -> 0 | FI34: =FH34/F34 -> 0 | FJ34: =ROUND(FI34-FF34,2) -> 0 | FN34: =ROUND(FM34/F34,2) -> 0 | FO34: =ROUND(FN34-FK34,2) -> 0 | FS34: =ROUND(FR34/F34,2) -> 0 | FT34: =FS34-FP34 -> 0 | FX34: =ROUND(FW34/F34,2) -> 0 | FY34: =FX34-FU34 -> 0 | GC34: =ROUND(GB34/F34,2) -> 0 | GD34: =GC34-FZ34 -> 0 | GH34: =GG34/F34 -> 0 | GI34: =GH34-GE34 -> 0 | GM34: =GL34/F34 -> 0 | GN34: =GM34-GJ34 -> 0 | GR34: =GQ34/F34 -> 0 | GS34: =GR34-GO34 -> 0 | GW34: =ROUND(GV34/F34,2) -> 0 | GX34: =GW34-GT34 -> 0
B35: 2330 | E35: 设计咨询 | F35: 0.06 | G35: =SUM(M35,P35:Q35,V35,AA35,AF35,AK35,AP35,AU35,AZ35,BE35,BJ35,BO35,BT35,BY35,CD35,CI35,CN35,CS35,CX35,DC35,DH35,DM35,DR35,DW35,EB35,EG35,EL35,EQ35,EV35,FA35,FF35,FK35,FP35,FU35,FZ35,GE35,GJ35,GO35,GT35) -> 0 | H35: =SUM(N35,R35,W35,AB35,AG35,AL35,AQ35,AV35,BA35,BF35,BK35,BP35,BU35,BZ35,CE35,CJ35,CO35,CT35,CY35,DD35,DI35,DN35,DS35,DX35,EC35,EH35,EM35,ER35,EW35,FB35,FG35,FL35,FQ35,FV35,GA35,GF35,GK35,GP35,GU35) -> 0 | I35: =SUM(O35,S35,X35,AC35,AH35,AM35,AR35,AW35,BB35,BG35,BL35,BQ35,BV35,CA35,CF35,CK35,CP35,CU35,CZ35,DE35,DJ35,DO35,DT35,DY35,ED35,EI35,EN35,ES35,EX35,FC35,FH35,FM35,FR35,FW35,GB35,GG35,GL35,GQ35,GV35) -> 0 | J35: =I35/F35 -> 0 | K35: =I35/F35-H35 -> 0 | L35: =J35-G35 -> 0 | T35: 0 | U35: =T35-Q35 -> 0 | Y35: =X35/F35 -> 0 | Z35: =Y35-V35 -> 0 | AD35: =AC35/F35 -> 0 | AE35: =AD35-AA35 -> 0 | AI35: =AH35/F35 -> 0 | AJ35: =AI35-AF35 -> 0 | AN35: =AM35/F35 -> 0 | AO35: =AN35-AK35 -> 0 | AS35: =AR35/F35 -> 0 | AT35: =AS35-AP35 -> 0 | AX35: =AW35/F35 -> 0 | AY35: =AX35-AU35 -> 0 | BC35: =BB35/F35 -> 0 | BH35: =BG35/F35 -> 0 | BI35: =BH35-BE35 -> 0 | BM35: =BL35/F35 -> 0 | BN35: =BM35-BJ35 -> 0 | BQ35: 0 | BR35: =BQ35/F35 -> 0 | BS35: =BR35-BO35 -> 0 | BX35: =BW35-BT35 -> 0 | CB35: =CA35/F35 -> 0 | CC35: =CB35-BY35 -> 0 | CG35: =CF35/F35 -> 0 | CH35: =CG35-CD35 -> 0 | CL35: =CK35/F35 -> 0 | CM35: =CL35-CI35 -> 0 | CR35: =ROUND(CQ35-CN35,2) -> 0 | CW35: =CV35-CS35 -> 0 | DA35: =ROUND(CZ35/F35,2) -> 0 | DB35: =ROUND(DA35-CX35,2) -> 0 | DF35: =DE35/F35 -> 0 | DG35: =DC35-DF35 -> 0 | DK35: =DJ35/F35 -> 0 | DL35: =DK35-DH35 -> 0 | DP35: =DO35/F35 -> 0 | DQ35: =DP35-DM35 -> 0 | DU35: =DT35/F35 -> 0 | DV35: =DU35-DR35 -> 0 | DZ35: =ROUND(DY35/F35,2) -> 0 | EA35: =ROUND(DZ35-DW35,2) -> 0 | EF35: =EE35-EB35 -> 0 | EJ35: =ROUND(EI35/F35,2) -> 0 | EK35: =ROUND(EJ35-EG35,2) -> 0 | EO35: =ROUND(EN35/F35,2) -> 0 | EP35: =ROUND(EO35-EL35,2) -> 0 | ET35: =ROUND(ES35/F35,2) -> 0 | EU35: =ROUND(ET35-EQ35,2) -> 0 | EY35: =ROUND(EX35/F35,2) -> 0 | EZ35: =ROUND(EY35-EV35,2) -> 0 | FD35: =ROUND(FC35/F35,2) -> 0 | FE35: =ROUND(FD35-FA35,2) -> 0 | FI35: =FH35/F35 -> 0 | FJ35: =ROUND(FI35-FF35,2) -> 0 | FN35: =ROUND(FM35/F35,2) -> 0 | FO35: =ROUND(FN35-FK35,2) -> 0 | FS35: =ROUND(FR35/F35,2) -> 0 | FT35: =FS35-FP35 -> 0 | FX35: =ROUND(FW35/F35,2) -> 0 | FY35: =FX35-FU35 -> 0 | GC35: =ROUND(GB35/F35,2) -> 0 | GD35: =GC35-FZ35 -> 0 | GH35: =GG35/F35 -> 0 | GI35: =GH35-GE35 -> 0 | GM35: =GL35/F35 -> 0 | GN35: =GM35-GJ35 -> 0 | GR35: =GQ35/F35 -> 0 | GS35: =GR35-GO35 -> 0 | GW35: =ROUND(GV35/F35,2) -> 0 | GX35: =GW35-GT35 -> 0
B36: 2370 | D36: 2370（馆陶一期）【23出售】 | E36: 商品销售 | F36: 0.16 | G36: =SUM(M36,P36:Q36,V36,AA36,AF36,AK36,AP36,AU36,AZ36,BE36,BJ36,BO36,BT36,BY36,CD36,CI36,CN36,CS36,CX36,DC36,DH36,DM36,DR36,DW36,EB36,EG36,EL36,EQ36,EV36,FA36,FF36,FK36,FP36,FU36,FZ36,GE36,GJ36,GO36,GT36) -> 0 | H36: =SUM(N36,R36,W36,AB36,AG36,AL36,AQ36,AV36,BA36,BF36,BK36,BP36,BU36,BZ36,CE36,CJ36,CO36,CT36,CY36,DD36,DI36,DN36,DS36,DX36,EC36,EH36,EM36,ER36,EW36,FB36,FG36,FL36,FQ36,FV36,GA36,GF36,GK36,GP36,GU36) -> 27837931 | I36: =SUM(O36,S36,X36,AC36,AH36,AM36,AR36,AW36,BB36,BG36,BL36,BQ36,BV36,CA36,CF36,CK36,CP36,CU36,CZ36,DE36,DJ36,DO36,DT36,DY36,ED36,EI36,EN36,ES36,EX36,FC36,FH36,FM36,FR36,FW36,GB36,GG36,GL36,GQ36,GV36) -> 4454068.9 | J36: =I36/F36 -> 27837931 | K36: =I36/F36-H36 -> -0.39 | L36: =J36-G36 -> 27837931 | N36: 27837931 | O36: 4454068.9 | T36: 0 | U36: =T36-Q36 -> 0 | Y36: =X36/F36 -> 0 | Z36: =Y36-V36 -> 0 | AD36: =AC36/F36 -> 0 | AE36: =AD36-AA36 -> 0 | AI36: =AH36/F36 -> 0 | AJ36: =AI36-AF36 -> 0 | AN36: =AM36/F36 -> 0 | AO36: =AN36-AK36 -> 0 | AS36: =AR36/F36 -> 0 | AT36: =AS36-AP36 -> 0 | AX36: =AW36/F36 -> 0 | AY36: =AX36-AU36 -> 0 | BC36: =BB36/F36 -> 0 | BH36: =BG36/F36 -> 0 | BI36: =BH36-BE36 -> 0 | BM36: =BL36/F36 -> 0 | BN36: =BM36-BJ36 -> 0 | BR36: =BQ36/F36 -> 0 | BS36: =BR36-BO36 -> 0 | BX36: =BW36-BT36 -> 0 | CB36: =CA36/F36 -> 0 | CC36: =CB36-BY36 -> 0 | CG36: =CF36/F36 -> 0 | CH36: =CG36-CD36 -> 0 | CL36: =CK36/F36 -> 0 | CM36: =CL36-CI36 -> 0 | CR36: =ROUND(CQ36-CN36,2) -> 0 | CW36: =CV36-CS36 -> 0 | DA36: =ROUND(CZ36/F36,2) -> 0 | DB36: =ROUND(DA36-CX36,2) -> 0 | DF36: =DE36/F36 -> 0 | DG36: =DC36-DF36 -> 0 | DK36: =DJ36/F36 -> 0 | DL36: =DK36-DH36 -> 0 | DP36: =DO36/F36 -> 0 | DQ36: =DP36-DM36 -> 0 | DU36: =DT36/F36 -> 0 | DV36: =DU36-DR36 -> 0 | DZ36: =ROUND(DY36/F36,2) -> 0 | EA36: =ROUND(DZ36-DW36,2) -> 0 | EF36: =EE36-EB36 -> 0 | EJ36: =ROUND(EI36/F36,2) -> 0 | EK36: =ROUND(EJ36-EG36,2) -> 0 | EO36: =ROUND(EN36/F36,2) -> 0 | EP36: =ROUND(EO36-EL36,2) -> 0 | ET36: =ROUND(ES36/F36,2) -> 0 | EU36: =ROUND(ET36-EQ36,2) -> 0 | EY36: =ROUND(EX36/F36,2) -> 0 | EZ36: =ROUND(EY36-EV36,2) -> 0 | FD36: =ROUND(FC36/F36,2) -> 0 | FE36: =ROUND(FD36-FA36,2) -> 0 | FI36: =FH36/F36 -> 0 | FJ36: =ROUND(FI36-FF36,2) -> 0 | FN36: =ROUND(FM36/F36,2) -> 0 | FO36: =ROUND(FN36-FK36,2) -> 0 | FS36: =ROUND(FR36/F36,2) -> 0 | FT36: =FS36-FP36 -> 0 | FX36: =ROUND(FW36/F36,2) -> 0 | FY36: =FX36-FU36 -> 0 | GC36: =ROUND(GB36/F36,2) -> 0 | GD36: =GC36-FZ36 -> 0 | GH36: =GG36/F36 -> 0 | GI36: =GH36-GE36 -> 0 | GM36: =GL36/F36 -> 0 | GN36: =GM36-GJ36 -> 0 | GR36: =GQ36/F36 -> 0 | GS36: =GR36-GO36 -> 0 | GW36: =ROUND(GV36/F36,2) -> 0 | GX36: =GW36-GT36 -> 0
B37: 2370 | F37: 0.13 | G37: =SUM(M37,P37:Q37,V37,AA37,AF37,AK37,AP37,AU37,AZ37,BE37,BJ37,BO37,BT37,BY37,CD37,CI37,CN37,CS37,CX37,DC37,DH37,DM37,DR37,DW37,EB37,EG37,EL37,EQ37,EV37,FA37,FF37,FK37,FP37,FU37,FZ37,GE37,GJ37,GO37,GT37) -> 30506032 | H37: =SUM(N37,R37,W37,AB37,AG37,AL37,AQ37,AV37,BA37,BF37,BK37,BP37,BU37,BZ37,CE37,CJ37,CO37,CT37,CY37,DD37,DI37,DN37,DS37,DX37,EC37,EH37,EM37,ER37,EW37,FB37,FG37,FL37,FQ37,FV37,GA37,GF37,GK37,GP37,GU37) -> 6515513.2 | I37: =SUM(O37,S37,X37,AC37,AH37,AM37,AR37,AW37,BB37,BG37,BL37,BQ37,BV37,CA37,CF37,CK37,CP37,CU37,CZ37,DE37,DJ37,DO37,DT37,DY37,ED37,EI37,EN37,ES37,EX37,FC37,FH37,FM37,FR37,FW37,GB37,GG37,GL37,GQ37,GV37) -> 346853.07 | J37: =I37/F37 -> 2668100.5 | K37: =I37/F37-H37 -> -3847412.7 | L37: =J37-G37 -> -27837931 | M37: 27837931 | N37: 0 | O37: 0 | T37: 0 | U37: =T37-Q37 -> 0 | Y37: =X37/F37 -> 0 | Z37: =Y37-V37 -> 0 | AD37: =AC37/F37 -> 0 | AE37: =AD37-AA37 -> 0 | AH37: -40754.673 | AI37: =AH37/F37 -> -313497.49 | AJ37: =AI37-AF37 -> -313497.49 | AN37: =AM37/F37 -> 0 | AO37: =AN37-AK37 -> 0 | AR37: 40754.67 | AS37: =AR37/F37 -> 313497.46 | AT37: =AS37-AP37 -> 313497.46 | AX37: =AW37/F37 -> 0 | AY37: =AX37-AU37 -> 0 | BC37: =BB37/F37 -> 0 | BH37: =BG37/F37 -> 0 | BI37: =BH37-BE37 -> 0 | BM37: =BL37/F37 -> 0 | BN37: =BM37-BJ37 -> 0 | BO37: 528762.93 | BQ37: 68739.18 | BR37: =BQ37/F37 -> 528762.92 | BS37: =BR37-BO37 -> -0.006923077 | BT37: 7700.43 | BV37: 1001.06 | BW37: 7700.43 | BX37: =BW37-BT37 -> 0 | CB37: =CA37/F37 -> 0 | CC37: =CB37-BY37 -> 0 | CG37: =CF37/F37 -> 0 | CH37: =CG37-CD37 -> 0 | CL37: =CK37/F37 -> 0 | CM37: =CL37-CI37 -> 0 | CR37: =ROUND(CQ37-CN37,2) -> 0 | CW37: =CV37-CS37 -> 0 | DA37: =ROUND(CZ37/F37,2) -> 0 | DB37: =ROUND(DA37-CX37,2) -> 0 | DF37: =DE37/F37 -> 0 | DG37: =DC37-DF37 -> 0 | DK37: =DJ37/F37 -> 0 | DL37: =DK37-DH37 -> 0 | DP37: =DO37/F37 -> 0 | DQ37: =DP37-DM37 -> 0 | DU37: =DT37/F37 -> 0 | DV37: =DU37-DR37 -> 0 | DZ37: =ROUND(DY37/F37,2) -> 0 | EA37: =ROUND(DZ37-DW37,2) -> 0 | EF37: =EE37-EB37 -> 0 | EJ37: =ROUND(EI37/F37,2) -> 0 | EK37: =ROUND(EJ37-EG37,2) -> 0 | EO37: =ROUND(EN37/F37,2) -> 0 | EP37: =ROUND(EO37-EL37,2) -> 0 | ET37: =ROUND(ES37/F37,2) -> 0 | EU37: =ROUND(ET37-EQ37,2) -> 0 | EY37: =ROUND(EX37/F37,2) -> 0 | EZ37: =ROUND(EY37-EV37,2) -> 0 | FD37: =ROUND(FC37/F37,2) -> 0 | FE37: =ROUND(FD37-FA37,2) -> 0 | FF37: 2131637.2 | FH37: 277112.83 | FI37: =FH37/F37 -> 2131637.2 | FJ37: =ROUND(FI37-FF37,2) -> -0.02 | FL37: 6515513.2 | FN37: =ROUND(FM37/F37,2) -> 0 | FO37: =ROUND(FN37-FK37,2) -> 0 | FS37: =ROUND(FR37/F37,2) -> 0 | FT37: =FS37-FP37 -> 0 | FX37: =ROUND(FW37/F37,2) -> 0 | FY37: =FX37-FU37 -> 0 | GC37: =ROUND(GB37/F37,2) -> 0 | GD37: =GC37-FZ37 -> 0 | GH37: =GG37/F37 -> 0 | GI37: =GH37-GE37 -> 0 | GM37: =GL37/F37 -> 0 | GN37: =GM37-GJ37 -> 0 | GR37: =GQ37/F37 -> 0 | GS37: =GR37-GO37 -> 0 | GW37: =ROUND(GV37/F37,2) -> 0 | GX37: =GW37-GT37 -> 0
B38: 2370 | E38: 工程施工 | F38: 0.09 | G38: =SUM(M38,P38:Q38,V38,AA38,AF38,AK38,AP38,AU38,AZ38,BE38,BJ38,BO38,BT38,BY38,CD38,CI38,CN38,CS38,CX38,DC38,DH38,DM38,DR38,DW38,EB38,EG38,EL38,EQ38,EV38,FA38,FF38,FK38,FP38,FU38,FZ38,GE38,GJ38,GO38,GT38) -> 1.334946e+08 | H38: =SUM(N38,R38,W38,AB38,AG38,AL38,AQ38,AV38,BA38,BF38,BK38,BP38,BU38,BZ38,CE38,CJ38,CO38,CT38,CY38,DD38,DI38,DN38,DS38,DX38,EC38,EH38,EM38,ER38,EW38,FB38,FG38,FL38,FQ38,FV38,GA38,GF38,GK38,GP38,GU38) -> 1.547219e+08 | I38: =SUM(O38,S38,X38,AC38,AH38,AM38,AR38,AW38,BB38,BG38,BL38,BQ38,BV38,CA38,CF38,CK38,CP38,CU38,CZ38,DE38,DJ38,DO38,DT38,DY38,ED38,EI38,EN38,ES38,EX38,FC38,FH38,FM38,FR38,FW38,GB38,GG38,GL38,GQ38,GV38) -> 12014514 | J38: =I38/F38 -> 1.334946e+08 | K38: =I38/F38-H38 -> -21227302 | L38: =J38-G38 -> 0 | M38: 1.32518e+08 | N38: 0 | O38: 11926620 | T38: 0 | U38: =T38-Q38 -> 0 | Y38: =X38/F38 -> 0 | Z38: =Y38-V38 -> 0 | AB38: 5994000 | AD38: =AC38/F38 -> 0 | AE38: =AD38-AA38 -> 0 | AG38: 91743119 | AH38: 0 | AI38: =AH38/F38 -> 0 | AJ38: =AI38-AF38 -> 0 | AN38: =AM38/F38 -> 0 | AO38: =AN38-AK38 -> 0 | AS38: =AR38/F38 -> 0 | AT38: =AS38-AP38 -> 0 | AX38: =AW38/F38 -> 0 | AY38: =AX38-AU38 -> 0 | BC38: =BB38/F38 -> 0 | BH38: =BG38/F38 -> 0 | BI38: =BH38-BE38 -> 0 | BM38: =BL38/F38 -> 0 | BN38: =BM38-BJ38 -> 0 | BR38: =BQ38/F38 -> 0 | BS38: =BR38-BO38 -> 0 | BT38: -11400 | BV38: -1026 | BW38: -11400 | BX38: =BW38-BT38 -> 0 | BY38: 988000 | CA38: 88920 | CB38: =CA38/F38 -> 988000 | CC38: =CB38-BY38 -> 0 | CG38: =CF38/F38 -> 0 | CH38: =CG38-CD38 -> 0 | CL38: =CK38/F38 -> 0 | CM38: =CL38-CI38 -> 0 | CR38: =ROUND(CQ38-CN38,2) -> 0 | CW38: =CV38-CS38 -> 0 | DA38: =ROUND(CZ38/F38,2) -> 0 | DB38: =ROUND(DA38-CX38,2) -> 0 | DF38: =DE38/F38 -> 0 | DG38: =DC38-DF38 -> 0 | DK38: =DJ38/F38 -> 0 | DL38: =DK38-DH38 -> 0 | DP38: =DO38/F38 -> 0 | DQ38: =DP38-DM38 -> 0 | DU38: =DT38/F38 -> 0 | DV38: =DU38-DR38 -> 0 | DZ38: =ROUND(DY38/F38,2) -> 0 | EA38: =ROUND(DZ38-DW38,2) -> 0 | EF38: =EE38-EB38 -> 0 | EJ38: =ROUND(EI38/F38,2) -> 0 | EK38: =ROUND(EJ38-EG38,2) -> 0 | EO38: =ROUND(EN38/F38,2) -> 0 | EP38: =ROUND(EO38-EL38,2) -> 0 | ET38: =ROUND(ES38/F38,2) -> 0 | EU38: =ROUND(ET38-EQ38,2) -> 0 | EW38: 50000000 | EY38: =ROUND(EX38/F38,2) -> 0 | EZ38: =ROUND(EY38-EV38,2) -> 0 | FD38: =ROUND(FC38/F38,2) -> 0 | FE38: =ROUND(FD38-FA38,2) -> 0 | FI38: =FH38/F38 -> 0 | FJ38: =ROUND(FI38-FF38,2) -> 0 | FL38: 6984780 | FN38: =ROUND(FM38/F38,2) -> 0 | FO38: =ROUND(FN38-FK38,2) -> 0 | FS38: =ROUND(FR38/F38,2) -> 0 | FT38: =FS38-FP38 -> 0 | FX38: =ROUND(FW38/F38,2) -> 0 | FY38: =FX38-FU38 -> 0 | GC38: =ROUND(GB38/F38,2) -> 0 | GD38: =GC38-FZ38 -> 0 | GH38: =GG38/F38 -> 0 | GI38: =GH38-GE38 -> 0 | GM38: =GL38/F38 -> 0 | GN38: =GM38-GJ38 -> 0 | GR38: =GQ38/F38 -> 0 | GS38: =GR38-GO38 -> 0 | GW38: =ROUND(GV38/F38,2) -> 0 | GX38: =GW38-GT38 -> 0
B39: 2370 | E39: 设计咨询 | F39: 0.06 | G39: =SUM(M39,P39:Q39,V39,AA39,AF39,AK39,AP39,AU39,AZ39,BE39,BJ39,BO39,BT39,BY39,CD39,CI39,CN39,CS39,CX39,DC39,DH39,DM39,DR39,DW39,EB39,EG39,EL39,EQ39,EV39,FA39,FF39,FK39,FP39,FU39,FZ39,GE39,GJ39,GO39,GT39) -> 3754538.9 | H39: =SUM(N39,R39,W39,AB39,AG39,AL39,AQ39,AV39,BA39,BF39,BK39,BP39,BU39,BZ39,CE39,CJ39,CO39,CT39,CY39,DD39,DI39,DN39,DS39,DX39,EC39,EH39,EM39,ER39,EW39,FB39,FG39,FL39,FQ39,FV39,GA39,GF39,GK39,GP39,GU39) -> 325968.49 | I39: =SUM(O39,S39,X39,AC39,AH39,AM39,AR39,AW39,BB39,BG39,BL39,BQ39,BV39,CA39,CF39,CK39,CP39,CU39,CZ39,DE39,DJ39,DO39,DT39,DY39,ED39,EI39,EN39,ES39,EX39,FC39,FH39,FM39,FR39,FW39,GB39,GG39,GL39,GQ39,GV39) -> 225272.35 | J39: =I39/F39 -> 3754539.2 | K39: =I39/F39-H39 -> 3428570.8 | L39: =J39-G39 -> 0.37416667 | M39: 3432060.4 | N39: 0 | O39: 205923.62 | T39: 0 | U39: =T39-Q39 -> 0 | Y39: =X39/F39 -> 0 | Z39: =Y39-V39 -> 0 | AD39: =AC39/F39 -> 0 | AE39: =AD39-AA39 -> 0 | AI39: =AH39/F39 -> 0 | AJ39: =AI39-AF39 -> 0 | AN39: =AM39/F39 -> 0 | AO39: =AN39-AK39 -> 0 | AS39: =AR39/F39 -> 0 | AT39: =AS39-AP39 -> 0 | AU39: 13722.82 | AW39: 823.36905 | AX39: =AW39/F39 -> 13722.817 | AY39: =AX39-AU39 -> -0.0025 | AZ39: 14843.02 | BB39: 890.58 | BC39: =BB39/F39 -> 14843 | BE39: 15144.45 | BG39: 908.67 | BH39: =BG39/F39 -> 15144.5 | BI39: =BH39-BE39 -> 0.05 | BJ39: 19643.44 | BL39: 1178.61 | BM39: =BL39/F39 -> 19643.5 | BN39: =BM39-BJ39 -> 0.06 | BO39: 24445.79 | BQ39: 1466.7474 | BR39: =BQ39/F39 -> 24445.79 | BS39: =BR39-BO39 -> 0 | BT39: 15189.23 | BV39: 911.35 | BW39: 15189.23 | BX39: =BW39-BT39 -> 0 | BY39: 48914.52 | CA39: 2934.87 | CB39: =CA39/F39 -> 48914.5 | CC39: =CB39-BY39 -> -0.02 | CD39: 8889.94 | CF39: 533.4 | CG39: =CF39/F39 -> 8890 | CH39: =CG39-CD39 -> 0.06 | CI39: 5262.3 | CK39: 315.74 | CL39: =CK39/F39 -> 5262.3333 | CM39: =CL39-CI39 -> 0.033333333 | CN39: 5946.21 | CP39: 356.77 | CQ39: 5946.21 | CR39: =ROUND(CQ39-CN39,2) -> 0 | CS39: 5966.55 | CU39: 357.99 | CV39: 5966.55 | CW39: =CV39-CS39 -> 0 | CX39: 1781.96 | CZ39: 106.92 | DA39: =ROUND(CZ39/F39,2) -> 1782 | DB39: =ROUND(DA39-CX39,2) -> 0.04 | DF39: =DE39/F39 -> 0 | DG39: =DC39-DF39 -> 0 | DH39: 3490 | DJ39: 209.4 | DK39: =DJ39/F39 -> 3490 | DL39: =DK39-DH39 -> 0 | DM39: 4526.29 | DO39: 271.58 | DP39: =DO39/F39 -> 4526.3333 | DQ39: =DP39-DM39 -> 0.043333333 | DR39: 4129.5 | DT39: 247.77 | DU39: =DT39/F39 -> 4129.5 | DV39: =DU39-DR39 -> 0 | DW39: 4167.98 | DY39: 250.08 | DZ39: =ROUND(DY39/F39,2) -> 4168 | EA39: =ROUND(DZ39-DW39,2) -> 0.02 | EB39: 8764.47 | ED39: 525.8682 | EE39: 8764.47 | EF39: =EE39-EB39 -> 0 | EG39: 22411.79 | EH39: 208318.47 | EI39: 1344.71 | EJ39: =ROUND(EI39/F39,2) -> 22411.83 | EK39: =ROUND(EJ39-EG39,2) -> 0.04 | EL39: 2036.6 | EN39: 122.2 | EO39: =ROUND(EN39/F39,2) -> 2036.67 | EP39: =ROUND(EO39-EL39,2) -> 0.07 | EQ39: 2528.88 | ES39: 151.73 | ET39: =ROUND(ES39/F39,2) -> 2528.83 | EU39: =ROUND(ET39-EQ39,2) -> -0.05 | EV39: 2601.28 | EW39: 26977.27 | EX39: 156.08 | EY39: =ROUND(EX39/F39,2) -> 2601.33 | EZ39: =ROUND(EY39-EV39,2) -> 0.05 | FD39: =ROUND(FC39/F39,2) -> 0 | FE39: =ROUND(FD39-FA39,2) -> 0 | FF39: 19872.09 | FH39: 1192.33 | FI39: =FH39/F39 -> 19872.167 | FJ39: =ROUND(FI39-FF39,2) -> 0.08 | FK39: 38111.29 | FM39: 2286.68 | FN39: =ROUND(FM39/F39,2) -> 38111.33 | FO39: =ROUND(FN39-FK39,2) -> 0.04 | FP39: 30088.1 | FQ39: 0 | FR39: 1805.29 | FS39: =ROUND(FR39/F39,2) -> 30088.17 | FT39: =FS39-FP39 -> 0.07 | FX39: =ROUND(FW39/F39,2) -> 0 | FY39: =FX39-FU39 -> 0 | GC39: =ROUND(GB39/F39,2) -> 0 | GD39: =GC39-FZ39 -> 0 | GF39: 90672.75 | GH39: =GG39/F39 -> 0 | GI39: =GH39-GE39 -> 0 | GM39: =GL39/F39 -> 0 | GN39: =GM39-GJ39 -> 0 | GR39: =GQ39/F39 -> 0 | GS39: =GR39-GO39 -> 0 | GW39: =ROUND(GV39/F39,2) -> 0 | GX39: =GW39-GT39 -> 0
B40: 2370 | D40: 2370（馆陶二期）【23出售】 | E40: 商品销售 | F40: 0.13 | G40: =SUM(M40,P40:Q40,V40,AA40,AF40,AK40,AP40,AU40,AZ40,BE40,BJ40,BO40,BT40,BY40,CD40,CI40,CN40,CS40,CX40,DC40,DH40,DM40,DR40,DW40,EB40,EG40,EL40,EQ40,EV40,FA40,FF40,FK40,FP40,FU40,FZ40,GE40,GJ40,GO40,GT40) -> 45003963 | H40: =SUM(N40,R40,W40,AB40,AG40,AL40,AQ40,AV40,BA40,BF40,BK40,BP40,BU40,BZ40,CE40,CJ40,CO40,CT40,CY40,DD40,DI40,DN40,DS40,DX40,EC40,EH40,EM40,ER40,EW40,FB40,FG40,FL40,FQ40,FV40,GA40,GF40,GK40,GP40,GU40) -> 41156551 | I40: =SUM(O40,S40,X40,AC40,AH40,AM40,AR40,AW40,BB40,BG40,BL40,BQ40,BV40,CA40,CF40,CK40,CP40,CU40,CZ40,DE40,DJ40,DO40,DT40,DY40,ED40,EI40,EN40,ES40,EX40,FC40,FH40,FM40,FR40,FW40,GB40,GG40,GL40,GQ40,GV40) -> 5850515.2 | J40: =I40/F40 -> 45003963 | K40: =I40/F40-H40 -> 3847412.7 | L40: =J40-G40 -> 0.019661538 | M40: 45317461 | N40: 0 | O40: 5891269.9 | P40: -313497.48 | T40: 0 | U40: =T40-Q40 -> 0 | Y40: =X40/F40 -> 0 | Z40: =Y40-V40 -> 0 | AD40: =AC40/F40 -> 0 | AE40: =AD40-AA40 -> 0 | AI40: =AH40/F40 -> 0 | AJ40: =AI40-AF40 -> 0 | AN40: =AM40/F40 -> 0 | AO40: =AN40-AK40 -> 0 | AR40: -40754.67 | AS40: =AR40/F40 -> -313497.46 | AT40: =AS40-AP40 -> -313497.46 | AX40: =AW40/F40 -> 0 | AY40: =AX40-AU40 -> 0 | BC40: =BB40/F40 -> 0 | BH40: =BG40/F40 -> 0 | BI40: =BH40-BE40 -> 0 | BM40: =BL40/F40 -> 0 | BN40: =BM40-BJ40 -> 0 | BR40: =BQ40/F40 -> 0 | BS40: =BR40-BO40 -> 0 | BX40: =BW40-BT40 -> 0 | CB40: =CA40/F40 -> 0 | CC40: =CB40-BY40 -> 0 | CG40: =CF40/F40 -> 0 | CH40: =CG40-CD40 -> 0 | CL40: =CK40/F40 -> 0 | CM40: =CL40-CI40 -> 0 | CR40: =ROUND(CQ40-CN40,2) -> 0 | CW40: =CV40-CS40 -> 0 | DA40: =ROUND(CZ40/F40,2) -> 0 | DB40: =ROUND(DA40-CX40,2) -> 0 | DF40: =DE40/F40 -> 0 | DG40: =DC40-DF40 -> 0 | DK40: =DJ40/F40 -> 0 | DL40: =DK40-DH40 -> 0 | DP40: =DO40/F40 -> 0 | DQ40: =DP40-DM40 -> 0 | DU40: =DT40/F40 -> 0 | DV40: =DU40-DR40 -> 0 | DZ40: =ROUND(DY40/F40,2) -> 0 | EA40: =ROUND(DZ40-DW40,2) -> 0 | EF40: =EE40-EB40 -> 0 | EJ40: =ROUND(EI40/F40,2) -> 0 | EK40: =ROUND(EJ40-EG40,2) -> 0 | EO40: =ROUND(EN40/F40,2) -> 0 | EP40: =ROUND(EO40-EL40,2) -> 0 | ET40: =ROUND(ES40/F40,2) -> 0 | EU40: =ROUND(ET40-EQ40,2) -> 0 | EY40: =ROUND(EX40/F40,2) -> 0 | EZ40: =ROUND(EY40-EV40,2) -> 0 | FD40: =ROUND(FC40/F40,2) -> 0 | FE40: =ROUND(FD40-FA40,2) -> 0 | FI40: =FH40/F40 -> 0 | FJ40: =ROUND(FI40-FF40,2) -> 0 | FL40: 41156551 | FN40: =ROUND(FM40/F40,2) -> 0 | FO40: =ROUND(FN40-FK40,2) -> 0 | FS40: =ROUND(FR40/F40,2) -> 0 | FT40: =FS40-FP40 -> 0 | FX40: =ROUND(FW40/F40,2) -> 0 | FY40: =FX40-FU40 -> 0 | GC40: =ROUND(GB40/F40,2) -> 0 | GD40: =GC40-FZ40 -> 0 | GH40: =GG40/F40 -> 0 | GI40: =GH40-GE40 -> 0 | GM40: =GL40/F40 -> 0 | GN40: =GM40-GJ40 -> 0 | GR40: =GQ40/F40 -> 0 | GS40: =GR40-GO40 -> 0 | GW40: =ROUND(GV40/F40,2) -> 0 | GX40: =GW40-GT40 -> 0
B41: 2370 | E41: 工程施工 | F41: 0.09 | G41: =SUM(M41,P41:Q41,V41,AA41,AF41,AK41,AP41,AU41,AZ41,BE41,BJ41,BO41,BT41,BY41,CD41,CI41,CN41,CS41,CX41,DC41,DH41,DM41,DR41,DW41,EB41,EG41,EL41,EQ41,EV41,FA41,FF41,FK41,FP41,FU41,FZ41,GE41,GJ41,GO41,GT41) -> 58034266 | H41: =SUM(N41,R41,W41,AB41,AG41,AL41,AQ41,AV41,BA41,BF41,BK41,BP41,BU41,BZ41,CE41,CJ41,CO41,CT41,CY41,DD41,DI41,DN41,DS41,DX41,EC41,EH41,EM41,ER41,EW41,FB41,FG41,FL41,FQ41,FV41,GA41,GF41,GK41,GP41,GU41) -> 36806964 | I41: =SUM(O41,S41,X41,AC41,AH41,AM41,AR41,AW41,BB41,BG41,BL41,BQ41,BV41,CA41,CF41,CK41,CP41,CU41,CZ41,DE41,DJ41,DO41,DT41,DY41,ED41,EI41,EN41,ES41,EX41,FC41,FH41,FM41,FR41,FW41,GB41,GG41,GL41,GQ41,GV41) -> 5223084 | J41: =I41/F41 -> 58034266 | K41: =I41/F41-H41 -> 21227302 | L41: =J41-G41 -> 0.13333334 | M41: 54954660 | N41: 0 | O41: 4945919.4 | T41: 0 | U41: =T41-Q41 -> 0 | Y41: =X41/F41 -> 0 | Z41: =Y41-V41 -> 0 | AD41: =AC41/F41 -> 0 | AE41: =AD41-AA41 -> 0 | AI41: =AH41/F41 -> 0 | AJ41: =AI41-AF41 -> 0 | AN41: =AM41/F41 -> 0 | AO41: =AN41-AK41 -> 0 | AS41: =AR41/F41 -> 0 | AT41: =AS41-AP41 -> 0 | AX41: =AW41/F41 -> 0 | AY41: =AX41-AU41 -> 0 | BC41: =BB41/F41 -> 0 | BH41: =BG41/F41 -> 0 | BI41: =BH41-BE41 -> 0 | BM41: =BL41/F41 -> 0 | BN41: =BM41-BJ41 -> 0 | BR41: =BQ41/F41 -> 0 | BS41: =BR41-BO41 -> 0 | BX41: =BW41-BT41 -> 0 | CB41: =CA41/F41 -> 0 | CC41: =CB41-BY41 -> 0 | CG41: =CF41/F41 -> 0 | CH41: =CG41-CD41 -> 0 | CL41: =CK41/F41 -> 0 | CM41: =CL41-CI41 -> 0 | CR41: =ROUND(CQ41-CN41,2) -> 0 | CW41: =CV41-CS41 -> 0 | DA41: =ROUND(CZ41/F41,2) -> 0 | DB41: =ROUND(DA41-CX41,2) -> 0 | DF41: =DE41/F41 -> 0 | DG41: =DC41-DF41 -> 0 | DK41: =DJ41/F41 -> 0 | DL41: =DK41-DH41 -> 0 | DP41: =DO41/F41 -> 0 | DQ41: =DP41-DM41 -> 0 | DU41: =DT41/F41 -> 0 | DV41: =DU41-DR41 -> 0 | DZ41: =ROUND(DY41/F41,2) -> 0 | EA41: =ROUND(DZ41-DW41,2) -> 0 | EF41: =EE41-EB41 -> 0 | EJ41: =ROUND(EI41/F41,2) -> 0 | EK41: =ROUND(EJ41-EG41,2) -> 0 | EO41: =ROUND(EN41/F41,2) -> 0 | EP41: =ROUND(EO41-EL41,2) -> 0 | ET41: =ROUND(ES41/F41,2) -> 0 | EU41: =ROUND(ET41-EQ41,2) -> 0 | EY41: =ROUND(EX41/F41,2) -> 0 | EZ41: =ROUND(EY41-EV41,2) -> 0 | FD41: =ROUND(FC41/F41,2) -> 0 | FE41: =ROUND(FD41-FA41,2) -> 0 | FF41: 3079606.2 | FH41: 277164.57 | FI41: =FH41/F41 -> 3079606.3 | FJ41: =ROUND(FI41-FF41,2) -> 0.13 | FL41: 36806964 | FN41: =ROUND(FM41/F41,2) -> 0 | FO41: =ROUND(FN41-FK41,2) -> 0 | FS41: =ROUND(FR41/F41,2) -> 0 | FT41: =FS41-FP41 -> 0 | FX41: =ROUND(FW41/F41,2) -> 0 | FY41: =FX41-FU41 -> 0 | GC41: =ROUND(GB41/F41,2) -> 0 | GD41: =GC41-FZ41 -> 0 | GH41: =GG41/F41 -> 0 | GI41: =GH41-GE41 -> 0 | GM41: =GL41/F41 -> 0 | GN41: =GM41-GJ41 -> 0 | GR41: =GQ41/F41 -> 0 | GS41: =GR41-GO41 -> 0 | GW41: =ROUND(GV41/F41,2) -> 0 | GX41: =GW41-GT41 -> 0
B42: 2370 | E42: 设计咨询 | F42: 0.06 | G42: =SUM(M42,P42:Q42,V42,AA42,AF42,AK42,AP42,AU42,AZ42,BE42,BJ42,BO42,BT42,BY42,CD42,CI42,CN42,CS42,CX42,DC42,DH42,DM42,DR42,DW42,EB42,EG42,EL42,EQ42,EV42,FA42,FF42,FK42,FP42,FU42,FZ42,GE42,GJ42,GO42,GT42) -> 5181033.4 | H42: =SUM(N42,R42,W42,AB42,AG42,AL42,AQ42,AV42,BA42,BF42,BK42,BP42,BU42,BZ42,CE42,CJ42,CO42,CT42,CY42,DD42,DI42,DN42,DS42,DX42,EC42,EH42,EM42,ER42,EW42,FB42,FG42,FL42,FQ42,FV42,GA42,GF42,GK42,GP42,GU42) -> 8613093.8 | I42: =SUM(O42,S42,X42,AC42,AH42,AM42,AR42,AW42,BB42,BG42,BL42,BQ42,BV42,CA42,CF42,CK42,CP42,CU42,CZ42,DE42,DJ42,DO42,DT42,DY42,ED42,EI42,EN42,ES42,EX42,FC42,FH42,FM42,FR42,FW42,GB42,GG42,GL42,GQ42,GV42) -> 310862 | J42: =I42/F42 -> 5181033.3 | K42: =I42/F42-H42 -> -3432060.5 | L42: =J42-G42 -> -0.101 | M42: 3432855.3 | N42: 0 | O42: 205971.32 | T42: 0 | U42: =T42-Q42 -> 0 | Y42: =X42/F42 -> 0 | Z42: =Y42-V42 -> 0 | AD42: =AC42/F42 -> 0 | AE42: =AD42-AA42 -> 0 | AI42: =AH42/F42 -> 0 | AJ42: =AI42-AF42 -> 0 | AN42: =AM42/F42 -> 0 | AO42: =AN42-AK42 -> 0 | AS42: =AR42/F42 -> 0 | AT42: =AS42-AP42 -> 0 | AX42: =AW42/F42 -> 0 | AY42: =AX42-AU42 -> 0 | BC42: =BB42/F42 -> 0 | BH42: =BG42/F42 -> 0 | BI42: =BH42-BE42 -> 0 | BM42: =BL42/F42 -> 0 | BN42: =BM42-BJ42 -> 0 | BQ42: 0 | BR42: =BQ42/F42 -> 0 | BS42: =BR42-BO42 -> 0 | BX42: =BW42-BT42 -> 0 | CB42: =CA42/F42 -> 0 | CC42: =CB42-BY42 -> 0 | CG42: =CF42/F42 -> 0 | CH42: =CG42-CD42 -> 0 | CL42: =CK42/F42 -> 0 | CM42: =CL42-CI42 -> 0 | CR42: =ROUND(CQ42-CN42,2) -> 0 | CW42: =CV42-CS42 -> 0 | DA42: =ROUND(CZ42/F42,2) -> 0 | DB42: =ROUND(DA42-CX42,2) -> 0 | DF42: =DE42/F42 -> 0 | DG42: =DC42-DF42 -> 0 | DK42: =DJ42/F42 -> 0 | DL42: =DK42-DH42 -> 0 | DP42: =DO42/F42 -> 0 | DQ42: =DP42-DM42 -> 0 | DU42: =DT42/F42 -> 0 | DV42: =DU42-DR42 -> 0 | DZ42: =ROUND(DY42/F42,2) -> 0 | EA42: =ROUND(DZ42-DW42,2) -> 0 | EF42: =EE42-EB42 -> 0 | EJ42: =ROUND(EI42/F42,2) -> 0 | EK42: =ROUND(EJ42-EG42,2) -> 0 | EO42: =ROUND(EN42/F42,2) -> 0 | EP42: =ROUND(EO42-EL42,2) -> 0 | ET42: =ROUND(ES42/F42,2) -> 0 | EU42: =ROUND(ET42-EQ42,2) -> 0 | EW42: 6864915.6 | EY42: =ROUND(EX42/F42,2) -> 0 | EZ42: =ROUND(EY42-EV42,2) -> 0 | FD42: =ROUND(FC42/F42,2) -> 0 | FE42: =ROUND(FD42-FA42,2) -> 0 | FF42: 1748178.1 | FH42: 104890.68 | FI42: =FH42/F42 -> 1748178 | FJ42: =ROUND(FI42-FF42,2) -> -0.1 | FL42: 1748178.1 | FN42: =ROUND(FM42/F42,2) -> 0 | FO42: =ROUND(FN42-FK42,2) -> 0 | FS42: =ROUND(FR42/F42,2) -> 0 | FT42: =FS42-FP42 -> 0 | FX42: =ROUND(FW42/F42,2) -> 0 | FY42: =FX42-FU42 -> 0 | GC42: =ROUND(GB42/F42,2) -> 0 | GD42: =GC42-FZ42 -> 0 | GH42: =GG42/F42 -> 0 | GI42: =GH42-GE42 -> 0 | GM42: =GL42/F42 -> 0 | GN42: =GM42-GJ42 -> 0 | GR42: =GQ42/F42 -> 0 | GS42: =GR42-GO42 -> 0 | GW42: =ROUND(GV42/F42,2) -> 0 | GX42: =GW42-GT42 -> 0
B43: 2440 | D43: 2440（绿港一期) | E43: 商品销售 | F43: 0.16 | G43: =SUM(M43,P43:Q43,V43,AA43,AF43,AK43,AP43,AU43,AZ43,BE43,BJ43,BO43,BT43,BY43,CD43,CI43,CN43,CS43,CX43,DC43,DH43,DM43,DR43,DW43,EB43,EG43,EL43,EQ43,EV43,FA43,FF43,FK43,FP43,FU43,FZ43,GE43,GJ43,GO43,GT43) -> 286222.47 | H43: =SUM(N43,R43,W43,AB43,AG43,AL43,AQ43,AV43,BA43,BF43,BK43,BP43,BU43,BZ43,CE43,CJ43,CO43,CT43,CY43,DD43,DI43,DN43,DS43,DX43,EC43,EH43,EM43,ER43,EW43,FB43,FG43,FL43,FQ43,FV43,GA43,GF43,GK43,GP43,GU43) -> 5762453.6 | I43: =SUM(O43,S43,X43,AC43,AH43,AM43,AR43,AW43,BB43,BG43,BL43,BQ43,BV43,CA43,CF43,CK43,CP43,CU43,CZ43,DE43,DJ43,DO43,DT43,DY43,ED43,EI43,EN43,ES43,EX43,FC43,FH43,FM43,FR43,FW43,GB43,GG43,GL43,GQ43,GV43) -> 921992.58 | J43: =I43/F43 -> 5762453.6 | M43: 286222.47 | N43: 5762453.6 | O43: 921992.58 | T43: 0 | U43: =T43-Q43 -> 0 | Y43: =X43/F43 -> 0 | Z43: =Y43-V43 -> 0 | AD43: =AC43/F43 -> 0 | AE43: =AD43-AA43 -> 0 | AI43: =AH43/F43 -> 0 | AJ43: =AI43-AF43 -> 0 | AN43: =AM43/F43 -> 0 | AO43: =AN43-AK43 -> 0 | AS43: =AR43/F43 -> 0 | AT43: =AS43-AP43 -> 0 | AX43: =AW43/F43 -> 0 | AY43: =AX43-AU43 -> 0 | BC43: =BB43/F43 -> 0 | BD43: =BC43-AZ43 -> 0 | BH43: =BG43/F43 -> 0 | BI43: =BH43-BE43 -> 0 | BM43: =BL43/F43 -> 0 | BN43: =BM43-BJ43 -> 0 | BR43: =BQ43/F43 -> 0 | BS43: =BR43-BO43 -> 0 | BX43: =BW43-BT43 -> 0 | CB43: =CA43/F43 -> 0 | CC43: =CB43-BY43 -> 0 | CG43: =CF43/F43 -> 0 | CH43: =CG43-CD43 -> 0 | CL43: =CK43/F43 -> 0 | CM43: =CL43-CI43 -> 0 | CR43: =ROUND(CQ43-CN43,2) -> 0 | CW43: =CV43-CS43 -> 0 | DA43: =ROUND(CZ43/F43,2) -> 0 | DB43: =ROUND(DA43-CX43,2) -> 0 | DF43: =DE43/F43 -> 0 | DG43: =DC43-DF43 -> 0 | DK43: =DJ43/F43 -> 0 | DL43: =DK43-DH43 -> 0 | DP43: =DO43/F43 -> 0 | DQ43: =DP43-DM43 -> 0 | DU43: =DT43/F43 -> 0 | DV43: =DU43-DR43 -> 0 | DZ43: =ROUND(DY43/F43,2) -> 0 | EA43: =ROUND(DZ43-DW43,2) -> 0 | EF43: =EE43-EB43 -> 0 | EJ43: =ROUND(EI43/F43,2) -> 0 | EK43: =ROUND(EJ43-EG43,2) -> 0 | EO43: =ROUND(EN43/F43,2) -> 0 | EP43: =ROUND(EO43-EL43,2) -> 0 | ET43: =ROUND(ES43/F43,2) -> 0 | EU43: =ROUND(ET43-EQ43,2) -> 0 | EY43: =ROUND(EX43/F43,2) -> 0 | EZ43: =ROUND(EY43-EV43,2) -> 0 | FD43: =ROUND(FC43/F43,2) -> 0 | FE43: =ROUND(FD43-FA43,2) -> 0 | FI43: =FH43/F43 -> 0 | FJ43: =ROUND(FI43-FF43,2) -> 0 | FN43: =ROUND(FM43/F43,2) -> 0 | FO43: =ROUND(FN43-FK43,2) -> 0 | FS43: =ROUND(FR43/F43,2) -> 0 | FT43: =FS43-FP43 -> 0 | FX43: =ROUND(FW43/F43,2) -> 0 | FY43: =FX43-FU43 -> 0 | GC43: =ROUND(GB43/F43,2) -> 0 | GD43: =GC43-FZ43 -> 0 | GH43: =GG43/F43 -> 0 | GI43: =GH43-GE43 -> 0 | GM43: =GL43/F43 -> 0 | GN43: =GM43-GJ43 -> 0 | GR43: =GQ43/F43 -> 0 | GS43: =GR43-GO43 -> 0 | GW43: =ROUND(GV43/F43,2) -> 0 | GX43: =GW43-GT43 -> 0
B44: 2440 | F44: 0.13 | G44: =SUM(M44,P44:Q44,V44,AA44,AF44,AK44,AP44,AU44,AZ44,BE44,BJ44,BO44,BT44,BY44,CD44,CI44,CN44,CS44,CX44,DC44,DH44,DM44,DR44,DW44,EB44,EG44,EL44,EQ44,EV44,FA44,FF44,FK44,FP44,FU44,FZ44,GE44,GJ44,GO44,GT44) -> 314857.77 | H44: =SUM(N44,R44,W44,AB44,AG44,AL44,AQ44,AV44,BA44,BF44,BK44,BP44,BU44,BZ44,CE44,CJ44,CO44,CT44,CY44,DD44,DI44,DN44,DS44,DX44,EC44,EH44,EM44,ER44,EW44,FB44,FG44,FL44,FQ44,FV44,GA44,GF44,GK44,GP44,GU44) -> 0 | I44: =SUM(O44,S44,X44,AC44,AH44,AM44,AR44,AW44,BB44,BG44,BL44,BQ44,BV44,CA44,CF44,CK44,CP44,CU44,CZ44,DE44,DJ44,DO44,DT44,DY44,ED44,EI44,EN44,ES44,EX44,FC44,FH44,FM44,FR44,FW44,GB44,GG44,GL44,GQ44,GV44) -> 48957.309 | J44: =I44/F44 -> 376594.68 | M44: 314857.77 | N44: 0 | O44: 48957.309 | T44: 0 | U44: =T44-Q44 -> 0 | Y44: =X44/F44 -> 0 | Z44: =Y44-V44 -> 0 | AD44: =AC44/F44 -> 0 | AE44: =AD44-AA44 -> 0 | AI44: =AH44/F44 -> 0 | AJ44: =AI44-AF44 -> 0 | AN44: =AM44/F44 -> 0 | AO44: =AN44-AK44 -> 0 | AS44: =AR44/F44 -> 0 | AT44: =AS44-AP44 -> 0 | AX44: =AW44/F44 -> 0 | AY44: =AX44-AU44 -> 0 | BC44: =BB44/F44 -> 0 | BD44: =BC44-AZ44 -> 0 | BH44: =BG44/F44 -> 0 | BI44: =BH44-BE44 -> 0 | BM44: =BL44/F44 -> 0 | BN44: =BM44-BJ44 -> 0 | BR44: =BQ44/F44 -> 0 | BS44: =BR44-BO44 -> 0 | BX44: =BW44-BT44 -> 0 | CB44: =CA44/F44 -> 0 | CC44: =CB44-BY44 -> 0 | CG44: =CF44/F44 -> 0 | CH44: =CG44-CD44 -> 0 | CL44: =CK44/F44 -> 0 | CM44: =CL44-CI44 -> 0 | CR44: =ROUND(CQ44-CN44,2) -> 0 | CW44: =CV44-CS44 -> 0 | DA44: =ROUND(CZ44/F44,2) -> 0 | DB44: =ROUND(DA44-CX44,2) -> 0 | DF44: =DE44/F44 -> 0 | DG44: =DC44-DF44 -> 0 | DK44: =DJ44/F44 -> 0 | DL44: =DK44-DH44 -> 0 | DP44: =DO44/F44 -> 0 | DQ44: =DP44-DM44 -> 0 | DU44: =DT44/F44 -> 0 | DV44: =DU44-DR44 -> 0 | DZ44: =ROUND(DY44/F44,2) -> 0 | EA44: =ROUND(DZ44-DW44,2) -> 0 | EF44: =EE44-EB44 -> 0 | EJ44: =ROUND(EI44/F44,2) -> 0 | EK44: =ROUND(EJ44-EG44,2) -> 0 | EO44: =ROUND(EN44/F44,2) -> 0 | EP44: =ROUND(EO44-EL44,2) -> 0 | ET44: =ROUND(ES44/F44,2) -> 0 | EU44: =ROUND(ET44-EQ44,2) -> 0 | EY44: =ROUND(EX44/F44,2) -> 0 | EZ44: =ROUND(EY44-EV44,2) -> 0 | FD44: =ROUND(FC44/F44,2) -> 0 | FE44: =ROUND(FD44-FA44,2) -> 0 | FI44: =FH44/F44 -> 0 | FJ44: =ROUND(FI44-FF44,2) -> 0 | FN44: =ROUND(FM44/F44,2) -> 0 | FO44: =ROUND(FN44-FK44,2) -> 0 | FS44: =ROUND(FR44/F44,2) -> 0 | FT44: =FS44-FP44 -> 0 | FX44: =ROUND(FW44/F44,2) -> 0 | FY44: =FX44-FU44 -> 0 | GC44: =ROUND(GB44/F44,2) -> 0 | GD44: =GC44-FZ44 -> 0 | GH44: =GG44/F44 -> 0 | GI44: =GH44-GE44 -> 0 | GM44: =GL44/F44 -> 0 | GN44: =GM44-GJ44 -> 0 | GR44: =GQ44/F44 -> 0 | GS44: =GR44-GO44 -> 0 | GW44: =ROUND(GV44/F44,2) -> 0 | GX44: =GW44-GT44 -> 0
B45: 2440 | E45: 工程施工 | F45: 0.1 | G45: =SUM(M45,P45:Q45,V45,AA45,AF45,AK45,AP45,AU45,AZ45,BE45,BJ45,BO45,BT45,BY45,CD45,CI45,CN45,CS45,CX45,DC45,DH45,DM45,DR45,DW45,EB45,EG45,EL45,EQ45,EV45,FA45,FF45,FK45,FP45,FU45,FZ45,GE45,GJ45,GO45,GT45) -> 10136577 | H45: =SUM(N45,R45,W45,AB45,AG45,AL45,AQ45,AV45,BA45,BF45,BK45,BP45,BU45,BZ45,CE45,CJ45,CO45,CT45,CY45,DD45,DI45,DN45,DS45,DX45,EC45,EH45,EM45,ER45,EW45,FB45,FG45,FL45,FQ45,FV45,GA45,GF45,GK45,GP45,GU45) -> 10136577 | I45: =SUM(O45,S45,X45,AC45,AH45,AM45,AR45,AW45,BB45,BG45,BL45,BQ45,BV45,CA45,CF45,CK45,CP45,CU45,CZ45,DE45,DJ45,DO45,DT45,DY45,ED45,EI45,EN45,ES45,EX45,FC45,FH45,FM45,FR45,FW45,GB45,GG45,GL45,GQ45,GV45) -> 1013657.7 | J45: =I45/F45 -> 10136577 | M45: 10136577 | N45: 10136577 | O45: 1013657.7 | T45: 0 | U45: =T45-Q45 -> 0 | Y45: =X45/F45 -> 0 | Z45: =Y45-V45 -> 0 | AD45: =AC45/F45 -> 0 | AE45: =AD45-AA45 -> 0 | AI45: =AH45/F45 -> 0 | AJ45: =AI45-AF45 -> 0 | AN45: =AM45/F45 -> 0 | AO45: =AN45-AK45 -> 0 | AS45: =AR45/F45 -> 0 | AT45: =AS45-AP45 -> 0 | AX45: =AW45/F45 -> 0 | AY45: =AX45-AU45 -> 0 | BC45: =BB45/F45 -> 0 | BD45: =BC45-AZ45 -> 0 | BH45: =BG45/F45 -> 0 | BI45: =BH45-BE45 -> 0 | BM45: =BL45/F45 -> 0 | BN45: =BM45-BJ45 -> 0 | BR45: =BQ45/F45 -> 0 | BS45: =BR45-BO45 -> 0 | BX45: =BW45-BT45 -> 0 | CB45: =CA45/F45 -> 0 | CC45: =CB45-BY45 -> 0 | CG45: =CF45/F45 -> 0 | CH45: =CG45-CD45 -> 0 | CL45: =CK45/F45 -> 0 | CM45: =CL45-CI45 -> 0 | CR45: =ROUND(CQ45-CN45,2) -> 0 | CW45: =CV45-CS45 -> 0 | DA45: =ROUND(CZ45/F45,2) -> 0 | DB45: =ROUND(DA45-CX45,2) -> 0 | DF45: =DE45/F45 -> 0 | DG45: =DC45-DF45 -> 0 | DK45: =DJ45/F45 -> 0 | DL45: =DK45-DH45 -> 0 | DP45: =DO45/F45 -> 0 | DQ45: =DP45-DM45 -> 0 | DU45: =DT45/F45 -> 0 | DV45: =DU45-DR45 -> 0 | DZ45: =ROUND(DY45/F45,2) -> 0 | EA45: =ROUND(DZ45-DW45,2) -> 0 | EF45: =EE45-EB45 -> 0 | EJ45: =ROUND(EI45/F45,2) -> 0 | EK45: =ROUND(EJ45-EG45,2) -> 0 | EO45: =ROUND(EN45/F45,2) -> 0 | EP45: =ROUND(EO45-EL45,2) -> 0 | ET45: =ROUND(ES45/F45,2) -> 0 | EU45: =ROUND(ET45-EQ45,2) -> 0 | EY45: =ROUND(EX45/F45,2) -> 0 | EZ45: =ROUND(EY45-EV45,2) -> 0 | FD45: =ROUND(FC45/F45,2) -> 0 | FE45: =ROUND(FD45-FA45,2) -> 0 | FI45: =FH45/F45 -> 0 | FJ45: =ROUND(FI45-FF45,2) -> 0 | FN45: =ROUND(FM45/F45,2) -> 0 | FO45: =ROUND(FN45-FK45,2) -> 0 | FS45: =ROUND(FR45/F45,2) -> 0 | FT45: =FS45-FP45 -> 0 | FX45: =ROUND(FW45/F45,2) -> 0 | FY45: =FX45-FU45 -> 0 | GC45: =ROUND(GB45/F45,2) -> 0 | GD45: =GC45-FZ45 -> 0 | GH45: =GG45/F45 -> 0 | GI45: =GH45-GE45 -> 0 | GM45: =GL45/F45 -> 0 | GN45: =GM45-GJ45 -> 0 | GR45: =GQ45/F45 -> 0 | GS45: =GR45-GO45 -> 0 | GW45: =ROUND(GV45/F45,2) -> 0 | GX45: =GW45-GT45 -> 0
B46: 2440 | F46: 0.09 | G46: =SUM(M46,P46:Q46,V46,AA46,AF46,AK46,AP46,AU46,AZ46,BE46,BJ46,BO46,BT46,BY46,CD46,CI46,CN46,CS46,CX46,DC46,DH46,DM46,DR46,DW46,EB46,EG46,EL46,EQ46,EV46,FA46,FF46,FK46,FP46,FU46,FZ46,GE46,GJ46,GO46,GT46) -> 1752149.1 | H46: =SUM(N46,R46,W46,AB46,AG46,AL46,AQ46,AV46,BA46,BF46,BK46,BP46,BU46,BZ46,CE46,CJ46,CO46,CT46,CY46,DD46,DI46,DN46,DS46,DX46,EC46,EH46,EM46,ER46,EW46,FB46,FG46,FL46,FQ46,FV46,GA46,GF46,GK46,GP46,GU46) -> 0 | I46: =SUM(O46,S46,X46,AC46,AH46,AM46,AR46,AW46,BB46,BG46,BL46,BQ46,BV46,CA46,CF46,CK46,CP46,CU46,CZ46,DE46,DJ46,DO46,DT46,DY46,ED46,EI46,EN46,ES46,EX46,FC46,FH46,FM46,FR46,FW46,GB46,GG46,GL46,GQ46,GV46) -> -82525.119 | J46: =I46/F46 -> -916945.77 | M46: 1667899.7 | N46: 0 | O46: -90107.56 | Q46: 84249.34 | S46: 7582.4406 | T46: 84249.34 | U46: =T46-Q46 -> 0 | Y46: =X46/F46 -> 0 | Z46: =Y46-V46 -> 0 | AD46: =AC46/F46 -> 0 | AE46: =AD46-AA46 -> 0 | AI46: =AH46/F46 -> 0 | AJ46: =AI46-AF46 -> 0 | AN46: =AM46/F46 -> 0 | AO46: =AN46-AK46 -> 0 | AS46: =AR46/F46 -> 0 | AT46: =AS46-AP46 -> 0 | AX46: =AW46/F46 -> 0 | AY46: =AX46-AU46 -> 0 | BC46: =BB46/F46 -> 0 | BD46: =BC46-AZ46 -> 0 | BH46: =BG46/F46 -> 0 | BI46: =BH46-BE46 -> 0 | BM46: =BL46/F46 -> 0 | BN46: =BM46-BJ46 -> 0 | BR46: =BQ46/F46 -> 0 | BS46: =BR46-BO46 -> 0 | BX46: =BW46-BT46 -> 0 | CB46: =CA46/F46 -> 0 | CC46: =CB46-BY46 -> 0 | CG46: =CF46/F46 -> 0 | CH46: =CG46-CD46 -> 0 | CL46: =CK46/F46 -> 0 | CM46: =CL46-CI46 -> 0 | CR46: =ROUND(CQ46-CN46,2) -> 0 | CW46: =CV46-CS46 -> 0 | DA46: =ROUND(CZ46/F46,2) -> 0 | DB46: =ROUND(DA46-CX46,2) -> 0 | DF46: =DE46/F46 -> 0 | DG46: =DC46-DF46 -> 0 | DK46: =DJ46/F46 -> 0 | DL46: =DK46-DH46 -> 0 | DP46: =DO46/F46 -> 0 | DQ46: =DP46-DM46 -> 0 | DU46: =DT46/F46 -> 0 | DV46: =DU46-DR46 -> 0 | DZ46: =ROUND(DY46/F46,2) -> 0 | EA46: =ROUND(DZ46-DW46,2) -> 0 | EF46: =EE46-EB46 -> 0 | EJ46: =ROUND(EI46/F46,2) -> 0 | EK46: =ROUND(EJ46-EG46,2) -> 0 | EO46: =ROUND(EN46/F46,2) -> 0 | EP46: =ROUND(EO46-EL46,2) -> 0 | ET46: =ROUND(ES46/F46,2) -> 0 | EU46: =ROUND(ET46-EQ46,2) -> 0 | EY46: =ROUND(EX46/F46,2) -> 0 | EZ46: =ROUND(EY46-EV46,2) -> 0 | FD46: =ROUND(FC46/F46,2) -> 0 | FE46: =ROUND(FD46-FA46,2) -> 0 | FI46: =FH46/F46 -> 0 | FJ46: =ROUND(FI46-FF46,2) -> 0 | FN46: =ROUND(FM46/F46,2) -> 0 | FO46: =ROUND(FN46-FK46,2) -> 0 | FS46: =ROUND(FR46/F46,2) -> 0 | FT46: =FS46-FP46 -> 0 | FX46: =ROUND(FW46/F46,2) -> 0 | FY46: =FX46-FU46 -> 0 | GC46: =ROUND(GB46/F46,2) -> 0 | GD46: =GC46-FZ46 -> 0 | GH46: =GG46/F46 -> 0 | GI46: =GH46-GE46 -> 0 | GM46: =GL46/F46 -> 0 | GN46: =GM46-GJ46 -> 0 | GR46: =GQ46/F46 -> 0 | GS46: =GR46-GO46 -> 0 | GW46: =ROUND(GV46/F46,2) -> 0 | GX46: =GW46-GT46 -> 0
B47: 2440 | E47: 设计咨询 | F47: 0.06 | G47: =SUM(M47,P47:Q47,V47,AA47,AF47,AK47,AP47,AU47,AZ47,BE47,BJ47,BO47,BT47,BY47,CD47,CI47,CN47,CS47,CX47,DC47,DH47,DM47,DR47,DW47,EB47,EG47,EL47,EQ47,EV47,FA47,FF47,FK47,FP47,FU47,FZ47,GE47,GJ47,GO47,GT47) -> 1676556 | H47: =SUM(N47,R47,W47,AB47,AG47,AL47,AQ47,AV47,BA47,BF47,BK47,BP47,BU47,BZ47,CE47,CJ47,CO47,CT47,CY47,DD47,DI47,DN47,DS47,DX47,EC47,EH47,EM47,ER47,EW47,FB47,FG47,FL47,FQ47,FV47,GA47,GF47,GK47,GP47,GU47) -> 0 | I47: =SUM(O47,S47,X47,AC47,AH47,AM47,AR47,AW47,BB47,BG47,BL47,BQ47,BV47,CA47,CF47,CK47,CP47,CU47,CZ47,DE47,DJ47,DO47,DT47,DY47,ED47,EI47,EN47,ES47,EX47,FC47,FH47,FM47,FR47,FW47,GB47,GG47,GL47,GQ47,GV47) -> 100593.34 | J47: =I47/F47 -> 1676555.6 | M47: 1641347.7 | N47: 0 | O47: 98480.863 | T47: 0 | U47: =T47-Q47 -> 0 | Y47: =X47/F47 -> 0 | Z47: =Y47-V47 -> 0 | AD47: =AC47/F47 -> 0 | AE47: =AD47-AA47 -> 0 | AI47: =AH47/F47 -> 0 | AJ47: =AI47-AF47 -> 0 | AN47: =AM47/F47 -> 0 | AO47: =AN47-AK47 -> 0 | AS47: =AR47/F47 -> 0 | AT47: =AS47-AP47 -> 0 | AU47: 2030.98 | AW47: 121.85838 | AX47: =AW47/F47 -> 2030.973 | AY47: =AX47-AU47 -> -0.007 | AZ47: 2196.77 | BB47: 131.81 | BC47: =BB47/F47 -> 2196.8333 | BD47: =BC47-AZ47 -> 0.063333333 | BE47: 2241.38 | BG47: 134.48 | BH47: =BG47/F47 -> 2241.3333 | BI47: =BH47-BE47 -> -0.046666667 | BJ47: 2907.23 | BL47: 174.43 | BM47: =BL47/F47 -> 2907.1667 | BN47: =BM47-BJ47 -> -0.063333333 | BO47: 3617.97 | BQ47: 217.0782 | BR47: =BQ47/F47 -> 3617.97 | BS47: =BR47-BO47 -> 0 | BT47: 2248.01 | BV47: 134.88 | BW47: 2248.01 | BX47: =BW47-BT47 -> 0 | BY47: 7239.18 | CA47: 434.35 | CB47: =CA47/F47 -> 7239.1667 | CC47: =CB47-BY47 -> -0.013333333 | CD47: 1315.41 | CF47: 78.92 | CG47: =CF47/F47 -> 1315.3333 | CH47: =CG47-CD47 -> -0.076666667 | CI47: 778.82 | CK47: 46.73 | CL47: =CK47/F47 -> 778.83333 | CM47: =CL47-CI47 -> 0.013333333 | CN47: 880.04 | CP47: 52.8 | CQ47: 880.04 | CR47: =ROUND(CQ47-CN47,2) -> 0 | CS47: 883.05 | CU47: 52.98 | CV47: 883.05 | CW47: =CV47-CS47 -> 0 | CX47: 263.73 | CZ47: 15.82 | DA47: =ROUND(CZ47/F47,2) -> 263.67 | DB47: =ROUND(DA47-CX47,2) -> -0.06 | DC47: 516.52 | DE47: 30.99 | DF47: =DE47/F47 -> 516.5 | DG47: =DC47-DF47 -> 0.02 | DH47: 516.52 | DJ47: 30.99 | DK47: =DJ47/F47 -> 516.5 | DL47: =DK47-DH47 -> -0.02 | DM47: 669.89 | DO47: 40.19 | DP47: =DO47/F47 -> 669.83333 | DQ47: =DP47-DM47 -> -0.056666667 | DR47: 611.16 | DT47: 36.67 | DU47: =DT47/F47 -> 611.16667 | DV47: =DU47-DR47 -> 0.0066666667 | DW47: 616.86 | DY47: 37.01 | DZ47: =ROUND(DY47/F47,2) -> 616.83 | EA47: =ROUND(DZ47-DW47,2) -> -0.03 | EB47: 1297.14 | ED47: 77.8284 | EE47: 1297.14 | EF47: =EE47-EB47 -> 0 | EG47: 3316.95 | EI47: 199.02 | EJ47: =ROUND(EI47/F47,2) -> 3317 | EK47: =ROUND(EJ47-EG47,2) -> 0.05 | EL47: 301.41 | EN47: 18.08 | EO47: =ROUND(EN47/F47,2) -> 301.33 | EP47: =ROUND(EO47-EL47,2) -> -0.08 | EQ47: 374.28 | ES47: 22.46 | ET47: =ROUND(ES47/F47,2) -> 374.33 | EU47: =ROUND(ET47-EQ47,2) -> 0.05 | EV47: 384.99 | EX47: 23.1 | EY47: =ROUND(EX47/F47,2) -> 385 | EZ47: =ROUND(EY47-EV47,2) -> 0.01 | FD47: =ROUND(FC47/F47,2) -> 0 | FE47: =ROUND(FD47-FA47,2) -> 0 | FI47: =FH47/F47 -> 0 | FJ47: =ROUND(FI47-FF47,2) -> 0 | FN47: =ROUND(FM47/F47,2) -> 0 | FO47: =ROUND(FN47-FK47,2) -> 0 | FS47: =ROUND(FR47/F47,2) -> 0 | FT47: =FS47-FP47 -> 0 | FX47: =ROUND(FW47/F47,2) -> 0 | FY47: =FX47-FU47 -> 0 | GC47: =ROUND(GB47/F47,2) -> 0 | GD47: =GC47-FZ47 -> 0 | GH47: =GG47/F47 -> 0 | GI47: =GH47-GE47 -> 0 | GM47: =GL47/F47 -> 0 | GN47: =GM47-GJ47 -> 0 | GR47: =GQ47/F47 -> 0 | GS47: =GR47-GO47 -> 0 | GW47: =ROUND(GV47/F47,2) -> 0 | GX47: =GW47-GT47 -> 0
B48: 2440 | D48: 2440（绿港二期) | E48: 商品销售 | F48: 0.16 | G48: =SUM(M48,P48:Q48,V48,AA48,AF48,AK48,AP48,AU48,AZ48,BE48,BJ48,BO48,BT48,BY48,CD48,CI48,CN48,CS48,CX48,DC48,DH48,DM48,DR48,DW48,EB48,EG48,EL48,EQ48,EV48,FA48,FF48,FK48,FP48,FU48,FZ48,GE48,GJ48,GO48,GT48) -> 181705.01 | H48: =SUM(N48,R48,W48,AB48,AG48,AL48,AQ48,AV48,BA48,BF48,BK48,BP48,BU48,BZ48,CE48,CJ48,CO48,CT48,CY48,DD48,DI48,DN48,DS48,DX48,EC48,EH48,EM48,ER48,EW48,FB48,FG48,FL48,FQ48,FV48,GA48,GF48,GK48,GP48,GU48) -> 7683271.5 | I48: =SUM(O48,S48,X48,AC48,AH48,AM48,AR48,AW48,BB48,BG48,BL48,BQ48,BV48,CA48,CF48,CK48,CP48,CU48,CZ48,DE48,DJ48,DO48,DT48,DY48,ED48,EI48,EN48,ES48,EX48,FC48,FH48,FM48,FR48,FW48,GB48,GG48,GL48,GQ48,GV48) -> 1229323.4 | J48: =I48/F48 -> 7683271.5 | N48: 7683271.5 | O48: 1229323.4 | P48: 181705.01 | T48: 0 | U48: =T48-Q48 -> 0 | Y48: =X48/F48 -> 0 | Z48: =Y48-V48 -> 0 | AD48: =AC48/F48 -> 0 | AE48: =AD48-AA48 -> 0 | AI48: =AH48/F48 -> 0 | AJ48: =AI48-AF48 -> 0 | AN48: =AM48/F48 -> 0 | AO48: =AN48-AK48 -> 0 | AS48: =AR48/F48 -> 0 | AT48: =AS48-AP48 -> 0 | AX48: =AW48/F48 -> 0 | AY48: =AX48-AU48 -> 0 | BC48: =BB48/F48 -> 0 | BD48: =BC48-AZ48 -> 0 | BH48: =BG48/F48 -> 0 | BI48: =BH48-BE48 -> 0 | BM48: =BL48/F48 -> 0 | BN48: =BM48-BJ48 -> 0 | BR48: =BQ48/F48 -> 0 | BS48: =BR48-BO48 -> 0 | BX48: =BW48-BT48 -> 0 | CB48: =CA48/F48 -> 0 | CC48: =CB48-BY48 -> 0 | CG48: =CF48/F48 -> 0 | CH48: =CG48-CD48 -> 0 | CL48: =CK48/F48 -> 0 | CM48: =CL48-CI48 -> 0 | CR48: =ROUND(CQ48-CN48,2) -> 0 | CW48: =CV48-CS48 -> 0 | DA48: =ROUND(CZ48/F48,2) -> 0 | DB48: =ROUND(DA48-CX48,2) -> 0 | DF48: =DE48/F48 -> 0 | DG48: =DC48-DF48 -> 0 | DK48: =DJ48/F48 -> 0 | DL48: =DK48-DH48 -> 0 | DP48: =DO48/F48 -> 0 | DQ48: =DP48-DM48 -> 0 | DU48: =DT48/F48 -> 0 | DV48: =DU48-DR48 -> 0 | DZ48: =ROUND(DY48/F48,2) -> 0 | EA48: =ROUND(DZ48-DW48,2) -> 0 | EF48: =EE48-EB48 -> 0 | EJ48: =ROUND(EI48/F48,2) -> 0 | EK48: =ROUND(EJ48-EG48,2) -> 0 | EO48: =ROUND(EN48/F48,2) -> 0 | EP48: =ROUND(EO48-EL48,2) -> 0 | ET48: =ROUND(ES48/F48,2) -> 0 | EU48: =ROUND(ET48-EQ48,2) -> 0 | EY48: =ROUND(EX48/F48,2) -> 0 | EZ48: =ROUND(EY48-EV48,2) -> 0 | FD48: =ROUND(FC48/F48,2) -> 0 | FE48: =ROUND(FD48-FA48,2) -> 0 | FI48: =FH48/F48 -> 0 | FJ48: =ROUND(FI48-FF48,2) -> 0 | FN48: =ROUND(FM48/F48,2) -> 0 | FO48: =ROUND(FN48-FK48,2) -> 0 | FS48: =ROUND(FR48/F48,2) -> 0 | FT48: =FS48-FP48 -> 0 | FX48: =ROUND(FW48/F48,2) -> 0 | FY48: =FX48-FU48 -> 0 | GC48: =ROUND(GB48/F48,2) -> 0 | GD48: =GC48-FZ48 -> 0 | GH48: =GG48/F48 -> 0 | GI48: =GH48-GE48 -> 0 | GM48: =GL48/F48 -> 0 | GN48: =GM48-GJ48 -> 0 | GR48: =GQ48/F48 -> 0 | GS48: =GR48-GO48 -> 0 | GW48: =ROUND(GV48/F48,2) -> 0 | GX48: =GW48-GT48 -> 0
B49: 2440 | F49: 0.13 | G49: =SUM(M49,P49:Q49,V49,AA49,AF49,AK49,AP49,AU49,AZ49,BE49,BJ49,BO49,BT49,BY49,CD49,CI49,CN49,CS49,CX49,DC49,DH49,DM49,DR49,DW49,EB49,EG49,EL49,EQ49,EV49,FA49,FF49,FK49,FP49,FU49,FZ49,GE49,GJ49,GO49,GT49) -> 13723366 | H49: =SUM(N49,R49,W49,AB49,AG49,AL49,AQ49,AV49,BA49,BF49,BK49,BP49,BU49,BZ49,CE49,CJ49,CO49,CT49,CY49,DD49,DI49,DN49,DS49,DX49,EC49,EH49,EM49,ER49,EW49,FB49,FG49,FL49,FQ49,FV49,GA49,GF49,GK49,GP49,GU49) -> 0 | I49: =SUM(O49,S49,X49,AC49,AH49,AM49,AR49,AW49,BB49,BG49,BL49,BQ49,BV49,CA49,CF49,CK49,CP49,CU49,CZ49,DE49,DJ49,DO49,DT49,DY49,ED49,EI49,EN49,ES49,EX49,FC49,FH49,FM49,FR49,FW49,GB49,GG49,GL49,GQ49,GV49) -> 65276.41 | J49: =I49/F49 -> 502126.23 | M49: 13723366 | N49: 0 | O49: 65276.41 | Q49: 181705.01 | S49: 0 | T49: 0 | U49: =T49-Q49 -> -181705.01 | V49: -181705.01 | Y49: =X49/F49 -> 0 | Z49: =Y49-V49 -> 181705.01 | AD49: =AC49/F49 -> 0 | AE49: =AD49-AA49 -> 0 | AI49: =AH49/F49 -> 0 | AJ49: =AI49-AF49 -> 0 | AN49: =AM49/F49 -> 0 | AO49: =AN49-AK49 -> 0 | AS49: =AR49/F49 -> 0 | AT49: =AS49-AP49 -> 0 | AX49: =AW49/F49 -> 0 | AY49: =AX49-AU49 -> 0 | BC49: =BB49/F49 -> 0 | BD49: =BC49-AZ49 -> 0 | BH49: =BG49/F49 -> 0 | BI49: =BH49-BE49 -> 0 | BM49: =BL49/F49 -> 0 | BN49: =BM49-BJ49 -> 0 | BR49: =BQ49/F49 -> 0 | BS49: =BR49-BO49 -> 0 | BX49: =BW49-BT49 -> 0 | CB49: =CA49/F49 -> 0 | CC49: =CB49-BY49 -> 0 | CG49: =CF49/F49 -> 0 | CH49: =CG49-CD49 -> 0 | CL49: =CK49/F49 -> 0 | CM49: =CL49-CI49 -> 0 | CR49: =ROUND(CQ49-CN49,2) -> 0 | CW49: =CV49-CS49 -> 0 | DA49: =ROUND(CZ49/F49,2) -> 0 | DB49: =ROUND(DA49-CX49,2) -> 0 | DF49: =DE49/F49 -> 0 | DG49: =DC49-DF49 -> 0 | DK49: =DJ49/F49 -> 0 | DL49: =DK49-DH49 -> 0 | DP49: =DO49/F49 -> 0 | DQ49: =DP49-DM49 -> 0 | DU49: =DT49/F49 -> 0 | DV49: =DU49-DR49 -> 0 | DZ49: =ROUND(DY49/F49,2) -> 0 | EA49: =ROUND(DZ49-DW49,2) -> 0 | EF49: =EE49-EB49 -> 0 | EJ49: =ROUND(EI49/F49,2) -> 0 | EK49: =ROUND(EJ49-EG49,2) -> 0 | EO49: =ROUND(EN49/F49,2) -> 0 | EP49: =ROUND(EO49-EL49,2) -> 0 | ET49: =ROUND(ES49/F49,2) -> 0 | EU49: =ROUND(ET49-EQ49,2) -> 0 | EY49: =ROUND(EX49/F49,2) -> 0 | EZ49: =ROUND(EY49-EV49,2) -> 0 | FD49: =ROUND(FC49/F49,2) -> 0 | FE49: =ROUND(FD49-FA49,2) -> 0 | FI49: =FH49/F49 -> 0 | FJ49: =ROUND(FI49-FF49,2) -> 0 | FN49: =ROUND(FM49/F49,2) -> 0 | FO49: =ROUND(FN49-FK49,2) -> 0 | FS49: =ROUND(FR49/F49,2) -> 0 | FT49: =FS49-FP49 -> 0 | FX49: =ROUND(FW49/F49,2) -> 0 | FY49: =FX49-FU49 -> 0 | GC49: =ROUND(GB49/F49,2) -> 0 | GD49: =GC49-FZ49 -> 0 | GH49: =GG49/F49 -> 0 | GI49: =GH49-GE49 -> 0 | GM49: =GL49/F49 -> 0 | GN49: =GM49-GJ49 -> 0 | GR49: =GQ49/F49 -> 0 | GS49: =GR49-GO49 -> 0 | GW49: =ROUND(GV49/F49,2) -> 0 | GX49: =GW49-GT49 -> 0
B50: 2440 | E50: 工程施工 | F50: 0.1 | G50: =SUM(M50,P50:Q50,V50,AA50,AF50,AK50,AP50,AU50,AZ50,BE50,BJ50,BO50,BT50,BY50,CD50,CI50,CN50,CS50,CX50,DC50,DH50,DM50,DR50,DW50,EB50,EG50,EL50,EQ50,EV50,FA50,FF50,FK50,FP50,FU50,FZ50,GE50,GJ50,GO50,GT50) -> 0 | H50: =SUM(N50,R50,W50,AB50,AG50,AL50,AQ50,AV50,BA50,BF50,BK50,BP50,BU50,BZ50,CE50,CJ50,CO50,CT50,CY50,DD50,DI50,DN50,DS50,DX50,EC50,EH50,EM50,ER50,EW50,FB50,FG50,FL50,FQ50,FV50,GA50,GF50,GK50,GP50,GU50) -> 8272727.3 | I50: =SUM(O50,S50,X50,AC50,AH50,AM50,AR50,AW50,BB50,BG50,BL50,BQ50,BV50,CA50,CF50,CK50,CP50,CU50,CZ50,DE50,DJ50,DO50,DT50,DY50,ED50,EI50,EN50,ES50,EX50,FC50,FH50,FM50,FR50,FW50,GB50,GG50,GL50,GQ50,GV50) -> 827272.74 | J50: =I50/F50 -> 8272727.4 | N50: 8272727.3 | O50: 827272.74 | T50: 0 | U50: =T50-Q50 -> 0 | Y50: =X50/F50 -> 0 | Z50: =Y50-V50 -> 0 | AD50: =AC50/F50 -> 0 | AE50: =AD50-AA50 -> 0 | AI50: =AH50/F50 -> 0 | AJ50: =AI50-AF50 -> 0 | AN50: =AM50/F50 -> 0 | AO50: =AN50-AK50 -> 0 | AS50: =AR50/F50 -> 0 | AT50: =AS50-AP50 -> 0 | AX50: =AW50/F50 -> 0 | AY50: =AX50-AU50 -> 0 | BC50: =BB50/F50 -> 0 | BD50: =BC50-AZ50 -> 0 | BH50: =BG50/F50 -> 0 | BI50: =BH50-BE50 -> 0 | BM50: =BL50/F50 -> 0 | BN50: =BM50-BJ50 -> 0 | BR50: =BQ50/F50 -> 0 | BS50: =BR50-BO50 -> 0 | BX50: =BW50-BT50 -> 0 | CB50: =CA50/F50 -> 0 | CC50: =CB50-BY50 -> 0 | CG50: =CF50/F50 -> 0 | CH50: =CG50-CD50 -> 0 | CL50: =CK50/F50 -> 0 | CM50: =CL50-CI50 -> 0 | CR50: =ROUND(CQ50-CN50,2) -> 0 | CW50: =CV50-CS50 -> 0 | DA50: =ROUND(CZ50/F50,2) -> 0 | DB50: =ROUND(DA50-CX50,2) -> 0 | DF50: =DE50/F50 -> 0 | DG50: =DC50-DF50 -> 0 | DK50: =DJ50/F50 -> 0 | DL50: =DK50-DH50 -> 0 | DP50: =DO50/F50 -> 0 | DQ50: =DP50-DM50 -> 0 | DU50: =DT50/F50 -> 0 | DV50: =DU50-DR50 -> 0 | DZ50: =ROUND(DY50/F50,2) -> 0 | EA50: =ROUND(DZ50-DW50,2) -> 0 | EF50: =EE50-EB50 -> 0 | EJ50: =ROUND(EI50/F50,2) -> 0 | EK50: =ROUND(EJ50-EG50,2) -> 0 | EO50: =ROUND(EN50/F50,2) -> 0 | EP50: =ROUND(EO50-EL50,2) -> 0 | ET50: =ROUND(ES50/F50,2) -> 0 | EU50: =ROUND(ET50-EQ50,2) -> 0 | EY50: =ROUND(EX50/F50,2) -> 0 | EZ50: =ROUND(EY50-EV50,2) -> 0 | FD50: =ROUND(FC50/F50,2) -> 0 | FE50: =ROUND(FD50-FA50,2) -> 0 | FI50: =FH50/F50 -> 0 | FJ50: =ROUND(FI50-FF50,2) -> 0 | FN50: =ROUND(FM50/F50,2) -> 0 | FO50: =ROUND(FN50-FK50,2) -> 0 | FS50: =ROUND(FR50/F50,2) -> 0 | FT50: =FS50-FP50 -> 0 | FX50: =ROUND(FW50/F50,2) -> 0 | FY50: =FX50-FU50 -> 0 | GC50: =ROUND(GB50/F50,2) -> 0 | GD50: =GC50-FZ50 -> 0 | GH50: =GG50/F50 -> 0 | GI50: =GH50-GE50 -> 0 | GM50: =GL50/F50 -> 0 | GN50: =GM50-GJ50 -> 0 | GR50: =GQ50/F50 -> 0 | GS50: =GR50-GO50 -> 0 | GW50: =ROUND(GV50/F50,2) -> 0 | GX50: =GW50-GT50 -> 0
