Workbook
Name \A: #REF!
Name \A: #REF!
Name \A: #REF!
Name \A: #REF!
Name \A: #REF!
Name \A: #REF!
Name \A: #REF!
Name \e: #REF!
Name \p: #REF!
Name \s: #N/A
Name _: #REF!
Name _.xls: #REF!
Name _?: #N/A
Name _??????: #N/A
Name __: #REF!
Name __?: #N/A
Name __??????: #N/A
Name __aaa5: [2]六纺!#REF!
Name __k3: #REF!
Name __sc13: #REF!
Name _00104gz: #REF!
Name _002报表: #REF!
Name _002科目余额表: #REF!
Name _003报表: #REF!
Name _003科目余额表: #REF!
Name _003年12月辅料库: #REF!
Name _01.xls: #REF!
Name _010104501: #REF!
Name _02.xls: #REF!
Name _03.xls: #REF!
Name _1_?: #N/A
Name _11.xls: #REF!
Name _12.xls: #REF!
Name _121.dbf: #REF!
Name _1212002.dbf: #REF!
Name _13: #REF!
Name _17103.dbf: #REF!
Name _171032002.dbf: #REF!
Name _2: #REF!
Name _2_??????: #N/A
Name _2009: #REF!
Name _3¸ß¼ÛÖÜ×ª¼þ_¨º½²Ä¹ý¶É: #REF!
Name _3年12月: #REF!
Name _3年12月后勤库: #REF!
Name _4_04标准价: #REF!
Name _5_20011225: #REF!
Name _55154: #REF!
Name _8未还DB_查询: #REF!
Name _9_12_mo_cost: #REF!
Name _999年12月31日股份应收帐款.dbf: #REF!
Name _aaa5: [2]六纺!#REF!
Name _act411: #REF!
Name _act412: #REF!
Name _act413: #REF!
Name _act414: #REF!
Name _DAT1: #REF!
Name _DAT10: #REF!
Name _DAT11: #REF!
Name _DAT12: #REF!
Name _DAT13: [12]Sheet1!#REF!

Sheet Ref 1_202502_Summary
A1: 伊金霍洛旗悦盛新能源有限公司2025年02月（税务所属期）税费申报明细
H2: 45689
A3: 序号 | B3: 申报税种 | C3: 税目 | D3: 计税依据（记账科目/计税表格） | E3: 计税金额 (A)-季度 | F3: 征收比例 (B) | G3: 税率 (C) | H3: 实际应纳税额 (D) | I3: 计税金额-2025年01月 | J3: 计税金额-2025年02月 | K3: 计税金额-2025年03月 | L3: 差异原因 | M3: 指引
B4: 印花税 | C4: 买卖合同 | D4: 主营业务收入&财务提供 | E4: 0 | F4: 1 | G4: 0.0003 | H4: =ROUND(E4*F4*G4,2) -> 0 | I4: ='[112]02月PL'!D6 -> 18613557 | J4: ='[112]02月PL'!D37 -> 15885357 | K4: ='[112]02月PL'!D69 -> 0 | M4: PL
C5: 融资租赁合同 | D5: 财务提供 | F5: 1 | G5: 5e-05 | H5: =ROUND(E5*F5*G5,2) -> 0 | M5: Ref 1
C6: 借款合同 | F6: 1 | G6: 5e-05 | H6: =ROUND(E6*F6*G6,2) -> 0 | M6: Ref 1
C7: 承揽合同 | E7: 0 | F7: 1 | G7: 0.0003 | H7: =ROUND(E7*F7*G7,2) -> 0 | M7: Ref 1
C8: 建设工程合同 | E8: 0 | F8: 1 | G8: 0.0003 | H8: =ROUND(E8*F8*G8,2) -> 0 | M8: Ref 1
C9: 运输合同 | F9: 1 | G9: 0.0003 | H9: =ROUND(E9*F9*G9,2) -> 0 | M9: Ref 1
C10: 技术合同 | E10: 0 | F10: 1 | G10: 0.0003 | H10: =ROUND(E10*F10*G10,2) -> 0 | M10: Ref 1
C11: 租赁合同 | E11: 0 | F11: 1 | G11: 0.001 | H11: =ROUND(E11*F11*G11,2) -> 0 | M11: Ref 1
C12: 保管合同 | F12: 1 | G12: 0.001 | H12: =ROUND(E12*F12*G12,2) -> 0 | M12: Ref 1
C13: 仓储合同 | F13: 1 | G13: 0.001 | H13: =ROUND(E13*F13*G13,2) -> 0 | M13: Ref 1
C14: 财产保险合同 | F14: 1 | G14: 0.001 | H14: =ROUND(E14*F14*G14,2) -> 0 | M14: Ref 1
C15: 营业账簿 | F15: 1 | G15: 0.00025 | H15: =ROUND(E15*F15*G15,2) -> 0 | M15: Ref 1
C16: 产权转移书据 | F16: 1 | G16: 0.0005 | H16: =ROUND(E16*F16*G16,2) -> 0
A17: 1 | B17: 印花税合计 | E17: =SUM(E4:E16) -> 0 | H17: =SUM(H4:H16) -> 0 | I17: 60000200000001 | K17: =H17-J17 -> 0 | N17: 自行判断：申报期上月末资产总额不超过5000万元
A18: 序号 | B18: 申报税种 | C18: 税目 | D18: 计税依据（记账科目/计税表格） | E18: 计税金额 | F18: 征收比例 (B) | G18: 税率 (C) | H18: 实际应纳税额 (D) | I18: 记账科目 | J18: 账面金额 | K18: 差异 | L18: 差异原因
B19: 增值税 | C19: 销项税额-主营业务收入 | D19: 主营业务收入 | E19: ='[112]02月PL'!D36 -> 15885357 | F19: 1 | G19: 0.13 | H19: =ROUND(E19*G19,2) -> 2065096.4 | I19: 2221010200 | J19: =-[112]销项明细!N10 -> 2065096.4 | K19: =H19-J19 -> 0 | L19: 尾差，以账面计提申报为准 | M19: PL
C20: 销项税额-固定资产处置收入 | D20: 固定资产销售收入 | E20: ='[112]Ref 4_202502 增值税变动表'!F4 -> 0 | F20: 1 | G20: 0.09 | H20: =E20*G20 -> 0
C21: 销项税额-财务费用-利息收入 | D21: 利息收入 | E21: ='[112]Ref 4_202502 增值税变动表'!F5 -> 0 | F21: 1 | G21: 0.06 | H21: =E21*G21 -> 0
C22: 销项税额-其他收益 | D22: 个税手续费返还 | E22: ='[112]Ref 4_202502 增值税变动表'!F6 -> 0 | F22: 1 | G22: 0.06 | H22: =E22*G22 -> 0
C23: 增值税进项税额 | D23: 见表-增值税进项认证清单 | E23: ='[112]Ref 3_202502 增值税进项认证清单'!K22 -> 1979092.2 | F23: 1 | G23: 不适用 | H23: ='[112]Ref 3_202502 增值税进项认证清单'!L22 -> 142670.14 | I23: 2221010100 | J23: =[112]进项明细!N28 -> 142670.14 | K23: =H23-J23 -> 0 | M23: Ref 3 | N23: 当期 | R23: 0.09
C24: 期初进项留抵金额 | D24: 见表-增值税变动表 | F24: 1 | H24: ='[112]Ref 4_202502 增值税变动表'!F15+'[112]Ref 4_202502 增值税变动表'!F16 -> 1.9248279e+08 | M24: Ref 4
C25: 期末进项留抵金额 | D25: 见表-增值税变动表 | F25: 1 | G25: 不适用 | H25: ='[112]Ref 4_202502 增值税变动表'!F17+'[112]Ref 4_202502 增值税变动表'!F18 -> 1.9056036e+08 | J25: =-'[112]02月BS'!I58 -> 1.9056036e+08 | K25: =H25-J25 -> 0 | M25: Ref 4
A26: 2 | B26: 增值税合计 | H26: 0 | I26: 61400200000001
B27: 企业所得税 | C27: 项目名称 | D27: 所处优惠期 | E27: 应纳税所得额 | F27: 征收税率 | G27: 当年应缴税额 | H27: Q1已缴税额 | I27: Q2应缴税额 | J27: Q3应缴税额 | K27: Q4应缴税额
C28: 鄂尔多斯（2023-2025三免期） | D28: 减免期 | E28: ='[112]02月PL'!E91 -> 0 | F28: =25% -> 0.25 | G28: =E28*F28*0 -> 0 | H28: 0 | I28: =G28-H28 -> 0
A29: 3 | B29: 企业所得税合计 | E29: =SUM(E28:E28) -> 0 | G29: =SUM(G28:G28) -> 0 | H29: =I28 -> 0 | I29: 2221050000
A30: 4 | B30: 城镇土地使用税 | C30: 县城、建制镇、工矿区 | D30: 建设用地面积 | F30: 5月、11月缴纳 | G30: 2.4 | H30: =(E30*G30/12*6) -> 0 | I30: 61408220000001 | K30: =H30-J30 -> 0
A31: 5 | B31: 房产税 | C31: 从价计征 | D31: 房产原值 | I31: 61409210000000
B32: 个人所得税 | D32: 实发工资
C33: 劳务报酬所得 | F33: 0.8 | G33: 0.2 | H33: =ROUND(IF(D33<=800,0,IF(D33<=3360,(D33-800)/4,IF(D33<=21000,0.16*D33/0.84,IF(D33<=49500,(0.24*D33-2000)/0.76,(0.32*D33-7000)/0.68)))),2) -> 0 | I33: 6600020002 | J33: 0 | K33: =H33-J33 -> 0
C34: 劳务报酬所得（倒算） | E34: =ROUND(IF(D34<=800,0,IF(D34<=3360,(D34-800)/4,IF(D34<=21000,0.16*D34/0.84,IF(D34<=49500,(0.24*D34-2000)/0.76,(0.32*D34-7000)/0.68)))),2)+D34 -> 0 | F34: 0.8 | G34: 0.4 | H34: =IF(AND(E34=0),0,IF(AND(E34<=4000),E34-800,IF(AND(E34>4000),E34*F34*G34-7000))) -> 0 | I34: 6600020002 | J34: 0
C35: 财产租赁所得 | F35: 0.8 | G35: 0.2
C36: 财产租赁所得（倒算） | F36: 0.8 | G36: 0.2
A37: 6 | B37: =B32 -> 个人所得税 | I37: 代扣代缴个税
A38: 7 | B38: 水利建设专项收入 | C38: 地方水利建设基金 | E38: =[112]伊金悦盛项目累计缴纳!D5 -> 0 | G38: 0.01 | H38: =E38*G38 -> 0
A39: 8 | B39: 耕地占用税 | C39: 林地、草地 | F39: 1 | G39: 27
A40: 9 | B40: 契税 | C40: 国有土地使用权出让（非居住用地） | F40: 1 | G40: 0.03
A41: 2月应申报合计 | H41: =H17+H26+H29+H30+H31+H37+H38+H39+H40 -> 0 | J41: =J17+J26+J29+J30+J31+J37+J38 -> 0

Sheet 说明
A1: 排序 | B1: 表名 | C1: 表名逻辑 | D1: 取值逻辑 | E1: 公司代码 | F1: 备注 | L1: 标黄 | M1: 需要计算的页签
A2: 1 | B2: 累计税金汇总表 | D2: 在上期台账数据基础上计算生成本期数据 | E2: 2320、2355 | L2: 标绿 | M2: 数据集捞取数据
A3: 2 | B3: 累计项目税收明细表 | D3: 手工上传 | E3: 2320、2355 | L3: 标蓝 | M3: 用户手工上传
A4: 3 | B4: 增值税表一 累计销项 | D4: 在上期台账数据基础上计算生成本期数据 | E4: 2320、2355 | L4: 标紫 | M4: 取上月台账导出
A5: 4 | B5: 账税差异监控 | D5: 在上期台账数据基础上计算生成本期数据 | E5: 2320、2355 | L5: 标橙色 | M5: 配置表
A6: 5 | B6: BS表 | C6: 台账月份&“BS表”，例如：12月BS表 | D6: 拼接上传的本年资产负债表&BS表附表 | E6: all
A7: 6 | B7: PL表 | D7: 拼接上传的本年利润表&PL表附表，如果公司代码=2320、2355那么PL表附表是计算的，如果公司代码≠2320、2355那么PL表附表不是必须上传 | E7: all
A8: 7 | B8: 收入明细 | E8: all
A9: 8 | B9: 销项明细 | E9: all
A10: 9 | B10: 进项明细 | E10: all
A11: 10 | B11: 所得税明细 | E11: all
A12: 11 | B12: summary表 | C12: “Ref 1”&_&台账年度台账月份&_&“summary表”，例如：Ref 1_202602_summary表 | E12: all
A13: 12 | B13: 增值税销项表 | C13: “Ref 2”&_&台账年度台账月份&_&“增值税销项（样式）”，例如：Ref 2_202602_增值税销项（样式） | E13: all
A14: 13 | B14: 增值税进项认证清单 | C14: “Ref 3”&_&台账年度台账月份&_&“增值税进项认证清单”，例如：Ref 3_202602_增值税进项认证清单 | E14: all
A15: 14 | B15: 增值税变动表 | C15: “Ref 4”&_&台账年度台账月份&_&“增值税变动表”，例如：Ref 4_202602_增值税变动表 | D15: 拼接增值税变动表&增值税变动表附表 | E15: all
A16: 15 | B16: 预开票收入计提及冲回统计 | E16: 2320、2355
A17: 16 | B17: 未开票数监控 | D17: 在上期台账数据基础上计算生成本期数据 | E17: all
A18: 17 | B18: 项目累计申报 | D18: 在上期台账数据基础上计算生成本期数据 | E18: all
A19: 18 | B19: 项目累计缴纳 | D19: 在上期台账数据基础上计算生成本期数据 | E19: all
A20: 19 | B20: 睿景景程月结数据表-报税 | F20: 只用于PL表附表取数，不实际在台账中显示
A21: 20 | B21: 其他科目明细 | F21: 只用于取数，不实际在台账中显示
A22: 21 | B22: 合同印花税明细台账 | F22: 只用于取数，不实际在台账中显示

Sheet 增值税变动表
B1: 基础条目 | C1: 拆分依据 | D1: 条目 | E1: 未开票金额 | F1: 当月开票金额 | G1: 以前月度开票金额 | H1: 合计
B2: 不显示此列 | C2: 不显示此列 | D2: 显示 | E2: 显示 | F2: 显示 | G2: 显示 | H2: 显示
B3: 取【增值税变动表基础条目配置表】中公司代码=台账公司或空，是否显示=Y，的基础条目字段，按照条目序号升序排列。 | C3: --若台账公司=2320/2450： 此字段默认为空 --若台账公司≠2320/2450： 1.在【增值税变动表基础条目配置表】表中取基础条目对应的是否拆分字段，若是否拆分=N，此字段默认为空，若是否拆分=Y，此字段取【PL附表】拆分依据列示。 | D3: ’--若台账公司=2320/2355： 取【睿景、景程增值税变动表特殊条目配置表】中公司代码=2320、2450或空，是否显示=Y的行，由取到行的条目序号=基础条目的条目序号，将【睿景、景程增值税变动表特殊条目配置表】中对应的特殊条目替换基础条目 --若台账公司≠2320/2450： 1.若拆分依据为空，此字段=基础条目 2.若拆分依据不为空，此条目=基础条目&“-”&拆分依据 | E3: ‘=合计-当月开票金额-以前月度开票金额 | F3: ’--若台账公司=2320/2355： 1.当条目=当月利润表主营业务收入（商品销售13%），此字段取【增值税销项表-按税率（征收率）统计表】中税率/征收率字段=0.13、发票类型=电子发票（增值税专用发票）对应数据行的实际开具发票金额 2.当条目=当月利润表主营业务收入（建安收入9%），此字段取【增值税销项表-按税率（征收率）统计表】中税率/征收率字段=0.09、发票类型=电子发票（增值税专用发票）对应数据行的实际开具发票金额 3.当条目=当月利润表主营业务收入（设计服务6%），此字段取【增值税销项表-按税率（征收率）统计表】中税率/征收率字段=0.06、发票类型=电子发票（增值税专用发票）对应数据行的实际开具发票金额 4.当条目=当月利润表主营业务收入（商品销售13%-普票），此字段取【增值税销项表-按税率（征收率）统计表】中税率/征收率字段=0.13、发票类型=电子发票（普通发票）对应数据行的实际开具发票金额 5.当条目=当月利润表主营业务收入（建安收入9%-普票），此字段取【增值税销项表-按税率（征收率）统计表】中税率/征收率字段=0.09、发票类型=电子发票（普通发票）对应数据行的实际开具发票金额 6.当条目=当月利润表主营业务收入（设计服务6%-普票），此字段取【增值税销项表-按税率（征收率）统计表】中税率/征收率字段=0.06、发票类型=电子发票（普通发票）对应数据行的实际开具发票金额 7.当条目=应交增值税-销项税（商品销售13%），此字段取【增值税销项表-按税率（征收率）统计表】中税率/征收率字段=0.13、发票类型=电子发票（增值税专用发票）对应数据行的实际开具发票税额 8.当条目=应交增值税-销项税（建安收入9%），此字段取【增值税销项表-按税率（征收率）统计表】中税率/征收率字段=0.09、发票类型=电子发票（增值税专用发票）对应数据行的实际开具发票税额 9.当条目=应交增值税-销项税（设计服务6%），此字段取【增值税销项表-按税率（征收率）统计表】中税率/征收率字段=0.06、发票类型=电子发票（增值税专用发票）对应数据行的实际开具发票税额 10.当条目=应交增值税-销项税（商品销售13%-普票），此字段取【增值税销项表-按税率（征收率）统计表】中税率/征收率字段=0.13、发票类型=电子发票（普通发票）对应数据行的实际开具发票税额 11.当条目=应交增值税-销项税（建安收入9%-普票），此字段取【增值税销项表-按税率（征收率）统计表】中税率/征收率字段=0.09、发票类型=电子发票（普通发票）对应数据行的实际开具发票税额 12.当条目=应交增值税-销项税（设计服务6%-普票），此字段取【增值税销项表-按税率（征收率）统计表】中税率/征收率字段=0.06、发票类型=电子发票（普通发票）对应数据行的实际开具发票税额 其他情况，此字段为空 --若台账公司≠2320/2450： 1.当基础条目=当月利润表主营业务收入，此字段取【增值税销项表-按税率（征收率）统计表】合计行实际开具发票金额 2.当基础条目=应交增值税-销项税，此字段取【增值税销项表-按税率（征收率）统计表】合计行实际开具发票税额 3.其他情况，此字段默认为空 | G3: 取基础条目=当月利润表主营业务收入 从上往下数第一行填入【收入明细表】中总账科目=6001000010的货币金额合计，其他数据行此字段默认为空 ---默认为空，由用户手工维护 | H3: ’--若台账公司=2320/2355： 1.当条目=当月利润表主营业务收入（商品销售13%），此字段取【PL表附表】中拆分依据=专票-13%对应数据行的申报金额 2.当条目=当月利润表主营业务收入（建安收入9%），此字段取【PL表附表】中拆分依据=专票-9%对应数据行的申报金额 3.当条目=当月利润表主营业务收入（设计服务6%），此字段取【PL表附表】中拆分依据=专票-6%对应数据行的申报金额 4.当条目=当月利润表主营业务收入（商品销售13%-普票），此字段取【PL表附表】中拆分依据=普票-13%对应数据行的申报金额 5.当条目=当月利润表主营业务收入（建安收入9%-普票），此字段取【PL表附表】中拆分依据=普票-9%对应数据行的申报金额 6.当条目=当月利润表主营业务收入（设计服务6%-普票），此字段取【PL表附表】中拆分依据=普票-6%对应数据行的申报金额 7.当条目=应交增值税-销项税（商品销售13%），此字段取【【PL表附表】中拆分依据=专票-13%对应数据行的申报税额 8.当条目=应交增值税-销项税（建安收入9%），此字段取【PL表附表】中拆分依据=专票-9%对应数据行的申报税额 9.当条目=应交增值税-销项税（设计服务6%），此字段取【PL表附表】中拆分依据=专票-6%对应数据行的申报税额 10.当条目=应交增值税-销项税（商品销售13%-普票），此字段取【PL表附表】中拆分依据=普票-13%对应数据行的申报税额 11.当条目=应交增值税-销项税（建安收入9%-普票），此字段取【PL表附表】中拆分依据=普票-9%对应数据行的申报税额 12.当条目=应交增值税-销项税（设计服务6%-普票），此字段取【【PL表附表】中拆分依据=普票-6%对应数据行的申报税额 13.当条目=增值税已认证进项税，此字段取【增值税进项认证清单】税额合计 14.当条目=期初留抵进项税，此字段取系统中台账公司、台账月份-1的【税务台账表-增值税变动表】页签期末留抵进项税行合计金额字段，如台账月份为1月，此字段取上年度12月期末留抵进项税 15.当条目=期末留抵进项税，此字段等于同一拆分依据下【应交增值税-销项税】-（【增值税已认证进项税】+【期初留抵进项税】-进项转出）小于0部分的绝对值，若【应交增值税-销项税】-（【增值税已认证进项税】+【期初留抵进项税】-进项转出）大于0.此字段默认为0 16.当条目=应交增值税，若【期末留抵进项税】合计>0，此字段为0，若【期末留抵进项税】合计<0，此字段=【销项税额*】合计+【应交增值税-销项税*】合计+【进项转出】合计-【增值税已认证进项税】合计-【期初留抵进项税】合计 17.当条目=本期应交增值税，此字段=【应交增值税】合计-【异地预缴抵减】合计 18.当条目=异地预缴递减，此字段=【增值税变动表附表】本期递减预缴 其他情况，此字段为空 --若台账公司≠2320/2450： 1.当基础条目=当月利润表主营业务收入，此字段取【PL表附表】拆分依据对应的主营业务收入字段。如无【PL附表】，取[PL表]主营业务收入本期发生数。 2.当基础条目=应交增值税-销项税，此字段取【PL表附表】拆分依据对应的销项字段，如无【PL附表】，取[BS表]应交税费（累计发生数-年初数）*-1。 3.当基础条目=增值税已认证进项税，此字段取【增值税进项认证清单】税额合计 4.当基础条目=期初留抵进项税，此字段取系统中台账公司、台账月份-1的【税务台账表-增值税变动表】页签期末留抵进项税行合计金额字段，如台账月份为1月，此字段取上年度12月期末留抵进项税 5.当基础条目=期末留抵进项税，此字段等于同一拆分依据下【应交增值税-销项税】-（【增值税已认证进项税】+【期初留抵进项税】-进项转出）小于0部分的绝对值，若【应交增值税-销项税】-（【增值税已认证进项税】+【期初留抵进项税】-进项转出）大于0.此字段默认为0 6.当条目=应交增值税，若【期末留抵进项税】合计>0，此字段为0，若【期末留抵进项税】合计<0，此字段=【销项税额*】合计+【应交增值税-销项税*】合计+【进项转出】合计-【增值税已认证进项税】合计-【期初留抵进项税】合计 7.其他情况，此字段默认为空
D4: 当月利润表主营业务收入-光伏收入
D5: 当月利润表主营业务收入-风电收入
D6: 销项税额-固定资产处置收入
D7: 销项税额-财务费用-利息收入
D8: 销项税额-其他收益
D10: 应交增值税-销项税-一般项目（光伏）
D11: 应交增值税-销项税-即征即退项目（风电）
D12: 预开票（未确认收入）-应交增值税
D13: 增值税已认证进项税-一般项目（光伏）
D14: 增值税已认证进项税-即征即退项目（风电）
D15: 进项转出-一般 | H15: ？
D16: 进项转出-即征即退
D17: 期初留抵进项税-一般项目（光伏）
D18: 期初留抵进项税-即征即退项目（风电）
D19: 期末留抵进项税-一般项目（光伏）
D20: 期末留抵进项税-即征即退项目（风电）
D21: 应交增值税-一般项目（光伏）
D22: 应交增值税-即征即退项目（风电）

Sheet Summary 
A1: 伊金霍洛旗悦盛新能源有限公司2025年02月（税务所属期）税费申报明细 | N1: 表头逻辑：由公司代码在【公司代码配置表】取到公司名称，按照示例拼接公司名称、台账年度、月份
B2: 申报税种取值逻辑：除印花税、增值税、企业所得税外，由【税目配置表】-公司代码=此表公司代码或空，取【税目配置表】-税种按照序号升序列示 | H2: 45689
A3: 序号 | B3: 申报税种 | C3: 税目 | D3: 计税依据（记账科目/计税表格） | E3: 计税金额 (A)-季度 | F3: 征收比例 (B) | G3: 税率 (C) | H3: 实际应纳税额 (D) | I3: 计税金额-2025年01月 | J3: 计税金额-2025年02月 | K3: 计税金额-2025年03月 | L3: 差异原因 | M3: 指引
B4: 印花税 | C4: 由【税目配置表】-税种=印花税，【税目配置表】-公司代码=此表公司代码或空，取【税目配置表】的税目列示。 | D4: 由【税目配置表】-税种="印花税"，【税目配置表】-公司代码=此表公司代码或空，【税目配置表】-税目=此表C列税目，取【税目配置表】-计税依据 | E4: 当税目=买卖合同，如台账月份为3、6、9、12，此字段取【印花税明细表】税目对应计税依据字段值+summary表计税金额当前季度计税金额 当税目≠买卖合同，如台账月份为3、6、9、12，此字段取【印花税明细表】税目对应计税依据字段值，反之此字段默认为0 | F4: 由【税目配置表】-税种="印花税"，【税目配置表】-公司代码=此表公司代码或空，【税目配置表】-税目=此表C列税目，取【税目配置表】-征收比例 | G4: 由【税目配置表】-税种="印花税"，【税目配置表】-公司代码=此表公司代码或空，【税目配置表】-税目=此表C列税目，取【税目配置表】-税率 | H4: 计税金额（A）-季度*征收比例（B）*税率（C） 保留两位小数 | I4: I3、J3、K3分别取台账月份对应季度的三个月，例如：台账月份为26年4月，则I3、J3、K3分别为计税金额-2026年04月、计税金额-2026年05月、计税金额-2026年06月 计税金额取值：当税目="买卖合同"，此字段取对应公司代码、I3、J3、K3单元格月份【PL表】-其中：营业收入的本期发生额，反之，此字段为空
C5: 融资租赁合同 | D5: 财务提供 | F5: 1 | G5: 5e-05 | H5: =ROUND(E5*F5*G5,2) -> 0
C6: 借款合同 | F6: 1 | G6: 5e-05 | H6: =ROUND(E6*F6*G6,2) -> 0 | I6: ='[112]02月PL'!D8 -> 0
C7: 承揽合同 | E7: 0 | F7: 1 | G7: 0.0003 | H7: =ROUND(E7*F7*G7,2) -> 0
C8: 建设工程合同 | E8: 0 | F8: 1 | G8: 0.0003 | H8: =ROUND(E8*F8*G8,2) -> 0
C9: 运输合同 | F9: 1 | G9: 0.0003 | H9: =ROUND(E9*F9*G9,2) -> 0
C10: 技术合同 | E10: 0 | F10: 1 | G10: 0.0003 | H10: =ROUND(E10*F10*G10,2) -> 0
C11: 租赁合同 | E11: 0 | F11: 1 | G11: 0.001 | H11: =ROUND(E11*F11*G11,2) -> 0
C12: 保管合同 | F12: 1 | G12: 0.001 | H12: =ROUND(E12*F12*G12,2) -> 0
C13: 仓储合同 | F13: 1 | G13: 0.001
C14: 财产保险合同 | F14: 1 | G14: 0.001 | H14: =ROUND(E14*F14*G14,2) -> 0
C15: 营业账簿 | F15: 1 | G15: 0.00025 | H15: =ROUND(E15*F15*G15,2) -> 0
C16: 产权转移书据 | F16: 1 | G16: 0.0005 | H16: =ROUND(E16*F16*G16,2) -> 0
A17: 1 | B17: 印花税合计 | H17: =SUM(H4:H16) 取印花税实际应纳税额（D）的合计
A18: 序号 | B18: 申报税种 | C18: 税目 | D18: 计税依据（记账科目/计税表格） | E18: 计税金额 | F18: 征收比例 (B) | G18: 税率 (C) | H18: 实际应纳税额 (D) | I18: 记账科目 | J18: 账面金额 | K18: 差异 | L18: 差异原因 | M18: 指引
B19: 增值税 | C19: 由【税目配置表】-税种=此表税种，【税目配置表】-公司代码=此表公司代码或空，取【税目配置表】的税目列示。 | D19: 由【税目配置表】-税种=此表税种，【税目配置表】-公司代码=此表公司代码或空，【税目配置表】-税目=此表C列税目，取【税目配置表】-计税依据 | E19: 当税种=增值税，税目="销项税额-主营业务收入*",取对应公司代码、台账月份【PL表附表】拆分依据对应申报金额 当税种=增值税，税目="销项税额-固定资产处置收入",取对应公司代码、台账月份【增值税变动表】-销项税额-固定资产处置收入的合计金额 当税种=增值税，税目="销项税额-财务费用-利息收入",取对应公司代码、台账月份【增值税变动表】-销项税额-财务费用-利息收入的合计金额 当税种=增值税，税目="销项税额-其他收益",取对应公司代码、台账月份【增值税变动表】-销项税额-其他收益的合计金额 当税种=增值税，税目="增值税进项税额",取对应公司代码、台账月份【增值税进项认证清单】-金额的合计 当税种=增值税，税目="期末进项留抵金额"、”期初进项留抵金额“,此字段默认为空 | F19: 由【税目配置表】-税种=此表税种，【税目配置表】-公司代码=此表公司代码或空，【税目配置表】-税目=此表C列税目，取【税目配置表】-征收比例 | G19: 由【税目配置表】-税种=此表税种，【税目配置表】-公司代码=此表公司代码或空，【税目配置表】-税目=此表C列税目，取【税目配置表】-税率 | H19: 若税种=增值税，税目=“销项税额*”，此字段=计税金额（A）*税率（C） 若税种=增值税，税目=“增值税进项税额”，此字段取【进项认证清单】税额合计 若税种=增值税，税目=“期初进项留抵金额”，此字段取【增值税变动表】期初留抵进项税*合计金额汇总 若税种=增值税，税目=“期末进项留抵金额”，此字段取【增值税变动表】期末留抵进项税*合计金额汇总 | I19: 由【税目配置表】-公司代码=此表公司代码/空，【税目配置表】-税目=此表税目取得对应会计科目 | J19: 当公司代码≠2320、2355 当税种=增值税，税目="销项税额-主营业务收入",取对应公司代码、台账月份【销项明细】-货币金额字段合计*-1； 当税种=增值税，税目="增值税进项税额",取对应公司代码、台账月份【进项明细】-货币金额字段合计； 当税种=增值税，税目="期末进项留抵金额",取对应公司代码、台账月份【BS表-附表】应交税费-增值税*科目累计余额合计。 反之，此字段为空 当公司代码=2330、2355 当税种=增值税，税目="销项税额-主营业务收入*",取对应公司代码、台账月份【PL表-附表】中拆分依据对应的申报税额； 当税种=增值税，税目="增值税进项税额",取对应公司代码、台账月份【进项明细】-货币金额字段合计； 当税种=增值税，税目="期末进项留抵金额",取对应公司代码、台账月份【BS表-附表】应交税费-增值税*科目累计余额合计。 反之，此字段为空 | K19: 实际应纳税额(D)-账面金额 | L19: 尾差，以账面计提申报为准
C20: 销项税额-固定资产处置收入 | D20: 固定资产销售收入 | E20: ='[112]Ref 4_202502 增值税变动表'!F4 -> 0 | F20: 1 | G20: 0.09 | H20: =E20*G20 -> 0
C21: 销项税额-财务费用-利息收入 | D21: 利息收入 | E21: ='[112]Ref 4_202502 增值税变动表'!F5 -> 0 | F21: 1 | G21: 0.06 | H21: =E21*G21 -> 0
C22: 销项税额-其他收益 | D22: 个税手续费返还 | E22: ='[112]Ref 4_202502 增值税变动表'!F6 -> 0 | F22: 1 | G22: 0.06 | H22: =E22*G22 -> 0
C23: 增值税进项税额 | D23: 见表-增值税进项认证清单 | E23: ='[112]Ref 3_202502 增值税进项认证清单'!K22 -> 1979092.2 | F23: 1 | G23: 不适用 | H23: ='[112]Ref 3_202502 增值税进项认证清单'!L22 -> 142670.14 | I23: 2221010100 | J23: =[112]进项明细!N28 -> 142670.14 | K23: =H23-J23 -> 0
C24: 期初进项留抵金额 | D24: 见表-增值税变动表 | F24: 1 | H24: ='[112]Ref 4_202502 增值税变动表'!F15+'[112]Ref 4_202502 增值税变动表'!F16 -> 1.9248279e+08
C25: 期末进项留抵金额 | D25: 见表-增值税变动表 | F25: 1 | G25: 不适用 | H25: ='[112]Ref 4_202502 增值税变动表'!F17+'[112]Ref 4_202502 增值税变动表'!F18 -> 1.9056036e+08 | J25: =-'[112]02月BS'!I58 -> 1.9056036e+08 | K25: =H25-J25 -> 0
A26: 2 | B26: 增值税合计 | H26: 取对应公司代码、台账月份【增值税变动表】应交增值税合计字段；
B27: 增值税附加 | C27: 城建税 | H27: ‘=G27*H26
C28: 教育费附加 | H28: ‘=G28*H26
C29: 地方教育费附加 | H29: ‘=G29*H26
B30: 增值税附加合计 | H30: =SUM(H27:H29)
B31: 企业所得税 | C31: 项目名称 | D31: 所处优惠期 | E31: 应纳税所得额 | F31: 征收税率 | G31: 当年应缴税额 | H31: Q1已缴税额 | I31: Q2应缴税额 | J31: Q3应缴税额 | K31: Q4应缴税额
C32: 由【项目配置表】-税种=企业所得税，【项目配置表】-公司代码=此表公司代码或空，取【项目配置表】的项目名称列示。 | D32: 由【项目配置表】-税种=企业所得税，【项目配置表】-公司代码=此表公司代码或空，取【项目配置表】项目名称对应的所属优惠期。 | E32: 第一行取对应公司代码、台账月份【PL表】利润总额累计发生额，其他行该字段为空 | F32: 由【税目配置表】-税种="企业所得税"，【税目配置表】-公司代码=此表公司代码或空，【税目配置表】-税目="企业所得税"，取【税目配置表】-税率 | G32: 如所处优惠期为“减免期”此字段默认为0；如所处优惠期为“减半期”此字段=应纳税所得额*征收税率*0.5；如所处优惠期为“非风场项目，无优惠期”此字段=应纳税所得额*征收税率 | H32: 取台账当前年度第一季度数据，如当前为26年2月，26年第一季度还未结束，表头为“应缴”，如当前为26年3月，26年第一季度已结束，表头为“已缴”，则此字段按如下逻辑从数据集中取值 由公司代码=company_code、fiscal_year_period=年度1月到3月、account=2221050000 ，从数据集finance_electronicarchives_accounting_document_print中取debit_amount_in_document_currency+credit_amount_in_document_currency*-1 | I32: 取第二季度数据，逻辑同Q1已缴税额 | J32: 取第三季度数据，逻辑同Q1已缴税额 | K32: 取第四季度数据，逻辑同Q1已缴税额
A33: 3 | B33: 企业所得税合计 | E33: 企业所得税应纳税所得额合计 | H33: 判断台账期为几季度，在对应季度列下显示当季度应交税额合计
A34: 4 | B34: 城镇土地使用税 | C34: 县城、建制镇、工矿区 | D34: 建设用地面积 | E34: 手工维护 | F34: 取配置表需缴税月份 | G34: 2.4 | H34: ‘=(E34*G34/12*6) | K34: =H34-J34 -> #VALUE!
A35: 5 | B35: 房产税 | C35: 从价计征 | D35: 房产原值 | E35: 手工维护 | H35: =E35*G35/12*6
B36: 个人所得税 | D36: 实发工资 | E36: 手工维护 | H36: 手工维护
C37: 劳务报酬所得 | E37: 手工维护 | F37: 0.8 | G37: 0.2 | H37: 手工维护 | I37: 6600020002 | J37: 0 | K37: =H37-J37 -> #VALUE!
C38: 劳务报酬所得（倒算） | E38: 手工维护 | F38: 0.8 | G38: 0.4 | H38: 手工维护 | I38: 6600020002 | J38: 0
C39: 财产租赁所得 | E39: 手工维护 | F39: 0.8 | G39: 0.2 | H39: 手工维护
C40: 财产租赁所得（倒算） | E40: 手工维护 | F40: 0.8 | G40: 0.2 | H40: 手工维护
A41: 6 | B41: =B36 -> 个人所得税 | E41: =sum(E36:E40) | H41: =sum(H36:H40) | I41: 代扣代缴个税
A42: 7 | B42: 水利建设专项收入 | C42: 地方水利建设基金 | E42: 待志颖确认 | G42: 0.01 | H42: ’=E42*G42
A43: 8 | B43: 耕地占用税 | C43: 林地、草地 | E43: 手工维护 | F43: 1 | G43: 27 | H43: ’=E43*G43
A44: 9 | B44: 契税 | C44: 国有土地使用权出让（非居住用地） | E44: 手工维护 | F44: 1 | G44: 0.03 | H44: ‘=E44*G44
A45: =台账月份&"应申报合计" | H45: 等于台账中所有税种实际应纳税额合计 | J45: 等于台账中所有税种账面金额合计

Sheet Summary 表样
A1: 伊金霍洛旗悦盛新能源有限公司2025年02月（税务所属期）税费申报明细
A2: 45689
A3: 序号 | B3: 申报税种 | C3: 税目 | D3: 计税依据（记账科目/计税表格） | E3: 计税金额 (A)-季度 | F3: 征收比例 (B) | G3: 税率 (C) | H3: 实际应纳税额 (D) | I3: 计税金额-2025年01月 | J3: 计税金额-2025年02月 | K3: 计税金额-2025年03月 | L3: 差异原因 | M3: 指引
B4: 印花税 | C4: 买卖合同 | D4: 主营业务收入&财务提供 | F4: 1 | G4: 0.0003
C5: 融资租赁合同 | D5: 财务提供 | F5: 1 | G5: 5e-05
C6: 借款合同 | F6: 1 | G6: 5e-05
C7: 承揽合同 | F7: 1 | G7: 0.0003
C8: 建设工程合同 | F8: 1 | G8: 0.0003
C9: 运输合同 | F9: 1 | G9: 0.0003
C10: 技术合同 | F10: 1 | G10: 0.0003
C11: 租赁合同 | F11: 1 | G11: 0.001
C12: 保管合同 | F12: 1 | G12: 0.001
C13: 仓储合同 | F13: 1 | G13: 0.001
C14: 财产保险合同 | F14: 1 | G14: 0.001
C15: 营业账簿 | F15: 1 | G15: 0.00025
C16: 产权转移书据 | F16: 1 | G16: 0.0005
A17: 1 | B17: 印花税合计
A18: 序号 | B18: 申报税种 | C18: 税目 | D18: 计税依据（记账科目/计税表格） | E18: 计税金额 | F18: 征收比例 (B) | G18: 税率 (C) | H18: 实际应纳税额 (D) | I18: 记账科目 | J18: 账面金额 | K18: 差异 | L18: 差异原因 | M18: 指引
B19: 增值税 | C19: 销项税额-主营业务收入 | D19: 主营业务收入 | F19: 1 | G19: 0.13 | I19: 2221010200
C20: 销项税额-固定资产处置收入 | D20: 固定资产销售收入 | F20: 1 | G20: 0.09
C21: 销项税额-财务费用-利息收入 | D21: 利息收入 | F21: 1 | G21: 0.06
C22: 销项税额-其他收益 | D22: 个税手续费返还 | F22: 1 | G22: 0.06
C23: 增值税进项税额 | D23: 见表-增值税进项认证清单 | F23: 1 | G23: 不适用 | I23: 2221010100
C24: 期初进项留抵金额 | D24: 见表-增值税变动表 | F24: 1
C25: 期末进项留抵金额 | D25: 见表-增值税变动表 | F25: 1 | G25: 不适用
A26: 2 | B26: 增值税合计
B27: 企业所得税 | C27: 项目名称 | D27: 所处优惠期 | E27: 应纳税所得额 | F27: 征收税率 | G27: 当年应缴税额 | H27: Q1已缴税额 | I27: Q2应缴税额 | J27: Q3应缴税额 | K27: Q4应缴税额
F28: =25% -> 0.25
A29: 3 | B29: 企业所得税合计 | I29: 2221050000
A30: 4 | B30: 城镇土地使用税 | C30: 县城、建制镇、工矿区 | D30: 建设用地面积 | F30: 5月、11月缴纳 | G30: 2.4
A31: 5 | B31: 房产税 | C31: 从价计征 | D31: 房产原值
B32: 个人所得税 | D32: 实发工资
C33: 劳务报酬所得 | F33: 0.8 | G33: 0.2
C34: 劳务报酬所得（倒算） | F34: 0.8 | G34: 0.4
C35: 财产租赁所得 | F35: 0.8 | G35: 0.2
C36: 财产租赁所得（倒算） | F36: 0.8 | G36: 0.2
A37: 6 | B37: =B32 -> 个人所得税 | I37: 代扣代缴个税
A38: 7 | B38: 水利建设专项收入 | C38: 地方水利建设基金 | G38: 0.01
A39: 8 | B39: 耕地占用税 | C39: 林地、草地 | F39: 1 | G39: 27
A40: 9 | B40: 契税 | C40: 国有土地使用权出让（非居住用地） | F40: 1 | G40: 0.03
A41: 2月应申报合计 | H41: =H17+H26+H29+H30+H31+H37+H38+H39+H40 -> 0 | J41: =J17+J26+J29+J30+J31+J37+J38+J39+J40 -> 0

Sheet 未开票数监控
A1: 所属期 | B1: 申报账面数 | F1: 开票数 | H1: 未开票数
B2: 营业收入 | C2: 利息收入 | D2: 其他收益 | E2: 销项税额 | F2: 销售收入 | G2: 销项税额 | H2: 销售收入 | I2: 销项税额 | K2: 在前序税务台账此页的基础上新增本次台账期数据
B3: 取本台账期【PL表】主营业收入 行的本期发生额 | C3: 取【其他科目明细表】科目=6603020011货币金额合计 | D3: 取【其他科目明细表】科目=6702000010货币金额合计 | E3: 取本台账期【销项明细】货币金额字段合计*-1 | F3: 取本台账期【增值税销项表-按税率（征收率）统计表】合计行实际开具发票金额 | G3: 取本台账期【增值税销项表-按税率（征收率）统计表】合计行实际开具发票税额 | H3: =B列+C列+D列-F列 | I3: =E列-F列
A4: 2025-1 | B4: 18613557 | E4: 2419762.4 | H4: =B4+C4+D4-F4 -> 18613557 | I4: =E4-G4 -> 2419762.4
A5: 2025-2 | B5: 15885357 | E5: 2065096.4 | H5: =B5+C5+D5-F5 -> 15885357 | I5: =E5-G5 -> 2065096.4
A6: 2025-3 | H6: =B6+C6+D6-F6 -> 0 | I6: =E6-G6 -> 0
A7: 2025-4 | H7: =B7+C7+D7-F7 -> 0 | I7: =E7-G7 -> 0
A8: 2025-5 | H8: =B8+C8+D8-F8 -> 0 | I8: =E8-G8 -> 0
A9: 2025-6 | H9: =B9+C9+D9-F9 -> 0 | I9: =E9-G9 -> 0
A10: 2025-7 | H10: =B10+C10+D10-F10 -> 0 | I10: =E10-G10 -> 0
A11: 2025-8 | H11: =B11+C11+D11-F11 -> 0 | I11: =E11-G11 -> 0
A12: 2025-9 | H12: =B12+C12+D12-F12 -> 0 | I12: =E12-G12 -> 0
A13: 2025-10 | H13: =B13+C13+D13-F13 -> 0 | I13: =E13-G13 -> 0
A14: 2025-11 | H14: =B14+C14+D14-F14 -> 0 | I14: =E14-G14 -> 0
A15: 2025-12 | H15: =B15+C15+D15-F15 -> 0 | I15: =E15-G15 -> 0
A16: 合计数 | B16: =SUM(B4:B15) -> 34498913 | C16: =SUM(C4:C15) -> 0 | D16: =SUM(D4:D15) -> 0 | E16: =SUM(E4:E15) -> 4484858.8 | F16: =SUM(F4:F15) -> 0 | G16: =SUM(G4:G15) -> 0 | H16: =SUM(H4:H15) -> 34498913 | I16: =SUM(I4:I15) -> 4484858.8

Sheet PL附表-2320、2355
A2: 睿景、景程PL附表
A3: 拆分依据 | B3: 未开票收入 | C3: 销项 | D3: 已开票收入 | E3: 已开票销项
A4: 专票-13% | B4: 申报金额-已开票收入 | C4: 申报税额-已开票销项 | D4: 取【睿景月结数据表】报税页签设备区域已开票收入列合计 | E4: 取【睿景月结数据表】报税页签设备区域已开票税额列合计
A5: 专票-9% | B5: 申报金额-已开票收入 | C5: 申报税额-已开票销项 | D5: 取【睿景月结数据表】报税页签建安区域已开票收入列合计 | E5: 取【睿景月结数据表】报税页签建安区域已开票税额列合计
A6: 专票-6% | B6: 申报金额-已开票收入 | C6: 申报税额-已开票销项 | D6: 取【睿景月结数据表】报税页签建安区域除设备、建安区域外其他区域已开票收入列合计 | E6: 取【睿景月结数据表】报税页签建安区域除设备、建安区域外其他区域已开票税额列合计
A7: 普票-13%
A8: 普票-9%
A9: 普票-6%
B10: =SUM(B4:B9) -> 0 | C10: =SUM(C4:C9) -> 0 | D10: =SUM(D4:D9) -> 0 | E10: =SUM(E4:E9) -> 0
A14: 拆分依据 | B14: 申报金额 | C14: 申报税额
A15: 专票-13% | B15: 取【睿景月结数据表】报税页签设备区域收入列合计 | C15: 取【睿景月结数据表】报税页签设备区域销项列合计
A16: 专票-9% | B16: 取【睿景月结数据表】报税页签建安区域收入列合计 | C16: 取【睿景月结数据表】报税页签建安区域销项列合计
A17: 专票-6% | B17: 取【睿景月结数据表】报税页签建安区域除设备、建安区域外其他区域收入列合计 | C17: 取【睿景月结数据表】报税页签建安区域除设备、建安区域外其他区域销项列合计
A18: 普票-13%
A19: 普票-9%
A20: 普票-6%
A21: 合计： | B21: =SUM(B15:B20) -> 0 | C21: =SUM(C15:C20) -> 0

Sheet 累计税金汇总表-2320、2355
A1: 时间：所属期 单位：元 | C1: 税金缴纳标准 | D1: 202412 | E1: 202501 | F1: 202502 | G1: 202503 | H1: 202504 | I1: 202505 | J1: 202506 | K1: 202507 | L1: 202508 | M1: 202509 | N1: 202510 | O1: 202511 | P1: 202512
A2: 基数 | B2: 账面收入 | D2: 1.5126491e+09 | E2: 4.3116584e+08 | F2: 3.5558408e+08 | G2: 48816138 | H2: 97382183 | I2: 50884270 | J2: 1.2171605e+08 | K2: 1.1081929e+08 | L2: 1.7958369e+08 | M2: 1.7442616e+08 | N2: 1.1709462e+08 | O2: 1.7393182e+09 | P2: 取台账期【增值税变动表】条目=当月利润表主营业务收入*合计列相加 | R2: 在前序税务台账此页的基础上新增本次台账期数据
B3: 其他收益 | P3: 取【其他科目明细表】科目=6702000010货币金额合计
B4: 项目开票 | D4: 1.1262598e+09 | E4: 7.805366e+08 | F4: 5.2620168e+08 | G4: 4.7608694e+08 | H4: 78604519 | I4: 37974761 | J4: 2.3684048e+08 | K4: 1.0914781e+08 | L4: 1.4016733e+08 | M4: 2.3979933e+08 | N4: 3.1389905e+08 | O4: 1.0132121e+09 | P4: 取台账期【增值税变动表】条目=当月利润表主营业务收入*当月开票金额列相加
B5: 利息开票 | P5: 取【其他科目明细表】科目=6603020011货币金额合计
B6: 销项税额 | C6: A | D6: 1.5335725e+08 | E6: 54874884 | F6: 45434329 | G6: 4651212.5 | H6: 9372591.2 | I6: 4606639.5 | J6: 10897955 | K6: 9901838.1 | L6: 12579095 | M6: 16661164 | N6: 12198025 | O6: 2.2262931e+08 | P6: 取台账期【增值税变动表】条目=条目=应交增值税-销项税*合计列相加
B7: 本期进项税额 | C7: B | D7: 67835873 | E7: 72025452 | F7: 60425055 | G7: 7987426.8 | H7: 7347644.3 | I7: 7003174.4 | J7: 4385018.7 | K7: 6626261.8 | L7: 22887594 | M7: 18893309 | N7: 18347860 | O7: 1.8479839e+08 | P7: 取台账期【增值税变动表】条目=应交增值税-增值税已认证进项税合计字段值
B8: 上期留抵税额 | C8: C | O8: 2228173.5 | P8: 取台账期【增值税变动表】条目=期初留抵进项税合计字段值
B9: 进项税额转出 | C9: D | E9: 14956.1 | F9: 3542.11 | G9: 595805.07 | H9: 22641.51 | J9: 272019.39 | K9: 43475.46 | L9: 267177.47 | M9: 82568.81 | P9: 取台账期【增值税变动表】条目=进项转出合计字段值
B10: 异地预缴税增值税 | C10: E | D10: 11847361 | G10: 29781.96 | H10: 2217866.5 | I10: 655226.71 | J10: 382841.63 | L10: 116982.96 | M10: 2762668.3 | P10: 取台账期【增值税变动表】条目=异地预缴抵减合计字段值
B11: 应纳增值税额 | C11: A-B-C+D-E | D11: 73674014 | P11: 取台账期【增值税变动表】条目=本期应交增值税合计字段值
B12: 增值税 | D12: 73674014 | E12: =E11 -> 0 | F12: =F11 -> 0 | G12: =G11 -> 0 | H12: 0 | I12: =I11 -> 0 | J12: =J11 -> 0 | K12: =K11 -> 0 | L12: =L11 -> 0 | M12: =M11 -> 0 | N12: =N11 -> 0 | O12: =O11 -> 0 | P12: ‘=P11
B13: 印花税 | D13: 1051983.4 | J13: 330365.58 | P13: 取summary表，税种=印花税合计，取实际应缴税额
B14: 城建税 | C14: 增值税额的7% | D14: 5157181 | E14: =E12*0.07 -> 0 | F14: =F12*0.07 -> 0 | G14: =G12*0.07 -> 0 | H14: =H12*0.07 -> 0 | I14: =I12*0.07 -> 0 | J14: =J12*0.07 -> 0 | K14: =K12*0.07 -> 0 | L14: =L12*0.07 -> 0 | ... O14: =O12*0.07 -> 0 | P14: =P12*税目配置表对应税率
B15: 教育费附加 | C15: 增值税额的3% | D15: 2210220.4 | E15: =E12*0.03 -> 0 | F15: =F12*0.03 -> 0 | G15: =G12*0.03 -> 0 | H15: =H12*0.03 -> 0 | I15: =I12*0.03 -> 0 | J15: =J12*0.03 -> 0 | K15: =K12*0.03 -> 0 | L15: =L12*0.03 -> 0 | ... O15: =O12*0.03 -> 0 | P15: =P12*税目配置表对应税率
B16: 地方教育费附加 | C16: 增值税额的2% | D16: 1473480.3 | E16: =E12*0.02 -> 0 | F16: =F12*0.02 -> 0 | G16: =G12*0.02 -> 0 | H16: =H12*0.02 -> 0 | I16: =I12*0.02 -> 0 | J16: =J12*0.02 -> 0 | K16: =K12*0.02 -> 0 | L16: =L12*0.02 -> 0 | ... O16: =O12*0.02 -> 0 | P16: =P12*税目配置表对应税率
B17: 房产税 | P17: 取summary表，税种=房产税，取实际应缴税额
B18: 城镇土地使用 | P18: 取summary表，税种=城镇土地使用税，取实际应缴税额
B19: 企业所得税 | D19: 3.8001788e+08 | J19: 29332502 | M19: 25579909 | P19: 取summary表，税种=企业所得税合计，取本季度应缴税额
B20: 个税 | P20: 取summary表，税种=城镇土地使用税，取实际应缴税额
B21: 残疾人保障金 | K21: 181635.35 | P21: 取summary表，税种=残疾人保障金，取实际应缴税额
B22: 合计 | D22: =SUM(D12:D21) -> 4.6358476e+08 | E22: =SUM(E12:E21) -> 0 | F22: =SUM(F12:F21) -> 0 | G22: =SUM(G12:G21) -> 0 | H22: =SUM(H12:H21) -> 0 | I22: =SUM(I12:I21) -> 0 | J22: =SUM(J12:J21) -> 29662867 | K22: =SUM(K12:K21) -> 181635.35 | ... P22: =SUM(P12:P21) -> 0
F26: 异地预缴 | H26: 异地预缴 | I26: 企业所得税
F27: 郎溪景宇风力发电有限公司 | H27: 郎溪
F28: 馆陶县汇恒风电有限公司 | H28: 察哈尔景源
F29: 伊金霍洛旗悦盛新能源有限公司 | H29: 定远纳驰 | I29: 450039.33
H30: 定远纳风 | I30: 734696.74
H31: 哈密博景
F33: 中国石油天然气股份有限公司 吐哈油田分公司 | H33: 吐哈油田 | I33: 136.15
F34: 定远智贮能源科技有限公司 | H34: 远景定远智慧储能共享电站项目 EPC | I34: 61976.18
E37: 45748 | F37: 定边远边汇新能源有限公司 | H37: 定边县红柳沟镇白兴庄 | I37: 443045.39
E39: 45778 | F39: 乌海市远鸿富景新能源科技有限公司 | H39: 乌海市金湖独立储能电站项目EPC总承 | I39: 96963.75
F40: 招银金融租赁有限公司 | H40: 利豪鸡泽县50MW保障类风电场 | I40: 172641.17
E42: 45809 | F42: 滨州远凌新能源有限责任公司 | H42: 滨州北海储能电站项目 | I42: 59826.73
F43: 清水河县云景风力发电有限公 司 | H43: 清水河县城关分散式风电场项目EPC总承包 | I43: 62095.04
E44: 2025.7 | H44: 射阳汇智风电场项目 EPC 总承包采购合同 | I44: 98649.14
E45: 2025.8 | G45: 陕西省榆林市靖边县东南部天赐湾乡 | H45: 靖边县状泽城河100兆瓦风电场项目EPC工程总承包合同 | I45: 364233.03
E46: 2025.9 | G46: 内蒙古自治区乌兰察布市察哈尔右翼后旗 | I46: 288997.39

Sheet 账税差异监控-2320、2355
B2: 日期 | C2: 商品销售（13%） | E2: 建筑安装（9%） | G2: 设计服务（6%） | I2: 汇总 | K2: 帐税差异 | L2: 差异分析 | N2: 在前序税务台账此页的基础上新增本次台账期数据
C3: 账面收入 | D3: 申报收入 | E3: 账面收入 | F3: 申报收入 | G3: 账面收入 | H3: 申报收入 | I3: 账面收入 | J3: 增值税申报收入
B4: 202501 | C4: 4.0460338e+08 | D4: 4.0460338e+08 | E4: 22756563 | F4: 22756563 | G4: 3805898.1 | H4: 3805898.1 | I4: =C4+E4+G4 -> 4.3116584e+08 | J4: =D4+F4+H4 -> 4.3116584e+08 | K4: =I4-J4 -> 0
B5: 202502 | C5: 3.4233211e+08 | D5: 3.4233211e+08 | E5: 4534546.6 | F5: 4534546.6 | G5: 8717422.1 | H5: 8717422.1 | I5: =C5+E5+G5 -> 3.5558408e+08 | J5: =D5+F5+H5 -> 3.5558408e+08 | K5: =I5-J5 -> 0
B6: 202503 | C6: 9263829.2 | D6: 9263829.2 | E6: 35792541 | F6: 35792541 | G6: 3759768 | H6: 3759768 | I6: =C6+E6+G6 -> 48816138 | J6: =D6+F6+H6 -> 48816138 | K6: =I6-J6 -> 0
B7: 202504 | C7: 21323842 | D7: 21323842 | E7: 67899709 | F7: 67899709 | G7: 8158632 | H7: 8158632 | I7: =C7+E7+G7 -> 97382183 | J7: =D7+F7+H7 -> 97382183 | K7: =I7-J7 -> 0
B8: 202505 | C8: 28632006 | D8: 28632006 | E8: -15021903 | F8: -15021903 | G8: 37274167 | H8: 37274167 | I8: =C8+E8+G8 -> 50884270 | J8: =D8+F8+H8 -> 50884270 | K8: =I8-J8 -> 0
B9: 202506 | C9: 5217250.7 | D9: 5217250.7 | E9: 15916344 | F9: 1.0765946e+08 | G9: 8839340.7 | H9: 8839340.7 | I9: =C9+E9+G9 -> 29972935 | J9: =D9+F9+H9 -> 1.2171605e+08 | K9: =I9-J9 -> -91743119 | L9: 调整5月数据，为了全年累计收入和销项税金额和账面对上
B10: 202507 | C10: 10527136 | D10: 10527136 | E10: 83859377 | F10: 83859377 | G10: 16432773 | H10: 16432773 | I10: =C10+E10+G10 -> 1.1081929e+08 | J10: =D10+F10+H10 -> 1.1081929e+08 | K10: =I10-J10 -> 0
B11: 202508 | C11: 36101207 | D11: 1.7123491e+08 | E11: 1.2087632e+08 | F11: 1.2100853e+08 | G11: 22606165 | H11: 22669790 | I11: =C11+E11+G11 -> 1.7958369e+08 | J11: =D11+F11+H11 -> 3.1491323e+08 | K11: =I11-J11 -> -1.3532954e+08 | L11: DHL项目8月只确认了销项，没确认收入，和大业项目预开票金额确认申报
B12: 202509 | C12: 38059869 | D12: 38059869 | E12: 1.1771344e+08 | F12: 1.1771344e+08 | G12: 18652850 | H12: 18652850 | I12: =C12+E12+G12 -> 1.7442616e+08 | J12: =D12+F12+H12 -> 1.7442616e+08 | K12: =I12-J12 -> 0
B13: 202510 | C13: 50555058 | D13: 1.9887533e+08 | E13: 53264485 | F13: 53659589 | G13: 13275081 | H13: 13275081 | I13: =C13+E13+G13 -> 1.1709462e+08 | J13: =D13+F13+H13 -> 2.6581e+08 | K13: =I13-J13 -> -1.4871537e+08 | L13: 大业项目预开票金额冲回10730530.06，综能项目预开票收入申报395103.89，五河项目融资设备预开票金额159050800.11
B14: 202511 | C14: 1.6361222e+09 | D14: 1.3529404e+09 | E14: 1.2590767e+08 | F14: 1.2551256e+08 | G14: -22711643 | H14: -22711643 | I14: =C14+E14+G14 -> 1.7393182e+09 | J14: =D14+F14+H14 -> 1.4557413e+09 | K14: =I14-J14 -> 2.8357688e+08 | L14: 大业项目预开票金额冲回124130974.37，综能项目预开票收入冲回395103.89，五河项目融资设备预开票冲回159050800.11
B15: 202512 | C15: 取【增值税变动表 】条目=当月利润表主营业务收入（商品销售13%）的合计金额 | D15: 默认为空 | E15: 取【增值税变动表 】条目=当月利润表主营业务收入（建安收入9%）的合计金额 | F15: 默认为空 | G15: 取【增值税变动表 】条目=当月利润表主营业务收入（设计服务6%）的合计金额 | H15: 默认为空 | I15: ’=C15+E15+G15 | J15: ‘=D15+F15+H15 | K15: ‘=I15-J15

Sheet 增值税表一 累计销项-2320、2355
A2: 所属期 | B2: 涉税类别 | C2: 已开票 | F2: 未开票 | I2: 合计 | M2: 在前序税务台账此页的基础上新增本次台账期数据
C3: 不含税金额 | D3: 税额 | E3: 税率 | F3: 不含税金额 | G3: 税额 | H3: 税率 | I3: 不含税金额 | J3: 税额
A4: 202501 | B4: 商品销售 | C4: 4.7777895e+08 | D4: =C4*E4 -> 62111263 | E4: 0.13 | F4: -73175570 | G4: =F4*H4 -> -9512824.1 | H4: 0.13 | I4: =C4+F4 -> 4.0460338e+08 | J4: =D4+G4 -> 52598439
B5: 工程建设 | C5: 2.8243024e+08 | D5: =C5*E5 -> 25418722 | E5: 0.09 | F5: -2.5967368e+08 | G5: =F5*H5 -> -23370631 | H5: 0.09 | I5: =C5+F5 -> 22756563 | J5: =D5+G5 -> 2048090.7
B6: 设计服务 | C6: 20327408 | D6: =C6*E6 -> 1219644.5 | E6: 0.06 | F6: -16521510 | G6: =F6*H6 -> -991290.58 | H6: 0.06 | I6: =C6+F6 -> 3805898.1 | J6: =D6+G6 -> 228353.89
A7: 202502 | B7: 商品销售 | C7: 4.4148457e+08 | D7: =C7*E7-0.04 -> 57392994 | E7: 0.13 | F7: -99152456 | G7: =F7*H7+0.04 -> -12889819 | H7: 0.13 | I7: =C7+F7 -> 3.4233211e+08 | J7: =D7+G7 -> 44503175
B8: 工程建设 | C8: 65474783 | D8: =C8*E8+0.02 -> 5892730.5 | E8: 0.09 | F8: -60940237 | G8: =F8*H8-0.03 -> -5484621.3 | H8: 0.09 | I8: =C8+F8 -> 4534546.6 | J8: =D8+G8 -> 408109.18
B9: 设计服务 | C9: 19242331 | D9: =C9*E9+0.05 -> 1154539.9 | E9: 0.06 | F9: -10524909 | G9: =F9*H9-0.03 -> -631494.55 | H9: 0.06 | I9: =C9+F9 -> 8717422.1 | J9: =D9+G9 -> 523045.35
A10: 202503 | B10: 商品销售 | C10: 3.5947726e+08 | D10: 46732044 | E10: 0.13 | F10: -3.5021343e+08 | G10: -45527746 | H10: 0.13 | I10: =C10+F10 -> 9263829.1 | J10: =D10+G10 -> 1204297.8
B11: 工程建设 | C11: 65827968 | D11: 5924517.1 | E11: 0.09 | F11: -30035427 | G11: -2703188.5 | H11: 0.09 | I11: =C11+F11 -> 35792541 | J11: =D11+G11 -> 3221328.7
B12: 设计服务 | C12: 50781714 | D12: 3046902.8 | E12: 0.06 | F12: -47021946 | G12: -2821316.7 | H12: 0.06 | I12: =C12+F12 -> 3759768 | J12: =D12+G12 -> 225586.09
A13: 202504 | B13: 商品销售 | C13: 17534647 | D13: =C13*E13+0.02 -> 2279504.2 | E13: 0.13 | F13: 3789194.8 | G13: =F13*H13-0.01 -> 492595.32 | H13: 0.13 | I13: =C13+F13 -> 21323842 | J13: =D13+G13 -> 2772099.5
B14: 工程建设 | C14: 60452779 | D14: =C14*E14-0.01 -> 5440750.1 | E14: 0.09 | F14: 7446930 | G14: =F14*H14 -> 670223.7 | H14: 0.09 | I14: =C14+F14 -> 67899709 | J14: =D14+G14 -> 6110973.8
B15: 设计服务 | C15: 617092.61 | D15: =C15*E15 -> 37025.557 | E15: 0.06 | F15: 7541539.4 | G15: =F15*H15 -> 452492.36 | H15: 0.06 | I15: =C15+F15 -> 8158632 | J15: =D15+G15 -> 489517.92
A16: 202505 | B16: 商品销售 | C16: 33522209 | D16: =C16*E16-0.01 -> 4357887.2 | E16: 0.13 | F16: -4890202.6 | G16: =F16*H16+0.01 -> -635726.33 | H16: 0.13 | I16: =C16+F16 -> 28632006 | J16: =D16+G16 -> 3722160.8
B17: 工程建设 | C17: 2703065 | D17: =C17*E17-0.01 -> 243275.84 | E17: 0.09 | F17: -17724968 | G17: =F17*H17-0.01 -> -1595247.1 | H17: 0.09 | I17: =C17+F17 -> -15021903 | J17: =D17+G17 -> -1351971.3
B18: 设计服务 | C18: 1749486.8 | D18: =C18*E18-0.03 -> 104969.18 | E18: 0.06 | F18: 35524680 | G18: =F18*H18-0.01 -> 2131480.8 | H18: 0.06 | I18: =C18+F18 -> 37274167 | J18: =D18+G18+0.01 -> 2236450
A19: 202506 | B19: 商品销售 | C19: 1.1092236e+08 | D19: =C19*E19+0.08 -> 14419907 | E19: 0.13 | F19: -1.0570511e+08 | G19: =F19*H19-0.08 -> -13741665 | H19: 0.13 | I19: =C19+F19 -> 5217250.7 | J19: =D19+G19 -> 678242.59
B20: 工程建设 | C20: 79949926 | D20: =C20*E20-0.03 -> 7195493.3 | E20: 0.09 | F20: 27709538 | G20: =F20*H20+0.05 -> 2493858.4 | H20: 0.09 | I20: =C20+F20 -> 1.0765946e+08 | J20: =D20+G20 -> 9689351.7
B21: 设计服务 | C21: 45968194 | D21: =C21*E21-0.02 -> 2758091.6 | E21: 0.06 | F21: -37128853 | G21: =F21*H21+0.02 -> -2227731.2 | H21: 0.06 | I21: =C21+F21 -> 8839340.7 | J21: =D21+G21 -> 530360.44
A22: 202507 | B22: 商品销售 | C22: 21068171 | D22: =C22*E22+0.07 -> 2738862.3 | E22: 0.13 | F22: -10541035 | G22: =F22*H22-0.08 -> -1370334.6 | H22: 0.13 | I22: =C22+F22 -> 10527136 | J22: =D22+G22-0.01 -> 1368527.7
B23: 工程建设 | C23: 74348075 | D23: =C23*E23-0.01 -> 6691326.8 | E23: 0.09 | F23: 9511301.3 | G23: =F23*H23-0.02 -> 856017.1 | H23: 0.09 | I23: =C23+F23 -> 83859377 | J23: =D23+G23+0.01 -> 7547343.9
B24: 设计服务 | C24: 13731566 | D24: =C24*E24+0.05 -> 823894.03 | E24: 0.06 | F24: 2701206.9 | G24: =F24*H24+0.02 -> 162072.44 | H24: 0.06 | I24: =C24+F24 -> 16432773 | J24: =D24+G24 -> 985966.47
A25: 202508 | B25: 商品销售 | C25: 1.3644534e+08 | D25: =C25*E25 -> 17737895 | E25: 0.13 | F25: 34789570 | G25: 4522644 | H25: 0.13 | I25: =C25+F25 -> 1.7123491e+08 | J25: =D25+G25 -> 22260539
B26: 工程建设 | C26: 866835.23 | D26: 78015.15 | E26: 0.09 | F26: 1.2014169e+08 | G26: 10812752 | H26: 0.09 | I26: =C26+F26 -> 1.2100853e+08 | J26: =D26+G26 -> 10890768
B27: 设计服务 | C27: 2855156.3 | D27: 171309.36 | E27: 0.06 | F27: 19814633 | G27: 1188878 | H27: 0.06 | I27: =C27+F27 -> 22669790 | J27: =D27+G27 -> 1360187.4
A28: 202509 | B28: 商品销售 | C28: 7446608.4 | D28: =C28*E28-0.01 -> 968059.09 | E28: 0.13 | F28: 30613261 | G28: =F28*H28 -> 3979723.9 | H28: 0.13 | I28: =C28+F28 -> 38059869 | J28: =D28+G28 -> 4947783
B29: 工程建设 | C29: 2.2254209e+08 | D29: =C29*E29+0.01 -> 20028788 | E29: 0.09 | F29: -1.0482864e+08 | G29: =F29*H29 -> -9434578 | H29: 0.09 | I29: =C29+F29 -> 1.1771344e+08 | J29: =D29+G29 -> 10594210
B30: 设计服务 | C30: 9810630.4 | D30: =C30*E30 -> 588637.82 | E30: 0.06 | F30: 8842219.5 | G30: =F30*H30+0.03 -> 530533.2 | H30: 0.06 | I30: =C30+F30 -> 18652850 | J30: =D30+G30-0.01 -> 1119171
A31: 202510 | B31: 商品销售 | C31: 1.9320679e+08 | D31: 25116882 | E31: 0.13 | F31: 5668542.2 | G31: 736910.5 | H31: 0.13 | I31: =C31+F31 -> 1.9887533e+08 | J31: =D31+G31 -> 25853793
B32: 工程建设 | C32: 80723241 | D32: 7265091.8 | E32: 0.09 | F32: -27063652 | G32: -2435728.7 | H32: 0.09 | I32: =C32+F32 -> 53659589 | J32: =D32+G32 -> 4829363
B33: 设计服务 | C33: 39969022 | D33: 2398141.3 | E33: 0.06 | F33: -26693940 | G33: -1601636.4 | H33: 0.06 | I33: =C33+F33 -> 13275081 | J33: =D33+G33 -> 796504.86
A34: 202511 | B34: 商品销售 | C34: 1.0352842e+09 | D34: 1.3458694e+08 | E34: 0.13 | F34: 3.1765623e+08 | G34: 41295310 | H34: 0.13 | I34: =C34+F34 -> 1.3529404e+09 | J34: =D34+G34 -> 1.7588225e+08
B35: 工程建设 | C35: 6040022.1 | D35: 543602.02 | E35: 0.09 | F35: 1.1947254e+08 | G35: 10752529 | H35: 0.09 | I35: =C35+F35 -> 1.2551256e+08 | J35: =D35+G35 -> 11296131
B36: 设计服务 | C36: -28112069 | D36: -1686724.1 | E36: 0.06 | F36: 5400425.7 | G36: 324025.52 | H36: 0.06 | I36: =C36+F36 -> -22711643 | J36: =D36+G36 -> -1362698.6
A37: 202512 | B37: 商品销售 | C37: 取【增值税变动表 】条目=当月利润表主营业务收入（商品销售*的当月开票金额 | D37: 取【增值税变动表 】条目=应交增值税-销项税（商品销售*的当月开票金额 | E37: 取【增值税变动表 】条目中的税率显示 | F37: 取【增值税变动表 】条目=当月利润表主营业务收入（商品销售*的未开票金额 | G37: 取【增值税变动表 】条目=应交增值税-销项税（商品销售*的未开票金额 | H37: 取【增值税变动表 】条目中的税率显示 | I37: ’=C37+F37 | J37: ‘=D37+G37
B38: 工程建设 | C38: 取【增值税变动表 】条目=当月利润表主营业务收入（建安收入*的当月开票金额 | D38: 取【增值税变动表 】条目=应交增值税-销项税（建安收入*的当月开票金额 | E38: 取【增值税变动表 】条目中的税率显示 | F38: 取【增值税变动表 】条目=当月利润表主营业务收入（建安收入*的未开票金额 | G38: 取【增值税变动表 】条目=应交增值税-销项税（建安部分*的未开票金额 | H38: 取【增值税变动表 】条目中的税率显示 | I38: ‘=C38+F38 | J38: ’=D38+G38
B39: 设计服务 | C39: 取【增值税变动表 】条目=当月利润表主营业务收入（设计服务*的当月开票金额 | D39: 取【增值税变动表 】条目=应交增值税-销项税（设计服务*的当月开票金额 | E39: 取【增值税变动表 】条目中的税率显示 | F39: 取【增值税变动表 】条目=当月利润表主营业务收入（设计服务*的未开票金额 | G39: 取【增值税变动表 】条目=应交增值税-销项税（设计服务*的未开票金额 | H39: 取【增值税变动表 】条目中的税率显示 | I39: ’=C39+F39 | J39: ‘=D39+G39

Sheet 项目累计申报
B1: 申报税费汇总表
B2: 上海睿景能源科技有限公司 | M2: 残疾人保证金 | P2: 单位：元
B3: 所属期 | C3: 所得税 | D3: 增值税 | E3: 增值税附加税 | F3: 印花税 | G3: 工会经费 | H3: 房产税 | I3: 个人所得税 | J3: 耕地占用税 | K3: 土地使用税 | L3: 垃圾费 | M3: 水利基金、残疾人保证金 | N3: 税务检查补税 | O3: 契税 | P3: 税款合计 | R3: 在前序税务台账此页的基础上新增本次台账期数据
B4: 45658 | P4: =SUM(C4:O4) -> 0
B5: 45689 | P5: =SUM(C5:O5) -> 0
B6: 45717 | F6: 241059.07 | P6: =SUM(C6:O6) -> 241059.07 | R6: 税目取summary税目配置表
B7: 45748 | P7: =SUM(C7:O7) -> 0
B8: 45778 | P8: =SUM(C8:O8) -> 0
B9: 45809 | C9: 29332502 | F9: 330365.58 | P9: =SUM(C9:O9) -> 29662867
B10: 45839 | M10: 181635.35 | P10: =SUM(C10:O10) -> 181635.35
B11: 45870 | P11: =SUM(C11:O11) -> 0
B12: 45901 | C12: 25579909 | F12: 344819.57 | P12: =SUM(C12:O12) -> 25924728
B13: 45931 | P13: =SUM(C13:O13) -> 0
B14: 45962 | P14: =SUM(C14:O14) -> 0
B15: 45992 | C15: 取【summary表】税种对应实际应纳税额合计 | P15: ‘=SUM(C15:O15)
B16: 合计 | C16: =SUM(C4:C15) -> 54912411 | D16: =SUM(D4:D15) -> 0 | E16: =SUM(E4:E15) -> 0 | F16: =SUM(F4:F15) -> 916244.22 | G16: =SUM(G4:G15) -> 0 | H16: =SUM(H4:H15) -> 0 | I16: =SUM(I4:I15) -> 0 | J16: =SUM(J4:J15) -> 0 | ... O16: =SUM(O4:O15) -> 0 | P16: ’=SUM(C16:O16)

Sheet 项目累计缴纳
B1: 实缴税费汇总表
B2: 上海睿景能源科技有限公司 | M2: 残疾人保证金 | P2: 单位：元
B3: 实际缴纳所属期 | C3: 所得税 | D3: 增值税 | E3: 增值税附加税 | F3: 印花税 | G3: 工会经费 | H3: 房产税 | I3: 个人所得税 | J3: 耕地占用税 | K3: 土地使用税 | L3: 垃圾费 | M3: 水利基金 | N3: 税务检查补税 | O3: 契税 | P3: 实缴税金 | Q3: 申请税金 | R3: 差异 | S3: 原因
B4: 45658 | C4: 3.8001788e+08 | D4: 77264494 | E4: 7,850, 055.95 | F4: 1051983.4 | P4: =SUM(C4:O4) -> 4.5833436e+08 | Q4: 0 | R4: =P4-Q4 -> 4.5833436e+08 | T4: 在前序税务台账此页的基础上新增本次台账期数据
B5: 45689 | P5: =SUM(C5:O5) -> 0 | Q5: 0 | R5: =P5-Q5 -> 0
B6: 45717 | P6: =SUM(C6:O6) -> 0 | Q6: 241059.07
B7: 45748 | F7: 241059.07 | P7: =SUM(C7:O7) -> 241059.07 | Q7: 0 | R7: =P7-Q6 -> 0 | U7: 税目取summary税目配置表
B8: 45778 | P8: =SUM(C8:O8) -> 0 | Q8: 0 | R8: =P8-Q8 -> 0
B9: 45809 | P9: =SUM(C9:O9) -> 0 | Q9: =[113]睿景项目累计申报!P9 -> 29662867 | R9: =P9-Q8 -> 0
B10: 45839 | C10: 29332502 | F10: 330365.58 | P10: =SUM(C10:O10) -> 29662867 | Q10: 0 | R10: =P10-Q9 -> 0
B11: 45870 | P11: =SUM(C11:O11) -> 0 | Q11: 0 | R11: =P11-Q11 -> 0
B12: 45901 | P12: =SUM(C12:O12) -> 0 | Q12: =[113]睿景项目累计申报!P12 -> 25924728 | R12: =P12-Q11 -> 0
B13: 45931 | C13: 25579909 | F13: 344819.57 | P13: =SUM(C13:O13) -> 25924728 | Q13: 0 | R13: =P13-Q12 -> 0
B14: 45962 | P14: =SUM(C14:O14) -> 0 | Q14: 0 | R14: =P14-Q14 -> 0
B15: 45992 | P15: =SUM(C15:O15) -> 0 | Q15: 取【项目累计申报表】台账期税款合计 | R15: =P15-Q15 -> #VALUE!
B16: 合计 | C16: =SUM(C4:C15) -> 4.3493029e+08 | D16: =SUM(D4:D15) -> 77264494 | E16: =SUM(E4:E15) -> 0 | F16: =SUM(F4:F15) -> 1968227.6 | G16: =SUM(G4:G15) -> 0 | H16: =SUM(H4:H15) -> 0 | I16: =SUM(I4:I15) -> 0 | J16: =SUM(J4:J15) -> 0 | ... O16: =SUM(O4:O15) -> 0 | P16: =SUM(C16:O16) -> 5.1416301e+08 | Q16: =SUM(Q4:Q15) -> 55828655 | R16: =SUM(R4:R15) -> #VALUE!

Sheet 印花税明细
A1: 序号 | B1: 税目 | C1: 计税依据 | D1: 税率 | E1: 应纳税额 | F1: 减免税额 | G1: 已缴税额 | H1: 应补（退）税额
A2: 正序填充 | B2: 取【合同印花税明细台账】台账月份所属季度的印花税税目去重填列 | C2: 由此表税目=【合同印花税明细台账】印花税税目，取得【合同印花税明细台账】合同金额字段汇总 | D2: 由此表税目=【合同印花税明细台账】印花税税目，取得【合同印花税明细台账】印花税税率 | E2: ’=C2*D2 | F2: 由此表税目=【合同印花税明细台账】印花税税目，取得【合同印花税明细台账】优惠比例、合同金额字段、印花税税率，计算取得行合同金额*印花税税率*优惠比例的汇总数填列 | G2: 默认为空 | H2: ‘=E2-F2
A3: 1 | B3: 借款合同 | C3: 0 | D3: 5e-05 | E3: 0 | F3: 0 | H3: 0
A4: 2 | B4: 融资租赁合同 | C4: 0 | D4: 5e-05 | E4: 0 | F4: 0 | H4: 0
A5: 3 | B5: 买卖合同 | C5: 3.3248115e+08 | D5: 0.0003 | E5: 99744.345 | F5: 49872.173 | H5: 49872.17
A6: 4 | B6: 承揽合同 | C6: 0 | D6: 0.0003 | E6: 0 | F6: 0 | H6: 0
A7: 5 | B7: 建设工程合同 | C7: 2.8617382e+08 | D7: 0.0003 | E7: 85852.145 | F7: 42926.073 | H7: 42926.07
A8: 6 | B8: 运输合同 | C8: 0 | D8: 0.0003 | E8: 0 | F8: 0 | H8: 0
A9: 7 | B9: 技术合同 | C9: 174528.3 | D9: 0.0003 | E9: 52.35849 | F9: 26.179245 | H9: 26.18
A10: 8 | B10: 租赁合同 | C10: 67129.74 | D10: 0.001 | E10: 67.12974 | F10: 33.56487 | H10: 33.56
A11: 9 | B11: 保管合同 | C11: 0 | D11: 0.001 | E11: 0 | F11: 0 | H11: 0
A12: 10 | B12: 仓储合同 | C12: 0 | D12: 0.001 | E12: 0 | F12: 0 | H12: 0
A13: 11 | B13: 财产保险合同 | C13: 0 | D13: 0.001 | E13: 0 | F13: 0 | H13: 0
A14: 12 | B14: 土地使用权 出让书据 | C14: 0 | D14: 0.0005 | E14: 0 | F14: 0 | H14: 0
... A19: 17 | B19: 证券交易 | C19: 0 | D19: 0.001 | E19: 0 | F19: 0 | H19: 0
B20: 合计 | C20: 6.1889663e+08 | E20: 185715.98 | F20: 92857.989 | G20: 0 | H20: 92857.98

Sheet 收入明细、销项明细、进项明细、所得税明细、其他科目明细
A1: 字段 | B1: 公司代码 | C1: 财政年/阶段 | D1: 凭证日期 | E1: 过账日期 | F1: 凭证类型 | G1: 凭证编号 | H1: 抬头文本 | I1: 行项目号 | J1: 总账科目 | K1: 本币金额 | L1: 本币 | M1: 货币金额 | N1: 凭证货币 | O1: 行文本 | P1: 付款参考 | Q1: 贸易伙伴 | R1: 客户 | S1: 供应商 | T1: 成本中心 | U1: WBS | V1: 参照 | W1: 冲销凭证号 | X1: 采购凭证 | Y1: 参考代码1 | Z1: 分配 | AA1: 用户名
A2: 数据集字段 | B2: company_code | C2: fiscal_year_period | D2: document_date | E2: posting_date_in_the_document | F2: document_type | G2: document_print_number | H2: document_header_text | I2: number_of_line_item_within_accounting_document | J2: account | K2: credit_amount_in_local_currency或者 debit_amount_in_local_currency | L2: currency_key_of_the_local_currency | M2: credit_amount_in_document_currency或者debit_amount_in_document_currency | N2: currency_key_of_the_document_currency | O2: item_text | P2: payment_reference | Q2: company_id_of_trading_partner | R2: customer_number | S2: vendor_number | T2: cost_center | U2: wbs_element | V2: reference | W2: reverse_document_number | X2: purchasing_document_number | Y2: reference_key_1_for_line_item | Z2: assignment | AA2: user_name
A3: 取值逻辑 | J3: 1. 销项明细，科目默认 2221010200 2. 进项明细，科目默认 2221010100、2221010400 3. 所得税明细，科目默认2221050000 4. 收入明细，取开头为6001的科目 5. 其他科目明细，科目=6603020011、6702000010 | K3: 如果debit_credit_indicator=”S”，此字段取debit_amount_in_local_currency字段；如果debit_credit_indicator=”H”，此字段取credit_amount_in_local_currency字段*-1； | M3: 如果debit_credit_indicator=”S”，此字段取debit_amount_in_document_currency字段；如果debit_credit_indicator=”H”，此字段取credit_amount_in_document_currency字段*-1；

Sheet 累计项目税收明细表202512
J1: ='[113]累计项目税收明细表2017-202302'!G355 -> 1.1960885e+10 | K1: ='[113]累计项目税收明细表2017-202302'!H355 -> 1.1569549e+10 | L1: =SUBTOTAL(9,L8:L143) -> 4.42397e+08 | M1: =SUBTOTAL(9,M9:M143) -> 5.4813931e+08 | N1: =SUBTOTAL(9,N8:N143) -> 5.2125169e+08 | O1: =SUBTOTAL(9,O8:O143) -> 5.1244236e+08 | P1: =SUBTOTAL(9,P8:P143) -> 6.3590871e+08 | Q1: =SUBTOTAL(9,Q8:Q143) -> 5.4741284e+08 | R1: =SUBTOTAL(9,R8:R150) -> 3.0901827e+08 | S1: =SUBTOTAL(9,S8:S150) -> 3.4998131e+08 | T1: =SUBTOTAL(9,T8:T157) -> 5.5568377e+08 | U1: =SUBTOTAL(9,U8:U150) -> 5.1789361e+08 | V1: =SUBTOTAL(9,V8:V150) -> 6.7448332e+08 | W1: =SUBTOTAL(9,W8:W150) -> 5.424389e+08 | X1: =SUBTOTAL(9,X8:X150) -> 3.3679561e+08 | Y1: =SUBTOTAL(9,Y8:Y150) -> 4.5653185e+08
B2: 项目类型 | C2: 公司代码 或项目号 | D2: 项目名称 | E2: 类别 | F2: 税率 | G2: 累计收入 | H2: 累计开票 | I2: 未开票收入 | J2: 202403之前月度 收入额小计 | K2: 202403之前月度 开票额小计 | L2: 202403账面收入 | M2: 202403开票 | N2: 202404账面收入 | O2: 202404开票 | P2: 202405账面收入 | Q2: 202405开票 | R2: 202406账面收入 | S2: 202406开票 | T2: 202407账面收入 | U2: 202407开票 | V2: 202408账面收入 | W2: 202408开票 | X2: 202409账面收入 | Y2: 202409开票 | Z2: 202410账面收入 | AA2: 202410开票 | AB2: 202411账面收入 | AC2: 202411开票 | AD2: 202412账面收入 | AE2: 202412开票 | AF2: 202501账面收入 | AG2: 202501开票 | AH2: 202502账面收入 | AI2: 202502开票 | AJ2: 202503账面收入 | AK2: 202503开票 | AL2: 202504账面收入 | AM2: 202504开票 | AN2: 202505账面收入 | AO2: 202505开票 | AP2: 202506账面收入 | AQ2: 202506开票 | AR2: 202507账面收入 | AS2: 202507开票 | AT2: 202508预开票金额 | AU2: 202508账面收入 | AV2: 202508开票 | AW2: 202509账面收入 | AX2: 202509开票 | AY2: 202510账面收入 | AZ2: 202510开票 | BA2: 202510预开票 | BB2: 202510预开票冲回 | BC2: 202511账面收入 | BD2: 202511开票 | BE2: 202511预开票 | BF2: 202511预开票冲回 | BG2: 202512账面收入 | BH2: 202512开票 | BI2: 202512预开票 | BJ2: 202512预开票冲回
D3: 202403之前 各月度数据结转 | E3: 商品销售 | F3: 0.16 | G3: =SUM(J3,L3,N3,P3,R3,T3,V3,X3,Z3) -> 467927.48 | H3: =SUM(K3,M3,O3,Q3) -> 88819830 | I3: =G3-H3 -> -88351903 | J3: 467927.48 | K3: 88819830
E4: 工程施工 | F4: 0.1 | G4: =SUM(J4,L4,N4,P4,R4,T4,V4,X4,Z4) -> -1.2564439e+08 | H4: =SUM(K4,M4,O4,Q4) -> -47524533 | I4: =G4-H4 -> -78119852 | J4: -1.2564439e+08 | K4: -47524533
E5: 商品销售 | F5: 0.13 | G5: =SUM(J5,L5,N5,P5,R5,T5,V5,X5,Z5) -> 6.6085485e+09 | H5: =SUM(K5,M5,O5,Q5) -> 6.2670488e+09 | I5: =G5-H5 -> 3.414997e+08 | J5: 6.6085485e+09 | K5: 6.2670488e+09
E6: 工程施工 | F6: 0.09 | G6: =SUM(J6,L6,N6,P6,R6,T6,V6,X6,Z6) -> 5.0145477e+09 | H6: =SUM(K6,M6,O6,Q6) -> 4.892353e+09 | I6: =G6-H6 -> 1.221947e+08 | J6: 5.0145477e+09 | K6: 4.892353e+09
E7: 设计咨询 | F7: 0.06 | G7: =SUM(J7,L7,N7,P7,R7,T7,V7,X7,Z7) -> 4.6296552e+08 | H7: =SUM(K7,M7,O7,Q7) -> 3.6885177e+08 | I7: =G7-H7 -> 94113747 | J7: 4.6296552e+08 | K7: 3.6885177e+08 | Y7: 0
B8: EPC自建 | C8: 2346 | D8: 安徽宣城郎溪 | E8: 商品销售 | F8: 0.13 | G8: =SUM(J8,L8,N8,P8,R8,T8,V8,X8,Z8,AB8,AD8,AF8,AH8,AJ8,AL8,AN8,AP8,AR8,AU8,AW8,AY8,BC8,BG8) -> 32635696 | H8: =SUM(K8,M8,O8,Q8,S8,U8,W8,Y8,AA8,AC8,AE8,AG8,AI8,AK8,AM8,AO8,AQ8,AS8,AV8,AX8,AZ8,BD8,BH8) -> 37275653 | I8: =G8-H8 -> -4639956.4 | N8: 7575879.3 | O8: 11624470 | P8: 17461283 | Q8: 7575879.3 | R8: 2028030.5 | S8: 10476770 | T8: 184101.94 | V8: 5386401.3 | W8: 0 | X8: 0 | Y8: 0 | AJ8: 0 | AK8: 7598533.8
C9: 2346 | E9: 工程施工 | F9: 0.09 | G9: =SUM(J9,L9,N9,P9,R9,T9,V9,X9,Z9,AB9,AD9,AF9,AH9,AJ9,AL9,AN9,AP9,AR9,AU9,AW9,AY9,BC9,BG9) -> 9498435.8 | H9: =SUM(K9,M9,O9,Q9,S9,U9,W9,Y9,AA9,AC9,AE9,AG9,AI9,AK9,AM9,AO9,AQ9,AS9,AV9,AX9,AZ9,BD9,BH9) -> 19399126 | I9: =G9-H9 -> -9900690.2 | L9: 1044857.3 | N9: 2871503.7 | P9: 1423208.3 | Q9: 15363805 | R9: 2364082.2 | S9: 4035321.1 | T9: 1100229.4 | V9: 470183.49 | W9: 0 | X9: 224371.56 | Y9: 0
C10: 2346 | E10: 设计咨询 | F10: 0.06 | G10: =SUM(J10,L10,N10,P10,R10,T10,V10,X10,Z10,AB10,AD10,AF10,AH10,AJ10,AL10,AN10,AP10,AR10,AU10,AW10,AY10,BC10,BG10) -> 1587499.5 | H10: =SUM(K10,M10,O10,Q10,S10,U10,W10,Y10,AA10,AC10,AE10,AG10,AI10,AK10,AM10,AO10,AQ10,AS10,AV10,AX10,AZ10,BD10,BH10) -> 1604523.2 | I10: =G10-H10 -> -17023.79 | L10: 116896.06 | N10: 170311.43 | P10: 316972.4 | Q10: 1050616 | R10: 634803.18 | S10: 362041.83 | T10: 201873.22 | U10: 45222.28 | V10: 68316.87 | W10: 68316.87 | X10: 44486.8 | Y10: 44486.8 | Z10: 33839.49 | AA10: 33839.49
C11: 安新县阔达有色金属熔炼有限公司 | D11: 安徽宣城郎溪 | E11: 商品销售 | F11: 0.13 | G11: =SUM(J11,L11,N11,P11,R11,T11,V11,X11,Z11,AB11,AD11,AF11,AH11,AJ11,AL11,AN11,AP11,AR11,AU11,AW11,AY11,BC11,BG11) -> 0 | H11: =SUM(K11,M11,O11,Q11,S11,U11,W11,Y11,AA11,AC11,AE11,AG11,AI11,AK11,AM11,AO11,AQ11,AS11,AV11,AX11,AZ11,BD11,BH11) -> 81415.93 | BH11: 81415.93
E12: 工程施工 | F12: 0.09 | G12: =SUM(J12,L12,N12,P12,R12,T12,V12,X12,Z12,AB12,AD12,AF12,AH12,AJ12,AL12,AN12,AP12,AR12,AU12,AW12,AY12,BC12,BG12) -> 0 | H12: =SUM(K12,M12,O12,Q12,S12,U12,W12,Y12,AA12,AC12,AE12,AG12,AI12,AK12,AM12,AO12,AQ12,AS12,AV12,AX12,AZ12,BD12,BH12) -> 0
E13: 设计咨询 | F13: 0.06 | G13: =SUM(J13,L13,N13,P13,R13,T13,V13,X13,Z13,AB13,AD13,AF13,AH13,AJ13,AL13,AN13,AP13,AR13,AU13,AW13,AY13,BC13,BG13) -> 0 | H13: =SUM(K13,M13,O13,Q13,S13,U13,W13,Y13,AA13,AC13,AE13,AG13,AI13,AK13,AM13,AO13,AQ13,AS13,AV13,AX13,AZ13,BD13,BH13) -> 0
B14: EPC自建 | C14: 3660 | D14: 巴彦淖尔 | E14: 商品销售 | F14: 0.13 | G14: =SUM(J14,L14,N14,P14,R14,T14,V14,X14,Z14,AB14,AD14,AF14,AH14,AJ14,AL14,AN14,AP14,AR14,AU14,AW14,AY14,BC14,BG14) -> 8211701.3 | H14: =SUM(K14,M14,O14,Q14,S14,U14,W14,Y14,AA14,AC14,AE14,AG14,AI14,AK14,AM14,AO14,AQ14,AS14,AV14,AX14,AZ14,BD14,BH14) -> 11336364 | I14: =G14-H14 -> -3124662.7 | L14: 8130064.1 | M14: 3124662.6 | N14: 81637.17 | V14: 0 | W14: 0 | X14: 0 | Y14: 8211701.4
C15: 3660 | E15: 工程施工 | F15: 0.09 | G15: =SUM(J15,L15,N15,P15,R15,T15,V15,X15,Z15,AB15,AD15,AF15,AH15,AJ15,AL15,AN15,AP15,AR15,AU15,AW15,AY15,BC15,BG15) -> 4.6214846e+08 | H15: =SUM(K15,M15,O15,Q15,S15,U15,W15,Y15,AA15,AC15,AE15,AG15,AI15,AK15,AM15,AO15,AQ15,AS15,AV15,AX15,AZ15,BD15,BH15) -> 4.6214846e+08 | I15: =G15-H15 -> -0.029999912 | L15: 1.8904657e+08 | M15: 1.8348624e+08 | N15: 2.2018349e+08 | O15: 2.2018349e+08 | P15: 1.9266055e+08 | Q15: 1.9266055e+08 | U15: 3981328.1 | V15: 1239039.6 | W15: 0 | X15: 0 | Y15: 2818045.8 | AD15: -1.4098119e+08 | AE15: 0 | AI15: -1.4098119e+08
C16: 3660 | E16: 设计咨询 | F16: 0.06 | G16: =SUM(J16,L16,N16,P16,R16,T16,V16,X16,Z16,AB16,AD16,AF16,AH16,AJ16,AL16,AN16,AP16,AR16,AU16,AW16,AY16,BC16,BG16) -> 5519384.1 | H16: =SUM(K16,M16,O16,Q16,S16,U16,W16,Y16,AA16,AC16,AE16,AG16,AI16,AK16,AM16,AO16,AQ16,AS16,AV16,AX16,AZ16,BD16,BH16) -> 6976051.5 | I16: =G16-H16 -> -1456667.3 | L16: 5238515.3 | M16: 1456667.3 | N16: -81637.17 | T16: 212735.85 | U16: 4216037.7 | V16: 52152 | W16: 0 | X16: 0 | Y16: 1205728.3 | AD16: 97618.11 | AE16: 97618.11
B17: EPC自建 | C17: 4030 | D17: 定边白兴庄 | E17: 商品销售 | F17: 0.13 | G17: =SUM(J17,L17,N17,P17,R17,T17,V17,X17,Z17,AB17,AD17,AF17,AH17,AJ17,AL17,AN17,AP17,AR17,AU17,AW17,AY17,BC17,BG17) -> 2.0329258e+08 | H17: =SUM(K17,M17,O17,Q17,S17,U17,W17,Y17,AA17,AC17,AE17,AG17,AI17,AK17,AM17,AO17,AQ17,AS17,AV17,AX17,AZ17,BD17,BH17) -> 1.1134199e+08 | I17: =G17-H17 -> 91950591 | N17: 3664601.8 | P17: 222234.5 | R17: 18651916 | S17: 0 | T17: 53556348 | V17: 14543776 | W17: 0 | X17: -9581572.7 | Y17: 8347326.5 | Z17: 32102530 | AA17: 11020813 | AB17: 90132743 | AC17: 91973846
C18: 4030 | E18: 工程施工 | F18: 0.09 | G18: =SUM(J18,L18,N18,P18,R18,T18,V18,X18,Z18,AB18,AD18,AF18,AH18,AJ18,AL18,AN18,AP18,AR18,AU18,AW18,AY18,BC18,BG18) -> 2.1309161e+08 | H18: =SUM(K18,M18,O18,Q18,S18,U18,W18,Y18,AA18,AC18,AE18,AG18,AI18,AK18,AM18,AO18,AQ18,AS18,AV18,AX18,AZ18,BD18,BH18) -> 1.8890447e+08 | I18: =G18-H18 -> 24187141 | L18: 489233.5 | N18: 9211423.6 | O18: 45871560 | P18: 10406006 | R18: 14196013 | S18: 0 | T18: 12344910 | V18: 9578080.4 | W18: 0 | X18: 15013767 | Y18: 18679332 | Z18: 37165437 | AA18: 9429091.5 | AB18: 53132537 | AC18: 63370283 | AD18: 51554199 | AE18: 51554199
C19: 4030 | E19: 设计咨询 | F19: 0.06 | G19: =SUM(J19,L19,N19,P19,R19,T19,V19,X19,Z19,AB19,AD19,AF19,AH19,AJ19,AL19,AN19,AP19,AR19,AU19,AW19,AY19,BC19,BG19) -> 8329405.3 | H19: =SUM(K19,M19,O19,Q19,S19,U19,W19,Y19,AA19,AC19,AE19,AG19,AI19,AK19,AM19,AO19,AQ19,AS19,AV19,AX19,AZ19,BD19,BH19) -> 7940431.8 | I19: =G19-H19 -> 388973.51 | L19: 43891.61 | N19: 685280.75 | P19: 64486.14 | R19: 156301.33 | S19: 60092.57 | T19: 3078319.5 | U19: 60296.37 | V19: =563843.01+91089.15 -> 654932.16 | W19: 91089.15 | X19: 165683.66 | Y19: 4427586 | Z19: 3031830.8 | AA19: 474936.19 | AB19: 448679.26 | AC19: 2826431.5
B20: EPC自建 | C20: 4020 | D20: 定边王家梁 | E20: 商品销售 | F20: 0.13 | G20: =SUM(J20,L20,N20,P20,R20,T20,V20,X20,Z20,AB20,AD20,AF20,AH20,AJ20,AL20,AN20,AP20,AR20,AU20,AW20,AY20,BC20,BG20) -> 1.0538136e+08 | H20: =SUM(K20,M20,O20,Q20,S20,U20,W20,Y20,AA20,AC20,AE20,AG20,AI20,AK20,AM20,AO20,AQ20,AS20,AV20,AX20,AZ20,BD20,BH20) -> 1.0767405e+08 | I20: =G20-H20 -> -2292690.1 | M20: 2292690 | N20: 10422345 | R20: 660150.8 | S20: 0 | T20: 27073953 | V20: 3545901.1 | W20: 13168633 | X20: 11705115 | Y20: 3422302.7 | Z20: 51973899 | AA20: 36816530 | AI20: 51973899
C21: 4020 | E21: 工程施工 | F21: 0.09 | G21: =SUM(J21,L21,N21,P21,R21,T21,V21,X21,Z21,AB21,AD21,AF21,AH21,AJ21,AL21,AN21,AP21,AR21,AU21,AW21,AY21,BC21,BG21) -> 2.9721338e+08 | H21: =SUM(K21,M21,O21,Q21,S21,U21,W21,Y21,AA21,AC21,AE21,AG21,AI21,AK21,AM21,AO21,AQ21,AS21,AV21,AX21,AZ21,BD21,BH21) -> 3.2681651e+08 | I21: =G21-H21 -> -29603135 | L21: 5244190.5 | M21: 29823783 | N21: 13660419 | O21: 1.6430483e+08 | P21: 27909442 | R21: 19309601 | S21: 0 | T21: 12545273 | V21: 7283802.8 | W21: 73424735 | X21: 8064138.7 | Y21: 2271099.1 | Z21: 2.0319651e+08 | AA21: 47672842 | AE21: 9319218.1
C22: 4020 | E22: 设计咨询 | F22: 0.06 | G22: =SUM(J22,L22,N22,P22,R22,T22,V22,X22,Z22,AB22,AD22,AF22,AH22,AJ22,AL22,AN22,AP22,AR22,AU22,AW22,AY22,BC22,BG22) -> 15200557 | H22: =SUM(K22,M22,O22,Q22,S22,U22,W22,Y22,AA22,AC22,AE22,AG22,AI22,AK22,AM22,AO22,AQ22,AS22,AV22,AX22,AZ22,BD22,BH22) -> 29092126 | I22: =G22-H22 -> -13891569 | L22: 387382.3 | M22: 6720925.1 | N22: 1991865.6 | O22: 614275.5 | P22: 1033444.8 | R22: 605451.16 | S22: 60092.57 | T22: 3642158.9 | U22: 60296.37 | V22: =451080.26+91089.15 -> 542169.41 | W22: 14187371 | X22: 453844.04 | Y22: 510396 | Z22: 5695184.2 | AA22: 394528.3 | AD22: 849056.6 | AE22: 5695184.2 | AG22: 849056.6
B23: EPC自建 | C23: 2319 | D23: 定远乘风 | E23: 商品销售 | F23: 0.13 | G23: =SUM(J23,L23,N23,P23,R23,T23,V23,X23,Z23,AB23,AD23,AF23,AH23,AJ23,AL23,AN23,AP23,AR23,AU23,AW23,AY23,BC23,BG23) -> 1.2192612e+08 | H23: =SUM(K23,M23,O23,Q23,S23,U23,W23,Y23,AA23,AC23,AE23,AG23,AI23,AK23,AM23,AO23,AQ23,AS23,AV23,AX23,AZ23,BD23,BH23) -> 1.4448884e+08 | I23: =G23-H23 -> -22562720 | L23: 3184412.9 | P23: 3053970.6 | R23: 1591338.1 | S23: 0 | T23: 28616.54 | U23: 30132373 | V23: 22396948 | W23: 0 | X23: 23544881 | Y23: 0 | Z23: 68125955 | AA23: 54847.11 | AC23: 1.1404155e+08 | AD23: 0 | AE23: 260067.96
C24: 2319 | E24: 工程施工 | F24: 0.09 | G24: =SUM(J24,L24,N24,P24,R24,T24,V24,X24,Z24,AB24,AD24,AF24,AH24,AJ24,AL24,AN24,AP24,AR24,AU24,AW24,AY24,BC24,BG24) -> 4.0298493e+08 | H24: =SUM(K24,M24,O24,Q24,S24,U24,W24,Y24,AA24,AC24,AE24,AG24,AI24,AK24,AM24,AO24,AQ24,AS24,AV24,AX24,AZ24,BD24,BH24) -> 4.7599102e+08 | I24: =G24-H24 -> -73006093 | L24: -493692.65 | N24: 11024685 | P24: 9616720.9 | R24: 15488844 | S24: 0 | T24: 5873943.7 | U24: 1.0864265e+08 | V24: 8786601.5 | W24: 0 | X24: 15887463 | Y24: 0 | Z24: 43577732 | AB24: 2.9396666e+08 | AC24: 74125740 | AD24: -744034.87 | AE24: 2.9322263e+08
C25: 2319 | E25: 设计咨询 | F25: 0.06 | G25: =SUM(J25,L25,N25,P25,R25,T25,V25,X25,Z25,AB25,AD25,AF25,AH25,AJ25,AL25,AN25,AP25,AR25,AU25,AW25,AY25,BC25,BG25) -> 12445292 | H25: =SUM(K25,M25,O25,Q25,S25,U25,W25,Y25,AA25,AC25,AE25,AG25,AI25,AK25,AM25,AO25,AQ25,AS25,AV25,AX25,AZ25,BD25,BH25) -> 25072324 | I25: =G25-H25 -> -12627032 | P25: 572632.47 | R25: 1198794.8 | S25: 60092.57 | T25: 1933105.9 | U25: 15442087 | V25: =2056169.38+91089.15 -> 2147258.5 | W25: -1053820.4 | X25: 1316111 | Y25: 59315.74 | Z25: 5207673.3 | AC25: 10494933 | AF25: 69716.4 | AG25: 69716.4
B26: EPC自建 | C26: 2318 | D26: 定远欣月 | E26: 商品销售 | F26: 0.13 | G26: =SUM(J26,L26,N26,P26,R26,T26,V26,X26,Z26,AB26,AD26,AF26,AH26,AJ26,AL26,AN26,AP26,AR26,AU26,AW26,AY26,BC26,BG26) -> 91048578 | H26: =SUM(K26,M26,O26,Q26,S26,U26,W26,Y26,AA26,AC26,AE26,AG26,AI26,AK26,AM26,AO26,AQ26,AS26,AV26,AX26,AZ26,BD26,BH26) -> 94539002 | I26: =G26-H26 -> -3490424.3 | P26: 18248654 | R26: 14223009 | S26: 0 | T26: 24448246 | U26: 35962087 | V26: 6740165.1 | W26: 0 | X26: -3136198 | Y26: 0 | Z26: 30470275 | AB26: 54427.05 | AC26: 58576915
C27: 2318 | E27: 工程施工 | F27: 0.09 | G27: =SUM(J27,L27,N27,P27,R27,T27,V27,X27,Z27,AB27,AD27,AF27,AH27,AJ27,AL27,AN27,AP27,AR27,AU27,AW27,AY27,BC27,BG27) -> 2.385241e+08 | H27: =SUM(K27,M27,O27,Q27,S27,U27,W27,Y27,AA27,AC27,AE27,AG27,AI27,AK27,AM27,AO27,AQ27,AS27,AV27,AX27,AZ27,BD27,BH27) -> 2.7753196e+08 | I27: =G27-H27 -> -39007863 | L27: -634747.7 | N27: 4893183.6 | P27: 1363532.1 | R27: 7882465.7 | S27: 0 | T27: 3424803.4 | U27: 52512297 | V27: 3477768.1 | W27: 0 | X27: -545268.65 | Y27: 0 | Z27: 17266715 | AB27: 1.5728736e+08 | AC27: 1.8091138e+08 | AD27: 44108287 | AE27: 44108287
C28: 2318 | E28: 设计咨询 | F28: 0.06 | G28: =SUM(J28,L28,N28,P28,R28,T28,V28,X28,Z28,AB28,AD28,AF28,AH28,AJ28,AL28,AN28,AP28,AR28,AU28,AW28,AY28,BC28,BG28) -> 9887422.4 | H28: =SUM(K28,M28,O28,Q28,S28,U28,W28,Y28,AA28,AC28,AE28,AG28,AI28,AK28,AM28,AO28,AQ28,AS28,AV28,AX28,AZ28,BD28,BH28) -> 22107136 | I28: =G28-H28 -> -12219713 | L28: 625546.26 | N28: 721744.48 | P28: 1109241.8 | R28: 848738.92 | S28: 45069.41 | T28: 1125155.6 | U28: 16630790 | V28: =1480911.13+68316.91 -> 1549228 | W28: -935850.35 | X28: 281836.92 | Y28: 44486.75 | Z28: 3625930.4 | AC28: 6322639.7
B29: EPC自建 | C29: 2A50 | D29: 定远独立储能 | E29: 商品销售 | F29: 0.13 | G29: =SUM(J29,L29,N29,P29,R29,T29,V29,X29,Z29,AB29,AD29,AF29,AH29,AJ29,AL29,AN29,AP29,AR29,AU29,AW29,AY29,BC29,BG29) -> 0 | H29: =SUM(K29,M29,O29,Q29,S29,U29,W29,Y29,AA29,AC29,AE29,AG29,AI29,AK29,AM29,AO29,AQ29,AS29,AV29,AX29,AZ29,BD29,BH29) -> 9836350.8 | I29: =G29-H29 -> -9836350.8 | V29: 0 | W29: 0 | X29: 0 | Y29: 0 | Z29: 117923.07 | AH29: -117923.07 | AJ29: 0 | AK29: 9836350.8
C30: 2A50 | E30: 工程施工 | F30: 0.09 | G30: =SUM(J30,L30,N30,P30,R30,T30,V30,X30,Z30,AB30,AD30,AF30,AH30,AJ30,AL30,AN30,AP30,AR30,AU30,AW30,AY30,BC30,BG30) -> 2073641.8 | H30: =SUM(K30,M30,O30,Q30,S30,U30,W30,Y30,AA30,AC30,AE30,AG30,AI30,AK30,AM30,AO30,AQ30,AS30,AV30,AX30,AZ30,BD30,BH30) -> 30988092 | I30: =G30-H30 -> -28914451 | V30: 0 | W30: 0 | X30: 0 | Y30: 0 | Z30: 2073641.8 | AI30: 30988092
C31: 2A50 | E31: 设计咨询 | F31: 0.06 | G31: =SUM(J31,L31,N31,P31,R31,T31,V31,X31,Z31,AB31,AD31,AF31,AH31,AJ31,AL31,AN31,AP31,AR31,AU31,AW31,AY31,BC31,BG31) -> 1726122.2 | H31: =SUM(K31,M31,O31,Q31,S31,U31,W31,Y31,AA31,AC31,AE31,AG31,AI31,AK31,AM31,AO31,AQ31,AS31,AV31,AX31,AZ31,BD31,BH31) -> 8077291.4 | I31: =G31-H31 -> -6351169.2 | L31: 1262584.2 | N31: 112007.19 | Q31: 7725760.7 | U31: 0 | V31: 0 | W31: 0 | X31: 0 | Y31: 0 | Z31: 351530.75 | AJ31: 0 | AK31: 351530.74
B32: EPC自建 | C32: 1080 | D32: 丰宁 | E32: 商品销售 | F32: 0.13 | G32: =SUM(J32,L32,N32,P32,R32,T32,V32,X32,Z32,AB32,AD32,AF32,AH32,AJ32,AL32,AN32,AP32,AR32,AU32,AW32,AY32,BC32,BG32) -> 0 | H32: =SUM(K32,M32,O32,Q32,S32,U32,W32,Y32,AA32,AC32,AE32,AG32,AI32,AK32,AM32,AO32,AQ32,AS32,AV32,AX32,AZ32,BD32,BH32) -> 0 | I32: =G32-H32 -> 0
C33: 1080 | E33: 工程施工 | F33: 0.09 | G33: =SUM(J33,L33,N33,P33,R33,T33,V33,X33,Z33,AB33,AD33,AF33,AH33,AJ33,AL33,AN33,AP33,AR33,AU33,AW33,AY33,BC33,BG33) -> 0 | H33: =SUM(K33,M33,O33,Q33,S33,U33,W33,Y33,AA33,AC33,AE33,AG33,AI33,AK33,AM33,AO33,AQ33,AS33,AV33,AX33,AZ33,BD33,BH33) -> 379237.83 | I33: =G33-H33 -> -379237.83 | AI33: 379237.83
C34: 1080 | E34: 设计咨询 | F34: 0.06 | G34: =SUM(J34,L34,N34,P34,R34,T34,V34,X34,Z34,AB34,AD34,AF34,AH34,AJ34,AL34,AN34,AP34,AR34,AU34,AW34,AY34,BC34,BG34) -> 0 | H34: =SUM(K34,M34,O34,Q34,S34,U34,W34,Y34,AA34,AC34,AE34,AG34,AI34,AK34,AM34,AO34,AQ34,AS34,AV34,AX34,AZ34,BD34,BH34) -> 475794.07 | I34: =G34-H34 -> -475794.07 | AI34: 475794.07
B35: EPC自建 | C35: 1080 | D35: 丰宁二期 | E35: 商品销售 | F35: 0.13 | G35: =SUM(J35,L35,N35,P35,R35,T35,V35,X35,Z35,AB35,AD35,AF35,AH35,AJ35,AL35,AN35,AP35,AR35,AU35,AW35,AY35,BC35,BG35) -> 2.1818304e+08 | H35: =SUM(K35,M35,O35,Q35,S35,U35,W35,Y35,AA35,AC35,AE35,AG35,AI35,AK35,AM35,AO35,AQ35,AS35,AV35,AX35,AZ35,BD35,BH35) -> 2.0772881e+08 | I35: =G35-H35 -> 10454224 | N35: 22944611 | P35: 9632042.6 | Q35: 21162439 | R35: 35911880 | S35: 11414215 | T35: 10896695 | V35: 1.0628981e+08 | W35: 36354351 | X35: 4407911.8 | Y35: 83150389 | Z35: 28100089 | AA35: 27533528 | AE35: 4012784.8 | AI35: 24101106
C36: 1080 | E36: 工程施工 | F36: 0.09 | G36: =SUM(J36,L36,N36,P36,R36,T36,V36,X36,Z36,AB36,AD36,AF36,AH36,AJ36,AL36,AN36,AP36,AR36,AU36,AW36,AY36,BC36,BG36) -> 1.1833155e+09 | H36: =SUM(K36,M36,O36,Q36,S36,U36,W36,Y36,AA36,AC36,AE36,AG36,AI36,AK36,AM36,AO36,AQ36,AS36,AV36,AX36,AZ36,BD36,BH36) -> 1.0976805e+09 | I36: =G36-H36 -> 85635052 | L36: 2011104.1 | N36: 16149385 | P36: 24831319 | R36: 29735687 | S36: 49099875 | T36: 1.5868586e+08 | U36: 1.3761468e+08 | V36: 1.7189511e+08 | W36: 2.0677017e+08 | X36: 1.1730584e+08 | Y36: 1.2733723e+08 | Z36: 75373568 | AA36: 28836197 | AD36: 5.8732768e+08 | AE36: 1.4418091e+08 | AG36: 2.7522936e+08 | AI36: 1.2861208e+08 | AN36: -91743119 | AP36: 91743119
C37: 1080 | E37: 设计咨询 | F37: 0.06 | G37: =SUM(J37,L37,N37,P37,R37,T37,V37,X37,Z37,AB37,AD37,AF37,AH37,AJ37,AL37,AN37,AP37,AR37,AU37,AW37,AY37,BC37,BG37) -> 20771259 | H37: =SUM(K37,M37,O37,Q37,S37,U37,W37,Y37,AA37,AC37,AE37,AG37,AI37,AK37,AM37,AO37,AQ37,AS37,AV37,AX37,AZ37,BD37,BH37) -> 22230481 | I37: =G37-H37 -> -1459221.8 | L37: 439078.6 | N37: 1226790.2 | P37: -113038.25 | Q37: 2831283.8 | R37: 60092.57 | S37: 60092.57 | T37: 472894.22 | U37: 60296.37 | V37: =7294630.9+91089.15 -> 7385720.1 | W37: 684455.55 | X37: 2150705.6 | Y37: 7353946.6 | Z37: 9149015.7 | AA37: 2091389.9 | AE37: 9149015.7
B38: EPC自建 | C38: 1080 | D38: 丰宁三期 | E38: 商品销售 | F38: 0.13 | G38: =SUM(J38,L38,N38,P38,R38,T38,V38,X38,Z38,AB38,AD38,AF38,AH38,AJ38,AL38,AN38,AP38,AR38,AU38,AW38,AY38,BC38,BG38) -> 1.3184584e+08 | H38: =SUM(K38,M38,O38,Q38,S38,U38,W38,Y38,AA38,AC38,AE38,AG38,AI38,AK38,AM38,AO38,AQ38,AS38,AV38,AX38,AZ38,BD38,BH38) -> 1.4230007e+08 | I38: =G38-H38 -> -10454224 | N38: 11498521 | P38: 7347191.1 | Q38: 11498521 | R38: 6781679.1 | S38: 7347191.1 | T38: 0.02 | V38: 80139398 | W38: 17235903 | X38: 4038990.7 | Y38: 0 | Z38: 22040064 | AA38: 84178389 | AE38: 15258591 | AI38: 6781472.8
C39: 1080 | E39: 工程施工 | F39: 0.09 | G39: =SUM(J39,L39,N39,P39,R39,T39,V39,X39,Z39,AB39,AD39,AF39,AH39,AJ39,AL39,AN39,AP39,AR39,AU39,AW39,AY39,BC39,BG39) -> 4.5751058e+08 | H39: =SUM(K39,M39,O39,Q39,S39,U39,W39,Y39,AA39,AC39,AE39,AG39,AI39,AK39,AM39,AO39,AQ39,AS39,AV39,AX39,AZ39,BD39,BH39) -> 4.5996331e+08 | I39: =G39-H39 -> -2452735.4 | L39: 498586.12 | N39: 5439135.9 | P39: 15436790 | R39: 23070803 | S39: 23827247 | T39: 27932492 | V39: 33910823 | W39: 51003294 | X39: 24149722 | Y39: 21902159 | Z39: 25856795 | AA39: 36158386 | AD39: 3.0121543e+08 | AE39: 3.2707223e+08
C40: 1080 | E40: 设计咨询 | F40: 0.06 | G40: =SUM(J40,L40,N40,P40,R40,T40,V40,X40,Z40,AB40,AD40,AF40,AH40,AJ40,AL40,AN40,AP40,AR40,AU40,AW40,AY40,BC40,BG40) -> 16797953 | H40: =SUM(K40,M40,O40,Q40,S40,U40,W40,Y40,AA40,AC40,AE40,AG40,AI40,AK40,AM40,AO40,AQ40,AS40,AV40,AX40,AZ40,BD40,BH40) -> 19963111 | I40: =G40-H40 -> -3165158.3 | L40: 404945.11 | N40: 887361.61 | P40: -78904.76 | Q40: 4197791.7 | R40: 60092.57 | S40: 60092.57 | T40: 652067.3 | U40: 60296.37 | V40: =5996293.68+91089.15 -> 6087382.8 | W40: 863628.63 | X40: 1635477.4 | Y40: 59315.74 | Z40: 7149530.6 | AA40: 7572455.4 | AE40: 7149530.6
B41: EPC自建 | C41: 2316 | D41: 广西融水 | E41: 商品销售 | F41: 0.13 | G41: =SUM(J41,L41,N41,P41,R41,T41,V41,X41,Z41,AB41,AD41,AF41,AH41,AJ41,AL41,AN41,AP41,AR41,AU41,AW41,AY41,BC41,BG41) -> 3526106.2 | H41: =SUM(K41,M41,O41,Q41,S41,U41,W41,Y41,AA41,AC41,AE41,AG41,AI41,AK41,AM41,AO41,AQ41,AS41,AV41,AX41,AZ41,BD41,BH41) -> 3526106.2 | I41: =G41-H41 -> 0 | V41: 0 | W41: 0 | X41: 0 | Y41: 0 | AD41: 3526106.2 | AK41: 3526106.2
C42: 2316 | E42: 工程施工 | F42: 0.09 | G42: =SUM(J42,L42,N42,P42,R42,T42,V42,X42,Z42,AB42,AD42,AF42,AH42,AJ42,AL42,AN42,AP42,AR42,AU42,AW42,AY42,BC42,BG42) -> 0 | H42: =SUM(K42,M42,O42,Q42,S42,U42,W42,Y42,AA42,AC42,AE42,AG42,AI42,AK42,AM42,AO42,AQ42,AS42,AV42,AX42,AZ42,BD42,BH42) -> 0 | I42: =G42-H42 -> 0 | V42: 0 | W42: 0 | X42: 0 | Y42: 0
C43: 2316 | E43: 设计咨询 | F43: 0.06 | G43: =SUM(J43,L43,N43,P43,R43,T43,V43,X43,Z43,AB43,AD43,AF43,AH43,AJ43,AL43,AN43,AP43,AR43,AU43,AW43,AY43,BC43,BG43) -> 3187758.4 | H43: =SUM(K43,M43,O43,Q43,S43,U43,W43,Y43,AA43,AC43,AE43,AG43,AI43,AK43,AM43,AO43,AQ43,AS43,AV43,AX43,AZ43,BD43,BH43) -> 10589330 | I43: =G43-H43 -> -7401571.8 | L43: =-6425985.71+6471185.29 -> 45199.58 | M43: 6439798.6 | N43: 54164.39 | P43: 832458.31 | Q43: 1061137.2 | R43: 313557.91 | S43: 60092.57 | T43: 60296.37 | U43: 110522.47 | V43: =119624.91+91089.15 -> 210714.06 | W43: 91089.15 | X43: 753655.36 | Y43: 59315.74 | Z43: 45119.28 | AA43: 45119.28 | AB43: 95097.08 | AC43: 95097.08 | AD43: 71287.13 | AG43: 1849662.1 | AK43: 71287.13 | AP43: 284905.66 | AQ43: 284905.66 | AR43: 201165.05 | AS43: 201165.05 | AW43: 220138.24 | AZ43: 220138.24
B44: EPC自建 | C44: 2026 | D44: 河南濮阳台前 | E44: 商品销售 | F44: 0.13 | G44: =SUM(J44,L44,N44,P44,R44,T44,V44,X44,Z44,AB44,AD44,AF44,AH44,AJ44,AL44,AN44,AP44,AR44,AU44,AW44,AY44,BC44,BG44) -> 0 | H44: =SUM(K44,M44,O44,Q44,S44,U44,W44,Y44,AA44,AC44,AE44,AG44,AI44,AK44,AM44,AO44,AQ44,AS44,AV44,AX44,AZ44,BD44,BH44) -> 31750113 | I44: =G44-H44 -> -31750113 | M44: 31750113 | V44: 0 | W44: 0 | X44: 0 | Y44: 0
C45: 2026 | E45: 工程施工 | F45: 0.09 | G45: =SUM(J45,L45,N45,P45,R45,T45,V45,X45,Z45,AB45,AD45,AF45,AH45,AJ45,AL45,AN45,AP45,AR45,AU45,AW45,AY45,BC45,BG45) -> 0 | H45: =SUM(K45,M45,O45,Q45,S45,U45,W45,Y45,AA45,AC45,AE45,AG45,AI45,AK45,AM45,AO45,AQ45,AS45,AV45,AX45,AZ45,BD45,BH45) -> 33171636 | I45: =G45-H45 -> -33171636 | M45: 33171636 | V45: 0 | W45: 0 | X45: 0 | Y45: 0
C46: 2026 | E46: 设计咨询 | F46: 0.06 | G46: =SUM(J46,L46,N46,P46,R46,T46,V46,X46,Z46,AB46,AD46,AF46,AH46,AJ46,AL46,AN46,AP46,AR46,AU46,AW46,AY46,BC46,BG46) -> 235849.06 | H46: =SUM(K46,M46,O46,Q46,S46,U46,W46,Y46,AA46,AC46,AE46,AG46,AI46,AK46,AM46,AO46,AQ46,AS46,AV46,AX46,AZ46,BD46,BH46) -> 4299687 | I46: =G46-H46 -> -4063837.9 | L46: 235849.06 | M46: 4299687 | V46: 0 | W46: 0 | X46: 0 | Y46: 0
B47: EPC自建 | C47: 3314 | D47: 江西高安 | E47: 商品销售 | F47: 0.13 | G47: =SUM(J47,L47,N47,P47,R47,T47,V47,X47,Z47,AB47,AD47,AF47,AH47,AJ47,AL47,AN47,AP47,AR47,AU47,AW47,AY47,BC47,BG47) -> 70891363 | H47: =SUM(K47,M47,O47,Q47,S47,U47,W47,Y47,AA47,AC47,AE47,AG47,AI47,AK47,AM47,AO47,AQ47,AS47,AV47,AX47,AZ47,BD47,BH47) -> 91744119 | I47: =G47-H47 -> -20852756 | L47: 12608407 | N47: 13606195 | P47: 13606195 | Q47: 47067357 | R47: 13661517 | S47: 13606195 | T47: 6803097.3 | V47: 3473441.9 | W47: 20464615 | X47: 1224583.2 | Y47: 0 | Z47: 5907926.6 | AA47: 4337007.4 | AJ47: 0 | AK47: 6268944.3
C48: 3314 | E48: 工程施工 | F48: 0.09 | G48: =SUM(J48,L48,N48,P48,R48,T48,V48,X48,Z48,AB48,AD48,AF48,AH48,AJ48,AL48,AN48,AP48,AR48,AU48,AW48,AY48,BC48,BG48) -> 1.0104876e+08 | H48: =SUM(K48,M48,O48,Q48,S48,U48,W48,Y48,AA48,AC48,AE48,AG48,AI48,AK48,AM48,AO48,AQ48,AS48,AV48,AX48,AZ48,BD48,BH48) -> 1.5990496e+08 | I48: =G48-H48 -> -58856195 | L48: 2430176.7 | N48: 4192187.1 | P48: 2922190.4 | R48: 7321918.8 | S48: 68400749 | T48: 4366907.6 | V48: 3350080.6 | W48: 11688826 | X48: 3602505 | Y48: 2521858.6 | Z48: 12889061 | AA48: 4430727.1 | AJ48: 0 | AK48: 12889061 | AL48: 59973737 | AM48: 59973737 | AR48: -0.01
C49: 3314 | E49: 设计咨询 | F49: 0.06 | G49: =SUM(J49,L49,N49,P49,R49,T49,V49,X49,Z49,AB49,AD49,AF49,AH49,AJ49,AL49,AN49,AP49,AR49,AU49,AW49,AY49,BC49,BG49) -> 14007096 | H49: =SUM(K49,M49,O49,Q49,S49,U49,W49,Y49,AA49,AC49,AE49,AG49,AI49,AK49,AM49,AO49,AQ49,AS49,AV49,AX49,AZ49,BD49,BH49) -> 16122173 | I49: =G49-H49 -> -2115077.3 | L49: 358897.98 | N49: 560269.57 | P49: 271800.08 | Q49: 2979681.3 | R49: 175308.31 | S49: 279199.94 | T49: 738198.42 | U49: 137455.33 | V49: =2418745.68+68316.87 -> 2487062.6 | W49: =823215.02+68316.87 -> 891531.89 | X49: 141236.73 | Y49: 0 | Z49: 9274322.3 | AA49: 2559982.4 | AJ49: 0 | AK49: 9274322.3
B50: EPC自建 | C50: 2016 | D50: 内蒙察右后旗项目二 | E50: 商品销售 | F50: 0.13 | G50: =SUM(J50,L50,N50,P50,R50,T50,V50,X50,Z50,AB50,AD50,AF50,AH50,AJ50,AL50,AN50,AP50,AR50,AU50,AW50,AY50,BC50,BG50) -> 19584963 | H50: =SUM(K50,M50,O50,Q50,S50,U50,W50,Y50,AA50,AC50,AE50,AG50,AI50,AK50,AM50,AO50,AQ50,AS50,AV50,AX50,AZ50,BD50,BH50) -> 19584963 | I50: =G50-H50 -> 0 | P50: 19584963 | R50: 0 | S50: 19584963 | V50: 0 | W50: 0 | X50: 0 | Y50: 0
C51: 2016 | E51: 工程施工 | F51: 0.09 | G51: =SUM(J51,L51,N51,P51,R51,T51,V51,X51,Z51,AB51,AD51,AF51,AH51,AJ51,AL51,AN51,AP51,AR51,AU51,AW51,AY51,BC51,BG51) -> 3991345.2 | H51: =SUM(K51,M51,O51,Q51,S51,U51,W51,Y51,AA51,AC51,AE51,AG51,AI51,AK51,AM51,AO51,AQ51,AS51,AV51,AX51,AZ51,BD51,BH51) -> 5446187.1 | I51: =G51-H51 -> -1454841.9 | R51: 0 | S51: 1454841.9 | V51: 0 | W51: 0 | X51: 0 | Y51: 0 | Z51: 3991345.2 | AC51: 3991345.2 | AR51: 0.01
C52: 2016 | E52: 设计咨询 | F52: 0.06 | G52: =SUM(J52,L52,N52,P52,R52,T52,V52,X52,Z52,AB52,AD52,AF52,AH52,AJ52,AL52,AN52,AP52,AR52,AU52,AW52,AY52,BC52,BG52) -> 4027205.7 | H52: =SUM(K52,M52,O52,Q52,S52,U52,W52,Y52,AA52,AC52,AE52,AG52,AI52,AK52,AM52,AO52,AQ52,AS52,AV52,AX52,AZ52,BD52,BH52) -> 3314881.9 | I52: =G52-H52 -> 712323.84 | L52: 20225.69 | N52: 89988.01 | P52: 18834.8 | Q52: 1207772.6 | R52: 22534.72 | S52: 22534.72 | T52: 22611.14 | U52: 41445.94 | V52: =1880746.37+34158.42 -> 1914904.8 | W52: 34158.42 | X52: 22243.4 | Y52: 155622.33 | Z52: 1853347.8 | AD52: 62515.32 | AI52: 1853347.8
B53: EPC自建 | C53: 2016 | D53: 内蒙察右后旗项目一 | E53: 商品销售 | F53: 0.13 | G53: =SUM(J53,L53,N53,P53,R53,T53,V53,X53,Z53,AB53,AD53,AF53,AH53,AJ53,AL53,AN53,AP53,AR53,AU53,AW53,AY53,BC53,BG53) -> 36181724 | H53: =SUM(K53,M53,O53,Q53,S53,U53,W53,Y53,AA53,AC53,AE53,AG53,AI53,AK53,AM53,AO53,AQ53,AS53,AV53,AX53,AZ53,BD53,BH53) -> 36181724 | I53: =G53-H53 -> 0 | P53: 27152204 | R53: 176101.34 | S53: 27152204 | V53: 3723884 | W53: 0 | X53: 0 | Y53: 3899985.3 | Z53: 5129535.4 | AI53: 5129535.4
C54: 2016 | E54: 工程施工 | F54: 0.09 | G54: =SUM(J54,L54,N54,P54,R54,T54,V54,X54,Z54,AB54,AD54,AF54,AH54,AJ54,AL54,AN54,AP54,AR54,AU54,AW54,AY54,BC54,BG54) -> 2.0832883e+08 | H54: =SUM(K54,M54,O54,Q54,S54,U54,W54,Y54,AA54,AC54,AE54,AG54,AI54,AK54,AM54,AO54,AQ54,AS54,AV54,AX54,AZ54,BD54,BH54) -> 2.1315087e+08 | I54: =G54-H54 -> -4822035.7 | L54: 507798.16 | N54: 1269495.4 | P54: 1360228.2 | R54: 0 | S54: 7959557.4 | T54: 1973247.2 | V54: 305907.77 | W54: 0 | X54: 7646759.4 | Y54: 2279155 | Z54: 50766702 | AC54: 11936901 | AI54: 46476560 | AR54: 73394495 | AS54: 73394495 | AU54: 71104199 | AX54: 71104199
C55: 2016 | E55: 设计咨询 | F55: 0.06 | G55: =SUM(J55,L55,N55,P55,R55,T55,V55,X55,Z55,AB55,AD55,AF55,AH55,AJ55,AL55,AN55,AP55,AR55,AU55,AW55,AY55,BC55,BG55) -> 15348125 | H55: =SUM(K55,M55,O55,Q55,S55,U55,W55,Y55,AA55,AC55,AE55,AG55,AI55,AK55,AM55,AO55,AQ55,AS55,AV55,AX55,AZ55,BD55,BH55) -> 17209687 | I55: =G55-H55 -> -1861562.5 | L55: 20225.69 | N55: 908379.56 | P55: 650679.63 | Q55: 980285.04 | R55: 2821931.8 | S55: 654379.55 | T55: 731886.98 | U55: 41445.94 | V55: =1959365.19+34158.42 -> 1993523.6 | W55: 34158.42 | X55: 1011104.7 | Y55: 7237649 | Z55: 6674545.2 | AB55: 900636.97 | AI55: 8626558.7 | AL55: 221438.68 | AR55: 0.01 | AS55: 221438.68 | AU55: -586228 | AX55: -586228
B56: EPC自建 | C56: 4470 | D56: 内蒙伊旗风光储 | E56: 商品销售 | F56: 0.13 | G56: =SUM(J56,L56,N56,P56,R56,T56,V56,X56,Z56,AB56,AD56,AF56,AH56,AJ56,AL56,AN56,AP56,AR56,AU56,AW56,AY56,BC56,BG56) -> 1.5632661e+08 | H56: =SUM(K56,M56,O56,Q56,S56,U56,W56,Y56,AA56,AC56,AE56,AG56,AI56,AK56,AM56,AO56,AQ56,AS56,AV56,AX56,AZ56,BD56,BH56) -> 62114591 | I56: =G56-H56 -> 94212016 | L56: 12953097 | N56: 7559164.6 | P56: 3793850.7 | T56: 55278600 | V56: 52916259 | W56: 9840417.2 | X56: 10795169 | Y56: 0 | AA56: -54847.11 | AB56: 114480.68 | AC56: -79871.12 | AD56: 16916191 | AE56: 50514064 | AF56: 12535.93 | AL56: 1882292.1 | AN56: 13869886 | AP56: 3314574.2 | AQ56: 1894828.1 | AW56: -103706.42 | BC56: -20924241 | BG56: -2051547.6
C57: 4470 | E57: 工程施工 | F57: 0.09 | G57: =SUM(J57,L57,N57,P57,R57,T57,V57,X57,Z57,AB57,AD57,AF57,AH57,AJ57,AL57,AN57,AP57,AR57,AU57,AW57,AY57,BC57,BG57) -> 1.269103e+08 | H57: =SUM(K57,M57,O57,Q57,S57,U57,W57,Y57,AA57,AC57,AE57,AG57,AI57,AK57,AM57,AO57,AQ57,AS57,AV57,AX57,AZ57,BD57,BH57) -> 1.2446601e+08 | I57: =G57-H57 -> 2444285 | N57: 12131406 | P57: 32038296 | Q57: 49098165 | T57: 23227907 | V57: 28676174 | W57: 32191615 | X57: 16473081 | Y57: 16473081 | Z57: 12571169 | AA57: 12571169 | AD57: 7925458.3 | AE57: 7925458.3 | AF57: =2781089.72+401414.45 -> 3182504.2 | AL57: 62534.4 | AN57: 288592.24 | AP57: 3479357.8 | AQ57: 6206522.4 | AW57: -220368.17 | BC57: -18201528 | BG57: 5275711.8
C58: 4470 | E58: 设计咨询 | F58: 0.06 | G58: =SUM(J58,L58,N58,P58,R58,T58,V58,X58,Z58,AB58,AD58,AF58,AH58,AJ58,AL58,AN58,AP58,AR58,AU58,AW58,AY58,BC58,BG58) -> 31903821 | H58: =SUM(K58,M58,O58,Q58,S58,U58,W58,Y58,AA58,AC58,AE58,AG58,AI58,AK58,AM58,AO58,AQ58,AS58,AV58,AX58,AZ58,BD58,BH58) -> 52059489 | I58: =G58-H58 -> -20155668 | L58: =53935.17+6741.9 -> 60677.07 | N58: =126783.7+6770.55 -> 133554.25 | P58: =605292.35+6278.27 -> 611570.62 | U58: 41285582 | V58: 91089.15 | W58: 91089.15 | X58: 602950.62 | Y58: 757667.6 | Z58: 251408.63 | AA58: 251408.63 | AC58: 11887.15 | AD58: 1892980.1 | AE58: 8434196.8 | AF58: 227323.24 | AL58: 3587500 | AN58: 594201.85 | AQ58: 1227657.2 | AW58: 1366564.2 | BC58: -351429.1 | BG58: 22835430
C59: 甘肃宏宇天成电力工程有限公司 | D59: 内蒙伊旗风光储 | E59: 商品销售 | F59: 0.13 | G59: =SUM(J59,L59,N59,P59,R59,T59,V59,X59,Z59,AB59,AD59,AF59,AH59,AJ59,AL59,AN59,AP59,AR59,AU59,AW59,AY59,BC59,BG59) -> 0 | H59: =SUM(K59,M59,O59,Q59,S59,U59,W59,Y59,AA59,AC59,AE59,AG59,AI59,AK59,AM59,AO59,AQ59,AS59,AV59,AX59,AZ59,BD59,BH59) -> 2451327.5 | BH59: 2451327.5
E60: 工程施工 | F60: 0.09 | G60: =SUM(J60,L60,N60,P60,R60,T60,V60,X60,Z60,AB60,AD60,AF60,AH60,AJ60,AL60,AN60,AP60,AR60,AU60,AW60,AY60,BC60,BG60) -> 0 | H60: =SUM(K60,M60,O60,Q60,S60,U60,W60,Y60,AA60,AC60,AE60,AG60,AI60,AK60,AM60,AO60,AQ60,AS60,AV60,AX60,AZ60,BD60,BH60) -> 0
E61: 设计咨询 | F61: 0.06 | G61: =SUM(J61,L61,N61,P61,R61,T61,V61,X61,Z61,AB61,AD61,AF61,AH61,AJ61,AL61,AN61,AP61,AR61,AU61,AW61,AY61,BC61,BG61) -> 0 | H61: =SUM(K61,M61,O61,Q61,S61,U61,W61,Y61,AA61,AC61,AE61,AG61,AI61,AK61,AM61,AO61,AQ61,AS61,AV61,AX61,AZ61,BD61,BH61) -> 0
C62: 河间市绿洁再生资源回收有限公司 | D62: 内蒙伊旗风光储 | E62: 商品销售 | F62: 0.13 | G62: =SUM(J62,L62,N62,P62,R62,T62,V62,X62,Z62,AB62,AD62,AF62,AH62,AJ62,AL62,AN62,AP62,AR62,AU62,AW62,AY62,BC62,BG62) -> 0 | H62: =SUM(K62,M62,O62,Q62,S62,U62,W62,Y62,AA62,AC62,AE62,AG62,AI62,AK62,AM62,AO62,AQ62,AS62,AV62,AX62,AZ62,BD62,BH62) -> 361770.42 | BH62: 361770.42
E63: 工程施工 | F63: 0.09 | G63: =SUM(J63,L63,N63,P63,R63,T63,V63,X63,Z63,AB63,AD63,AF63,AH63,AJ63,AL63,AN63,AP63,AR63,AU63,AW63,AY63,BC63,BG63) -> 0 | H63: =SUM(K63,M63,O63,Q63,S63,U63,W63,Y63,AA63,AC63,AE63,AG63,AI63,AK63,AM63,AO63,AQ63,AS63,AV63,AX63,AZ63,BD63,BH63) -> 0
E64: 设计咨询 | F64: 0.06 | G64: =SUM(J64,L64,N64,P64,R64,T64,V64,X64,Z64,AB64,AD64,AF64,AH64,AJ64,AL64,AN64,AP64,AR64,AU64,AW64,AY64,BC64,BG64) -> 0 | H64: =SUM(K64,M64,O64,Q64,S64,U64,W64,Y64,AA64,AC64,AE64,AG64,AI64,AK64,AM64,AO64,AQ64,AS64,AV64,AX64,AZ64,BD64,BH64) -> 0
B65: EPC自建 | C65: 3A18 | D65: 钦州灵山独立储能 | E65: 商品销售 | F65: 0.13 | G65: =SUM(J65,L65,N65,P65,R65,T65,V65,X65,Z65,AB65,AD65,AF65,AH65,AJ65,AL65,AN65,AP65,AR65,AU65,AW65,AY65,BC65,BG65) -> 0 | H65: =SUM(K65,M65,O65,Q65,S65,U65,W65,Y65,AA65,AC65,AE65,AG65,AI65,AK65,AM65,AO65,AQ65,AS65,AV65,AX65,AZ65,BD65,BH65) -> 0 | I65: =G65-H65 -> 0 | V65: 0 | W65: 0 | X65: 0 | Y65: 0
C66: 3A18 | E66: 工程施工 | F66: 0.09 | G66: =SUM(J66,L66,N66,P66,R66,T66,V66,X66,Z66,AB66,AD66,AF66,AH66,AJ66,AL66,AN66,AP66,AR66,AU66,AW66,AY66,BC66,BG66) -> 0 | H66: =SUM(K66,M66,O66,Q66,S66,U66,W66,Y66,AA66,AC66,AE66,AG66,AI66,AK66,AM66,AO66,AQ66,AS66,AV66,AX66,AZ66,BD66,BH66) -> 0 | I66: =G66-H66 -> 0 | V66: 0 | W66: 0 | X66: 0 | Y66: 0
C67: 3A18 | E67: 设计咨询 | F67: 0.06 | G67: =SUM(J67,L67,N67,P67,R67,T67,V67,X67,Z67,AB67,AD67,AF67,AH67,AJ67,AL67,AN67,AP67,AR67,AU67,AW67,AY67,BC67,BG67) -> 60072 | H67: =SUM(K67,M67,O67,Q67,S67,U67,W67,Y67,AA67,AC67,AE67,AG67,AI67,AK67,AM67,AO67,AQ67,AS67,AV67,AX67,AZ67,BD67,BH67) -> 813027.61 | I67: =G67-H67 -> -752955.61 | L67: 7219.88 | N67: 7220.06 | P67: 7307.29 | R67: 7319.78 | S67: 7319.78 | T67: 11645.92 | U67: 805707.83 | V67: 0 | W67: 0 | X67: 0 | Y67: 0 | AR67: 19359.07
B68: EPC自建 | C68: 3318 | D68: 新疆巴里坤 | E68: 商品销售 | F68: 0.13 | G68: =SUM(J68,L68,N68,P68,R68,T68,V68,X68,Z68,AB68,AD68,AF68,AH68,AJ68,AL68,AN68,AP68,AR68,AU68,AW68,AY68,BC68,BG68) -> 0 | H68: =SUM(K68,M68,O68,Q68,S68,U68,W68,Y68,AA68,AC68,AE68,AG68,AI68,AK68,AM68,AO68,AQ68,AS68,AV68,AX68,AZ68,BD68,BH68) -> 0 | I68: =G68-H68 -> 0 | V68: 0 | W68: 0 | X68: 0 | Y68: 0
C69: 3318 | E69: 工程施工 | F69: 0.09 | G69: =SUM(J69,L69,N69,P69,R69,T69,V69,X69,Z69,AB69,AD69,AF69,AH69,AJ69,AL69,AN69,AP69,AR69,AU69,AW69,AY69,BC69,BG69) -> 0 | H69: =SUM(K69,M69,O69,Q69,S69,U69,W69,Y69,AA69,AC69,AE69,AG69,AI69,AK69,AM69,AO69,AQ69,AS69,AV69,AX69,AZ69,BD69,BH69) -> 0 | I69: =G69-H69 -> 0 | V69: 0 | W69: 0 | X69: 0 | Y69: 0
C70: 3318 | E70: 设计咨询 | F70: 0.06 | G70: =SUM(J70,L70,N70,P70,R70,T70,V70,X70,Z70,AB70,AD70,AF70,AH70,AJ70,AL70,AN70,AP70,AR70,AU70,AW70,AY70,BC70,BG70) -> 1132075.5 | H70: =SUM(K70,M70,O70,Q70,S70,U70,W70,Y70,AA70,AC70,AE70,AG70,AI70,AK70,AM70,AO70,AQ70,AS70,AV70,AX70,AZ70,BD70,BH70) -> 1132075.5 | I70: =G70-H70 -> 0 | L70: 1132075.5 | M70: 1132075.5 | V70: 0 | W70: 0 | X70: 0 | Y70: 0
B71: EPC自建 | C71: 3350 | D71: 射阳汇智风电场110kv升压站站内设备检测工程 | E71: 商品销售 | F71: 0.13 | G71: =SUM(J71,L71,N71,P71,R71,T71,V71,X71,Z71,AB71,AD71,AF71,AH71,AJ71,AL71,AN71,AP71,AR71,AU71,AW71,AY71,BC71,BG71) -> 0 | H71: =SUM(K71,M71,O71,Q71,S71,U71,W71,Y71,AA71,AC71,AE71,AG71,AI71,AK71,AM71,AO71,AQ71,AS71,AV71,AX71,AZ71,BD71,BH71) -> 0 | I71: =G71-H71 -> 0 | V71: 0 | W71: 0 | X71: 0 | Y71: 0
C72: 3350 | E72: 工程施工 | F72: 0.09 | G72: =SUM(J72,L72,N72,P72,R72,T72,V72,X72,Z72,AB72,AD72,AF72,AH72,AJ72,AL72,AN72,AP72,AR72,AU72,AW72,AY72,BC72,BG72) -> 0 | H72: =SUM(K72,M72,O72,Q72,S72,U72,W72,Y72,AA72,AC72,AE72,AG72,AI72,AK72,AM72,AO72,AQ72,AS72,AV72,AX72,AZ72,BD72,BH72) -> 479041.85 | I72: =G72-H72 -> -479041.85 | Q72: 258731.46 | V72: 0 | W72: 0 | X72: 0 | Y72: 0 | AE72: -258731.46 | AM72: 479041.85
C73: 3350 | E73: 设计咨询 | F73: 0.06 | G73: =SUM(J73,L73,N73,P73,R73,T73,V73,X73,Z73,AB73,AD73,AF73,AH73,AJ73,AL73,AN73,AP73,AR73,AU73,AW73,AY73,BC73,BG73) -> 0 | H73: =SUM(K73,M73,O73,Q73,S73,U73,W73,Y73,AA73,AC73,AE73,AG73,AI73,AK73,AM73,AO73,AQ73,AS73,AV73,AX73,AZ73,BD73,BH73) -> 0 | I73: =G73-H73 -> 0 | R73: 191067.96 | S73: 0 | V73: 0 | W73: 0 | X73: 0 | Y73: 0 | BC73: -191067.96
B74: EPC自建 | C74: 4470 | D74: 内蒙鄂尔多斯风电场运检维护项目 | E74: 商品销售 | F74: 0.13 | G74: =SUM(J74,L74,N74,P74,R74,T74,V74,X74,Z74,AB74,AD74,AF74,AH74,AJ74,AL74,AN74,AP74,AR74,AU74,AW74,AY74,BC74,BG74) -> 38525142 | H74: =SUM(K74,M74,O74,Q74,S74,U74,W74,Y74,AA74,AC74,AE74,AG74,AI74,AK74,AM74,AO74,AQ74,AS74,AV74,AX74,AZ74,BD74,BH74) -> 16726499 | I74: =G74-H74 -> 21798643 | R74: 535025.56 | S74: 0 | U74: 16726499 | V74: =4376588 -> 4376588 | W74: 0 | X74: 0 | Y74: 0 | Z74: 32984880 | AB74: 610464.6 | AN74: 18184.68
C75: 4470 | E75: 工程施工 | F75: 0.09 | G75: =SUM(J75,L75,N75,P75,R75,T75,V75,X75,Z75,AB75,AD75,AF75,AH75,AJ75,AL75,AN75,AP75,AR75,AU75,AW75,AY75,BC75,BG75) -> 2594225.3 | H75: =SUM(K75,M75,O75,Q75,S75,U75,W75,Y75,AA75,AC75,AE75,AG75,AI75,AK75,AM75,AO75,AQ75,AS75,AV75,AX75,AZ75,BD75,BH75) -> 31473110 | I75: =G75-H75 -> -28878885 | Q75: 486312.49 | R75: 831989.3 | S75: 0 | U75: 30542864 | V75: =831989.3+930246.74 -> 1762236 | W75: 930246.74 | X75: 0 | Y75: 0 | AE75: -486312.49
C76: 4470 | E76: 设计咨询 | F76: 0.06 | G76: =SUM(J76,L76,N76,P76,R76,T76,V76,X76,Z76,AB76,AD76,AF76,AH76,AJ76,AL76,AN76,AP76,AR76,AU76,AW76,AY76,BC76,BG76) -> 47143610 | H76: =SUM(K76,M76,O76,Q76,S76,U76,W76,Y76,AA76,AC76,AE76,AG76,AI76,AK76,AM76,AO76,AQ76,AS76,AV76,AX76,AZ76,BD76,BH76) -> 7511.57 | I76: =G76-H76 -> 47136098 | R76: 7511.57 | S76: 7511.57 | T76: 41339457 | V76: 0 | W76: 0 | X76: 0 | Y76: 0 | AB76: 5796641.1 | BC76: 0
B77: EPC自建 | C77: 4470 | D77: 内蒙伊旗风光储-光伏 | E77: 商品销售 | F77: 0.13 | G77: =SUM(J77,L77,N77,P77,R77,T77,V77,X77,Z77,AB77,AD77,AF77,AH77,AJ77,AL77,AN77,AP77,AR77,AU77,AW77,AY77,BC77,BG77) -> 27234067 | H77: =SUM(K77,M77,O77,Q77,S77,U77,W77,Y77,AA77,AC77,AE77,AG77,AI77,AK77,AM77,AO77,AQ77,AS77,AV77,AX77,AZ77,BD77,BH77) -> 63552791 | I77: =G77-H77 -> -36318724 | R77: 19775234 | S77: 50697108 | T77: 535025.56 | V77: 0 | W77: 0 | X77: 2690452.9 | Y77: 2690452.9 | Z77: 1610020.5 | AA77: 1610020.5 | AD77: 323827.43 | AE77: 6057103.7 | AF77: 1710381 | AH77: 412382.29 | AQ77: 1186468.6 | AR77: 518750.43 | AV77: 1311637.2 | AY77: -342007.13
C78: 4470 | E78: 工程施工 | F78: 0.09 | G78: =SUM(J78,L78,N78,P78,R78,T78,V78,X78,Z78,AB78,AD78,AF78,AH78,AJ78,AL78,AN78,AP78,AR78,AU78,AW78,AY78,BC78,BG78) -> 20631616 | H78: =SUM(K78,M78,O78,Q78,S78,U78,W78,Y78,AA78,AC78,AE78,AG78,AI78,AK78,AM78,AO78,AQ78,AS78,AV78,AX78,AZ78,BD78,BH78) -> 8131237.4 | I78: =G78-H78 -> 12500378 | R78: 11119160 | S78: 917431.19 | V78: 207306.14 | W78: 207306.14 | X78: 0 | Y78: 0 | AB78: 270555.32 | AD78: 757261.12 | AE78: =2421239.72+270555.32 -> 2691795 | AF78: 5127803.9 | AQ78: 3671822.6 | AR78: 188073.4 | AV78: 642882.47 | AY78: 402538 | BG78: 2558917.5
C79: 4470 | E79: 设计咨询 | F79: 0.06 | G79: =SUM(J79,L79,N79,P79,R79,T79,V79,X79,Z79,AB79,AD79,AF79,AH79,AJ79,AL79,AN79,AP79,AR79,AU79,AW79,AY79,BC79,BG79) -> 945443.01 | H79: =SUM(K79,M79,O79,Q79,S79,U79,W79,Y79,AA79,AC79,AE79,AG79,AI79,AK79,AM79,AO79,AQ79,AS79,AV79,AX79,AZ79,BD79,BH79) -> 1160920.3 | I79: =G79-H79 -> -215477.27 | R79: 60092.57 | S79: 687778.13 | V79: =186949.69+11386.14 -> 198335.83 | W79: =186949.69+11386.14 -> 198335.83 | X79: 7414.46 | Y79: 7414.46 | Z79: 5639.92 | AA79: 5639.92 | AB79: 11887.15 | AD79: 197931.19 | AE79: 197931.19 | AR79: 63820.75 | AU79: 15471.7 | AV79: 63820.75 | AY79: 287000 | BG79: 97849.44
B80: EPC自建 | C80: 4570 | D80: 河北沧县 | E80: 商品销售 | F80: 0.13 | G80: =SUM(J80,L80,N80,P80,R80,T80,V80,X80,Z80,AB80,AD80,AF80,AH80,AJ80,AL80,AN80,AP80,AR80,AU80,AW80,AY80,BC80,BG80) -> 40316.81 | H80: =SUM(K80,M80,O80,Q80,S80,U80,W80,Y80,AA80,AC80,AE80,AG80,AI80,AK80,AM80,AO80,AQ80,AS80,AV80,AX80,AZ80,BD80,BH80) -> 40316.81 | I80: =G80-H80 -> 0 | V80: 40316.81 | W80: 0 | X80: 0 | Y80: 0 | AG80: 40316.81
C81: 4570 | E81: 工程施工 | F81: 0.09 | G81: =SUM(J81,L81,N81,P81,R81,T81,V81,X81,Z81,AB81,AD81,AF81,AH81,AJ81,AL81,AN81,AP81,AR81,AU81,AW81,AY81,BC81,BG81) -> 291262.14 | H81: =SUM(K81,M81,O81,Q81,S81,U81,W81,Y81,AA81,AC81,AE81,AG81,AI81,AK81,AM81,AO81,AQ81,AS81,AV81,AX81,AZ81,BD81,BH81) -> 291262.14 | I81: =G81-H81 -> 0 | L81: 291262.14 | M81: 291262.14 | V81: 0 | W81: 0 | X81: 0 | Y81: 0
C82: 4570 | E82: 设计咨询 | F82: 0.06 | G82: =SUM(J82,L82,N82,P82,R82,T82,V82,X82,Z82,AB82,AD82,AF82,AH82,AJ82,AL82,AN82,AP82,AR82,AU82,AW82,AY82,BC82,BG82) -> 10105098 | H82: =SUM(K82,M82,O82,Q82,S82,U82,W82,Y82,AA82,AC82,AE82,AG82,AI82,AK82,AM82,AO82,AQ82,AS82,AV82,AX82,AZ82,BD82,BH82) -> 10455261 | I82: =G82-H82 -> -350163.07 | L82: =4391330.09+329654.87 -> 4720985 | M82: 4203905.6 | N82: 488607.91 | P82: 323799.97 | Q82: 1355850.4 | R82: 864773.96 | S82: 67604.15 | T82: 67833.42 | U82: 124337.79 | V82: =1327755.84+102475.29 -> 1430231.1 | W82: 102475.29 | X82: 962956.63 | Y82: 66730.21 | Z82: 50759.24 | AA82: 50759.24 | AB82: 467059.25 | AC82: 467059.25 | AD82: 300060.87 | AG82: 3588508.5 | AN82: 157232.7 | AQ82: 157232.7 | AR82: 181699.17 | AS82: 181699.17 | AU82: 89098.55 | AZ82: 89098.55
B83: EPC自建 | C83: 2351 | D83: 河南濮阳昆吾 | E83: 商品销售 | F83: 0.13 | G83: =SUM(J83,L83,N83,P83,R83,T83,V83,X83,Z83,AB83,AD83,AF83,AH83,AJ83,AL83,AN83,AP83,AR83,AU83,AW83,AY83,BC83,BG83) -> 0 | H83: =SUM(K83,M83,O83,Q83,S83,U83,W83,Y83,AA83,AC83,AE83,AG83,AI83,AK83,AM83,AO83,AQ83,AS83,AV83,AX83,AZ83,BD83,BH83) -> 0 | I83: =G83-H83 -> 0 | V83: 0 | W83: 0 | X83: 0 | Y83: 0
C84: 2351 | E84: 工程施工 | F84: 0.09 | G84: =SUM(J84,L84,N84,P84,R84,T84,V84,X84,Z84,AB84,AD84,AF84,AH84,AJ84,AL84,AN84,AP84,AR84,AU84,AW84,AY84,BC84,BG84) -> 769393.45 | H84: =SUM(K84,M84,O84,Q84,S84,U84,W84,Y84,AA84,AC84,AE84,AG84,AI84,AK84,AM84,AO84,AQ84,AS84,AV84,AX84,AZ84,BD84,BH84) -> 769393.45 | I84: =G84-H84 -> 0 | L84: 769393.45 | M84: 769393.45 | V84: 0 | W84: 0 | X84: 0 | Y84: 0
C85: 2351 | E85: 设计咨询 | F85: 0.06 | G85: =SUM(J85,L85,N85,P85,R85,T85,V85,X85,Z85,AB85,AD85,AF85,AH85,AJ85,AL85,AN85,AP85,AR85,AU85,AW85,AY85,BC85,BG85) -> 8138787.5 | H85: =SUM(K85,M85,O85,Q85,S85,U85,W85,Y85,AA85,AC85,AE85,AG85,AI85,AK85,AM85,AO85,AQ85,AS85,AV85,AX85,AZ85,BD85,BH85) -> 8461721.4 | I85: =G85-H85 -> -322933.89 | L85: =354587.32+4501401.45 -> 4855988.8 | M85: 3388193.9 | N85: 420738.6 | P85: 226506.05 | Q85: 2123417 | R85: 761004.23 | S85: 45069.43 | T85: 93440.31 | U85: 82891.85 | V85: 203692.85 | W85: 68316.87 | X85: 44486.8 | Y85: 44486.8 | Z85: 306376.18 | AA85: 33839.49 | AB85: 143021.01 | AC85: 71322.9 | AD85: 167722.12 | AG85: 1520650.4 | AJ85: 89108.91 | AK85: 256831.03 | AN85: 260405.04 | AP85: 78613.21 | AQ85: 339018.25 | AR85: 27096.43 | AS85: 27096.43 | AU85: 460587 | BH85: 460587
B86: EPC自建 | C86: 3307 | D86: 灵山玖伯一期 | E86: 商品销售 | F86: 0.13 | G86: =SUM(J86,L86,N86,P86,R86,T86,V86,X86,Z86,AB86,AD86,AF86,AH86,AJ86,AL86,AN86,AP86,AR86,AU86,AW86,AY86,BC86,BG86) -> 0 | H86: =SUM(K86,M86,O86,Q86,S86,U86,W86,Y86,AA86,AC86,AE86,AG86,AI86,AK86,AM86,AO86,AQ86,AS86,AV86,AX86,AZ86,BD86,BH86) -> 0 | I86: =G86-H86 -> 0 | V86: 0 | W86: 0 | X86: 0 | Y86: 0
C87: 3307 | E87: 工程施工 | F87: 0.09 | G87: =SUM(J87,L87,N87,P87,R87,T87,V87,X87,Z87,AB87,AD87,AF87,AH87,AJ87,AL87,AN87,AP87,AR87,AU87,AW87,AY87,BC87,BG87) -> 194174.76 | H87: =SUM(K87,M87,O87,Q87,S87,U87,W87,Y87,AA87,AC87,AE87,AG87,AI87,AK87,AM87,AO87,AQ87,AS87,AV87,AX87,AZ87,BD87,BH87) -> 194174.76 | I87: =G87-H87 -> 0 | L87: 194174.76 | M87: 194174.76 | V87: 0 | W87: 0 | X87: 0 | Y87: 0
C88: 3307 | E88: 设计咨询 | F88: 0.06 | G88: =SUM(J88,L88,N88,P88,R88,T88,V88,X88,Z88,AB88,AD88,AF88,AH88,AJ88,AL88,AN88,AP88,AR88,AU88,AW88,AY88,BC88,BG88) -> 5322473.7 | H88: =SUM(K88,M88,O88,Q88,S88,U88,W88,Y88,AA88,AC88,AE88,AG88,AI88,AK88,AM88,AO88,AQ88,AS88,AV88,AX88,AZ88,BD88,BH88) -> 5584965 | I88: =G88-H88 -> -262491.27 | L88: =1978162.8+131078.12 -> 2109240.9 | M88: 1918579.9 | N88: 54164.39 | P88: 555432.9 | Q88: 500605.24 | R88: 60092.57 | S88: 60092.57 | U88: 110522.47 | V88: =525589.21+91089.15 -> 616678.36 | W88: 91089.15 | X88: 141957.25 | Y88: 59315.74 | Z88: 45119.32 | AA88: 45119.32 | AB88: 175474.56 | AC88: 95097.2 | AD88: 87852.62 | AE88: 87852.62 | AG88: 1193814.9 | AH88: 1099136.7 | AI88: 1099136.7 | BC88: 323739.19 | BG88: 53584.91 | BH88: 323739.19
B89: EPC自建 | C89: 3307 | D89: 灵山玖伯二期 | E89: 商品销售 | F89: 0.13 | G89: =SUM(J89,L89,N89,P89,R89,T89,V89,X89,Z89,AB89,AD89,AF89,AH89,AJ89,AL89,AN89,AP89,AR89,AU89,AW89,AY89,BC89,BG89) -> 0 | H89: =SUM(K89,M89,O89,Q89,S89,U89,W89,Y89,AA89,AC89,AE89,AG89,AI89,AK89,AM89,AO89,AQ89,AS89,AV89,AX89,AZ89,BD89,BH89) -> 0 | I89: =G89-H89 -> 0 | V89: 0 | W89: 0 | X89: 0 | Y89: 0
C90: 3307 | E90: 工程施工 | F90: 0.09 | G90: =SUM(J90,L90,N90,P90,R90,T90,V90,X90,Z90,AB90,AD90,AF90,AH90,AJ90,AL90,AN90,AP90,AR90,AU90,AW90,AY90,BC90,BG90) -> 0 | H90: =SUM(K90,M90,O90,Q90,S90,U90,W90,Y90,AA90,AC90,AE90,AG90,AI90,AK90,AM90,AO90,AQ90,AS90,AV90,AX90,AZ90,BD90,BH90) -> 0 | I90: =G90-H90 -> 0 | V90: 0 | W90: 0 | X90: 0 | Y90: 0
C91: 3307 | E91: 设计咨询 | F91: 0.06 | G91: =SUM(J91,L91,N91,P91,R91,T91,V91,X91,Z91,AB91,AD91,AF91,AH91,AJ91,AL91,AN91,AP91,AR91,AU91,AW91,AY91,BC91,BG91) -> 3482281.2 | H91: =SUM(K91,M91,O91,Q91,S91,U91,W91,Y91,AA91,AC91,AE91,AG91,AI91,AK91,AM91,AO91,AQ91,AS91,AV91,AX91,AZ91,BD91,BH91) -> 3677764.7 | I91: =G91-H91 -> -195483.44 | L91: =1299437.53+115623.92 -> 1415061.4 | M91: 1245812.9 | N91: 54164.39 | P91: 352625.48 | Q91: 479192.75 | R91: 60092.57 | S91: 60092.57 | T91: 120592.74 | U91: 110522.47 | V91: =408373.06+91089.15 -> 499462.21 | W91: 91089.15 | X91: 59315.74 | Y91: 59315.74 | Z91: 45119.32 | AA91: 45119.32 | AB91: 95097.2 | AC91: 95097.2 | AD91: 87852.62 | AE91: 87852.62 | AG91: 710772.44 | AH91: 473848.28 | AI91: 473848.28 | BC91: 219049.25 | BH91: 219049.25
B92: EPC自建 | C92: 2058 | D92: 钦南久沙 | E92: 商品销售 | F92: 0.13 | G92: =SUM(J92,L92,N92,P92,R92,T92,V92,X92,Z92,AB92,AD92,AF92,AH92,AJ92,AL92,AN92,AP92,AR92,AU92,AW92,AY92,BC92,BG92) -> 165026.55 | H92: =SUM(K92,M92,O92,Q92,S92,U92,W92,Y92,AA92,AC92,AE92,AG92,AI92,AK92,AM92,AO92,AQ92,AS92,AV92,AX92,AZ92,BD92,BH92) -> 165026.55 | I92: =G92-H92 -> 0 | V92: 0 | W92: 0 | X92: 0 | Y92: 0 | AW92: 165026.55 | AX92: 165026.55
C93: 2058 | E93: 工程施工 | F93: 0.09 | G93: =SUM(J93,L93,N93,P93,R93,T93,V93,X93,Z93,AB93,AD93,AF93,AH93,AJ93,AL93,AN93,AP93,AR93,AU93,AW93,AY93,BC93,BG93) -> 0 | H93: =SUM(K93,M93,O93,Q93,S93,U93,W93,Y93,AA93,AC93,AE93,AG93,AI93,AK93,AM93,AO93,AQ93,AS93,AV93,AX93,AZ93,BD93,BH93) -> 0 | I93: =G93-H93 -> 0 | V93: 0 | W93: 0 | X93: 0 | Y93: 0
C94: 2058 | E94: 设计咨询 | F94: 0.06 | G94: =SUM(J94,L94,N94,P94,R94,T94,V94,X94,Z94,AB94,AD94,AF94,AH94,AJ94,AL94,AN94,AP94,AR94,AU94,AW94,AY94,BC94,BG94) -> 3616053.3 | H94: =SUM(K94,M94,O94,Q94,S94,U94,W94,Y94,AA94,AC94,AE94,AG94,AI94,AK94,AM94,AO94,AQ94,AS94,AV94,AX94,AZ94,BD94,BH94) -> 3786782.4 | I94: =G94-H94 -> -170729.16 | L94: =1077061.32+144175.76 -> 1221237.1 | M94: 995856.92 | N94: 221154.96 | P94: 74754.4 | Q94: 705314.59 | R94: =60092.57+81205.45 -> 141298.02 | S94: 60092.57 | T94: 366187.35 | U94: 110522.47 | V94: =484600.63+91089.15 -> 575689.78 | W94: 91089.15 | X94: 59315.74 | Y94: 59315.74 | Z94: 45119.32 | AA94: 45119.32 | AB94: 387259.95 | AD94: 111327.04 | AG94: 1195435 | AJ94: 200000 | AK94: 311327.04 | AL94: 185642.56 | AN94: 27067.09 | AQ94: 212709.65
B95: EPC自建 | C95: 3308 | D95: 灵山文利 | E95: 商品销售 | F95: 0.13 | G95: =SUM(J95,L95,N95,P95,R95,T95,V95,X95,Z95,AB95,AD95,AF95,AH95,AJ95,AL95,AN95,AP95,AR95,AU95,AW95,AY95,BC95,BG95) -> 0 | H95: =SUM(K95,M95,O95,Q95,S95,U95,W95,Y95,AA95,AC95,AE95,AG95,AI95,AK95,AM95,AO95,AQ95,AS95,AV95,AX95,AZ95,BD95,BH95) -> 0 | I95: =G95-H95 -> 0 | V95: 0 | W95: 0 | X95: 0 | Y95: 0
C96: 3308 | E96: 工程施工 | F96: 0.09 | G96: =SUM(J96,L96,N96,P96,R96,T96,V96,X96,Z96,AB96,AD96,AF96,AH96,AJ96,AL96,AN96,AP96,AR96,AU96,AW96,AY96,BC96,BG96) -> 214563.11 | H96: =SUM(K96,M96,O96,Q96,S96,U96,W96,Y96,AA96,AC96,AE96,AG96,AI96,AK96,AM96,AO96,AQ96,AS96,AV96,AX96,AZ96,BD96,BH96) -> 214563.11 | I96: =G96-H96 -> 0 | L96: 214563.11 | M96: 214563.11 | V96: 0 | W96: 0 | X96: 0 | Y96: 0
C97: 3308 | E97: 设计咨询 | F97: 0.06 | G97: =SUM(J97,L97,N97,P97,R97,T97,V97,X97,Z97,AB97,AD97,AF97,AH97,AJ97,AL97,AN97,AP97,AR97,AU97,AW97,AY97,BC97,BG97) -> 10809477 | H97: =SUM(K97,M97,O97,Q97,S97,U97,W97,Y97,AA97,AC97,AE97,AG97,AI97,AK97,AM97,AO97,AQ97,AS97,AV97,AX97,AZ97,BD97,BH97) -> 11105978 | I97: =G97-H97 -> -296501.27 | L97: =3640904.27+199508.76 -> 3840413 | M97: 3640904.3 | N97: 60934.95 | P97: 406510.66 | Q97: 556944.98 | R97: 67604.15 | S97: 67604.15 | T97: 2107833.4 | U97: 124337.79 | V97: =102475.29+1542313.07 -> 1644788.4 | W97: 102475.29 | X97: 66730.21 | Y97: 66730.21 | Z97: 50759.24 | AA97: 50759.24 | AB97: 106984.35 | AC97: 106984.35 | AD97: 179211.56 | AE97: 98834.2 | AG97: 3932319.4 | AH97: 1659585.2 | AI97: 1659585.2 | AK97: 80377.36 | BC97: 618121.66 | BH97: 618121.66
B98: EPC自建 | C98: 2057 | D98: 钦州三期 （枫木山） | E98: 商品销售 | F98: 0.13 | G98: =SUM(J98,L98,N98,P98,R98,T98,V98,X98,Z98,AB98,AD98,AF98,AH98,AJ98,AL98,AN98,AP98,AR98,AU98,AW98,AY98,BC98,BG98) -> 0 | H98: =SUM(K98,M98,O98,Q98,S98,U98,W98,Y98,AA98,AC98,AE98,AG98,AI98,AK98,AM98,AO98,AQ98,AS98,AV98,AX98,AZ98,BD98,BH98) -> 0 | I98: =G98-H98 -> 0 | V98: 0 | W98: 0 | X98: 0 | Y98: 0
C99: 2057 | E99: 工程施工 | F99: 0.09 | G99: =SUM(J99,L99,N99,P99,R99,T99,V99,X99,Z99,AB99,AD99,AF99,AH99,AJ99,AL99,AN99,AP99,AR99,AU99,AW99,AY99,BC99,BG99) -> 0 | H99: =SUM(K99,M99,O99,Q99,S99,U99,W99,Y99,AA99,AC99,AE99,AG99,AI99,AK99,AM99,AO99,AQ99,AS99,AV99,AX99,AZ99,BD99,BH99) -> 0 | I99: =G99-H99 -> 0 | V99: 0 | W99: 0 | X99: 0 | Y99: 0
C100: 2057 | E100: 设计咨询 | F100: 0.06 | G100: =SUM(J100,L100,N100,P100,R100,T100,V100,X100,Z100,AB100,AD100,AF100,AH100,AJ100,AL100,AN100,AP100,AR100,AU100,AW100,AY100,BC100,BG100) -> 1706596.8 | H100: =SUM(K100,M100,O100,Q100,S100,U100,W100,Y100,AA100,AC100,AE100,AG100,AI100,AK100,AM100,AO100,AQ100,AS100,AV100,AX100,AZ100,BD100,BH100) -> 1903931 | I100: =G100-H100 -> -197334.22 | L100: =497018.11+195454.72 -> 692472.83 | M100: 195454.72 | N100: 40623.3 | P100: 37669.57 | Q100: 734975.63 | R100: 45069.43 | S100: 45069.43 | T100: 45222.28 | U100: 82891.85 | V100: =200000+68316.87 -> 268316.87 | W100: 68316.87 | X100: 44486.8 | Y100: 44486.8 | Z100: 33839.49 | AA100: 33839.49 | AB100: 166298.74 | AF100: 277164.57 | AG100: 366298.74 | AK100: 277164.57 | BC100: 55432.92 | BH100: 55432.92
...

Sheet 增值税变动表附表
A1: 序号 | B1: 省份 | C1: 县市 | D1: 项目公司 | E1: 项目名称 | F1: 异地预缴申报所属期 | G1: 总包金额 | H1: 异地预缴收入 | I1: 扣除金额 | J1: 异地预缴增值税扣除额 | K1: 地方水利建设基金 | L1: 增值税 | M1: 附加税费 | N1: 企业所得税
A2: 6 | B2: 新疆 | C2: 和田市吐哈 | D2: 中国石油天然气股份有限公司吐哈油田分公司 | E2: 吐哈油田 | F2: 202401 | G2: 996000 | H2: 667825.56 | J2: 12253.68 | L2: 12253.68 | M2: 1225.37 | N2: 1225.368 | O2: VAT已于所属期5月申报抵减 | P2: 企税于所属期6月已抵减
A3: 7 | B3: 安徽 | C3: 宣城市郎溪县凌笪镇 | D3: 郎溪景宇风力发电有限公司 | E3: 郎溪景瑞 | F3: 202404 | G3: 32917417 | H3: 32917417 | J3: 21943.21 | L3: 21943.21 | M3: =1097.16+658.3+438.86 -> 2194.32 | N3: 60398.93 | O3: VAT已于所属期5月申报抵减 | P3: 企税于所属期6月已抵减
A5: 8 | B5: 河北 | C5: 邯郸市馆陶县 | D5: 馆陶县汇恒风电有限公司 | E5: 河北馆陶 | F5: 202405 | G5: 208766461 | H5: 208766461 | I5: 2.0642153e+08 | J5: =(H5-I5)/1.09*2% -> 43026.283 | L5: 43026.283 | M5: =2151.31+860.53+1290.79 -> 4302.63 | N5: 383057.73 | O5: VAT已于所属期5月申报抵减 | P5: 企税于所属期6月已抵减
A6: 9 | B6: 内蒙古 | C6: 鄂尔多斯市伊金霍洛旗 | D6: 伊金霍洛旗悦盛新能源有限公司 | E6: 鄂尔多斯零碳产业园 | F6: 202406 | G6: 208766461 | H6: 88930666 | I6: 86173010 | J6: =(H6-I6)/1.09*2% -> 50599.204 | L6: 50599.204 | M6: 5059.92 | N6: 163175.53 | O6: VAT已于所属期5月申报抵减 | P6: 企税于所属期6月已抵减
A8: 10 | B8: 安徽 | C8: 宣城市郎溪县凌笪镇 | D8: 郎溪景宇风力发电有限公司 | E8: 远景郎溪县风电场项目 | F8: 202406 | G8: 21145047 | H8: 21145047 | I8: 12080329 | J8: =(H8-I8)/1.09*2% -> 166325.11 | L8: =J8 -> 166325.11 | M8: =8316.26+4989.75+3326.5 -> 16632.51 | N8: 38798.25 | O8: VAT已于所属期7月申报抵减 | P8: 企税于所属期6月已抵减
A10: 11 | B10: 内蒙古 | C10: 内蒙古自治区乌兰察布市察哈尔右翼后旗白音察干镇后旗 | D10: 察哈尔右翼后旗景源新能源有限公司 | E10: 察哈尔景源（源荷互动绿色大数据中心） | F10: 202407 | G10: 10261695 | H10: 10261695 | I10: 9970877.9 | J10: 5336.1 | L10: 5336.1 | M10: 533.61 | N10: 18828.8 | O10: VAT已于所属期7月申报抵减 | P10: 企税于所属期9月已抵减
A12: 12 | B12: 安徽 | C12: 定远县经济开发区 | D12: 定远纳驰风力发电有限公司 | E12: 安徽定远欣月(四期)工程项目 | F12: 202407 | G12: 57238404 | H12: 57238404 | I12: 52256733 | J12: 91406.8 | L12: 91406.8 | M12: 9140.68 | N12: 105024.59 | O12: VAT已于所属期7月申报抵减 | P12: 企税于所属期9月已抵减
A13: 13 | B13: 安徽 | C13: 定远县定远经济开发区 | D13: 定远纳风风力发电有限公司 | E13: 安徽定远乘风(三期)工程项目 | F13: 202407 | G13: 1.1842049e+08 | H13: 1.1842049e+08 | I13: 1.1462059e+08 | J13: 69722.84 | L13: 69722.84 | M13: 6972.29 | N13: 217285.3 | O13: VAT已于所属期7月申报抵减 | P13: 企税于所属期9月已抵减
A14: 14 | B14: 新疆 | C14: 新疆哈密市巴里坤哈萨克自治县 | D14: 哈密博景新能源有限责任公司 | E14: 巴里坤县 40 万千瓦风电+40 万千瓦时储能新能源项目 | F14: 202407 | G14: 5.959407e+08 | H14: 5.959407e+08 | I14: 1.9773964e+08 | J14: 7306441.5 | L14: 7306441.5 | M14: 730644.14 | N14: 1093469.2 | O14: VAT已于所属期7月申报抵减 | P14: 企税于所属期9月已抵减
A15: 15 | B15: 内蒙古 | C15: 内蒙古自治区乌兰察布市察哈尔右翼后旗 | D15: 察哈尔右翼后旗景源新能源有限公司 | E15: 源荷互动绿色大数据中心示范项目EPC总承包采购合同 | F15: 202411 | G15: 2484279 | H15: 2484279 | I15: 2405780 | J15: 1440.35 | L15: 1440.35 | M15: 72.02 | N15: 4558.31 | O15: vat于11期抵减 | P15: cit于12期已抵减
A16: 16 | B16: 安徽 | C16: 定边县贺圈镇王家梁 | D16: 定边远定新能源有限公司 | E16: 定边王家梁风电项目工程项目 EPC 总承包采购合同 | F16: 202411 | G16: 3.4607205e+08 | H16: 3.4607205e+08 | I16: 1.3199066e+08 | J16: 3928098.9 | L16: 3928098.9 | M16: 392809.89 | N16: 634994.58 | O16: vat于11期抵减 | P16: cit于12期已抵减
A17: 17 | B17: 河北 | C17: 河北省承德市丰宁满族自治县鱼儿山镇 | D17: 丰宁满族自治县康宁新能源有限公司 | E17: 丰宁一期 | F17: 202411 | G17: 56649418 | H17: 56649418 | I17: 56649418 | J17: 0 | L17: 0 | M17: 0 | N17: 103943.89 | O17: vat于11期抵减 | P17: cit于12期已抵减
A18: 18 | B18: 河北 | C18: 丰宁满族自治县大滩镇 | D18: 丰宁满族自治县康宁新能源有限公司 | E18: 丰宁二期 | F18: 202411 | G18: 5.9912739e+08 | H18: 5.9912739e+08 | I18: 1.7907874e+08 | J18: 7707314.5 | L18: 7707314.5 | M18: 770731.46 | N18: 1099316.3 | O18: vat于11期抵减 | P18: cit于12期已抵减
A19: 19 | B19: 河北 | C19: 丰宁满族自治县草原乡 | D19: 丰宁满族自治县康宁新能源有限公司 | E19: 丰宁三期 | F19: 202411 | G19: 1.4485128e+08 | H19: 1.4485128e+08 | I19: 1.4485128e+08 | J19: 0 | L19: 0 | M19: 0 | N19: 265782.17 | O19: vat于11期抵减 | P19: cit于12期已抵减
A20: 20 | B20: 宁夏 | C20: 宁夏灵武市白土岗乡大唐灵武风电场 | D20: 大唐灵武新能源有限公司 | E20: 大唐灵武新能源有限公司远景 1.5MW 双馈风机叶片增效关键技术成果项目合同 | F20: 202411 | G20: 1044000 | H20: 1044000 | I20: 0 | J20: 19155.96 | L20: 19155.96 | M20: 1149.36 | N20: 1915.6 | O20: vat于11期抵减 | P20: cit于12期已抵减
A21: 21 | B21: 内蒙古 | C21: 内蒙古自治区巴彦淖尔市乌拉特后旗获格琦苏木 | D21: 乌拉特后旗鸿晟风能有限公司 | E21: 巴彦淖尔风电场项目 EPC 总承包采购合同 | F21: 202412 | G21: 8.5441747e+08 | H21: 8.5441747e+08 | I21: 1.9607146e+08 | J21: 12079743 | L21: 12079743 | M21: 724784.59 | N21: 1567738.5 | O21: vat于11期抵减 | P21: cit于12期已抵减
A22: 22 | B22: 安徽 | C22: 定远县经济开发区 | D22: 定远纳驰风力发电有限公司 | E22: 安徽定远欣月(四期)工程项目 EPC 总承包采购合同 | F22: 202501 | G22: 2.4527143e+08 | H22: 2.4527143e+08 | I22: 0 | J22: 4500393.3 | L22: 4500393.3 | M22: 450039.33 | N22: 450039.33 | O22: vat于12期抵减 | P22: cit于3期已抵减
A23: 23 | B23: 安徽 | C23: 定远县定远经济开发区 | D23: 定远纳风风力发电有限公司 | E23: 安徽定远乘风(三期)工程项目EPC总承包采购合同 | F23: 202501 | G23: 4.0040972e+08 | H23: 4.0040972e+08 | I23: 0 | J23: 7346967.4 | L23: 7346967.4 | M23: 734696.74 | N23: 734696.74 | O23: vat于12期抵减 | P23: cit于3期已抵减
A24: 24 | B24: 新疆 | C24: 和田市吐哈 | D24: 中国石油天然气股份有限公司吐哈油田分公司 | E24: 吐哈油田 | F24: 202503 | G24: 996000 | H24: 74202.84 | L24: 1361.52 | M24: 136.16 | N24: 136.15 | O24: VAT于所属期3月已经申报抵减，所属期12月已抵减 | P24: cit于3期已抵减
A25: 25 | B25: 安徽 | C25: 定远县界牌集镇 | D25: 定远智贮能源科技有限公司 | E25: 远景定远智慧储能共享电站项目 EPC | F25: 202503 | G25: 33400000 | H25: 33777021 | I25: 32228107 | L25: 28420.44 | M25: 2842.04 | N25: 61976.18 | O25: VAT于所属期3月已经申报抵减，所属期12月已抵减 | P25: cit于3期已抵减
A26: 26 | B26: 安徽 | C26: 定边县红柳沟镇白兴庄 | D26: 定边远边汇新能源有限公司 | E26: 定边白兴庄风电场项目 EPC 总承包采购合同 | F26: 202504 | G26: 334431000 | H26: 2.4145974e+08 | I26: 1.2058601e+08 | L26: 2217866.5 | M26: 221786.66 | N26: 443045.39 | O26: VAT于所属期4月申报抵减，所属期12月已抵减 | P26: cit于6月已抵减
C27: 河北省邯郸市鸡泽县 | D27: 招银金融租赁有限公司 | E27: 利豪鸡泽县50MW保障类风电场项目EPC工程总承包合同 | F27: 2025.05 | H27: 94089440 | I27: 94089440 | N27: 172641.17 | P27: cit于6月已抵减
C28: 乌海市乌达区五虎山街道 | E28: 乌海市金湖独立储能电站项目EPC总承 包合同 | F28: 2025.05 | H28: 52845244 | I28: 17135388 | L28: 655226.71 | M28: 78627.2 | N28: 96963.75 | O28: VAT于所属期5月申报抵减，所属期12月已抵减 | P28: cit于6月已抵减
D29: 滨州远凌新能源有限责任公司 | E29: 滨州北海储能电站项目 | F29: 2025.06 | G29: 70000000 | H29: 32605568 | I29: 31810310 | L29: 14591.89 | M29: 1459.19 | N29: 59826.73 | O29: VAT于所属期6月申报抵减，所属期12月已抵减 | P29: cit于6月已抵减
D30: 清水河县云景风力发电有限公 司 | E30: 清水河县城关分散式风电场项目EPC总承包 | F30: 2025.06 | G30: 56655857 | H30: 33841798 | I30: 13772187 | L30: 368249.74 | M30: 36824.97 | N30: 62095.04 | O30: VAT于所属期6月申报抵减，所属期12月已抵减 | P30: cit于6月已抵减
C31: 盐城市射阳县射阳港经济开发区护堆河西侧 | E31: 射阳汇智风电场项目 EPC 总承包采购合同 | F31: 2025.7 | H31: 53763780 | I31: 53763780 | N31: 98649.14 | P31: cit于9月已抵减
A32: 2025.8 | C32: 陕西省榆林市靖边县东南部天赐湾乡 | E32: 靖边县状泽城河100兆瓦风电场项目EPC工程总承包合同 | F32: 2025.8 | H32: 198507000 | I32: 1.9213143e+08 | L32: 116982.96 | N32: 364233.03 | O32: VAT于所属期8月申报抵减，所属期12月已抵减 | P32: cit于9月已抵减
A33: 2025.09 | C33: 内蒙古自治区乌兰察布市察哈尔右翼后旗 | E33: 源荷互动绿色大数据中心示范项目EPC总承包采购合同 | F33: 2025.09 | H33: 1.5750358e+08 | I33: 6938155.2 | K33: 13813.341 | L33: 2762668.3 | M33: 276266.83 | N33: 288997.39 | O33: VAT于所属期9月申报抵减，所属期12月已抵减 | P33: cit于9月已抵减
C34: 江苏省盐城市射阳县射阳港经济开发区 | E34: 远景能源射阳样机拆除改造 EPC 总承包 | F34: 202512 | H34: 3370207.3 | I34: 3135076.5 | L34: 4314.33 | M34: 431.44 | N34: 6183.87 | O34: VAT于所属期12月已抵减 | P34: cit于12月已抵减
C35: 内蒙古自治区呼和浩特市武川县哈乐镇卜圪素村 | E35: 呼和浩特武川 100 万千瓦/400 万千瓦时独立储能电站项目 EPC 总承包采购合 | F35: 202512 | H35: 10684188 | I35: 10231192 | L35: 8311.86 | M35: 831.19 | N35: 19604.01
C36: 甘肃省武威市民勤县红沙岗镇 | E36: 景威民勤10万千瓦风电项目EPC总承包采购 同 | F36: 202512 | H36: 1.4264438e+08 | I36: 60075768 | L36: 1515020.4 | M36: 151502.04 | N36: 261732.81
C37: 鄂尔多斯伊金霍洛旗红庆河镇 | E37: 远景鄂尔多斯零碳产业园样机项目EPC总承包采购合同 | F37: 202512 | H37: 6397101.4 | I37: 6323584.1 | L37: 1348.94 | M37: 67.45 | N37: 11737.8
C38: 鄂尔多斯伊金霍洛旗红庆河镇 | E38: 远景鄂尔多斯零碳产业园样机项目EPC总承包采购合同 | F38: 202512 | H38: 6228102.9 | I38: 6215792 | L38: 225.89 | M38: 11.29 | N38: 11427.71
C39: 定远县安徽省滁州市定远县定城镇靠山路与连江路交叉口 | E39: 远景能源定远万家风电场升压站消缺工程 | F39: 202601 | H39: 514605.35 | L39: 9442.3 | N39: 944.23 | O39: VAT于所属期01月申报抵减 | P39: cit于3月抵减
C40: 江苏省盐城市射阳县射阳港经济开发区 | E40: 远景能源射阳样机增补拆除吊装 EPC 总承包采购合同 | F40: 202601 | H40: 1888374.9 | I40: 1566000 | L40: 5915.14 | N40: 3464.91
C41: 江苏省盐城市射阳县射阳港经济开发区 | E41: 远景能源射阳样机拆机吊装EPC总承包采购合同 | F41: 202601 | H41: 7109191.2 | I41: 5320034.2 | L41: 32828.57 | N41: 13044.39
C42: 江苏省盐城市射阳县射阳港经济开发区 | E42: 远景能源射阳样机拆除改造 EPC 总承包采购合同 | F42: 202601 | H42: 11797106 | I42: 9108212.2 | L42: 49337.49 | N42: 21646.07
J44: 本期抵减预缴 | L44: =SUM(L39:L42) -> 97523.5
J46: 2025年累计预缴 | L46: =SUM(L22:L38) -> 19541950 | N46: =SUM(N22:N38) -> 3143986.2

Sheet PL附表-项目公司
A1: 项目公司PL附表
A2: 拆分依据 | B2: 主营业务收入 | C2: 销项
A3: A | B3: 15371.42
A4: B | B4: 4569869.6
A5: C
A6: D

Sheet 增值税进项认证清单
A1: 发票清单 | B1: 发票清单 | C1: 发票清单 | D1: 发票清单 | E1: 发票清单 | F1: 发票清单 | G1: 发票清单 | H1: 发票清单 | I1: 发票清单 | J1: 发票清单 | K1: 发票清单 | L1: 发票清单 | M1: 发票清单 | N1: 发票清单 | O1: 发票清单 | P1: 发票清单 | Q1: 发票清单 | R1: 发票清单 | S1: 发票清单
A2: 纳税人识别号 | B2: 91150627MA7JDD6F4F | E2: 税款所属期 | F2: 202502 | H2: 纳税人名称 | I2: 伊金霍洛旗悦盛新能源有限公司
A3: 序号 | B3: 勾选状态 | C3: 发票来源 | D3: 转内销证明编号 | E3: 数电票号码 | F3: 发票代码 | G3: 发票号码 | H3: 开票日期 | I3: 销售方纳税人识别号 | J3: 销售方纳税人名称 | K3: 金额 | L3: 税额 | M3: 有效抵扣税额 | N3: 票种 | O3: 票种标签 | P3: 发票状态 | Q3: 勾选时间 | R3: 发票风险等级 | S3: 风险状态
A4: 1 | B4: 已勾选 | C4: 电子发票服务平台 | E4: 25342000000021849078 | H4: 2025-02-08 18:05:42 | I4: 91340700MA8PUEPEXD | J4: 薪班班（安徽）网络科技有限公司 | K4: 5771.94 | L4: 346.32 | M4: 346.32 | N4: 数电票(增值税专用发票) | O4: 增值税专用发票 | P4: 正常 | Q4: 2025-03-10 14:11:27 | R4: 正常 | S4: 无风险
A5: 合计 | K5: 1979092.2 | L5: 142670.14 | M5: 142670.14

Sheet 增值税销项 
A1: 序号 | B1: 发票代码 | C1: 发票号码 | D1: 数电发票号码 | E1: 销方识别号 | F1: 销方名称 | G1: 购方识别号 | H1: 购买方名称 | I1: 开票日期 | J1: 税收分类编码 | K1: 特定业务类型 | L1: 货物或应税劳务名称 | M1: 规格型号 | N1: 单位 | O1: 数量 | P1: 单价 | Q1: 金额 | R1: 税率 | S1: 税额 | T1: 价税合计 | U1: 发票来源 | V1: 发票票种 | W1: 发票状态 | X1: 是否正数发票 | Y1: 发票风险等级 | Z1: 开票人 | AA1: 备注
A2: 1 | D2: 25312000000440783357 | E2: 91310105MA1FW25C2F | F2: 上海睿景能源科技有限公司 | G2: 91320281673004487B | H2: 远景能源有限公司 | I2: 2025-12-31 17:53:08 | J2: 3040602990000000000 | L2: *鉴证咨询服务*咨询服务* | M2: 无 | N2: 项 | O2: 1 | P2: 74704.1037735849 | Q2: 74704.1 | R2: 6% | S2: 4482.25 | T2: 79186.35 | U2: 电子发票服务平台 | V2: 数电发票（增值税专用发票） | W2: 正常 | X2: 是 | Y2: 正常 | Z2: 胡杰
A3: 2 | D3: 25312000000439661122 | E3: 91310105MA1FW25C2F | F3: 上海睿景能源科技有限公司 | G3: 91150403MA7MK1BK5F | H3: 远景零碳技术（赤峰）有限公司 | I3: 2025-12-31 10:57:11 | J3: 3040602990000000000 | L3: *鉴证咨询服务*咨询服务 | M3: 无 | N3: 项 | O3: 1 | P3: 65705.72 | Q3: 65705.72 | R3: 6% | S3: 3942.34 | T3: 69648.06 | U3: 电子发票服务平台 | V3: 数电发票（增值税专用发票） | W3: 正常 | X3: 是 | Y3: 正常 | Z3: 胡杰 | AA3: 项目名称：赤峰市风光制氢一体化项目-赤峰翁牛特旗P1-850
A4: 3 | D4: 25312000000439659989 | E4: 91310105MA1FW25C2F | F4: 上海睿景能源科技有限公司 | G4: 91150223MACJF88R1P | H4: 内蒙古远景绿色新材料有限公司 | I4: 2025-12-31 10:57:08 | J4: 3040602990000000000 | L4: *鉴证咨询服务*咨询服务 | M4: 无 | N4: 项 | O4: 1 | P4: 47786.02 | Q4: 47786.02 | R4: 6% | S4: 2867.16 | T4: 50653.18 | U4: 电子发票服务平台 | V4: 数电发票（增值税专用发票） | W4: 正常 | X4: 是 | Y4: 正常 | Z4: 胡杰 | AA4: 项目名称：零碳合金
A5: 4 | D5: 25312000000439660527 | E5: 91310105MA1FW25C2F | F5: 上海睿景能源科技有限公司 | G5: 91150403MA7MK1BK5F | H5: 远景零碳技术（赤峰）有限公司 | I5: 2025-12-31 10:57:05 | J5: 3040602990000000000 | L5: *鉴证咨询服务*咨询服务 | M5: 无 | N5: 项 | O5: 1 | P5: 31788.38 | Q5: 31788.38 | R5: 6% | S5: 1907.3 | T5: 33695.68 | U5: 电子发票服务平台 | V5: 数电发票（增值税专用发票） | W5: 正常 | X5: 是 | Y5: 正常 | Z5: 胡杰 | AA5: 项目名称：赤峰市风光制氢一体化项目-赤峰翁牛特旗P1-375-风电
A6: 5 | D6: 25312000000439514492 | E6: 91310105MA1FW25C2F | F6: 上海睿景能源科技有限公司 | G6: 91320281673004487B | H6: 远景能源有限公司 | I6: 2025-12-31 10:13:46 | J6: 3040301010000000000 | L6: *设计服务*工程设计服务 | M6: 无 | N6: 项 | O6: 1 | P6: 1736477.51 | Q6: 1736477.5 | R6: 6% | S6: 104188.66 | T6: 1840666.2 | U6: 电子发票服务平台 | V6: 数电发票（增值税专用发票） | W6: 正常 | X6: 是 | Y6: 正常 | Z6: 胡杰
A8: 按税率（征收率）统计表 | B8: 按税率（征收率）统计表 | C8: 按税率（征收率）统计表 | D8: 按税率（征收率）统计表 | E8: 按税率（征收率）统计表 | F8: 按税率（征收率）统计表 | G8: 按税率（征收率）统计表 | H8: 按税率（征收率）统计表 | I8: 按税率（征收率）统计表 | J8: 按税率（征收率）统计表 | K8: 按税率（征收率）统计表 | L8: 按税率（征收率）统计表 | M8: 按税率（征收率）统计表 | N8: 按税率（征收率）统计表
A9: 纳税人识别号： | B9: 91310105MA1FW25C2F
A10: 纳税人名称： | B10: 上海睿景能源科技有限公司
A11: 查询月份： | B11: 2025年12月-2025年12月
A12: 序号 | B12: 发票种类 | C12: 税率/征收率 | D12: 开具蓝字发票金额 | E12: 开具蓝字发票税额 | F12: 作废蓝字发票金额 | G12: 作废蓝字发票税额 | H12: 开具红字发票金额 | I12: 开具红字发票税额 | J12: 作废红字发票金额 | K12: 作废红字发票税额 | L12: 实际开具发票金额 | M12: 实际开具发票税额 | N12: 统计日期
A13: 1 | B13: 电子发票（增值税专用发票） | C13: 0.06 | D13: 20383591.90 | E13: 1223015.54 | F13: 0.00 | G13: 0.00 | H13: -118090.27 | I13: -7085.42 | J13: 0.00 | K13: 0.00 | L13: 20265502 | M13: 1215930.1 | N13: 2025-12-31 23:03:39
A14: 2 | B14: 电子发票（增值税专用发票） | C14: 0.13 | D14: 854194844.02 | E14: 111045329.72 | F14: 0.00 | G14: 0.00 | H14: 0.00 | I14: 0.00 | J14: 0.00 | K14: 0.00 | L14: 8.5419484e+08 | M14: 1.1104533e+08 | N14: 2025-12-29 22:55:00
A15: 3 | B15: 电子发票（增值税专用发票） | C15: 0.09 | D15: 220186683.55 | E15: 19816801.55 | F15: 0.00 | G15: 0.00 | H15: 0.00 | I15: 0.00 | J15: 0.00 | K15: 0.00 | L15: 2.2018668e+08 | M15: 19816802 | N15: 2025-12-30 22:59:06
A16: 4 | B16: 合计 | D16: 1094765119.47 | E16: 132085146.81 | F16: 0.00 | G16: 0.00 | H16: -118090.27 | I16: -7085.42 | J16: 0.00 | K16: 0.00 | L16: 1.094647e+09 | M16: 1.3207806e+08

Sheet BS附表
A1: 公司 | B1: 总账科目 | C1: 短文本 | D1: 货币 | E1: 已结转余额 | F1: 累计余额
A2: 2320 | B2: 2221010100 | D2: RMB
B3: 2221010200
B4: 2221010300
B5: 2221010400

Sheet 合同印花税明细台账
B1: 序号 | C1: 季度 | D1: 单号/合同编码 | E1: 供应商 | F1: 合同内容 | G1: 合同金额 （含税） | H1: 税率 | I1: 合同金额 | J1: 印花税税目 | K1: 印花税税率 | L1: 应纳税额（元） | M1: 优惠比例 | N1: 实缴税额（元） | O1: 申报日期
D2: 全生命周期合计 | G2: =+G3 -> 1.7224981e+08 | I2: =+I3 -> 1.5859816e+08 | L2: =+L3 -> 46139.395 | N2: =+N3 -> 46139.395
D3: 2025年Q3季度 | G3: =SUM(G4:G39) -> 1.7224981e+08 | I3: =SUM(I4:I39) -> 1.5859816e+08 | L3: =SUM(L4:L39) -> 46139.395 | N3: =SUM(N4:N39) -> 46139.395
B4: 1 | C4: Q3 | D4: 9210225667 | E4: V3833-中国人民财产保险股份有限公司上海市分公司 | F4: 2025-09-01-鄂尔多斯零碳产业园500MW风光储一体化示范项目-样机光伏建工一切险延期20250829-20251231 | G4: 13519.99 | H4: 0.06 | I4: =ROUND(G4/(1+H4),2) -> 12754.71 | J4: 财产保险合同 | K4: =IFERROR(VLOOKUP(J4,[114]印花税税目汇总!$B$1:$D$16,3,0),"") -> 0.001 | L4: =IFERROR(K4*I4,0) -> 12.75471 | N4: {=IFERROR(_xlfn.IFS(M4>0%,L4*M4,M4=0,L4*1),0)} -> 12.75471
B5: 2 | C5: Q3 | D5: 9210224380 | E5: V3833-中国人民财产保险股份有限公司上海市分公司 | F5: 2025-08-26-鄂尔多斯零碳产业园500MW风光储一体化示范项目-建筑工程一切险延期（20250101-20250430） | G5: 349933.15 | H5: 0.06 | I5: =ROUND(G5/(1+H5),2) -> 330125.61 | J5: 财产保险合同 | K5: =IFERROR(VLOOKUP(J5,[114]印花税税目汇总!$B$1:$D$16,3,0),"") -> 0.001 | L5: =IFERROR(K5*I5,0) -> 330.12561 | N5: {=IFERROR(_xlfn.IFS(M5>0%,L5*M5,M5=0,L5*1),0)} -> 330.12561
B6: 3 | C6: Q3 | D6: 9720012871 | E6: V6371-北京神州汽车租赁有限公司 | F6: 2025-08-05-鄂尔多斯零碳产业园500MW风光储一体化示范项目-长租车采购申请 | G6: 11388 | H6: 0.13 | I6: =ROUND(G6/(1+H6),2) -> 10077.88 | J6: 租赁合同 | K6: =IFERROR(VLOOKUP(J6,[114]印花税税目汇总!$B$1:$D$16,3,0),"") -> 0.001 | L6: =IFERROR(K6*I6,0) -> 10.07788 | N6: {=IFERROR(_xlfn.IFS(M6>0%,L6*M6,M6=0,L6*1),0)} -> 10.07788
B7: 4 | C7: Q3 | D7: 9210214629 | E7: V3833-中国人民财产保险股份有限公司上海市分公司 | F7: 2025-07-07-生产部-景元站-零碳46万保险 | G7: 74246.19 | H7: 0.06 | I7: =ROUND(G7/(1+H7),2) -> 70043.58 | J7: 财产保险合同 | K7: =IFERROR(VLOOKUP(J7,[114]印花税税目汇总!$B$1:$D$16,3,0),"") -> 0.001 | L7: =IFERROR(K7*I7,0) -> 70.04358 | N7: {=IFERROR(_xlfn.IFS(M7>0%,L7*M7,M7=0,L7*1),0)} -> 70.04358
B8: 5 | C8: Q3 | D8: 9720012772 | E8: V6371-北京神州汽车租赁有限公司 | F8: 2025-07-04-鄂尔多斯零碳产业园500MW风光储一体化示范项目-临租车采购申请 | G8: 7840.78 | H8: 0.13 | I8: =ROUND(G8/(1+H8),2) -> 6938.74 | J8: 租赁合同 | K8: =IFERROR(VLOOKUP(J8,[114]印花税税目汇总!$B$1:$D$16,3,0),"") -> 0.001 | L8: =IFERROR(K8*I8,0) -> 6.93874 | N8: {=IFERROR(_xlfn.IFS(M8>0%,L8*M8,M8=0,L8*1),0)} -> 6.93874
B9: 6 | C9: Q3 | D9: OFPCN44702025092500012 | E9: 郑州普荣汽车服务有限公司 | F9: 2025-09-25-鄂尔多斯零碳产业园500MW风光储一体化示范项目-租用四驱坦克一辆 | G9: 25235 | H9: 0.01 | I9: =ROUND(G9/(1+H9),2) -> 24985.15 | J9: 租赁合同 | K9: =IFERROR(VLOOKUP(J9,[114]印花税税目汇总!$B$1:$D$16,3,0),"") -> 0.001 | L9: =IFERROR(K9*I9,0) -> 24.98515 | N9: {=IFERROR(_xlfn.IFS(M9>0%,L9*M9,M9=0,L9*1),0)} -> 24.98515
B10: 7 | C10: Q3 | D10: OFPCN44702025090700003 | E10: 杜在兰 | F10: 2025-09-07-鄂尔多斯零碳产业园500MW风光储一体化示范项目-租房两间 | G10: 8748 | H10: 0 | I10: =ROUND(G10/(1+H10),2) -> 8748 | J10: 租赁合同 | K10: =IFERROR(VLOOKUP(J10,[114]印花税税目汇总!$B$1:$D$16,3,0),"") -> 0.001 | L10: =IFERROR(K10*I10,0) -> 8.748 | N10: {=IFERROR(_xlfn.IFS(M10>0%,L10*M10,M10=0,L10*1),0)} -> 8.748
B11: 8 | C11: Q3 | D11: XNCN44702025092100654 | E11: 中国移动通信集团内蒙古有限公司鄂尔多斯分公司 | F11: 鄂尔多斯零碳项目景元站26年固话付款申请 | G11: 1200 | H11: 0.06 | I11: =ROUND(G11/(1+H11),2) -> 1132.08 | K11: =IFERROR(VLOOKUP(J11,[114]印花税税目汇总!$B$1:$D$16,3,0),"") | L11: =IFERROR(K11*I11,0) -> 0 | N11: {=IFERROR(_xlfn.IFS(M11>0%,L11*M11,M11=0,L11*1),0)} -> 0
B12: 9 | C12: Q3 | D12: XNCN44702025092300785 | E12: 远景能源有限公司 | F12: 鄂尔多斯零碳产业园 （景元站）2025年8月份变电运维服务费付款申请 | G12: 86615.91 | H12: 0.06 | I12: =ROUND(G12/(1+H12),2) -> 81713.12 | J12: 承揽合同 | K12: =IFERROR(VLOOKUP(J12,[114]印花税税目汇总!$B$1:$D$16,3,0),"") -> 0.0003 | L12: =IFERROR(K12*I12,0) -> 24.513936 | N12: {=IFERROR(_xlfn.IFS(M12>0%,L12*M12,M12=0,L12*1),0)} -> 24.513936
B13: 10 | C13: Q3 | D13: XNCN44702025092500836 | E13: 上海风韵汽车租赁有限公司 | F13: 零碳项目景元站8月车辆付款申请 | G13: 11755.65 | H13: 0.09 | I13: =ROUND(G13/(1+H13),2) -> 10785 | J13: 运输合同 | K13: =IFERROR(VLOOKUP(J13,[114]印花税税目汇总!$B$1:$D$16,3,0),"") -> 0.0003 | L13: =IFERROR(K13*I13,0) -> 3.2355 | N13: {=IFERROR(_xlfn.IFS(M13>0%,L13*M13,M13=0,L13*1),0)} -> 3.2355
B14: 11 | C14: Q3 | D14: XNCN44702025092300794 | E14: 中国移动通信集团内蒙古有限公司鄂尔多斯分公司 | F14: 鄂尔多斯零碳项目昌渠站26年固话付款申请 | G14: 1200 | H14: 0.06 | I14: =ROUND(G14/(1+H14),2) -> 1132.08 | K14: =IFERROR(VLOOKUP(J14,[114]印花税税目汇总!$B$1:$D$16,3,0),"") | L14: =IFERROR(K14*I14,0) -> 0 | N14: {=IFERROR(_xlfn.IFS(M14>0%,L14*M14,M14=0,L14*1),0)} -> 0
B15: 12 | C15: Q3 | D15: XNCN44702025092300774 | E15: 远景能源有限公司 | F15: 伊金霍洛旗零碳项目2025年8月份变电运维服务费付款申请 | G15: 1946.3 | H15: 0.06 | I15: =ROUND(G15/(1+H15),2) -> 1836.13 | J15: 承揽合同 | K15: =IFERROR(VLOOKUP(J15,[114]印花税税目汇总!$B$1:$D$16,3,0),"") -> 0.0003 | L15: =IFERROR(K15*I15,0) -> 0.550839 | N15: {=IFERROR(_xlfn.IFS(M15>0%,L15*M15,M15=0,L15*1),0)} -> 0.550839
B16: 13 | C16: Q3 | D16: XNCN44702025092500834 | E16: 上海风韵汽车租赁有限公司 | F16: 零碳项目悦盛昌渠站8月车辆付款申请 | G16: 12300.65 | H16: 0.09 | I16: =ROUND(G16/(1+H16),2) -> 11285 | J16: 运输合同 | K16: =IFERROR(VLOOKUP(J16,[114]印花税税目汇总!$B$1:$D$16,3,0),"") -> 0.0003 | L16: =IFERROR(K16*I16,0) -> 3.3855 | N16: {=IFERROR(_xlfn.IFS(M16>0%,L16*M16,M16=0,L16*1),0)} -> 3.3855
B17: 14 | C17: Q3 | D17: XNCN44702025092300798 | E17: 中国移动通信集团内蒙古有限公司鄂尔多斯分公司 | F17: 鄂尔多斯零碳项目昌渠站26年专网付款申请 | G17: 28800 | H17: 0.06 | I17: =ROUND(G17/(1+H17),2) -> 27169.81 | K17: =IFERROR(VLOOKUP(J17,[114]印花税税目汇总!$B$1:$D$16,3,0),"") | L17: =IFERROR(K17*I17,0) -> 0 | N17: {=IFERROR(_xlfn.IFS(M17>0%,L17*M17,M17=0,L17*1),0)} -> 0
B18: 15 | C18: Q3 | D18: XNCN44702025092300796 | E18: 中国移动通信集团内蒙古有限公司鄂尔多斯分公司 | F18: 鄂尔多斯零碳项目景元站26年专网付款申请 | G18: 28800 | H18: 0.06 | I18: =ROUND(G18/(1+H18),2) -> 27169.81 | K18: =IFERROR(VLOOKUP(J18,[114]印花税税目汇总!$B$1:$D$16,3,0),"") | L18: =IFERROR(K18*I18,0) -> 0 | N18: {=IFERROR(_xlfn.IFS(M18>0%,L18*M18,M18=0,L18*1),0)} -> 0
B19: 16 | C19: Q3 | D19: XNCN44702025092300781 | E19: 远景能源有限公司 | F19: 鄂尔多斯零碳产业园500MW风光储一体化示范项目二期46万项目2025年8月变电运维服务费付款申请 | G19: 552501.56 | H19: 0.06 | I19: =ROUND(G19/(1+H19),2) -> 521227.89 | J19: 承揽合同 | K19: =IFERROR(VLOOKUP(J19,[114]印花税税目汇总!$B$1:$D$16,3,0),"") -> 0.0003 | L19: =IFERROR(K19*I19,0) -> 156.36837 | N19: {=IFERROR(_xlfn.IFS(M19>0%,L19*M19,M19=0,L19*1),0)} -> 156.36837
B20: 17 | C20: Q3 | D20: XNCN44702025091600374 | E20: 上海峙雄新能源科技有限公司 | F20: 鄂尔多斯零碳产业园项目生态员工2025年8月工资 | G20: 60797.58 | H20: 0.06 | I20: =ROUND(G20/(1+H20),2) -> 57356.21 | K20: =IFERROR(VLOOKUP(J20,[114]印花税税目汇总!$B$1:$D$16,3,0),"") | L20: =IFERROR(K20*I20,0) -> 0 | N20: {=IFERROR(_xlfn.IFS(M20>0%,L20*M20,M20=0,L20*1),0)} -> 0
B21: 18 | C21: Q3 | D21: XNCN44702025071600441 | E21: 上海峙雄新能源科技有限公司 | F21: 鄂尔多斯零碳产业园项目生态员工2025年6月工资 | G21: 31565.09 | H21: 0.06 | I21: =ROUND(G21/(1+H21),2) -> 29778.39 | K21: =IFERROR(VLOOKUP(J21,[114]印花税税目汇总!$B$1:$D$16,3,0),"") | L21: =IFERROR(K21*I21,0) -> 0 | N21: {=IFERROR(_xlfn.IFS(M21>0%,L21*M21,M21=0,L21*1),0)} -> 0
B22: 19 | C22: Q3 | D22: XNCN44702025090300054 | E22: 内蒙古电力（集团）有限责任公司鄂尔多斯供电分公司 | F22: 零碳46万项目下网电费预存20万 | G22: 200000 | H22: 0.13 | I22: =ROUND(G22/(1+H22),2) -> 176991.15 | K22: =IFERROR(VLOOKUP(J22,[114]印花税税目汇总!$B$1:$D$16,3,0),"") | L22: =IFERROR(K22*I22,0) -> 0 | N22: {=IFERROR(_xlfn.IFS(M22>0%,L22*M22,M22=0,L22*1),0)} -> 0
B23: 20 | C23: Q3 | D23: XNCN44702025082000568 | E23: 远景能源有限公司 | F23: 伊金霍洛旗零碳项目2025年7月份变电运维服务费付款申请 | G23: 72691.55 | H23: 0.06 | I23: =ROUND(G23/(1+H23),2) -> 68576.93 | J23: 承揽合同 | K23: =IFERROR(VLOOKUP(J23,[114]印花税税目汇总!$B$1:$D$16,3,0),"") -> 0.0003 | L23: =IFERROR(K23*I23,0) -> 20.573079 | N23: {=IFERROR(_xlfn.IFS(M23>0%,L23*M23,M23=0,L23*1),0)} -> 20.573079
B24: 21 | C24: Q3 | D24: XNCN44702025081900558 | E24: 远景能源有限公司 | F24: 鄂尔多斯零碳产业园 （景元站）2025年7月份变电运维服务费付款申请 | G24: 96881.86 | H24: 0.06 | I24: =ROUND(G24/(1+H24),2) -> 91397.98 | J24: 承揽合同 | K24: =IFERROR(VLOOKUP(J24,[114]印花税税目汇总!$B$1:$D$16,3,0),"") -> 0.0003 | L24: =IFERROR(K24*I24,0) -> 27.419394 | N24: {=IFERROR(_xlfn.IFS(M24>0%,L24*M24,M24=0,L24*1),0)} -> 27.419394
B25: 22 | C25: Q3 | D25: XNCN44702025081500369 | E25: 上海峙雄新能源科技有限公司 | F25: 鄂尔多斯零碳产业园项目生态员工2025年7月工资 | G25: 31380.65 | H25: 0.06 | I25: =ROUND(G25/(1+H25),2) -> 29604.39 | K25: =IFERROR(VLOOKUP(J25,[114]印花税税目汇总!$B$1:$D$16,3,0),"") | L25: =IFERROR(K25*I25,0) -> 0 | N25: {=IFERROR(_xlfn.IFS(M25>0%,L25*M25,M25=0,L25*1),0)} -> 0
B26: 23 | C26: Q3 | D26: XNCN44702025090200045 | E26: 内蒙古电力(集团)有限责任公司鄂尔多斯供电分公司 | F26: 鄂尔多斯零碳产业昌渠站农网电费预存10000 | G26: 10000 | H26: 0.13 | I26: =ROUND(G26/(1+H26),2) -> 8849.56 | K26: =IFERROR(VLOOKUP(J26,[114]印花税税目汇总!$B$1:$D$16,3,0),"") | L26: =IFERROR(K26*I26,0) -> 0 | N26: {=IFERROR(_xlfn.IFS(M26>0%,L26*M26,M26=0,L26*1),0)} -> 0
B27: 24 | C27: Q3 | D27: XNCN44702025081300269 | E27: 中国石油天然气股份有限公司内蒙古鄂尔多斯市销售分公司 | F27: 20250813鄂尔多斯零碳产业园500MW风光储一体化项目车辆加油卡充值支付申请 | G27: 5000 | H27: 0.13 | I27: =ROUND(G27/(1+H27),2) -> 4424.78 | K27: =IFERROR(VLOOKUP(J27,[114]印花税税目汇总!$B$1:$D$16,3,0),"") | L27: =IFERROR(K27*I27,0) -> 0 | N27: {=IFERROR(_xlfn.IFS(M27>0%,L27*M27,M27=0,L27*1),0)} -> 0
B28: 25 | C28: Q3 | D28: XNCN44702025082000566 | E28: 远景能源有限公司 | F28: 鄂尔多斯零碳产业园500MW风光储一体化示范项目二期46万项目2025年7月变电运维服务费付款申请 | G28: 207333.26 | H28: 0.06 | I28: =ROUND(G28/(1+H28),2) -> 195597.42 | J28: 承揽合同 | K28: =IFERROR(VLOOKUP(J28,[114]印花税税目汇总!$B$1:$D$16,3,0),"") -> 0.0003 | L28: =IFERROR(K28*I28,0) -> 58.679226 | N28: {=IFERROR(_xlfn.IFS(M28>0%,L28*M28,M28=0,L28*1),0)} -> 58.679226
B29: 26 | C29: Q3 | D29: XNCN44702025071400338 | E29: 远景能源有限公司 | F29: 鄂尔多斯零碳产业园 （景元站）2025年6月份变电运维服务费付款申请 | G29: 69209.22 | H29: 0.06 | I29: =ROUND(G29/(1+H29),2) -> 65291.72 | J29: 承揽合同 | K29: =IFERROR(VLOOKUP(J29,[114]印花税税目汇总!$B$1:$D$16,3,0),"") -> 0.0003 | L29: =IFERROR(K29*I29,0) -> 19.587516 | N29: {=IFERROR(_xlfn.IFS(M29>0%,L29*M29,M29=0,L29*1),0)} -> 19.587516
B30: 27 | C30: Q3 | D30: XNCN44702025071400352 | E30: 远景能源有限公司 | F30: 伊金霍洛旗零碳项目2025年6月份变电运维服务费付款申请 | G30: 53251.08 | H30: 0.06 | I30: =ROUND(G30/(1+H30),2) -> 50236.87 | J30: 承揽合同 | K30: =IFERROR(VLOOKUP(J30,[114]印花税税目汇总!$B$1:$D$16,3,0),"") -> 0.0003 | L30: =IFERROR(K30*I30,0) -> 15.071061 | N30: {=IFERROR(_xlfn.IFS(M30>0%,L30*M30,M30=0,L30*1),0)} -> 15.071061
B31: 28 | C31: Q3 | D31: XNCN44702025080800178 | E31: 鄂尔多斯市财政局 | F31: 鄂尔多斯零碳46万项目样机企业行政处罚付款（市能源局）（付款备注：鄂尔多斯零碳50万项目企业罚款缴纳） | G31: 5180800 | H31: 0 | I31: =ROUND(G31/(1+H31),2) -> 5180800 | K31: =IFERROR(VLOOKUP(J31,[114]印花税税目汇总!$B$1:$D$16,3,0),"") | L31: =IFERROR(K31*I31,0) -> 0 | N31: {=IFERROR(_xlfn.IFS(M31>0%,L31*M31,M31=0,L31*1),0)} -> 0
B32: 29 | C32: Q3 | D32: XNCN44702025070800144 | E32: 内蒙古电力（集团）有限 责任公司鄂尔多斯供电分公司 | F32: 零碳46万项目下网电费预存20万 | G32: 200000 | H32: 0.13 | I32: =ROUND(G32/(1+H32),2) -> 176991.15 | K32: =IFERROR(VLOOKUP(J32,[114]印花税税目汇总!$B$1:$D$16,3,0),"") | L32: =IFERROR(K32*I32,0) -> 0 | N32: {=IFERROR(_xlfn.IFS(M32>0%,L32*M32,M32=0,L32*1),0)} -> 0
B33: 30 | C33: Q3 | D33: XNCN44702025080700138 | E33: 王卓 | F33: 鄂尔多斯零碳46万项目样机项目负责人行政处罚付款（市能源局） | G33: 30000 | H33: 0 | I33: =ROUND(G33/(1+H33),2) -> 30000 | K33: =IFERROR(VLOOKUP(J33,[114]印花税税目汇总!$B$1:$D$16,3,0),"") | L33: =IFERROR(K33*I33,0) -> 0 | N33: {=IFERROR(_xlfn.IFS(M33>0%,L33*M33,M33=0,L33*1),0)} -> 0
B34: 31 | C34: Q3 | D34: XNCN44702025080700141 | E34: 王尧 | F34: 鄂尔多斯零碳46万项目样机企业负责人行政处罚付款（市能源局） | G34: 30000 | H34: 0 | I34: =ROUND(G34/(1+H34),2) -> 30000 | K34: =IFERROR(VLOOKUP(J34,[114]印花税税目汇总!$B$1:$D$16,3,0),"") | L34: =IFERROR(K34*I34,0) -> 0 | N34: {=IFERROR(_xlfn.IFS(M34>0%,L34*M34,M34=0,L34*1),0)} -> 0
B35: 32 | C35: Q3 | D35: XNCN44702025071400329 | E35: 远景能源有限公司 | F35: 鄂尔多斯零碳产业园500MW风光储一体化示范项目二期46万项目2025年6月变电运维服务费付款申请 | G35: 150658.54 | H35: 0.06 | I35: =ROUND(G35/(1+H35),2) -> 142130.7 | J35: 承揽合同 | K35: =IFERROR(VLOOKUP(J35,[114]印花税税目汇总!$B$1:$D$16,3,0),"") -> 0.0003 | L35: =IFERROR(K35*I35,0) -> 42.63921 | N35: {=IFERROR(_xlfn.IFS(M35>0%,L35*M35,M35=0,L35*1),0)} -> 42.63921
B36: 33 | C36: Q3 | D36: XNCN44702025071300262 | E36: 伊金霍洛旗自然资源局 | F36: 鄂尔多斯零碳产业园配电网输变电项目景元变电站契税、印花税缴纳 | G36: 100688.31 | H36: 0 | I36: =ROUND(G36/(1+H36),2) -> 100688.31 | K36: =IFERROR(VLOOKUP(J36,[114]印花税税目汇总!$B$1:$D$16,3,0),"") | L36: =IFERROR(K36*I36,0) -> 0 | N36: {=IFERROR(_xlfn.IFS(M36>0%,L36*M36,M36=0,L36*1),0)} -> 0
B37: 34 | C37: Q3 | D37: N.A. | E37: 睿景能源科技有限公司 | F37: EPC总包（设备） | G37: 33060828 | H37: 0.13 | I37: =ROUND(G37/(1+H37),2) -> 29257370 | J37: 买卖合同 （动产买卖合同，不包括个人书立） | K37: =IFERROR(VLOOKUP(J37,[114]印花税税目汇总!$B$1:$D$16,3,0),"") -> 0.0003 | L37: =IFERROR(K37*I37,0) -> 8777.2109 | N37: {=IFERROR(_xlfn.IFS(M37>0%,L37*M37,M37=0,L37*1),0)} -> 8777.2109
B38: 35 | C38: Q3 | D38: N.A. | E38: 睿景能源科技有限公司 | F38: EPC总包（建安） | G38: 86562204 | H38: 0.09 | I38: =ROUND(G38/(1+H38),2)+0.02 -> 79414866 | J38: 建设工程合同 | K38: =IFERROR(VLOOKUP(J38,[114]印花税税目汇总!$B$1:$D$16,3,0),"") -> 0.0003 | L38: =IFERROR(K38*I38,0) -> 23824.46 | N38: {=IFERROR(_xlfn.IFS(M38>0%,L38*M38,M38=0,L38*1),0)} -> 23824.46
B39: 36 | C39: Q3 | D39: N.A. | E39: 睿景能源科技有限公司 | F39: EPC总包（服务） | G39: 44880494 | H39: 0.06 | I39: =ROUND(G39/(1+H39),2)+0.01 -> 42340089 | J39: 建设工程合同 | K39: =IFERROR(VLOOKUP(J39,[114]印花税税目汇总!$B$1:$D$16,3,0),"") -> 0.0003 | L39: =IFERROR(K39*I39,0) -> 12702.027 | N39: {=IFERROR(_xlfn.IFS(M39>0%,L39*M39,M39=0,L39*1),0)} -> 12702.027
D40: 2025年Q4季度 | G40: =SUM(G41:G84) -> 65184054 | I40: =SUM(I41:I84) -> 57721010 | L40: =SUM(L41:L84) -> 17195.256 | N40: =SUM(N41:N84) -> 17195.256
C41: Q4 | D41: 9720013246 | E41: 北京神州汽车租赁有限公司 | F41: 2025-11-18-鄂尔多斯零碳产业园500MW风光储一体化示范项目-项目租车ETC费用采购申请 | G41: =ROUND(I41*(1+H41),2) -> 466.31 | H41: 0.13 | I41: 412.66 | J41: 租赁合同 | K41: =IFERROR(VLOOKUP(J41,[114]印花税税目汇总!$B$1:$D$16,3,0),"") -> 0.001 | L41: =IFERROR(K41*I41,0) -> 0.41266 | N41: {=IFERROR(_xlfn.IFS(M41>0%,L41*M41,M41=0,L41*1),0)} -> 0.41266
C42: Q4 | D42: 9720013225 | E42: 薪班班（安徽）网络科技有限公司 | F42: 2025-11-05-生产部-零碳46万(昌渠)-鄂尔多斯零碳项目昌渠站厨师招聘 | G42: =ROUND(I42*(1+H42),2) -> 6059.56 | H42: 0.06 | I42: 5716.57 | K42: =IFERROR(VLOOKUP(J42,[114]印花税税目汇总!$B$1:$D$16,3,0),"") | L42: =IFERROR(K42*I42,0) -> 0 | N42: {=IFERROR(_xlfn.IFS(M42>0%,L42*M42,M42=0,L42*1),0)} -> 0
C43: Q4 | D43: 9720013223 | E43: 北京神州汽车租赁有限公司 | F43: 2025-11-17-生产部-景元站-10月短租车 | G43: =ROUND(I43*(1+H43),2) -> 1097.9 | H43: 0.13 | I43: 971.59 | J43: 租赁合同 | K43: =IFERROR(VLOOKUP(J43,[114]印花税税目汇总!$B$1:$D$16,3,0),"") -> 0.001 | L43: =IFERROR(K43*I43,0) -> 0.97159 | N43: {=IFERROR(_xlfn.IFS(M43>0%,L43*M43,M43=0,L43*1),0)} -> 0.97159
C44: Q4 | D44: 9720013224 | E44: 北京神州汽车租赁有限公司 | F44: 2025-11-17-生产部-景元站-10月短租车 | G44: =ROUND(I44*(1+H44),2) -> 1614 | H44: 0.13 | I44: 1428.32 | J44: 租赁合同 | K44: =IFERROR(VLOOKUP(J44,[114]印花税税目汇总!$B$1:$D$16,3,0),"") -> 0.001 | L44: =IFERROR(K44*I44,0) -> 1.42832 | N44: {=IFERROR(_xlfn.IFS(M44>0%,L44*M44,M44=0,L44*1),0)} -> 1.42832
C45: Q4 | D45: 9720013173 | E45: 北京神州汽车租赁有限公司 | F45: 2025-09-25-生产部-零碳46万(昌渠)-零碳项目，昌渠站租车 | G45: =ROUND(I45*(1+H45),2) -> 3796 | H45: 0.13 | I45: 3359.29 | J45: 租赁合同 | K45: =IFERROR(VLOOKUP(J45,[114]印花税税目汇总!$B$1:$D$16,3,0),"") -> 0.001 | L45: =IFERROR(K45*I45,0) -> 3.35929 | N45: {=IFERROR(_xlfn.IFS(M45>0%,L45*M45,M45=0,L45*1),0)} -> 3.35929
C46: Q4 | D46: 9720013151 | E46: 薪班班（安徽）网络科技有限公司 | F46: 2025-10-10-生产部-零碳46万(昌渠)-零碳项目，昌渠站司机招聘 | G46: =ROUND(I46*(1+H46),2) -> 4766.12 | H46: 0.06 | I46: 4496.34 | K46: =IFERROR(VLOOKUP(J46,[114]印花税税目汇总!$B$1:$D$16,3,0),"") | L46: =IFERROR(K46*I46,0) -> 0 | N46: {=IFERROR(_xlfn.IFS(M46>0%,L46*M46,M46=0,L46*1),0)} -> 0
C47: Q4 | D47: OFPCN44702025102800025 | E47: 内蒙古国友工程检测服务有限公司 | F47: 2025-10-28-生产部-景元站-防雷检测 | G47: 11154 | H47: 0.06 | I47: =ROUND(G47/(1+H47),2) -> 10522.64 | J47: 技术合同 | K47: =IFERROR(VLOOKUP(J47,[114]印花税税目汇总!$B$1:$D$16,3,0),"") -> 0.0003 | L47: =IFERROR(K47*I47,0) -> 3.156792 | N47: {=IFERROR(_xlfn.IFS(M47>0%,L47*M47,M47=0,L47*1),0)} -> 3.156792
C48: Q4 | D48: OFPCN44702025102800024 | E48: 内蒙古国友工程检测服务有限公司 | F48: 2025-10-28-生产部-零碳46万(昌渠)-防雷检测 | G48: 77113 | H48: 0.06 | I48: =ROUND(G48/(1+H48),2) -> 72748.11 | J48: 技术合同 | K48: =IFERROR(VLOOKUP(J48,[114]印花税税目汇总!$B$1:$D$16,3,0),"") -> 0.0003 | L48: =IFERROR(K48*I48,0) -> 21.824433 | N48: {=IFERROR(_xlfn.IFS(M48>0%,L48*M48,M48=0,L48*1),0)} -> 21.824433
C49: Q4 | D49: OFPCN44702025101900004 | E49: 内蒙古思沃科技有限公司 | F49: 2025-10-19-生产部-景元站-电力监控系统等级保护测评及安全防护评估 | G49: 22500 | H49: 0.06 | I49: =ROUND(G49/(1+H49),2) -> 21226.42 | J49: 技术合同 | K49: =IFERROR(VLOOKUP(J49,[114]印花税税目汇总!$B$1:$D$16,3,0),"") -> 0.0003 | L49: =IFERROR(K49*I49,0) -> 6.367926 | N49: {=IFERROR(_xlfn.IFS(M49>0%,L49*M49,M49=0,L49*1),0)} -> 6.367926
C50: Q4 | D50: OFPCN44702025101900003 | E50: 内蒙古思沃科技有限公司 | F50: 2025-10-19-生产部-零碳46万(昌渠)-电力监控系统等级保护测评及安全防护评估 | G50: 45000 | H50: 0.06 | I50: =ROUND(G50/(1+H50),2) -> 42452.83 | J50: 技术合同 | K50: =IFERROR(VLOOKUP(J50,[114]印花税税目汇总!$B$1:$D$16,3,0),"") -> 0.0003 | L50: =IFERROR(K50*I50,0) -> 12.735849 | N50: {=IFERROR(_xlfn.IFS(M50>0%,L50*M50,M50=0,L50*1),0)} -> 12.735849
C51: Q4 | D51: OFPCN44702025101400020 | E51: 上海远景科创智能科技有限公司 | F51: 2025-10-14-生产部-零碳46万(昌渠)-场站智能一体化软硬件部署 | G51: 751000 | H51: 0.13 | I51: =ROUND(G51/(1+H51),2) -> 664601.77 | J51: 买卖合同 （动产买卖合同，不包括个人书立） | K51: =IFERROR(VLOOKUP(J51,[114]印花税税目汇总!$B$1:$D$16,3,0),"") -> 0.0003 | L51: =IFERROR(K51*I51,0) -> 199.38053 | N51: {=IFERROR(_xlfn.IFS(M51>0%,L51*M51,M51=0,L51*1),0)} -> 199.38053
C52: Q4 | D52: XNCN44702025100900028 | E52: 中国石油天然气股份有限公司内蒙古鄂尔多斯市销售分公司 | F52: 20251009鄂尔多斯零碳产业园500MW风光储一体化项目车辆加油卡充值支付申请 | G52: 5000 | H52: 0.13 | I52: =ROUND(G52/(1+H52),2) -> 4424.78 | K52: =IFERROR(VLOOKUP(J52,[114]印花税税目汇总!$B$1:$D$16,3,0),"") | L52: =IFERROR(K52*I52,0) -> 0 | N52: {=IFERROR(_xlfn.IFS(M52>0%,L52*M52,M52=0,L52*1),0)} -> 0
C53: Q4 | D53: XNCN44702025110900260 | E53: 远景能源有限公司 | F53: 鄂尔多斯零碳产业园500MW风光储一体化示范项目二期46万项目2025年9月变电运维服务费付款申请 | G53: 3796.2 | H53: 0.06 | I53: =ROUND(G53/(1+H53),2) -> 3581.32 | J53: 承揽合同 | K53: =IFERROR(VLOOKUP(J53,[114]印花税税目汇总!$B$1:$D$16,3,0),"") -> 0.0003 | L53: =IFERROR(K53*I53,0) -> 1.074396 | N53: {=IFERROR(_xlfn.IFS(M53>0%,L53*M53,M53=0,L53*1),0)} -> 1.074396
C54: Q4 | D54: XNCN44702025110900262 | E54: 远景能源有限公司 | F54: 伊金霍洛旗零碳项目2025年9月份变电运维服务费付款申请 | G54: 3334.87 | H54: 0.06 | I54: =ROUND(G54/(1+H54),2) -> 3146.1 | J54: 承揽合同 | K54: =IFERROR(VLOOKUP(J54,[114]印花税税目汇总!$B$1:$D$16,3,0),"") -> 0.0003 | L54: =IFERROR(K54*I54,0) -> 0.94383 | N54: {=IFERROR(_xlfn.IFS(M54>0%,L54*M54,M54=0,L54*1),0)} -> 0.94383
C55: Q4 | D55: XNCN44702025111100391 | E55: 远景能源有限公司 | F55: 鄂尔多斯零碳产业园500MW风光储一体化示范项目二期46万项目2025年10月变电运维服务费付款申请 | G55: 1644.01 | H55: 0.06 | I55: =ROUND(G55/(1+H55),2) -> 1550.95 | J55: 承揽合同 | K55: =IFERROR(VLOOKUP(J55,[114]印花税税目汇总!$B$1:$D$16,3,0),"") -> 0.0003 | L55: =IFERROR(K55*I55,0) -> 0.465285 | N55: {=IFERROR(_xlfn.IFS(M55>0%,L55*M55,M55=0,L55*1),0)} -> 0.465285
C56: Q4 | D56: XNCN44702025111200401 | E56: 上海风韵汽车租赁有限公司 | F56: 零碳项目悦盛昌渠站9月车辆付款申请 | G56: 11903.85 | H56: 0.09 | I56: =ROUND(G56/(1+H56),2) -> 10920.96 | J56: 运输合同 | K56: =IFERROR(VLOOKUP(J56,[114]印花税税目汇总!$B$1:$D$16,3,0),"") -> 0.0003 | L56: =IFERROR(K56*I56,0) -> 3.276288 | N56: {=IFERROR(_xlfn.IFS(M56>0%,L56*M56,M56=0,L56*1),0)} -> 3.276288
C57: Q4 | D57: XNCN44702025111100393 | E57: 远景能源有限公司 | F57: 鄂尔多斯零碳产业园 （景元站）2025年10月份变电运维服务费付款申请 | G57: 660.4 | H57: 0.06 | I57: =ROUND(G57/(1+H57),2) -> 623.02 | J57: 承揽合同 | K57: =IFERROR(VLOOKUP(J57,[114]印花税税目汇总!$B$1:$D$16,3,0),"") -> 0.0003 | L57: =IFERROR(K57*I57,0) -> 0.186906 | N57: {=IFERROR(_xlfn.IFS(M57>0%,L57*M57,M57=0,L57*1),0)} -> 0.186906
C58: Q4 | D58: XNCN44702025111100389 | E58: 远景能源有限公司 | F58: 伊金霍洛旗零碳项目2025年10月份变电运维服务费付款申请 | G58: 86 | H58: 0.06 | I58: =ROUND(G58/(1+H58),2) -> 81.13 | J58: 承揽合同 | K58: =IFERROR(VLOOKUP(J58,[114]印花税税目汇总!$B$1:$D$16,3,0),"") -> 0.0003 | L58: =IFERROR(K58*I58,0) -> 0.024339 | N58: {=IFERROR(_xlfn.IFS(M58>0%,L58*M58,M58=0,L58*1),0)} -> 0.024339
C59: Q4 | D59: XNCN44702025111700628 | E59: 上海峙雄新能源科技有限公司 | F59: 鄂尔多斯零碳产业园项目生态员工2025年10月工资 | G59: 60543.38 | H59: 0.06 | I59: =ROUND(G59/(1+H59),2) -> 57116.4 | K59: =IFERROR(VLOOKUP(J59,[114]印花税税目汇总!$B$1:$D$16,3,0),"") | L59: =IFERROR(K59*I59,0) -> 0 | N59: {=IFERROR(_xlfn.IFS(M59>0%,L59*M59,M59=0,L59*1),0)} -> 0
C60: Q4 | D60: XNCN44702025111200403 | E60: 上海风韵汽车租赁有限公司 | F60: 零碳项目景元站9月车辆付款申请 | G60: 11455.9 | H60: 0.09 | I60: =ROUND(G60/(1+H60),2) -> 10510 | J60: 运输合同 | K60: =IFERROR(VLOOKUP(J60,[114]印花税税目汇总!$B$1:$D$16,3,0),"") -> 0.0003 | L60: =IFERROR(K60*I60,0) -> 3.153 | N60: {=IFERROR(_xlfn.IFS(M60>0%,L60*M60,M60=0,L60*1),0)} -> 3.153
C61: Q4 | D61: XNCN44702025110900257 | E61: 远景能源有限公司 | F61: 鄂尔多斯零碳产业园 （景元站）2025年9月份变电运维服务费付款申请 | G61: 3965.46 | H61: 0.06 | I61: =ROUND(G61/(1+H61),2) -> 3741 | J61: 承揽合同 | K61: =IFERROR(VLOOKUP(J61,[114]印花税税目汇总!$B$1:$D$16,3,0),"") -> 0.0003 | L61: =IFERROR(K61*I61,0) -> 1.1223 | N61: {=IFERROR(_xlfn.IFS(M61>0%,L61*M61,M61=0,L61*1),0)} -> 1.1223
C62: Q4 | D62: XNCN44702025101400250 | E62: 上海峙雄新能源科技有限公司 | F62: 鄂尔多斯零碳产业园项目生态员工2025年9月工资 | G62: 61283.78 | H62: 0.06 | I62: =ROUND(G62/(1+H62),2) -> 57814.89 | K62: =IFERROR(VLOOKUP(J62,[114]印花税税目汇总!$B$1:$D$16,3,0),"") | L62: =IFERROR(K62*I62,0) -> 0 | N62: {=IFERROR(_xlfn.IFS(M62>0%,L62*M62,M62=0,L62*1),0)} -> 0
C63: Q4 | D63: XNCN44702025101800420 | E63: 中国石油天然气股份有限公司内蒙古鄂尔多斯市销售分公司 | F63: 鄂尔多斯零碳项目昌渠站燃油卡充值申请 | G63: 10000 | H63: 0.13 | I63: =ROUND(G63/(1+H63),2) -> 8849.56 | K63: =IFERROR(VLOOKUP(J63,[114]印花税税目汇总!$B$1:$D$16,3,0),"") | L63: =IFERROR(K63*I63,0) -> 0 | N63: {=IFERROR(_xlfn.IFS(M63>0%,L63*M63,M63=0,L63*1),0)} -> 0
C64: Q4 | D64: XNCN44702025120900405 | E64: 内蒙古电力(集团)有限责任公司鄂尔多斯供电分公司 | F64: 鄂尔多斯零碳产业景元站农网电费预存20000 | G64: 20000 | H64: 0.13 | I64: =ROUND(G64/(1+H64),2) -> 17699.12 | K64: =IFERROR(VLOOKUP(J64,[114]印花税税目汇总!$B$1:$D$16,3,0),"") | L64: =IFERROR(K64*I64,0) -> 0 | N64: {=IFERROR(_xlfn.IFS(M64>0%,L64*M64,M64=0,L64*1),0)} -> 0
C65: Q4 | D65: XNCN44702025121100494 | E65: 伊金霍洛旗自然资源局 | F65: 鄂尔多斯零碳产业园配电网输变电项目景元变电站城市配套费契税缴纳 | G65: 761.76 | H65: 0 | I65: =ROUND(G65/(1+H65),2) -> 761.76 | K65: =IFERROR(VLOOKUP(J65,[114]印花税税目汇总!$B$1:$D$16,3,0),"") | L65: =IFERROR(K65*I65,0) -> 0 | N65: {=IFERROR(_xlfn.IFS(M65>0%,L65*M65,M65=0,L65*1),0)} -> 0
C66: Q4 | D66: XNCN44702025121100490 | E66: 伊金霍洛旗财政局 | F66: 伊旗46万零碳产业园景元站城市基础设施配套费缴纳 | G66: 25391.85 | H66: 0 | I66: =ROUND(G66/(1+H66),2) -> 25391.85 | K66: =IFERROR(VLOOKUP(J66,[114]印花税税目汇总!$B$1:$D$16,3,0),"") | L66: =IFERROR(K66*I66,0) -> 0 | N66: {=IFERROR(_xlfn.IFS(M66>0%,L66*M66,M66=0,L66*1),0)} -> 0
C67: Q4 | D67: XNCN44702025112300902 | E67: 上海峙雄新能源科技有限公司 | F67: 鄂尔多斯零碳项目二期8月员工工资付款申请 | G67: 40809.5 | H67: 0.06 | I67: =ROUND(G67/(1+H67),2) -> 38499.53 | K67: =IFERROR(VLOOKUP(J67,[114]印花税税目汇总!$B$1:$D$16,3,0),"") | L67: =IFERROR(K67*I67,0) -> 0 | N67: {=IFERROR(_xlfn.IFS(M67>0%,L67*M67,M67=0,L67*1),0)} -> 0
C68: Q4 | D68: XNCN44702025112801750 | E68: 云南众协运维风电电力科技有限公司 | F68: 鄂尔多斯零碳项目二期10月员工工资付款申请 | G68: 14714.1 | H68: 0.06 | I68: =ROUND(G68/(1+H68),2) -> 13881.23 | K68: =IFERROR(VLOOKUP(J68,[114]印花税税目汇总!$B$1:$D$16,3,0),"") | L68: =IFERROR(K68*I68,0) -> 0 | N68: {=IFERROR(_xlfn.IFS(M68>0%,L68*M68,M68=0,L68*1),0)} -> 0
C69: Q4 | D69: XNCN44702025112801748 | E69: 山东博程新能源科技有限公司 | F69: 鄂尔多斯零碳项目二期10月员工工资付款申请 | G69: 10138.37 | H69: 0.06 | I69: =ROUND(G69/(1+H69),2) -> 9564.5 | K69: =IFERROR(VLOOKUP(J69,[114]印花税税目汇总!$B$1:$D$16,3,0),"") | L69: =IFERROR(K69*I69,0) -> 0 | N69: {=IFERROR(_xlfn.IFS(M69>0%,L69*M69,M69=0,L69*1),0)} -> 0
C70: Q4 | D70: XNCN44702025112701400 | E70: 山东博程新能源科技有限公司 | F70: 鄂尔多斯零碳项目二期9月员工工资付款申请 | G70: 10516.79 | H70: 0.06 | I70: =ROUND(G70/(1+H70),2) -> 9921.5 | K70: =IFERROR(VLOOKUP(J70,[114]印花税税目汇总!$B$1:$D$16,3,0),"") | L70: =IFERROR(K70*I70,0) -> 0 | N70: {=IFERROR(_xlfn.IFS(M70>0%,L70*M70,M70=0,L70*1),0)} -> 0
C71: Q4 | D71: XNCN44702025112701412 | E71: 上海峙雄新能源科技有限公司 | F71: 鄂尔多斯零碳项目一期10月员工工资付款申请 | G71: 10235.33 | H71: 0.06 | I71: =ROUND(G71/(1+H71),2) -> 9655.97 | K71: =IFERROR(VLOOKUP(J71,[114]印花税税目汇总!$B$1:$D$16,3,0),"") | L71: =IFERROR(K71*I71,0) -> 0 | N71: {=IFERROR(_xlfn.IFS(M71>0%,L71*M71,M71=0,L71*1),0)} -> 0
C72: Q4 | D72: XNCN44702025112300904 | E72: 山东博程新能源科技有限公司 | F72: 鄂尔多斯零碳项目二期8月员工工资付款申请 | G72: 11489.87 | H72: 0.06 | I72: =ROUND(G72/(1+H72),2) -> 10839.5 | K72: =IFERROR(VLOOKUP(J72,[114]印花税税目汇总!$B$1:$D$16,3,0),"") | L72: =IFERROR(K72*I72,0) -> 0 | N72: {=IFERROR(_xlfn.IFS(M72>0%,L72*M72,M72=0,L72*1),0)} -> 0
C73: Q4 | D73: XNCN44702025112300912 | E73: 云南众协运维风电电力科技有限公司 | F73: 鄂尔多斯零碳项目二期8月员工工资付款申请 | G73: 14899.6 | H73: 0.06 | I73: =ROUND(G73/(1+H73),2) -> 14056.23 | K73: =IFERROR(VLOOKUP(J73,[114]印花税税目汇总!$B$1:$D$16,3,0),"") | L73: =IFERROR(K73*I73,0) -> 0 | N73: {=IFERROR(_xlfn.IFS(M73>0%,L73*M73,M73=0,L73*1),0)} -> 0
... C79: Q4 | D79: XNCN44702025112701402 | E79: 上海峙雄新能源科技有限公司 | F79: 鄂尔多斯零碳项目二期9月员工工资付款申请 | G79: 33032.31 | H79: 0.06 | I79: =ROUND(G79/(1+H79),2) -> 31162.56 | K79: =IFERROR(VLOOKUP(J79,[114]印花税税目汇总!$B$1:$D$16,3,0),"") | L79: =IFERROR(K79*I79,0) -> 0 | N79: {=IFERROR(_xlfn.IFS(M79>0%,L79*M79,M79=0,L79*1),0)} -> 0
C80: Q4 | F80: 售电收入 | G80: =ROUND(I80*(1+H80),2) -> 63789903 | H80: 0.13 | I80: 56451242 | J80: 买卖合同 （动产买卖合同，不包括个人书立） | K80: =IFERROR(VLOOKUP(J80,[114]印花税税目汇总!$B$1:$D$16,3,0),"") -> 0.0003 | L80: =IFERROR(K80*I80,0) -> 16935.373 | N80: {=IFERROR(_xlfn.IFS(M80>0%,L80*M80,M80=0,L80*1),0)} -> 16935.373
L81: =IFERROR(K81*I81,0) -> 0 | N81: {=IFERROR(_xlfn.IFS(M81>0%,L81*M81,M81=0,L81*1),0)} -> 0
L82: =IFERROR(K82*I82,0) -> 0 | N82: {=IFERROR(_xlfn.IFS(M82>0%,L82*M82,M82=0,L82*1),0)} -> 0
N83: {=IFERROR(_xlfn.IFS(M83>0%,L83*M83,M83=0,L83*1),0)} -> 0

Sheet 睿景景程月结数据表-报税
A1: 1、取自：报税pt（筛选：月份）
A2: 2、核对：已开票收入+未开票收入=账面主营收入
C3: 建安 | J3: 设备 | Q3: 设计服务 | X3: 咨询服务-在建 | AE3: 咨询服务-在运 | AL3: 仓储保管
A4: 行标签 | B4: 项目代码 | C4: 成本 | D4: 收入 | E4: 销项 | F4: 已开票收入 | G4: 已开票税额 | H4: 未开票收入 | I4: 未开票税额 | J4: 成本 | K4: 收入 | L4: 销项 | M4: 已开票收入 | N4: 已开票税额 | O4: 未开票收入 | P4: 未开票税额 | Q4: 成本 | R4: 收入 | S4: 销项 | T4: 已开票收入 | U4: 已开票税额 | V4: 未开票收入 | W4: 未开票税额 | X4: 成本 | Y4: 收入 | Z4: 销项 | AA4: 已开票收入 | AB4: 已开票税额 | AC4: 未开票收入 | AD4: 未开票税额 | AE4: 成本 | AF4: 收入 | AG4: 销项 | AH4: 已开票收入 | AI4: 已开票税额 | AJ4: 未开票收入 | AK4: 未开票税额 | AL4: 收入 | AM4: 销项 | AN4: 已开票收入 | AO4: 已开票税额 | AP4: 未开票收入 | AQ4: 未开票税额
A5: 正镶白旗10万风电治沙项目 | B5: 4305 | M5: =SUMIFS([115]项目开票!L:L,[115]项目开票!A:A,'睿景景程月结数据表-报税'!A5) -> 0 | N5: =SUMIFS([115]项目开票!M:M,[115]项目开票!A:A,'睿景景程月结数据表-报税'!A5) -> 0 | O5: =K5-M5 -> 0 | P5: =L5-N5 -> 0 | T5: =SUMIFS([115]项目开票!F:F,[115]项目开票!A:A,'睿景景程月结数据表-报税'!A5) -> 0 | U5: =SUMIFS([115]项目开票!G:G,[115]项目开票!A:A,'睿景景程月结数据表-报税'!A5) -> 0 | V5: =R5-T5 -> 0 | W5: =S5-U5 -> 0 | AA5: =SUMIFS([115]项目开票!I:I,[115]项目开票!A:A,'睿景景程月结数据表-报税'!A5) -> 0 | AB5: =SUMIFS([115]项目开票!J:J,[115]项目开票!A:A,'睿景景程月结数据表-报税'!A5) -> 0 | AC5: =Y5-AA5 -> 0 | AD5: =Z5-AB5 -> 0 | AJ5: =AF5-AH5 -> 0 | AK5: =AG5-AI5 -> 0 | AP5: =AL5-AN5 -> 0 | AQ5: =AM5-AO5 -> 0
AJ6: =AF6-AH6 -> 0 | AK6: =AG6-AI6 -> 0 | AP6: =AL6-AN6 -> 0 | AQ6: =AM6-AO6 -> 0
AJ7: =AF7-AH7 -> 0 | AK7: =AG7-AI7 -> 0 | AP7: =AL7-AN7 -> 0 | AQ7: =AM7-AO7 -> 0
AJ8: =AF8-AH8 -> 0 | AK8: =AG8-AI8 -> 0 | AP8: =AL8-AN8 -> 0 | AQ8: =AM8-AO8 -> 0
AJ9: =AF9-AH9 -> 0 | AK9: =AG9-AI9 -> 0 | AP9: =AL9-AN9 -> 0 | AQ9: =AM9-AO9 -> 0
AJ10: =AF10-AH10 -> 0 | AK10: =AG10-AI10 -> 0 | AP10: =AL10-AN10 -> 0 | AQ10: =AM10-AO10 -> 0
AJ53: =AF53-AH53 -> 0 | AK53: =AG53-AI53 -> 0 | AP53: =AL53-AN53 -> 0 | AQ53: =AM53-AO53 -> 0
AF54: =SUM(AF5:AF53) -> 0 | AG54: =SUM(AG5:AG53) -> 0 | AH54: =SUM(AH5:AH53) -> 0 | AI54: =SUM(AI5:AI53) -> 0 | AJ54: =SUM(AJ5:AJ53) -> 0 | AK54: =SUM(AK5:AK53) -> 0 | AL54: =SUM(AL5:AL53) -> 0 | AM54: =SUM(AM5:AM53) -> 0 | ... AQ54: =SUM(AQ5:AQ53) -> 0
C57: =C54+J54+Q54+X54+AE54+C69 -> 0 | D57: =D54+K54+R54+Y54+AF54+AL54 -> 0 | E57: =E54+L54+S54+Z54+AG54+AM54 -> 0 | F57: =F54+M54+T54+AA54+AH54+AN54 -> 0 | G57: =G54+N54+U54+AB54+AI54+AO54 -> 0 | H57: =H54+O54+V54+AC54+AJ54 -> 0 | I57: =I54+P54+W54+AD54+AK54 -> 0
B59: CHECK | C59: =$C$57-[115]项目收入!$C$56 -> -1.4228968e+08 | D59: =$D$57-[115]项目收入!$D$56 -> -2.0861489e+08 | E59: =$E$57-[115]项目收入!$E$56 -> -19724935 | F59: =$F$54+$M$54+$T$54+$AA$54+$AH$54+$AN$54-$F$57 -> 0 | G59: =$G$57-[115]项目开票!$P$27 -> -36208944 | H59: =$D$57-[115]项目开票!$O$27-$H$57 -> -3.1478481e+08 | I59: =$E57-[115]项目开票!$P27-$I57 -> -36208944
E60: =E57-[115]账面应交税费金额!F8 -> -19724935
C61: 开票
F67: =F54-[115]项目开票!C27 -> -90583173 | M67: =M54-[115]项目开票!L27 -> -2.0863371e+08 | T67: =T54-[115]项目开票!F27 -> -15567934
A69: 总计 | B69: =SUM(B61:B66) -> 0

Sheet 预开票收入计提及冲回统计（2320、2355）
O2: 和账面差异
A3: 序号 | B3: 项目 | C3: 事项 | D3: 年份 | E3: 月份 | F3: 类别 | G3: 税率 | H3: 含税金额 | I3: 已申报预开票收入 | J3: 已申报预开票税金 | K3: 累计已实现收入 | L3: 累计已实现税金 | M3: 剩余预开票收入 | N3: 剩余预开票税金 | O3: 收入差异 | P3: 税金差异
A4: 1 | B4: 大业项目 | C4: 融资设备预开票 | D4: 2025 | E4: 8 | F4: 设备 | G4: 0.13 | H4: =I4+J4 -> 152393500 | I4: 1.348615e+08 | J4: 17531996 | K4: =I17 -> 1.348615e+08 | L4: =J17 -> 17531996 | M4: =I4-K4 -> 0 | N4: =J4-L4 -> 0 | O4: =M4 -> 0 | P4: =N4 -> 0
A5: 2 | B5: 综能-DHL项目 | C5: 综能项目预开票（账面已计提销项税，未计提收入） | D5: 2025 | E5: 8 | F5: 设备 | G5: 0.13 | H5: =I5+J5 -> 307587.79 | I5: 272201.58 | J5: 35386.21 | K5: =I30 -> 0 | L5: =J30 -> 0 | M5: =I5-K5 -> 272201.58 | N5: =J5-L5 -> 35386.21 | O5: =M5 -> 272201.58
D6: 2025 | E6: 8 | F6: 建安 | G6: 0.09 | H6: =I6+J6 -> 144108.51 | I6: 132209.64 | J6: 11898.87 | K6: =I31 -> 0 | L6: =J31 -> 0 | M6: =I6-K6 -> 132209.64 | N6: =J6-L6 -> 11898.87 | O6: =M6 -> 132209.64
D7: 2025 | E7: 8 | F7: 设计 | G7: 0.06 | H7: =I7+J7 -> 67442.21 | I7: 63624.73 | J7: 3817.48 | K7: =I32 -> 0 | L7: =J32 -> 0 | M7: =I7-K7 -> 63624.73 | N7: =J7-L7 -> 3817.48 | O7: =M7 -> 63624.73
A8: 3 | B8: 综能-射阳光伏车棚 | C8: 综能项目预开票（账面已计提销项税，未计提收入） | D8: 2025 | E8: 10 | F8: 建安 | G8: 0.09 | H8: =I8+J8 -> 430663.24 | I8: =3109166.81-2714062.92 -> 395103.89 | J8: 35559.35 | K8: =I43 -> 395103.89 | L8: =J43 -> 0 | M8: =I8-K8 -> 0 | N8: =J8-L8 -> 35559.35 | O8: =M8 -> 0
A9: 4 | B9: 五河项目 | C9: 融资设备预开票 | D9: 2025 | E9: 10 | F9: 设备 | G9: 0.13 | H9: =I9+J9 -> 1.797274e+08 | I9: 1.590508e+08 | J9: 20676604 | K9: =I54 -> 1.590508e+08 | L9: =J54 -> 20676604 | M9: =I9-K9 -> 0 | N9: =J9-L9 -> 0 | O9: =M9 -> 0 | P9: =N9 -> 0
N11: 小计 | O11: =SUM(O4:O10) -> 468035.95 | P11: =SUM(P4:P10) -> 0
A15: 序号 | B15: 项目 | C15: 事项 | D15: 年份 | E15: 月份 | F15: 类别 | G15: 税率 | H15: 含税金额 | I15: 已申报预开票收入 | J15: 已申报预开票税金
A16: 1 | B16: 大业项目 | C16: 税务申报预开票收入 | D16: 2025 | E16: 8 | F16: 设备 | G16: 0.13 | H16: =I16+J16 -> 152393500 | I16: 1.348615e+08 | J16: 17531996 | K16: =J16/I16 -> 0.13
C17: 账面已实现收入 | D17: / | E17: / | F17: 设备 | G17: 0.13 | H17: =I17+J17 -> 152393500 | I17: =I23 -> 1.348615e+08 | J17: =J23 -> 17531996 | K17: =J17/I17 -> 0.13
C19: 账面已确认收入明细 | D19: 2025 | E19: 10 | H19: =I19+J19 -> 12125499 | I19: 10730530 | J19: 1394968.9 | K19: =J19/I19 -> 0.13
D20: 2025 | E20: 11 | H20: =I20+J20 -> 1.40268e+08 | I20: 1.2413097e+08 | J20: 16137027
D23: 已确认合计 | H23: =SUM(H19:H22) -> 152393500 | I23: =SUM(I19:I22) -> 1.348615e+08 | J23: =SUM(J19:J22) -> 17531996
A26: 序号 | B26: 项目 | C26: 事项 | D26: 年份 | E26: 月份 | F26: 类别 | G26: 税率 | H26: 含税金额 | I26: 已申报预开票收入 | J26: 已申报预开票税金
A27: 2 | B27: 综能-DHL项目 | C27: 税务申报预开票收入 | D27: 2025 | E27: 8 | F27: 设备 | G27: 0.13 | H27: =I27+J27 -> 307587.79 | I27: 272201.58 | J27: 35386.21 | K27: =J27/I27 -> 0.13000002
D28: 2025 | E28: 8 | F28: 建安 | G28: 0.09 | H28: =I28+J28 -> 144108.51 | I28: 132209.64 | J28: 11898.87 | K28: =J28/I28 -> 0.090000018
D29: 2025 | E29: 8 | F29: 设计 | G29: 0.06 | H29: =I29+J29 -> 67442.21 | I29: 63624.73 | J29: 3817.48 | K29: =J29/I29 -> 0.05999994
C30: 账面已实现收入 | D30: / | E30: / | F30: 设备 | G30: 0.13 | H30: =I30+J30 -> 0
D31: / | E31: / | F31: 建安 | G31: 0.09 | H31: =I31+J31 -> 0
D32: / | E32: / | F32: 设计 | G32: 0.06 | H32: =I32+J32 -> 0 | I32: =I38 -> 0 | J32: =J38 -> 0
C34: 账面已确认收入明细 | D34: 2025 | E34: 10 | H34: =I34+J34 -> 0
L35: =J56+J20 -> 36813631
D38: 已确认合计 | H38: =SUM(H34:H37) -> 0 | I38: =SUM(I34:I37) -> 0 | J38: =SUM(J34:J37) -> 0
A41: 序号 | B41: 项目 | C41: 事项 | D41: 年份 | E41: 月份 | F41: 类别 | G41: 税率 | H41: 含税金额 | I41: 已申报预开票收入 | J41: 已申报预开票税金
A42: 3 | B42: 综能-射阳光伏车棚 | C42: 税务申报预开票收入 | D42: 2025 | E42: 10 | F42: 建安 | G42: 0.09 | H42: =I42+J42 -> 430663.24 | I42: =3109166.81-2714062.92 -> 395103.89 | J42: 35559.35 | K42: =J42/I42 -> 0.09
C43: 账面已实现收入 | D43: / | E43: / | F43: 建安 | G43: 0.09 | H43: =I43+J43 -> 395103.89 | I43: =I49 -> 395103.89 | J43: =J49 -> 0
C45: 账面已确认收入明细 | D45: 2025 | E45: 11 | H45: =I45+J45 -> 395103.89 | I45: 395103.89
D49: 已确认合计 | H49: =SUM(H45:H48) -> 395103.89 | I49: =SUM(I45:I48) -> 395103.89 | J49: =SUM(J45:J48) -> 0
A52: 序号 | B52: 项目 | C52: 事项 | D52: 年份 | E52: 月份 | F52: 类别 | G52: 税率 | H52: 含税金额 | I52: 已申报预开票收入 | J52: 已申报预开票税金
A53: 4 | B53: 五河项目 | C53: 税务申报预开票收入 | D53: 2025 | E53: 10 | F53: 设备 | G53: 0.13 | H53: =I53+J53 -> 1.797274e+08 | I53: 1.590508e+08 | J53: 20676604 | K53: =J53/I53 -> 0.13
C54: 账面已实现收入 | D54: / | E54: / | F54: 设备 | G54: 0.13 | H54: =I54+J54 -> 1.797274e+08 | I54: =I60 -> 1.590508e+08 | J54: =J60 -> 20676604
C56: 账面已确认收入明细 | D56: 2025 | E56: 11 | H56: =I56+J56 -> 1.797274e+08 | I56: 1.590508e+08 | J56: 20676604
D60: 已确认合计 | H60: =SUM(H56:H59) -> 1.797274e+08 | I60: =SUM(I56:I59) -> 1.590508e+08 | J60: =SUM(J56:J59) -> 20676604

Sheet 公司代码配置表
A1: 公司代码 | B1: 公司名称 | C1: 财务BP_AD号 | D1: 财务BP | E1: 财务BP邮箱
A2: 必填 | B2: 必填 | C2: 非必填 | D2: 非必填 | E2: 非必填

Sheet 总账明细配置表
A1: 公司代码 | B1: 总账明细类别 | C1: 会计科目
A2: 非必填 | B2: 下拉选择： 销项明细、进项明细、所得税明细、收入明细、其他科目明细、企业所得税明细 | C2: 非必填
G18: 公司代码 | H18: 公司名称 | I18: 财务BP_AD号
G19: 必填 | H19: 必填 | I19: 非必填

Sheet 税目配置表
A1: 序号 | B1: 公司代码 | C1: 税种 | D1: 税目 | E1: 计税依据 | F1: 征收比例 | G1: 税率 | H1: 会计科目 | I1: 需缴税月份 | J1: 实际缴税月份
A2: 必填 | B2: 非必填 | C2: 必填 | D2: 必填 | E2: 必填 | F2: 必填 | G2: 必填 | H2: 非必填 | I2: 非必填、多选 | J2: 非必填、多选
A3: 1 | C3: 印花税合计 | H3: 6405000002
A4: 1.1 | C4: 印花税
A5: 2 | C5: 增值税合计
A6: 2.1 | C6: 增值税 | D6: 销项税额-主营业务收入 | H6: 2221010200
A7: 2.2 | C7: 增值税 | D7: 增值税进项税额 | H7: 2221010100
A8: 3 | C8: 企业所得税合计 | H8: 6801000000
A9: 3.1 | C9: 企业所得税
A10: 4 | C10: 城镇土地使用税 | H10: 6405000004
A11: 5 | C11: 房产税 | H11: 6405000003
A12: 6 | C12: 个人所得税合计
A13: 6.1 | C13: 个人所得税 | D13: 劳务报酬所得 | H13: 6600020002
A14: 6.2 | C14: 个人所得税 | D14: 劳务报酬所得（倒算） | H14: 6600020002
A15: 7 | C15: 残疾人保障金

Sheet 项目配置表
A1: 公司代码 | B1: 税种 | C1: 税目 | D1: 项目名称 | E1: 所属优惠期
A2: 必填 | B2: 必填 | C2: 非必填 | D2: 非必填 | E2: 必填
A3: 2320 | B3: 企业所得税 | C3: 企业所得税 | E3: 非风场项目，无优惠期
A4: 4470 | B4: 企业所得税 | C4: 企业所得税 | D4: 鄂尔多斯（2023-2025三免期） | E4: 减免期

Sheet 增值税变动表基础条目配置表
A1: 条目序号 | B1: 公司代码 | C1: 基础条目 | D1: 是否拆分 | E1: 是否显示
A2: 必填 | B2: 非必填 | C2: 必填 | D2: 必填 | E2: 必填
A3: 1 | C3: 当月利润表主营业务收入 | D3: Y | E3: Y
A4: 2 | C4: 固定资产处置收入 | D4: N
A5: 3 | C5: 销项税额-固定资产处置收入 | D5: N | E5: Y
A6: 4 | C6: 财务费用-利息收入 | D6: N
A7: 5 | C7: 销项税额-财务费用-利息收入 | D7: N | E7: Y
A8: 6 | B8: 2320、2355 | C8: 其他收益计税金额 | D8: N | E8: Y
A9: 7 | C9: 销项税额-其他收益 | D9: N | E9: Y
A10: 8 | C10: 应交增值税-销项税 | D10: Y | E10: Y
A11: 9 | C11: 预开票（未确认收入）-应交增值税 | D11: N | E11: Y
A12: 10 | C12: 增值税已认证进项税 | D12: N | E12: Y
A13: 11 | C13: 进项转出 | D13: Y | E13: Y
A14: 12 | C14: 期初留抵进项税 | D14: Y | E14: Y
A15: 13 | C15: 期末留抵进项税 | D15: Y | E15: Y
A16: 14 | C16: 应交增值税 | D16: Y | E16: Y
A17: 15 | B17: 2320、2355 | C17: 异地预缴抵减 | D17: N | E17: Y
A18: 16 | B18: 2320、2355 | C18: 本期应交增值税 | D18: N | E18: Y

Sheet 睿景、景程增值税变动表特殊条目配置表
A1: 条目序号 | B1: 公司代码 | C1: 特殊条目 | D1: 是否显示
A2: 必填 | B2: 必填，多选 | C2: 必填 | D2: 必填
A3: 1 | B3: 2320、2355 | C3: 当月利润表主营业务收入（商品销售13%） | D3: Y
A4: 1 | B4: 2320、2355 | C4: 当月利润表主营业务收入（商品销售13%-普票） | D4: Y
A5: 1 | B5: 2320、2355 | C5: 当月利润表主营业务收入（建安收入9%） | D5: Y
A6: 1 | B6: 2320、2355 | C6: 当月利润表主营业务收入（建安收入9%-普票） | D6: Y
A7: 1 | B7: 2320、2355 | C7: 当月利润表主营业务收入（设计服务6%） | D7: Y
A8: 1 | B8: 2320、2355 | C8: 当月利润表主营业务收入（设计服务6%-普票） | D8: Y
