Workbook
Name \A: #REF!
Name \e: #REF!
Name \p: #REF!
Name \s: #N/A
Name _: #REF!
Name _.xls: #REF!
Name _?: #N/A
Name _??????: #N/A
Name __: #REF!
Name __?: #N/A
Name __??????: #N/A
Name __aaa5: [3]六纺!#REF!
Name __k3: #REF!
Name __sc13: #REF!
Name _00104gz: #REF!
Name _002报表: #REF!
Name _002科目余额表: #REF!
Name _003报表: #REF!
Name _003科目余额表: #REF!
Name _003年12月辅料库: #REF!
Name _01.xls: #REF!
Name _010104501: #REF!
Name _02.xls: #REF!
Name _03.xls: #REF!
Name _1_?: #N/A
Name _11.xls: #REF!
Name _12.xls: #REF!
Name _121.dbf: #REF!
Name _1212002.dbf: #REF!
Name _13: #REF!
Name _17103.dbf: #REF!
Name _171032002.dbf: #REF!
Name _2: #REF!
Name _2_??????: #N/A
Name _2009: #REF!
Name _3¸ß¼ÛÖÜ×ª¼þ_¨º½²Ä¹ý¶É: #REF!
Name _3年12月: #REF!
Name _3年12月后勤库: #REF!
Name _4_04标准价: #REF!
Name _5_20011225: #REF!
Name _55154: #REF!
Name _8未还DB_查询: #REF!
Name _9_12_mo_cost: #REF!
Name _999年12月31日股份应收帐款.dbf: #REF!
Name _aaa5: [3]六纺!#REF!
Name _act411: #REF!
Name _act412: #REF!
Name _act413: #REF!
Name _act414: #REF!
Name _DAT1: #REF!
Name _DAT10: #REF!
Name _DAT11: #REF!
Name _DAT12: #REF!
Name _DAT13: [13]Sheet1!#REF!
Name _DAT14: [13]Sheet1!#REF!
Name _DAT15: [13]Sheet1!#REF!
Name _DAT16: [13]Sheet1!#REF!
Name _DAT2: #REF!
Name _DAT3: #REF!
Name _DAT4: #REF!

Sheet 报税
A1: 1、取自：报税pt（筛选：月份）
A2: 2、核对：已开票收入+未开票收入=账面主营收入
D3: 建安9% | K3: 设备13% | R3: 设计服务6% | Y3: 咨询服务-在建6% | AF3: 咨询服务-在运6% | AM3: 仓储保管6%
A4: 行标签 | B4: 项目代码 | C4: 业务类型 | D4: 成本 | E4: 收入 | F4: 销项 | G4: 已开票收入 | H4: 已开票税额 | I4: 未开票收入 | J4: 未开票税额 | K4: 成本 | L4: 收入 | M4: 销项 | N4: 已开票收入 | O4: 已开票税额 | P4: 未开票收入 | Q4: 未开票税额 | R4: 成本 | S4: 收入 | T4: 销项 | U4: 已开票收入 | V4: 已开票税额 | W4: 未开票收入 | X4: 未开票税额 | Y4: 成本 | Z4: 收入 | AA4: 销项 | AB4: 已开票收入 | AC4: 已开票税额 | AD4: 未开票收入 | AE4: 未开票税额 | AF4: 成本 | AG4: 收入 | AH4: 销项 | AI4: 已开票收入 | AJ4: 已开票税额 | AK4: 未开票收入 | AL4: 未开票税额 | AM4: 收入 | AN4: 销项 | AO4: 已开票收入 | AP4: 已开票税额 | AQ4: 未开票收入 | AR4: 未开票税额
A5: 安徽宣城郎溪 | B5: 2346 | C5: EPC | D5: 531538.49 | G5: =SUMIFS([1]项目开票!C:C,[1]项目开票!B:B,报税!B5,[1]项目开票!A:A,报税!A5) -> 0 | H5: =SUMIFS([1]项目开票!D:D,[1]项目开票!B:B,报税!B5,[1]项目开票!A:A,报税!A5) -> 0 | I5: =E5-G5 -> 0 | J5: =F5-H5 -> 0 | K5: -27787.63 | N5: =SUMIFS([1]项目开票!O:O,[1]项目开票!B:B,报税!B5,[1]项目开票!A:A,报税!A5) -> 0 | O5: =SUMIFS([1]项目开票!P:P,[1]项目开票!B:B,报税!B5,[1]项目开票!A:A,报税!A5) -> 0 | P5: =L5-N5 -> 0 | Q5: =M5-O5 -> 0 | R5: 525720 | U5: =SUMIFS([1]项目开票!F:F,[1]项目开票!B:B,报税!B5,[1]项目开票!A:A,报税!A5) -> 0 | V5: =SUMIFS([1]项目开票!G:G,[1]项目开票!B:B,报税!B5,[1]项目开票!A:A,报税!A5) -> 0 | W5: =S5-U5 -> 0 | X5: =T5-V5 -> 0 | AB5: =SUMIFS([1]项目开票!I:I,[1]项目开票!B:B,报税!B5,[1]项目开票!A:A,报税!A5) -> 0 | AC5: =SUMIFS([1]项目开票!J:J,[1]项目开票!B:B,报税!B5,[1]项目开票!A:A,报税!A5) -> 0 | AD5: =Z5-AB5 -> 0 | AE5: =AA5-AC5 -> 0 | AI5: =SUMIFS([1]项目开票!L:L,[1]项目开票!B:B,报税!B5,[1]项目开票!A:A,报税!A5) -> 0 | AJ5: =SUMIFS([1]项目开票!M:M,[1]项目开票!B:B,报税!B5,[1]项目开票!A:A,报税!A5) -> 0 | AK5: =AG5-AI5 -> 0 | AL5: =AH5-AJ5 -> 0 | AQ5: =AM5-AO5 -> 0 | AR5: =AN5-AP5 -> 0 | AS5: =G5+N5+U5+AB5+AI5+AO5 -> 0
A6: 安徽宣城郎溪 | B6: 安新县阔达有色金属熔炼有限公司 | C6: EPC | G6: =SUMIFS([1]项目开票!C:C,[1]项目开票!B:B,报税!B6,[1]项目开票!A:A,报税!A6) -> 0 | H6: =SUMIFS([1]项目开票!D:D,[1]项目开票!B:B,报税!B6,[1]项目开票!A:A,报税!A6) -> 0 | I6: =E6-G6 -> 0 | J6: =F6-H6 -> 0 | M6: 10584.07 | N6: =SUMIFS([1]项目开票!O:O,[1]项目开票!B:B,报税!B6,[1]项目开票!A:A,报税!A6) -> 81415.93 | O6: =SUMIFS([1]项目开票!P:P,[1]项目开票!B:B,报税!B6,[1]项目开票!A:A,报税!A6) -> 10584.07 | P6: =L6-N6 -> -81415.93 | Q6: =M6-O6 -> 0 | U6: =SUMIFS([1]项目开票!F:F,[1]项目开票!B:B,报税!B6,[1]项目开票!A:A,报税!A6) -> 0 | V6: =SUMIFS([1]项目开票!G:G,[1]项目开票!B:B,报税!B6,[1]项目开票!A:A,报税!A6) -> 0 | W6: =S6-U6 -> 0 | X6: =T6-V6 -> 0 | AB6: =SUMIFS([1]项目开票!I:I,[1]项目开票!B:B,报税!B6,[1]项目开票!A:A,报税!A6) -> 0 | AC6: =SUMIFS([1]项目开票!J:J,[1]项目开票!B:B,报税!B6,[1]项目开票!A:A,报税!A6) -> 0 | AD6: =Z6-AB6 -> 0 | AE6: =AA6-AC6 -> 0 | AI6: =SUMIFS([1]项目开票!L:L,[1]项目开票!B:B,报税!B6,[1]项目开票!A:A,报税!A6) -> 0 | AJ6: =SUMIFS([1]项目开票!M:M,[1]项目开票!B:B,报税!B6,[1]项目开票!A:A,报税!A6) -> 0 | AK6: =AG6-AI6 -> 0 | AL6: =AH6-AJ6 -> 0 | AQ6: =AM6-AO6 -> 0 | AR6: =AN6-AP6 -> 0 | AS6: =G6+N6+U6+AB6+AI6+AO6 -> 81415.93
A7: 内蒙赤峰零碳氢氨-赤峰元宝山 | B7: XC00 | C7: EPC | D7: 165863.18 | E7: 284666.26 | F7: 25619.96 | G7: =SUMIFS([1]项目开票!C:C,[1]项目开票!B:B,报税!B7,[1]项目开票!A:A,报税!A7) -> 0 | H7: =SUMIFS([1]项目开票!D:D,[1]项目开票!B:B,报税!B7,[1]项目开票!A:A,报税!A7) -> 0 | I7: =E7-G7 -> 284666.26 | J7: =F7-H7 -> 25619.96 | N7: =SUMIFS([1]项目开票!O:O,[1]项目开票!B:B,报税!B7,[1]项目开票!A:A,报税!A7) -> 0 | O7: =SUMIFS([1]项目开票!P:P,[1]项目开票!B:B,报税!B7,[1]项目开票!A:A,报税!A7) -> 0 | P7: =L7-N7 -> 0 | Q7: =M7-O7 -> 0 | U7: =SUMIFS([1]项目开票!F:F,[1]项目开票!B:B,报税!B7,[1]项目开票!A:A,报税!A7) -> 0 | V7: =SUMIFS([1]项目开票!G:G,[1]项目开票!B:B,报税!B7,[1]项目开票!A:A,报税!A7) -> 0 | W7: =S7-U7 -> 0 | X7: =T7-V7 -> 0 | AB7: =SUMIFS([1]项目开票!I:I,[1]项目开票!B:B,报税!B7,[1]项目开票!A:A,报税!A7) -> 0 | AC7: =SUMIFS([1]项目开票!J:J,[1]项目开票!B:B,报税!B7,[1]项目开票!A:A,报税!A7) -> 0 | AD7: =Z7-AB7 -> 0 | AE7: =AA7-AC7 -> 0 | AI7: =SUMIFS([1]项目开票!L:L,[1]项目开票!B:B,报税!B7,[1]项目开票!A:A,报税!A7) -> 0 | AJ7: =SUMIFS([1]项目开票!M:M,[1]项目开票!B:B,报税!B7,[1]项目开票!A:A,报税!A7) -> 0 | AK7: =AG7-AI7 -> 0 | AL7: =AH7-AJ7 -> 0 | AQ7: =AM7-AO7 -> 0 | AR7: =AN7-AP7 -> 0 | AS7: =G7+N7+U7+AB7+AI7+AO7 -> 0
A8: 内蒙武川 | B8: 3690 | C8: 已出售 | G8: =SUMIFS([1]项目开票!C:C,[1]项目开票!B:B,报税!B8,[1]项目开票!A:A,报税!A8) -> 0 | H8: =SUMIFS([1]项目开票!D:D,[1]项目开票!B:B,报税!B8,[1]项目开票!A:A,报税!A8) -> 0 | I8: =E8-G8 -> 0 | J8: =F8-H8 -> 0 | N8: =SUMIFS([1]项目开票!O:O,[1]项目开票!B:B,报税!B8,[1]项目开票!A:A,报税!A8) -> 0 | O8: =SUMIFS([1]项目开票!P:P,[1]项目开票!B:B,报税!B8,[1]项目开票!A:A,报税!A8) -> 0 | P8: =L8-N8 -> 0 | Q8: =M8-O8 -> 0 | R8: -23551097 | U8: =SUMIFS([1]项目开票!F:F,[1]项目开票!B:B,报税!B8,[1]项目开票!A:A,报税!A8) -> 0 | V8: =SUMIFS([1]项目开票!G:G,[1]项目开票!B:B,报税!B8,[1]项目开票!A:A,报税!A8) -> 0 | W8: =S8-U8 -> 0 | X8: =T8-V8 -> 0 | AB8: =SUMIFS([1]项目开票!I:I,[1]项目开票!B:B,报税!B8,[1]项目开票!A:A,报税!A8) -> 0 | AC8: =SUMIFS([1]项目开票!J:J,[1]项目开票!B:B,报税!B8,[1]项目开票!A:A,报税!A8) -> 0 | AD8: =Z8-AB8 -> 0 | AE8: =AA8-AC8 -> 0 | AI8: =SUMIFS([1]项目开票!L:L,[1]项目开票!B:B,报税!B8,[1]项目开票!A:A,报税!A8) -> 0 | AJ8: =SUMIFS([1]项目开票!M:M,[1]项目开票!B:B,报税!B8,[1]项目开票!A:A,报税!A8) -> 0 | AK8: =AG8-AI8 -> 0 | AL8: =AH8-AJ8 -> 0 | AQ8: =AM8-AO8 -> 0 | AR8: =AN8-AP8 -> 0 | AS8: =G8+N8+U8+AB8+AI8+AO8 -> 0
A9: 内蒙伊旗风光储 | B9: 4470 | C9: EPC | D9: 5147036 | E9: 5275711.8 | F9: 474814.06 | G9: =SUMIFS([1]项目开票!C:C,[1]项目开票!B:B,报税!B9,[1]项目开票!A:A,报税!A9) -> 0 | H9: =SUMIFS([1]项目开票!D:D,[1]项目开票!B:B,报税!B9,[1]项目开票!A:A,报税!A9) -> 0 | I9: =E9-G9 -> 5275711.8 | J9: =F9-H9 -> 474814.06 | K9: -2001509.9 | L9: -2051547.6 | M9: -266701.21 | N9: =SUMIFS([1]项目开票!O:O,[1]项目开票!B:B,报税!B9,[1]项目开票!A:A,报税!A9) -> 0 | O9: =SUMIFS([1]项目开票!P:P,[1]项目开票!B:B,报税!B9,[1]项目开票!A:A,报税!A9) -> 0 | P9: =L9-N9 -> -2051547.6 | Q9: =M9-O9 -> -266701.21 | R9: 22278469 | S9: 22835430 | T9: 1370125.8 | U9: =SUMIFS([1]项目开票!F:F,[1]项目开票!B:B,报税!B9,[1]项目开票!A:A,报税!A9) -> 0 | V9: =SUMIFS([1]项目开票!G:G,[1]项目开票!B:B,报税!B9,[1]项目开票!A:A,报税!A9) -> 0 | W9: =S9-U9 -> 22835430 | X9: =T9-V9 -> 1370125.8 | AB9: =SUMIFS([1]项目开票!I:I,[1]项目开票!B:B,报税!B9,[1]项目开票!A:A,报税!A9) -> 0 | AC9: =SUMIFS([1]项目开票!J:J,[1]项目开票!B:B,报税!B9,[1]项目开票!A:A,报税!A9) -> 0 | AD9: =Z9-AB9 -> 0 | AE9: =AA9-AC9 -> 0 | AI9: =SUMIFS([1]项目开票!L:L,[1]项目开票!B:B,报税!B9,[1]项目开票!A:A,报税!A9) -> 0 | AJ9: =SUMIFS([1]项目开票!M:M,[1]项目开票!B:B,报税!B9,[1]项目开票!A:A,报税!A9) -> 0 | AK9: =AG9-AI9 -> 0 | AL9: =AH9-AJ9 -> 0 | AQ9: =AM9-AO9 -> 0 | AR9: =AN9-AP9 -> 0 | AS9: =G9+N9+U9+AB9+AI9+AO9 -> 0
A10: 内蒙伊旗风光储 | B10: 甘肃宏宇天成电力工程有限公司 | C10: EPC | G10: =SUMIFS([1]项目开票!C:C,[1]项目开票!B:B,报税!B10,[1]项目开票!A:A,报税!A10) -> 0 | H10: =SUMIFS([1]项目开票!D:D,[1]项目开票!B:B,报税!B10,[1]项目开票!A:A,报税!A10) -> 0 | I10: =E10-G10 -> 0 | J10: =F10-H10 -> 0 | M10: 318672.55 | N10: =SUMIFS([1]项目开票!O:O,[1]项目开票!B:B,报税!B10,[1]项目开票!A:A,报税!A10) -> 2451327.5 | O10: =SUMIFS([1]项目开票!P:P,[1]项目开票!B:B,报税!B10,[1]项目开票!A:A,报税!A10) -> 318672.55 | P10: =L10-N10 -> -2451327.5 | Q10: =M10-O10 -> 0 | U10: =SUMIFS([1]项目开票!F:F,[1]项目开票!B:B,报税!B10,[1]项目开票!A:A,报税!A10) -> 0 | V10: =SUMIFS([1]项目开票!G:G,[1]项目开票!B:B,报税!B10,[1]项目开票!A:A,报税!A10) -> 0 | W10: =S10-U10 -> 0 | X10: =T10-V10 -> 0 | AB10: =SUMIFS([1]项目开票!I:I,[1]项目开票!B:B,报税!B10,[1]项目开票!A:A,报税!A10) -> 0 | AC10: =SUMIFS([1]项目开票!J:J,[1]项目开票!B:B,报税!B10,[1]项目开票!A:A,报税!A10) -> 0 | AD10: =Z10-AB10 -> 0 | AE10: =AA10-AC10 -> 0 | AI10: =SUMIFS([1]项目开票!L:L,[1]项目开票!B:B,报税!B10,[1]项目开票!A:A,报税!A10) -> 0 | AJ10: =SUMIFS([1]项目开票!M:M,[1]项目开票!B:B,报税!B10,[1]项目开票!A:A,报税!A10) -> 0 | AK10: =AG10-AI10 -> 0 | AL10: =AH10-AJ10 -> 0 | AQ10: =AM10-AO10 -> 0 | AR10: =AN10-AP10 -> 0 | AS10: =G10+N10+U10+AB10+AI10+AO10 -> 2451327.5
A11: 内蒙伊旗风光储 | B11: 河间市绿洁再生资源回收有限公司 | C11: EPC | G11: =SUMIFS([1]项目开票!C:C,[1]项目开票!B:B,报税!B11,[1]项目开票!A:A,报税!A11) -> 0 | H11: =SUMIFS([1]项目开票!D:D,[1]项目开票!B:B,报税!B11,[1]项目开票!A:A,报税!A11) -> 0 | I11: =E11-G11 -> 0 | J11: =F11-H11 -> 0 | M11: 47030.16 | N11: =SUMIFS([1]项目开票!O:O,[1]项目开票!B:B,报税!B11,[1]项目开票!A:A,报税!A11) -> 361770.42 | O11: =SUMIFS([1]项目开票!P:P,[1]项目开票!B:B,报税!B11,[1]项目开票!A:A,报税!A11) -> 47030.16 | P11: =L11-N11 -> -361770.42 | Q11: =M11-O11 -> 0 | U11: =SUMIFS([1]项目开票!F:F,[1]项目开票!B:B,报税!B11,[1]项目开票!A:A,报税!A11) -> 0 | V11: =SUMIFS([1]项目开票!G:G,[1]项目开票!B:B,报税!B11,[1]项目开票!A:A,报税!A11) -> 0 | W11: =S11-U11 -> 0 | X11: =T11-V11 -> 0 | AB11: =SUMIFS([1]项目开票!I:I,[1]项目开票!B:B,报税!B11,[1]项目开票!A:A,报税!A11) -> 0 | AC11: =SUMIFS([1]项目开票!J:J,[1]项目开票!B:B,报税!B11,[1]项目开票!A:A,报税!A11) -> 0 | AD11: =Z11-AB11 -> 0 | AE11: =AA11-AC11 -> 0 | AI11: =SUMIFS([1]项目开票!L:L,[1]项目开票!B:B,报税!B11,[1]项目开票!A:A,报税!A11) -> 0 | AJ11: =SUMIFS([1]项目开票!M:M,[1]项目开票!B:B,报税!B11,[1]项目开票!A:A,报税!A11) -> 0 | AK11: =AG11-AI11 -> 0 | AL11: =AH11-AJ11 -> 0 | AQ11: =AM11-AO11 -> 0 | AR11: =AN11-AP11 -> 0 | AS11: =G11+N11+U11+AB11+AI11+AO11 -> 361770.42
A12: 内蒙伊旗风光储-光伏 | B12: 4470 | C12: EPC | D12: 2496504.9 | E12: 2558917.5 | F12: 230302.58 | G12: =SUMIFS([1]项目开票!C:C,[1]项目开票!B:B,报税!B12,[1]项目开票!A:A,报税!A12) -> 0 | H12: =SUMIFS([1]项目开票!D:D,[1]项目开票!B:B,报税!B12,[1]项目开票!A:A,报税!A12) -> 0 | I12: =E12-G12 -> 2558917.5 | J12: =F12-H12 -> 230302.58 | N12: =SUMIFS([1]项目开票!O:O,[1]项目开票!B:B,报税!B12,[1]项目开票!A:A,报税!A12) -> 0 | O12: =SUMIFS([1]项目开票!P:P,[1]项目开票!B:B,报税!B12,[1]项目开票!A:A,报税!A12) -> 0 | P12: =L12-N12 -> 0 | Q12: =M12-O12 -> 0 | R12: 95462.87 | S12: 97849.44 | T12: 5870.97 | U12: =SUMIFS([1]项目开票!F:F,[1]项目开票!B:B,报税!B12,[1]项目开票!A:A,报税!A12) -> 0 | V12: =SUMIFS([1]项目开票!G:G,[1]项目开票!B:B,报税!B12,[1]项目开票!A:A,报税!A12) -> 0 | W12: =S12-U12 -> 97849.44 | X12: =T12-V12 -> 5870.97 | AB12: =SUMIFS([1]项目开票!I:I,[1]项目开票!B:B,报税!B12,[1]项目开票!A:A,报税!A12) -> 0 | AC12: =SUMIFS([1]项目开票!J:J,[1]项目开票!B:B,报税!B12,[1]项目开票!A:A,报税!A12) -> 0 | AD12: =Z12-AB12 -> 0 | AE12: =AA12-AC12 -> 0 | AI12: =SUMIFS([1]项目开票!L:L,[1]项目开票!B:B,报税!B12,[1]项目开票!A:A,报税!A12) -> 0 | AJ12: =SUMIFS([1]项目开票!M:M,[1]项目开票!B:B,报税!B12,[1]项目开票!A:A,报税!A12) -> 0 | AK12: =AG12-AI12 -> 0 | AL12: =AH12-AJ12 -> 0 | AQ12: =AM12-AO12 -> 0 | AR12: =AN12-AP12 -> 0 | AS12: =G12+N12+U12+AB12+AI12+AO12 -> 0
A13: 灵山玖伯一期 | B13: 3307 | C13: 已出售 | G13: =SUMIFS([1]项目开票!C:C,[1]项目开票!B:B,报税!B13,[1]项目开票!A:A,报税!A13) -> 0 | H13: =SUMIFS([1]项目开票!D:D,[1]项目开票!B:B,报税!B13,[1]项目开票!A:A,报税!A13) -> 0 | I13: =E13-G13 -> 0 | J13: =F13-H13 -> 0 | N13: =SUMIFS([1]项目开票!O:O,[1]项目开票!B:B,报税!B13,[1]项目开票!A:A,报税!A13) -> 0 | O13: =SUMIFS([1]项目开票!P:P,[1]项目开票!B:B,报税!B13,[1]项目开票!A:A,报税!A13) -> 0 | P13: =L13-N13 -> 0 | Q13: =M13-O13 -> 0 | R13: 53584.91 | S13: 53584.91 | T13: 3215.09 | U13: =SUMIFS([1]项目开票!F:F,[1]项目开票!B:B,报税!B13,[1]项目开票!A:A,报税!A13) -> 323739.19 | V13: =SUMIFS([1]项目开票!G:G,[1]项目开票!B:B,报税!B13,[1]项目开票!A:A,报税!A13) -> 19424.35 | W13: =S13-U13 -> -270154.28 | X13: =T13-V13 -> -16209.26 | AB13: =SUMIFS([1]项目开票!I:I,[1]项目开票!B:B,报税!B13,[1]项目开票!A:A,报税!A13) -> 0 | AC13: =SUMIFS([1]项目开票!J:J,[1]项目开票!B:B,报税!B13,[1]项目开票!A:A,报税!A13) -> 0 | AD13: =Z13-AB13 -> 0 | AE13: =AA13-AC13 -> 0 | AI13: =SUMIFS([1]项目开票!L:L,[1]项目开票!B:B,报税!B13,[1]项目开票!A:A,报税!A13) -> 0 | AJ13: =SUMIFS([1]项目开票!M:M,[1]项目开票!B:B,报税!B13,[1]项目开票!A:A,报税!A13) -> 0 | AK13: =AG13-AI13 -> 0 | AL13: =AH13-AJ13 -> 0 | AS13: =G13+N13+U13+AB13+AI13+AO13 -> 323739.19
A14: 利豪鸡泽县项目 | B14: 利豪泽风邯郸风力发电有限责任公司 | C14: 对外EPC | G14: =SUMIFS([1]项目开票!C:C,[1]项目开票!B:B,报税!B14,[1]项目开票!A:A,报税!A14) -> 0 | H14: =SUMIFS([1]项目开票!D:D,[1]项目开票!B:B,报税!B14,[1]项目开票!A:A,报税!A14) -> 0 | I14: =E14-G14 -> 0 | J14: =F14-H14 -> 0 | K14: 122417.26 | L14: 132550.47 | M14: 17231.56 | N14: =SUMIFS([1]项目开票!O:O,[1]项目开票!B:B,报税!B14,[1]项目开票!A:A,报税!A14) -> 0 | O14: =SUMIFS([1]项目开票!P:P,[1]项目开票!B:B,报税!B14,[1]项目开票!A:A,报税!A14) -> 0 | P14: =L14-N14 -> 132550.47 | Q14: =M14-O14 -> 17231.56 | R14: 315272.44 | S14: 345134.82 | T14: 20708.09 | U14: =SUMIFS([1]项目开票!F:F,[1]项目开票!B:B,报税!B14,[1]项目开票!A:A,报税!A14) -> 0 | V14: =SUMIFS([1]项目开票!G:G,[1]项目开票!B:B,报税!B14,[1]项目开票!A:A,报税!A14) -> 0 | W14: =S14-U14 -> 345134.82 | X14: =T14-V14 -> 20708.09 | AB14: =SUMIFS([1]项目开票!I:I,[1]项目开票!B:B,报税!B14,[1]项目开票!A:A,报税!A14) -> 0 | AC14: =SUMIFS([1]项目开票!J:J,[1]项目开票!B:B,报税!B14,[1]项目开票!A:A,报税!A14) -> 0 | AD14: =Z14-AB14 -> 0 | AE14: =AA14-AC14 -> 0 | AI14: =SUMIFS([1]项目开票!L:L,[1]项目开票!B:B,报税!B14,[1]项目开票!A:A,报税!A14) -> 0 | AJ14: =SUMIFS([1]项目开票!M:M,[1]项目开票!B:B,报税!B14,[1]项目开票!A:A,报税!A14) -> 0 | AK14: =AG14-AI14 -> 0 | AL14: =AH14-AJ14 -> 0 | AQ14: =AM14-AO14 -> 0 | AR14: =AN14-AP14 -> 0 | AS14: =G14+N14+U14+AB14+AI14+AO14 -> 0
A15: 安徽定远 | B15: 1A00 | C15: 已出售 | D15: 460600 | E15: 472115 | F15: 42490.35 | G15: =SUMIFS([1]项目开票!C:C,[1]项目开票!B:B,报税!B15,[1]项目开票!A:A,报税!A15) -> 472115 | H15: =SUMIFS([1]项目开票!D:D,[1]项目开票!B:B,报税!B15,[1]项目开票!A:A,报税!A15) -> 42490.35 | I15: =E15-G15 -> 0 | J15: =F15-H15 -> 0 | N15: =SUMIFS([1]项目开票!O:O,[1]项目开票!B:B,报税!B15,[1]项目开票!A:A,报税!A15) -> 0 | O15: =SUMIFS([1]项目开票!P:P,[1]项目开票!B:B,报税!B15,[1]项目开票!A:A,报税!A15) -> 0 | P15: =L15-N15 -> 0 | Q15: =M15-O15 -> 0 | U15: =SUMIFS([1]项目开票!F:F,[1]项目开票!B:B,报税!B15,[1]项目开票!A:A,报税!A15) -> 0 | V15: =SUMIFS([1]项目开票!G:G,[1]项目开票!B:B,报税!B15,[1]项目开票!A:A,报税!A15) -> 0 | W15: =S15-U15 -> 0 | X15: =T15-V15 -> 0 | AB15: =SUMIFS([1]项目开票!I:I,[1]项目开票!B:B,报税!B15,[1]项目开票!A:A,报税!A15) -> 0 | AC15: =SUMIFS([1]项目开票!J:J,[1]项目开票!B:B,报税!B15,[1]项目开票!A:A,报税!A15) -> 0 | AD15: =Z15-AB15 -> 0 | AE15: =AA15-AC15 -> 0 | AI15: =SUMIFS([1]项目开票!L:L,[1]项目开票!B:B,报税!B15,[1]项目开票!A:A,报税!A15) -> 0 | AJ15: =SUMIFS([1]项目开票!M:M,[1]项目开票!B:B,报税!B15,[1]项目开票!A:A,报税!A15) -> 0 | AK15: =AG15-AI15 -> 0 | AL15: =AH15-AJ15 -> 0 | AQ15: =AM15-AO15 -> 0 | AR15: =AN15-AP15 -> 0 | AS15: =G15+N15+U15+AB15+AI15+AO15 -> 472115
A16: 内蒙鄂尔多斯分散式 | B16: 4470 | C16: EPC | D16: -0.01 | G16: =SUMIFS([1]项目开票!C:C,[1]项目开票!B:B,报税!B16,[1]项目开票!A:A,报税!A16) -> 0 | H16: =SUMIFS([1]项目开票!D:D,[1]项目开票!B:B,报税!B16,[1]项目开票!A:A,报税!A16) -> 0 | I16: =E16-G16 -> 0 | J16: =F16-H16 -> 0 | N16: =SUMIFS([1]项目开票!O:O,[1]项目开票!B:B,报税!B16,[1]项目开票!A:A,报税!A16) -> 0 | O16: =SUMIFS([1]项目开票!P:P,[1]项目开票!B:B,报税!B16,[1]项目开票!A:A,报税!A16) -> 0 | P16: =L16-N16 -> 0 | Q16: =M16-O16 -> 0 | R16: 3624400.4 | S16: 3715010.5 | T16: 222900.63 | U16: =SUMIFS([1]项目开票!F:F,[1]项目开票!B:B,报税!B16,[1]项目开票!A:A,报税!A16) -> 0 | V16: =SUMIFS([1]项目开票!G:G,[1]项目开票!B:B,报税!B16,[1]项目开票!A:A,报税!A16) -> 0 | W16: =S16-U16 -> 3715010.5 | X16: =T16-V16 -> 222900.63 | AB16: =SUMIFS([1]项目开票!I:I,[1]项目开票!B:B,报税!B16,[1]项目开票!A:A,报税!A16) -> 0 | AC16: =SUMIFS([1]项目开票!J:J,[1]项目开票!B:B,报税!B16,[1]项目开票!A:A,报税!A16) -> 0 | AD16: =Z16-AB16 -> 0 | AE16: =AA16-AC16 -> 0 | AI16: =SUMIFS([1]项目开票!L:L,[1]项目开票!B:B,报税!B16,[1]项目开票!A:A,报税!A16) -> 0 | AJ16: =SUMIFS([1]项目开票!M:M,[1]项目开票!B:B,报税!B16,[1]项目开票!A:A,报税!A16) -> 0 | AK16: =AG16-AI16 -> 0 | AL16: =AH16-AJ16 -> 0 | AQ16: =AM16-AO16 -> 0 | AR16: =AN16-AP16 -> 0 | AS16: =G16+N16+U16+AB16+AI16+AO16 -> 0
A17: 赤峰市风光制氢一体化项目-赤峰翁牛特旗P1-375 | B17: XC00 | C17: EPC | G17: =SUMIFS([1]项目开票!C:C,[1]项目开票!B:B,报税!B17,[1]项目开票!A:A,报税!A17) -> 0 | H17: =SUMIFS([1]项目开票!D:D,[1]项目开票!B:B,报税!B17,[1]项目开票!A:A,报税!A17) -> 0 | I17: =E17-G17 -> 0 | J17: =F17-H17 -> 0 | N17: =SUMIFS([1]项目开票!O:O,[1]项目开票!B:B,报税!B17,[1]项目开票!A:A,报税!A17) -> 0 | O17: =SUMIFS([1]项目开票!P:P,[1]项目开票!B:B,报税!B17,[1]项目开票!A:A,报税!A17) -> 0 | P17: =L17-N17 -> 0 | Q17: =M17-O17 -> 0 | U17: =SUMIFS([1]项目开票!F:F,[1]项目开票!B:B,报税!B17,[1]项目开票!A:A,报税!A17) -> 0 | V17: =SUMIFS([1]项目开票!G:G,[1]项目开票!B:B,报税!B17,[1]项目开票!A:A,报税!A17) -> 0 | W17: =S17-U17 -> 0 | X17: =T17-V17 -> 0 | Y17: 31013.05 | Z17: 31788.38 | AA17: 1907.3 | AB17: =SUMIFS([1]项目开票!I:I,[1]项目开票!B:B,报税!B17,[1]项目开票!A:A,报税!A17) -> 31788.38 | AC17: =SUMIFS([1]项目开票!J:J,[1]项目开票!B:B,报税!B17,[1]项目开票!A:A,报税!A17) -> 1907.3 | AD17: =Z17-AB17 -> 0 | AE17: =AA17-AC17 -> 0 | AI17: =SUMIFS([1]项目开票!L:L,[1]项目开票!B:B,报税!B17,[1]项目开票!A:A,报税!A17) -> 0 | AJ17: =SUMIFS([1]项目开票!M:M,[1]项目开票!B:B,报税!B17,[1]项目开票!A:A,报税!A17) -> 0 | AK17: =AG17-AI17 -> 0 | AL17: =AH17-AJ17 -> 0 | AQ17: =AM17-AO17 -> 0 | AR17: =AN17-AP17 -> 0 | AS17: =G17+N17+U17+AB17+AI17+AO17 -> 31788.38
A18: 民勤共享储能电站 | B18: 3A12 | C18: EPC | D18: -2109767.6 | E18: -2162511.8 | F18: -194626.06 | G18: =SUMIFS([1]项目开票!C:C,[1]项目开票!B:B,报税!B18,[1]项目开票!A:A,报税!A18) -> 0 | H18: =SUMIFS([1]项目开票!D:D,[1]项目开票!B:B,报税!B18,[1]项目开票!A:A,报税!A18) -> 0 | I18: =E18-G18 -> -2162511.8 | J18: =F18-H18 -> -194626.06 | N18: =SUMIFS([1]项目开票!O:O,[1]项目开票!B:B,报税!B18,[1]项目开票!A:A,报税!A18) -> 0 | O18: =SUMIFS([1]项目开票!P:P,[1]项目开票!B:B,报税!B18,[1]项目开票!A:A,报税!A18) -> 0 | P18: =L18-N18 -> 0 | Q18: =M18-O18 -> 0 | R18: 854960.78 | S18: 876334.8 | T18: 52580.09 | U18: =SUMIFS([1]项目开票!F:F,[1]项目开票!B:B,报税!B18,[1]项目开票!A:A,报税!A18) -> 0 | V18: =SUMIFS([1]项目开票!G:G,[1]项目开票!B:B,报税!B18,[1]项目开票!A:A,报税!A18) -> 0 | W18: =S18-U18 -> 876334.8 | X18: =T18-V18 -> 52580.09 | AB18: =SUMIFS([1]项目开票!I:I,[1]项目开票!B:B,报税!B18,[1]项目开票!A:A,报税!A18) -> 0 | AC18: =SUMIFS([1]项目开票!J:J,[1]项目开票!B:B,报税!B18,[1]项目开票!A:A,报税!A18) -> 0 | AD18: =Z18-AB18 -> 0 | AE18: =AA18-AC18 -> 0 | AI18: =SUMIFS([1]项目开票!L:L,[1]项目开票!B:B,报税!B18,[1]项目开票!A:A,报税!A18) -> 0 | AJ18: =SUMIFS([1]项目开票!M:M,[1]项目开票!B:B,报税!B18,[1]项目开票!A:A,报税!A18) -> 0 | AK18: =AG18-AI18 -> 0 | AL18: =AH18-AJ18 -> 0 | AQ18: =AM18-AO18 -> 0 | AR18: =AN18-AP18 -> 0 | AS18: =G18+N18+U18+AB18+AI18+AO18 -> 0
A19: 锡盟苏右100万千瓦/400万千瓦时储能 | B19: 4301 | C19: EPC | D19: 40479053 | E19: 16308117 | F19: 1467730.5 | G19: =SUMIFS([1]项目开票!C:C,[1]项目开票!B:B,报税!B19,[1]项目开票!A:A,报税!A19) -> 0 | H19: =SUMIFS([1]项目开票!D:D,[1]项目开票!B:B,报税!B19,[1]项目开票!A:A,报税!A19) -> 0 | I19: =E19-G19 -> 16308117 | J19: =F19-H19 -> 1467730.5 | K19: 8.6568815e+08 | L19: 8.5109174e+08 | M19: 1.1064193e+08 | N19: =SUMIFS([1]项目开票!O:O,[1]项目开票!B:B,报税!B19,[1]项目开票!A:A,报税!A19) -> 0 | O19: =SUMIFS([1]项目开票!P:P,[1]项目开票!B:B,报税!B19,[1]项目开票!A:A,报税!A19) -> 0 | P19: =L19-N19 -> 8.5109174e+08 | Q19: =M19-O19 -> 1.1064193e+08 | R19: 32786646 | S19: 33410446 | T19: 2004626.8 | U19: =SUMIFS([1]项目开票!F:F,[1]项目开票!B:B,报税!B19,[1]项目开票!A:A,报税!A19) -> 0 | V19: =SUMIFS([1]项目开票!G:G,[1]项目开票!B:B,报税!B19,[1]项目开票!A:A,报税!A19) -> 0 | W19: =S19-U19 -> 33410446 | X19: =T19-V19 -> 2004626.8 | Y19: 29801.75 | Z19: 30546.79 | AA19: 1832.81 | AB19: =SUMIFS([1]项目开票!I:I,[1]项目开票!B:B,报税!B19,[1]项目开票!A:A,报税!A19) -> 30546.79 | AC19: =SUMIFS([1]项目开票!J:J,[1]项目开票!B:B,报税!B19,[1]项目开票!A:A,报税!A19) -> 1832.81 | AD19: =Z19-AB19 -> 0 | AE19: =AA19-AC19 -> 0 | AI19: =SUMIFS([1]项目开票!L:L,[1]项目开票!B:B,报税!B19,[1]项目开票!A:A,报税!A19) -> 0 | AJ19: =SUMIFS([1]项目开票!M:M,[1]项目开票!B:B,报税!B19,[1]项目开票!A:A,报税!A19) -> 0 | AK19: =AG19-AI19 -> 0 | AL19: =AH19-AJ19 -> 0 | AQ19: =AM19-AO19 -> 0 | AR19: =AN19-AP19 -> 0 | AS19: =G19+N19+U19+AB19+AI19+AO19 -> 30546.79
A20: 巴彦淖尔1000MW/4000MWh储能 | B20: 3A17 | C20: EPC | D20: 74809451 | E20: 1.9768947e+08 | F20: 17792052 | G20: =SUMIFS([1]项目开票!C:C,[1]项目开票!B:B,报税!B20,[1]项目开票!A:A,报税!A20) -> 1.859622e+08 | H20: =SUMIFS([1]项目开票!D:D,[1]项目开票!B:B,报税!B20,[1]项目开票!A:A,报税!A20) -> 16736598 | I20: =E20-G20 -> 11727267 | J20: =F20-H20 -> 1055454 | K20: 5.6543495e+08 | L20: 5.6708361e+08 | M20: 73720869 | N20: =SUMIFS([1]项目开票!O:O,[1]项目开票!B:B,报税!B20,[1]项目开票!A:A,报税!A20) -> 0 | O20: =SUMIFS([1]项目开票!P:P,[1]项目开票!B:B,报税!B20,[1]项目开票!A:A,报税!A20) -> 0 | P20: =L20-N20 -> 5.6708361e+08 | Q20: =M20-O20 -> 73720869 | R20: 23806211 | S20: 24044065 | T20: 1442643.9 | U20: =SUMIFS([1]项目开票!F:F,[1]项目开票!B:B,报税!B20,[1]项目开票!A:A,报税!A20) -> 0 | V20: =SUMIFS([1]项目开票!G:G,[1]项目开票!B:B,报税!B20,[1]项目开票!A:A,报税!A20) -> 0 | W20: =S20-U20 -> 24044065 | X20: =T20-V20 -> 1442643.9 | Y20: 29801.75 | Z20: 30546.79 | AA20: 1832.81 | AB20: =SUMIFS([1]项目开票!I:I,[1]项目开票!B:B,报税!B20,[1]项目开票!A:A,报税!A20) -> 30546.79 | AC20: =SUMIFS([1]项目开票!J:J,[1]项目开票!B:B,报税!B20,[1]项目开票!A:A,报税!A20) -> 1832.81 | AD20: =Z20-AB20 -> 0 | AE20: =AA20-AC20 -> 0 | AI20: =SUMIFS([1]项目开票!L:L,[1]项目开票!B:B,报税!B20,[1]项目开票!A:A,报税!A20) -> 0 | AJ20: =SUMIFS([1]项目开票!M:M,[1]项目开票!B:B,报税!B20,[1]项目开票!A:A,报税!A20) -> 0 | AK20: =AG20-AI20 -> 0 | AL20: =AH20-AJ20 -> 0 | AQ20: =AM20-AO20 -> 0 | AR20: =AN20-AP20 -> 0 | AS20: =G20+N20+U20+AB20+AI20+AO20 -> 1.8599275e+08
A21: 陕西佳县 | B21: 3316 | C21: EPC | G21: =SUMIFS([1]项目开票!C:C,[1]项目开票!B:B,报税!B21,[1]项目开票!A:A,报税!A21) -> 0 | H21: =SUMIFS([1]项目开票!D:D,[1]项目开票!B:B,报税!B21,[1]项目开票!A:A,报税!A21) -> 0 | I21: =E21-G21 -> 0 | J21: =F21-H21 -> 0 | N21: =SUMIFS([1]项目开票!O:O,[1]项目开票!B:B,报税!B21,[1]项目开票!A:A,报税!A21) -> 0 | O21: =SUMIFS([1]项目开票!P:P,[1]项目开票!B:B,报税!B21,[1]项目开票!A:A,报税!A21) -> 0 | P21: =L21-N21 -> 0 | Q21: =M21-O21 -> 0 | R21: 619297.69 | S21: 619297.69 | T21: 37157.86 | U21: =SUMIFS([1]项目开票!F:F,[1]项目开票!B:B,报税!B21,[1]项目开票!A:A,报税!A21) -> 0 | V21: =SUMIFS([1]项目开票!G:G,[1]项目开票!B:B,报税!B21,[1]项目开票!A:A,报税!A21) -> 0 | W21: =S21-U21 -> 619297.69 | X21: =T21-V21 -> 37157.86 | Y21: 47683.01 | Z21: 48875.09 | AA21: 2932.51 | AB21: =SUMIFS([1]项目开票!I:I,[1]项目开票!B:B,报税!B21,[1]项目开票!A:A,报税!A21) -> 48875.09 | AC21: =SUMIFS([1]项目开票!J:J,[1]项目开票!B:B,报税!B21,[1]项目开票!A:A,报税!A21) -> 2932.51 | AD21: =Z21-AB21 -> 0 | AE21: =AA21-AC21 -> 0 | AI21: =SUMIFS([1]项目开票!L:L,[1]项目开票!B:B,报税!B21,[1]项目开票!A:A,报税!A21) -> 0 | AJ21: =SUMIFS([1]项目开票!M:M,[1]项目开票!B:B,报税!B21,[1]项目开票!A:A,报税!A21) -> 0 | AK21: =AG21-AI21 -> 0 | AL21: =AH21-AJ21 -> 0 | AQ21: =AM21-AO21 -> 0 | AR21: =AN21-AP21 -> 0 | AS21: =G21+N21+U21+AB21+AI21+AO21 -> 48875.09
A22: 乌海市金湖500kV独立储能电站 | B22: 乌海市远鸿富景新能源科技有限公司 | C22: 对外EPC | D22: 327698.08 | E22: 8550.45 | F22: 769.54 | G22: =SUMIFS([1]项目开票!C:C,[1]项目开票!B:B,报税!B22,[1]项目开票!A:A,报税!A22) -> 0 | H22: =SUMIFS([1]项目开票!D:D,[1]项目开票!B:B,报税!B22,[1]项目开票!A:A,报税!A22) -> 0 | I22: =E22-G22 -> 8550.45 | J22: =F22-H22 -> 769.54 | N22: =SUMIFS([1]项目开票!O:O,[1]项目开票!B:B,报税!B22,[1]项目开票!A:A,报税!A22) -> 0 | O22: =SUMIFS([1]项目开票!P:P,[1]项目开票!B:B,报税!B22,[1]项目开票!A:A,报税!A22) -> 0 | P22: =L22-N22 -> 0 | Q22: =M22-O22 -> 0 | U22: =SUMIFS([1]项目开票!F:F,[1]项目开票!B:B,报税!B22,[1]项目开票!A:A,报税!A22) -> 0 | V22: =SUMIFS([1]项目开票!G:G,[1]项目开票!B:B,报税!B22,[1]项目开票!A:A,报税!A22) -> 0 | W22: =S22-U22 -> 0 | X22: =T22-V22 -> 0 | AB22: =SUMIFS([1]项目开票!I:I,[1]项目开票!B:B,报税!B22,[1]项目开票!A:A,报税!A22) -> 0 | AC22: =SUMIFS([1]项目开票!J:J,[1]项目开票!B:B,报税!B22,[1]项目开票!A:A,报税!A22) -> 0 | AD22: =Z22-AB22 -> 0 | AE22: =AA22-AC22 -> 0 | AI22: =SUMIFS([1]项目开票!L:L,[1]项目开票!B:B,报税!B22,[1]项目开票!A:A,报税!A22) -> 0 | AJ22: =SUMIFS([1]项目开票!M:M,[1]项目开票!B:B,报税!B22,[1]项目开票!A:A,报税!A22) -> 0 | AK22: =AG22-AI22 -> 0 | AL22: =AH22-AJ22 -> 0 | AQ22: =AM22-AO22 -> 0 | AR22: =AN22-AP22 -> 0 | AS22: =G22+N22+U22+AB22+AI22+AO22 -> 0
A23: 射阳样机_远景 | B23: 1000 | C23: EPC | D23: 10067937 | E23: 10823033 | F23: 974072.94 | G23: =SUMIFS([1]项目开票!C:C,[1]项目开票!B:B,报税!B23,[1]项目开票!A:A,报税!A23) -> 10823033 | H23: =SUMIFS([1]项目开票!D:D,[1]项目开票!B:B,报税!B23,[1]项目开票!A:A,报税!A23) -> 974072.94 | I23: =E23-G23 -> 0 | J23: =F23-H23 -> 0 | N23: =SUMIFS([1]项目开票!O:O,[1]项目开票!B:B,报税!B23,[1]项目开票!A:A,报税!A23) -> 0 | O23: =SUMIFS([1]项目开票!P:P,[1]项目开票!B:B,报税!B23,[1]项目开票!A:A,报税!A23) -> 0 | P23: =L23-N23 -> 0 | Q23: =M23-O23 -> 0 | R23: 784711.52 | S23: 843564.88 | T23: 50613.89 | U23: =SUMIFS([1]项目开票!F:F,[1]项目开票!B:B,报税!B23,[1]项目开票!A:A,报税!A23) -> 843564.88 | V23: =SUMIFS([1]项目开票!G:G,[1]项目开票!B:B,报税!B23,[1]项目开票!A:A,报税!A23) -> 50613.89 | W23: =S23-U23 -> 0 | X23: =T23-V23 -> 0 | AB23: =SUMIFS([1]项目开票!I:I,[1]项目开票!B:B,报税!B23,[1]项目开票!A:A,报税!A23) -> 0 | AC23: =SUMIFS([1]项目开票!J:J,[1]项目开票!B:B,报税!B23,[1]项目开票!A:A,报税!A23) -> 0 | AD23: =Z23-AB23 -> 0 | AE23: =AA23-AC23 -> 0 | AI23: =SUMIFS([1]项目开票!L:L,[1]项目开票!B:B,报税!B23,[1]项目开票!A:A,报税!A23) -> 0 | AJ23: =SUMIFS([1]项目开票!M:M,[1]项目开票!B:B,报税!B23,[1]项目开票!A:A,报税!A23) -> 0 | AK23: =AG23-AI23 -> 0 | AL23: =AH23-AJ23 -> 0 | AQ23: =AM23-AO23 -> 0 | AR23: =AN23-AP23 -> 0 | AS23: =G23+N23+U23+AB23+AI23+AO23 -> 11666597
A24: 射阳样机_远景 | B24: 2060 | C24: EPC | D24: 6067157 | E24: 6522193.7 | F24: 586997.45 | G24: =SUMIFS([1]项目开票!C:C,[1]项目开票!B:B,报税!B24,[1]项目开票!A:A,报税!A24) -> 6522193.7 | H24: =SUMIFS([1]项目开票!D:D,[1]项目开票!B:B,报税!B24,[1]项目开票!A:A,报税!A24) -> 586997.45 | I24: =E24-G24 -> 0 | J24: =F24-H24 -> 0 | N24: =SUMIFS([1]项目开票!O:O,[1]项目开票!B:B,报税!B24,[1]项目开票!A:A,报税!A24) -> 0 | O24: =SUMIFS([1]项目开票!P:P,[1]项目开票!B:B,报税!B24,[1]项目开票!A:A,报税!A24) -> 0 | P24: =L24-N24 -> 0 | Q24: =M24-O24 -> 0 | R24: 472792.64 | S24: 508252.09 | T24: 30495.12 | U24: =SUMIFS([1]项目开票!F:F,[1]项目开票!B:B,报税!B24,[1]项目开票!A:A,报税!A24) -> 508252.09 | V24: =SUMIFS([1]项目开票!G:G,[1]项目开票!B:B,报税!B24,[1]项目开票!A:A,报税!A24) -> 30495.12 | W24: =S24-U24 -> 0 | X24: =T24-V24 -> 0 | AB24: =SUMIFS([1]项目开票!I:I,[1]项目开票!B:B,报税!B24,[1]项目开票!A:A,报税!A24) -> 0 | AC24: =SUMIFS([1]项目开票!J:J,[1]项目开票!B:B,报税!B24,[1]项目开票!A:A,报税!A24) -> 0 | AD24: =Z24-AB24 -> 0 | AE24: =AA24-AC24 -> 0 | AI24: =SUMIFS([1]项目开票!L:L,[1]项目开票!B:B,报税!B24,[1]项目开票!A:A,报税!A24) -> 0 | AJ24: =SUMIFS([1]项目开票!M:M,[1]项目开票!B:B,报税!B24,[1]项目开票!A:A,报税!A24) -> 0 | AK24: =AG24-AI24 -> 0 | AL24: =AH24-AJ24 -> 0 | AQ24: =AM24-AO24 -> 0 | AR24: =AN24-AP24 -> 0 | AS24: =G24+N24+U24+AB24+AI24+AO24 -> 7030445.8
A25: 射阳样机_远景 | B25: 2260 | C25: EPC | D25: 4487802.2 | E25: 4824387.3 | F25: 434194.86 | G25: =SUMIFS([1]项目开票!C:C,[1]项目开票!B:B,报税!B25,[1]项目开票!A:A,报税!A25) -> 4824387.3 | H25: =SUMIFS([1]项目开票!D:D,[1]项目开票!B:B,报税!B25,[1]项目开票!A:A,报税!A25) -> 434194.86 | I25: =E25-G25 -> 0 | J25: =F25-H25 -> 0 | N25: =SUMIFS([1]项目开票!O:O,[1]项目开票!B:B,报税!B25,[1]项目开票!A:A,报税!A25) -> 0 | O25: =SUMIFS([1]项目开票!P:P,[1]项目开票!B:B,报税!B25,[1]项目开票!A:A,报税!A25) -> 0 | P25: =L25-N25 -> 0 | Q25: =M25-O25 -> 0 | R25: 472792.64 | S25: 508252.09 | T25: 30495.12 | U25: =SUMIFS([1]项目开票!F:F,[1]项目开票!B:B,报税!B25,[1]项目开票!A:A,报税!A25) -> 508252.09 | V25: =SUMIFS([1]项目开票!G:G,[1]项目开票!B:B,报税!B25,[1]项目开票!A:A,报税!A25) -> 30495.12 | W25: =S25-U25 -> 0 | X25: =T25-V25 -> 0 | AB25: =SUMIFS([1]项目开票!I:I,[1]项目开票!B:B,报税!B25,[1]项目开票!A:A,报税!A25) -> 0 | AC25: =SUMIFS([1]项目开票!J:J,[1]项目开票!B:B,报税!B25,[1]项目开票!A:A,报税!A25) -> 0 | AD25: =Z25-AB25 -> 0 | AE25: =AA25-AC25 -> 0 | AI25: =SUMIFS([1]项目开票!L:L,[1]项目开票!B:B,报税!B25,[1]项目开票!A:A,报税!A25) -> 0 | AJ25: =SUMIFS([1]项目开票!M:M,[1]项目开票!B:B,报税!B25,[1]项目开票!A:A,报税!A25) -> 0 | AK25: =AG25-AI25 -> 0 | AL25: =AH25-AJ25 -> 0 | AQ25: =AM25-AO25 -> 0 | AR25: =AN25-AP25 -> 0 | AS25: =G25+N25+U25+AB25+AI25+AO25 -> 5332639.4
A26: F-001227海伦市东林乡分散式风电场项目场站运维服务 | B26: 海伦京网新能源有限公司 | C26: 后服务收入 | G26: =SUMIFS([1]项目开票!C:C,[1]项目开票!B:B,报税!B26,[1]项目开票!A:A,报税!A26) -> 0 | H26: =SUMIFS([1]项目开票!D:D,[1]项目开票!B:B,报税!B26,[1]项目开票!A:A,报税!A26) -> 0 | I26: =E26-G26 -> 0 | J26: =F26-H26 -> 0 | K26: 10679.25 | L26: 10953.1 | M26: 1423.9 | N26: =SUMIFS([1]项目开票!O:O,[1]项目开票!B:B,报税!B26,[1]项目开票!A:A,报税!A26) -> 0 | O26: =SUMIFS([1]项目开票!P:P,[1]项目开票!B:B,报税!B26,[1]项目开票!A:A,报税!A26) -> 0 | P26: =L26-N26 -> 10953.1 | Q26: =M26-O26 -> 1423.9 | R26: 105136.18 | S26: 107831.98 | T26: 6469.92 | U26: =SUMIFS([1]项目开票!F:F,[1]项目开票!B:B,报税!B26,[1]项目开票!A:A,报税!A26) -> 0 | V26: =SUMIFS([1]项目开票!G:G,[1]项目开票!B:B,报税!B26,[1]项目开票!A:A,报税!A26) -> 0 | W26: =S26-U26 -> 107831.98 | X26: =T26-V26 -> 6469.92 | AB26: =SUMIFS([1]项目开票!I:I,[1]项目开票!B:B,报税!B26,[1]项目开票!A:A,报税!A26) -> 0 | AC26: =SUMIFS([1]项目开票!J:J,[1]项目开票!B:B,报税!B26,[1]项目开票!A:A,报税!A26) -> 0 | AD26: =Z26-AB26 -> 0 | AE26: =AA26-AC26 -> 0 | AI26: =SUMIFS([1]项目开票!L:L,[1]项目开票!B:B,报税!B26,[1]项目开票!A:A,报税!A26) -> 0 | AJ26: =SUMIFS([1]项目开票!M:M,[1]项目开票!B:B,报税!B26,[1]项目开票!A:A,报税!A26) -> 0 | AK26: =AG26-AI26 -> 0 | AL26: =AH26-AJ26 -> 0 | AQ26: =AM26-AO26 -> 0 | AR26: =AN26-AP26 -> 0 | AS26: =G26+N26+U26+AB26+AI26+AO26 -> 0
A27: 贵港桂平一期 | B27: 2056 | C27: EPC | G27: =SUMIFS([1]项目开票!C:C,[1]项目开票!B:B,报税!B27,[1]项目开票!A:A,报税!A27) -> 0 | H27: =SUMIFS([1]项目开票!D:D,[1]项目开票!B:B,报税!B27,[1]项目开票!A:A,报税!A27) -> 0 | I27: =E27-G27 -> 0 | J27: =F27-H27 -> 0 | N27: =SUMIFS([1]项目开票!O:O,[1]项目开票!B:B,报税!B27,[1]项目开票!A:A,报税!A27) -> 0 | O27: =SUMIFS([1]项目开票!P:P,[1]项目开票!B:B,报税!B27,[1]项目开票!A:A,报税!A27) -> 0 | P27: =L27-N27 -> 0 | Q27: =M27-O27 -> 0 | R27: 96855.35 | S27: 96855.35 | T27: 5811.32 | U27: =SUMIFS([1]项目开票!F:F,[1]项目开票!B:B,报税!B27,[1]项目开票!A:A,报税!A27) -> 999308.33 | V27: =SUMIFS([1]项目开票!G:G,[1]项目开票!B:B,报税!B27,[1]项目开票!A:A,报税!A27) -> 59958.51 | W27: =S27-U27 -> -902452.98 | X27: =T27-V27 -> -54147.19 | AB27: =SUMIFS([1]项目开票!I:I,[1]项目开票!B:B,报税!B27,[1]项目开票!A:A,报税!A27) -> 61093.6 | AC27: =SUMIFS([1]项目开票!J:J,[1]项目开票!B:B,报税!B27,[1]项目开票!A:A,报税!A27) -> 3665.62 | AD27: =Z27-AB27 -> -61093.6 | AE27: =AA27-AC27 -> -3665.62 | AI27: =SUMIFS([1]项目开票!L:L,[1]项目开票!B:B,报税!B27,[1]项目开票!A:A,报税!A27) -> 0 | AJ27: =SUMIFS([1]项目开票!M:M,[1]项目开票!B:B,报税!B27,[1]项目开票!A:A,报税!A27) -> 0 | AK27: =AG27-AI27 -> 0 | AL27: =AH27-AJ27 -> 0 | AQ27: =AM27-AO27 -> 0 | AR27: =AN27-AP27 -> 0 | AS27: =G27+N27+U27+AB27+AI27+AO27 -> 1060401.9
A28: FC-000068清池河北沧县浮阳风电场变电运维服务 | B28: 沧县清池新能源有限公司 | C28: 后服务收入 | G28: =SUMIFS([1]项目开票!C:C,[1]项目开票!B:B,报税!B28,[1]项目开票!A:A,报税!A28) -> 0 | H28: =SUMIFS([1]项目开票!D:D,[1]项目开票!B:B,报税!B28,[1]项目开票!A:A,报税!A28) -> 0 | I28: =E28-G28 -> 0 | J28: =F28-H28 -> 0 | N28: =SUMIFS([1]项目开票!O:O,[1]项目开票!B:B,报税!B28,[1]项目开票!A:A,报税!A28) -> 0 | O28: =SUMIFS([1]项目开票!P:P,[1]项目开票!B:B,报税!B28,[1]项目开票!A:A,报税!A28) -> 0 | P28: =L28-N28 -> 0 | Q28: =M28-O28 -> 0 | R28: 733456.66 | S28: 752263.25 | T28: 45135.8 | U28: =SUMIFS([1]项目开票!F:F,[1]项目开票!B:B,报税!B28,[1]项目开票!A:A,报税!A28) -> 0 | V28: =SUMIFS([1]项目开票!G:G,[1]项目开票!B:B,报税!B28,[1]项目开票!A:A,报税!A28) -> 0 | W28: =S28-U28 -> 752263.25 | X28: =T28-V28 -> 45135.8 | AB28: =SUMIFS([1]项目开票!I:I,[1]项目开票!B:B,报税!B28,[1]项目开票!A:A,报税!A28) -> 0 | AC28: =SUMIFS([1]项目开票!J:J,[1]项目开票!B:B,报税!B28,[1]项目开票!A:A,报税!A28) -> 0 | AD28: =Z28-AB28 -> 0 | AE28: =AA28-AC28 -> 0 | AI28: =SUMIFS([1]项目开票!L:L,[1]项目开票!B:B,报税!B28,[1]项目开票!A:A,报税!A28) -> 0 | AJ28: =SUMIFS([1]项目开票!M:M,[1]项目开票!B:B,报税!B28,[1]项目开票!A:A,报税!A28) -> 0 | AK28: =AG28-AI28 -> 0 | AL28: =AH28-AJ28 -> 0 | AS28: =G28+N28+U28+AB28+AI28+AO28 -> 0
A29: 河北沧县开元 | B29: 4620 | C29: EPC | G29: =SUMIFS([1]项目开票!C:C,[1]项目开票!B:B,报税!B29,[1]项目开票!A:A,报税!A29) -> 0 | H29: =SUMIFS([1]项目开票!D:D,[1]项目开票!B:B,报税!B29,[1]项目开票!A:A,报税!A29) -> 0 | I29: =E29-G29 -> 0 | J29: =F29-H29 -> 0 | N29: =SUMIFS([1]项目开票!O:O,[1]项目开票!B:B,报税!B29,[1]项目开票!A:A,报税!A29) -> 0 | O29: =SUMIFS([1]项目开票!P:P,[1]项目开票!B:B,报税!B29,[1]项目开票!A:A,报税!A29) -> 0 | P29: =L29-N29 -> 0 | Q29: =M29-O29 -> 0 | U29: =SUMIFS([1]项目开票!F:F,[1]项目开票!B:B,报税!B29,[1]项目开票!A:A,报税!A29) -> 0 | V29: =SUMIFS([1]项目开票!G:G,[1]项目开票!B:B,报税!B29,[1]项目开票!A:A,报税!A29) -> 0 | W29: =S29-U29 -> 0 | X29: =T29-V29 -> 0 | Y29: 59603.51 | Z29: 61093.6 | AA29: 3665.62 | AB29: =SUMIFS([1]项目开票!I:I,[1]项目开票!B:B,报税!B29,[1]项目开票!A:A,报税!A29) -> 999188.32 | AC29: =SUMIFS([1]项目开票!J:J,[1]项目开票!B:B,报税!B29,[1]项目开票!A:A,报税!A29) -> 59951.3 | AD29: =Z29-AB29 -> -938094.72 | AE29: =AA29-AC29 -> -56285.68 | AI29: =SUMIFS([1]项目开票!L:L,[1]项目开票!B:B,报税!B29,[1]项目开票!A:A,报税!A29) -> 0 | AJ29: =SUMIFS([1]项目开票!M:M,[1]项目开票!B:B,报税!B29,[1]项目开票!A:A,报税!A29) -> 0 | AK29: =AG29-AI29 -> 0 | AL29: =AH29-AJ29 -> 0 | AS29: =G29+N29+U29+AB29+AI29+AO29 -> 999188.32
A30: 民勤三期 | B30: 3397 | C30: EPC | G30: =SUMIFS([1]项目开票!C:C,[1]项目开票!B:B,报税!B30,[1]项目开票!A:A,报税!A30) -> 0 | H30: =SUMIFS([1]项目开票!D:D,[1]项目开票!B:B,报税!B30,[1]项目开票!A:A,报税!A30) -> 0 | I30: =E30-G30 -> 0 | J30: =F30-H30 -> 0 | N30: =SUMIFS([1]项目开票!O:O,[1]项目开票!B:B,报税!B30,[1]项目开票!A:A,报税!A30) -> 0 | O30: =SUMIFS([1]项目开票!P:P,[1]项目开票!B:B,报税!B30,[1]项目开票!A:A,报税!A30) -> 0 | P30: =L30-N30 -> 0 | Q30: =M30-O30 -> 0 | U30: =SUMIFS([1]项目开票!F:F,[1]项目开票!B:B,报税!B30,[1]项目开票!A:A,报税!A30) -> 0 | V30: =SUMIFS([1]项目开票!G:G,[1]项目开票!B:B,报税!B30,[1]项目开票!A:A,报税!A30) -> 0 | W30: =S30-U30 -> 0 | X30: =T30-V30 -> 0 | Y30: 59603.51 | Z30: 61093.6 | AA30: 3665.62 | AB30: =SUMIFS([1]项目开票!I:I,[1]项目开票!B:B,报税!B30,[1]项目开票!A:A,报税!A30) -> 61093.6 | AC30: =SUMIFS([1]项目开票!J:J,[1]项目开票!B:B,报税!B30,[1]项目开票!A:A,报税!A30) -> 3665.62 | AD30: =Z30-AB30 -> 0 | AE30: =AA30-AC30 -> 0 | AI30: =SUMIFS([1]项目开票!L:L,[1]项目开票!B:B,报税!B30,[1]项目开票!A:A,报税!A30) -> 0 | AJ30: =SUMIFS([1]项目开票!M:M,[1]项目开票!B:B,报税!B30,[1]项目开票!A:A,报税!A30) -> 0 | AK30: =AG30-AI30 -> 0 | AL30: =AH30-AJ30 -> 0 | AS30: =G30+N30+U30+AB30+AI30+AO30 -> 61093.6
A31: 锡盟防沙治沙二连浩特市20万kW | B31: 4304 | C31: EPC | G31: =SUMIFS([1]项目开票!C:C,[1]项目开票!B:B,报税!B31,[1]项目开票!A:A,报税!A31) -> 0 | H31: =SUMIFS([1]项目开票!D:D,[1]项目开票!B:B,报税!B31,[1]项目开票!A:A,报税!A31) -> 0 | I31: =E31-G31 -> 0 | J31: =F31-H31 -> 0 | N31: =SUMIFS([1]项目开票!O:O,[1]项目开票!B:B,报税!B31,[1]项目开票!A:A,报税!A31) -> 0 | O31: =SUMIFS([1]项目开票!P:P,[1]项目开票!B:B,报税!B31,[1]项目开票!A:A,报税!A31) -> 0 | P31: =L31-N31 -> 0 | Q31: =M31-O31 -> 0 | U31: =SUMIFS([1]项目开票!F:F,[1]项目开票!B:B,报税!B31,[1]项目开票!A:A,报税!A31) -> 0 | V31: =SUMIFS([1]项目开票!G:G,[1]项目开票!B:B,报税!B31,[1]项目开票!A:A,报税!A31) -> 0 | W31: =S31-U31 -> 0 | X31: =T31-V31 -> 0 | Y31: 47682.81 | Z31: 48874.88 | AA31: 2932.49 | AB31: =SUMIFS([1]项目开票!I:I,[1]项目开票!B:B,报税!B31,[1]项目开票!A:A,报税!A31) -> 586686.32 | AC31: =SUMIFS([1]项目开票!J:J,[1]项目开票!B:B,报税!B31,[1]项目开票!A:A,报税!A31) -> 35201.18 | AD31: =Z31-AB31 -> -537811.44 | AE31: =AA31-AC31 -> -32268.69 | AI31: =SUMIFS([1]项目开票!L:L,[1]项目开票!B:B,报税!B31,[1]项目开票!A:A,报税!A31) -> 0 | AJ31: =SUMIFS([1]项目开票!M:M,[1]项目开票!B:B,报税!B31,[1]项目开票!A:A,报税!A31) -> 0 | AK31: =AG31-AI31 -> 0 | AL31: =AH31-AJ31 -> 0 | AS31: =G31+N31+U31+AB31+AI31+AO31 -> 586686.32
A32: 阿拉善左旗 | B32: 4302 | C32: EPC | G32: =SUMIFS([1]项目开票!C:C,[1]项目开票!B:B,报税!B32,[1]项目开票!A:A,报税!A32) -> 0 | H32: =SUMIFS([1]项目开票!D:D,[1]项目开票!B:B,报税!B32,[1]项目开票!A:A,报税!A32) -> 0 | I32: =E32-G32 -> 0 | J32: =F32-H32 -> 0 | N32: =SUMIFS([1]项目开票!O:O,[1]项目开票!B:B,报税!B32,[1]项目开票!A:A,报税!A32) -> 0 | O32: =SUMIFS([1]项目开票!P:P,[1]项目开票!B:B,报税!B32,[1]项目开票!A:A,报税!A32) -> 0 | P32: =L32-N32 -> 0 | Q32: =M32-O32 -> 0 | U32: =SUMIFS([1]项目开票!F:F,[1]项目开票!B:B,报税!B32,[1]项目开票!A:A,报税!A32) -> 0 | V32: =SUMIFS([1]项目开票!G:G,[1]项目开票!B:B,报税!B32,[1]项目开票!A:A,报税!A32) -> 0 | W32: =S32-U32 -> 0 | X32: =T32-V32 -> 0 | Y32: 59603.51 | Z32: 61093.6 | AA32: 3665.62 | AB32: =SUMIFS([1]项目开票!I:I,[1]项目开票!B:B,报税!B32,[1]项目开票!A:A,报税!A32) -> 61093.6 | AC32: =SUMIFS([1]项目开票!J:J,[1]项目开票!B:B,报税!B32,[1]项目开票!A:A,报税!A32) -> 3665.62 | AD32: =Z32-AB32 -> 0 | AE32: =AA32-AC32 -> 0 | AI32: =SUMIFS([1]项目开票!L:L,[1]项目开票!B:B,报税!B32,[1]项目开票!A:A,报税!A32) -> 0 | AJ32: =SUMIFS([1]项目开票!M:M,[1]项目开票!B:B,报税!B32,[1]项目开票!A:A,报税!A32) -> 0 | AK32: =AG32-AI32 -> 0 | AL32: =AH32-AJ32 -> 0 | AS32: =G32+N32+U32+AB32+AI32+AO32 -> 61093.6
A33: 沧县三期沧县永乐风电场 | B33: 4312 | C33: EPC | G33: =SUMIFS([1]项目开票!C:C,[1]项目开票!B:B,报税!B33,[1]项目开票!A:A,报税!A33) -> 0 | H33: =SUMIFS([1]项目开票!D:D,[1]项目开票!B:B,报税!B33,[1]项目开票!A:A,报税!A33) -> 0 | I33: =E33-G33 -> 0 | J33: =F33-H33 -> 0 | N33: =SUMIFS([1]项目开票!O:O,[1]项目开票!B:B,报税!B33,[1]项目开票!A:A,报税!A33) -> 0 | O33: =SUMIFS([1]项目开票!P:P,[1]项目开票!B:B,报税!B33,[1]项目开票!A:A,报税!A33) -> 0 | P33: =L33-N33 -> 0 | Q33: =M33-O33 -> 0 | U33: =SUMIFS([1]项目开票!F:F,[1]项目开票!B:B,报税!B33,[1]项目开票!A:A,报税!A33) -> 0 | V33: =SUMIFS([1]项目开票!G:G,[1]项目开票!B:B,报税!B33,[1]项目开票!A:A,报税!A33) -> 0 | W33: =S33-U33 -> 0 | X33: =T33-V33 -> 0 | Y33: 59603.51 | Z33: 61093.6 | AA33: 3665.62 | AB33: =SUMIFS([1]项目开票!I:I,[1]项目开票!B:B,报税!B33,[1]项目开票!A:A,报税!A33) -> 409146.79 | AC33: =SUMIFS([1]项目开票!J:J,[1]项目开票!B:B,报税!B33,[1]项目开票!A:A,报税!A33) -> 24548.81 | AD33: =Z33-AB33 -> -348053.19 | AE33: =AA33-AC33 -> -20883.19 | AI33: =SUMIFS([1]项目开票!L:L,[1]项目开票!B:B,报税!B33,[1]项目开票!A:A,报税!A33) -> 0 | AJ33: =SUMIFS([1]项目开票!M:M,[1]项目开票!B:B,报税!B33,[1]项目开票!A:A,报税!A33) -> 0 | AK33: =AG33-AI33 -> 0 | AL33: =AH33-AJ33 -> 0 | AS33: =G33+N33+U33+AB33+AI33+AO33 -> 409146.79
A34: 大业EPC项目 | B34: 山东大业新能源有限公司 | C34: 对外EPC | D34: 1.1209041e+08 | E34: 1.3774398e+08 | F34: 12396958 | G34: =SUMIFS([1]项目开票!C:C,[1]项目开票!B:B,报税!B34,[1]项目开票!A:A,报税!A34) -> 0 | H34: =SUMIFS([1]项目开票!D:D,[1]项目开票!B:B,报税!B34,[1]项目开票!A:A,报税!A34) -> 0 | I34: =E34-G34 -> 1.3774398e+08 | J34: =F34-H34 -> 12396958 | K34: 2.9106224e+08 | L34: 2.9108043e+08 | M34: 37840455 | N34: =SUMIFS([1]项目开票!O:O,[1]项目开票!B:B,报税!B34,[1]项目开票!A:A,报税!A34) -> 0 | O34: =SUMIFS([1]项目开票!P:P,[1]项目开票!B:B,报税!B34,[1]项目开票!A:A,报税!A34) -> 0 | P34: =L34-N34 -> 2.9108043e+08 | Q34: =M34-O34 -> 37840455 | U34: =SUMIFS([1]项目开票!F:F,[1]项目开票!B:B,报税!B34,[1]项目开票!A:A,报税!A34) -> 0 | V34: =SUMIFS([1]项目开票!G:G,[1]项目开票!B:B,报税!B34,[1]项目开票!A:A,报税!A34) -> 0 | W34: =S34-U34 -> 0 | X34: =T34-V34 -> 0 | AB34: =SUMIFS([1]项目开票!I:I,[1]项目开票!B:B,报税!B34,[1]项目开票!A:A,报税!A34) -> 0 | AC34: =SUMIFS([1]项目开票!J:J,[1]项目开票!B:B,报税!B34,[1]项目开票!A:A,报税!A34) -> 0 | AD34: =Z34-AB34 -> 0 | AE34: =AA34-AC34 -> 0 | AI34: =SUMIFS([1]项目开票!L:L,[1]项目开票!B:B,报税!B34,[1]项目开票!A:A,报税!A34) -> 0 | AJ34: =SUMIFS([1]项目开票!M:M,[1]项目开票!B:B,报税!B34,[1]项目开票!A:A,报税!A34) -> 0 | AK34: =AG34-AI34 -> 0 | AL34: =AH34-AJ34 -> 0 | AQ34: =AM34-AO34 -> 0 | AR34: =AN34-AP34 -> 0 | AS34: =G34+N34+U34+AB34+AI34+AO34 -> 0
A35: 滨州二期 | B35: 4313 | C35: EPC | G35: =SUMIFS([1]项目开票!C:C,[1]项目开票!B:B,报税!B35,[1]项目开票!A:A,报税!A35) -> 0 | H35: =SUMIFS([1]项目开票!D:D,[1]项目开票!B:B,报税!B35,[1]项目开票!A:A,报税!A35) -> 0 | I35: =E35-G35 -> 0 | J35: =F35-H35 -> 0 | N35: =SUMIFS([1]项目开票!O:O,[1]项目开票!B:B,报税!B35,[1]项目开票!A:A,报税!A35) -> 0 | O35: =SUMIFS([1]项目开票!P:P,[1]项目开票!B:B,报税!B35,[1]项目开票!A:A,报税!A35) -> 0 | P35: =L35-N35 -> 0 | Q35: =M35-O35 -> 0 | U35: =SUMIFS([1]项目开票!F:F,[1]项目开票!B:B,报税!B35,[1]项目开票!A:A,报税!A35) -> 0 | V35: =SUMIFS([1]项目开票!G:G,[1]项目开票!B:B,报税!B35,[1]项目开票!A:A,报税!A35) -> 0 | W35: =S35-U35 -> 0 | X35: =T35-V35 -> 0 | Y35: 47682.81 | Z35: 48874.88 | AA35: 2932.49 | AB35: =SUMIFS([1]项目开票!I:I,[1]项目开票!B:B,报税!B35,[1]项目开票!A:A,报税!A35) -> 436473.13 | AC35: =SUMIFS([1]项目开票!J:J,[1]项目开票!B:B,报税!B35,[1]项目开票!A:A,报税!A35) -> 26188.39 | AD35: =Z35-AB35 -> -387598.25 | AE35: =AA35-AC35 -> -23255.9 | AI35: =SUMIFS([1]项目开票!L:L,[1]项目开票!B:B,报税!B35,[1]项目开票!A:A,报税!A35) -> 0 | AJ35: =SUMIFS([1]项目开票!M:M,[1]项目开票!B:B,报税!B35,[1]项目开票!A:A,报税!A35) -> 0 | AK35: =AG35-AI35 -> 0 | AL35: =AH35-AJ35 -> 0 | AQ35: =AM35-AO35 -> 0 | AR35: =AN35-AP35 -> 0 | AS35: =G35+N35+U35+AB35+AI35+AO35 -> 436473.13
A36: 广西邕宁百济风电场 | B36: 3403 | C36: EPC | G36: =SUMIFS([1]项目开票!C:C,[1]项目开票!B:B,报税!B36,[1]项目开票!A:A,报税!A36) -> 0 | H36: =SUMIFS([1]项目开票!D:D,[1]项目开票!B:B,报税!B36,[1]项目开票!A:A,报税!A36) -> 0 | I36: =E36-G36 -> 0 | J36: =F36-H36 -> 0 | N36: =SUMIFS([1]项目开票!O:O,[1]项目开票!B:B,报税!B36,[1]项目开票!A:A,报税!A36) -> 0 | O36: =SUMIFS([1]项目开票!P:P,[1]项目开票!B:B,报税!B36,[1]项目开票!A:A,报税!A36) -> 0 | P36: =L36-N36 -> 0 | Q36: =M36-O36 -> 0 | U36: =SUMIFS([1]项目开票!F:F,[1]项目开票!B:B,报税!B36,[1]项目开票!A:A,报税!A36) -> 0 | V36: =SUMIFS([1]项目开票!G:G,[1]项目开票!B:B,报税!B36,[1]项目开票!A:A,报税!A36) -> 0 | W36: =S36-U36 -> 0 | X36: =T36-V36 -> 0 | Y36: 47682.81 | Z36: 48874.88 | AA36: 2932.49 | AB36: =SUMIFS([1]项目开票!I:I,[1]项目开票!B:B,报税!B36,[1]项目开票!A:A,报税!A36) -> 399864.1 | AC36: =SUMIFS([1]项目开票!J:J,[1]项目开票!B:B,报税!B36,[1]项目开票!A:A,报税!A36) -> 23991.85 | AD36: =Z36-AB36 -> -350989.22 | AE36: =AA36-AC36 -> -21059.36 | AI36: =SUMIFS([1]项目开票!L:L,[1]项目开票!B:B,报税!B36,[1]项目开票!A:A,报税!A36) -> 0 | AJ36: =SUMIFS([1]项目开票!M:M,[1]项目开票!B:B,报税!B36,[1]项目开票!A:A,报税!A36) -> 0 | AK36: =AG36-AI36 -> 0 | AL36: =AH36-AJ36 -> 0 | AQ36: =AM36-AO36 -> 0 | AR36: =AN36-AP36 -> 0 | AS36: =G36+N36+U36+AB36+AI36+AO36 -> 399864.1
A37: 广西邕宁那楼中山风电场 | B37: 3398 | C37: EPC | G37: =SUMIFS([1]项目开票!C:C,[1]项目开票!B:B,报税!B37,[1]项目开票!A:A,报税!A37) -> 0 | H37: =SUMIFS([1]项目开票!D:D,[1]项目开票!B:B,报税!B37,[1]项目开票!A:A,报税!A37) -> 0 | I37: =E37-G37 -> 0 | J37: =F37-H37 -> 0 | N37: =SUMIFS([1]项目开票!O:O,[1]项目开票!B:B,报税!B37,[1]项目开票!A:A,报税!A37) -> 0 | O37: =SUMIFS([1]项目开票!P:P,[1]项目开票!B:B,报税!B37,[1]项目开票!A:A,报税!A37) -> 0 | P37: =L37-N37 -> 0 | Q37: =M37-O37 -> 0 | U37: =SUMIFS([1]项目开票!F:F,[1]项目开票!B:B,报税!B37,[1]项目开票!A:A,报税!A37) -> 0 | V37: =SUMIFS([1]项目开票!G:G,[1]项目开票!B:B,报税!B37,[1]项目开票!A:A,报税!A37) -> 0 | W37: =S37-U37 -> 0 | X37: =T37-V37 -> 0 | Y37: 47682.81 | Z37: 48874.88 | AA37: 2932.49 | AB37: =SUMIFS([1]项目开票!I:I,[1]项目开票!B:B,报税!B37,[1]项目开票!A:A,报税!A37) -> 399864.1 | AC37: =SUMIFS([1]项目开票!J:J,[1]项目开票!B:B,报税!B37,[1]项目开票!A:A,报税!A37) -> 23991.85 | AD37: =Z37-AB37 -> -350989.22 | AE37: =AA37-AC37 -> -21059.36 | AI37: =SUMIFS([1]项目开票!L:L,[1]项目开票!B:B,报税!B37,[1]项目开票!A:A,报税!A37) -> 0 | AJ37: =SUMIFS([1]项目开票!M:M,[1]项目开票!B:B,报税!B37,[1]项目开票!A:A,报税!A37) -> 0 | AK37: =AG37-AI37 -> 0 | AL37: =AH37-AJ37 -> 0 | AQ37: =AM37-AO37 -> 0 | AR37: =AN37-AP37 -> 0 | AS37: =G37+N37+U37+AB37+AI37+AO37 -> 399864.1
A38: 广西邕宁中和风电场 | B38: 3402 | C38: EPC | G38: =SUMIFS([1]项目开票!C:C,[1]项目开票!B:B,报税!B38,[1]项目开票!A:A,报税!A38) -> 0 | H38: =SUMIFS([1]项目开票!D:D,[1]项目开票!B:B,报税!B38,[1]项目开票!A:A,报税!A38) -> 0 | I38: =E38-G38 -> 0 | J38: =F38-H38 -> 0 | N38: =SUMIFS([1]项目开票!O:O,[1]项目开票!B:B,报税!B38,[1]项目开票!A:A,报税!A38) -> 0 | O38: =SUMIFS([1]项目开票!P:P,[1]项目开票!B:B,报税!B38,[1]项目开票!A:A,报税!A38) -> 0 | P38: =L38-N38 -> 0 | Q38: =M38-O38 -> 0 | U38: =SUMIFS([1]项目开票!F:F,[1]项目开票!B:B,报税!B38,[1]项目开票!A:A,报税!A38) -> 0 | V38: =SUMIFS([1]项目开票!G:G,[1]项目开票!B:B,报税!B38,[1]项目开票!A:A,报税!A38) -> 0 | W38: =S38-U38 -> 0 | X38: =T38-V38 -> 0 | Y38: 47682.81 | Z38: 48874.88 | AA38: 2932.49 | AB38: =SUMIFS([1]项目开票!I:I,[1]项目开票!B:B,报税!B38,[1]项目开票!A:A,报税!A38) -> 399864.1 | AC38: =SUMIFS([1]项目开票!J:J,[1]项目开票!B:B,报税!B38,[1]项目开票!A:A,报税!A38) -> 23991.85 | AD38: =Z38-AB38 -> -350989.22 | AE38: =AA38-AC38 -> -21059.36 | AI38: =SUMIFS([1]项目开票!L:L,[1]项目开票!B:B,报税!B38,[1]项目开票!A:A,报税!A38) -> 0 | AJ38: =SUMIFS([1]项目开票!M:M,[1]项目开票!B:B,报税!B38,[1]项目开票!A:A,报税!A38) -> 0 | AK38: =AG38-AI38 -> 0 | AL38: =AH38-AJ38 -> 0 | AQ38: =AM38-AO38 -> 0 | AR38: =AN38-AP38 -> 0 | AS38: =G38+N38+U38+AB38+AI38+AO38 -> 399864.1
A39: 四子王旗储能站 | B39: 4317 | C39: EPC | G39: =SUMIFS([1]项目开票!C:C,[1]项目开票!B:B,报税!B39,[1]项目开票!A:A,报税!A39) -> 0 | H39: =SUMIFS([1]项目开票!D:D,[1]项目开票!B:B,报税!B39,[1]项目开票!A:A,报税!A39) -> 0 | I39: =E39-G39 -> 0 | J39: =F39-H39 -> 0 | N39: =SUMIFS([1]项目开票!O:O,[1]项目开票!B:B,报税!B39,[1]项目开票!A:A,报税!A39) -> 0 | O39: =SUMIFS([1]项目开票!P:P,[1]项目开票!B:B,报税!B39,[1]项目开票!A:A,报税!A39) -> 0 | P39: =L39-N39 -> 0 | Q39: =M39-O39 -> 0 | U39: =SUMIFS([1]项目开票!F:F,[1]项目开票!B:B,报税!B39,[1]项目开票!A:A,报税!A39) -> 0 | V39: =SUMIFS([1]项目开票!G:G,[1]项目开票!B:B,报税!B39,[1]项目开票!A:A,报税!A39) -> 0 | W39: =S39-U39 -> 0 | X39: =T39-V39 -> 0 | Y39: 29801.75 | Z39: 29801.75 | AA39: 1788.11 | AB39: =SUMIFS([1]项目开票!I:I,[1]项目开票!B:B,报税!B39,[1]项目开票!A:A,报税!A39) -> 191331.26 | AC39: =SUMIFS([1]项目开票!J:J,[1]项目开票!B:B,报税!B39,[1]项目开票!A:A,报税!A39) -> 11479.88 | AD39: =Z39-AB39 -> -161529.51 | AE39: =AA39-AC39 -> -9691.77 | AI39: =SUMIFS([1]项目开票!L:L,[1]项目开票!B:B,报税!B39,[1]项目开票!A:A,报税!A39) -> 0 | AJ39: =SUMIFS([1]项目开票!M:M,[1]项目开票!B:B,报税!B39,[1]项目开票!A:A,报税!A39) -> 0 | AK39: =AG39-AI39 -> 0 | AL39: =AH39-AJ39 -> 0 | AQ39: =AM39-AO39 -> 0 | AR39: =AN39-AP39 -> 0 | AS39: =G39+N39+U39+AB39+AI39+AO39 -> 191331.26
A40: 白城洮北 | B40: 4650 | C40: EPC | G40: =SUMIFS([1]项目开票!C:C,[1]项目开票!B:B,报税!B40,[1]项目开票!A:A,报税!A40) -> 0 | H40: =SUMIFS([1]项目开票!D:D,[1]项目开票!B:B,报税!B40,[1]项目开票!A:A,报税!A40) -> 0 | I40: =E40-G40 -> 0 | J40: =F40-H40 -> 0 | N40: =SUMIFS([1]项目开票!O:O,[1]项目开票!B:B,报税!B40,[1]项目开票!A:A,报税!A40) -> 0 | O40: =SUMIFS([1]项目开票!P:P,[1]项目开票!B:B,报税!B40,[1]项目开票!A:A,报税!A40) -> 0 | P40: =L40-N40 -> 0 | Q40: =M40-O40 -> 0 | U40: =SUMIFS([1]项目开票!F:F,[1]项目开票!B:B,报税!B40,[1]项目开票!A:A,报税!A40) -> 0 | V40: =SUMIFS([1]项目开票!G:G,[1]项目开票!B:B,报税!B40,[1]项目开票!A:A,报税!A40) -> 0 | W40: =S40-U40 -> 0 | X40: =T40-V40 -> 0 | Y40: 33798.75 | Z40: 34643.72 | AA40: 2078.62 | AB40: =SUMIFS([1]项目开票!I:I,[1]项目开票!B:B,报税!B40,[1]项目开票!A:A,报税!A40) -> 34643.72 | AC40: =SUMIFS([1]项目开票!J:J,[1]项目开票!B:B,报税!B40,[1]项目开票!A:A,报税!A40) -> 2078.62 | AD40: =Z40-AB40 -> 0 | AE40: =AA40-AC40 -> 0 | AI40: =SUMIFS([1]项目开票!L:L,[1]项目开票!B:B,报税!B40,[1]项目开票!A:A,报税!A40) -> 0 | AJ40: =SUMIFS([1]项目开票!M:M,[1]项目开票!B:B,报税!B40,[1]项目开票!A:A,报税!A40) -> 0 | AK40: =AG40-AI40 -> 0 | AL40: =AH40-AJ40 -> 0 | AQ40: =AM40-AO40 -> 0 | AR40: =AN40-AP40 -> 0 | AS40: =G40+N40+U40+AB40+AI40+AO40 -> 34643.72
A41: 锡盟防沙治沙正镶白旗10万kW风电 | B41: 4305 | C41: EPC | G41: =SUMIFS([1]项目开票!C:C,[1]项目开票!B:B,报税!B41,[1]项目开票!A:A,报税!A41) -> 0 | H41: =SUMIFS([1]项目开票!D:D,[1]项目开票!B:B,报税!B41,[1]项目开票!A:A,报税!A41) -> 0 | I41: =E41-G41 -> 0 | J41: =F41-H41 -> 0 | N41: =SUMIFS([1]项目开票!O:O,[1]项目开票!B:B,报税!B41,[1]项目开票!A:A,报税!A41) -> 0 | O41: =SUMIFS([1]项目开票!P:P,[1]项目开票!B:B,报税!B41,[1]项目开票!A:A,报税!A41) -> 0 | P41: =L41-N41 -> 0 | Q41: =M41-O41 -> 0 | U41: =SUMIFS([1]项目开票!F:F,[1]项目开票!B:B,报税!B41,[1]项目开票!A:A,报税!A41) -> 0 | V41: =SUMIFS([1]项目开票!G:G,[1]项目开票!B:B,报税!B41,[1]项目开票!A:A,报税!A41) -> 0 | W41: =S41-U41 -> 0 | X41: =T41-V41 -> 0 | Y41: 47682.81 | Z41: 48874.88 | AA41: 2932.49 | AB41: =SUMIFS([1]项目开票!I:I,[1]项目开票!B:B,报税!B41,[1]项目开票!A:A,报税!A41) -> 48874.88 | AC41: =SUMIFS([1]项目开票!J:J,[1]项目开票!B:B,报税!B41,[1]项目开票!A:A,报税!A41) -> 2932.49 | AD41: =Z41-AB41 -> 0 | AE41: =AA41-AC41 -> 0 | AI41: =SUMIFS([1]项目开票!L:L,[1]项目开票!B:B,报税!B41,[1]项目开票!A:A,报税!A41) -> 0 | AJ41: =SUMIFS([1]项目开票!M:M,[1]项目开票!B:B,报税!B41,[1]项目开票!A:A,报税!A41) -> 0 | AK41: =AG41-AI41 -> 0 | AL41: =AH41-AJ41 -> 0 | AQ41: =AM41-AO41 -> 0 | AR41: =AN41-AP41 -> 0 | AS41: =G41+N41+U41+AB41+AI41+AO41 -> 48874.88
A42: 沧县四期沧县长芦风电场 | B42: 4318 | C42: EPC | G42: =SUMIFS([1]项目开票!C:C,[1]项目开票!B:B,报税!B42,[1]项目开票!A:A,报税!A42) -> 0 | H42: =SUMIFS([1]项目开票!D:D,[1]项目开票!B:B,报税!B42,[1]项目开票!A:A,报税!A42) -> 0 | I42: =E42-G42 -> 0 | J42: =F42-H42 -> 0 | N42: =SUMIFS([1]项目开票!O:O,[1]项目开票!B:B,报税!B42,[1]项目开票!A:A,报税!A42) -> 0 | O42: =SUMIFS([1]项目开票!P:P,[1]项目开票!B:B,报税!B42,[1]项目开票!A:A,报税!A42) -> 0 | P42: =L42-N42 -> 0 | Q42: =M42-O42 -> 0 | U42: =SUMIFS([1]项目开票!F:F,[1]项目开票!B:B,报税!B42,[1]项目开票!A:A,报税!A42) -> 0 | V42: =SUMIFS([1]项目开票!G:G,[1]项目开票!B:B,报税!B42,[1]项目开票!A:A,报税!A42) -> 0 | W42: =S42-U42 -> 0 | X42: =T42-V42 -> 0 | Y42: 25804.76 | Z42: 26449.88 | AA42: 1586.99 | AB42: =SUMIFS([1]项目开票!I:I,[1]项目开票!B:B,报税!B42,[1]项目开票!A:A,报税!A42) -> 512542.19 | AC42: =SUMIFS([1]项目开票!J:J,[1]项目开票!B:B,报税!B42,[1]项目开票!A:A,报税!A42) -> 30752.52 | AD42: =Z42-AB42 -> -486092.31 | AE42: =AA42-AC42 -> -29165.53 | AI42: =SUMIFS([1]项目开票!L:L,[1]项目开票!B:B,报税!B42,[1]项目开票!A:A,报税!A42) -> 0 | AJ42: =SUMIFS([1]项目开票!M:M,[1]项目开票!B:B,报税!B42,[1]项目开票!A:A,报税!A42) -> 0 | AK42: =AG42-AI42 -> 0 | AL42: =AH42-AJ42 -> 0 | AQ42: =AM42-AO42 -> 0 | AR42: =AN42-AP42 -> 0 | AS42: =G42+N42+U42+AB42+AI42+AO42 -> 512542.19
A43: 零碳合金 | B43: XJ00 | C43: EPC | G43: =SUMIFS([1]项目开票!C:C,[1]项目开票!B:B,报税!B43,[1]项目开票!A:A,报税!A43) -> 0 | H43: =SUMIFS([1]项目开票!D:D,[1]项目开票!B:B,报税!B43,[1]项目开票!A:A,报税!A43) -> 0 | I43: =E43-G43 -> 0 | J43: =F43-H43 -> 0 | N43: =SUMIFS([1]项目开票!O:O,[1]项目开票!B:B,报税!B43,[1]项目开票!A:A,报税!A43) -> 0 | O43: =SUMIFS([1]项目开票!P:P,[1]项目开票!B:B,报税!B43,[1]项目开票!A:A,报税!A43) -> 0 | P43: =L43-N43 -> 0 | Q43: =M43-O43 -> 0 | U43: =SUMIFS([1]项目开票!F:F,[1]项目开票!B:B,报税!B43,[1]项目开票!A:A,报税!A43) -> 0 | V43: =SUMIFS([1]项目开票!G:G,[1]项目开票!B:B,报税!B43,[1]项目开票!A:A,报税!A43) -> 0 | W43: =S43-U43 -> 0 | X43: =T43-V43 -> 0 | Y43: 46620.51 | Z43: 47786.02 | AA43: 2867.16 | AB43: =SUMIFS([1]项目开票!I:I,[1]项目开票!B:B,报税!B43,[1]项目开票!A:A,报税!A43) -> 47786.02 | AC43: =SUMIFS([1]项目开票!J:J,[1]项目开票!B:B,报税!B43,[1]项目开票!A:A,报税!A43) -> 2867.16 | AD43: =Z43-AB43 -> 0 | AE43: =AA43-AC43 -> 0 | AI43: =SUMIFS([1]项目开票!L:L,[1]项目开票!B:B,报税!B43,[1]项目开票!A:A,报税!A43) -> 0 | AJ43: =SUMIFS([1]项目开票!M:M,[1]项目开票!B:B,报税!B43,[1]项目开票!A:A,报税!A43) -> 0 | AK43: =AG43-AI43 -> 0 | AL43: =AH43-AJ43 -> 0 | AQ43: =AM43-AO43 -> 0 | AR43: =AN43-AP43 -> 0 | AS43: =G43+N43+U43+AB43+AI43+AO43 -> 47786.02
A44: 赤峰市能源物联网零碳氢氨一体化示范项目（元宝山区34兆瓦光伏） | B44: XC00 | C44: EPC | D44: 1995305.6 | E44: 2045188.2 | F44: 184066.94 | G44: =SUMIFS([1]项目开票!C:C,[1]项目开票!B:B,报税!B44,[1]项目开票!A:A,报税!A44) -> 0 | H44: =SUMIFS([1]项目开票!D:D,[1]项目开票!B:B,报税!B44,[1]项目开票!A:A,报税!A44) -> 0 | I44: =E44-G44 -> 2045188.2 | J44: =F44-H44 -> 184066.94 | K44: 139169.19 | L44: 150950.93 | M44: 19623.62 | N44: =SUMIFS([1]项目开票!O:O,[1]项目开票!B:B,报税!B44,[1]项目开票!A:A,报税!A44) -> 0 | O44: =SUMIFS([1]项目开票!P:P,[1]项目开票!B:B,报税!B44,[1]项目开票!A:A,报税!A44) -> 0 | P44: =L44-N44 -> 150950.93 | Q44: =M44-O44 -> 19623.62 | R44: 2086401.1 | S44: 2138561.1 | T44: 128313.67 | U44: =SUMIFS([1]项目开票!F:F,[1]项目开票!B:B,报税!B44,[1]项目开票!A:A,报税!A44) -> 0 | V44: =SUMIFS([1]项目开票!G:G,[1]项目开票!B:B,报税!B44,[1]项目开票!A:A,报税!A44) -> 0 | W44: =S44-U44 -> 2138561.1 | X44: =T44-V44 -> 128313.67 | AB44: =SUMIFS([1]项目开票!I:I,[1]项目开票!B:B,报税!B44,[1]项目开票!A:A,报税!A44) -> 0 | AC44: =SUMIFS([1]项目开票!J:J,[1]项目开票!B:B,报税!B44,[1]项目开票!A:A,报税!A44) -> 0 | AD44: =Z44-AB44 -> 0 | AE44: =AA44-AC44 -> 0 | AI44: =SUMIFS([1]项目开票!L:L,[1]项目开票!B:B,报税!B44,[1]项目开票!A:A,报税!A44) -> 0 | AJ44: =SUMIFS([1]项目开票!M:M,[1]项目开票!B:B,报税!B44,[1]项目开票!A:A,报税!A44) -> 0 | AK44: =AG44-AI44 -> 0 | AL44: =AH44-AJ44 -> 0 | AQ44: =AM44-AO44 -> 0 | AR44: =AN44-AP44 -> 0 | AS44: =G44+N44+U44+AB44+AI44+AO44 -> 0
A45: 五河彩舟 | B45: 2342 | C45: EPC | D45: 68830378 | E45: 75861442 | F45: 6827529.8 | G45: =SUMIFS([1]项目开票!C:C,[1]项目开票!B:B,报税!B45,[1]项目开票!A:A,报税!A45) -> 0 | H45: =SUMIFS([1]项目开票!D:D,[1]项目开票!B:B,报税!B45,[1]项目开票!A:A,报税!A45) -> 0 | I45: =E45-G45 -> 75861442 | J45: =F45-H45 -> 6827529.8 | K45: 1.9741622e+08 | L45: 2.041575e+08 | M45: 26540475 | N45: =SUMIFS([1]项目开票!O:O,[1]项目开票!B:B,报税!B45,[1]项目开票!A:A,报税!A45) -> 0 | O45: =SUMIFS([1]项目开票!P:P,[1]项目开票!B:B,报税!B45,[1]项目开票!A:A,报税!A45) -> 0 | P45: =L45-N45 -> 2.041575e+08 | Q45: =M45-O45 -> 26540475 | R45: 27202003 | S45: 24301284 | T45: 1458077 | U45: =SUMIFS([1]项目开票!F:F,[1]项目开票!B:B,报税!B45,[1]项目开票!A:A,报税!A45) -> 0 | V45: =SUMIFS([1]项目开票!G:G,[1]项目开票!B:B,报税!B45,[1]项目开票!A:A,报税!A45) -> 0 | W45: =S45-U45 -> 24301284 | X45: =T45-V45 -> 1458077 | Y45: 47682.81 | Z45: 48874.88 | AA45: 2932.49 | AB45: =SUMIFS([1]项目开票!I:I,[1]项目开票!B:B,报税!B45,[1]项目开票!A:A,报税!A45) -> 48874.88 | AC45: =SUMIFS([1]项目开票!J:J,[1]项目开票!B:B,报税!B45,[1]项目开票!A:A,报税!A45) -> 2932.49 | AD45: =Z45-AB45 -> 0 | AE45: =AA45-AC45 -> 0 | AI45: =SUMIFS([1]项目开票!L:L,[1]项目开票!B:B,报税!B45,[1]项目开票!A:A,报税!A45) -> 0 | AJ45: =SUMIFS([1]项目开票!M:M,[1]项目开票!B:B,报税!B45,[1]项目开票!A:A,报税!A45) -> 0 | AK45: =AG45-AI45 -> 0 | AL45: =AH45-AJ45 -> 0 | AQ45: =AM45-AO45 -> 0 | AR45: =AN45-AP45 -> 0 | AS45: =G45+N45+U45+AB45+AI45+AO45 -> 48874.88
A46: 赤峰市风光制氢一体化项目-赤峰翁牛特旗P1-850 | B46: XC00 | C46: EPC | G46: =SUMIFS([1]项目开票!C:C,[1]项目开票!B:B,报税!B46,[1]项目开票!A:A,报税!A46) -> 0 | H46: =SUMIFS([1]项目开票!D:D,[1]项目开票!B:B,报税!B46,[1]项目开票!A:A,报税!A46) -> 0 | I46: =E46-G46 -> 0 | J46: =F46-H46 -> 0 | N46: =SUMIFS([1]项目开票!O:O,[1]项目开票!B:B,报税!B46,[1]项目开票!A:A,报税!A46) -> 0 | O46: =SUMIFS([1]项目开票!P:P,[1]项目开票!B:B,报税!B46,[1]项目开票!A:A,报税!A46) -> 0 | P46: =L46-N46 -> 0 | Q46: =M46-O46 -> 0 | U46: =SUMIFS([1]项目开票!F:F,[1]项目开票!B:B,报税!B46,[1]项目开票!A:A,报税!A46) -> 0 | V46: =SUMIFS([1]项目开票!G:G,[1]项目开票!B:B,报税!B46,[1]项目开票!A:A,报税!A46) -> 0 | W46: =S46-U46 -> 0 | X46: =T46-V46 -> 0 | Y46: 64103.14 | Z46: 65705.72 | AA46: 3942.34 | AB46: =SUMIFS([1]项目开票!I:I,[1]项目开票!B:B,报税!B46,[1]项目开票!A:A,报税!A46) -> 65705.72 | AC46: =SUMIFS([1]项目开票!J:J,[1]项目开票!B:B,报税!B46,[1]项目开票!A:A,报税!A46) -> 3942.34 | AD46: =Z46-AB46 -> 0 | AE46: =AA46-AC46 -> 0 | AI46: =SUMIFS([1]项目开票!L:L,[1]项目开票!B:B,报税!B46,[1]项目开票!A:A,报税!A46) -> 0 | AJ46: =SUMIFS([1]项目开票!M:M,[1]项目开票!B:B,报税!B46,[1]项目开票!A:A,报税!A46) -> 0 | AK46: =AG46-AI46 -> 0 | AL46: =AH46-AJ46 -> 0 | AQ46: =AM46-AO46 -> 0 | AR46: =AN46-AP46 -> 0 | AS46: =G46+N46+U46+AB46+AI46+AO46 -> 65705.72
A47: 呼市武川100万千瓦/400万千瓦时储能 | B47: 4A60 | C47: EPC | D47: 58830638 | E47: 17323176 | F47: 1559085.9 | G47: =SUMIFS([1]项目开票!C:C,[1]项目开票!B:B,报税!B47,[1]项目开票!A:A,报税!A47) -> 0 | H47: =SUMIFS([1]项目开票!D:D,[1]项目开票!B:B,报税!B47,[1]项目开票!A:A,报税!A47) -> 0 | I47: =E47-G47 -> 17323176 | J47: =F47-H47 -> 1559085.9 | K47: 40628973 | L47: 42922183 | M47: 5579883.8 | N47: =SUMIFS([1]项目开票!O:O,[1]项目开票!B:B,报税!B47,[1]项目开票!A:A,报税!A47) -> 0 | O47: =SUMIFS([1]项目开票!P:P,[1]项目开票!B:B,报税!B47,[1]项目开票!A:A,报税!A47) -> 0 | P47: =L47-N47 -> 42922183 | Q47: =M47-O47 -> 5579883.8 | R47: 19367687 | S47: 25591172 | T47: 1535470.4 | U47: =SUMIFS([1]项目开票!F:F,[1]项目开票!B:B,报税!B47,[1]项目开票!A:A,报税!A47) -> 0 | V47: =SUMIFS([1]项目开票!G:G,[1]项目开票!B:B,报税!B47,[1]项目开票!A:A,报税!A47) -> 0 | W47: =S47-U47 -> 25591172 | X47: =T47-V47 -> 1535470.4 | Y47: 29801.75 | Z47: 30546.79 | AA47: 1832.81 | AB47: =SUMIFS([1]项目开票!I:I,[1]项目开票!B:B,报税!B47,[1]项目开票!A:A,报税!A47) -> 30546.79 | AC47: =SUMIFS([1]项目开票!J:J,[1]项目开票!B:B,报税!B47,[1]项目开票!A:A,报税!A47) -> 1832.81 | AD47: =Z47-AB47 -> 0 | AE47: =AA47-AC47 -> 0 | AI47: =SUMIFS([1]项目开票!L:L,[1]项目开票!B:B,报税!B47,[1]项目开票!A:A,报税!A47) -> 0 | AJ47: =SUMIFS([1]项目开票!M:M,[1]项目开票!B:B,报税!B47,[1]项目开票!A:A,报税!A47) -> 0 | AK47: =AG47-AI47 -> 0 | AL47: =AH47-AJ47 -> 0 | AQ47: =AM47-AO47 -> 0 | AR47: =AN47-AP47 -> 0 | AS47: =G47+N47+U47+AB47+AI47+AO47 -> 30546.79
A48: 阿拉善1000MW/4000MWh储能 | B48: 4307 | C48: EPC | D48: 40025103 | E48: 84269003 | F48: 7584210.3 | G48: =SUMIFS([1]项目开票!C:C,[1]项目开票!B:B,报税!B48,[1]项目开票!A:A,报税!A48) -> 0 | H48: =SUMIFS([1]项目开票!D:D,[1]项目开票!B:B,报税!B48,[1]项目开票!A:A,报税!A48) -> 0 | I48: =E48-G48 -> 84269003 | J48: =F48-H48 -> 7584210.3 | K48: 44318051 | L48: 45426002 | M48: 5905380.3 | N48: =SUMIFS([1]项目开票!O:O,[1]项目开票!B:B,报税!B48,[1]项目开票!A:A,报税!A48) -> 0 | O48: =SUMIFS([1]项目开票!P:P,[1]项目开票!B:B,报税!B48,[1]项目开票!A:A,报税!A48) -> 0 | P48: =L48-N48 -> 45426002 | Q48: =M48-O48 -> 5905380.3 | R48: 25074876 | S48: 26590364 | T48: 1595421.9 | U48: =SUMIFS([1]项目开票!F:F,[1]项目开票!B:B,报税!B48,[1]项目开票!A:A,报税!A48) -> 0 | V48: =SUMIFS([1]项目开票!G:G,[1]项目开票!B:B,报税!B48,[1]项目开票!A:A,报税!A48) -> 0 | W48: =S48-U48 -> 26590364 | X48: =T48-V48 -> 1595421.9 | Y48: 29801.75 | Z48: 30546.79 | AA48: 1832.81 | AB48: =SUMIFS([1]项目开票!I:I,[1]项目开票!B:B,报税!B48,[1]项目开票!A:A,报税!A48) -> 30546.79 | AC48: =SUMIFS([1]项目开票!J:J,[1]项目开票!B:B,报税!B48,[1]项目开票!A:A,报税!A48) -> 1832.81 | AD48: =Z48-AB48 -> 0 | AE48: =AA48-AC48 -> 0 | AI48: =SUMIFS([1]项目开票!L:L,[1]项目开票!B:B,报税!B48,[1]项目开票!A:A,报税!A48) -> 0 | AJ48: =SUMIFS([1]项目开票!M:M,[1]项目开票!B:B,报税!B48,[1]项目开票!A:A,报税!A48) -> 0 | AK48: =AG48-AI48 -> 0 | AL48: =AH48-AJ48 -> 0 | AQ48: =AM48-AO48 -> 0 | AR48: =AN48-AP48 -> 0 | AS48: =G48+N48+U48+AB48+AI48+AO48 -> 30546.79
A49: 唐山乐亭项目（保障性） | B49: 4315 | C49: EPC | G49: =SUMIFS([1]项目开票!C:C,[1]项目开票!B:B,报税!B49,[1]项目开票!A:A,报税!A49) -> 0 | H49: =SUMIFS([1]项目开票!D:D,[1]项目开票!B:B,报税!B49,[1]项目开票!A:A,报税!A49) -> 0 | I49: =E49-G49 -> 0 | J49: =F49-H49 -> 0 | N49: =SUMIFS([1]项目开票!O:O,[1]项目开票!B:B,报税!B49,[1]项目开票!A:A,报税!A49) -> 0 | O49: =SUMIFS([1]项目开票!P:P,[1]项目开票!B:B,报税!B49,[1]项目开票!A:A,报税!A49) -> 0 | P49: =L49-N49 -> 0 | Q49: =M49-O49 -> 0 | U49: =SUMIFS([1]项目开票!F:F,[1]项目开票!B:B,报税!B49,[1]项目开票!A:A,报税!A49) -> 0 | V49: =SUMIFS([1]项目开票!G:G,[1]项目开票!B:B,报税!B49,[1]项目开票!A:A,报税!A49) -> 0 | W49: =S49-U49 -> 0 | X49: =T49-V49 -> 0 | Y49: 28385.24 | Z49: 28385.24 | AA49: 1703.11 | AB49: =SUMIFS([1]项目开票!I:I,[1]项目开票!B:B,报税!B49,[1]项目开票!A:A,报税!A49) -> 28385.24 | AC49: =SUMIFS([1]项目开票!J:J,[1]项目开票!B:B,报税!B49,[1]项目开票!A:A,报税!A49) -> 1703.11 | AD49: =Z49-AB49 -> 0 | AE49: =AA49-AC49 -> 0 | AI49: =SUMIFS([1]项目开票!L:L,[1]项目开票!B:B,报税!B49,[1]项目开票!A:A,报税!A49) -> 0 | AJ49: =SUMIFS([1]项目开票!M:M,[1]项目开票!B:B,报税!B49,[1]项目开票!A:A,报税!A49) -> 0 | AK49: =AG49-AI49 -> 0 | AL49: =AH49-AJ49 -> 0 | AQ49: =AM49-AO49 -> 0 | AR49: =AN49-AP49 -> 0 | AS49: =G49+N49+U49+AB49+AI49+AO49 -> 28385.24
A50: 唐山乐亭项目（市场化） | B50: 4316 | C50: EPC | G50: =SUMIFS([1]项目开票!C:C,[1]项目开票!B:B,报税!B50,[1]项目开票!A:A,报税!A50) -> 0 | H50: =SUMIFS([1]项目开票!D:D,[1]项目开票!B:B,报税!B50,[1]项目开票!A:A,报税!A50) -> 0 | I50: =E50-G50 -> 0 | J50: =F50-H50 -> 0 | N50: =SUMIFS([1]项目开票!O:O,[1]项目开票!B:B,报税!B50,[1]项目开票!A:A,报税!A50) -> 0 | O50: =SUMIFS([1]项目开票!P:P,[1]项目开票!B:B,报税!B50,[1]项目开票!A:A,报税!A50) -> 0 | P50: =L50-N50 -> 0 | Q50: =M50-O50 -> 0 | U50: =SUMIFS([1]项目开票!F:F,[1]项目开票!B:B,报税!B50,[1]项目开票!A:A,报税!A50) -> 0 | V50: =SUMIFS([1]项目开票!G:G,[1]项目开票!B:B,报税!B50,[1]项目开票!A:A,报税!A50) -> 0 | W50: =S50-U50 -> 0 | X50: =T50-V50 -> 0 | Y50: 28385.24 | Z50: 28385.24 | AA50: 1703.11 | AB50: =SUMIFS([1]项目开票!I:I,[1]项目开票!B:B,报税!B50,[1]项目开票!A:A,报税!A50) -> 28385.24 | AC50: =SUMIFS([1]项目开票!J:J,[1]项目开票!B:B,报税!B50,[1]项目开票!A:A,报税!A50) -> 1703.11 | AD50: =Z50-AB50 -> 0 | AE50: =AA50-AC50 -> 0 | AI50: =SUMIFS([1]项目开票!L:L,[1]项目开票!B:B,报税!B50,[1]项目开票!A:A,报税!A50) -> 0 | AJ50: =SUMIFS([1]项目开票!M:M,[1]项目开票!B:B,报税!B50,[1]项目开票!A:A,报税!A50) -> 0 | AK50: =AG50-AI50 -> 0 | AL50: =AH50-AJ50 -> 0 | AQ50: =AM50-AO50 -> 0 | AR50: =AN50-AP50 -> 0 | AS50: =G50+N50+U50+AB50+AI50+AO50 -> 28385.24
A51: 龙江 | B51: 4340 | C51: EPC | G51: =SUMIFS([1]项目开票!C:C,[1]项目开票!B:B,报税!B51,[1]项目开票!A:A,报税!A51) -> 0 | H51: =SUMIFS([1]项目开票!D:D,[1]项目开票!B:B,报税!B51,[1]项目开票!A:A,报税!A51) -> 0 | I51: =E51-G51 -> 0 | J51: =F51-H51 -> 0 | K51: 0 | N51: =SUMIFS([1]项目开票!O:O,[1]项目开票!B:B,报税!B51,[1]项目开票!A:A,报税!A51) -> 0 | O51: =SUMIFS([1]项目开票!P:P,[1]项目开票!B:B,报税!B51,[1]项目开票!A:A,报税!A51) -> 0 | P51: =L51-N51 -> 0 | Q51: =M51-O51 -> 0 | U51: =SUMIFS([1]项目开票!F:F,[1]项目开票!B:B,报税!B51,[1]项目开票!A:A,报税!A51) -> 0 | V51: =SUMIFS([1]项目开票!G:G,[1]项目开票!B:B,报税!B51,[1]项目开票!A:A,报税!A51) -> 0 | W51: =S51-U51 -> 0 | X51: =T51-V51 -> 0 | AB51: =SUMIFS([1]项目开票!I:I,[1]项目开票!B:B,报税!B51,[1]项目开票!A:A,报税!A51) -> 0 | AC51: =SUMIFS([1]项目开票!J:J,[1]项目开票!B:B,报税!B51,[1]项目开票!A:A,报税!A51) -> 0 | AD51: =Z51-AB51 -> 0 | AE51: =AA51-AC51 -> 0 | AI51: =SUMIFS([1]项目开票!L:L,[1]项目开票!B:B,报税!B51,[1]项目开票!A:A,报税!A51) -> 0 | AJ51: =SUMIFS([1]项目开票!M:M,[1]项目开票!B:B,报税!B51,[1]项目开票!A:A,报税!A51) -> 0 | AK51: =AG51-AI51 -> 0 | AL51: =AH51-AJ51 -> 0 | AS51: =G51+N51+U51+AB51+AI51+AO51 -> 0
A52: 谷山梁1000MW/4000MWh | B52: 4A00 | C52: EPC | D52: 76209312 | E52: 2.1767793e+08 | F52: 19591013 | G52: =SUMIFS([1]项目开票!C:C,[1]项目开票!B:B,报税!B52,[1]项目开票!A:A,报税!A52) -> 0 | H52: =SUMIFS([1]项目开票!D:D,[1]项目开票!B:B,报税!B52,[1]项目开票!A:A,报税!A52) -> 0 | I52: =E52-G52 -> 2.1767793e+08 | J52: =F52-H52 -> 19591013 | K52: 8.9795472e+08 | L52: 9.2635848e+08 | M52: 1.204266e+08 | N52: =SUMIFS([1]项目开票!O:O,[1]项目开票!B:B,报税!B52,[1]项目开票!A:A,报税!A52) -> 0 | O52: =SUMIFS([1]项目开票!P:P,[1]项目开票!B:B,报税!B52,[1]项目开票!A:A,报税!A52) -> 0 | P52: =L52-N52 -> 9.2635848e+08 | Q52: =M52-O52 -> 1.204266e+08 | R52: 25474927 | S52: -294317.81 | T52: -17659.07 | U52: =SUMIFS([1]项目开票!F:F,[1]项目开票!B:B,报税!B52,[1]项目开票!A:A,报税!A52) -> 0 | V52: =SUMIFS([1]项目开票!G:G,[1]项目开票!B:B,报税!B52,[1]项目开票!A:A,报税!A52) -> 0 | W52: =S52-U52 -> -294317.81 | X52: =T52-V52 -> -17659.07 | Y52: 29801.75 | Z52: -30546.79 | AA52: -1832.81 | AB52: =SUMIFS([1]项目开票!I:I,[1]项目开票!B:B,报税!B52,[1]项目开票!A:A,报税!A52) -> -30546.79 | AC52: =SUMIFS([1]项目开票!J:J,[1]项目开票!B:B,报税!B52,[1]项目开票!A:A,报税!A52) -> -1832.81 | AD52: =Z52-AB52 -> 0 | AE52: =AA52-AC52 -> 0 | AI52: =SUMIFS([1]项目开票!L:L,[1]项目开票!B:B,报税!B52,[1]项目开票!A:A,报税!A52) -> 0 | AJ52: =SUMIFS([1]项目开票!M:M,[1]项目开票!B:B,报税!B52,[1]项目开票!A:A,报税!A52) -> 0 | AK52: =AG52-AI52 -> 0 | AL52: =AH52-AJ52 -> 0 | AS52: =G52+N52+U52+AB52+AI52+AO52 -> -30546.79
A53: F-001812大唐宁夏灵武风电场3年检修维护 | B53: 大唐灵武新能源有限公司 | C53: 后服务收入 | G53: =SUMIFS([1]项目开票!C:C,[1]项目开票!B:B,报税!B53,[1]项目开票!A:A,报税!A53) -> 0 | H53: =SUMIFS([1]项目开票!D:D,[1]项目开票!B:B,报税!B53,[1]项目开票!A:A,报税!A53) -> 0 | I53: =E53-G53 -> 0 | J53: =F53-H53 -> 0 | N53: =SUMIFS([1]项目开票!O:O,[1]项目开票!B:B,报税!B53,[1]项目开票!A:A,报税!A53) -> 0 | O53: =SUMIFS([1]项目开票!P:P,[1]项目开票!B:B,报税!B53,[1]项目开票!A:A,报税!A53) -> 0 | P53: =L53-N53 -> 0 | Q53: =M53-O53 -> 0 | R53: 94107.43 | S53: 96520.44 | T53: 5791.23 | U53: =SUMIFS([1]项目开票!F:F,[1]项目开票!B:B,报税!B53,[1]项目开票!A:A,报税!A53) -> 0 | V53: =SUMIFS([1]项目开票!G:G,[1]项目开票!B:B,报税!B53,[1]项目开票!A:A,报税!A53) -> 0 | W53: =S53-U53 -> 96520.44 | X53: =T53-V53 -> 5791.23 | AB53: =SUMIFS([1]项目开票!I:I,[1]项目开票!B:B,报税!B53,[1]项目开票!A:A,报税!A53) -> 0 | AC53: =SUMIFS([1]项目开票!J:J,[1]项目开票!B:B,报税!B53,[1]项目开票!A:A,报税!A53) -> 0 | AD53: =Z53-AB53 -> 0 | AE53: =AA53-AC53 -> 0 | AI53: =SUMIFS([1]项目开票!L:L,[1]项目开票!B:B,报税!B53,[1]项目开票!A:A,报税!A53) -> 0 | AJ53: =SUMIFS([1]项目开票!M:M,[1]项目开票!B:B,报税!B53,[1]项目开票!A:A,报税!A53) -> 0 | AK53: =AG53-AI53 -> 0 | AL53: =AH53-AJ53 -> 0 | AS53: =G53+N53+U53+AB53+AI53+AO53 -> 0
A54: 睿景代后服务（致博）人员费用 | B54: 1000 | C54: EPC | G54: =SUMIFS([1]项目开票!C:C,[1]项目开票!B:B,报税!B54,[1]项目开票!A:A,报税!A54) -> 0 | H54: =SUMIFS([1]项目开票!D:D,[1]项目开票!B:B,报税!B54,[1]项目开票!A:A,报税!A54) -> 0 | I54: =E54-G54 -> 0 | J54: =F54-H54 -> 0 | N54: =SUMIFS([1]项目开票!O:O,[1]项目开票!B:B,报税!B54,[1]项目开票!A:A,报税!A54) -> 0 | O54: =SUMIFS([1]项目开票!P:P,[1]项目开票!B:B,报税!B54,[1]项目开票!A:A,报税!A54) -> 0 | P54: =L54-N54 -> 0 | Q54: =M54-O54 -> 0 | U54: =SUMIFS([1]项目开票!F:F,[1]项目开票!B:B,报税!B54,[1]项目开票!A:A,报税!A54) -> 0 | V54: =SUMIFS([1]项目开票!G:G,[1]项目开票!B:B,报税!B54,[1]项目开票!A:A,报税!A54) -> 0 | W54: =S54-U54 -> 0 | X54: =T54-V54 -> 0 | Y54: 71146.76 | Z54: 74704.1 | AA54: 4482.25 | AB54: =SUMIFS([1]项目开票!I:I,[1]项目开票!B:B,报税!B54,[1]项目开票!A:A,报税!A54) -> 74704.1 | AC54: =SUMIFS([1]项目开票!J:J,[1]项目开票!B:B,报税!B54,[1]项目开票!A:A,报税!A54) -> 4482.25 | AD54: =Z54-AB54 -> 0 | AE54: =AA54-AC54 -> 0 | AI54: =SUMIFS([1]项目开票!L:L,[1]项目开票!B:B,报税!B54,[1]项目开票!A:A,报税!A54) -> 0 | AJ54: =SUMIFS([1]项目开票!M:M,[1]项目开票!B:B,报税!B54,[1]项目开票!A:A,报税!A54) -> 0 | AK54: =AG54-AI54 -> 0 | AL54: =AH54-AJ54 -> 0 | AS54: =G54+N54+U54+AB54+AI54+AO54 -> 74704.1
A55: 内蒙伊旗风光储-远景样机 | B55: 1000 | C55: EPC | D55: 5459442.2 | E55: 5868900.4 | F55: 528201.03 | G55: =SUMIFS([1]项目开票!C:C,[1]项目开票!B:B,报税!B55,[1]项目开票!A:A,报税!A55) -> 5868900.4 | H55: =SUMIFS([1]项目开票!D:D,[1]项目开票!B:B,报税!B55,[1]项目开票!A:A,报税!A55) -> 528201.03 | I55: =E55-G55 -> 0 | J55: =F55-H55 -> 0 | K55: 3182987.5 | L55: 3421711.5 | M55: 444822.5 | N55: =SUMIFS([1]项目开票!O:O,[1]项目开票!B:B,报税!B55,[1]项目开票!A:A,报税!A55) -> 3421711.5 | O55: =SUMIFS([1]项目开票!P:P,[1]项目开票!B:B,报税!B55,[1]项目开票!A:A,报税!A55) -> 444822.5 | P55: =L55-N55 -> 0 | Q55: =M55-O55 -> 0 | R55: 2500966.7 | S55: 2688539.2 | T55: 161312.35 | U55: =SUMIFS([1]项目开票!F:F,[1]项目开票!B:B,报税!B55,[1]项目开票!A:A,报税!A55) -> 2688539.2 | V55: =SUMIFS([1]项目开票!G:G,[1]项目开票!B:B,报税!B55,[1]项目开票!A:A,报税!A55) -> 161312.35 | W55: =S55-U55 -> 0 | X55: =T55-V55 -> 0 | AB55: =SUMIFS([1]项目开票!I:I,[1]项目开票!B:B,报税!B55,[1]项目开票!A:A,报税!A55) -> 0 | AC55: =SUMIFS([1]项目开票!J:J,[1]项目开票!B:B,报税!B55,[1]项目开票!A:A,报税!A55) -> 0 | AD55: =Z55-AB55 -> 0 | AE55: =AA55-AC55 -> 0 | AI55: =SUMIFS([1]项目开票!L:L,[1]项目开票!B:B,报税!B55,[1]项目开票!A:A,报税!A55) -> 0 | AJ55: =SUMIFS([1]项目开票!M:M,[1]项目开票!B:B,报税!B55,[1]项目开票!A:A,报税!A55) -> 0 | AK55: =AG55-AI55 -> 0 | AL55: =AH55-AJ55 -> 0 | AQ55: =AM55-AO55 -> 0 | AR55: =AN55-AP55 -> 0 | AS55: =G55+N55+U55+AB55+AI55+AO55 -> 11979151
A56: 内蒙伊旗风光储-远景样机 | B56: 2260 | C56: EPC | D56: 5315214.8 | E56: 5713855.8 | F56: 514247.04 | G56: =SUMIFS([1]项目开票!C:C,[1]项目开票!B:B,报税!B56,[1]项目开票!A:A,报税!A56) -> 5713855.8 | H56: =SUMIFS([1]项目开票!D:D,[1]项目开票!B:B,报税!B56,[1]项目开票!A:A,报税!A56) -> 514247.04 | I56: =E56-G56 -> 0 | J56: =F56-H56 -> 0 | K56: 8860168.6 | L56: 9524681.2 | M56: 1238208.6 | N56: =SUMIFS([1]项目开票!O:O,[1]项目开票!B:B,报税!B56,[1]项目开票!A:A,报税!A56) -> 9524681.2 | O56: =SUMIFS([1]项目开票!P:P,[1]项目开票!B:B,报税!B56,[1]项目开票!A:A,报税!A56) -> 1238208.6 | P56: =L56-N56 -> 0 | Q56: =M56-O56 -> 0 | R56: 5001933.4 | S56: 5377078.4 | T56: 322624.69 | U56: =SUMIFS([1]项目开票!F:F,[1]项目开票!B:B,报税!B56,[1]项目开票!A:A,报税!A56) -> 5377078.4 | V56: =SUMIFS([1]项目开票!G:G,[1]项目开票!B:B,报税!B56,[1]项目开票!A:A,报税!A56) -> 322624.7 | W56: =S56-U56 -> -0.0099999998 | X56: =T56-V56 -> -0.01 | AB56: =SUMIFS([1]项目开票!I:I,[1]项目开票!B:B,报税!B56,[1]项目开票!A:A,报税!A56) -> 0 | AC56: =SUMIFS([1]项目开票!J:J,[1]项目开票!B:B,报税!B56,[1]项目开票!A:A,报税!A56) -> 0 | AD56: =Z56-AB56 -> 0 | AE56: =AA56-AC56 -> 0 | AI56: =SUMIFS([1]项目开票!L:L,[1]项目开票!B:B,报税!B56,[1]项目开票!A:A,报税!A56) -> 0 | AJ56: =SUMIFS([1]项目开票!M:M,[1]项目开票!B:B,报税!B56,[1]项目开票!A:A,报税!A56) -> 0 | AK56: =AG56-AI56 -> 0 | AL56: =AH56-AJ56 -> 0 | AQ56: =AM56-AO56 -> 0 | AR56: =AN56-AP56 -> 0 | AS56: =G56+N56+U56+AB56+AI56+AO56 -> 20615615
A57: 内蒙伊旗风光储-远景样机 | B57: 4470 | C57: EPC | D57: 729357.8 | E57: 747591.74 | F57: 67283.25 | G57: =SUMIFS([1]项目开票!C:C,[1]项目开票!B:B,报税!B57,[1]项目开票!A:A,报税!A57) -> 0 | H57: =SUMIFS([1]项目开票!D:D,[1]项目开票!B:B,报税!B57,[1]项目开票!A:A,报税!A57) -> 0 | I57: =E57-G57 -> 747591.74 | J57: =F57-H57 -> 67283.25 | K57: 5848940.7 | L57: 5995164.2 | M57: 779371.35 | N57: =SUMIFS([1]项目开票!O:O,[1]项目开票!B:B,报税!B57,[1]项目开票!A:A,报税!A57) -> 0 | O57: =SUMIFS([1]项目开票!P:P,[1]项目开票!B:B,报税!B57,[1]项目开票!A:A,报税!A57) -> 0 | P57: =L57-N57 -> 5995164.2 | Q57: =M57-O57 -> 779371.35 | U57: =SUMIFS([1]项目开票!F:F,[1]项目开票!B:B,报税!B57,[1]项目开票!A:A,报税!A57) -> 0 | V57: =SUMIFS([1]项目开票!G:G,[1]项目开票!B:B,报税!B57,[1]项目开票!A:A,报税!A57) -> 0 | W57: =S57-U57 -> 0 | X57: =T57-V57 -> 0 | AB57: =SUMIFS([1]项目开票!I:I,[1]项目开票!B:B,报税!B57,[1]项目开票!A:A,报税!A57) -> 0 | AC57: =SUMIFS([1]项目开票!J:J,[1]项目开票!B:B,报税!B57,[1]项目开票!A:A,报税!A57) -> 0 | AD57: =Z57-AB57 -> 0 | AE57: =AA57-AC57 -> 0 | AI57: =SUMIFS([1]项目开票!L:L,[1]项目开票!B:B,报税!B57,[1]项目开票!A:A,报税!A57) -> 0 | AJ57: =SUMIFS([1]项目开票!M:M,[1]项目开票!B:B,报税!B57,[1]项目开票!A:A,报税!A57) -> 0 | AK57: =AG57-AI57 -> 0 | AL57: =AH57-AJ57 -> 0 | AQ57: =AM57-AO57 -> 0 | AR57: =AN57-AP57 -> 0 | AS57: =G57+N57+U57+AB57+AI57+AO57 -> 0
A58: F-001660大唐湖南永州分水塘风电场维检技术服务 | B58: 大唐永州新能源有限公司 | C58: 后服务收入 | G58: =SUMIFS([1]项目开票!C:C,[1]项目开票!B:B,报税!B58,[1]项目开票!A:A,报税!A58) -> 0 | H58: =SUMIFS([1]项目开票!D:D,[1]项目开票!B:B,报税!B58,[1]项目开票!A:A,报税!A58) -> 0 | I58: =E58-G58 -> 0 | J58: =F58-H58 -> 0 | K58: 159250 | L58: 163333.33 | M58: 21233.33 | N58: =SUMIFS([1]项目开票!O:O,[1]项目开票!B:B,报税!B58,[1]项目开票!A:A,报税!A58) -> 0 | O58: =SUMIFS([1]项目开票!P:P,[1]项目开票!B:B,报税!B58,[1]项目开票!A:A,报税!A58) -> 0 | P58: =L58-N58 -> 163333.33 | Q58: =M58-O58 -> 21233.33 | U58: =SUMIFS([1]项目开票!F:F,[1]项目开票!B:B,报税!B58,[1]项目开票!A:A,报税!A58) -> 0 | V58: =SUMIFS([1]项目开票!G:G,[1]项目开票!B:B,报税!B58,[1]项目开票!A:A,报税!A58) -> 0 | W58: =S58-U58 -> 0 | X58: =T58-V58 -> 0 | AB58: =SUMIFS([1]项目开票!I:I,[1]项目开票!B:B,报税!B58,[1]项目开票!A:A,报税!A58) -> 0 | AC58: =SUMIFS([1]项目开票!J:J,[1]项目开票!B:B,报税!B58,[1]项目开票!A:A,报税!A58) -> 0 | AD58: =Z58-AB58 -> 0 | AE58: =AA58-AC58 -> 0 | AI58: =SUMIFS([1]项目开票!L:L,[1]项目开票!B:B,报税!B58,[1]项目开票!A:A,报税!A58) -> 0 | AJ58: =SUMIFS([1]项目开票!M:M,[1]项目开票!B:B,报税!B58,[1]项目开票!A:A,报税!A58) -> 0 | AK58: =AG58-AI58 -> 0 | AL58: =AH58-AJ58 -> 0 | AQ58: =AM58-AO58 -> 0 | AR58: =AN58-AP58 -> 0 | AS58: =G58+N58+U58+AB58+AI58+AO58 -> 0
A59: FC-000071 广西钦南久沙风电场一期场站运维服务 | B59: 钦州远沙风力发电有限公司 | C59: 后服务收入 | G59: =SUMIFS([1]项目开票!C:C,[1]项目开票!B:B,报税!B59,[1]项目开票!A:A,报税!A59) -> 0 | H59: =SUMIFS([1]项目开票!D:D,[1]项目开票!B:B,报税!B59,[1]项目开票!A:A,报税!A59) -> 0 | I59: =E59-G59 -> 0 | J59: =F59-H59 -> 0 | N59: =SUMIFS([1]项目开票!O:O,[1]项目开票!B:B,报税!B59,[1]项目开票!A:A,报税!A59) -> 0 | O59: =SUMIFS([1]项目开票!P:P,[1]项目开票!B:B,报税!B59,[1]项目开票!A:A,报税!A59) -> 0 | P59: =L59-N59 -> 0 | Q59: =M59-O59 -> 0 | R59: 215106.76 | S59: 220622.31 | T59: 13237.34 | U59: =SUMIFS([1]项目开票!F:F,[1]项目开票!B:B,报税!B59,[1]项目开票!A:A,报税!A59) -> 185322.75 | V59: =SUMIFS([1]项目开票!G:G,[1]项目开票!B:B,报税!B59,[1]项目开票!A:A,报税!A59) -> 11119.36 | W59: =S59-U59 -> 35299.56 | X59: =T59-V59 -> 2117.98 | AB59: =SUMIFS([1]项目开票!I:I,[1]项目开票!B:B,报税!B59,[1]项目开票!A:A,报税!A59) -> 0 | AC59: =SUMIFS([1]项目开票!J:J,[1]项目开票!B:B,报税!B59,[1]项目开票!A:A,报税!A59) -> 0 | AD59: =Z59-AB59 -> 0 | AE59: =AA59-AC59 -> 0 | AI59: =SUMIFS([1]项目开票!L:L,[1]项目开票!B:B,报税!B59,[1]项目开票!A:A,报税!A59) -> 0 | AJ59: =SUMIFS([1]项目开票!M:M,[1]项目开票!B:B,报税!B59,[1]项目开票!A:A,报税!A59) -> 0 | AK59: =AG59-AI59 -> 0 | AL59: =AH59-AJ59 -> 0 | AQ59: =AM59-AO59 -> 0 | AR59: =AN59-AP59 -> 0 | AS59: =G59+N59+U59+AB59+AI59+AO59 -> 185322.75
A60: F-000824三峡新能源云南姚安 | B60: 三峡新能源云南姚安发电有限公司 | C60: 后服务收入 | G60: =SUMIFS([1]项目开票!C:C,[1]项目开票!B:B,报税!B60,[1]项目开票!A:A,报税!A60) -> 0 | H60: =SUMIFS([1]项目开票!D:D,[1]项目开票!B:B,报税!B60,[1]项目开票!A:A,报税!A60) -> 0 | I60: =E60-G60 -> 0 | J60: =F60-H60 -> 0 | N60: =SUMIFS([1]项目开票!O:O,[1]项目开票!B:B,报税!B60,[1]项目开票!A:A,报税!A60) -> 0 | O60: =SUMIFS([1]项目开票!P:P,[1]项目开票!B:B,报税!B60,[1]项目开票!A:A,报税!A60) -> 0 | P60: =L60-N60 -> 0 | Q60: =M60-O60 -> 0 | R60: 75995.78 | S60: 75995.78 | T60: 4559.75 | U60: =SUMIFS([1]项目开票!F:F,[1]项目开票!B:B,报税!B60,[1]项目开票!A:A,报税!A60) -> 221628.86 | V60: =SUMIFS([1]项目开票!G:G,[1]项目开票!B:B,报税!B60,[1]项目开票!A:A,报税!A60) -> 13297.73 | W60: =S60-U60 -> -145633.08 | X60: =T60-V60 -> -8737.98 | AB60: =SUMIFS([1]项目开票!I:I,[1]项目开票!B:B,报税!B60,[1]项目开票!A:A,报税!A60) -> 0 | AC60: =SUMIFS([1]项目开票!J:J,[1]项目开票!B:B,报税!B60,[1]项目开票!A:A,报税!A60) -> 0 | AD60: =Z60-AB60 -> 0 | AE60: =AA60-AC60 -> 0 | AI60: =SUMIFS([1]项目开票!L:L,[1]项目开票!B:B,报税!B60,[1]项目开票!A:A,报税!A60) -> 0 | AJ60: =SUMIFS([1]项目开票!M:M,[1]项目开票!B:B,报税!B60,[1]项目开票!A:A,报税!A60) -> 0 | AK60: =AG60-AI60 -> 0 | AL60: =AH60-AJ60 -> 0 | AQ60: =AM60-AO60 -> 0 | AR60: =AN60-AP60 -> 0 | AS60: =G60+N60+U60+AB60+AI60+AO60 -> 221628.86
A61: F-001454华能安徽龙池风电场年度定检、检修 | B61: 华能安徽怀宁风力发电有限责任公司 | C61: 后服务收入 | G61: =SUMIFS([1]项目开票!C:C,[1]项目开票!B:B,报税!B61,[1]项目开票!A:A,报税!A61) -> 0 | H61: =SUMIFS([1]项目开票!D:D,[1]项目开票!B:B,报税!B61,[1]项目开票!A:A,报税!A61) -> 0 | I61: =E61-G61 -> 0 | J61: =F61-H61 -> 0 | K61: 324808.74 | L61: 333137.17 | M61: 43307.83 | N61: =SUMIFS([1]项目开票!O:O,[1]项目开票!B:B,报税!B61,[1]项目开票!A:A,报税!A61) -> 0 | O61: =SUMIFS([1]项目开票!P:P,[1]项目开票!B:B,报税!B61,[1]项目开票!A:A,报税!A61) -> 0 | P61: =L61-N61 -> 333137.17 | Q61: =M61-O61 -> 43307.83 | U61: =SUMIFS([1]项目开票!F:F,[1]项目开票!B:B,报税!B61,[1]项目开票!A:A,报税!A61) -> 0 | V61: =SUMIFS([1]项目开票!G:G,[1]项目开票!B:B,报税!B61,[1]项目开票!A:A,报税!A61) -> 0 | W61: =S61-U61 -> 0 | X61: =T61-V61 -> 0 | AB61: =SUMIFS([1]项目开票!I:I,[1]项目开票!B:B,报税!B61,[1]项目开票!A:A,报税!A61) -> 0 | AC61: =SUMIFS([1]项目开票!J:J,[1]项目开票!B:B,报税!B61,[1]项目开票!A:A,报税!A61) -> 0 | AD61: =Z61-AB61 -> 0 | AE61: =AA61-AC61 -> 0 | AI61: =SUMIFS([1]项目开票!L:L,[1]项目开票!B:B,报税!B61,[1]项目开票!A:A,报税!A61) -> 0 | AJ61: =SUMIFS([1]项目开票!M:M,[1]项目开票!B:B,报税!B61,[1]项目开票!A:A,报税!A61) -> 0 | AK61: =AG61-AI61 -> 0 | AL61: =AH61-AJ61 -> 0 | AQ61: =AM61-AO61 -> 0 | AR61: =AN61-AP61 -> 0 | AS61: =G61+N61+U61+AB61+AI61+AO61 -> 0
A62: F-001612国电投广西黄花岭风电场 23 台风机运维服务 | B62: 大唐全州新能源有限公司 | C62: 后服务收入 | G62: =SUMIFS([1]项目开票!C:C,[1]项目开票!B:B,报税!B62,[1]项目开票!A:A,报税!A62) -> 0 | H62: =SUMIFS([1]项目开票!D:D,[1]项目开票!B:B,报税!B62,[1]项目开票!A:A,报税!A62) -> 0 | I62: =E62-G62 -> 0 | J62: =F62-H62 -> 0 | K62: 149500 | L62: 153333.33 | M62: 19933.33 | N62: =SUMIFS([1]项目开票!O:O,[1]项目开票!B:B,报税!B62,[1]项目开票!A:A,报税!A62) -> 0 | O62: =SUMIFS([1]项目开票!P:P,[1]项目开票!B:B,报税!B62,[1]项目开票!A:A,报税!A62) -> 0 | P62: =L62-N62 -> 153333.33 | Q62: =M62-O62 -> 19933.33 | U62: =SUMIFS([1]项目开票!F:F,[1]项目开票!B:B,报税!B62,[1]项目开票!A:A,报税!A62) -> 0 | V62: =SUMIFS([1]项目开票!G:G,[1]项目开票!B:B,报税!B62,[1]项目开票!A:A,报税!A62) -> 0 | W62: =S62-U62 -> 0 | X62: =T62-V62 -> 0 | AB62: =SUMIFS([1]项目开票!I:I,[1]项目开票!B:B,报税!B62,[1]项目开票!A:A,报税!A62) -> 0 | AC62: =SUMIFS([1]项目开票!J:J,[1]项目开票!B:B,报税!B62,[1]项目开票!A:A,报税!A62) -> 0 | AD62: =Z62-AB62 -> 0 | AE62: =AA62-AC62 -> 0 | AI62: =SUMIFS([1]项目开票!L:L,[1]项目开票!B:B,报税!B62,[1]项目开票!A:A,报税!A62) -> 0 | AJ62: =SUMIFS([1]项目开票!M:M,[1]项目开票!B:B,报税!B62,[1]项目开票!A:A,报税!A62) -> 0 | AK62: =AG62-AI62 -> 0 | AL62: =AH62-AJ62 -> 0 | AQ62: =AM62-AO62 -> 0 | AR62: =AN62-AP62 -> 0 | AS62: =G62+N62+U62+AB62+AI62+AO62 -> 0
A63: F-001421华能陕西靖边马畔梁风电场度运行维护 | B63: 华能陕西靖边电力有限公司 | C63: 后服务收入 | E63: 122242.08 | F63: 11001.79 | G63: =SUMIFS([1]项目开票!C:C,[1]项目开票!B:B,报税!B63,[1]项目开票!A:A,报税!A63) -> 0 | H63: =SUMIFS([1]项目开票!D:D,[1]项目开票!B:B,报税!B63,[1]项目开票!A:A,报税!A63) -> 0 | I63: =E63-G63 -> 122242.08 | J63: =F63-H63 -> 11001.79 | N63: =SUMIFS([1]项目开票!O:O,[1]项目开票!B:B,报税!B63,[1]项目开票!A:A,报税!A63) -> 0 | O63: =SUMIFS([1]项目开票!P:P,[1]项目开票!B:B,报税!B63,[1]项目开票!A:A,报税!A63) -> 0 | P63: =L63-N63 -> 0 | Q63: =M63-O63 -> 0 | R63: 119186.05 | U63: =SUMIFS([1]项目开票!F:F,[1]项目开票!B:B,报税!B63,[1]项目开票!A:A,报税!A63) -> 0 | V63: =SUMIFS([1]项目开票!G:G,[1]项目开票!B:B,报税!B63,[1]项目开票!A:A,报税!A63) -> 0 | W63: =S63-U63 -> 0 | X63: =T63-V63 -> 0 | AB63: =SUMIFS([1]项目开票!I:I,[1]项目开票!B:B,报税!B63,[1]项目开票!A:A,报税!A63) -> 0 | AC63: =SUMIFS([1]项目开票!J:J,[1]项目开票!B:B,报税!B63,[1]项目开票!A:A,报税!A63) -> 0 | AD63: =Z63-AB63 -> 0 | AE63: =AA63-AC63 -> 0 | AI63: =SUMIFS([1]项目开票!L:L,[1]项目开票!B:B,报税!B63,[1]项目开票!A:A,报税!A63) -> 0 | AJ63: =SUMIFS([1]项目开票!M:M,[1]项目开票!B:B,报税!B63,[1]项目开票!A:A,报税!A63) -> 0 | AK63: =AG63-AI63 -> 0 | AL63: =AH63-AJ63 -> 0 | AQ63: =AM63-AO63 -> 0 | AR63: =AN63-AP63 -> 0 | AS63: =G63+N63+U63+AB63+AI63+AO63 -> 0
A64: 内蒙鄂尔多斯分散式-改造 | B64: 4470 | C64: EPC | G64: =SUMIFS([1]项目开票!C:C,[1]项目开票!B:B,报税!B64,[1]项目开票!A:A,报税!A64) -> 0 | H64: =SUMIFS([1]项目开票!D:D,[1]项目开票!B:B,报税!B64,[1]项目开票!A:A,报税!A64) -> 0 | I64: =E64-G64 -> 0 | J64: =F64-H64 -> 0 | N64: =SUMIFS([1]项目开票!O:O,[1]项目开票!B:B,报税!B64,[1]项目开票!A:A,报税!A64) -> 0 | O64: =SUMIFS([1]项目开票!P:P,[1]项目开票!B:B,报税!B64,[1]项目开票!A:A,报税!A64) -> 0 | P64: =L64-N64 -> 0 | Q64: =M64-O64 -> 0 | R64: 60000 | S64: 61500 | T64: 3690 | U64: =SUMIFS([1]项目开票!F:F,[1]项目开票!B:B,报税!B64,[1]项目开票!A:A,报税!A64) -> 0 | V64: =SUMIFS([1]项目开票!G:G,[1]项目开票!B:B,报税!B64,[1]项目开票!A:A,报税!A64) -> 0 | W64: =S64-U64 -> 61500 | X64: =T64-V64 -> 3690 | AB64: =SUMIFS([1]项目开票!I:I,[1]项目开票!B:B,报税!B64,[1]项目开票!A:A,报税!A64) -> 0 | AC64: =SUMIFS([1]项目开票!J:J,[1]项目开票!B:B,报税!B64,[1]项目开票!A:A,报税!A64) -> 0 | AD64: =Z64-AB64 -> 0 | AE64: =AA64-AC64 -> 0 | AI64: =SUMIFS([1]项目开票!L:L,[1]项目开票!B:B,报税!B64,[1]项目开票!A:A,报税!A64) -> 0 | AJ64: =SUMIFS([1]项目开票!M:M,[1]项目开票!B:B,报税!B64,[1]项目开票!A:A,报税!A64) -> 0 | AK64: =AG64-AI64 -> 0 | AL64: =AH64-AJ64 -> 0 | AQ64: =AM64-AO64 -> 0 | AR64: =AN64-AP64 -> 0 | AS64: =G64+N64+U64+AB64+AI64+AO64 -> 0
A65: 锡盟京能储能项目 | B65: 1A00 | C65: EPC | G65: =SUMIFS([1]项目开票!C:C,[1]项目开票!B:B,报税!B65,[1]项目开票!A:A,报税!A65) -> 0 | H65: =SUMIFS([1]项目开票!D:D,[1]项目开票!B:B,报税!B65,[1]项目开票!A:A,报税!A65) -> 0 | I65: =E65-G65 -> 0 | J65: =F65-H65 -> 0 | N65: =SUMIFS([1]项目开票!O:O,[1]项目开票!B:B,报税!B65,[1]项目开票!A:A,报税!A65) -> 0 | O65: =SUMIFS([1]项目开票!P:P,[1]项目开票!B:B,报税!B65,[1]项目开票!A:A,报税!A65) -> 0 | P65: =L65-N65 -> 0 | Q65: =M65-O65 -> 0 | R65: 283863.6 | S65: 298056.78 | T65: 17883.41 | U65: =SUMIFS([1]项目开票!F:F,[1]项目开票!B:B,报税!B65,[1]项目开票!A:A,报税!A65) -> 298056.78 | V65: =SUMIFS([1]项目开票!G:G,[1]项目开票!B:B,报税!B65,[1]项目开票!A:A,报税!A65) -> 17883.41 | W65: =S65-U65 -> 0 | X65: =T65-V65 -> 0 | AB65: =SUMIFS([1]项目开票!I:I,[1]项目开票!B:B,报税!B65,[1]项目开票!A:A,报税!A65) -> 0 | AC65: =SUMIFS([1]项目开票!J:J,[1]项目开票!B:B,报税!B65,[1]项目开票!A:A,报税!A65) -> 0 | AD65: =Z65-AB65 -> 0 | AE65: =AA65-AC65 -> 0 | AI65: =SUMIFS([1]项目开票!L:L,[1]项目开票!B:B,报税!B65,[1]项目开票!A:A,报税!A65) -> 0 | AJ65: =SUMIFS([1]项目开票!M:M,[1]项目开票!B:B,报税!B65,[1]项目开票!A:A,报税!A65) -> 0 | AK65: =AG65-AI65 -> 0 | AL65: =AH65-AJ65 -> 0 | AQ65: =AM65-AO65 -> 0 | AR65: =AN65-AP65 -> 0 | AS65: =G65+N65+U65+AB65+AI65+AO65 -> 298056.78
A66: 大金重工70万风电项目 | B66: 1000 | C66: EPC | G66: =SUMIFS([1]项目开票!C:C,[1]项目开票!B:B,报税!B66,[1]项目开票!A:A,报税!A66) -> 0 | H66: =SUMIFS([1]项目开票!D:D,[1]项目开票!B:B,报税!B66,[1]项目开票!A:A,报税!A66) -> 0 | I66: =E66-G66 -> 0 | J66: =F66-H66 -> 0 | N66: =SUMIFS([1]项目开票!O:O,[1]项目开票!B:B,报税!B66,[1]项目开票!A:A,报税!A66) -> 0 | O66: =SUMIFS([1]项目开票!P:P,[1]项目开票!B:B,报税!B66,[1]项目开票!A:A,报税!A66) -> 0 | P66: =L66-N66 -> 0 | Q66: =M66-O66 -> 0 | R66: 1653788.1 | S66: 1736477.5 | T66: 104188.66 | U66: =SUMIFS([1]项目开票!F:F,[1]项目开票!B:B,报税!B66,[1]项目开票!A:A,报税!A66) -> 1736477.5 | V66: =SUMIFS([1]项目开票!G:G,[1]项目开票!B:B,报税!B66,[1]项目开票!A:A,报税!A66) -> 104188.66 | W66: =S66-U66 -> 0 | X66: =T66-V66 -> 0 | AB66: =SUMIFS([1]项目开票!I:I,[1]项目开票!B:B,报税!B66,[1]项目开票!A:A,报税!A66) -> 0 | AC66: =SUMIFS([1]项目开票!J:J,[1]项目开票!B:B,报税!B66,[1]项目开票!A:A,报税!A66) -> 0 | AD66: =Z66-AB66 -> 0 | AE66: =AA66-AC66 -> 0 | AI66: =SUMIFS([1]项目开票!L:L,[1]项目开票!B:B,报税!B66,[1]项目开票!A:A,报税!A66) -> 0 | AJ66: =SUMIFS([1]项目开票!M:M,[1]项目开票!B:B,报税!B66,[1]项目开票!A:A,报税!A66) -> 0 | AK66: =AG66-AI66 -> 0 | AL66: =AH66-AJ66 -> 0 | AQ66: =AM66-AO66 -> 0 | AR66: =AN66-AP66 -> 0 | AS66: =G66+N66+U66+AB66+AI66+AO66 -> 1736477.5
A67: 232012成本中心结转代维成本 | B67: NA | C67: EPC | G67: =SUMIFS([1]项目开票!C:C,[1]项目开票!B:B,报税!B67,[1]项目开票!A:A,报税!A67) -> 0 | H67: =SUMIFS([1]项目开票!D:D,[1]项目开票!B:B,报税!B67,[1]项目开票!A:A,报税!A67) -> 0 | I67: =E67-G67 -> 0 | J67: =F67-H67 -> 0 | N67: =SUMIFS([1]项目开票!O:O,[1]项目开票!B:B,报税!B67,[1]项目开票!A:A,报税!A67) -> 0 | O67: =SUMIFS([1]项目开票!P:P,[1]项目开票!B:B,报税!B67,[1]项目开票!A:A,报税!A67) -> 0 | P67: =L67-N67 -> 0 | Q67: =M67-O67 -> 0 | R67: 37485.85 | U67: =SUMIFS([1]项目开票!F:F,[1]项目开票!B:B,报税!B67,[1]项目开票!A:A,报税!A67) -> 0 | V67: =SUMIFS([1]项目开票!G:G,[1]项目开票!B:B,报税!B67,[1]项目开票!A:A,报税!A67) -> 0 | W67: =S67-U67 -> 0 | X67: =T67-V67 -> 0 | AB67: =SUMIFS([1]项目开票!I:I,[1]项目开票!B:B,报税!B67,[1]项目开票!A:A,报税!A67) -> 0 | AC67: =SUMIFS([1]项目开票!J:J,[1]项目开票!B:B,报税!B67,[1]项目开票!A:A,报税!A67) -> 0 | AD67: =Z67-AB67 -> 0 | AE67: =AA67-AC67 -> 0 | AI67: =SUMIFS([1]项目开票!L:L,[1]项目开票!B:B,报税!B67,[1]项目开票!A:A,报税!A67) -> 0 | AJ67: =SUMIFS([1]项目开票!M:M,[1]项目开票!B:B,报税!B67,[1]项目开票!A:A,报税!A67) -> 0 | AK67: =AG67-AI67 -> 0 | AL67: =AH67-AJ67 -> 0 | AQ67: =AM67-AO67 -> 0 | AR67: =AN67-AP67 -> 0 | AS67: =G67+N67+U67+AB67+AI67+AO67 -> 0
A68: 大宗商品_钢材_龙源射阳项目_10套 | B68: NA | C68: 钢贸 | G68: =SUMIFS([1]项目开票!C:C,[1]项目开票!B:B,报税!B68,[1]项目开票!A:A,报税!A68) -> 0 | H68: =SUMIFS([1]项目开票!D:D,[1]项目开票!B:B,报税!B68,[1]项目开票!A:A,报税!A68) -> 0 | I68: =E68-G68 -> 0 | J68: =F68-H68 -> 0 | K68: 2188130.5 | N68: =SUMIFS([1]项目开票!O:O,[1]项目开票!B:B,报税!B68,[1]项目开票!A:A,报税!A68) -> 0 | O68: =SUMIFS([1]项目开票!P:P,[1]项目开票!B:B,报税!B68,[1]项目开票!A:A,报税!A68) -> 0 | P68: =L68-N68 -> 0 | Q68: =M68-O68 -> 0 | U68: =SUMIFS([1]项目开票!F:F,[1]项目开票!B:B,报税!B68,[1]项目开票!A:A,报税!A68) -> 0 | V68: =SUMIFS([1]项目开票!G:G,[1]项目开票!B:B,报税!B68,[1]项目开票!A:A,报税!A68) -> 0 | W68: =S68-U68 -> 0 | X68: =T68-V68 -> 0 | AB68: =SUMIFS([1]项目开票!I:I,[1]项目开票!B:B,报税!B68,[1]项目开票!A:A,报税!A68) -> 0 | AC68: =SUMIFS([1]项目开票!J:J,[1]项目开票!B:B,报税!B68,[1]项目开票!A:A,报税!A68) -> 0 | AD68: =Z68-AB68 -> 0 | AE68: =AA68-AC68 -> 0 | AI68: =SUMIFS([1]项目开票!L:L,[1]项目开票!B:B,报税!B68,[1]项目开票!A:A,报税!A68) -> 0 | AJ68: =SUMIFS([1]项目开票!M:M,[1]项目开票!B:B,报税!B68,[1]项目开票!A:A,报税!A68) -> 0 | AK68: =AG68-AI68 -> 0 | AL68: =AH68-AJ68 -> 0 | AQ68: =AM68-AO68 -> 0 | AR68: =AN68-AP68 -> 0 | AS68: =G68+N68+U68+AB68+AI68+AO68 -> 0
A69: 大宗商品_钢材_沙特项目_8套（筒体板） | B69: NA | C69: 钢贸 | G69: =SUMIFS([1]项目开票!C:C,[1]项目开票!B:B,报税!B69,[1]项目开票!A:A,报税!A69) -> 0 | H69: =SUMIFS([1]项目开票!D:D,[1]项目开票!B:B,报税!B69,[1]项目开票!A:A,报税!A69) -> 0 | I69: =E69-G69 -> 0 | J69: =F69-H69 -> 0 | K69: 6405.2 | N69: =SUMIFS([1]项目开票!O:O,[1]项目开票!B:B,报税!B69,[1]项目开票!A:A,报税!A69) -> 0 | O69: =SUMIFS([1]项目开票!P:P,[1]项目开票!B:B,报税!B69,[1]项目开票!A:A,报税!A69) -> 0 | P69: =L69-N69 -> 0 | Q69: =M69-O69 -> 0 | U69: =SUMIFS([1]项目开票!F:F,[1]项目开票!B:B,报税!B69,[1]项目开票!A:A,报税!A69) -> 0 | V69: =SUMIFS([1]项目开票!G:G,[1]项目开票!B:B,报税!B69,[1]项目开票!A:A,报税!A69) -> 0 | W69: =S69-U69 -> 0 | X69: =T69-V69 -> 0 | AB69: =SUMIFS([1]项目开票!I:I,[1]项目开票!B:B,报税!B69,[1]项目开票!A:A,报税!A69) -> 0 | AC69: =SUMIFS([1]项目开票!J:J,[1]项目开票!B:B,报税!B69,[1]项目开票!A:A,报税!A69) -> 0 | AD69: =Z69-AB69 -> 0 | AE69: =AA69-AC69 -> 0 | AI69: =SUMIFS([1]项目开票!L:L,[1]项目开票!B:B,报税!B69,[1]项目开票!A:A,报税!A69) -> 0 | AJ69: =SUMIFS([1]项目开票!M:M,[1]项目开票!B:B,报税!B69,[1]项目开票!A:A,报税!A69) -> 0 | AK69: =AG69-AI69 -> 0 | AL69: =AH69-AJ69 -> 0 | AQ69: =AM69-AO69 -> 0 | AR69: =AN69-AP69 -> 0 | AS69: =G69+N69+U69+AB69+AI69+AO69 -> 0
A70: 大宗商品_钢材_自建昆吾项目_重山9套（筒体板） | B70: NA | C70: 钢贸 | G70: =SUMIFS([1]项目开票!C:C,[1]项目开票!B:B,报税!B70,[1]项目开票!A:A,报税!A70) -> 0 | H70: =SUMIFS([1]项目开票!D:D,[1]项目开票!B:B,报税!B70,[1]项目开票!A:A,报税!A70) -> 0 | I70: =E70-G70 -> 0 | J70: =F70-H70 -> 0 | K70: 6119.04 | N70: =SUMIFS([1]项目开票!O:O,[1]项目开票!B:B,报税!B70,[1]项目开票!A:A,报税!A70) -> 0 | O70: =SUMIFS([1]项目开票!P:P,[1]项目开票!B:B,报税!B70,[1]项目开票!A:A,报税!A70) -> 0 | P70: =L70-N70 -> 0 | Q70: =M70-O70 -> 0 | U70: =SUMIFS([1]项目开票!F:F,[1]项目开票!B:B,报税!B70,[1]项目开票!A:A,报税!A70) -> 0 | V70: =SUMIFS([1]项目开票!G:G,[1]项目开票!B:B,报税!B70,[1]项目开票!A:A,报税!A70) -> 0 | W70: =S70-U70 -> 0 | X70: =T70-V70 -> 0 | AB70: =SUMIFS([1]项目开票!I:I,[1]项目开票!B:B,报税!B70,[1]项目开票!A:A,报税!A70) -> 0 | AC70: =SUMIFS([1]项目开票!J:J,[1]项目开票!B:B,报税!B70,[1]项目开票!A:A,报税!A70) -> 0 | AD70: =Z70-AB70 -> 0 | AE70: =AA70-AC70 -> 0 | AI70: =SUMIFS([1]项目开票!L:L,[1]项目开票!B:B,报税!B70,[1]项目开票!A:A,报税!A70) -> 0 | AJ70: =SUMIFS([1]项目开票!M:M,[1]项目开票!B:B,报税!B70,[1]项目开票!A:A,报税!A70) -> 0 | AK70: =AG70-AI70 -> 0 | AL70: =AH70-AJ70 -> 0 | AQ70: =AM70-AO70 -> 0 | AR70: =AN70-AP70 -> 0 | AS70: =G70+N70+U70+AB70+AI70+AO70 -> 0
A71: 大宗商品_钢材_自建昆吾项目_重山9套（正火板） | B71: NA | C71: 钢贸 | G71: =SUMIFS([1]项目开票!C:C,[1]项目开票!B:B,报税!B71,[1]项目开票!A:A,报税!A71) -> 0 | H71: =SUMIFS([1]项目开票!D:D,[1]项目开票!B:B,报税!B71,[1]项目开票!A:A,报税!A71) -> 0 | I71: =E71-G71 -> 0 | J71: =F71-H71 -> 0 | K71: 50694.35 | N71: =SUMIFS([1]项目开票!O:O,[1]项目开票!B:B,报税!B71,[1]项目开票!A:A,报税!A71) -> 0 | O71: =SUMIFS([1]项目开票!P:P,[1]项目开票!B:B,报税!B71,[1]项目开票!A:A,报税!A71) -> 0 | P71: =L71-N71 -> 0 | Q71: =M71-O71 -> 0 | U71: =SUMIFS([1]项目开票!F:F,[1]项目开票!B:B,报税!B71,[1]项目开票!A:A,报税!A71) -> 0 | V71: =SUMIFS([1]项目开票!G:G,[1]项目开票!B:B,报税!B71,[1]项目开票!A:A,报税!A71) -> 0 | W71: =S71-U71 -> 0 | X71: =T71-V71 -> 0 | AB71: =SUMIFS([1]项目开票!I:I,[1]项目开票!B:B,报税!B71,[1]项目开票!A:A,报税!A71) -> 0 | AC71: =SUMIFS([1]项目开票!J:J,[1]项目开票!B:B,报税!B71,[1]项目开票!A:A,报税!A71) -> 0 | AD71: =Z71-AB71 -> 0 | AE71: =AA71-AC71 -> 0 | AI71: =SUMIFS([1]项目开票!L:L,[1]项目开票!B:B,报税!B71,[1]项目开票!A:A,报税!A71) -> 0 | AJ71: =SUMIFS([1]项目开票!M:M,[1]项目开票!B:B,报税!B71,[1]项目开票!A:A,报税!A71) -> 0 | AK71: =AG71-AI71 -> 0 | AL71: =AH71-AJ71 -> 0 | AQ71: =AM71-AO71 -> 0 | AR71: =AN71-AP71 -> 0 | AS71: =G71+N71+U71+AB71+AI71+AO71 -> 0
A72: 灵山玖伯二期 | B72: 3307 | C72: 已出售 | G72: =SUMIFS([1]项目开票!C:C,[1]项目开票!B:B,报税!B72,[1]项目开票!A:A,报税!A72) -> 0 | H72: =SUMIFS([1]项目开票!D:D,[1]项目开票!B:B,报税!B72,[1]项目开票!A:A,报税!A72) -> 0 | I72: =E72-G72 -> 0 | J72: =F72-H72 -> 0 | N72: =SUMIFS([1]项目开票!O:O,[1]项目开票!B:B,报税!B72,[1]项目开票!A:A,报税!A72) -> 0 | O72: =SUMIFS([1]项目开票!P:P,[1]项目开票!B:B,报税!B72,[1]项目开票!A:A,报税!A72) -> 0 | P72: =L72-N72 -> 0 | Q72: =M72-O72 -> 0 | U72: =SUMIFS([1]项目开票!F:F,[1]项目开票!B:B,报税!B72,[1]项目开票!A:A,报税!A72) -> 219049.25 | V72: =SUMIFS([1]项目开票!G:G,[1]项目开票!B:B,报税!B72,[1]项目开票!A:A,报税!A72) -> 13142.96 | W72: =S72-U72 -> -219049.25 | X72: =T72-V72 -> -13142.96 | AB72: =SUMIFS([1]项目开票!I:I,[1]项目开票!B:B,报税!B72,[1]项目开票!A:A,报税!A72) -> 0 | AC72: =SUMIFS([1]项目开票!J:J,[1]项目开票!B:B,报税!B72,[1]项目开票!A:A,报税!A72) -> 0 | AD72: =Z72-AB72 -> 0 | AE72: =AA72-AC72 -> 0 | AI72: =SUMIFS([1]项目开票!L:L,[1]项目开票!B:B,报税!B72,[1]项目开票!A:A,报税!A72) -> 0 | AJ72: =SUMIFS([1]项目开票!M:M,[1]项目开票!B:B,报税!B72,[1]项目开票!A:A,报税!A72) -> 0 | AK72: =AG72-AI72 -> 0 | AL72: =AH72-AJ72 -> 0 | AQ72: =AM72-AO72 -> 0 | AR72: =AN72-AP72 -> 0 | AS72: =G72+N72+U72+AB72+AI72+AO72 -> 219049.25
A73: 灵山文利 | B73: 3308 | C73: 已出售 | G73: =SUMIFS([1]项目开票!C:C,[1]项目开票!B:B,报税!B73,[1]项目开票!A:A,报税!A73) -> 0 | H73: =SUMIFS([1]项目开票!D:D,[1]项目开票!B:B,报税!B73,[1]项目开票!A:A,报税!A73) -> 0 | I73: =E73-G73 -> 0 | J73: =F73-H73 -> 0 | N73: =SUMIFS([1]项目开票!O:O,[1]项目开票!B:B,报税!B73,[1]项目开票!A:A,报税!A73) -> 0 | O73: =SUMIFS([1]项目开票!P:P,[1]项目开票!B:B,报税!B73,[1]项目开票!A:A,报税!A73) -> 0 | P73: =L73-N73 -> 0 | Q73: =M73-O73 -> 0 | U73: =SUMIFS([1]项目开票!F:F,[1]项目开票!B:B,报税!B73,[1]项目开票!A:A,报税!A73) -> 618121.66 | V73: =SUMIFS([1]项目开票!G:G,[1]项目开票!B:B,报税!B73,[1]项目开票!A:A,报税!A73) -> 37087.3 | W73: =S73-U73 -> -618121.66 | X73: =T73-V73 -> -37087.3 | AB73: =SUMIFS([1]项目开票!I:I,[1]项目开票!B:B,报税!B73,[1]项目开票!A:A,报税!A73) -> 0 | AC73: =SUMIFS([1]项目开票!J:J,[1]项目开票!B:B,报税!B73,[1]项目开票!A:A,报税!A73) -> 0 | AD73: =Z73-AB73 -> 0 | AE73: =AA73-AC73 -> 0 | AI73: =SUMIFS([1]项目开票!L:L,[1]项目开票!B:B,报税!B73,[1]项目开票!A:A,报税!A73) -> 0 | AJ73: =SUMIFS([1]项目开票!M:M,[1]项目开票!B:B,报税!B73,[1]项目开票!A:A,报税!A73) -> 0 | AK73: =AG73-AI73 -> 0 | AL73: =AH73-AJ73 -> 0 | AQ73: =AM73-AO73 -> 0 | AR73: =AN73-AP73 -> 0 | AS73: =G73+N73+U73+AB73+AI73+AO73 -> 618121.66
A74: 巴彦淖尔1000MW/4000MWh储能 | B74: 兴业金融租赁有限责任公司 | C74: EPC | G74: =SUMIFS([1]项目开票!C:C,[1]项目开票!B:B,报税!B74,[1]项目开票!A:A,报税!A74) -> 0 | H74: =SUMIFS([1]项目开票!D:D,[1]项目开票!B:B,报税!B74,[1]项目开票!A:A,报税!A74) -> 0 | I74: =E74-G74 -> 0 | J74: =F74-H74 -> 0 | N74: =SUMIFS([1]项目开票!O:O,[1]项目开票!B:B,报税!B74,[1]项目开票!A:A,报税!A74) -> 4.8347035e+08 | O74: =SUMIFS([1]项目开票!P:P,[1]项目开票!B:B,报税!B74,[1]项目开票!A:A,报税!A74) -> 62851145 | P74: =L74-N74 -> -4.8347035e+08 | Q74: =M74-O74 -> -62851145 | U74: =SUMIFS([1]项目开票!F:F,[1]项目开票!B:B,报税!B74,[1]项目开票!A:A,报税!A74) -> 0 | V74: =SUMIFS([1]项目开票!G:G,[1]项目开票!B:B,报税!B74,[1]项目开票!A:A,报税!A74) -> 0 | W74: =S74-U74 -> 0 | X74: =T74-V74 -> 0 | AB74: =SUMIFS([1]项目开票!I:I,[1]项目开票!B:B,报税!B74,[1]项目开票!A:A,报税!A74) -> 0 | AC74: =SUMIFS([1]项目开票!J:J,[1]项目开票!B:B,报税!B74,[1]项目开票!A:A,报税!A74) -> 0 | AD74: =Z74-AB74 -> 0 | AE74: =AA74-AC74 -> 0 | AI74: =SUMIFS([1]项目开票!L:L,[1]项目开票!B:B,报税!B74,[1]项目开票!A:A,报税!A74) -> 0 | AJ74: =SUMIFS([1]项目开票!M:M,[1]项目开票!B:B,报税!B74,[1]项目开票!A:A,报税!A74) -> 0 | AK74: =AG74-AI74 -> 0 | AL74: =AH74-AJ74 -> 0 | AQ74: =AM74-AO74 -> 0 | AR74: =AN74-AP74 -> 0 | AS74: =G74+N74+U74+AB74+AI74+AO74 -> 4.8347035e+08
A75: 巴彦淖尔1000MW/4000MWh储能 | B75: 光大金融租赁股份有限公司 | C75: EPC | G75: =SUMIFS([1]项目开票!C:C,[1]项目开票!B:B,报税!B75,[1]项目开票!A:A,报税!A75) -> 0 | H75: =SUMIFS([1]项目开票!D:D,[1]项目开票!B:B,报税!B75,[1]项目开票!A:A,报税!A75) -> 0 | I75: =E75-G75 -> 0 | J75: =F75-H75 -> 0 | N75: =SUMIFS([1]项目开票!O:O,[1]项目开票!B:B,报税!B75,[1]项目开票!A:A,报税!A75) -> 3.5488359e+08 | O75: =SUMIFS([1]项目开票!P:P,[1]项目开票!B:B,报税!B75,[1]项目开票!A:A,报税!A75) -> 46134867 | P75: =L75-N75 -> -3.5488359e+08 | Q75: =M75-O75 -> -46134867 | U75: =SUMIFS([1]项目开票!F:F,[1]项目开票!B:B,报税!B75,[1]项目开票!A:A,报税!A75) -> 0 | V75: =SUMIFS([1]项目开票!G:G,[1]项目开票!B:B,报税!B75,[1]项目开票!A:A,报税!A75) -> 0 | W75: =S75-U75 -> 0 | X75: =T75-V75 -> 0 | AB75: =SUMIFS([1]项目开票!I:I,[1]项目开票!B:B,报税!B75,[1]项目开票!A:A,报税!A75) -> 0 | AC75: =SUMIFS([1]项目开票!J:J,[1]项目开票!B:B,报税!B75,[1]项目开票!A:A,报税!A75) -> 0 | AD75: =Z75-AB75 -> 0 | AE75: =AA75-AC75 -> 0 | AI75: =SUMIFS([1]项目开票!L:L,[1]项目开票!B:B,报税!B75,[1]项目开票!A:A,报税!A75) -> 0 | AJ75: =SUMIFS([1]项目开票!M:M,[1]项目开票!B:B,报税!B75,[1]项目开票!A:A,报税!A75) -> 0 | AK75: =AG75-AI75 -> 0 | AL75: =AH75-AJ75 -> 0 | AQ75: =AM75-AO75 -> 0 | AR75: =AN75-AP75 -> 0 | AS75: =G75+N75+U75+AB75+AI75+AO75 -> 3.5488359e+08
A76: 钦州三期 | B76: 2057 | C76: 已出售 | G76: =SUMIFS([1]项目开票!C:C,[1]项目开票!B:B,报税!B76,[1]项目开票!A:A,报税!A76) -> 0 | H76: =SUMIFS([1]项目开票!D:D,[1]项目开票!B:B,报税!B76,[1]项目开票!A:A,报税!A76) -> 0 | I76: =E76-G76 -> 0 | J76: =F76-H76 -> 0 | N76: =SUMIFS([1]项目开票!O:O,[1]项目开票!B:B,报税!B76,[1]项目开票!A:A,报税!A76) -> 0 | O76: =SUMIFS([1]项目开票!P:P,[1]项目开票!B:B,报税!B76,[1]项目开票!A:A,报税!A76) -> 0 | P76: =L76-N76 -> 0 | Q76: =M76-O76 -> 0 | U76: =SUMIFS([1]项目开票!F:F,[1]项目开票!B:B,报税!B76,[1]项目开票!A:A,报税!A76) -> 55432.92 | V76: =SUMIFS([1]项目开票!G:G,[1]项目开票!B:B,报税!B76,[1]项目开票!A:A,报税!A76) -> 3325.98 | W76: =S76-U76 -> -55432.92 | X76: =T76-V76 -> -3325.98 | AB76: =SUMIFS([1]项目开票!I:I,[1]项目开票!B:B,报税!B76,[1]项目开票!A:A,报税!A76) -> 0 | AC76: =SUMIFS([1]项目开票!J:J,[1]项目开票!B:B,报税!B76,[1]项目开票!A:A,报税!A76) -> 0 | AD76: =Z76-AB76 -> 0 | AE76: =AA76-AC76 -> 0 | AI76: =SUMIFS([1]项目开票!L:L,[1]项目开票!B:B,报税!B76,[1]项目开票!A:A,报税!A76) -> 0 | AJ76: =SUMIFS([1]项目开票!M:M,[1]项目开票!B:B,报税!B76,[1]项目开票!A:A,报税!A76) -> 0 | AK76: =AG76-AI76 -> 0 | AL76: =AH76-AJ76 -> 0 | AQ76: =AM76-AO76 -> 0 | AR76: =AN76-AP76 -> 0 | AS76: =G76+N76+U76+AB76+AI76+AO76 -> 55432.92
A77: 河南濮阳昆吾-风电 | B77: 2351 | C77: 已出售 | G77: =SUMIFS([1]项目开票!C:C,[1]项目开票!B:B,报税!B77,[1]项目开票!A:A,报税!A77) -> 0 | H77: =SUMIFS([1]项目开票!D:D,[1]项目开票!B:B,报税!B77,[1]项目开票!A:A,报税!A77) -> 0 | I77: =E77-G77 -> 0 | J77: =F77-H77 -> 0 | N77: =SUMIFS([1]项目开票!O:O,[1]项目开票!B:B,报税!B77,[1]项目开票!A:A,报税!A77) -> 0 | O77: =SUMIFS([1]项目开票!P:P,[1]项目开票!B:B,报税!B77,[1]项目开票!A:A,报税!A77) -> 0 | P77: =L77-N77 -> 0 | Q77: =M77-O77 -> 0 | U77: =SUMIFS([1]项目开票!F:F,[1]项目开票!B:B,报税!B77,[1]项目开票!A:A,报税!A77) -> 460587 | V77: =SUMIFS([1]项目开票!G:G,[1]项目开票!B:B,报税!B77,[1]项目开票!A:A,报税!A77) -> 27635.22 | W77: =S77-U77 -> -460587 | X77: =T77-V77 -> -27635.22 | AB77: =SUMIFS([1]项目开票!I:I,[1]项目开票!B:B,报税!B77,[1]项目开票!A:A,报税!A77) -> 0 | AC77: =SUMIFS([1]项目开票!J:J,[1]项目开票!B:B,报税!B77,[1]项目开票!A:A,报税!A77) -> 0 | AD77: =Z77-AB77 -> 0 | AE77: =AA77-AC77 -> 0 | AI77: =SUMIFS([1]项目开票!L:L,[1]项目开票!B:B,报税!B77,[1]项目开票!A:A,报税!A77) -> 0 | AJ77: =SUMIFS([1]项目开票!M:M,[1]项目开票!B:B,报税!B77,[1]项目开票!A:A,报税!A77) -> 0 | AK77: =AG77-AI77 -> 0 | AL77: =AH77-AJ77 -> 0 | AQ77: =AM77-AO77 -> 0 | AR77: =AN77-AP77 -> 0 | AS77: =G77+N77+U77+AB77+AI77+AO77 -> 460587
A78: 锡盟防沙治沙正镶白旗10万kW光伏 | B78: 4306 | G78: =SUMIFS([1]项目开票!C:C,[1]项目开票!B:B,报税!B78,[1]项目开票!A:A,报税!A78) -> 0 | H78: =SUMIFS([1]项目开票!D:D,[1]项目开票!B:B,报税!B78,[1]项目开票!A:A,报税!A78) -> 0 | I78: =E78-G78 -> 0 | J78: =F78-H78 -> 0 | N78: =SUMIFS([1]项目开票!O:O,[1]项目开票!B:B,报税!B78,[1]项目开票!A:A,报税!A78) -> 0 | O78: =SUMIFS([1]项目开票!P:P,[1]项目开票!B:B,报税!B78,[1]项目开票!A:A,报税!A78) -> 0 | P78: =L78-N78 -> 0 | Q78: =M78-O78 -> 0 | U78: =SUMIFS([1]项目开票!F:F,[1]项目开票!B:B,报税!B78,[1]项目开票!A:A,报税!A78) -> 0 | V78: =SUMIFS([1]项目开票!G:G,[1]项目开票!B:B,报税!B78,[1]项目开票!A:A,报税!A78) -> 0 | W78: =S78-U78 -> 0 | X78: =T78-V78 -> 0 | AB78: =SUMIFS([1]项目开票!I:I,[1]项目开票!B:B,报税!B78,[1]项目开票!A:A,报税!A78) -> 48874.88 | AC78: =SUMIFS([1]项目开票!J:J,[1]项目开票!B:B,报税!B78,[1]项目开票!A:A,报税!A78) -> 2932.49 | AD78: =Z78-AB78 -> -48874.88 | AE78: =AA78-AC78 -> -2932.49 | AI78: =SUMIFS([1]项目开票!L:L,[1]项目开票!B:B,报税!B78,[1]项目开票!A:A,报税!A78) -> 0 | AJ78: =SUMIFS([1]项目开票!M:M,[1]项目开票!B:B,报税!B78,[1]项目开票!A:A,报税!A78) -> 0 | AK78: =AG78-AI78 -> 0 | AL78: =AH78-AJ78 -> 0 | AQ78: =AM78-AO78 -> 0 | AR78: =AN78-AP78 -> 0 | AS78: =G78+N78+U78+AB78+AI78+AO78 -> 48874.88
G79: =SUMIFS([1]项目开票!C:C,[1]项目开票!B:B,报税!B79,[1]项目开票!A:A,报税!A79) -> 0 | H79: =SUMIFS([1]项目开票!D:D,[1]项目开票!B:B,报税!B79,[1]项目开票!A:A,报税!A79) -> 0 | I79: =E79-G79 -> 0 | J79: =F79-H79 -> 0 | N79: =SUMIFS([1]项目开票!O:O,[1]项目开票!B:B,报税!B79,[1]项目开票!A:A,报税!A79) -> 0 | O79: =SUMIFS([1]项目开票!P:P,[1]项目开票!B:B,报税!B79,[1]项目开票!A:A,报税!A79) -> 0 | P79: =L79-N79 -> 0 | Q79: =M79-O79 -> 0 | U79: =SUMIFS([1]项目开票!F:F,[1]项目开票!B:B,报税!B79,[1]项目开票!A:A,报税!A79) -> 0 | V79: =SUMIFS([1]项目开票!G:G,[1]项目开票!B:B,报税!B79,[1]项目开票!A:A,报税!A79) -> 0 | W79: =S79-U79 -> 0 | X79: =T79-V79 -> 0 | AB79: =SUMIFS([1]项目开票!I:I,[1]项目开票!B:B,报税!B79,[1]项目开票!A:A,报税!A79) -> 0 | AC79: =SUMIFS([1]项目开票!J:J,[1]项目开票!B:B,报税!B79,[1]项目开票!A:A,报税!A79) -> 0 | AD79: =Z79-AB79 -> 0 | AE79: =AA79-AC79 -> 0 | AI79: =SUMIFS([1]项目开票!L:L,[1]项目开票!B:B,报税!B79,[1]项目开票!A:A,报税!A79) -> 0 | AJ79: =SUMIFS([1]项目开票!M:M,[1]项目开票!B:B,报税!B79,[1]项目开票!A:A,报税!A79) -> 0 | AK79: =AG79-AI79 -> 0 | AL79: =AH79-AJ79 -> 0 | AQ79: =AM79-AO79 -> 0 | AR79: =AN79-AP79 -> 0 | AS79: =G79+N79+U79+AB79+AI79+AO79 -> 0
G80: =SUMIFS([1]项目开票!C:C,[1]项目开票!B:B,报税!B80,[1]项目开票!A:A,报税!A80) -> 0 | H80: =SUMIFS([1]项目开票!D:D,[1]项目开票!B:B,报税!B80,[1]项目开票!A:A,报税!A80) -> 0 | I80: =E80-G80 -> 0 | J80: =F80-H80 -> 0 | N80: =SUMIFS([1]项目开票!O:O,[1]项目开票!B:B,报税!B80,[1]项目开票!A:A,报税!A80) -> 0 | O80: =SUMIFS([1]项目开票!P:P,[1]项目开票!B:B,报税!B80,[1]项目开票!A:A,报税!A80) -> 0 | P80: =L80-N80 -> 0 | Q80: =M80-O80 -> 0 | U80: =SUMIFS([1]项目开票!F:F,[1]项目开票!B:B,报税!B80,[1]项目开票!A:A,报税!A80) -> 0 | V80: =SUMIFS([1]项目开票!G:G,[1]项目开票!B:B,报税!B80,[1]项目开票!A:A,报税!A80) -> 0 | W80: =S80-U80 -> 0 | X80: =T80-V80 -> 0 | AB80: =SUMIFS([1]项目开票!I:I,[1]项目开票!B:B,报税!B80,[1]项目开票!A:A,报税!A80) -> 0 | AC80: =SUMIFS([1]项目开票!J:J,[1]项目开票!B:B,报税!B80,[1]项目开票!A:A,报税!A80) -> 0 | AD80: =Z80-AB80 -> 0 | AE80: =AA80-AC80 -> 0 | AI80: =SUMIFS([1]项目开票!L:L,[1]项目开票!B:B,报税!B80,[1]项目开票!A:A,报税!A80) -> 0 | AJ80: =SUMIFS([1]项目开票!M:M,[1]项目开票!B:B,报税!B80,[1]项目开票!A:A,报税!A80) -> 0 | AK80: =AG80-AI80 -> 0 | AL80: =AH80-AJ80 -> 0 | AQ80: =AM80-AO80 -> 0 | AR80: =AN80-AP80 -> 0 | AS80: =G80+N80+U80+AB80+AI80+AO80 -> 0
G81: =SUMIFS([1]项目开票!C:C,[1]项目开票!B:B,报税!B81,[1]项目开票!A:A,报税!A81) -> 0 | H81: =SUMIFS([1]项目开票!D:D,[1]项目开票!B:B,报税!B81,[1]项目开票!A:A,报税!A81) -> 0 | I81: =E81-G81 -> 0 | J81: =F81-H81 -> 0 | N81: =SUMIFS([1]项目开票!O:O,[1]项目开票!B:B,报税!B81,[1]项目开票!A:A,报税!A81) -> 0 | O81: =SUMIFS([1]项目开票!P:P,[1]项目开票!B:B,报税!B81,[1]项目开票!A:A,报税!A81) -> 0 | P81: =L81-N81 -> 0 | Q81: =M81-O81 -> 0 | U81: =SUMIFS([1]项目开票!F:F,[1]项目开票!B:B,报税!B81,[1]项目开票!A:A,报税!A81) -> 0 | V81: =SUMIFS([1]项目开票!G:G,[1]项目开票!B:B,报税!B81,[1]项目开票!A:A,报税!A81) -> 0 | W81: =S81-U81 -> 0 | X81: =T81-V81 -> 0 | AB81: =SUMIFS([1]项目开票!I:I,[1]项目开票!B:B,报税!B81,[1]项目开票!A:A,报税!A81) -> 0 | AC81: =SUMIFS([1]项目开票!J:J,[1]项目开票!B:B,报税!B81,[1]项目开票!A:A,报税!A81) -> 0 | AD81: =Z81-AB81 -> 0 | AE81: =AA81-AC81 -> 0 | AI81: =SUMIFS([1]项目开票!L:L,[1]项目开票!B:B,报税!B81,[1]项目开票!A:A,报税!A81) -> 0 | AJ81: =SUMIFS([1]项目开票!M:M,[1]项目开票!B:B,报税!B81,[1]项目开票!A:A,报税!A81) -> 0 | AK81: =AG81-AI81 -> 0 | AL81: =AH81-AJ81 -> 0 | AQ81: =AM81-AO81 -> 0 | AR81: =AN81-AP81 -> 0 | AS81: =G81+N81+U81+AB81+AI81+AO81 -> 0
G82: =SUMIFS([1]项目开票!C:C,[1]项目开票!B:B,报税!B82,[1]项目开票!A:A,报税!A82) -> 0 | H82: =SUMIFS([1]项目开票!D:D,[1]项目开票!B:B,报税!B82,[1]项目开票!A:A,报税!A82) -> 0 | I82: =E82-G82 -> 0 | J82: =F82-H82 -> 0 | N82: =SUMIFS([1]项目开票!O:O,[1]项目开票!B:B,报税!B82,[1]项目开票!A:A,报税!A82) -> 0 | O82: =SUMIFS([1]项目开票!P:P,[1]项目开票!B:B,报税!B82,[1]项目开票!A:A,报税!A82) -> 0 | P82: =L82-N82 -> 0 | Q82: =M82-O82 -> 0 | U82: =SUMIFS([1]项目开票!F:F,[1]项目开票!B:B,报税!B82,[1]项目开票!A:A,报税!A82) -> 0 | V82: =SUMIFS([1]项目开票!G:G,[1]项目开票!B:B,报税!B82,[1]项目开票!A:A,报税!A82) -> 0 | W82: =S82-U82 -> 0 | X82: =T82-V82 -> 0 | AB82: =SUMIFS([1]项目开票!I:I,[1]项目开票!B:B,报税!B82,[1]项目开票!A:A,报税!A82) -> 0 | AC82: =SUMIFS([1]项目开票!J:J,[1]项目开票!B:B,报税!B82,[1]项目开票!A:A,报税!A82) -> 0 | AD82: =Z82-AB82 -> 0 | AE82: =AA82-AC82 -> 0 | AI82: =SUMIFS([1]项目开票!L:L,[1]项目开票!B:B,报税!B82,[1]项目开票!A:A,报税!A82) -> 0 | AJ82: =SUMIFS([1]项目开票!M:M,[1]项目开票!B:B,报税!B82,[1]项目开票!A:A,报税!A82) -> 0 | AK82: =AG82-AI82 -> 0 | AL82: =AH82-AJ82 -> 0 | AQ82: =AM82-AO82 -> 0 | AR82: =AN82-AP82 -> 0 | AS82: =G82+N82+U82+AB82+AI82+AO82 -> 0
G83: =SUMIFS([1]项目开票!C:C,[1]项目开票!B:B,报税!B83,[1]项目开票!A:A,报税!A83) -> 0 | H83: =SUMIFS([1]项目开票!D:D,[1]项目开票!B:B,报税!B83,[1]项目开票!A:A,报税!A83) -> 0 | I83: =E83-G83 -> 0 | J83: =F83-H83 -> 0 | N83: =SUMIFS([1]项目开票!O:O,[1]项目开票!B:B,报税!B83,[1]项目开票!A:A,报税!A83) -> 0 | O83: =SUMIFS([1]项目开票!P:P,[1]项目开票!B:B,报税!B83,[1]项目开票!A:A,报税!A83) -> 0 | P83: =L83-N83 -> 0 | Q83: =M83-O83 -> 0 | U83: =SUMIFS([1]项目开票!F:F,[1]项目开票!B:B,报税!B83,[1]项目开票!A:A,报税!A83) -> 0 | V83: =SUMIFS([1]项目开票!G:G,[1]项目开票!B:B,报税!B83,[1]项目开票!A:A,报税!A83) -> 0 | W83: =S83-U83 -> 0 | X83: =T83-V83 -> 0 | AB83: =SUMIFS([1]项目开票!I:I,[1]项目开票!B:B,报税!B83,[1]项目开票!A:A,报税!A83) -> 0 | AC83: =SUMIFS([1]项目开票!J:J,[1]项目开票!B:B,报税!B83,[1]项目开票!A:A,报税!A83) -> 0 | AD83: =Z83-AB83 -> 0 | AE83: =AA83-AC83 -> 0 | AI83: =SUMIFS([1]项目开票!L:L,[1]项目开票!B:B,报税!B83,[1]项目开票!A:A,报税!A83) -> 0 | AJ83: =SUMIFS([1]项目开票!M:M,[1]项目开票!B:B,报税!B83,[1]项目开票!A:A,报税!A83) -> 0 | AK83: =AG83-AI83 -> 0 | AL83: =AH83-AJ83 -> 0 | AQ83: =AM83-AO83 -> 0 | AR83: =AN83-AP83 -> 0 | AS83: =G83+N83+U83+AB83+AI83+AO83 -> 0
G84: =SUMIFS([1]项目开票!C:C,[1]项目开票!B:B,报税!B84,[1]项目开票!A:A,报税!A84) -> 0 | H84: =SUMIFS([1]项目开票!D:D,[1]项目开票!B:B,报税!B84,[1]项目开票!A:A,报税!A84) -> 0 | I84: =E84-G84 -> 0 | J84: =F84-H84 -> 0 | N84: =SUMIFS([1]项目开票!O:O,[1]项目开票!B:B,报税!B84,[1]项目开票!A:A,报税!A84) -> 0 | O84: =SUMIFS([1]项目开票!P:P,[1]项目开票!B:B,报税!B84,[1]项目开票!A:A,报税!A84) -> 0 | P84: =L84-N84 -> 0 | Q84: =M84-O84 -> 0 | U84: =SUMIFS([1]项目开票!F:F,[1]项目开票!B:B,报税!B84,[1]项目开票!A:A,报税!A84) -> 0 | V84: =SUMIFS([1]项目开票!G:G,[1]项目开票!B:B,报税!B84,[1]项目开票!A:A,报税!A84) -> 0 | W84: =S84-U84 -> 0 | X84: =T84-V84 -> 0 | AB84: =SUMIFS([1]项目开票!I:I,[1]项目开票!B:B,报税!B84,[1]项目开票!A:A,报税!A84) -> 0 | AC84: =SUMIFS([1]项目开票!J:J,[1]项目开票!B:B,报税!B84,[1]项目开票!A:A,报税!A84) -> 0 | AD84: =Z84-AB84 -> 0 | AE84: =AA84-AC84 -> 0 | AI84: =SUMIFS([1]项目开票!L:L,[1]项目开票!B:B,报税!B84,[1]项目开票!A:A,报税!A84) -> 0 | AJ84: =SUMIFS([1]项目开票!M:M,[1]项目开票!B:B,报税!B84,[1]项目开票!A:A,报税!A84) -> 0 | AK84: =AG84-AI84 -> 0 | AL84: =AH84-AJ84 -> 0 | AQ84: =AM84-AO84 -> 0 | AR84: =AN84-AP84 -> 0 | AS84: =G84+N84+U84+AB84+AI84+AO84 -> 0
G85: =SUMIFS([1]项目开票!C:C,[1]项目开票!B:B,报税!B85,[1]项目开票!A:A,报税!A85) -> 0 | H85: =SUMIFS([1]项目开票!D:D,[1]项目开票!B:B,报税!B85,[1]项目开票!A:A,报税!A85) -> 0 | I85: =E85-G85 -> 0 | J85: =F85-H85 -> 0 | N85: =SUMIFS([1]项目开票!O:O,[1]项目开票!B:B,报税!B85,[1]项目开票!A:A,报税!A85) -> 0 | O85: =SUMIFS([1]项目开票!P:P,[1]项目开票!B:B,报税!B85,[1]项目开票!A:A,报税!A85) -> 0 | P85: =L85-N85 -> 0 | Q85: =M85-O85 -> 0 | U85: =SUMIFS([1]项目开票!F:F,[1]项目开票!B:B,报税!B85,[1]项目开票!A:A,报税!A85) -> 0 | V85: =SUMIFS([1]项目开票!G:G,[1]项目开票!B:B,报税!B85,[1]项目开票!A:A,报税!A85) -> 0 | W85: =S85-U85 -> 0 | X85: =T85-V85 -> 0 | AB85: =SUMIFS([1]项目开票!I:I,[1]项目开票!B:B,报税!B85,[1]项目开票!A:A,报税!A85) -> 0 | AC85: =SUMIFS([1]项目开票!J:J,[1]项目开票!B:B,报税!B85,[1]项目开票!A:A,报税!A85) -> 0 | AD85: =Z85-AB85 -> 0 | AE85: =AA85-AC85 -> 0 | AI85: =SUMIFS([1]项目开票!L:L,[1]项目开票!B:B,报税!B85,[1]项目开票!A:A,报税!A85) -> 0 | AJ85: =SUMIFS([1]项目开票!M:M,[1]项目开票!B:B,报税!B85,[1]项目开票!A:A,报税!A85) -> 0 | AK85: =AG85-AI85 -> 0 | AL85: =AH85-AJ85 -> 0 | AQ85: =AM85-AO85 -> 0 | AR85: =AN85-AP85 -> 0 | AS85: =G85+N85+U85+AB85+AI85+AO85 -> 0
G86: =SUMIFS([1]项目开票!C:C,[1]项目开票!B:B,报税!B86,[1]项目开票!A:A,报税!A86) -> 0 | H86: =SUMIFS([1]项目开票!D:D,[1]项目开票!B:B,报税!B86,[1]项目开票!A:A,报税!A86) -> 0 | I86: =E86-G86 -> 0 | J86: =F86-H86 -> 0 | N86: =SUMIFS([1]项目开票!O:O,[1]项目开票!B:B,报税!B86,[1]项目开票!A:A,报税!A86) -> 0 | O86: =SUMIFS([1]项目开票!P:P,[1]项目开票!B:B,报税!B86,[1]项目开票!A:A,报税!A86) -> 0 | P86: =L86-N86 -> 0 | Q86: =M86-O86 -> 0 | U86: =SUMIFS([1]项目开票!F:F,[1]项目开票!B:B,报税!B86,[1]项目开票!A:A,报税!A86) -> 0 | V86: =SUMIFS([1]项目开票!G:G,[1]项目开票!B:B,报税!B86,[1]项目开票!A:A,报税!A86) -> 0 | W86: =S86-U86 -> 0 | X86: =T86-V86 -> 0 | AB86: =SUMIFS([1]项目开票!I:I,[1]项目开票!B:B,报税!B86,[1]项目开票!A:A,报税!A86) -> 0 | AC86: =SUMIFS([1]项目开票!J:J,[1]项目开票!B:B,报税!B86,[1]项目开票!A:A,报税!A86) -> 0 | AD86: =Z86-AB86 -> 0 | AE86: =AA86-AC86 -> 0 | AI86: =SUMIFS([1]项目开票!L:L,[1]项目开票!B:B,报税!B86,[1]项目开票!A:A,报税!A86) -> 0 | AJ86: =SUMIFS([1]项目开票!M:M,[1]项目开票!B:B,报税!B86,[1]项目开票!A:A,报税!A86) -> 0 | AK86: =AG86-AI86 -> 0 | AL86: =AH86-AJ86 -> 0 | AQ86: =AM86-AO86 -> 0 | AR86: =AN86-AP86 -> 0 | AS86: =G86+N86+U86+AB86+AI86+AO86 -> 0
G87: =SUMIFS([1]项目开票!C:C,[1]项目开票!B:B,报税!B87,[1]项目开票!A:A,报税!A87) -> 0 | H87: =SUMIFS([1]项目开票!D:D,[1]项目开票!B:B,报税!B87,[1]项目开票!A:A,报税!A87) -> 0 | I87: =E87-G87 -> 0 | J87: =F87-H87 -> 0 | N87: =SUMIFS([1]项目开票!O:O,[1]项目开票!B:B,报税!B87,[1]项目开票!A:A,报税!A87) -> 0 | O87: =SUMIFS([1]项目开票!P:P,[1]项目开票!B:B,报税!B87,[1]项目开票!A:A,报税!A87) -> 0 | P87: =L87-N87 -> 0 | Q87: =M87-O87 -> 0 | U87: =SUMIFS([1]项目开票!F:F,[1]项目开票!B:B,报税!B87,[1]项目开票!A:A,报税!A87) -> 0 | V87: =SUMIFS([1]项目开票!G:G,[1]项目开票!B:B,报税!B87,[1]项目开票!A:A,报税!A87) -> 0 | W87: =S87-U87 -> 0 | X87: =T87-V87 -> 0 | AB87: =SUMIFS([1]项目开票!I:I,[1]项目开票!B:B,报税!B87,[1]项目开票!A:A,报税!A87) -> 0 | AC87: =SUMIFS([1]项目开票!J:J,[1]项目开票!B:B,报税!B87,[1]项目开票!A:A,报税!A87) -> 0 | AD87: =Z87-AB87 -> 0 | AE87: =AA87-AC87 -> 0 | AI87: =SUMIFS([1]项目开票!L:L,[1]项目开票!B:B,报税!B87,[1]项目开票!A:A,报税!A87) -> 0 | AJ87: =SUMIFS([1]项目开票!M:M,[1]项目开票!B:B,报税!B87,[1]项目开票!A:A,报税!A87) -> 0 | AK87: =AG87-AI87 -> 0 | AL87: =AH87-AJ87 -> 0 | AQ87: =AM87-AO87 -> 0 | AR87: =AN87-AP87 -> 0 | AS87: =G87+N87+U87+AB87+AI87+AO87 -> 0
G88: =SUMIFS([1]项目开票!C:C,[1]项目开票!B:B,报税!B88,[1]项目开票!A:A,报税!A88) -> 0 | H88: =SUMIFS([1]项目开票!D:D,[1]项目开票!B:B,报税!B88,[1]项目开票!A:A,报税!A88) -> 0 | I88: =E88-G88 -> 0 | J88: =F88-H88 -> 0 | N88: =SUMIFS([1]项目开票!O:O,[1]项目开票!B:B,报税!B88,[1]项目开票!A:A,报税!A88) -> 0 | O88: =SUMIFS([1]项目开票!P:P,[1]项目开票!B:B,报税!B88,[1]项目开票!A:A,报税!A88) -> 0 | P88: =L88-N88 -> 0 | Q88: =M88-O88 -> 0 | U88: =SUMIFS([1]项目开票!F:F,[1]项目开票!B:B,报税!B88,[1]项目开票!A:A,报税!A88) -> 0 | V88: =SUMIFS([1]项目开票!G:G,[1]项目开票!B:B,报税!B88,[1]项目开票!A:A,报税!A88) -> 0 | W88: =S88-U88 -> 0 | X88: =T88-V88 -> 0 | AB88: =SUMIFS([1]项目开票!I:I,[1]项目开票!B:B,报税!B88,[1]项目开票!A:A,报税!A88) -> 0 | AC88: =SUMIFS([1]项目开票!J:J,[1]项目开票!B:B,报税!B88,[1]项目开票!A:A,报税!A88) -> 0 | AD88: =Z88-AB88 -> 0 | AE88: =AA88-AC88 -> 0 | AI88: =SUMIFS([1]项目开票!L:L,[1]项目开票!B:B,报税!B88,[1]项目开票!A:A,报税!A88) -> 0 | AJ88: =SUMIFS([1]项目开票!M:M,[1]项目开票!B:B,报税!B88,[1]项目开票!A:A,报税!A88) -> 0 | AK88: =AG88-AI88 -> 0 | AL88: =AH88-AJ88 -> 0 | AQ88: =AM88-AO88 -> 0 | AR88: =AN88-AP88 -> 0 | AS88: =G88+N88+U88+AB88+AI88+AO88 -> 0
G89: =SUMIFS([1]项目开票!C:C,[1]项目开票!B:B,报税!B89,[1]项目开票!A:A,报税!A89) -> 0 | H89: =SUMIFS([1]项目开票!D:D,[1]项目开票!B:B,报税!B89,[1]项目开票!A:A,报税!A89) -> 0 | I89: =E89-G89 -> 0 | J89: =F89-H89 -> 0 | N89: =SUMIFS([1]项目开票!O:O,[1]项目开票!B:B,报税!B89,[1]项目开票!A:A,报税!A89) -> 0 | O89: =SUMIFS([1]项目开票!P:P,[1]项目开票!B:B,报税!B89,[1]项目开票!A:A,报税!A89) -> 0 | P89: =L89-N89 -> 0 | Q89: =M89-O89 -> 0 | U89: =SUMIFS([1]项目开票!F:F,[1]项目开票!B:B,报税!B89,[1]项目开票!A:A,报税!A89) -> 0 | V89: =SUMIFS([1]项目开票!G:G,[1]项目开票!B:B,报税!B89,[1]项目开票!A:A,报税!A89) -> 0 | W89: =S89-U89 -> 0 | X89: =T89-V89 -> 0 | AB89: =SUMIFS([1]项目开票!I:I,[1]项目开票!B:B,报税!B89,[1]项目开票!A:A,报税!A89) -> 0 | AC89: =SUMIFS([1]项目开票!J:J,[1]项目开票!B:B,报税!B89,[1]项目开票!A:A,报税!A89) -> 0 | AD89: =Z89-AB89 -> 0 | AE89: =AA89-AC89 -> 0 | AI89: =SUMIFS([1]项目开票!L:L,[1]项目开票!B:B,报税!B89,[1]项目开票!A:A,报税!A89) -> 0 | AJ89: =SUMIFS([1]项目开票!M:M,[1]项目开票!B:B,报税!B89,[1]项目开票!A:A,报税!A89) -> 0 | AK89: =AG89-AI89 -> 0 | AL89: =AH89-AJ89 -> 0 | AQ89: =AM89-AO89 -> 0 | AR89: =AN89-AP89 -> 0 | AS89: =G89+N89+U89+AB89+AI89+AO89 -> 0
G90: =SUMIFS([1]项目开票!C:C,[1]项目开票!B:B,报税!B90,[1]项目开票!A:A,报税!A90) -> 0 | H90: =SUMIFS([1]项目开票!D:D,[1]项目开票!B:B,报税!B90,[1]项目开票!A:A,报税!A90) -> 0 | I90: =E90-G90 -> 0 | J90: =F90-H90 -> 0 | N90: =SUMIFS([1]项目开票!O:O,[1]项目开票!B:B,报税!B90,[1]项目开票!A:A,报税!A90) -> 0 | O90: =SUMIFS([1]项目开票!P:P,[1]项目开票!B:B,报税!B90,[1]项目开票!A:A,报税!A90) -> 0 | P90: =L90-N90 -> 0 | Q90: =M90-O90 -> 0 | U90: =SUMIFS([1]项目开票!F:F,[1]项目开票!B:B,报税!B90,[1]项目开票!A:A,报税!A90) -> 0 | V90: =SUMIFS([1]项目开票!G:G,[1]项目开票!B:B,报税!B90,[1]项目开票!A:A,报税!A90) -> 0 | W90: =S90-U90 -> 0 | X90: =T90-V90 -> 0 | AB90: =SUMIFS([1]项目开票!I:I,[1]项目开票!B:B,报税!B90,[1]项目开票!A:A,报税!A90) -> 0 | AC90: =SUMIFS([1]项目开票!J:J,[1]项目开票!B:B,报税!B90,[1]项目开票!A:A,报税!A90) -> 0 | AD90: =Z90-AB90 -> 0 | AE90: =AA90-AC90 -> 0 | AI90: =SUMIFS([1]项目开票!L:L,[1]项目开票!B:B,报税!B90,[1]项目开票!A:A,报税!A90) -> 0 | AJ90: =SUMIFS([1]项目开票!M:M,[1]项目开票!B:B,报税!B90,[1]项目开票!A:A,报税!A90) -> 0 | AK90: =AG90-AI90 -> 0 | AL90: =AH90-AJ90 -> 0 | AQ90: =AM90-AO90 -> 0 | AR90: =AN90-AP90 -> 0 | AS90: =G90+N90+U90+AB90+AI90+AO90 -> 0
... G106: =SUMIFS([1]项目开票!C:C,[1]项目开票!B:B,报税!B106,[1]项目开票!A:A,报税!A106) -> 0 | H106: =SUMIFS([1]项目开票!D:D,[1]项目开票!B:B,报税!B106,[1]项目开票!A:A,报税!A106) -> 0 | I106: =E106-G106 -> 0 | J106: =F106-H106 -> 0 | N106: =SUMIFS([1]项目开票!O:O,[1]项目开票!B:B,报税!B106,[1]项目开票!A:A,报税!A106) -> 0 | O106: =SUMIFS([1]项目开票!P:P,[1]项目开票!B:B,报税!B106,[1]项目开票!A:A,报税!A106) -> 0 | P106: =L106-N106 -> 0 | Q106: =M106-O106 -> 0 | U106: =SUMIFS([1]项目开票!F:F,[1]项目开票!B:B,报税!B106,[1]项目开票!A:A,报税!A106) -> 0 | V106: =SUMIFS([1]项目开票!G:G,[1]项目开票!B:B,报税!B106,[1]项目开票!A:A,报税!A106) -> 0 | W106: =S106-U106 -> 0 | X106: =T106-V106 -> 0 | AB106: =SUMIFS([1]项目开票!I:I,[1]项目开票!B:B,报税!B106,[1]项目开票!A:A,报税!A106) -> 0 | AC106: =SUMIFS([1]项目开票!J:J,[1]项目开票!B:B,报税!B106,[1]项目开票!A:A,报税!A106) -> 0 | AD106: =Z106-AB106 -> 0 | AE106: =AA106-AC106 -> 0 | AI106: =SUMIFS([1]项目开票!L:L,[1]项目开票!B:B,报税!B106,[1]项目开票!A:A,报税!A106) -> 0 | AJ106: =SUMIFS([1]项目开票!M:M,[1]项目开票!B:B,报税!B106,[1]项目开票!A:A,报税!A106) -> 0 | AK106: =AG106-AI106 -> 0 | AL106: =AH106-AJ106 -> 0 | AQ106: =AM106-AO106 -> 0 | AR106: =AN106-AP106 -> 0 | AS106: =G106+N106+U106+AB106+AI106+AO106 -> 0
D107: =SUM(D5:D106) -> 5.1241603e+08 | E107: =SUM(E5:E106) -> 7.8997795e+08 | F107: =SUM(F5:F106) -> 71098016 | G107: =SUM(G5:G106) -> 2.2018668e+08 | H107: =SUM(H5:H106) -> 19816802 | I107: =SUM(I5:I106) -> 5.6979127e+08 | J107: =SUM(J5:J106) -> 51281214 | K107: =SUM(K5:K106) -> 2.9215233e+09 | ... AR107: =SUM(AR5:AR106) -> 0
D110: =D107+K107+R107+Y107+AF107 -> 3.6083902e+09 | E110: =E107+L107+S107+Z107+AG107+AM107 -> 3.9147228e+09 | F110: =F107+M107+T107+AA107+AH107+AN107 -> 4.6517579e+08 | G110: =G107+N107+U107+AB107+AI107+AO107 -> 1.0945417e+09 | H110: =H107+O107+V107+AC107+AJ107+AP107 -> 1.3207174e+08 | I110: =I107+P107+W107+AD107+AK107 -> 2.8201811e+09 | J110: =J107+Q107+X107+AE107+AL107 -> 3.3310405e+08
D112: 3.6083902e+09 | E112: 3.9147228e+09 | F112: 4.6517579e+08 | G112: 1.0945417e+09 | H112: 1.3207174e+08
D113: =D112-D110 -> 0.00020647049 | E113: =E112-E110 -> -0.00057077408 | F113: =F112-F110 -> 0.0027433634
A114: 母公司 | B114: 所属项目 | D114: 消缺服务 | G114: =G112-G110 -> 0 | H114: =H112-H110 -> 0
B140: 总计 | D140: =SUM(D115:D138) -> 0
